Workbook

Sheet Diagrama de clases

Sheet Clases
A1: Clase | B1: Estereotipo | C1: Desripción
A2: Barberia | B2: class | C2: Representa la cadena o marca comercial de barbería, dueña de una o varias sedes.
A3: DiaSemana | B3: class | C3: Representa cada uno de los días de la semana, incluyendo festivo, que se usa como catálogo para definir los horarios de la barbería y de cada barbero.
A4: Departamento | B4: class | C4: Representa cada uno de los departamentos del país en los que se encuentran las ciudades donde la barbería puede tener sedes.
A5: Estado | B5: class | C5: Representa en qué situación puntual se encuentra una cita: agendada, finalizada, cancelada por alguna de las partes, con tardanza del cliente o del barbero, o con inasistencia del cliente.
A6: PrefijoCelular | B6: class | C6: Representa el catálogo de prefijos telefónicos de país que el administrador habilita, y que son los únicos que barberos y clientes pueden usar en su número de celular.
A7: TipoMulta | B7: class | C7: Representa los tipos de multa que puede recibir un cliente: por tardanza o por inasistencia.
A8: TipoRegistroHora | B8: class | C8: Representa el catálogo de los distintos momentos en que se puede registrar una hora real durante una cita: llegada del cliente, barbero preparado, inicio y fin de la atención.
A9: Cliente | B9: class | C9: Representa a la persona que solicita citas en la barbería.
A10: Ciudad | B10: class | C10: Representa cada una de las ciudades, pertenecientes a un departamento, en las que puede estar ubicada una sede de la barbería.
A11: Sede | B11: class | C11: Representa cada una de las sucursales físicas de una barbería, ubicada en una ciudad puntual, donde se ofrecen los servicios y trabajan los barberos.
A12: Barbero | B12: class | C12: Representa a un trabajador de la barbería que atiende clientes según los servicios que sabe realizar, organiza su propio horario y tiene su agenda personal para atender todas las citas que valla teniendo.
... A22: RegistroHoraCita | B22: class | C22: Representa cada hora real registrada durante una cita puntual, según el tipo de momento al que corresponde (llegada del cliente, barbero preparado, inicio o fin de la atención).

Sheet Barberia
A1: <-Volver al inicio
A2: =Clases!$A$1 -> Clase | B2: =Clases!A2 -> Barberia
A3: =Clases!$B$1 -> Estereotipo | B3: =Clases!B2 -> class
A4: =Clases!$C$1 -> Desripción | B4: =Clases!C2 -> Representa la cadena o marca comercial de barbería, dueña de una o varias sedes.
A5: Modificador acceso: | B5: public
A6: Tipo clase: | B6: no final
A7: Relaciones
A8: Relación | B8: Tipo relación | E8: Estructura
A9: Es usada por | B9: Composición | E9: =Sede!B2 -> Sede
A10: Atributos
A11: Modificador de aceso | B11: Nombre | C11: Tipo de dato | E11: Tipo modificación atributo | F11: Tipo acceso atributo | G11: Valor por defecto | J11: Descripción atributo
C12: Tipo de dato | D12: ¿Cuál?
A13: private | B13: id | C13: Otro | D13: UUID | E13: no final | F13: no static | G13: new UUID(0L, 0L) | J13: Representa un identificador que hará unico cada objeto de dominio de este tipo, no se puede repetir
A14: private | B14: nombre | C14: String | E14: no final | F14: no static | G14: "" | J14: Representa el nombre comercial de la cadena de barbería, dueña de una o varias sedes
A15: private | B15: nit | C15: String | E15: no final | F15: no static | G15: "" | J15: Representa el número de identificación tributaria (NIT) que identifica legalmente a la barbería como empresa
A16: Constructores
A17: Modificador de aceso | B17: Nombre | C17: Tipo constructor | D17: Descripción | E17: Parámetros | M17: Excepciones
E18: Nombre | F18: Tipo de dato | G18: ¿Cuál? | H18: Tipo parámetro | I18: Tipo modificación atributo | J18: Descripción
A19: public | B19: =B2 -> Barberia | C19: Defecto | D19: Constructor por defecto que crea un objeto Barberia con todos sus atributos en su valor por defecto
A20: public | B20: =B2 -> Barberia | C20: Parametrizado | D20: Constructor parametrizado que crea un objeto Barberia asignando el valor recibido a cada uno de sus atributos | E20: valorId | F20: Otro | G20: UUID | H20: Por referencia | I20: no final | J20: Valor que se asigna al atributo id
E21: valorNombre | F21: String | H21: Por valor | I21: no final | J21: Valor que se asigna al atributo nombre
E22: valorNit | F22: String | H22: Por valor | I22: no final | J22: Valor que se asigna al atributo nit
A23: Métodos accesores
A24: Modificador de aceso | B24: Nombre | C24: Tipo método accesor | D24: Tipo modificación método | E24: Descripción | F24: Parámetros | L24: Tipo dato de retorno | N24: Excepciones
F25: Nombre | G25: Tipo de dato | H25: ¿Cuál? | I25: Tipo parámetro | J25: Tipo modificación atributo | K25: Descripción | L25: Tipo de dato | M25: ¿Cuál?
A26: public | B26: getId | C26: getter | D26: no final | E26: Método encargado de obtener el valor del atributo id | L26: Otro | M26: UUID
A27: public | B27: setId | C27: setter | D27: no final | E27: Método encargado de colocar el valor al atributo id | F27: valorId | G27: Otro | H27: UUID | I27: Por referencia | J27: no final | K27: Nuevo valor del atributo id | L27: void
A28: public | B28: getNombre | C28: getter | D28: no final | E28: Método encargado de obtener el valor del atributo nombre | L28: String
A29: public | B29: setNombre | C29: setter | D29: no final | E29: Método encargado de colocar el valor al atributo nombre | F29: valorNombre | G29: String | I29: Por valor | J29: no final | K29: Nuevo valor del atributo nombre | L29: void
A30: public | B30: getNit | C30: getter | D30: no final | E30: Método encargado de obtener el valor del atributo nit | L30: String
A31: public | B31: setNit | C31: setter | D31: no final | E31: Método encargado de colocar el valor al atributo nit | F31: valorNit | G31: String | I31: Por valor | J31: no final | K31: Nuevo valor del atributo nit | L31: void
A32: Métodos
A33: Modificador de aceso | B33: Nombre | C33: Tipo acceso método | D33: Tipo modificación método | E33: Descripción | F33: Parámetros | L33: Tipo dato de retorno | N33: Excepciones
F34: Nombre | G34: Tipo de dato | H34: ¿Cuál? | I34: Tipo parámetro | J34: Tipo modificación atributo | K34: Descripción | L34: Tipo de dato | M34: ¿Cuál?
A35: public | B35: registrarBarberia | C35: no static | D35: no final | E35: Comando que permite registrar una nueva barbería con su nombre y nit | F35: nombre | G35: String | I35: Por valor | J35: no final | K35: Representa el nombre comercial de la cadena de barbería, dueña de una o varias sedes | L35: Otro | M35: Barberia | N35: Generar una excepción indicándole al administrador que los datos no cumplen; Generar una excepción indicándole al administrador que ya existe una barbería con ese nit
F36: nit | G36: String | I36: Por valor | J36: no final | K36: Representa el número de identificación tributaria (NIT) que identifica legalmente a la barbería como empresa
A37: public | B37: consultarDatosBarberia | C37: no static | D37: no final | E37: Permite al administrador consultar el nombre y el nit de la barbería | F37: id | G37: Otro | H37: UUID | I37: Por referencia | J37: no final | K37: Corresponde al identificador de la barbería que se va a consultar | L37: Otro | M37: Barberia | N37: Informar con un mensaje que no existe una barbería con el identificador enviado y por lo tanto no se puede realizar la operación
A38: public | B38: consultarNombreBarberia | C38: no static | D38: no final | E38: Permite al barbero y al cliente consultar el nombre de la barbería | F38: id | G38: Otro | H38: UUID | I38: Por referencia | J38: no final | K38: Corresponde al identificador de la barbería que se va a consultar | L38: String | N38: Informar con un mensaje que no existe una barbería con el identificador enviado y por lo tanto no se puede realizar la operación
A39: public | B39: cambiarNombreBarberia | C39: no static | D39: no final | E39: Permite al administrador cambiar el nombre comercial de la barbería | F39: id | G39: Otro | H39: UUID | I39: Por referencia | J39: no final | K39: Corresponde al identificador de la barbería | L39: Otro | M39: Barberia | N39: Informar con un mensaje que no existe una barbería con el identificador enviado y por lo tanto no se puede realizar la operación; Generar una excepción indicándole al administrador cuáles datos de la barbería no cumplen con las reglas definidas
F40: nombre | G40: String | I40: Por valor | J40: no final | K40: Representa el nombre comercial de la cadena de barbería, dueña de una o varias sedes
A41: public | B41: darDeBajaBarberia | C41: no static | D41: no final | E41: Permite al administrador eliminar la barbería del sistema cuando ya no tiene sedes registradas | F41: id | G41: Otro | H41: UUID | I41: Por referencia | J41: no final | K41: Corresponde al identificador de la barbería que se va a dar de baja | L41: void | N41: Informar con un mensaje que no existe una barbería con el identificador enviado y por lo tanto no se puede realizar la operación

Sheet DiaSemana
A1: <-Volver al inicio
A2: =Clases!$A$1 -> Clase | B2: =Clases!A3 -> DiaSemana
A3: =Clases!$B$1 -> Estereotipo | B3: =Clases!B3 -> class
A4: =Clases!$C$1 -> Desripción | B4: =Clases!C3 -> Representa cada uno de los días de la semana, incluyendo festivo, que se usa como catálogo para definir los horarios de la barbería y de cada barbero.
A5: Modificador acceso: | B5: public
A6: Tipo clase: | B6: no final
A7: Relaciones
A8: Relación | B8: Tipo relación | E8: Estructura
A9: Es usada por | B9: Asociación | E9: =HorarioBarberia!B2 -> HorarioBarberia
A10: Atributos
A11: Modificador de aceso | B11: Nombre | C11: Tipo de dato | E11: Tipo modificación atributo | F11: Tipo acceso atributo | G11: Valor por defecto | J11: Descripción atributo
C12: Tipo de dato | D12: ¿Cuál?
A13: private | B13: id | C13: Otro | D13: UUID | E13: no final | F13: no static | G13: new UUID(0L, 0L) | J13: Representa un identificador que hará unico cada objeto de dominio de este tipo, no se puede repetir
A14: private | B14: nombre | C14: String | E14: no final | F14: no static | G14: "" | J14: Representa como se llama el dia de la semana, para los horarios
A15: Constructores
A16: Modificador de aceso | B16: Nombre | C16: Tipo constructor | D16: Descripción | E16: Parámetros | M16: Excepciones
E17: Nombre | F17: Tipo de dato | G17: ¿Cuál? | H17: Tipo parámetro | I17: Tipo modificación atributo | J17: Descripción
A18: public | B18: =B2 -> DiaSemana | C18: Defecto | D18: Constructor por defecto que crea un objeto DiaSemana con todos sus atributos en su valor por defecto
A19: public | B19: =B2 -> DiaSemana | C19: Parametrizado | D19: Constructor parametrizado que crea un objeto DiaSemana asignando el valor recibido a cada uno de sus atributos | E19: valorId | F19: Otro | G19: UUID | H19: Por referencia | I19: no final | J19: Valor que se asigna al atributo id
E20: valorNombre | F20: String | H20: Por valor | I20: no final | J20: Valor que se asigna al atributo nombre
A21: Métodos accesores
A22: Modificador de aceso | B22: Nombre | C22: Tipo método accesor | D22: Tipo modificación método | E22: Descripción | F22: Parámetros | L22: Tipo dato de retorno | N22: Excepciones
F23: Nombre | G23: Tipo de dato | H23: ¿Cuál? | I23: Tipo parámetro | J23: Tipo modificación atributo | K23: Descripción | L23: Tipo de dato | M23: ¿Cuál?
A24: public | B24: getId | C24: getter | D24: no final | E24: Método encargado de obtener el valor del atributo id | L24: Otro | M24: UUID
A25: public | B25: setId | C25: setter | D25: no final | E25: Método encargado de colocar el valor al atributo id | F25: valorId | G25: Otro | H25: UUID | I25: Por referencia | J25: no final | K25: Nuevo valor del atributo id | L25: void
A26: public | B26: getNombre | C26: getter | D26: no final | E26: Método encargado de obtener el valor del atributo nombre | L26: String
A27: public | B27: setNombre | C27: setter | D27: no final | E27: Método encargado de colocar el valor al atributo nombre | F27: valorNombre | G27: String | I27: Por valor | J27: no final | K27: Nuevo valor del atributo nombre | L27: void
A28: Métodos
A29: Modificador de aceso | B29: Nombre | C29: Tipo acceso método | D29: Tipo modificación método | E29: Descripción | F29: Parámetros | L29: Tipo dato de retorno | N29: Excepciones
F30: Nombre | G30: Tipo de dato | H30: ¿Cuál? | I30: Tipo parámetro | J30: Tipo modificación atributo | K30: Descripción | L30: Tipo de dato | M30: ¿Cuál?
A31: public | B31: verDiasDeLaSemana | C31: no static | D31: no final | E31: Permite consultar el catálogo de días de la semana, incluyendo festivo, para definir los horarios | L31: Otro | M31: List<DiaSemana> | N31: No aplica

Sheet Departamento
A1: <-Volver al inicio
A2: =Clases!$A$1 -> Clase | B2: =Clases!A4 -> Departamento
A3: =Clases!$B$1 -> Estereotipo | B3: =Clases!B4 -> class
A4: =Clases!$C$1 -> Desripción | B4: =Clases!C4 -> Representa cada uno de los departamentos del país en los que se encuentran las ciudades donde la barbería puede tener sedes.
A5: Modificador acceso: | B5: public
A6: Tipo clase: | B6: no final
A7: Relaciones
A8: Relación | B8: Tipo relación | E8: Estructura
A9: Es usada por | B9: Composición | E9: =Ciudad!B2 -> Ciudad
A10: Atributos
A11: Modificador de aceso | B11: Nombre | C11: Tipo de dato | E11: Tipo modificación atributo | F11: Tipo acceso atributo | G11: Valor por defecto | J11: Descripción atributo
C12: Tipo de dato | D12: ¿Cuál?
A13: private | B13: id | C13: Otro | D13: UUID | E13: no final | F13: no static | G13: new UUID(0L, 0L) | J13: Representa un identificador que hará unico cada objeto de dominio de este tipo, no se puede repetir
A14: private | B14: nombre | C14: String | E14: no final | F14: no static | G14: "" | J14: Representa el nombre del departamento en el que están ubicadas las ciudades donde la barbería puede tener sedes
A15: Constructores
A16: Modificador de aceso | B16: Nombre | C16: Tipo constructor | D16: Descripción | E16: Parámetros | M16: Excepciones
E17: Nombre | F17: Tipo de dato | G17: ¿Cuál? | H17: Tipo parámetro | I17: Tipo modificación atributo | J17: Descripción
A18: public | B18: =B2 -> Departamento | C18: Defecto | D18: Constructor por defecto que crea un objeto Departamento con todos sus atributos en su valor por defecto
A19: public | B19: =B2 -> Departamento | C19: Parametrizado | D19: Constructor parametrizado que crea un objeto Departamento asignando el valor recibido a cada uno de sus atributos | E19: valorId | F19: Otro | G19: UUID | H19: Por referencia | I19: no final | J19: Valor que se asigna al atributo id
E20: valorNombre | F20: String | H20: Por valor | I20: no final | J20: Valor que se asigna al atributo nombre
A21: Métodos accesores
A22: Modificador de aceso | B22: Nombre | C22: Tipo método accesor | D22: Tipo modificación método | E22: Descripción | F22: Parámetros | L22: Tipo dato de retorno | N22: Excepciones
F23: Nombre | G23: Tipo de dato | H23: ¿Cuál? | I23: Tipo parámetro | J23: Tipo modificación atributo | K23: Descripción | L23: Tipo de dato | M23: ¿Cuál?
A24: public | B24: getId | C24: getter | D24: no final | E24: Método encargado de obtener el valor del atributo id | L24: Otro | M24: UUID
A25: public | B25: setId | C25: setter | D25: no final | E25: Método encargado de colocar el valor al atributo id | F25: valorId | G25: Otro | H25: UUID | I25: Por referencia | J25: no final | K25: Nuevo valor del atributo id | L25: void
A26: public | B26: getNombre | C26: getter | D26: no final | E26: Método encargado de obtener el valor del atributo nombre | L26: String
A27: public | B27: setNombre | C27: setter | D27: no final | E27: Método encargado de colocar el valor al atributo nombre | F27: valorNombre | G27: String | I27: Por valor | J27: no final | K27: Nuevo valor del atributo nombre | L27: void
A28: Métodos
A29: Modificador de aceso | B29: Nombre | C29: Tipo acceso método | D29: Tipo modificación método | E29: Descripción | F29: Parámetros | L29: Tipo dato de retorno | N29: Excepciones
F30: Nombre | G30: Tipo de dato | H30: ¿Cuál? | I30: Tipo parámetro | J30: Tipo modificación atributo | K30: Descripción | L30: Tipo de dato | M30: ¿Cuál?
A31: public | B31: consultarDepartamentos | C31: no static | D31: no final | E31: Permite consultar el catálogo de departamentos disponibles | L31: Otro | M31: List<Departamento> | N31: No aplica

Sheet Estado
A1: <-Volver al inicio
A2: =Clases!$A$1 -> Clase | B2: =Clases!A5 -> Estado
A3: =Clases!$B$1 -> Estereotipo | B3: =Clases!B5 -> class
A4: =Clases!$C$1 -> Desripción | B4: =Clases!C5 -> Representa en qué situación puntual se encuentra una cita: agendada, finalizada, cancelada por alguna de las partes, con tardanza del cliente o del barbero, o con inasistencia del cliente.
A5: Modificador acceso: | B5: public
A6: Tipo clase: | B6: no final
A7: Relaciones
A8: Relación | B8: Tipo relación | E8: Estructura
A9: Es usada por | B9: Asociación | E9: =Cita!B2 -> Cita
A10: Atributos
A11: Modificador de aceso | B11: Nombre | C11: Tipo de dato | E11: Tipo modificación atributo | F11: Tipo acceso atributo | G11: Valor por defecto | J11: Descripción atributo
C12: Tipo de dato | D12: ¿Cuál?
A13: private | B13: id | C13: Otro | D13: UUID | E13: no final | F13: no static | G13: new UUID(0L, 0L) | J13: Representa un identificador que hará unico cada objeto de dominio de este tipo, no se puede repetir
A14: private | B14: nombre | C14: String | E14: no final | F14: no static | G14: "" | J14: Representa como se llama el estado en el que se encuentra una cita puntual
A15: private | B15: descripcion | C15: String | E15: no final | F15: no static | G15: "" | J15: Representa el significado de que representa cada estado para la cita
A16: Constructores
A17: Modificador de aceso | B17: Nombre | C17: Tipo constructor | D17: Descripción | E17: Parámetros | M17: Excepciones
E18: Nombre | F18: Tipo de dato | G18: ¿Cuál? | H18: Tipo parámetro | I18: Tipo modificación atributo | J18: Descripción
A19: public | B19: =B2 -> Estado | C19: Defecto | D19: Constructor por defecto que crea un objeto Estado con todos sus atributos en su valor por defecto
A20: public | B20: =B2 -> Estado | C20: Parametrizado | D20: Constructor parametrizado que crea un objeto Estado asignando el valor recibido a cada uno de sus atributos | E20: valorId | F20: Otro | G20: UUID | H20: Por referencia | I20: no final | J20: Valor que se asigna al atributo id
E21: valorNombre | F21: String | H21: Por valor | I21: no final | J21: Valor que se asigna al atributo nombre
E22: valorDescripcion | F22: String | H22: Por valor | I22: no final | J22: Valor que se asigna al atributo descripcion
A23: Métodos accesores
A24: Modificador de aceso | B24: Nombre | C24: Tipo método accesor | D24: Tipo modificación método | E24: Descripción | F24: Parámetros | L24: Tipo dato de retorno | N24: Excepciones
F25: Nombre | G25: Tipo de dato | H25: ¿Cuál? | I25: Tipo parámetro | J25: Tipo modificación atributo | K25: Descripción | L25: Tipo de dato | M25: ¿Cuál?
A26: public | B26: getId | C26: getter | D26: no final | E26: Método encargado de obtener el valor del atributo id | L26: Otro | M26: UUID
A27: public | B27: setId | C27: setter | D27: no final | E27: Método encargado de colocar el valor al atributo id | F27: valorId | G27: Otro | H27: UUID | I27: Por referencia | J27: no final | K27: Nuevo valor del atributo id | L27: void
A28: public | B28: getNombre | C28: getter | D28: no final | E28: Método encargado de obtener el valor del atributo nombre | L28: String
A29: public | B29: setNombre | C29: setter | D29: no final | E29: Método encargado de colocar el valor al atributo nombre | F29: valorNombre | G29: String | I29: Por valor | J29: no final | K29: Nuevo valor del atributo nombre | L29: void
A30: public | B30: getDescripcion | C30: getter | D30: no final | E30: Método encargado de obtener el valor del atributo descripcion | L30: String
A31: public | B31: setDescripcion | C31: setter | D31: no final | E31: Método encargado de colocar el valor al atributo descripcion | F31: valorDescripcion | G31: String | I31: Por valor | J31: no final | K31: Nuevo valor del atributo descripcion | L31: void
A32: Métodos
A33: Modificador de aceso | B33: Nombre | C33: Tipo acceso método | D33: Tipo modificación método | E33: Descripción | F33: Parámetros | L33: Tipo dato de retorno | N33: Excepciones
F34: Nombre | G34: Tipo de dato | H34: ¿Cuál? | I34: Tipo parámetro | J34: Tipo modificación atributo | K34: Descripción | L34: Tipo de dato | M34: ¿Cuál?
A35: public | B35: consultarTodosLosEstados | C35: no static | D35: no final | E35: Permite consultar los estados posibles que puede tener una cita | L35: Otro | M35: List<Estado> | N35: No aplica
A36: public | B36: editarDescripcion | C36: no static | D36: no final | E36: Permite ajustar el texto descriptivo de un estado ya creado, sin cambiar su significado en el flujo de la cita | F36: id | G36: Otro | H36: UUID | I36: Por referencia | J36: no final | K36: Corresponde al identificador del estado que se va a editar | L36: void | N36: Informar con un mensaje que no existe un estado con el identificador enviado y por lo tanto no es posible modificar la descripción; Generar una excepción indicándole al usuario cuáles datos de la descripción del estado no cumplen con las reglas definidas
F37: descripcion | G37: String | I37: Por valor | J37: no final | K37: Representa el significado de que representa cada estado para la cita
A38: public | B38: consultarDescripcion | C38: no static | D38: no final | E38: Permite consultar la descripcion de un estado en especifico | F38: nombre | G38: String | I38: Por valor | J38: no final | K38: Representa como se llama el estado en el que se encuentra una cita puntual | L38: String | N38: Informar con un mensaje que no existe un Estado con el identificador enviado y por lo tanto no es posible modificar la descripción

Sheet PrefijoCelular
A1: <-Volver al inicio
A2: =Clases!$A$1 -> Clase | B2: =Clases!A6 -> PrefijoCelular
A3: =Clases!$B$1 -> Estereotipo | B3: =Clases!B6 -> class
A4: =Clases!$C$1 -> Desripción | B4: =Clases!C6 -> Representa el catálogo de prefijos telefónicos de país que el administrador habilita, y que son los únicos que barberos y clientes pueden usar en su número de celular.
A5: Modificador acceso: | B5: public
A6: Tipo clase: | B6: no final
A7: Relaciones
A8: Relación | B8: Tipo relación | E8: Estructura
A9: Es usada por | B9: Asociación | E9: =Cliente!B2 -> Cliente
A10: Es usada por | B10: Asociación | E10: =Barbero!B2 -> Barbero
A11: Atributos
A12: Modificador de aceso | B12: Nombre | C12: Tipo de dato | E12: Tipo modificación atributo | F12: Tipo acceso atributo | G12: Valor por defecto | J12: Descripción atributo
C13: Tipo de dato | D13: ¿Cuál?
A14: private | B14: id | C14: Otro | D14: UUID | E14: no final | F14: no static | G14: new UUID(0L, 0L) | J14: Representa un identificador que hará unico cada objeto de dominio de este tipo, no se puede repetir
A15: private | B15: prefijo | C15: String | E15: no final | F15: no static | G15: "+0" | J15: Representa el prefijo telefónico del país que el administrador habilita para que la barbería pueda atender números de ese país
A16: Constructores
A17: Modificador de aceso | B17: Nombre | C17: Tipo constructor | D17: Descripción | E17: Parámetros | M17: Excepciones
E18: Nombre | F18: Tipo de dato | G18: ¿Cuál? | H18: Tipo parámetro | I18: Tipo modificación atributo | J18: Descripción
A19: public | B19: =B2 -> PrefijoCelular | C19: Defecto | D19: Constructor por defecto que crea un objeto PrefijoCelular con todos sus atributos en su valor por defecto
A20: public | B20: =B2 -> PrefijoCelular | C20: Parametrizado | D20: Constructor parametrizado que crea un objeto PrefijoCelular asignando el valor recibido a cada uno de sus atributos | E20: valorId | F20: Otro | G20: UUID | H20: Por referencia | I20: no final | J20: Valor que se asigna al atributo id
E21: valorPrefijo | F21: String | H21: Por valor | I21: no final | J21: Valor que se asigna al atributo prefijo
A22: Métodos accesores
A23: Modificador de aceso | B23: Nombre | C23: Tipo método accesor | D23: Tipo modificación método | E23: Descripción | F23: Parámetros | L23: Tipo dato de retorno | N23: Excepciones
F24: Nombre | G24: Tipo de dato | H24: ¿Cuál? | I24: Tipo parámetro | J24: Tipo modificación atributo | K24: Descripción | L24: Tipo de dato | M24: ¿Cuál?
A25: public | B25: getId | C25: getter | D25: no final | E25: Método encargado de obtener el valor del atributo id | L25: Otro | M25: UUID
A26: public | B26: setId | C26: setter | D26: no final | E26: Método encargado de colocar el valor al atributo id | F26: valorId | G26: Otro | H26: UUID | I26: Por referencia | J26: no final | K26: Nuevo valor del atributo id | L26: void
A27: public | B27: getPrefijo | C27: getter | D27: no final | E27: Método encargado de obtener el valor del atributo prefijo | L27: String
A28: public | B28: setPrefijo | C28: setter | D28: no final | E28: Método encargado de colocar el valor al atributo prefijo | F28: valorPrefijo | G28: String | I28: Por valor | J28: no final | K28: Nuevo valor del atributo prefijo | L28: void
A29: Métodos
A30: Modificador de aceso | B30: Nombre | C30: Tipo acceso método | D30: Tipo modificación método | E30: Descripción | F30: Parámetros | L30: Tipo dato de retorno | N30: Excepciones
F31: Nombre | G31: Tipo de dato | H31: ¿Cuál? | I31: Tipo parámetro | J31: Tipo modificación atributo | K31: Descripción | L31: Tipo de dato | M31: ¿Cuál?
A32: public | B32: consultarPrefijosCelular | C32: no static | D32: no final | E32: Permite al administrador consultar el catálogo de prefijos telefónicos de país que tiene habilitados | L32: Otro | M32: List<PrefijoCelular> | N32: No aplica

Sheet TipoMulta
A1: <-Volver al inicio
A2: =Clases!$A$1 -> Clase | B2: =Clases!A7 -> TipoMulta
A3: =Clases!$B$1 -> Estereotipo | B3: =Clases!B7 -> class
A4: =Clases!$C$1 -> Desripción | B4: =Clases!C7 -> Representa los tipos de multa que puede recibir un cliente: por tardanza o por inasistencia.
A5: Modificador acceso: | B5: public
A6: Tipo clase: | B6: no final
A7: Relaciones
A8: Relación | B8: Tipo relación | E8: Estructura
A9: Es usada por | B9: Asociación | E9: =Multa!B2 -> Multa
A10: Atributos
A11: Modificador de aceso | B11: Nombre | C11: Tipo de dato | E11: Tipo modificación atributo | F11: Tipo acceso atributo | G11: Valor por defecto | J11: Descripción atributo
C12: Tipo de dato | D12: ¿Cuál?
A13: private | B13: id | C13: Otro | D13: UUID | E13: no final | F13: no static | G13: new UUID(0L, 0L) | J13: Representa un identificador que hará unico cada objeto de dominio de este tipo, no se puede repetir
A14: private | B14: nombre | C14: String | E14: no final | F14: no static | G14: "" | J14: Representa el nombre del tipo de multa
A15: private | B15: descripcion | C15: String | E15: no final | F15: no static | G15: "" | J15: Representa que hace cada tipo de multa
A16: Constructores
A17: Modificador de aceso | B17: Nombre | C17: Tipo constructor | D17: Descripción | E17: Parámetros | M17: Excepciones
E18: Nombre | F18: Tipo de dato | G18: ¿Cuál? | H18: Tipo parámetro | I18: Tipo modificación atributo | J18: Descripción
A19: public | B19: =B2 -> TipoMulta | C19: Defecto | D19: Constructor por defecto que crea un objeto TipoMulta con todos sus atributos en su valor por defecto
A20: public | B20: =B2 -> TipoMulta | C20: Parametrizado | D20: Constructor parametrizado que crea un objeto TipoMulta asignando el valor recibido a cada uno de sus atributos | E20: valorId | F20: Otro | G20: UUID | H20: Por referencia | I20: no final | J20: Valor que se asigna al atributo id
E21: valorNombre | F21: String | H21: Por valor | I21: no final | J21: Valor que se asigna al atributo nombre
E22: valorDescripcion | F22: String | H22: Por valor | I22: no final | J22: Valor que se asigna al atributo descripcion
A23: Métodos accesores
A24: Modificador de aceso | B24: Nombre | C24: Tipo método accesor | D24: Tipo modificación método | E24: Descripción | F24: Parámetros | L24: Tipo dato de retorno | N24: Excepciones
F25: Nombre | G25: Tipo de dato | H25: ¿Cuál? | I25: Tipo parámetro | J25: Tipo modificación atributo | K25: Descripción | L25: Tipo de dato | M25: ¿Cuál?
A26: public | B26: getId | C26: getter | D26: no final | E26: Método encargado de obtener el valor del atributo id | L26: Otro | M26: UUID
A27: public | B27: setId | C27: setter | D27: no final | E27: Método encargado de colocar el valor al atributo id | F27: valorId | G27: Otro | H27: UUID | I27: Por referencia | J27: no final | K27: Nuevo valor del atributo id | L27: void
A28: public | B28: getNombre | C28: getter | D28: no final | E28: Método encargado de obtener el valor del atributo nombre | L28: String
A29: public | B29: setNombre | C29: setter | D29: no final | E29: Método encargado de colocar el valor al atributo nombre | F29: valorNombre | G29: String | I29: Por valor | J29: no final | K29: Nuevo valor del atributo nombre | L29: void
A30: public | B30: getDescripcion | C30: getter | D30: no final | E30: Método encargado de obtener el valor del atributo descripcion | L30: String
A31: public | B31: setDescripcion | C31: setter | D31: no final | E31: Método encargado de colocar el valor al atributo descripcion | F31: valorDescripcion | G31: String | I31: Por valor | J31: no final | K31: Nuevo valor del atributo descripcion | L31: void
A32: Métodos
A33: Modificador de aceso | B33: Nombre | C33: Tipo acceso método | D33: Tipo modificación método | E33: Descripción | F33: Parámetros | L33: Tipo dato de retorno | N33: Excepciones
F34: Nombre | G34: Tipo de dato | H34: ¿Cuál? | I34: Tipo parámetro | J34: Tipo modificación atributo | K34: Descripción | L34: Tipo de dato | M34: ¿Cuál?
A35: public | B35: consultarTodosLosTiposMulta | C35: no static | D35: no final | E35: Permite consultar los tipos de multa que puede recibir un cliente | L35: Otro | M35: List<TipoMulta> | N35: No aplica

Sheet TipoRegistroHora
A1: <-Volver al inicio
A2: =Clases!$A$1 -> Clase | B2: =Clases!A8 -> TipoRegistroHora
A3: =Clases!$B$1 -> Estereotipo | B3: =Clases!B8 -> class
A4: =Clases!$C$1 -> Desripción | B4: =Clases!C8 -> Representa el catálogo de los distintos momentos en que se puede registrar una hora real durante una cita: llegada del cliente, barbero preparado, inicio y fin de la atención.
A5: Modificador acceso: | B5: public
A6: Tipo clase: | B6: no final
A7: Relaciones
A8: Relación | B8: Tipo relación | E8: Estructura
A9: Es usada por | B9: Asociación | E9: =RegistroHoraCita!B2 -> RegistroHoraCita
A10: Atributos
A11: Modificador de aceso | B11: Nombre | C11: Tipo de dato | E11: Tipo modificación atributo | F11: Tipo acceso atributo | G11: Valor por defecto | J11: Descripción atributo
C12: Tipo de dato | D12: ¿Cuál?
A13: private | B13: id | C13: Otro | D13: UUID | E13: no final | F13: no static | G13: new UUID(0L, 0L) | J13: Representa un identificador que hará unico cada objeto de dominio de este tipo, no se puede repetir
A14: private | B14: nombre | C14: String | E14: no final | F14: no static | G14: "" | J14: Representa el nombre del tipo de hora real que se puede registrar durante una cita
A15: Constructores
A16: Modificador de aceso | B16: Nombre | C16: Tipo constructor | D16: Descripción | E16: Parámetros | M16: Excepciones
E17: Nombre | F17: Tipo de dato | G17: ¿Cuál? | H17: Tipo parámetro | I17: Tipo modificación atributo | J17: Descripción
A18: public | B18: =B2 -> TipoRegistroHora | C18: Defecto | D18: Constructor por defecto que crea un objeto TipoRegistroHora con todos sus atributos en su valor por defecto
A19: public | B19: =B2 -> TipoRegistroHora | C19: Parametrizado | D19: Constructor parametrizado que crea un objeto TipoRegistroHora asignando el valor recibido a cada uno de sus atributos | E19: valorId | F19: Otro | G19: UUID | H19: Por referencia | I19: no final | J19: Valor que se asigna al atributo id
E20: valorNombre | F20: String | H20: Por valor | I20: no final | J20: Valor que se asigna al atributo nombre
A21: Métodos accesores
A22: Modificador de aceso | B22: Nombre | C22: Tipo método accesor | D22: Tipo modificación método | E22: Descripción | F22: Parámetros | L22: Tipo dato de retorno | N22: Excepciones
F23: Nombre | G23: Tipo de dato | H23: ¿Cuál? | I23: Tipo parámetro | J23: Tipo modificación atributo | K23: Descripción | L23: Tipo de dato | M23: ¿Cuál?
A24: public | B24: getId | C24: getter | D24: no final | E24: Método encargado de obtener el valor del atributo id | L24: Otro | M24: UUID
A25: public | B25: setId | C25: setter | D25: no final | E25: Método encargado de colocar el valor al atributo id | F25: valorId | G25: Otro | H25: UUID | I25: Por referencia | J25: no final | K25: Nuevo valor del atributo id | L25: void
A26: public | B26: getNombre | C26: getter | D26: no final | E26: Método encargado de obtener el valor del atributo nombre | L26: String
A27: public | B27: setNombre | C27: setter | D27: no final | E27: Método encargado de colocar el valor al atributo nombre | F27: valorNombre | G27: String | I27: Por valor | J27: no final | K27: Nuevo valor del atributo nombre | L27: void
A28: Métodos
A29: Modificador de aceso | B29: Nombre | C29: Tipo acceso método | D29: Tipo modificación método | E29: Descripción | F29: Parámetros | L29: Tipo dato de retorno | N29: Excepciones
F30: Nombre | G30: Tipo de dato | H30: ¿Cuál? | I30: Tipo parámetro | J30: Tipo modificación atributo | K30: Descripción | L30: Tipo de dato | M30: ¿Cuál?
A31: public | B31: consultarTiposRegistroHora | C31: no static | D31: no final | E31: Permite consultar el catálogo de tipos de registro de hora de una cita | L31: Otro | M31: List<TipoRegistroHora> | N31: No aplica

Sheet Cliente
A1: <-Volver al inicio
A2: =Clases!$A$1 -> Clase | B2: =Clases!A9 -> Cliente
A3: =Clases!$B$1 -> Estereotipo | B3: =Clases!B9 -> class
A4: =Clases!$C$1 -> Desripción | B4: =Clases!C9 -> Representa a la persona que solicita citas en la barbería.
A5: Modificador acceso: | B5: public
A6: Tipo clase: | B6: no final
A7: Relaciones
A8: Relación | B8: Tipo relación | E8: Estructura
A9: Necesita de | B9: Asociación | E9: =PrefijoCelular!B2 -> PrefijoCelular
A10: Es usada por | B10: Composición | E10: =Cita!B2 -> Cita
A11: Atributos
A12: Modificador de aceso | B12: Nombre | C12: Tipo de dato | E12: Tipo modificación atributo | F12: Tipo acceso atributo | G12: Valor por defecto | J12: Descripción atributo
C13: Tipo de dato | D13: ¿Cuál?
A14: private | B14: id | C14: Otro | D14: UUID | E14: no final | F14: no static | G14: new UUID(0L, 0L) | J14: Representa un identificador que hará unico cada objeto de dominio de este tipo, no se puede repetir
A15: private | B15: primerNombre | C15: String | E15: no final | F15: no static | G15: "" | J15: Representa el primer nombre de la persona, que va a estar llendo a la barberia para las citas
A16: private | B16: segundoNombre | C16: String | E16: no final | F16: no static | G16: "" | J16: Representa el segundo nombre de la persona, que va a estar llendo a la barberia para las citas
A17: private | B17: primerApellido | C17: String | E17: no final | F17: no static | G17: "" | J17: Representa el primer apellido de la persona, que va a estar llendo a la barberia para las citas
A18: private | B18: segundoApellido | C18: String | E18: no final | F18: no static | G18: "" | J18: Representa el segundo apellido de la persona, que va a estar llendo a la barberia para las citas
A19: private | B19: prefijoCelular | C19: Otro | D19: PrefijoCelular | E19: no final | F19: no static | G19: new PrefijoCelular() | J19: Representa cual es el prefijo del numero de celular del cliente
A20: private | B20: celular | C20: String | E20: no final | F20: no static | G20: "0" | J20: Representa el numero de celular del cliente, es el dato que el barbero necesita en caso de que tenga que contactarse con el
A21: private | B21: elNumeroCelularEsCorrecto | C21: boolean/Boolean | E21: no final | F21: no static | G21: false | J21: Representa si el numero que ingreso el cliente es correcto o no
A22: private | B22: estaVetado | C22: boolean/Boolean | E22: no final | F22: no static | G22: false | J22: Representa si el cliente esta en estado de veto o no, cuando el cliente esta vetado el sistema no va a permitir agendar citas con este cliente con ningun barbero
A23: Constructores
A24: Modificador de aceso | B24: Nombre | C24: Tipo constructor | D24: Descripción | E24: Parámetros | M24: Excepciones
E25: Nombre | F25: Tipo de dato | G25: ¿Cuál? | H25: Tipo parámetro | I25: Tipo modificación atributo | J25: Descripción
A26: public | B26: =B2 -> Cliente | C26: Defecto | D26: Constructor por defecto que crea un objeto Cliente con todos sus atributos en su valor por defecto
A27: public | B27: =B2 -> Cliente | C27: Parametrizado | D27: Constructor parametrizado que crea un objeto Cliente asignando el valor recibido a cada uno de sus atributos | E27: valorId | F27: Otro | G27: UUID | H27: Por referencia | I27: no final | J27: Valor que se asigna al atributo id
E28: valorPrimerNombre | F28: String | H28: Por valor | I28: no final | J28: Valor que se asigna al atributo primerNombre
E29: valorSegundoNombre | F29: String | H29: Por valor | I29: no final | J29: Valor que se asigna al atributo segundoNombre
E30: valorPrimerApellido | F30: String | H30: Por valor | I30: no final | J30: Valor que se asigna al atributo primerApellido
E31: valorSegundoApellido | F31: String | H31: Por valor | I31: no final | J31: Valor que se asigna al atributo segundoApellido
E32: valorPrefijoCelular | F32: Otro | G32: PrefijoCelular | H32: Por referencia | I32: no final | J32: Valor que se asigna al atributo prefijoCelular
E33: valorCelular | F33: String | H33: Por valor | I33: no final | J33: Valor que se asigna al atributo celular
E34: valorElNumeroCelularEsCorrecto | F34: boolean/Boolean | H34: Por valor | I34: no final | J34: Valor que se asigna al atributo elNumeroCelularEsCorrecto
E35: valorEstaVetado | F35: boolean/Boolean | H35: Por valor | I35: no final | J35: Valor que se asigna al atributo estaVetado
A36: Métodos accesores
A37: Modificador de aceso | B37: Nombre | C37: Tipo método accesor | D37: Tipo modificación método | E37: Descripción | F37: Parámetros | L37: Tipo dato de retorno | N37: Excepciones
F38: Nombre | G38: Tipo de dato | H38: ¿Cuál? | I38: Tipo parámetro | J38: Tipo modificación atributo | K38: Descripción | L38: Tipo de dato | M38: ¿Cuál?
A39: public | B39: getId | C39: getter | D39: no final | E39: Método encargado de obtener el valor del atributo id | L39: Otro | M39: UUID
A40: public | B40: setId | C40: setter | D40: no final | E40: Método encargado de colocar el valor al atributo id | F40: valorId | G40: Otro | H40: UUID | I40: Por referencia | J40: no final | K40: Nuevo valor del atributo id | L40: void
A41: public | B41: getPrimerNombre | C41: getter | D41: no final | E41: Método encargado de obtener el valor del atributo primerNombre | L41: String
A42: public | B42: setPrimerNombre | C42: setter | D42: no final | E42: Método encargado de colocar el valor al atributo primerNombre | F42: valorPrimerNombre | G42: String | I42: Por valor | J42: no final | K42: Nuevo valor del atributo primerNombre | L42: void
A43: public | B43: getSegundoNombre | C43: getter | D43: no final | E43: Método encargado de obtener el valor del atributo segundoNombre | L43: String
A44: public | B44: setSegundoNombre | C44: setter | D44: no final | E44: Método encargado de colocar el valor al atributo segundoNombre | F44: valorSegundoNombre | G44: String | I44: Por valor | J44: no final | K44: Nuevo valor del atributo segundoNombre | L44: void
A45: public | B45: getPrimerApellido | C45: getter | D45: no final | E45: Método encargado de obtener el valor del atributo primerApellido | L45: String
A46: public | B46: setPrimerApellido | C46: setter | D46: no final | E46: Método encargado de colocar el valor al atributo primerApellido | F46: valorPrimerApellido | G46: String | I46: Por valor | J46: no final | K46: Nuevo valor del atributo primerApellido | L46: void
A47: public | B47: getSegundoApellido | C47: getter | D47: no final | E47: Método encargado de obtener el valor del atributo segundoApellido | L47: String
A48: public | B48: setSegundoApellido | C48: setter | D48: no final | E48: Método encargado de colocar el valor al atributo segundoApellido | F48: valorSegundoApellido | G48: String | I48: Por valor | J48: no final | K48: Nuevo valor del atributo segundoApellido | L48: void
A49: public | B49: getPrefijoCelular | C49: getter | D49: no final | E49: Método encargado de obtener el valor del atributo prefijoCelular | L49: Otro | M49: PrefijoCelular
A50: public | B50: setPrefijoCelular | C50: setter | D50: no final | E50: Método encargado de colocar el valor al atributo prefijoCelular | F50: valorPrefijoCelular | G50: Otro | H50: PrefijoCelular | I50: Por referencia | J50: no final | K50: Nuevo valor del atributo prefijoCelular | L50: void
A51: public | B51: getCelular | C51: getter | D51: no final | E51: Método encargado de obtener el valor del atributo celular | L51: String
A52: public | B52: setCelular | C52: setter | D52: no final | E52: Método encargado de colocar el valor al atributo celular | F52: valorCelular | G52: String | I52: Por valor | J52: no final | K52: Nuevo valor del atributo celular | L52: void
A53: public | B53: getElNumeroCelularEsCorrecto | C53: getter | D53: no final | E53: Método encargado de obtener el valor del atributo elNumeroCelularEsCorrecto | L53: boolean/Boolean
A54: public | B54: setElNumeroCelularEsCorrecto | C54: setter | D54: no final | E54: Método encargado de colocar el valor al atributo elNumeroCelularEsCorrecto | F54: valorElNumeroCelularEsCorrecto | G54: boolean/Boolean | I54: Por valor | J54: no final | K54: Nuevo valor del atributo elNumeroCelularEsCorrecto | L54: void
A55: public | B55: getEstaVetado | C55: getter | D55: no final | E55: Método encargado de obtener el valor del atributo estaVetado | L55: boolean/Boolean
A56: public | B56: setEstaVetado | C56: setter | D56: no final | E56: Método encargado de colocar el valor al atributo estaVetado | F56: valorEstaVetado | G56: boolean/Boolean | I56: Por valor | J56: no final | K56: Nuevo valor del atributo estaVetado | L56: void
A57: Métodos
A58: Modificador de aceso | B58: Nombre | C58: Tipo acceso método | D58: Tipo modificación método | E58: Descripción | F58: Parámetros | L58: Tipo dato de retorno | N58: Excepciones
F59: Nombre | G59: Tipo de dato | H59: ¿Cuál? | I59: Tipo parámetro | J59: Tipo modificación atributo | K59: Descripción | L59: Tipo de dato | M59: ¿Cuál?
A60: public | B60: registrarCliente | C60: no static | D60: no final | E60: Comando que permite el registro de un nuevo cliente en la barbería | F60: primerNombre | G60: String | I60: Por valor | J60: no final | K60: Representa el primer nombre de la persona, que va a estar llendo a la barberia para las citas | L60: Otro | M60: Cliente | N60: Generar una excepción indicándole al usuario cuáles datos del cliente no cumplen con las reglas definidas; Generar una excepción indicándole al usuario que ya existe otro cliente registrado con ese prefijo y número de celular
F61: segundoNombre | G61: String | I61: Por valor | J61: no final | K61: Representa el segundo nombre de la persona, que va a estar llendo a la barberia para las citas
F62: primerApellido | G62: String | I62: Por valor | J62: no final | K62: Representa el primer apellido de la persona, que va a estar llendo a la barberia para las citas
F63: segundoApellido | G63: String | I63: Por valor | J63: no final | K63: Representa el segundo apellido de la persona, que va a estar llendo a la barberia para las citas
F64: prefijoCelular | G64: Otro | H64: PrefijoCelular | I64: Por referencia | J64: no final | K64: Representa cual es el prefijo del numero de celular del cliente
F65: celular | G65: String | I65: Por valor | J65: no final | K65: Representa el numero de celular del cliente, es el dato que el barbero necesita en caso de que tenga que contactarse con el
A66: public | B66: editarContactoCliente | C66: no static | D66: no final | E66: Permite al cliente actualizar su número de celular y su prefijo | F66: id | G66: Otro | H66: UUID | I66: Por referencia | J66: no final | K66: Corresponde al identificador del cliente que va a editar su contacto | L66: Otro | M66: Cliente | N66: Informar con un mensaje que no existe un cliente con el identificador enviado y por lo tanto no es posible editar el contacto del cliente; Generar una excepción indicándole al usuario cuáles datos de contacto del cliente no cumplen con las reglas definidas
F67: prefijoCelular | G67: Otro | H67: PrefijoCelular | I67: Por referencia | J67: no final | K67: Representa cual es el prefijo del numero de celular del cliente
F68: celular | G68: String | I68: Por valor | J68: no final | K68: Representa el numero de celular del cliente, es el dato que el barbero necesita en caso de que tenga que contactarse con el
A69: public | B69: consultarDatosCliente | C69: no static | D69: no final | E69: Permite a un barbero ver los datos de un cliente que le va a pedir una cita | F69: id | G69: Otro | H69: UUID | I69: Por referencia | J69: no final | K69: Corresponde al identificador del cliente que se va a consultar | L69: Otro | M69: Cliente | N69: Informar con un mensaje que no existe un cliente con el identificador enviado y por lo tanto no es posible llevar a cabo la operación
A70: public | B70: consultarEstadoVetoCliente | C70: no static | D70: no final | E70: Permite al cliente ver si tiene alguna multa sin pagar que le impida agendar nuevas citas | F70: id | G70: Otro | H70: UUID | I70: Por referencia | J70: no final | K70: Corresponde al identificador del cliente que se va a consultar | L70: boolean/Boolean | N70: Informar con un mensaje que no existe un cliente con el identificador enviado y por lo tanto no es posible llevar a cabo la operación
A71: public | B71: consultarCantidadMultasSinPagar | C71: no static | D71: no final | E71: Permite al cliente ver cuántas multas sin pagar tiene | F71: id | G71: Otro | H71: UUID | I71: Por referencia | J71: no final | K71: Corresponde al identificador del cliente que se va a consultar | L71: int/Integer | N71: Informar con un mensaje que no existe un cliente con el identificador enviado y por lo tanto no es posible llevar a cabo la operación
A72: public | B72: vetarCliente | C72: no static | D72: no final | E72: Permite al sistema vetar a un cliente que tiene multas sin pagar, para que no pueda agendar nuevas citas | F72: id | G72: Otro | H72: UUID | I72: Por referencia | J72: no final | K72: Corresponde al identificador del cliente que se va a vetar | L72: void | N72: Informar con un mensaje que no existe un cliente con el identificador enviado; No dar el veto porque el cliente no tiene multas sin pagar
A73: public | B73: quitarVetoCliente | C73: no static | D73: no final | E73: Permite al sistema quitar el veto a un cliente cuando ya no tiene multas sin pagar | F73: id | G73: Otro | H73: UUID | I73: Por referencia | J73: no final | K73: Corresponde al identificador del cliente al que se le va a quitar el veto | L73: void | N73: Informar con un mensaje que no existe un cliente con el identificador enviado; No quitar el veto porque el cliente todavía tiene multas sin pagar

Sheet Ciudad
A1: <-Volver al inicio
A2: =Clases!$A$1 -> Clase | B2: =Clases!A10 -> Ciudad
A3: =Clases!$B$1 -> Estereotipo | B3: =Clases!B10 -> class
A4: =Clases!$C$1 -> Desripción | B4: =Clases!C10 -> Representa cada una de las ciudades, pertenecientes a un departamento, en las que puede estar ubicada una sede de la barbería.
A5: Modificador acceso: | B5: public
A6: Tipo clase: | B6: no final
A7: Relaciones
A8: Relación | B8: Tipo relación | E8: Estructura
A9: Necesita de | B9: Composición | E9: =Departamento!B2 -> Departamento
A10: Es usada por | B10: Agregación | E10: =Sede!B2 -> Sede
A11: Atributos
A12: Modificador de aceso | B12: Nombre | C12: Tipo de dato | E12: Tipo modificación atributo | F12: Tipo acceso atributo | G12: Valor por defecto | J12: Descripción atributo
C13: Tipo de dato | D13: ¿Cuál?
A14: private | B14: id | C14: Otro | D14: UUID | E14: no final | F14: no static | G14: new UUID(0L, 0L) | J14: Representa un identificador que hará unico cada objeto de dominio de este tipo, no se puede repetir
A15: private | B15: nombre | C15: String | E15: no final | F15: no static | G15: "" | J15: Representa el nombre de la ciudad en la que puede estar ubicada una sede de la barbería
A16: private | B16: departamento | C16: Otro | D16: Departamento | E16: no final | F16: no static | G16: new Departamento() | J16: Representa a qué departamento pertenece esta ciudad
A17: Constructores
A18: Modificador de aceso | B18: Nombre | C18: Tipo constructor | D18: Descripción | E18: Parámetros | M18: Excepciones
E19: Nombre | F19: Tipo de dato | G19: ¿Cuál? | H19: Tipo parámetro | I19: Tipo modificación atributo | J19: Descripción
A20: public | B20: =B2 -> Ciudad | C20: Defecto | D20: Constructor por defecto que crea un objeto Ciudad con todos sus atributos en su valor por defecto
A21: public | B21: =B2 -> Ciudad | C21: Parametrizado | D21: Constructor parametrizado que crea un objeto Ciudad asignando el valor recibido a cada uno de sus atributos | E21: valorId | F21: Otro | G21: UUID | H21: Por referencia | I21: no final | J21: Valor que se asigna al atributo id
E22: valorNombre | F22: String | H22: Por valor | I22: no final | J22: Valor que se asigna al atributo nombre
E23: valorDepartamento | F23: Otro | G23: Departamento | H23: Por referencia | I23: no final | J23: Valor que se asigna al atributo departamento
A24: Métodos accesores
A25: Modificador de aceso | B25: Nombre | C25: Tipo método accesor | D25: Tipo modificación método | E25: Descripción | F25: Parámetros | L25: Tipo dato de retorno | N25: Excepciones
F26: Nombre | G26: Tipo de dato | H26: ¿Cuál? | I26: Tipo parámetro | J26: Tipo modificación atributo | K26: Descripción | L26: Tipo de dato | M26: ¿Cuál?
A27: public | B27: getId | C27: getter | D27: no final | E27: Método encargado de obtener el valor del atributo id | L27: Otro | M27: UUID
A28: public | B28: setId | C28: setter | D28: no final | E28: Método encargado de colocar el valor al atributo id | F28: valorId | G28: Otro | H28: UUID | I28: Por referencia | J28: no final | K28: Nuevo valor del atributo id | L28: void
A29: public | B29: getNombre | C29: getter | D29: no final | E29: Método encargado de obtener el valor del atributo nombre | L29: String
A30: public | B30: setNombre | C30: setter | D30: no final | E30: Método encargado de colocar el valor al atributo nombre | F30: valorNombre | G30: String | I30: Por valor | J30: no final | K30: Nuevo valor del atributo nombre | L30: void
A31: public | B31: getDepartamento | C31: getter | D31: no final | E31: Método encargado de obtener el valor del atributo departamento | L31: Otro | M31: Departamento
A32: public | B32: setDepartamento | C32: setter | D32: no final | E32: Método encargado de colocar el valor al atributo departamento | F32: valorDepartamento | G32: Otro | H32: Departamento | I32: Por referencia | J32: no final | K32: Nuevo valor del atributo departamento | L32: void
A33: Métodos
A34: Modificador de aceso | B34: Nombre | C34: Tipo acceso método | D34: Tipo modificación método | E34: Descripción | F34: Parámetros | L34: Tipo dato de retorno | N34: Excepciones
F35: Nombre | G35: Tipo de dato | H35: ¿Cuál? | I35: Tipo parámetro | J35: Tipo modificación atributo | K35: Descripción | L35: Tipo de dato | M35: ¿Cuál?
A36: public | B36: consultarCiudades | C36: no static | D36: no final | E36: Permite consultar el catálogo de ciudades con su departamento | L36: Otro | M36: List<Ciudad> | N36: No aplica

Sheet Sede
A1: <-Volver al inicio
A2: =Clases!$A$1 -> Clase | B2: =Clases!A11 -> Sede
A3: =Clases!$B$1 -> Estereotipo | B3: =Clases!B11 -> class
A4: =Clases!$C$1 -> Desripción | B4: =Clases!C11 -> Representa cada una de las sucursales físicas de una barbería, ubicada en una ciudad puntual, donde se ofrecen los servicios y trabajan los barberos.
A5: Modificador acceso: | B5: public
A6: Tipo clase: | B6: no final
A7: Relaciones
A8: Relación | B8: Tipo relación | E8: Estructura
A9: Necesita de | B9: Agregación | E9: =Ciudad!B2 -> Ciudad
A10: Necesita de | B10: Composición | E10: =Barberia!B2 -> Barberia
A11: Es usada por | B11: Agregación | E11: =Barbero!B2 -> Barbero
A12: Es usada por | B12: Composición | E12: =HorarioBarberia!B2 -> HorarioBarberia
A13: Es usada por | B13: Asociación | E13: =Servicio!B2 -> Servicio
A14: Atributos
A15: Modificador de aceso | B15: Nombre | C15: Tipo de dato | E15: Tipo modificación atributo | F15: Tipo acceso atributo | G15: Valor por defecto | J15: Descripción atributo
C16: Tipo de dato | D16: ¿Cuál?
A17: private | B17: id | C17: Otro | D17: UUID | E17: no final | F17: no static | G17: new UUID(0L, 0L) | J17: Representa un identificador que hará unico cada objeto de dominio de este tipo, no se puede repetir
A18: private | B18: ciudad | C18: Otro | D18: Ciudad | E18: no final | F18: no static | G18: new Ciudad() | J18: Representa a qué ciudad pertenece esta sede
A19: private | B19: barberia | C19: Otro | D19: Barberia | E19: no final | F19: no static | G19: new Barberia() | J19: Representa a qué barbería pertenece esta sede
A20: private | B20: nombre | C20: String | E20: no final | F20: no static | G20: "" | J20: Representa el nombre con el que se identifica esta sede dentro de la barbería a la que pertenece
A21: private | B21: direccion | C21: String | E21: no final | F21: no static | G21: "" | J21: Representa la dirección física en la que está ubicada esta sede
A22: Constructores
A23: Modificador de aceso | B23: Nombre | C23: Tipo constructor | D23: Descripción | E23: Parámetros | M23: Excepciones
E24: Nombre | F24: Tipo de dato | G24: ¿Cuál? | H24: Tipo parámetro | I24: Tipo modificación atributo | J24: Descripción
A25: public | B25: =B2 -> Sede | C25: Defecto | D25: Constructor por defecto que crea un objeto Sede con todos sus atributos en su valor por defecto
A26: public | B26: =B2 -> Sede | C26: Parametrizado | D26: Constructor parametrizado que crea un objeto Sede asignando el valor recibido a cada uno de sus atributos | E26: valorId | F26: Otro | G26: UUID | H26: Por referencia | I26: no final | J26: Valor que se asigna al atributo id
E27: valorCiudad | F27: Otro | G27: Ciudad | H27: Por referencia | I27: no final | J27: Valor que se asigna al atributo ciudad
E28: valorBarberia | F28: Otro | G28: Barberia | H28: Por referencia | I28: no final | J28: Valor que se asigna al atributo barberia
E29: valorNombre | F29: String | H29: Por valor | I29: no final | J29: Valor que se asigna al atributo nombre
E30: valorDireccion | F30: String | H30: Por valor | I30: no final | J30: Valor que se asigna al atributo direccion
A31: Métodos accesores
A32: Modificador de aceso | B32: Nombre | C32: Tipo método accesor | D32: Tipo modificación método | E32: Descripción | F32: Parámetros | L32: Tipo dato de retorno | N32: Excepciones
F33: Nombre | G33: Tipo de dato | H33: ¿Cuál? | I33: Tipo parámetro | J33: Tipo modificación atributo | K33: Descripción | L33: Tipo de dato | M33: ¿Cuál?
A34: public | B34: getId | C34: getter | D34: no final | E34: Método encargado de obtener el valor del atributo id | L34: Otro | M34: UUID
A35: public | B35: setId | C35: setter | D35: no final | E35: Método encargado de colocar el valor al atributo id | F35: valorId | G35: Otro | H35: UUID | I35: Por referencia | J35: no final | K35: Nuevo valor del atributo id | L35: void
A36: public | B36: getCiudad | C36: getter | D36: no final | E36: Método encargado de obtener el valor del atributo ciudad | L36: Otro | M36: Ciudad
A37: public | B37: setCiudad | C37: setter | D37: no final | E37: Método encargado de colocar el valor al atributo ciudad | F37: valorCiudad | G37: Otro | H37: Ciudad | I37: Por referencia | J37: no final | K37: Nuevo valor del atributo ciudad | L37: void
A38: public | B38: getBarberia | C38: getter | D38: no final | E38: Método encargado de obtener el valor del atributo barberia | L38: Otro | M38: Barberia
A39: public | B39: setBarberia | C39: setter | D39: no final | E39: Método encargado de colocar el valor al atributo barberia | F39: valorBarberia | G39: Otro | H39: Barberia | I39: Por referencia | J39: no final | K39: Nuevo valor del atributo barberia | L39: void
A40: public | B40: getNombre | C40: getter | D40: no final | E40: Método encargado de obtener el valor del atributo nombre | L40: String
A41: public | B41: setNombre | C41: setter | D41: no final | E41: Método encargado de colocar el valor al atributo nombre | F41: valorNombre | G41: String | I41: Por valor | J41: no final | K41: Nuevo valor del atributo nombre | L41: void
A42: public | B42: getDireccion | C42: getter | D42: no final | E42: Método encargado de obtener el valor del atributo direccion | L42: String
A43: public | B43: setDireccion | C43: setter | D43: no final | E43: Método encargado de colocar el valor al atributo direccion | F43: valorDireccion | G43: String | I43: Por valor | J43: no final | K43: Nuevo valor del atributo direccion | L43: void
A44: Métodos
A45: Modificador de aceso | B45: Nombre | C45: Tipo acceso método | D45: Tipo modificación método | E45: Descripción | F45: Parámetros | L45: Tipo dato de retorno | N45: Excepciones
F46: Nombre | G46: Tipo de dato | H46: ¿Cuál? | I46: Tipo parámetro | J46: Tipo modificación atributo | K46: Descripción | L46: Tipo de dato | M46: ¿Cuál?
A47: public | B47: registrarSede | C47: no static | D47: no final | E47: Comando que permite registrar una nueva sede de una barbería en una ciudad | F47: barberia | G47: Otro | H47: Barberia | I47: Por referencia | J47: no final | K47: Representa a qué barbería pertenece esta sede | L47: Otro | M47: Sede | N47: Generar una excepción indicándole al administrador cuáles datos de la sede no cumplen con las reglas definidas; Generar una excepción indicándole al administrador que ya existe una sede con ese nombre en la barbería
F48: ciudad | G48: Otro | H48: Ciudad | I48: Por referencia | J48: no final | K48: Representa a qué ciudad pertenece esta sede
F49: nombre | G49: String | I49: Por valor | J49: no final | K49: Representa el nombre con el que se identifica esta sede dentro de la barbería a la que pertenece
F50: direccion | G50: String | I50: Por valor | J50: no final | K50: Representa la dirección física en la que está ubicada esta sede
A51: public | B51: consultarDatosSede | C51: no static | D51: no final | E51: Permite consultar el nombre y la dirección de una sede | F51: id | G51: Otro | H51: UUID | I51: Por referencia | J51: no final | K51: Corresponde al identificador de la sede que se va a consultar | L51: Otro | M51: Sede | N51: Informar con un mensaje que no existe una sede con el identificador enviado y por lo tanto no se puede realizar la operación
A52: public | B52: cambiarNombreSede | C52: no static | D52: no final | E52: Permite al administrador cambiar el nombre de la sede | F52: id | G52: Otro | H52: UUID | I52: Por referencia | J52: no final | K52: Corresponde al identificador de la sede | L52: Otro | M52: Sede | N52: Informar con un mensaje que no existe una sede con el identificador enviado y por lo tanto no se puede realizar la operación; Generar una excepción indicándole al administrador cuáles datos de la sede no cumplen con las reglas definidas; Generar una excepción indicándole al administrador que ya existe una sede con ese nombre en la barbería
F53: nombre | G53: String | I53: Por valor | J53: no final | K53: Representa el nombre con el que se identifica esta sede dentro de la barbería a la que pertenece
A54: public | B54: cambiarDireccionSede | C54: no static | D54: no final | E54: Permite al administrador cambiar la dirección de la sede | F54: id | G54: Otro | H54: UUID | I54: Por referencia | J54: no final | K54: Corresponde al identificador de la sede | L54: Otro | M54: Sede | N54: Informar con un mensaje que no existe una sede con el identificador enviado y por lo tanto no se puede realizar la operación; Generar una excepción indicándole al administrador cuáles datos de la sede no cumplen con las reglas definidas
F55: direccion | G55: String | I55: Por valor | J55: no final | K55: Representa la dirección física en la que está ubicada esta sede
A56: public | B56: darDeBajaSede | C56: no static | D56: no final | E56: Permite al administrador dar de baja una sede para que deje de operar | F56: id | G56: Otro | H56: UUID | I56: Por referencia | J56: no final | K56: Corresponde al identificador de la sede que se va a dar de baja | L56: void | N56: Informar con un mensaje que no existe una sede con el identificador enviado y por lo tanto no se puede realizar la operación; Generar una excepción indicándole al administrador que la sede todavía tiene barberos trabajando en ella; Generar una excepción indicándole al administrador que la sede tiene citas futuras agendadas

Sheet Barbero
A1: <-Volver al inicio
A2: =Clases!$A$1 -> Clase | B2: =Clases!A12 -> Barbero
A3: =Clases!$B$1 -> Estereotipo | B3: =Clases!B12 -> class
A4: =Clases!$C$1 -> Desripción | B4: =Clases!C12 -> Representa a un trabajador de la barbería que atiende clientes según los servicios que sabe realizar, organiza su propio horario y tiene su agenda personal para atender todas las citas que valla teniendo.
A5: Modificador acceso: | B5: public
A6: Tipo clase: | B6: no final
A7: Relaciones
A8: Relación | B8: Tipo relación | E8: Estructura
A9: Necesita de | B9: Asociación | E9: =PrefijoCelular!B2 -> PrefijoCelular
A10: Necesita de | B10: Agregación | E10: =Sede!B2 -> Sede
A11: Es usada por | B11: Composición | E11: =BarberoServicio!B2 -> BarberoServicio
A12: Es usada por | B12: Composición | E12: =Bloqueo!B2 -> Bloqueo
A13: Es usada por | B13: Composición | E13: =HorarioBarbero!B2 -> HorarioBarbero
A14: Atributos
A15: Modificador de aceso | B15: Nombre | C15: Tipo de dato | E15: Tipo modificación atributo | F15: Tipo acceso atributo | G15: Valor por defecto | J15: Descripción atributo
C16: Tipo de dato | D16: ¿Cuál?
A17: private | B17: id | C17: Otro | D17: UUID | E17: no final | F17: no static | G17: new UUID(0L, 0L) | J17: Representa un identificador que hará unico cada objeto de dominio de este tipo, no se puede repetir
A18: private | B18: primerNombre | C18: String | E18: no final | F18: no static | G18: "" | J18: Representa el primer nombre del barbero que trabaja en barbería
A19: private | B19: segundoNombre | C19: String | E19: no final | F19: no static | G19: "" | J19: Representa el segundo nombre del barbero que trabaja en barbería
A20: private | B20: primerApellido | C20: String | E20: no final | F20: no static | G20: "" | J20: Representa el primer apellido del barbero que trabaja en la barbería
A21: private | B21: segundoApellido | C21: String | E21: no final | F21: no static | G21: "" | J21: Representa el segundo apellido del barbero que trabaja en la barbería
A22: private | B22: prefijo | C22: Otro | D22: PrefijoCelular | E22: no final | F22: no static | G22: new PrefijoCelular() | J22: Representa cual es el prefijo del numero de celular del barbero
A23: private | B23: celular | C23: String | E23: no final | F23: no static | G23: "0" | J23: Representa el número de celular del barbero, es el dato que el cliente necesita en caso de que tenga que contactarse con el
A24: private | B24: elNumeroCelularEsCorrecto | C24: boolean/Boolean | E24: no final | F24: no static | G24: false | J24: Representa si el numero que ingreso el cliente es correcto o no
A25: private | B25: vigente | C25: boolean/Boolean | E25: no final | F25: no static | G25: true | J25: Representa si el barbero sigue o no trabajando en la barberia
A26: private | B26: sedeDeTrabajo | C26: Otro | D26: Sede | E26: no final | F26: no static | G26: new Sede() | J26: Representa cual es la sede y la barberia donde trabaja el barbero
A27: Constructores
A28: Modificador de aceso | B28: Nombre | C28: Tipo constructor | D28: Descripción | E28: Parámetros | M28: Excepciones
E29: Nombre | F29: Tipo de dato | G29: ¿Cuál? | H29: Tipo parámetro | I29: Tipo modificación atributo | J29: Descripción
A30: public | B30: =B2 -> Barbero | C30: Defecto | D30: Constructor por defecto que crea un objeto Barbero con todos sus atributos en su valor por defecto
A31: public | B31: =B2 -> Barbero | C31: Parametrizado | D31: Constructor parametrizado que crea un objeto Barbero asignando el valor recibido a cada uno de sus atributos | E31: valorId | F31: Otro | G31: UUID | H31: Por referencia | I31: no final | J31: Valor que se asigna al atributo id
E32: valorPrimerNombre | F32: String | H32: Por valor | I32: no final | J32: Valor que se asigna al atributo primerNombre
E33: valorSegundoNombre | F33: String | H33: Por valor | I33: no final | J33: Valor que se asigna al atributo segundoNombre
E34: valorPrimerApellido | F34: String | H34: Por valor | I34: no final | J34: Valor que se asigna al atributo primerApellido
E35: valorSegundoApellido | F35: String | H35: Por valor | I35: no final | J35: Valor que se asigna al atributo segundoApellido
E36: valorPrefijo | F36: Otro | G36: PrefijoCelular | H36: Por referencia | I36: no final | J36: Valor que se asigna al atributo prefijo
E37: valorCelular | F37: String | H37: Por valor | I37: no final | J37: Valor que se asigna al atributo celular
E38: valorElNumeroCelularEsCorrecto | F38: boolean/Boolean | H38: Por valor | I38: no final | J38: Valor que se asigna al atributo elNumeroCelularEsCorrecto
E39: valorVigente | F39: boolean/Boolean | H39: Por valor | I39: no final | J39: Valor que se asigna al atributo vigente
E40: valorSedeDeTrabajo | F40: Otro | G40: Sede | H40: Por referencia | I40: no final | J40: Valor que se asigna al atributo sedeDeTrabajo
A41: Métodos accesores
A42: Modificador de aceso | B42: Nombre | C42: Tipo método accesor | D42: Tipo modificación método | E42: Descripción | F42: Parámetros | L42: Tipo dato de retorno | N42: Excepciones
F43: Nombre | G43: Tipo de dato | H43: ¿Cuál? | I43: Tipo parámetro | J43: Tipo modificación atributo | K43: Descripción | L43: Tipo de dato | M43: ¿Cuál?
A44: public | B44: getId | C44: getter | D44: no final | E44: Método encargado de obtener el valor del atributo id | L44: Otro | M44: UUID
A45: public | B45: setId | C45: setter | D45: no final | E45: Método encargado de colocar el valor al atributo id | F45: valorId | G45: Otro | H45: UUID | I45: Por referencia | J45: no final | K45: Nuevo valor del atributo id | L45: void
A46: public | B46: getPrimerNombre | C46: getter | D46: no final | E46: Método encargado de obtener el valor del atributo primerNombre | L46: String
A47: public | B47: setPrimerNombre | C47: setter | D47: no final | E47: Método encargado de colocar el valor al atributo primerNombre | F47: valorPrimerNombre | G47: String | I47: Por valor | J47: no final | K47: Nuevo valor del atributo primerNombre | L47: void
A48: public | B48: getSegundoNombre | C48: getter | D48: no final | E48: Método encargado de obtener el valor del atributo segundoNombre | L48: String
A49: public | B49: setSegundoNombre | C49: setter | D49: no final | E49: Método encargado de colocar el valor al atributo segundoNombre | F49: valorSegundoNombre | G49: String | I49: Por valor | J49: no final | K49: Nuevo valor del atributo segundoNombre | L49: void
A50: public | B50: getPrimerApellido | C50: getter | D50: no final | E50: Método encargado de obtener el valor del atributo primerApellido | L50: String
A51: public | B51: setPrimerApellido | C51: setter | D51: no final | E51: Método encargado de colocar el valor al atributo primerApellido | F51: valorPrimerApellido | G51: String | I51: Por valor | J51: no final | K51: Nuevo valor del atributo primerApellido | L51: void
A52: public | B52: getSegundoApellido | C52: getter | D52: no final | E52: Método encargado de obtener el valor del atributo segundoApellido | L52: String
A53: public | B53: setSegundoApellido | C53: setter | D53: no final | E53: Método encargado de colocar el valor al atributo segundoApellido | F53: valorSegundoApellido | G53: String | I53: Por valor | J53: no final | K53: Nuevo valor del atributo segundoApellido | L53: void
A54: public | B54: getPrefijo | C54: getter | D54: no final | E54: Método encargado de obtener el valor del atributo prefijo | L54: Otro | M54: PrefijoCelular
A55: public | B55: setPrefijo | C55: setter | D55: no final | E55: Método encargado de colocar el valor al atributo prefijo | F55: valorPrefijo | G55: Otro | H55: PrefijoCelular | I55: Por referencia | J55: no final | K55: Nuevo valor del atributo prefijo | L55: void
A56: public | B56: getCelular | C56: getter | D56: no final | E56: Método encargado de obtener el valor del atributo celular | L56: String
A57: public | B57: setCelular | C57: setter | D57: no final | E57: Método encargado de colocar el valor al atributo celular | F57: valorCelular | G57: String | I57: Por valor | J57: no final | K57: Nuevo valor del atributo celular | L57: void
A58: public | B58: getElNumeroCelularEsCorrecto | C58: getter | D58: no final | E58: Método encargado de obtener el valor del atributo elNumeroCelularEsCorrecto | L58: boolean/Boolean
A59: public | B59: setElNumeroCelularEsCorrecto | C59: setter | D59: no final | E59: Método encargado de colocar el valor al atributo elNumeroCelularEsCorrecto | F59: valorElNumeroCelularEsCorrecto | G59: boolean/Boolean | I59: Por valor | J59: no final | K59: Nuevo valor del atributo elNumeroCelularEsCorrecto | L59: void
A60: public | B60: getVigente | C60: getter | D60: no final | E60: Método encargado de obtener el valor del atributo vigente | L60: boolean/Boolean
A61: public | B61: setVigente | C61: setter | D61: no final | E61: Método encargado de colocar el valor al atributo vigente | F61: valorVigente | G61: boolean/Boolean | I61: Por valor | J61: no final | K61: Nuevo valor del atributo vigente | L61: void
A62: public | B62: getSedeDeTrabajo | C62: getter | D62: no final | E62: Método encargado de obtener el valor del atributo sedeDeTrabajo | L62: Otro | M62: Sede
A63: public | B63: setSedeDeTrabajo | C63: setter | D63: no final | E63: Método encargado de colocar el valor al atributo sedeDeTrabajo | F63: valorSedeDeTrabajo | G63: Otro | H63: Sede | I63: Por referencia | J63: no final | K63: Nuevo valor del atributo sedeDeTrabajo | L63: void
A64: Métodos
A65: Modificador de aceso | B65: Nombre | C65: Tipo acceso método | D65: Tipo modificación método | E65: Descripción | F65: Parámetros | L65: Tipo dato de retorno | N65: Excepciones
F66: Nombre | G66: Tipo de dato | H66: ¿Cuál? | I66: Tipo parámetro | J66: Tipo modificación atributo | K66: Descripción | L66: Tipo de dato | M66: ¿Cuál?
A67: public | B67: registrarBarbero | C67: no static | D67: no final | E67: Comando que permite el ingreso de un nuevo barbero a trabajar en la barbería | F67: primerNombre | G67: String | I67: Por valor | J67: no final | K67: Representa el primer nombre del barbero que trabaja en barbería | L67: Otro | M67: Barbero | N67: Generar una excepción indicándole al barbero que los datos ingresados no son válidos; Generar una excepción indicándole al usuario que ya existe otro barbero registrado con ese prefijo y número de celular; Generar una excepción indicándole al barbero que ponga si en elNumeroCelularEsCorrecto
F68: segundoNombre | G68: String | I68: Por valor | J68: no final | K68: Representa el segundo nombre del barbero que trabaja en barbería
F69: primerApellido | G69: String | I69: Por valor | J69: no final | K69: Representa el primer apellido del barbero que trabaja en la barbería
F70: segundoApellido | G70: String | I70: Por valor | J70: no final | K70: Representa el segundo apellido del barbero que trabaja en la barbería
F71: prefijoCelular | G71: Otro | H71: PrefijoCelular | I71: Por referencia | J71: no final | K71: Prefijo del número de celular
F72: celular | G72: String | I72: Por valor | J72: no final | K72: Representa el número de celular del barbero, es el dato que el cliente necesita en caso de que tenga que contactarse con el
F73: elNumeroCelularEsCorrecto | G73: boolean/Boolean | I73: Por valor | J73: no final | K73: Representa si el numero que ingreso el cliente es correcto o no
F74: sedeDeTrabajo | G74: Otro | H74: Sede | I74: Por referencia | J74: no final | K74: Representa cual es la sede y la barberia donde trabaja el barbero
A75: public | B75: editarContactoBarbero | C75: no static | D75: no final | E75: Permite al barbero actualizar su número de celular y su prefijo | F75: id | G75: Otro | H75: UUID | I75: Por referencia | J75: no final | K75: Corresponde al identificador del barbero que va a editar su contacto | L75: Otro | M75: Barbero | N75: Informar con un mensaje que no existe un barbero con el identificador enviado y por lo tanto no es posible editar el contacto del barbero; Generar una excepción indicándole al usuario cuáles datos de contacto del barbero no cumplen con las reglas definidas
F76: prefijoCelular | G76: Otro | H76: PrefijoCelular | I76: Por referencia | J76: no final | K76: Prefijo del número de celular
F77: celular | G77: String | I77: Por valor | J77: no final | K77: Representa el número de celular del barbero, es el dato que el cliente necesita en caso de que tenga que contactarse con el
A78: public | B78: consultarDatosBarbero | C78: no static | D78: no final | E78: Permite a un cliente ver los datos públicos de un barbero, como sus nombres, apellidos y su contacto | F78: id | G78: Otro | H78: UUID | I78: Por referencia | J78: no final | K78: Corresponde al identificador del barbero que se va a consultar | L78: Otro | M78: Barbero | N78: Informar con un mensaje que no existe un barbero con el identificador enviado y por lo tanto no es posible consultar los datos
A79: public | B79: desactivarBarbero | C79: no static | D79: no final | E79: Permite desactivar a un barbero para que ya no pueda recibir nuevas citas | F79: id | G79: Otro | H79: UUID | I79: Por referencia | J79: no final | K79: Corresponde al identificador del barbero que va a dejar de trabajar | L79: void | N79: Generar una excepción indicándole al usuario que el barbero no puede dejar de trabajar porque todavía tiene citas futuras pendientes; Informar con un mensaje que no existe un barbero con el identificador enviado y por lo tanto no es posible desactivar el barbero
A80: public | B80: reactivarBarbero | C80: no static | D80: no final | E80: Permite activar a un barbero para que ya pueda volver a recibir citas de sus clientes | F80: id | G80: Otro | H80: UUID | I80: Por referencia | J80: no final | K80: Corresponde al identificador del barbero que va a dejar de trabajar | L80: void | N80: Informar con un mensaje que no existe un barbero con el identificador enviado y por lo tanto no es posible reactivar el barbero
A81: public | B81: cambiarSedeDeTrabajoBarbero | C81: no static | D81: no final | E81: Permite al barbero cambiar la sede en la que trabaja, que puede pertenecer a otra barbería, sin modificar sus citas pasadas | F81: id | G81: Otro | H81: UUID | I81: Por referencia | J81: no final | K81: Corresponde al identificador del barbero que va a cambiar de sede | L81: Otro | M81: Barbero | N81: Informar con un mensaje que no existe un barbero con el identificador enviado; Generar una excepción indicándole al barbero que no puede cambiar de sede o de barbería porque tiene citas futuras agendadas
F82: sedeDeTrabajo | G82: Otro | H82: Sede | I82: Por referencia | J82: no final | K82: Representa cual es la sede y la barberia donde trabaja el barbero
A83: public | B83: consultarServiciosSedeBarbero | C83: no static | D83: no final | E83: Permite al barbero consultar únicamente los servicios disponibles de la sede en la que trabaja | F83: id | G83: Otro | H83: UUID | I83: Por referencia | J83: no final | K83: Corresponde al identificador del barbero que consulta los servicios | L83: Otro | M83: List<Servicio> | N83: Informar con un mensaje que no existe un barbero con el identificador enviado y por lo tanto no se puede realizar la operación; Generar una excepción indicándole al barbero que solo puede consultar los servicios de su sede de trabajo

Sheet HorarioBarberia
A1: <-Volver al inicio
A2: =Clases!$A$1 -> Clase | B2: =Clases!A13 -> HorarioBarberia
A3: =Clases!$B$1 -> Estereotipo | B3: =Clases!B13 -> class
A4: =Clases!$C$1 -> Desripción | B4: =Clases!C13 -> Representa, día por día, a qué hora abre y cierra el negocio; es el límite dentro del cual debe caber el horario de cualquier barbero.
A5: Modificador acceso: | B5: public
A6: Tipo clase: | B6: no final
A7: Relaciones
A8: Relación | B8: Tipo relación | E8: Estructura
A9: Necesita de | B9: Composición | E9: =Sede!B2 -> Sede
A10: Necesita de | B10: Asociación | E10: =DiaSemana!B2 -> DiaSemana
A11: Es usada por | B11: Composición | E11: =HorarioBarbero!B2 -> HorarioBarbero
A12: Atributos
A13: Modificador de aceso | B13: Nombre | C13: Tipo de dato | E13: Tipo modificación atributo | F13: Tipo acceso atributo | G13: Valor por defecto | J13: Descripción atributo
C14: Tipo de dato | D14: ¿Cuál?
A15: private | B15: id | C15: Otro | D15: UUID | E15: no final | F15: no static | G15: new UUID(0L, 0L) | J15: Representa un identificador que hará unico cada objeto de dominio de este tipo, no se puede repetir
A16: private | B16: sedeDeLaBarberia | C16: Otro | D16: Sede | E16: no final | F16: no static | G16: new Sede() | J16: Representa a cual barberia y sede pertenece el horario de apertura y cierre
A17: private | B17: diaDeLaSemana | C17: Otro | D17: DiaSemana | E17: no final | F17: no static | G17: new DiaSemana() | J17: Representa el día de la semana en el que la barberia abre
A18: private | B18: horaApertura | C18: Otro | D18: LocalTime | E18: no final | F18: no static | G18: LocalTime.of(0, 0) | J18: Representa la hora a la que abre la barbería
A19: private | B19: horaCierre | C19: Otro | D19: LocalTime | E19: no final | F19: no static | G19: LocalTime.of(0, 0) | J19: Representa la hora a la que cierra la barbería
A20: private | B20: fechaCreacion | C20: Otro | D20: LocalDate | E20: no final | F20: no static | G20: LocalDate.of(1000, 1, 1) | J20: Representa la fecha en el que el administrador definio el horario de la barberia. Es un dato calculado que toma la fecha del sistema en ese momento
A21: private | B21: fechaDesactivacion | C21: Otro | D21: LocalDate | E21: no final | F21: no static | G21: LocalDate.of(1000, 1, 1) | J21: Representa la fecha en la que este horario dejó de estar vigente. Es un dato calculado que toma la fecha del sistema en ese momento
A22: private | B22: vigente | C22: boolean/Boolean | E22: no final | F22: no static | G22: true | J22: Representa si este horario lo sigue o no vigente en la barberia. Una vez que el administrador desactive el horario de la barberia, no se puede volver a cambiar
A23: Constructores
A24: Modificador de aceso | B24: Nombre | C24: Tipo constructor | D24: Descripción | E24: Parámetros | M24: Excepciones
E25: Nombre | F25: Tipo de dato | G25: ¿Cuál? | H25: Tipo parámetro | I25: Tipo modificación atributo | J25: Descripción
A26: public | B26: =B2 -> HorarioBarberia | C26: Defecto | D26: Constructor por defecto que crea un objeto HorarioBarberia con todos sus atributos en su valor por defecto
A27: public | B27: =B2 -> HorarioBarberia | C27: Parametrizado | D27: Constructor parametrizado que crea un objeto HorarioBarberia asignando el valor recibido a cada uno de sus atributos | E27: valorId | F27: Otro | G27: UUID | H27: Por referencia | I27: no final | J27: Valor que se asigna al atributo id
E28: valorSedeDeLaBarberia | F28: Otro | G28: Sede | H28: Por referencia | I28: no final | J28: Valor que se asigna al atributo sedeDeLaBarberia
E29: valorDiaDeLaSemana | F29: Otro | G29: DiaSemana | H29: Por referencia | I29: no final | J29: Valor que se asigna al atributo diaDeLaSemana
E30: valorHoraApertura | F30: Otro | G30: LocalTime | H30: Por referencia | I30: no final | J30: Valor que se asigna al atributo horaApertura
E31: valorHoraCierre | F31: Otro | G31: LocalTime | H31: Por referencia | I31: no final | J31: Valor que se asigna al atributo horaCierre
E32: valorFechaCreacion | F32: Otro | G32: LocalDate | H32: Por referencia | I32: no final | J32: Valor que se asigna al atributo fechaCreacion
E33: valorFechaDesactivacion | F33: Otro | G33: LocalDate | H33: Por referencia | I33: no final | J33: Valor que se asigna al atributo fechaDesactivacion
E34: valorVigente | F34: boolean/Boolean | H34: Por valor | I34: no final | J34: Valor que se asigna al atributo vigente
A35: Métodos accesores
A36: Modificador de aceso | B36: Nombre | C36: Tipo método accesor | D36: Tipo modificación método | E36: Descripción | F36: Parámetros | L36: Tipo dato de retorno | N36: Excepciones
F37: Nombre | G37: Tipo de dato | H37: ¿Cuál? | I37: Tipo parámetro | J37: Tipo modificación atributo | K37: Descripción | L37: Tipo de dato | M37: ¿Cuál?
A38: public | B38: getId | C38: getter | D38: no final | E38: Método encargado de obtener el valor del atributo id | L38: Otro | M38: UUID
A39: public | B39: setId | C39: setter | D39: no final | E39: Método encargado de colocar el valor al atributo id | F39: valorId | G39: Otro | H39: UUID | I39: Por referencia | J39: no final | K39: Nuevo valor del atributo id | L39: void
A40: public | B40: getSedeDeLaBarberia | C40: getter | D40: no final | E40: Método encargado de obtener el valor del atributo sedeDeLaBarberia | L40: Otro | M40: Sede
A41: public | B41: setSedeDeLaBarberia | C41: setter | D41: no final | E41: Método encargado de colocar el valor al atributo sedeDeLaBarberia | F41: valorSedeDeLaBarberia | G41: Otro | H41: Sede | I41: Por referencia | J41: no final | K41: Nuevo valor del atributo sedeDeLaBarberia | L41: void
A42: public | B42: getDiaDeLaSemana | C42: getter | D42: no final | E42: Método encargado de obtener el valor del atributo diaDeLaSemana | L42: Otro | M42: DiaSemana
A43: public | B43: setDiaDeLaSemana | C43: setter | D43: no final | E43: Método encargado de colocar el valor al atributo diaDeLaSemana | F43: valorDiaDeLaSemana | G43: Otro | H43: DiaSemana | I43: Por referencia | J43: no final | K43: Nuevo valor del atributo diaDeLaSemana | L43: void
A44: public | B44: getHoraApertura | C44: getter | D44: no final | E44: Método encargado de obtener el valor del atributo horaApertura | L44: Otro | M44: LocalTime
A45: public | B45: setHoraApertura | C45: setter | D45: no final | E45: Método encargado de colocar el valor al atributo horaApertura | F45: valorHoraApertura | G45: Otro | H45: LocalTime | I45: Por referencia | J45: no final | K45: Nuevo valor del atributo horaApertura | L45: void
A46: public | B46: getHoraCierre | C46: getter | D46: no final | E46: Método encargado de obtener el valor del atributo horaCierre | L46: Otro | M46: LocalTime
A47: public | B47: setHoraCierre | C47: setter | D47: no final | E47: Método encargado de colocar el valor al atributo horaCierre | F47: valorHoraCierre | G47: Otro | H47: LocalTime | I47: Por referencia | J47: no final | K47: Nuevo valor del atributo horaCierre | L47: void
A48: public | B48: getFechaCreacion | C48: getter | D48: no final | E48: Método encargado de obtener el valor del atributo fechaCreacion | L48: Otro | M48: LocalDate
A49: public | B49: setFechaCreacion | C49: setter | D49: no final | E49: Método encargado de colocar el valor al atributo fechaCreacion | F49: valorFechaCreacion | G49: Otro | H49: LocalDate | I49: Por referencia | J49: no final | K49: Nuevo valor del atributo fechaCreacion | L49: void
A50: public | B50: getFechaDesactivacion | C50: getter | D50: no final | E50: Método encargado de obtener el valor del atributo fechaDesactivacion | L50: Otro | M50: LocalDate
A51: public | B51: setFechaDesactivacion | C51: setter | D51: no final | E51: Método encargado de colocar el valor al atributo fechaDesactivacion | F51: valorFechaDesactivacion | G51: Otro | H51: LocalDate | I51: Por referencia | J51: no final | K51: Nuevo valor del atributo fechaDesactivacion | L51: void
A52: public | B52: getVigente | C52: getter | D52: no final | E52: Método encargado de obtener el valor del atributo vigente | L52: boolean/Boolean
A53: public | B53: setVigente | C53: setter | D53: no final | E53: Método encargado de colocar el valor al atributo vigente | F53: valorVigente | G53: boolean/Boolean | I53: Por valor | J53: no final | K53: Nuevo valor del atributo vigente | L53: void
A54: Métodos
A55: Modificador de aceso | B55: Nombre | C55: Tipo acceso método | D55: Tipo modificación método | E55: Descripción | F55: Parámetros | L55: Tipo dato de retorno | N55: Excepciones
F56: Nombre | G56: Tipo de dato | H56: ¿Cuál? | I56: Tipo parámetro | J56: Tipo modificación atributo | K56: Descripción | L56: Tipo de dato | M56: ¿Cuál?
A57: public | B57: definirHorarioBarberia | C57: no static | D57: no final | E57: Comando que permite registrar la hora de apertura y cierre de la barbería para un día de la semana | F57: sedeDeLaBarberia | G57: Otro | H57: Sede | I57: Por referencia | J57: no final | K57: Representa a cual barberia y sede pertenece el horario de apertura y cierre | L57: Otro | M57: HorarioBarberia | N57: Generar una excepción indicándole al administrador que los datos no cumplen con las reglas definidas; Generar una excepción indicándole al administrador que ya existe un horario vigente para ese día que se cruza con las horas indicadas; Generar una excepción indicandole al administrador que la hora de cierre debe de ser mayor a la hora de apertura
F58: diaDeLaSemana | G58: Otro | H58: DiaSemana | I58: Por referencia | J58: no final | K58: Representa el día de la semana en el que la barberia abre
F59: horaApertura | G59: Otro | H59: LocalTime | I59: Por referencia | J59: no final | K59: Representa la hora a la que abre la barbería
F60: horaCierre | G60: Otro | H60: LocalTime | I60: Por referencia | J60: no final | K60: Representa la hora a la que cierra la barbería
A61: public | B61: consultarHorariosBarberia | C61: no static | D61: no final | E61: Permite al administrador consultar los horarios de apertura y cierre definidos para cada día de la semana | L61: Otro | M61: List<HorarioBarberia> | N61: No aplica
A62: public | B62: desactivarHorarioBarberia | C62: no static | D62: no final | E62: Permite desactivar el horario en el que la barberia ya no abrira | F62: id | G62: Otro | H62: UUID | I62: Por referencia | J62: no final | K62: Corresponde al identificador del horario de la barbería que se va a desactivar | L62: void | N62: Si alguno de los horarios de barbero no pudo ser desactivado, revertir toda la operación e informar el error; Si alguna de las citas futuras no pudo ser cancelada, revertir toda la operación e informar el error; Informar con un mensaje que no existe un horario de la barbería con el identificador enviado y por lo tanto no es posible llevar a cabo la operación; Informar con un mensaje que ese horario de la barbería ya se encuentra desactivado y por lo tanto no puede volver a desactivarse

Sheet Servicio
A1: <-Volver al inicio
A2: =Clases!$A$1 -> Clase | B2: =Clases!A14 -> Servicio
A3: =Clases!$B$1 -> Estereotipo | B3: =Clases!B14 -> class
A4: =Clases!$C$1 -> Desripción | B4: =Clases!C14 -> Representa cada tipo de corte o arreglo que ofrece la barbería, definido por el administrador, para que luego cada barbero decida cuáles sabe hacer.
A5: Modificador acceso: | B5: public
A6: Tipo clase: | B6: no final
A7: Relaciones
A8: Relación | B8: Tipo relación | E8: Estructura
A9: Necesita de | B9: Asociación | E9: =Sede!B2 -> Sede
A10: Es usada por | B10: Composición | E10: =BarberoServicio!B2 -> BarberoServicio
A11: Atributos
A12: Modificador de aceso | B12: Nombre | C12: Tipo de dato | E12: Tipo modificación atributo | F12: Tipo acceso atributo | G12: Valor por defecto | J12: Descripción atributo
C13: Tipo de dato | D13: ¿Cuál?
A14: private | B14: id | C14: Otro | D14: UUID | E14: no final | F14: no static | G14: new UUID(0L, 0L) | J14: Representa un identificador que hará unico cada objeto de dominio de este tipo, no se puede repetir
A15: private | B15: sedeDeLaBarberia | C15: Otro | D15: Sede | E15: no final | F15: no static | G15: new Sede() | J15: Representa a cual barberia y sede va a pertenecer el servicio
A16: private | B16: nombre | C16: String | E16: no final | F16: no static | G16: "" | J16: Representa el nombre del servicio que va estar en la barberia, para que el barbero elija los servicios que el sabe hacer
A17: private | B17: descripcion | C17: String | E17: no final | F17: no static | G17: "" | J17: Representa una descripcion de que va a hacer cada servicio en la barberia, para que el barbero sepa que hace el servicio
A18: private | B18: precio | C18: int/Integer | E18: no final | F18: no static | G18: 0 | J18: Representa cuanto va a valer el servicio en pesos colombianos
A19: private | B19: disponible | C19: boolean/Boolean | E19: no final | F19: no static | G19: true | J19: Representa si el servicio sigue o no disponible en la barberia
A20: Constructores
A21: Modificador de aceso | B21: Nombre | C21: Tipo constructor | D21: Descripción | E21: Parámetros | M21: Excepciones
E22: Nombre | F22: Tipo de dato | G22: ¿Cuál? | H22: Tipo parámetro | I22: Tipo modificación atributo | J22: Descripción
A23: public | B23: =B2 -> Servicio | C23: Defecto | D23: Constructor por defecto que crea un objeto Servicio con todos sus atributos en su valor por defecto
A24: public | B24: =B2 -> Servicio | C24: Parametrizado | D24: Constructor parametrizado que crea un objeto Servicio asignando el valor recibido a cada uno de sus atributos | E24: valorId | F24: Otro | G24: UUID | H24: Por referencia | I24: no final | J24: Valor que se asigna al atributo id
E25: valorSedeDeLaBarberia | F25: Otro | G25: Sede | H25: Por referencia | I25: no final | J25: Valor que se asigna al atributo sedeDeLaBarberia
E26: valorNombre | F26: String | H26: Por valor | I26: no final | J26: Valor que se asigna al atributo nombre
E27: valorDescripcion | F27: String | H27: Por valor | I27: no final | J27: Valor que se asigna al atributo descripcion
E28: valorPrecio | F28: int/Integer | H28: Por valor | I28: no final | J28: Valor que se asigna al atributo precio
E29: valorDisponible | F29: boolean/Boolean | H29: Por valor | I29: no final | J29: Valor que se asigna al atributo disponible
A30: Métodos accesores
A31: Modificador de aceso | B31: Nombre | C31: Tipo método accesor | D31: Tipo modificación método | E31: Descripción | F31: Parámetros | L31: Tipo dato de retorno | N31: Excepciones
F32: Nombre | G32: Tipo de dato | H32: ¿Cuál? | I32: Tipo parámetro | J32: Tipo modificación atributo | K32: Descripción | L32: Tipo de dato | M32: ¿Cuál?
A33: public | B33: getId | C33: getter | D33: no final | E33: Método encargado de obtener el valor del atributo id | L33: Otro | M33: UUID
A34: public | B34: setId | C34: setter | D34: no final | E34: Método encargado de colocar el valor al atributo id | F34: valorId | G34: Otro | H34: UUID | I34: Por referencia | J34: no final | K34: Nuevo valor del atributo id | L34: void
A35: public | B35: getSedeDeLaBarberia | C35: getter | D35: no final | E35: Método encargado de obtener el valor del atributo sedeDeLaBarberia | L35: Otro | M35: Sede
A36: public | B36: setSedeDeLaBarberia | C36: setter | D36: no final | E36: Método encargado de colocar el valor al atributo sedeDeLaBarberia | F36: valorSedeDeLaBarberia | G36: Otro | H36: Sede | I36: Por referencia | J36: no final | K36: Nuevo valor del atributo sedeDeLaBarberia | L36: void
A37: public | B37: getNombre | C37: getter | D37: no final | E37: Método encargado de obtener el valor del atributo nombre | L37: String
A38: public | B38: setNombre | C38: setter | D38: no final | E38: Método encargado de colocar el valor al atributo nombre | F38: valorNombre | G38: String | I38: Por valor | J38: no final | K38: Nuevo valor del atributo nombre | L38: void
A39: public | B39: getDescripcion | C39: getter | D39: no final | E39: Método encargado de obtener el valor del atributo descripcion | L39: String
A40: public | B40: setDescripcion | C40: setter | D40: no final | E40: Método encargado de colocar el valor al atributo descripcion | F40: valorDescripcion | G40: String | I40: Por valor | J40: no final | K40: Nuevo valor del atributo descripcion | L40: void
A41: public | B41: getPrecio | C41: getter | D41: no final | E41: Método encargado de obtener el valor del atributo precio | L41: int/Integer
A42: public | B42: setPrecio | C42: setter | D42: no final | E42: Método encargado de colocar el valor al atributo precio | F42: valorPrecio | G42: int/Integer | I42: Por valor | J42: no final | K42: Nuevo valor del atributo precio | L42: void
A43: public | B43: getDisponible | C43: getter | D43: no final | E43: Método encargado de obtener el valor del atributo disponible | L43: boolean/Boolean
A44: public | B44: setDisponible | C44: setter | D44: no final | E44: Método encargado de colocar el valor al atributo disponible | F44: valorDisponible | G44: boolean/Boolean | I44: Por valor | J44: no final | K44: Nuevo valor del atributo disponible | L44: void
A45: Métodos
A46: Modificador de aceso | B46: Nombre | C46: Tipo acceso método | D46: Tipo modificación método | E46: Descripción | F46: Parámetros | L46: Tipo dato de retorno | N46: Excepciones
F47: Nombre | G47: Tipo de dato | H47: ¿Cuál? | I47: Tipo parámetro | J47: Tipo modificación atributo | K47: Descripción | L47: Tipo de dato | M47: ¿Cuál?
A48: public | B48: ofrecerServicioNuevo | C48: no static | D48: no final | E48: Comando que permite registrar un nuevo tipo de servicio que la barbería pondrá a disposición de los barberos | F48: sedeDeLaBarberia | G48: Otro | H48: Sede | I48: Por referencia | J48: no final | K48: Representa a cual barberia y sede va a pertenecer el servicio | L48: Otro | M48: Servicio | N48: Generar una excepción indicándole al usuario cuáles datos del servicio no cumplen con las reglas definidas; Generar una excepción indicándole al usuario que ya existe un servicio registrado con ese mismo nombre en la barbería
F49: nombre | G49: String | I49: Por valor | J49: no final | K49: Representa el nombre del servicio que va estar en la barberia, para que el barbero elija los servicios que el sabe hacer
F50: descripcion | G50: String | I50: Por valor | J50: no final | K50: Representa una descripcion de que va a hacer cada servicio en la barberia, para que el barbero sepa que hace el servicio
F51: precio | G51: int/Integer | I51: Por valor | J51: no final | K51: Representa cuanto va a valer el servicio en pesos colombianos
A52: public | B52: editarServicio | C52: no static | D52: no final | E52: Permite modificar todos los atibutos de un servicio, que son el nombre, la descripción y el precio | F52: id | G52: Otro | H52: UUID | I52: Por referencia | J52: no final | K52: Corresponde al identificador del servicio que se va a editar | L52: Otro | M52: Servicio | N52: Informar con un mensaje que no existe un servicio con el identificador enviado y por lo tanto no es posible modificar el servicio; Generar una excepción indicándole al usuario cuáles datos del servicio no cumplen con las reglas definidas; Generar una excepción indicándole al usuario que ya existe un servicio registrado con ese mismo nombre en la barbería
F53: sedeDeLaBarberia | G53: Otro | H53: Sede | I53: Por referencia | J53: no final | K53: Representa a cual barberia y sede va a pertenecer el servicio
F54: nombre | G54: String | I54: Por valor | J54: no final | K54: Representa el nombre del servicio que va estar en la barberia, para que el barbero elija los servicios que el sabe hacer
F55: descripcion | G55: String | I55: Por valor | J55: no final | K55: Representa una descripcion de que va a hacer cada servicio en la barberia, para que el barbero sepa que hace el servicio
F56: precio | G56: int/Integer | I56: Por valor | J56: no final | K56: Representa cuanto va a valer el servicio en pesos colombianos
A57: public | B57: consultarServiciosDisponibles | C57: no static | D57: no final | E57: Permite consultar el catálogo de servicios que ofrece la barbería | F57: sedeDeLaBarberia | G57: Otro | H57: Sede | I57: Por referencia | J57: no final | K57: Representa a cual barberia y sede va a pertenecer el servicio (filtro) | L57: Otro | M57: List<Servicio> | N57: No aplica
A58: public | B58: retirarServicio | C58: no static | D58: no final | E58: Permite retirar un servicio de la sede para que deje de ofrecerse a nuevos clientes y cancelar sus citas futuras | F58: id | G58: Otro | H58: UUID | I58: Por referencia | J58: no final | K58: Corresponde al identificador del servicio que se va a retirar | L58: void | N58: Generar una excepción indicándole al usuario que el servicio no se puede retirar porque todavía lo ofrece al menos un barbero vigente; Informar con un mensaje que no existe un servicio con el identificador enviado y por lo tanto no es posible desactivar el servicio; Generar una excepción indicándole al usuario que el servicio ya se encuentra retirado; Si alguna de las citas futuras no pudo ser cancelada, revertir el retiro del servicio
A59: public | B59: reactivarServicio | C59: no static | D59: no final | E59: Permite volver a ofrecer un servicio que había sido retirado, para que vuelva a estar disponible para nuevos clientes en la sede de la barbería | F59: id | G59: Otro | H59: UUID | I59: Por referencia | J59: no final | K59: Corresponde al identificador del servicio que se va a volver a ofrecer | L59: void | N59: Informar con un mensaje que no existe un servicio con el identificador enviado; Generar una excepción indicándole al usuario que el servicio ya se encuentra disponible
A60: public | B60: consultarServiciosNoDisponibles | C60: no static | D60: no final | E60: Permite consultar el catálogo de servicios retirados en una sede de una barbería | F60: sedeDeLaBarberia | G60: Otro | H60: Sede | I60: Por referencia | J60: no final | K60: Representa a cual barberia y sede va a pertenecer el servicio (filtro) | L60: Otro | M60: List<Servicio> | N60: No aplica

Sheet BarberoServicio
A1: <-Volver al inicio
A2: =Clases!$A$1 -> Clase | B2: =Clases!A15 -> BarberoServicio
A3: =Clases!$B$1 -> Estereotipo | B3: =Clases!B15 -> class
A4: =Clases!$C$1 -> Desripción | B4: =Clases!C15 -> Representa qué servicios sabe hacer cada barbero, cuánto se demora en realizarlos y cuánto tiempo extra usa de colchón, ya que no todos los barberos ofrecen los mismos servicios que están en la barbería.
A5: Modificador acceso: | B5: public
A6: Tipo clase: | B6: no final
A7: Relaciones
A8: Relación | B8: Tipo relación | E8: Estructura
A9: Necesita de | B9: Composición | E9: =Barbero!B2 -> Barbero
A10: Necesita de | B10: Composición | E10: =Servicio!B2 -> Servicio
A11: Es usada por | B11: Composición | E11: =CitaServicio!B2 -> CitaServicio
A12: Atributos
A13: Modificador de aceso | B13: Nombre | C13: Tipo de dato | E13: Tipo modificación atributo | F13: Tipo acceso atributo | G13: Valor por defecto | J13: Descripción atributo
C14: Tipo de dato | D14: ¿Cuál?
A15: private | B15: id | C15: Otro | D15: UUID | E15: no final | F15: no static | G15: new UUID(0L, 0L) | J15: Representa un identificador que hará unico cada objeto de dominio de este tipo, no se puede repetir
A16: private | B16: barbero | C16: Otro | D16: Barbero | E16: no final | F16: no static | G16: new Barbero() | J16: Representa el nombre y apellidos del barbero
A17: private | B17: servicio | C17: Otro | D17: Servicio | E17: no final | F17: no static | G17: new Servicio() | J17: Representa el nombre del servicio de la barberia
A18: private | B18: duracionEnHoras | C18: int/Integer | E18: no final | F18: no static | G18: 0 | J18: Representa la cantidad de horas que un barbero tarda en realizar un servicio, esta duracion el barbero debe de ser consiente de cuanto se demora en realizarlo
A19: private | B19: duracionEnMinutos | C19: int/Integer | E19: no final | F19: no static | G19: 0 | J19: Representa la cantidad de minutos que un barbero tarda en realizar un servicio, esta duracion el barbero debe de ser consiente de cuanto se demora en realizarlo
A20: private | B20: tiempoExtra | C20: int/Integer | E20: no final | F20: no static | G20: 0 | J20: Representa la cantidad de minutos que un barbero pone de tiempo extra en las citas de su agenda, cada barbero usa este tiempo porque hay ocaciones que la cita se puede demorar más de lo previsto. Este tiempo les ayuda a evitar que se les retrase la agenda
A21: private | B21: vigente | C21: boolean/Boolean | E21: no final | F21: no static | G21: true | J21: Representa si el barbero sigue o no presentando el servicio en la barbería
A22: Constructores
A23: Modificador de aceso | B23: Nombre | C23: Tipo constructor | D23: Descripción | E23: Parámetros | M23: Excepciones
E24: Nombre | F24: Tipo de dato | G24: ¿Cuál? | H24: Tipo parámetro | I24: Tipo modificación atributo | J24: Descripción
A25: public | B25: =B2 -> BarberoServicio | C25: Defecto | D25: Constructor por defecto que crea un objeto BarberoServicio con todos sus atributos en su valor por defecto
A26: public | B26: =B2 -> BarberoServicio | C26: Parametrizado | D26: Constructor parametrizado que crea un objeto BarberoServicio asignando el valor recibido a cada uno de sus atributos | E26: valorId | F26: Otro | G26: UUID | H26: Por referencia | I26: no final | J26: Valor que se asigna al atributo id
E27: valorBarbero | F27: Otro | G27: Barbero | H27: Por referencia | I27: no final | J27: Valor que se asigna al atributo barbero
E28: valorServicio | F28: Otro | G28: Servicio | H28: Por referencia | I28: no final | J28: Valor que se asigna al atributo servicio
E29: valorDuracionEnHoras | F29: int/Integer | H29: Por valor | I29: no final | J29: Valor que se asigna al atributo duracionEnHoras
E30: valorDuracionEnMinutos | F30: int/Integer | H30: Por valor | I30: no final | J30: Valor que se asigna al atributo duracionEnMinutos
E31: valorTiempoExtra | F31: int/Integer | H31: Por valor | I31: no final | J31: Valor que se asigna al atributo tiempoExtra
E32: valorVigente | F32: boolean/Boolean | H32: Por valor | I32: no final | J32: Valor que se asigna al atributo vigente
A33: Métodos accesores
A34: Modificador de aceso | B34: Nombre | C34: Tipo método accesor | D34: Tipo modificación método | E34: Descripción | F34: Parámetros | L34: Tipo dato de retorno | N34: Excepciones
F35: Nombre | G35: Tipo de dato | H35: ¿Cuál? | I35: Tipo parámetro | J35: Tipo modificación atributo | K35: Descripción | L35: Tipo de dato | M35: ¿Cuál?
A36: public | B36: getId | C36: getter | D36: no final | E36: Método encargado de obtener el valor del atributo id | L36: Otro | M36: UUID
A37: public | B37: setId | C37: setter | D37: no final | E37: Método encargado de colocar el valor al atributo id | F37: valorId | G37: Otro | H37: UUID | I37: Por referencia | J37: no final | K37: Nuevo valor del atributo id | L37: void
A38: public | B38: getBarbero | C38: getter | D38: no final | E38: Método encargado de obtener el valor del atributo barbero | L38: Otro | M38: Barbero
A39: public | B39: setBarbero | C39: setter | D39: no final | E39: Método encargado de colocar el valor al atributo barbero | F39: valorBarbero | G39: Otro | H39: Barbero | I39: Por referencia | J39: no final | K39: Nuevo valor del atributo barbero | L39: void
A40: public | B40: getServicio | C40: getter | D40: no final | E40: Método encargado de obtener el valor del atributo servicio | L40: Otro | M40: Servicio
A41: public | B41: setServicio | C41: setter | D41: no final | E41: Método encargado de colocar el valor al atributo servicio | F41: valorServicio | G41: Otro | H41: Servicio | I41: Por referencia | J41: no final | K41: Nuevo valor del atributo servicio | L41: void
A42: public | B42: getDuracionEnHoras | C42: getter | D42: no final | E42: Método encargado de obtener el valor del atributo duracionEnHoras | L42: int/Integer
A43: public | B43: setDuracionEnHoras | C43: setter | D43: no final | E43: Método encargado de colocar el valor al atributo duracionEnHoras | F43: valorDuracionEnHoras | G43: int/Integer | I43: Por valor | J43: no final | K43: Nuevo valor del atributo duracionEnHoras | L43: void
A44: public | B44: getDuracionEnMinutos | C44: getter | D44: no final | E44: Método encargado de obtener el valor del atributo duracionEnMinutos | L44: int/Integer
A45: public | B45: setDuracionEnMinutos | C45: setter | D45: no final | E45: Método encargado de colocar el valor al atributo duracionEnMinutos | F45: valorDuracionEnMinutos | G45: int/Integer | I45: Por valor | J45: no final | K45: Nuevo valor del atributo duracionEnMinutos | L45: void
A46: public | B46: getTiempoExtra | C46: getter | D46: no final | E46: Método encargado de obtener el valor del atributo tiempoExtra | L46: int/Integer
A47: public | B47: setTiempoExtra | C47: setter | D47: no final | E47: Método encargado de colocar el valor al atributo tiempoExtra | F47: valorTiempoExtra | G47: int/Integer | I47: Por valor | J47: no final | K47: Nuevo valor del atributo tiempoExtra | L47: void
A48: public | B48: getVigente | C48: getter | D48: no final | E48: Método encargado de obtener el valor del atributo vigente | L48: boolean/Boolean
A49: public | B49: setVigente | C49: setter | D49: no final | E49: Método encargado de colocar el valor al atributo vigente | F49: valorVigente | G49: boolean/Boolean | I49: Por valor | J49: no final | K49: Nuevo valor del atributo vigente | L49: void
A50: Métodos
A51: Modificador de aceso | B51: Nombre | C51: Tipo acceso método | D51: Tipo modificación método | E51: Descripción | F51: Parámetros | L51: Tipo dato de retorno | N51: Excepciones
F52: Nombre | G52: Tipo de dato | H52: ¿Cuál? | I52: Tipo parámetro | J52: Tipo modificación atributo | K52: Descripción | L52: Tipo de dato | M52: ¿Cuál?
A53: public | B53: habilitarServicioBarbero | C53: no static | D53: no final | E53: Comando que permite a un barbero indicar que sabe realizar un servicio del catálogo, con su duración y colchón | F53: barbero | G53: Otro | H53: Barbero | I53: Por referencia | J53: no final | K53: Representa el nombre y apellidos del barbero | L53: Otro | M53: BarberoServicio | N53: Generar una excepción indicándole al barbero que los datos no cumplen las reglas definidas; Generar una excepción indicándole el barbero ya tiene habilitado ese mismo servicio; Generar una excepción indicándole al barbero que los no se puede realizar un servicio en tiempo cero, es decir que debe de poner un timpio mayor a cer, ya que en la hora o en el minuto
F54: servicio | G54: Otro | H54: Servicio | I54: Por referencia | J54: no final | K54: Representa el nombre del servicio de la barberia
F55: duracionEnHoras | G55: int/Integer | I55: Por valor | J55: no final | K55: Representa la cantidad de horas que un barbero tarda en realizar un servicio, esta duracion el barbero debe de ser consiente de cuanto se demora en realizarlo
F56: duracionEnMinutos | G56: int/Integer | I56: Por valor | J56: no final | K56: Representa la cantidad de minutos que un barbero tarda en realizar un servicio, esta duracion el barbero debe de ser consiente de cuanto se demora en realizarlo
F57: tiempoExtra | G57: int/Integer | I57: Por valor | J57: no final | K57: Representa la cantidad de minutos que un barbero pone de tiempo extra en las citas de su agenda, cada barbero usa este tiempo porque hay ocaciones que la cita se puede demorar más de lo previsto. Este tiempo les ayuda a evitar que se les retrase la agenda
A58: public | B58: ajustarTiemposServicioBarbero | C58: no static | D58: no final | E58: Permite modificar la duración y el tiempo extra que un barbero usa para un servicio ya habilitado | F58: id | G58: Otro | H58: UUID | I58: Por referencia | J58: no final | K58: Corresponde al identificador del servicio del barbero que se va a ajustar | L58: Otro | M58: BarberoServicio | N58: Informar con un mensaje que no existe un servicio habilitado del barbero con el identificador enviado y por lo tanto no es posible llevar a cabo la operación; Generar una excepción indicándole al barbero que los datos no cumplen las reglas definidas; Generar una excepción indicándole al barbero que los no se puede realizar un servicio en tiempo cero, es decir que debe de poner un timpio mayor a cer, ya que en la hora o en el minuto
F59: duracionEnHoras | G59: int/Integer | I59: Por valor | J59: no final | K59: Representa la cantidad de horas que un barbero tarda en realizar un servicio, esta duracion el barbero debe de ser consiente de cuanto se demora en realizarlo
F60: duracionEnMinutos | G60: int/Integer | I60: Por valor | J60: no final | K60: Representa la cantidad de minutos que un barbero tarda en realizar un servicio, esta duracion el barbero debe de ser consiente de cuanto se demora en realizarlo
F61: tiempoExtra | G61: int/Integer | I61: Por valor | J61: no final | K61: Representa la cantidad de minutos que un barbero pone de tiempo extra en las citas de su agenda, cada barbero usa este tiempo porque hay ocaciones que la cita se puede demorar más de lo previsto. Este tiempo les ayuda a evitar que se les retrase la agenda
A62: public | B62: consultarServiciosElegidos | C62: no static | D62: no final | E62: Permite a un barbero consultar los servicios que esten vigentes | F62: barbero | G62: Otro | H62: Barbero | I62: Por referencia | J62: no final | K62: Representa el nombre y apellidos del barbero (filtro) | L62: Otro | M62: List<BarberoServicio> | N62: No aplica
A63: public | B63: consultarServiciosDeBarbero | C63: no static | D63: no final | E63: Permite a un cliente consultar qué servicios ofrece un barbero en particular | F63: barbero | G63: Otro | H63: Barbero | I63: Por referencia | J63: no final | K63: Representa el nombre y apellidos del barbero (filtro) | L63: Otro | M63: List<BarberoServicio> | N63: No aplica
A64: public | B64: desactivarServicioBarbero | C64: no static | D64: no final | E64: Permite a un barbero desactivar un servicio que ya no quiere seguir ofreciendo | F64: id | G64: Otro | H64: UUID | I64: Por referencia | J64: no final | K64: Corresponde al identificador del servicio del barbero que se va a desactivar | L64: void | N64: Informar con un mensaje que no existe un servicio habilitado del barbero con el identificador enviado y por lo tanto no es posible llevar a cabo la operación; Informar al barbero que el servicio que quiere desactivar, ya se encuentra desactivado
A65: public | B65: reactivarServicioBarbero | C65: no static | D65: no final | E65: Permite a un barbero activar un servicio que ya se habia desactivado | F65: id | G65: Otro | H65: UUID | I65: Por referencia | J65: no final | K65: Corresponde al identificador del servicio del barbero que se va a desactivar | L65: void | N65: Informar con un mensaje que no existe un servicio habilitado del barbero con el identificador enviado y por lo tanto no es posible llevar a cabo la operación; Informar al barbero que el servicio que quiere reactivar, ya se encuentra activado

Sheet Bloqueo
A1: <-Volver al inicio
A2: =Clases!$A$1 -> Clase | B2: =Clases!A16 -> Bloqueo
A3: =Clases!$B$1 -> Estereotipo | B3: =Clases!B16 -> class
A4: =Clases!$C$1 -> Desripción | B4: =Clases!C16 -> Representa los momentos en que el barbero no esta disponible para atender sus citas, el barbero establece la hora y la fecha en que empieza y termina ese estado de no disponible.
A5: Modificador acceso: | B5: public
A6: Tipo clase: | B6: no final
A7: Relaciones
A8: Relación | B8: Tipo relación | E8: Estructura
A9: Necesita de | B9: Composición | E9: =Barbero!B2 -> Barbero
A10: Atributos
A11: Modificador de aceso | B11: Nombre | C11: Tipo de dato | E11: Tipo modificación atributo | F11: Tipo acceso atributo | G11: Valor por defecto | J11: Descripción atributo
C12: Tipo de dato | D12: ¿Cuál?
A13: private | B13: id | C13: Otro | D13: UUID | E13: no final | F13: no static | G13: new UUID(0L, 0L) | J13: Representa un identificador que hará unico cada objeto de dominio de este tipo, no se puede repetir
A14: private | B14: barbero | C14: Otro | D14: Barbero | E14: no final | F14: no static | G14: new Barbero() | J14: Referencia a qué barbero le pertence este bloqueo
A15: private | B15: fechaHoraInicio | C15: Otro | D15: LocalDateTime | E15: no final | F15: no static | G15: LocalDateTime.of(1000, 1, 1, 0, 0) | J15: Representa la fecha y hora en el que el barbero empieza a no estar disponible para atender las citas
A16: private | B16: fechaHoraFinal | C16: Otro | D16: LocalDateTime | E16: no final | F16: no static | G16: LocalDateTime.of(1000, 1, 1, 0, 0) | J16: Representa la fecha y hora en el que el barbero empieza estar disponible nuevamente para atender las citas
A17: Constructores
A18: Modificador de aceso | B18: Nombre | C18: Tipo constructor | D18: Descripción | E18: Parámetros | M18: Excepciones
E19: Nombre | F19: Tipo de dato | G19: ¿Cuál? | H19: Tipo parámetro | I19: Tipo modificación atributo | J19: Descripción
A20: public | B20: =B2 -> Bloqueo | C20: Defecto | D20: Constructor por defecto que crea un objeto Bloqueo con todos sus atributos en su valor por defecto
A21: public | B21: =B2 -> Bloqueo | C21: Parametrizado | D21: Constructor parametrizado que crea un objeto Bloqueo asignando el valor recibido a cada uno de sus atributos | E21: valorId | F21: Otro | G21: UUID | H21: Por referencia | I21: no final | J21: Valor que se asigna al atributo id
E22: valorBarbero | F22: Otro | G22: Barbero | H22: Por referencia | I22: no final | J22: Valor que se asigna al atributo barbero
E23: valorFechaHoraInicio | F23: Otro | G23: LocalDateTime | H23: Por referencia | I23: no final | J23: Valor que se asigna al atributo fechaHoraInicio
E24: valorFechaHoraFinal | F24: Otro | G24: LocalDateTime | H24: Por referencia | I24: no final | J24: Valor que se asigna al atributo fechaHoraFinal
A25: Métodos accesores
A26: Modificador de aceso | B26: Nombre | C26: Tipo método accesor | D26: Tipo modificación método | E26: Descripción | F26: Parámetros | L26: Tipo dato de retorno | N26: Excepciones
F27: Nombre | G27: Tipo de dato | H27: ¿Cuál? | I27: Tipo parámetro | J27: Tipo modificación atributo | K27: Descripción | L27: Tipo de dato | M27: ¿Cuál?
A28: public | B28: getId | C28: getter | D28: no final | E28: Método encargado de obtener el valor del atributo id | L28: Otro | M28: UUID
A29: public | B29: setId | C29: setter | D29: no final | E29: Método encargado de colocar el valor al atributo id | F29: valorId | G29: Otro | H29: UUID | I29: Por referencia | J29: no final | K29: Nuevo valor del atributo id | L29: void
A30: public | B30: getBarbero | C30: getter | D30: no final | E30: Método encargado de obtener el valor del atributo barbero | L30: Otro | M30: Barbero
A31: public | B31: setBarbero | C31: setter | D31: no final | E31: Método encargado de colocar el valor al atributo barbero | F31: valorBarbero | G31: Otro | H31: Barbero | I31: Por referencia | J31: no final | K31: Nuevo valor del atributo barbero | L31: void
A32: public | B32: getFechaHoraInicio | C32: getter | D32: no final | E32: Método encargado de obtener el valor del atributo fechaHoraInicio | L32: Otro | M32: LocalDateTime
A33: public | B33: setFechaHoraInicio | C33: setter | D33: no final | E33: Método encargado de colocar el valor al atributo fechaHoraInicio | F33: valorFechaHoraInicio | G33: Otro | H33: LocalDateTime | I33: Por referencia | J33: no final | K33: Nuevo valor del atributo fechaHoraInicio | L33: void
A34: public | B34: getFechaHoraFinal | C34: getter | D34: no final | E34: Método encargado de obtener el valor del atributo fechaHoraFinal | L34: Otro | M34: LocalDateTime
A35: public | B35: setFechaHoraFinal | C35: setter | D35: no final | E35: Método encargado de colocar el valor al atributo fechaHoraFinal | F35: valorFechaHoraFinal | G35: Otro | H35: LocalDateTime | I35: Por referencia | J35: no final | K35: Nuevo valor del atributo fechaHoraFinal | L35: void
A36: Métodos
A37: Modificador de aceso | B37: Nombre | C37: Tipo acceso método | D37: Tipo modificación método | E37: Descripción | F37: Parámetros | L37: Tipo dato de retorno | N37: Excepciones
F38: Nombre | G38: Tipo de dato | H38: ¿Cuál? | I38: Tipo parámetro | J38: Tipo modificación atributo | K38: Descripción | L38: Tipo de dato | M38: ¿Cuál?
A39: public | B39: definirBloqueo | C39: no static | D39: no final | E39: Comando que permite a un barbero asignar un espacio de no disponibilidad para atender sus citas | F39: barbero | G39: Otro | H39: Barbero | I39: Por referencia | J39: no final | K39: Referencia a qué barbero le pertence este bloqueo | L39: Otro | M39: Bloqueo | N39: Generar una excepción indicándole al barbero que los datos no cumplen los datos requeridos; Generar una excepción indicándole al barbero que ese rango no se puede bloquear porque ya tiene citas agendadas; Generar una excepción indicándole al barbero que el rango se solapa con otro bloqueo suyo; Generar una excepción indicandole al barbero que la fecha y hora de fin debe de ser mayor a la fecha y hora de inicio
F40: fechaHoraInicio | G40: Otro | H40: LocalDateTime | I40: Por referencia | J40: no final | K40: Representa la fecha y hora en el que el barbero empieza a no estar disponible para atender las citas
F41: fechaHoraFinal | G41: Otro | H41: LocalDateTime | I41: Por referencia | J41: no final | K41: Representa la fecha y hora en el que el barbero empieza estar disponible nuevamente para atender las citas
A42: public | B42: eliminarBloqueo | C42: no static | D42: no final | E42: Permite a un barbero liberar un espacio de su agenda que había bloqueado previamente | F42: id | G42: Otro | H42: UUID | I42: Por referencia | J42: no final | K42: Corresponde al identificador del bloqueo que se va a eliminar | L42: void | N42: Generar una excepción indicándole al usuario que el bloqueo no le pertenece; Informar con un mensaje que no existe un bloqueo con el identificador enviado y por lo tanto no es posible llevar a cabo la operación
A43: public | B43: consultarBloqueosPorFecha | C43: no static | D43: no final | E43: Permite a un barbero ver los espacios que tiene bloqueados en una fecha dada | F43: barbero | G43: Otro | H43: Barbero | I43: Por referencia | J43: no final | K43: Referencia a qué barbero le pertence este bloqueo (filtro) | L43: Otro | M43: List<Bloqueo> | N43: No aplica
F44: fecha | G44: Otro | H44: LocalDate | I44: Por referencia | J44: no final | K44: Fecha por la cual se va a filtrar
A45: public | B45: consultarBloqueoPorFechaHora | C45: no static | D45: no final | E45: Permite al sistema ver si hay o no un bloqueo en una fecha y hora, en el que empieza el bloqueo, para que el determine luego si el cliente puede agenda una cita en ese momento | F45: barbero | G45: Otro | H45: Barbero | I45: Por referencia | J45: no final | K45: Referencia a qué barbero le pertence este bloqueo (filtro) | L45: Otro | M45: Bloqueo | N45: No aplica
F46: fechaHoraInicio | G46: Otro | H46: LocalDateTime | I46: Por referencia | J46: no final | K46: Representa la fecha y hora en el que el barbero empieza a no estar disponible para atender las citas (filtro)
A47: public | B47: editarBloqueo | C47: no static | D47: no final | E47: Permite al barbero poder editar la fecha y hora en que inicia o termina | F47: id | G47: Otro | H47: UUID | I47: Por referencia | J47: no final | K47: Corresponde al identificador del bloqueo que se va a editar | L47: Otro | M47: Bloqueo | N47: Informar con un mensaje que no existe un bloqueo con el identificador enviado y por lo tanto no es posible llevar a cabo la operación; Generar una excepción indicándole al usuario cuáles datos del bloqueo que se va a editar no cumplen con las reglas definidas; Generar una excepción indicándole al usuario que ese rango no se puede bloquear porque ya tiene citas agendadas
F48: fechaHoraInicio | G48: Otro | H48: LocalDateTime | I48: Por referencia | J48: no final | K48: Representa la fecha y hora en el que el barbero empieza a no estar disponible para atender las citas
F49: fechaHoraFinal | G49: Otro | H49: LocalDateTime | I49: Por referencia | J49: no final | K49: Representa la fecha y hora en el que el barbero empieza estar disponible nuevamente para atender las citas

Sheet HorarioBarbero
A1: <-Volver al inicio
A2: =Clases!$A$1 -> Clase | B2: =Clases!A17 -> HorarioBarbero
A3: =Clases!$B$1 -> Estereotipo | B3: =Clases!B17 -> class
A4: =Clases!$C$1 -> Desripción | B4: =Clases!C17 -> Representa el día de la semana en que trabaja un barbero, junto con la hora en la que empieza y termina su jornada de trabajo.
A5: Modificador acceso: | B5: public
A6: Tipo clase: | B6: no final
A7: Relaciones
A8: Relación | B8: Tipo relación | E8: Estructura
A9: Necesita de | B9: Composición | E9: =Barbero!B2 -> Barbero
A10: Necesita de | B10: Composición | E10: =HorarioBarberia!B2 -> HorarioBarberia
A11: Es usada por | B11: Composición | E11: =Agenda!B2 -> Agenda
A12: Atributos
A13: Modificador de aceso | B13: Nombre | C13: Tipo de dato | E13: Tipo modificación atributo | F13: Tipo acceso atributo | G13: Valor por defecto | J13: Descripción atributo
C14: Tipo de dato | D14: ¿Cuál?
A15: private | B15: id | C15: Otro | D15: UUID | E15: no final | F15: no static | G15: new UUID(0L, 0L) | J15: Representa un identificador que hará unico cada objeto de dominio de este tipo, no se puede repetir
A16: private | B16: barbero | C16: Otro | D16: Barbero | E16: no final | F16: no static | G16: new Barbero() | J16: Referencia a que barbero va a ser dueño de este horario
A17: private | B17: horarioDeLaBarberia | C17: Otro | D17: HorarioBarberia | E17: no final | F17: no static | G17: new HorarioBarberia() | J17: Hace referencia a la agenda del barbero en la que queda guardado este horario de trabajo
A18: private | B18: horaInicio | C18: Otro | D18: LocalTime | E18: no final | F18: no static | G18: LocalTime.of(0, 0) | J18: Representa la hora en la que el barbero empieza a estar disponible ese dia
A19: private | B19: horaFinal | C19: Otro | D19: LocalTime | E19: no final | F19: no static | G19: LocalTime.of(0, 0) | J19: Representa la hora en la que el barbero deja de estar disponible ese día.
A20: private | B20: fechaCreacion | C20: Otro | D20: LocalDate | E20: no final | F20: no static | G20: LocalDate.of(1000, 1, 1) | J20: Representa la fecha en el que el barbero creo su horario. Es un dato calculado que toma la fecha de hoy cuando el barbero la crea
A21: private | B21: fechaDesactivacion | C21: Otro | D21: LocalDate | E21: no final | F21: no static | G21: LocalDate.of(1000, 1, 1) | J21: Representa la fecha en la que este horario dejó de estar vigente, ya sea porque el barbero lo retiró o porque se desactivó el horario de la barbería del que depende. Es un dato calculado que toma la fecha del sistema en ese momento.
A22: private | B22: vigente | C22: boolean/Boolean | E22: no final | F22: no static | G22: true | J22: Representa si este horario lo sigue o no usando el barbero. Una vez que el barbero cambie este estado a no vigente, no se puede volver a cambiar
A23: Constructores
A24: Modificador de aceso | B24: Nombre | C24: Tipo constructor | D24: Descripción | E24: Parámetros | M24: Excepciones
E25: Nombre | F25: Tipo de dato | G25: ¿Cuál? | H25: Tipo parámetro | I25: Tipo modificación atributo | J25: Descripción
A26: public | B26: =B2 -> HorarioBarbero | C26: Defecto | D26: Constructor por defecto que crea un objeto HorarioBarbero con todos sus atributos en su valor por defecto
A27: public | B27: =B2 -> HorarioBarbero | C27: Parametrizado | D27: Constructor parametrizado que crea un objeto HorarioBarbero asignando el valor recibido a cada uno de sus atributos | E27: valorId | F27: Otro | G27: UUID | H27: Por referencia | I27: no final | J27: Valor que se asigna al atributo id
E28: valorBarbero | F28: Otro | G28: Barbero | H28: Por referencia | I28: no final | J28: Valor que se asigna al atributo barbero
E29: valorHorarioDeLaBarberia | F29: Otro | G29: HorarioBarberia | H29: Por referencia | I29: no final | J29: Valor que se asigna al atributo horarioDeLaBarberia
E30: valorHoraInicio | F30: Otro | G30: LocalTime | H30: Por referencia | I30: no final | J30: Valor que se asigna al atributo horaInicio
E31: valorHoraFinal | F31: Otro | G31: LocalTime | H31: Por referencia | I31: no final | J31: Valor que se asigna al atributo horaFinal
E32: valorFechaCreacion | F32: Otro | G32: LocalDate | H32: Por referencia | I32: no final | J32: Valor que se asigna al atributo fechaCreacion
E33: valorFechaDesactivacion | F33: Otro | G33: LocalDate | H33: Por referencia | I33: no final | J33: Valor que se asigna al atributo fechaDesactivacion
E34: valorVigente | F34: boolean/Boolean | H34: Por valor | I34: no final | J34: Valor que se asigna al atributo vigente
A35: Métodos accesores
A36: Modificador de aceso | B36: Nombre | C36: Tipo método accesor | D36: Tipo modificación método | E36: Descripción | F36: Parámetros | L36: Tipo dato de retorno | N36: Excepciones
F37: Nombre | G37: Tipo de dato | H37: ¿Cuál? | I37: Tipo parámetro | J37: Tipo modificación atributo | K37: Descripción | L37: Tipo de dato | M37: ¿Cuál?
A38: public | B38: getId | C38: getter | D38: no final | E38: Método encargado de obtener el valor del atributo id | L38: Otro | M38: UUID
A39: public | B39: setId | C39: setter | D39: no final | E39: Método encargado de colocar el valor al atributo id | F39: valorId | G39: Otro | H39: UUID | I39: Por referencia | J39: no final | K39: Nuevo valor del atributo id | L39: void
A40: public | B40: getBarbero | C40: getter | D40: no final | E40: Método encargado de obtener el valor del atributo barbero | L40: Otro | M40: Barbero
A41: public | B41: setBarbero | C41: setter | D41: no final | E41: Método encargado de colocar el valor al atributo barbero | F41: valorBarbero | G41: Otro | H41: Barbero | I41: Por referencia | J41: no final | K41: Nuevo valor del atributo barbero | L41: void
A42: public | B42: getHorarioDeLaBarberia | C42: getter | D42: no final | E42: Método encargado de obtener el valor del atributo horarioDeLaBarberia | L42: Otro | M42: HorarioBarberia
A43: public | B43: setHorarioDeLaBarberia | C43: setter | D43: no final | E43: Método encargado de colocar el valor al atributo horarioDeLaBarberia | F43: valorHorarioDeLaBarberia | G43: Otro | H43: HorarioBarberia | I43: Por referencia | J43: no final | K43: Nuevo valor del atributo horarioDeLaBarberia | L43: void
A44: public | B44: getHoraInicio | C44: getter | D44: no final | E44: Método encargado de obtener el valor del atributo horaInicio | L44: Otro | M44: LocalTime
A45: public | B45: setHoraInicio | C45: setter | D45: no final | E45: Método encargado de colocar el valor al atributo horaInicio | F45: valorHoraInicio | G45: Otro | H45: LocalTime | I45: Por referencia | J45: no final | K45: Nuevo valor del atributo horaInicio | L45: void
A46: public | B46: getHoraFinal | C46: getter | D46: no final | E46: Método encargado de obtener el valor del atributo horaFinal | L46: Otro | M46: LocalTime
A47: public | B47: setHoraFinal | C47: setter | D47: no final | E47: Método encargado de colocar el valor al atributo horaFinal | F47: valorHoraFinal | G47: Otro | H47: LocalTime | I47: Por referencia | J47: no final | K47: Nuevo valor del atributo horaFinal | L47: void
A48: public | B48: getFechaCreacion | C48: getter | D48: no final | E48: Método encargado de obtener el valor del atributo fechaCreacion | L48: Otro | M48: LocalDate
A49: public | B49: setFechaCreacion | C49: setter | D49: no final | E49: Método encargado de colocar el valor al atributo fechaCreacion | F49: valorFechaCreacion | G49: Otro | H49: LocalDate | I49: Por referencia | J49: no final | K49: Nuevo valor del atributo fechaCreacion | L49: void
A50: public | B50: getFechaDesactivacion | C50: getter | D50: no final | E50: Método encargado de obtener el valor del atributo fechaDesactivacion | L50: Otro | M50: LocalDate
A51: public | B51: setFechaDesactivacion | C51: setter | D51: no final | E51: Método encargado de colocar el valor al atributo fechaDesactivacion | F51: valorFechaDesactivacion | G51: Otro | H51: LocalDate | I51: Por referencia | J51: no final | K51: Nuevo valor del atributo fechaDesactivacion | L51: void
A52: public | B52: getVigente | C52: getter | D52: no final | E52: Método encargado de obtener el valor del atributo vigente | L52: boolean/Boolean
A53: public | B53: setVigente | C53: setter | D53: no final | E53: Método encargado de colocar el valor al atributo vigente | F53: valorVigente | G53: boolean/Boolean | I53: Por valor | J53: no final | K53: Nuevo valor del atributo vigente | L53: void
A54: Métodos
A55: Modificador de aceso | B55: Nombre | C55: Tipo acceso método | D55: Tipo modificación método | E55: Descripción | F55: Parámetros | L55: Tipo dato de retorno | N55: Excepciones
F56: Nombre | G56: Tipo de dato | H56: ¿Cuál? | I56: Tipo parámetro | J56: Tipo modificación atributo | K56: Descripción | L56: Tipo de dato | M56: ¿Cuál?
A57: public | B57: definirHorarioDeTrabajo | C57: no static | D57: no final | E57: Comando que permite a un barbero registrar el día de la semana y las horas en que trabaja | F57: barbero | G57: Otro | H57: Barbero | I57: Por referencia | J57: no final | K57: Referencia a que barbero va a ser dueño de este horario | L57: Otro | M57: HorarioBarbero | N57: Generar una excepción indicándole al barbero que los datos no cumplen las reglas definidas; Generar una excepción indicándole al usuario que el horario de trabajo queda por fuera del horario de apertura y cierre de la barbería para ese día; Generar una excepción indicándole al barbero que la hora de fin debe ser mayor a la hora de inicio
F58: horarioDeLaBarberia | G58: Otro | H58: HorarioBarberia | I58: Por referencia | J58: no final | K58: Hace referencia a la agenda del barbero en la que queda guardado este horario de trabajo
F59: horaInicio | G59: Otro | H59: LocalTime | I59: Por referencia | J59: no final | K59: Representa la hora en la que el barbero empieza a estar disponible ese dia
F60: horaFinal | G60: Otro | H60: LocalTime | I60: Por referencia | J60: no final | K60: Representa la hora en la que el barbero deja de estar disponible ese día.
A61: public | B61: consultarHorariosDefinidos | C61: no static | D61: no final | E61: Permite a un barbero consultar los horarios de trabajo que ha definido | F61: barbero | G61: Otro | H61: Barbero | I61: Por referencia | J61: no final | K61: Referencia a que barbero va a ser dueño de este horario (filtro) | L61: Otro | M61: List<HorarioBarbero> | N61: No aplica
A62: public | B62: desactivarHorarioDeTrabajo | C62: no static | D62: no final | E62: Permite a un barbero desactivar un horario para dejar de trabajar ese día de la semana, cancelando las citas futuras que dependían de él | F62: id | G62: Otro | H62: UUID | I62: Por referencia | J62: no final | K62: Corresponde al identificador del horario de trabajo que se va a desactivar | L62: void | N62: Si alguna de las citas futuras no pudo ser cancelada, revertir toda la operación e informar el error; Informar con un mensaje que no existe un horario de trabajo con el identificador enviado y por lo tanto no es posible llevar a cabo la operación; Informar con un mensaje que ese horario de trabajo ya se encuentra desactivado y por lo tanto no puede volver a desactivarse
A63: public | B63: consultarHorariosDeTrabajoDeBarbero | C63: no static | D63: no final | E63: Permite a un cliente consultar en qué días y horas trabaja un barbero | F63: barbero | G63: Otro | H63: Barbero | I63: Por referencia | J63: no final | K63: Referencia a que barbero va a ser dueño de este horario (filtro) | L63: Otro | M63: List<HorarioBarbero> | N63: No aplica

Sheet Agenda
A1: <-Volver al inicio
A2: =Clases!$A$1 -> Clase | B2: =Clases!A18 -> Agenda
A3: =Clases!$B$1 -> Estereotipo | B3: =Clases!B18 -> class
A4: =Clases!$C$1 -> Desripción | B4: =Clases!C18 -> Representa una fecha puntual en donde el barbero ve todas las citas que debe de atender ese día.
A5: Modificador acceso: | B5: public
A6: Tipo clase: | B6: no final
A7: Relaciones
A8: Relación | B8: Tipo relación | E8: Estructura
A9: Necesita de | B9: Composición | E9: =HorarioBarbero!B2 -> HorarioBarbero
A10: Es usada por | B10: Composición | E10: =Cita!B2 -> Cita
A11: Atributos
A12: Modificador de aceso | B12: Nombre | C12: Tipo de dato | E12: Tipo modificación atributo | F12: Tipo acceso atributo | G12: Valor por defecto | J12: Descripción atributo
C13: Tipo de dato | D13: ¿Cuál?
A14: private | B14: id | C14: Otro | D14: UUID | E14: no final | F14: no static | G14: new UUID(0L, 0L) | J14: Representa un identificador que hará unico cada objeto de dominio de este tipo, no se puede repetir
A15: private | B15: horarioDelBarbero | C15: Otro | D15: HorarioBarbero | E15: no final | F15: no static | G15: new HorarioBarbero() | J15: Hace referencia al horario de trabajo del barbero (día de la semana, hora de inicio y hora final) al que pertenece esta agenda
A16: private | B16: fecha | C16: Otro | D16: LocalDate | E16: no final | F16: no static | G16: LocalDate.of(1000, 1, 1) | J16: Representa la fecha específica en el que la agenda va a guardar las citas de ese barbero
A17: Constructores
A18: Modificador de aceso | B18: Nombre | C18: Tipo constructor | D18: Descripción | E18: Parámetros | M18: Excepciones
E19: Nombre | F19: Tipo de dato | G19: ¿Cuál? | H19: Tipo parámetro | I19: Tipo modificación atributo | J19: Descripción
A20: public | B20: =B2 -> Agenda | C20: Defecto | D20: Constructor por defecto que crea un objeto Agenda con todos sus atributos en su valor por defecto
A21: public | B21: =B2 -> Agenda | C21: Parametrizado | D21: Constructor parametrizado que crea un objeto Agenda asignando el valor recibido a cada uno de sus atributos | E21: valorId | F21: Otro | G21: UUID | H21: Por referencia | I21: no final | J21: Valor que se asigna al atributo id
E22: valorHorarioDelBarbero | F22: Otro | G22: HorarioBarbero | H22: Por referencia | I22: no final | J22: Valor que se asigna al atributo horarioDelBarbero
E23: valorFecha | F23: Otro | G23: LocalDate | H23: Por referencia | I23: no final | J23: Valor que se asigna al atributo fecha
A24: Métodos accesores
A25: Modificador de aceso | B25: Nombre | C25: Tipo método accesor | D25: Tipo modificación método | E25: Descripción | F25: Parámetros | L25: Tipo dato de retorno | N25: Excepciones
F26: Nombre | G26: Tipo de dato | H26: ¿Cuál? | I26: Tipo parámetro | J26: Tipo modificación atributo | K26: Descripción | L26: Tipo de dato | M26: ¿Cuál?
A27: public | B27: getId | C27: getter | D27: no final | E27: Método encargado de obtener el valor del atributo id | L27: Otro | M27: UUID
A28: public | B28: setId | C28: setter | D28: no final | E28: Método encargado de colocar el valor al atributo id | F28: valorId | G28: Otro | H28: UUID | I28: Por referencia | J28: no final | K28: Nuevo valor del atributo id | L28: void
A29: public | B29: getHorarioDelBarbero | C29: getter | D29: no final | E29: Método encargado de obtener el valor del atributo horarioDelBarbero | L29: Otro | M29: HorarioBarbero
A30: public | B30: setHorarioDelBarbero | C30: setter | D30: no final | E30: Método encargado de colocar el valor al atributo horarioDelBarbero | F30: valorHorarioDelBarbero | G30: Otro | H30: HorarioBarbero | I30: Por referencia | J30: no final | K30: Nuevo valor del atributo horarioDelBarbero | L30: void
A31: public | B31: getFecha | C31: getter | D31: no final | E31: Método encargado de obtener el valor del atributo fecha | L31: Otro | M31: LocalDate
A32: public | B32: setFecha | C32: setter | D32: no final | E32: Método encargado de colocar el valor al atributo fecha | F32: valorFecha | G32: Otro | H32: LocalDate | I32: Por referencia | J32: no final | K32: Nuevo valor del atributo fecha | L32: void
A33: Métodos
A34: Modificador de aceso | B34: Nombre | C34: Tipo acceso método | D34: Tipo modificación método | E34: Descripción | F34: Parámetros | L34: Tipo dato de retorno | N34: Excepciones
F35: Nombre | G35: Tipo de dato | H35: ¿Cuál? | I35: Tipo parámetro | J35: Tipo modificación atributo | K35: Descripción | L35: Tipo de dato | M35: ¿Cuál?
A36: public | B36: crearAgendaBarbero | C36: no static | D36: no final | E36: Comando que crea la agenda del día para un barbero y pueda saber que citas debe de atender | F36: horarioDelBarbero | G36: Otro | H36: HorarioBarbero | I36: Por referencia | J36: no final | K36: Hace referencia al horario de trabajo del barbero (día de la semana, hora de inicio y hora final) al que pertenece esta agenda | L36: Otro | M36: Agenda | N36: Generar una excepción indicándole al usuario que ya existe una agenda para ese horario de barbero y esa misma fecha; Generar una excepción indicándole al usuario que no se le puede abrir agenda porque el barbero no está vigente
F37: fecha | G37: Otro | H37: LocalDate | I37: Por referencia | J37: no final | K37: Representa la fecha específica en el que la agenda va a guardar las citas de ese barbero
A38: public | B38: consultarDisponibilidadBarbero | C38: no static | D38: no final | E38: Permite a un cliente ver qué espacios le quedan libres a un barbero en una fecha, descontando sus citas ya agendadas y sus bloqueos | F38: barbero | G38: Otro | H38: Barbero | I38: Por referencia | J38: no final | K38: Barbero por el cual se va a filtrar | L38: Otro | M38: List<LocalTime> | N38: Si no se pueden descontar las citas o los bloqueos, informar que la disponibilidad no se pudo calcular
F39: fecha | G39: Otro | H39: LocalDate | I39: Por referencia | J39: no final | K39: Representa la fecha específica en el que la agenda va a guardar las citas de ese barbero (filtro)
A40: public | B40: consultarCitasDeAgenda | C40: no static | D40: no final | E40: Permite consultar todas las citas agrupadas en la agenda de un barbero para una fecha puntual | F40: barbero | G40: Otro | H40: Barbero | I40: Por referencia | J40: no final | K40: Barbero por el cual se va a filtrar | L40: Otro | M40: List<Cita> | N40: No aplica
F41: fecha | G41: Otro | H41: LocalDate | I41: Por referencia | J41: no final | K41: Representa la fecha específica en el que la agenda va a guardar las citas de ese barbero (filtro)
A42: public | B42: consultarCitasPorBarberoYRango | C42: no static | D42: no final | E42: Permite consultar las citas no canceladas de un barbero dentro de un rango de fecha y hora, recorriendo todas las agendas comprendidas en ese rango | F42: barbero | G42: Otro | H42: Barbero | I42: Por referencia | J42: no final | K42: Barbero por el cual se va a filtrar | L42: Otro | M42: List<Cita> | N42: No aplica
F43: fechaHoraInicio | G43: Otro | H43: LocalDateTime | I43: Por referencia | J43: no final | K43: Fecha y hora inicial del rango
F44: fechaHoraFinal | G44: Otro | H44: LocalDateTime | I44: Por referencia | J44: no final | K44: Fecha y hora final del rango

Sheet Cita
A1: <-Volver al inicio
A2: =Clases!$A$1 -> Clase | B2: =Clases!A19 -> Cita
A3: =Clases!$B$1 -> Estereotipo | B3: =Clases!B19 -> class
A4: =Clases!$C$1 -> Desripción | B4: =Clases!C19 -> Representa la reserva de un cliente con un barbero para un fecha y hora puntual, con los servicios pedidos, su estado, y lo que realmente ocurrió (llegada, atención, tardanzas).
A5: Modificador acceso: | B5: public
A6: Tipo clase: | B6: no final
A7: Relaciones
A8: Relación | B8: Tipo relación | E8: Estructura
A9: Necesita de | B9: Composición | E9: =Cliente!B2 -> Cliente
A10: Necesita de | B10: Composición | E10: =Agenda!B2 -> Agenda
A11: Necesita de | B11: Asociación | E11: =Estado!B2 -> Estado
A12: Es usada por | B12: Composición | E12: =CitaServicio!B2 -> CitaServicio
A13: Es usada por | B13: Composición | E13: =Multa!B2 -> Multa
A14: Es usada por | B14: Composición | E14: =RegistroHoraCita!B2 -> RegistroHoraCita
A15: Atributos
A16: Modificador de aceso | B16: Nombre | C16: Tipo de dato | E16: Tipo modificación atributo | F16: Tipo acceso atributo | G16: Valor por defecto | J16: Descripción atributo
C17: Tipo de dato | D17: ¿Cuál?
A18: private | B18: id | C18: Otro | D18: UUID | E18: no final | F18: no static | G18: new UUID(0L, 0L) | J18: Representa un identificador que hará unico cada objeto de dominio de este tipo, no se puede repetir
A19: private | B19: cliente | C19: Otro | D19: Cliente | E19: no final | F19: no static | G19: new Cliente() | J19: Representa a cuál cliente le pertenece esta cita
A20: private | B20: agenda | C20: Otro | D20: Agenda | E20: no final | F20: no static | G20: new Agenda() | J20: Referencia en cual agenda va a estar esta cita
A21: private | B21: estado | C21: Otro | D21: Estado | E21: no final | F21: no static | G21: new Estado() | J21: Representa en qué estado se encuentra esta cita puntual: agendada, finalizada, cancelada, con tardanza del cliente o del barbero, o inasistencia
A22: private | B22: horaInicio | C22: Otro | D22: LocalTime | E22: no final | F22: no static | G22: LocalTime.of(0, 0) | J22: Representa la hora en la que se va a realizar la cita al cliente
A23: private | B23: horaFinEstimada | C23: Otro | D23: LocalTime | E23: no final | F23: no static | G23: LocalTime.of(0, 0) | J23: Representa la hora en la que se espera que termine la cita, sumando horaInicio más la duración total de los servicios pedidos. Es un dato calculado
A24: private | B24: porcentajeDescuento | C24: int/Integer | E24: no final | F24: no static | G24: 0 | J24: Representa el descuento que el barbero le concede al cliente por haberse demorado en atenderlo; solo se descuenta del precioTotal cuando la cita queda en el estado "El barbero se demoro"
A25: private | B25: multa | C25: int/Integer | E25: no final | F25: no static | G25: 0 | J25: Representa el precio de sancion, en caso de que el cliente se demore
A26: private | B26: tiempoEspera | C26: int/Integer | E26: no final | F26: no static | G26: 0 | J26: Representa la cantidad de minutos en el que el barbero puede esperar a un cliente, después de este tiempo de espera se le hace una sanción por retraso. Si el barbero se pasa de este tiempo se le da el descuento al cliente
A27: private | B27: precioTotal | C27: int/Integer | E27: no final | F27: no static | G27: 0 | J27: Representa cuánto debe pagar el cliente por los servicios de esta cita: la suma del precioServicio de todos sus CitaServicio, al que solo se le aplica el porcentajeDescuento cuando la cita quedó en el estado "El barbero se demoro"
A28: Constructores
A29: Modificador de aceso | B29: Nombre | C29: Tipo constructor | D29: Descripción | E29: Parámetros | M29: Excepciones
E30: Nombre | F30: Tipo de dato | G30: ¿Cuál? | H30: Tipo parámetro | I30: Tipo modificación atributo | J30: Descripción
A31: public | B31: =B2 -> Cita | C31: Defecto | D31: Constructor por defecto que crea un objeto Cita con todos sus atributos en su valor por defecto
A32: public | B32: =B2 -> Cita | C32: Parametrizado | D32: Constructor parametrizado que crea un objeto Cita asignando el valor recibido a cada uno de sus atributos | E32: valorId | F32: Otro | G32: UUID | H32: Por referencia | I32: no final | J32: Valor que se asigna al atributo id
E33: valorCliente | F33: Otro | G33: Cliente | H33: Por referencia | I33: no final | J33: Valor que se asigna al atributo cliente
E34: valorAgenda | F34: Otro | G34: Agenda | H34: Por referencia | I34: no final | J34: Valor que se asigna al atributo agenda
E35: valorEstado | F35: Otro | G35: Estado | H35: Por referencia | I35: no final | J35: Valor que se asigna al atributo estado
E36: valorHoraInicio | F36: Otro | G36: LocalTime | H36: Por referencia | I36: no final | J36: Valor que se asigna al atributo horaInicio
E37: valorHoraFinEstimada | F37: Otro | G37: LocalTime | H37: Por referencia | I37: no final | J37: Valor que se asigna al atributo horaFinEstimada
E38: valorPorcentajeDescuento | F38: int/Integer | H38: Por valor | I38: no final | J38: Valor que se asigna al atributo porcentajeDescuento
E39: valorMulta | F39: int/Integer | H39: Por valor | I39: no final | J39: Valor que se asigna al atributo multa
E40: valorTiempoEspera | F40: int/Integer | H40: Por valor | I40: no final | J40: Valor que se asigna al atributo tiempoEspera
E41: valorPrecioTotal | F41: int/Integer | H41: Por valor | I41: no final | J41: Valor que se asigna al atributo precioTotal
A42: Métodos accesores
A43: Modificador de aceso | B43: Nombre | C43: Tipo método accesor | D43: Tipo modificación método | E43: Descripción | F43: Parámetros | L43: Tipo dato de retorno | N43: Excepciones
F44: Nombre | G44: Tipo de dato | H44: ¿Cuál? | I44: Tipo parámetro | J44: Tipo modificación atributo | K44: Descripción | L44: Tipo de dato | M44: ¿Cuál?
A45: public | B45: getId | C45: getter | D45: no final | E45: Método encargado de obtener el valor del atributo id | L45: Otro | M45: UUID
A46: public | B46: setId | C46: setter | D46: no final | E46: Método encargado de colocar el valor al atributo id | F46: valorId | G46: Otro | H46: UUID | I46: Por referencia | J46: no final | K46: Nuevo valor del atributo id | L46: void
A47: public | B47: getCliente | C47: getter | D47: no final | E47: Método encargado de obtener el valor del atributo cliente | L47: Otro | M47: Cliente
A48: public | B48: setCliente | C48: setter | D48: no final | E48: Método encargado de colocar el valor al atributo cliente | F48: valorCliente | G48: Otro | H48: Cliente | I48: Por referencia | J48: no final | K48: Nuevo valor del atributo cliente | L48: void
A49: public | B49: getAgenda | C49: getter | D49: no final | E49: Método encargado de obtener el valor del atributo agenda | L49: Otro | M49: Agenda
A50: public | B50: setAgenda | C50: setter | D50: no final | E50: Método encargado de colocar el valor al atributo agenda | F50: valorAgenda | G50: Otro | H50: Agenda | I50: Por referencia | J50: no final | K50: Nuevo valor del atributo agenda | L50: void
A51: public | B51: getEstado | C51: getter | D51: no final | E51: Método encargado de obtener el valor del atributo estado | L51: Otro | M51: Estado
A52: public | B52: setEstado | C52: setter | D52: no final | E52: Método encargado de colocar el valor al atributo estado | F52: valorEstado | G52: Otro | H52: Estado | I52: Por referencia | J52: no final | K52: Nuevo valor del atributo estado | L52: void
A53: public | B53: getHoraInicio | C53: getter | D53: no final | E53: Método encargado de obtener el valor del atributo horaInicio | L53: Otro | M53: LocalTime
A54: public | B54: setHoraInicio | C54: setter | D54: no final | E54: Método encargado de colocar el valor al atributo horaInicio | F54: valorHoraInicio | G54: Otro | H54: LocalTime | I54: Por referencia | J54: no final | K54: Nuevo valor del atributo horaInicio | L54: void
A55: public | B55: getHoraFinEstimada | C55: getter | D55: no final | E55: Método encargado de obtener el valor del atributo horaFinEstimada | L55: Otro | M55: LocalTime
A56: public | B56: setHoraFinEstimada | C56: setter | D56: no final | E56: Método encargado de colocar el valor al atributo horaFinEstimada | F56: valorHoraFinEstimada | G56: Otro | H56: LocalTime | I56: Por referencia | J56: no final | K56: Nuevo valor del atributo horaFinEstimada | L56: void
A57: public | B57: getPorcentajeDescuento | C57: getter | D57: no final | E57: Método encargado de obtener el valor del atributo porcentajeDescuento | L57: int/Integer
A58: public | B58: setPorcentajeDescuento | C58: setter | D58: no final | E58: Método encargado de colocar el valor al atributo porcentajeDescuento | F58: valorPorcentajeDescuento | G58: int/Integer | I58: Por valor | J58: no final | K58: Nuevo valor del atributo porcentajeDescuento | L58: void
A59: public | B59: getMulta | C59: getter | D59: no final | E59: Método encargado de obtener el valor del atributo multa | L59: int/Integer
A60: public | B60: setMulta | C60: setter | D60: no final | E60: Método encargado de colocar el valor al atributo multa | F60: valorMulta | G60: int/Integer | I60: Por valor | J60: no final | K60: Nuevo valor del atributo multa | L60: void
A61: public | B61: getTiempoEspera | C61: getter | D61: no final | E61: Método encargado de obtener el valor del atributo tiempoEspera | L61: int/Integer
A62: public | B62: setTiempoEspera | C62: setter | D62: no final | E62: Método encargado de colocar el valor al atributo tiempoEspera | F62: valorTiempoEspera | G62: int/Integer | I62: Por valor | J62: no final | K62: Nuevo valor del atributo tiempoEspera | L62: void
A63: public | B63: getPrecioTotal | C63: getter | D63: no final | E63: Método encargado de obtener el valor del atributo precioTotal | L63: int/Integer
A64: public | B64: setPrecioTotal | C64: setter | D64: no final | E64: Método encargado de colocar el valor al atributo precioTotal | F64: valorPrecioTotal | G64: int/Integer | I64: Por valor | J64: no final | K64: Nuevo valor del atributo precioTotal | L64: void
A65: Métodos
A66: Modificador de aceso | B66: Nombre | C66: Tipo acceso método | D66: Tipo modificación método | E66: Descripción | F66: Parámetros | L66: Tipo dato de retorno | N66: Excepciones
F67: Nombre | G67: Tipo de dato | H67: ¿Cuál? | I67: Tipo parámetro | J67: Tipo modificación atributo | K67: Descripción | L67: Tipo de dato | M67: ¿Cuál?
A68: public | B68: pedirCita | C68: no static | D68: no final | E68: Comando que permite a un cliente solicitar una cita con un barbero, en una fecha y hora puntual, con uno o más servicios | F68: cliente | G68: Otro | H68: Cliente | I68: Por referencia | J68: no final | K68: Representa a cuál cliente le pertenece esta cita | L68: Otro | M68: Cita | N68: Generar una excepción indicándole al cliente que los datos de la cita no cumplen con las reglas definidas; Generar una excepción indicándole al cliente que no puede agendar porque el cliente está vetado; Generar una excepción indicándole al cliente que el barbero no tiene disponibilidad en la hora solicitada; Generar una excepción indicándole al cliente que la hora solicitada cae dentro de un bloqueo del barbero; Generar una excepción indicándole al cliente que alguno de los servicios pedidos no está habilitado para ese barbero; Generar una excepción indicándole al cliente que los servicios pedidos pertenecen a más de un barbero; Generar una excepción indicándole al cliente que no puede agendar una cita para una fecha y hora que ya pasaron; Generar una excepción indicándole al cliente que solo puede agendar hasta 15 días después del día actual; Si los valores de multa, tiempoEspera y porcentajeDescuento no se pueden congelar, no registrar la cita
F69: agenda | G69: Otro | H69: Agenda | I69: Por referencia | J69: no final | K69: Referencia en cual agenda va a estar esta cita
F70: horaInicio | G70: Otro | H70: LocalTime | I70: Por referencia | J70: no final | K70: Representa la hora en la que se va a realizar la cita al cliente
F71: servicios | G71: Otro | H71: List<BarberoServicio> | I71: Por referencia | J71: no final | K71: Servicios del barbero que el cliente desea incluir en la cita
A72: public | B72: reprogramarCita | C72: no static | D72: no final | E72: Permite a un cliente cambiar la fecha, hora o barbero de una cita que aún no ha ocurrido | F72: id | G72: Otro | H72: UUID | I72: Por referencia | J72: no final | K72: Corresponde al identificador de la cita que se va a reprogramar | L72: Otro | M72: Cita | N72: Informar con un mensaje que no existe una cita con el identificador enviado y por lo tanto no es posible llevar a cabo la operación; Generar una excepción indicándole al cliente que la cita no se puede reprogramar porque no se encuentra en estado Agendada; Generar una excepción indicándole al cliente que el barbero no tiene disponibilidad en la hora solicitada; Generar una excepción indicándole al cliente que la hora solicitada cae dentro de un bloqueo del barbero; Generar una excepción indicándole al cliente que solo puede reprogramar hasta 15 días después del día actual; Generar una excepción indicándole al cliente que no puede agendar una cita para una fecha y hora que ya pasaron
F73: agenda | G73: Otro | H73: Agenda | I73: Por referencia | J73: no final | K73: Referencia en cual agenda va a estar esta cita
F74: horaInicio | G74: Otro | H74: LocalTime | I74: Por referencia | J74: no final | K74: Representa la hora en la que se va a realizar la cita al cliente
A75: public | B75: cancelarCitaPorCliente | C75: no static | D75: no final | E75: Permite a un cliente cancelar una cita antes de que ocurra | F75: id | G75: Otro | H75: UUID | I75: Por referencia | J75: no final | K75: Corresponde al identificador de la cita que el cliente va a cancelar | L75: Otro | M75: Cita | N75: Informar con un mensaje que no existe una cita con el identificador enviado y por lo tanto no es posible llevar a cabo la operación; Generar una excepción indicándole al cliente que la cita no se puede cancelar porque no se encuentra en estado Agendada; Generar una excepción indicándole al cliente que ya no puede cancelar la cita porque faltan menos de 2 horas para su horaInicio
A76: public | B76: cancelarCitaPorBarbero | C76: no static | D76: no final | E76: Permite a un barbero cancelar una cita antes de que ocurra | F76: id | G76: Otro | H76: UUID | I76: Por referencia | J76: no final | K76: Corresponde al identificador de la cita que el barbero va a cancelar | L76: Otro | M76: Cita | N76: Informar con un mensaje que no existe una cita con el identificador enviado y por lo tanto no es posible llevar a cabo la operación; Generar una excepción indicándole al barbero que la cita no se puede cancelar porque no se encuentra en estado Agendada; Generar una excepción indicándole al barbero que ya no puede cancelar la cita porque faltan menos de 2 horas para su horaInicio
A77: public | B77: registrarInasistenciaCliente | C77: no static | D77: no final | E77: Permite al barbero indicar que el cliente nunca llegó a la cita | F77: id | G77: Otro | H77: UUID | I77: Por referencia | J77: no final | K77: Corresponde al identificador de la cita a la que el cliente no asistió | L77: Otro | M77: Cita | N77: Informar con un mensaje que no existe una cita con el identificador enviado y por lo tanto no es posible llevar a cabo la operación; Generar una excepción indicándole al barbero que no se puede registrar la inasistencia porque la cita no se encuentra en estado Agendada; Generar una excepción indicándole al barbero que no se puede registrar la inasistencia porque la llegada del cliente ya fue registrada; Si la multa no se puede generar, registrar el error y dejar la inasistencia pendiente de multa

Sheet CitaServicio
A1: <-Volver al inicio
A2: =Clases!$A$1 -> Clase | B2: =Clases!A20 -> CitaServicio
A3: =Clases!$B$1 -> Estereotipo | B3: =Clases!B20 -> class
A4: =Clases!$C$1 -> Desripción | B4: =Clases!C20 -> Representa cada servicio incluido dentro de una cita puntual, guardando el precio y la duración que tenía ese servicio para ese barbero en el momento exacto en que se agendó, para que cambios futuros en el catálogo no alteren citas ya registradas.
A5: Modificador acceso: | B5: public
A6: Tipo clase: | B6: no final
A7: Relaciones
A8: Relación | B8: Tipo relación | E8: Estructura
A9: Necesita de | B9: Composición | E9: =Cita!B2 -> Cita
A10: Necesita de | B10: Composición | E10: =BarberoServicio!B2 -> BarberoServicio
A11: Atributos
A12: Modificador de aceso | B12: Nombre | C12: Tipo de dato | E12: Tipo modificación atributo | F12: Tipo acceso atributo | G12: Valor por defecto | J12: Descripción atributo
C13: Tipo de dato | D13: ¿Cuál?
A14: private | B14: id | C14: Otro | D14: UUID | E14: no final | F14: no static | G14: new UUID(0L, 0L) | J14: Representa un identificador que hará unico cada objeto de dominio de este tipo, no se puede repetir
A15: private | B15: cita | C15: Otro | D15: Cita | E15: no final | F15: no static | G15: new Cita() | J15: Hace referencia a la cita a la que pertenece este servicio pedido
A16: private | B16: barberoServicio | C16: Otro | D16: BarberoServicio | E16: no final | F16: no static | G16: new BarberoServicio() | J16: Hace referencia a qué servicio, de qué barbero específico, se pidió en esta cita. No se referencia el Servicio directamente porque un barbero podría no ofrecerlo
A17: private | B17: precioServicio | C17: int/Integer | E17: no final | F17: no static | G17: 0 | J17: Representa el precio que tenía el servicio en el momento en que se agendó esta cita. Es un dato auto generado: copia de Servicio.precio, para que cambios futuros en el precio del catálogo no alteren una cita ya registrada
A18: private | B18: duracionEnHorasElServicio | C18: int/Integer | E18: no final | F18: no static | G18: 0 | J18: Representa la duración en horas que tenía el servicio para ese barbero en el momento en que se agendó esta cita. Es un dato auto generado: copia de BarberoServicio.duracionServicio
A19: private | B19: duracionEnMinutosElServicio | C19: int/Integer | E19: no final | F19: no static | G19: 0 | J19: Representa la duración en minutos que tenía el servicio para ese barbero en el momento en que se agendó esta cita. Es un dato auto generado: copia de BarberoServicio.duracionServicio
A20: private | B20: tiempoExtra | C20: int/Integer | E20: no final | F20: no static | G20: 0 | J20: Representa el tiempo extra en minutos que ese barbero tenía configurado para este servicio en el momento en que se agendó la cita. Es un dato auto generado: copia de BarberoServicio.tiempoExtra, para que cambios futuros en el tiempo extra no alteren una cita ya registrada
A21: Constructores
A22: Modificador de aceso | B22: Nombre | C22: Tipo constructor | D22: Descripción | E22: Parámetros | M22: Excepciones
E23: Nombre | F23: Tipo de dato | G23: ¿Cuál? | H23: Tipo parámetro | I23: Tipo modificación atributo | J23: Descripción
A24: public | B24: =B2 -> CitaServicio | C24: Defecto | D24: Constructor por defecto que crea un objeto CitaServicio con todos sus atributos en su valor por defecto
A25: public | B25: =B2 -> CitaServicio | C25: Parametrizado | D25: Constructor parametrizado que crea un objeto CitaServicio asignando el valor recibido a cada uno de sus atributos | E25: valorId | F25: Otro | G25: UUID | H25: Por referencia | I25: no final | J25: Valor que se asigna al atributo id
E26: valorCita | F26: Otro | G26: Cita | H26: Por referencia | I26: no final | J26: Valor que se asigna al atributo cita
E27: valorBarberoServicio | F27: Otro | G27: BarberoServicio | H27: Por referencia | I27: no final | J27: Valor que se asigna al atributo barberoServicio
E28: valorPrecioServicio | F28: int/Integer | H28: Por valor | I28: no final | J28: Valor que se asigna al atributo precioServicio
E29: valorDuracionEnHorasElServicio | F29: int/Integer | H29: Por valor | I29: no final | J29: Valor que se asigna al atributo duracionEnHorasElServicio
E30: valorDuracionEnMinutosElServicio | F30: int/Integer | H30: Por valor | I30: no final | J30: Valor que se asigna al atributo duracionEnMinutosElServicio
E31: valorTiempoExtra | F31: int/Integer | H31: Por valor | I31: no final | J31: Valor que se asigna al atributo tiempoExtra
A32: Métodos accesores
A33: Modificador de aceso | B33: Nombre | C33: Tipo método accesor | D33: Tipo modificación método | E33: Descripción | F33: Parámetros | L33: Tipo dato de retorno | N33: Excepciones
F34: Nombre | G34: Tipo de dato | H34: ¿Cuál? | I34: Tipo parámetro | J34: Tipo modificación atributo | K34: Descripción | L34: Tipo de dato | M34: ¿Cuál?
A35: public | B35: getId | C35: getter | D35: no final | E35: Método encargado de obtener el valor del atributo id | L35: Otro | M35: UUID
A36: public | B36: setId | C36: setter | D36: no final | E36: Método encargado de colocar el valor al atributo id | F36: valorId | G36: Otro | H36: UUID | I36: Por referencia | J36: no final | K36: Nuevo valor del atributo id | L36: void
A37: public | B37: getCita | C37: getter | D37: no final | E37: Método encargado de obtener el valor del atributo cita | L37: Otro | M37: Cita
A38: public | B38: setCita | C38: setter | D38: no final | E38: Método encargado de colocar el valor al atributo cita | F38: valorCita | G38: Otro | H38: Cita | I38: Por referencia | J38: no final | K38: Nuevo valor del atributo cita | L38: void
A39: public | B39: getBarberoServicio | C39: getter | D39: no final | E39: Método encargado de obtener el valor del atributo barberoServicio | L39: Otro | M39: BarberoServicio
A40: public | B40: setBarberoServicio | C40: setter | D40: no final | E40: Método encargado de colocar el valor al atributo barberoServicio | F40: valorBarberoServicio | G40: Otro | H40: BarberoServicio | I40: Por referencia | J40: no final | K40: Nuevo valor del atributo barberoServicio | L40: void
A41: public | B41: getPrecioServicio | C41: getter | D41: no final | E41: Método encargado de obtener el valor del atributo precioServicio | L41: int/Integer
A42: public | B42: setPrecioServicio | C42: setter | D42: no final | E42: Método encargado de colocar el valor al atributo precioServicio | F42: valorPrecioServicio | G42: int/Integer | I42: Por valor | J42: no final | K42: Nuevo valor del atributo precioServicio | L42: void
A43: public | B43: getDuracionEnHorasElServicio | C43: getter | D43: no final | E43: Método encargado de obtener el valor del atributo duracionEnHorasElServicio | L43: int/Integer
A44: public | B44: setDuracionEnHorasElServicio | C44: setter | D44: no final | E44: Método encargado de colocar el valor al atributo duracionEnHorasElServicio | F44: valorDuracionEnHorasElServicio | G44: int/Integer | I44: Por valor | J44: no final | K44: Nuevo valor del atributo duracionEnHorasElServicio | L44: void
A45: public | B45: getDuracionEnMinutosElServicio | C45: getter | D45: no final | E45: Método encargado de obtener el valor del atributo duracionEnMinutosElServicio | L45: int/Integer
A46: public | B46: setDuracionEnMinutosElServicio | C46: setter | D46: no final | E46: Método encargado de colocar el valor al atributo duracionEnMinutosElServicio | F46: valorDuracionEnMinutosElServicio | G46: int/Integer | I46: Por valor | J46: no final | K46: Nuevo valor del atributo duracionEnMinutosElServicio | L46: void
A47: public | B47: getTiempoExtra | C47: getter | D47: no final | E47: Método encargado de obtener el valor del atributo tiempoExtra | L47: int/Integer
A48: public | B48: setTiempoExtra | C48: setter | D48: no final | E48: Método encargado de colocar el valor al atributo tiempoExtra | F48: valorTiempoExtra | G48: int/Integer | I48: Por valor | J48: no final | K48: Nuevo valor del atributo tiempoExtra | L48: void
A49: Métodos
A50: Modificador de aceso | B50: Nombre | C50: Tipo acceso método | D50: Tipo modificación método | E50: Descripción | F50: Parámetros | L50: Tipo dato de retorno | N50: Excepciones
F51: Nombre | G51: Tipo de dato | H51: ¿Cuál? | I51: Tipo parámetro | J51: Tipo modificación atributo | K51: Descripción | L51: Tipo de dato | M51: ¿Cuál?
A52: public | B52: consultarServiciosDeCita | C52: no static | D52: no final | E52: Permite ver qué servicios fueron pedidos dentro de una cita puntual | F52: cita | G52: Otro | H52: Cita | I52: Por referencia | J52: no final | K52: Hace referencia a la cita a la que pertenece este servicio pedido (filtro) | L52: Otro | M52: List<CitaServicio> | N52: No aplica
A53: public | B53: consultarPrecioDeCadaServicio | C53: no static | D53: no final | E53: Permite consultar el precio que quedó congelado para cada servicio de una cita en el momento en que se agendó | F53: cita | G53: Otro | H53: Cita | I53: Por referencia | J53: no final | K53: Hace referencia a la cita a la que pertenece este servicio pedido (filtro) | L53: Otro | M53: List<CitaServicio> | N53: No aplica
A54: public | B54: crearCitaServicio | C54: no static | D54: no final | E54: Comando que permite al sistema registrar un servicio pedido dentro de una cita, copiando el precio y la duración vigentes en el momento de agendarla | F54: cita | G54: Otro | H54: Cita | I54: Por referencia | J54: no final | K54: Hace referencia a la cita a la que pertenece este servicio pedido | L54: Otro | M54: CitaServicio | N54: Si los valores no se pueden copiar, no registrar el servicio y revertir el agendamiento de la cita
F55: barberoServicio | G55: Otro | H55: BarberoServicio | I55: Por referencia | J55: no final | K55: Hace referencia a qué servicio, de qué barbero específico, se pidió en esta cita. No se referencia el Servicio directamente porque un barbero podría no ofrecerlo

Sheet Multa
A1: <-Volver al inicio
A2: =Clases!$A$1 -> Clase | B2: =Clases!A21 -> Multa
A3: =Clases!$B$1 -> Estereotipo | B3: =Clases!B21 -> class
A4: =Clases!$C$1 -> Desripción | B4: =Clases!C21 -> Representa la sanción económica que se le impone a un cliente por incumplir una cita, ya sea por llegar tarde fuera de tolerancia o por no presentarse, calculada a partir de la cita específica que la originó.
A5: Modificador acceso: | B5: public
A6: Tipo clase: | B6: no final
A7: Relaciones
A8: Relación | B8: Tipo relación | E8: Estructura
A9: Necesita de | B9: Composición | E9: =Cita!B2 -> Cita
A10: Necesita de | B10: Asociación | E10: =TipoMulta!B2 -> TipoMulta
A11: Atributos
A12: Modificador de aceso | B12: Nombre | C12: Tipo de dato | E12: Tipo modificación atributo | F12: Tipo acceso atributo | G12: Valor por defecto | J12: Descripción atributo
C13: Tipo de dato | D13: ¿Cuál?
A14: private | B14: id | C14: Otro | D14: UUID | E14: no final | F14: no static | G14: new UUID(0L, 0L) | J14: Representa un identificador que hará unico cada objeto de dominio de este tipo, no se puede repetir
A15: private | B15: cita | C15: Otro | D15: Cita | E15: no final | F15: no static | G15: new Cita() | J15: Hace referencia a la cita puntual que el cliente incumplió (llegando tarde fuera de la tolerancia o no presentándose), de esa cita es de donde sale el valor de monto si fue el caso de no presentase
A16: private | B16: tipo | C16: Otro | D16: TipoMulta | E16: no final | F16: no static | G16: new TipoMulta() | J16: Hace referencia al tipo de multa -tardanza o inasistencia- según lo que haya ocurrido con la cita
A17: private | B17: monto | C17: int/Integer | E17: no final | F17: no static | G17: 0 | J17: Representa cuánto dinero en pesos colombianos debe pagar el cliente por esta multa. Es un dato auto generado: si el tipo es Tardanza copia el valor de multa de la Cita incumplida; si el tipo es Inasistencia copia el precioTotal de la Cita incumplida
A18: private | B18: horaGeneracion | C18: Otro | D18: LocalTime | E18: no final | F18: no static | G18: LocalTime.of(0, 0) | J18: Representa la hora en la que el sistema generó esta multa: si es por tardanza, en el momento en que el cliente llega superando la tolerancia; si es por inasistencia, en la hora estimada de finalización de la cita sin que el cliente haya llegado. El día es el mismo día de la agenda de la cita que la originó
A19: private | B19: fechaHoraPago | C19: Otro | D19: LocalDateTime | E19: no final | F19: no static | G19: LocalDateTime.of(1000, 1, 1, 0, 0) | J19: Representa la fecha y hora en la que el cliente pagó esta multa. Su valor por defecto es 01/01/1000 00:00 y es permitido: significa que la multa sigue sin pagar
A20: private | B20: pagada | C20: boolean/Boolean | E20: no final | F20: no static | G20: false | J20: Representa si el cliente ya pagó o no esta multa, es el dato que se revisa para decidir si un cliente queda vetado: mientras tenga una multa sin pagar no puede agendar
A21: Constructores
A22: Modificador de aceso | B22: Nombre | C22: Tipo constructor | D22: Descripción | E22: Parámetros | M22: Excepciones
E23: Nombre | F23: Tipo de dato | G23: ¿Cuál? | H23: Tipo parámetro | I23: Tipo modificación atributo | J23: Descripción
A24: public | B24: =B2 -> Multa | C24: Defecto | D24: Constructor por defecto que crea un objeto Multa con todos sus atributos en su valor por defecto
A25: public | B25: =B2 -> Multa | C25: Parametrizado | D25: Constructor parametrizado que crea un objeto Multa asignando el valor recibido a cada uno de sus atributos | E25: valorId | F25: Otro | G25: UUID | H25: Por referencia | I25: no final | J25: Valor que se asigna al atributo id
E26: valorCita | F26: Otro | G26: Cita | H26: Por referencia | I26: no final | J26: Valor que se asigna al atributo cita
E27: valorTipo | F27: Otro | G27: TipoMulta | H27: Por referencia | I27: no final | J27: Valor que se asigna al atributo tipo
E28: valorMonto | F28: int/Integer | H28: Por valor | I28: no final | J28: Valor que se asigna al atributo monto
E29: valorHoraGeneracion | F29: Otro | G29: LocalTime | H29: Por referencia | I29: no final | J29: Valor que se asigna al atributo horaGeneracion
E30: valorFechaHoraPago | F30: Otro | G30: LocalDateTime | H30: Por referencia | I30: no final | J30: Valor que se asigna al atributo fechaHoraPago
E31: valorPagada | F31: boolean/Boolean | H31: Por valor | I31: no final | J31: Valor que se asigna al atributo pagada
A32: Métodos accesores
A33: Modificador de aceso | B33: Nombre | C33: Tipo método accesor | D33: Tipo modificación método | E33: Descripción | F33: Parámetros | L33: Tipo dato de retorno | N33: Excepciones
F34: Nombre | G34: Tipo de dato | H34: ¿Cuál? | I34: Tipo parámetro | J34: Tipo modificación atributo | K34: Descripción | L34: Tipo de dato | M34: ¿Cuál?
A35: public | B35: getId | C35: getter | D35: no final | E35: Método encargado de obtener el valor del atributo id | L35: Otro | M35: UUID
A36: public | B36: setId | C36: setter | D36: no final | E36: Método encargado de colocar el valor al atributo id | F36: valorId | G36: Otro | H36: UUID | I36: Por referencia | J36: no final | K36: Nuevo valor del atributo id | L36: void
A37: public | B37: getCita | C37: getter | D37: no final | E37: Método encargado de obtener el valor del atributo cita | L37: Otro | M37: Cita
A38: public | B38: setCita | C38: setter | D38: no final | E38: Método encargado de colocar el valor al atributo cita | F38: valorCita | G38: Otro | H38: Cita | I38: Por referencia | J38: no final | K38: Nuevo valor del atributo cita | L38: void
A39: public | B39: getTipo | C39: getter | D39: no final | E39: Método encargado de obtener el valor del atributo tipo | L39: Otro | M39: TipoMulta
A40: public | B40: setTipo | C40: setter | D40: no final | E40: Método encargado de colocar el valor al atributo tipo | F40: valorTipo | G40: Otro | H40: TipoMulta | I40: Por referencia | J40: no final | K40: Nuevo valor del atributo tipo | L40: void
A41: public | B41: getMonto | C41: getter | D41: no final | E41: Método encargado de obtener el valor del atributo monto | L41: int/Integer
A42: public | B42: setMonto | C42: setter | D42: no final | E42: Método encargado de colocar el valor al atributo monto | F42: valorMonto | G42: int/Integer | I42: Por valor | J42: no final | K42: Nuevo valor del atributo monto | L42: void
A43: public | B43: getHoraGeneracion | C43: getter | D43: no final | E43: Método encargado de obtener el valor del atributo horaGeneracion | L43: Otro | M43: LocalTime
A44: public | B44: setHoraGeneracion | C44: setter | D44: no final | E44: Método encargado de colocar el valor al atributo horaGeneracion | F44: valorHoraGeneracion | G44: Otro | H44: LocalTime | I44: Por referencia | J44: no final | K44: Nuevo valor del atributo horaGeneracion | L44: void
A45: public | B45: getFechaHoraPago | C45: getter | D45: no final | E45: Método encargado de obtener el valor del atributo fechaHoraPago | L45: Otro | M45: LocalDateTime
A46: public | B46: setFechaHoraPago | C46: setter | D46: no final | E46: Método encargado de colocar el valor al atributo fechaHoraPago | F46: valorFechaHoraPago | G46: Otro | H46: LocalDateTime | I46: Por referencia | J46: no final | K46: Nuevo valor del atributo fechaHoraPago | L46: void
A47: public | B47: getPagada | C47: getter | D47: no final | E47: Método encargado de obtener el valor del atributo pagada | L47: boolean/Boolean
A48: public | B48: setPagada | C48: setter | D48: no final | E48: Método encargado de colocar el valor al atributo pagada | F48: valorPagada | G48: boolean/Boolean | I48: Por valor | J48: no final | K48: Nuevo valor del atributo pagada | L48: void
A49: Métodos
A50: Modificador de aceso | B50: Nombre | C50: Tipo acceso método | D50: Tipo modificación método | E50: Descripción | F50: Parámetros | L50: Tipo dato de retorno | N50: Excepciones
F51: Nombre | G51: Tipo de dato | H51: ¿Cuál? | I51: Tipo parámetro | J51: Tipo modificación atributo | K51: Descripción | L51: Tipo de dato | M51: ¿Cuál?
A52: public | B52: imponerMultaCliente | C52: no static | D52: no final | E52: Genera automáticamente una multa a un cliente cuando se registra una inasistencia o una tardanza fuera de tolerancia | F52: cita | G52: Otro | H52: Cita | I52: Por referencia | J52: no final | K52: Hace referencia a la cita puntual que el cliente incumplió (llegando tarde fuera de la tolerancia o no presentándose), de esa cita es de donde sale el valor de monto si fue el caso de no presentase | L52: Otro | M52: Multa | N52: Si el tipo de multa y el monto no se pueden congelar, no registrar la multa e informar el error; Si el veto del cliente no se puede actualizar, registrar el error sin revertir la multa
F53: tipo | G53: Otro | H53: TipoMulta | I53: Por referencia | J53: no final | K53: Hace referencia al tipo de multa -tardanza o inasistencia- según lo que haya ocurrido con la cita
A54: public | B54: consultarMultasDeCliente | C54: no static | D54: no final | E54: Permite a un cliente consultar el historial de multas que se le han impuesto | F54: cliente | G54: Otro | H54: Cliente | I54: Por referencia | J54: no final | K54: Cliente por el cual se va a filtrar | L54: Otro | M54: List<Multa> | N54: No aplica
A55: public | B55: registrarPagoMulta | C55: no static | D55: no final | E55: Permite al barbero marcar que un cliente ya pagó una multa pendiente | F55: id | G55: Otro | H55: UUID | I55: Por referencia | J55: no final | K55: Corresponde al identificador de la multa que se va a marcar como pagada | L55: Otro | M55: Multa | N55: Informar con un mensaje que no existe una multa con el identificador enviado y por lo tanto no es posible llevar a cabo la operación; Generar una excepción indicándole al usuario que esa multa ya está pagada
F56: fechaHoraPago | G56: Otro | H56: LocalDateTime | I56: Por referencia | J56: no final | K56: Contiene la fecha y hora en la que el cliente pagó la multa

Sheet RegistroHoraCita
A1: <-Volver al inicio
A2: =Clases!$A$1 -> Clase | B2: =Clases!A22 -> RegistroHoraCita
A3: =Clases!$B$1 -> Estereotipo | B3: =Clases!B22 -> class
A4: =Clases!$C$1 -> Desripción | B4: =Clases!C22 -> Representa cada hora real registrada durante una cita puntual, según el tipo de momento al que corresponde (llegada del cliente, barbero preparado, inicio o fin de la atención).
A5: Modificador acceso: | B5: public
A6: Tipo clase: | B6: no final
A7: Relaciones
A8: Relación | B8: Tipo relación | E8: Estructura
A9: Necesita de | B9: Composición | E9: =Cita!B2 -> Cita
A10: Necesita de | B10: Asociación | E10: =TipoRegistroHora!B2 -> TipoRegistroHora
A11: Atributos
A12: Modificador de aceso | B12: Nombre | C12: Tipo de dato | E12: Tipo modificación atributo | F12: Tipo acceso atributo | G12: Valor por defecto | J12: Descripción atributo
C13: Tipo de dato | D13: ¿Cuál?
A14: private | B14: id | C14: Otro | D14: UUID | E14: no final | F14: no static | G14: new UUID(0L, 0L) | J14: Representa un identificador que hará unico cada objeto de dominio de este tipo, no se puede repetir
A15: private | B15: cita | C15: Otro | D15: Cita | E15: no final | F15: no static | G15: new Cita() | J15: Referencia a qué cita pertenece este registro de hora real
A16: private | B16: tipoRegistroHora | C16: Otro | D16: TipoRegistroHora | E16: no final | F16: no static | G16: new TipoRegistroHora() | J16: Referencia a qué tipo de hora real corresponde este registro
A17: private | B17: hora | C17: Otro | D17: LocalTime | E17: no final | F17: no static | G17: LocalTime.of(0, 0) | J17: Representa la hora real en la que ocurrió el evento registrado
A18: Constructores
A19: Modificador de aceso | B19: Nombre | C19: Tipo constructor | D19: Descripción | E19: Parámetros | M19: Excepciones
E20: Nombre | F20: Tipo de dato | G20: ¿Cuál? | H20: Tipo parámetro | I20: Tipo modificación atributo | J20: Descripción
A21: public | B21: =B2 -> RegistroHoraCita | C21: Defecto | D21: Constructor por defecto que crea un objeto RegistroHoraCita con todos sus atributos en su valor por defecto
A22: public | B22: =B2 -> RegistroHoraCita | C22: Parametrizado | D22: Constructor parametrizado que crea un objeto RegistroHoraCita asignando el valor recibido a cada uno de sus atributos | E22: valorId | F22: Otro | G22: UUID | H22: Por referencia | I22: no final | J22: Valor que se asigna al atributo id
E23: valorCita | F23: Otro | G23: Cita | H23: Por referencia | I23: no final | J23: Valor que se asigna al atributo cita
E24: valorTipoRegistroHora | F24: Otro | G24: TipoRegistroHora | H24: Por referencia | I24: no final | J24: Valor que se asigna al atributo tipoRegistroHora
E25: valorHora | F25: Otro | G25: LocalTime | H25: Por referencia | I25: no final | J25: Valor que se asigna al atributo hora
A26: Métodos accesores
A27: Modificador de aceso | B27: Nombre | C27: Tipo método accesor | D27: Tipo modificación método | E27: Descripción | F27: Parámetros | L27: Tipo dato de retorno | N27: Excepciones
F28: Nombre | G28: Tipo de dato | H28: ¿Cuál? | I28: Tipo parámetro | J28: Tipo modificación atributo | K28: Descripción | L28: Tipo de dato | M28: ¿Cuál?
A29: public | B29: getId | C29: getter | D29: no final | E29: Método encargado de obtener el valor del atributo id | L29: Otro | M29: UUID
A30: public | B30: setId | C30: setter | D30: no final | E30: Método encargado de colocar el valor al atributo id | F30: valorId | G30: Otro | H30: UUID | I30: Por referencia | J30: no final | K30: Nuevo valor del atributo id | L30: void
A31: public | B31: getCita | C31: getter | D31: no final | E31: Método encargado de obtener el valor del atributo cita | L31: Otro | M31: Cita
A32: public | B32: setCita | C32: setter | D32: no final | E32: Método encargado de colocar el valor al atributo cita | F32: valorCita | G32: Otro | H32: Cita | I32: Por referencia | J32: no final | K32: Nuevo valor del atributo cita | L32: void
A33: public | B33: getTipoRegistroHora | C33: getter | D33: no final | E33: Método encargado de obtener el valor del atributo tipoRegistroHora | L33: Otro | M33: TipoRegistroHora
A34: public | B34: setTipoRegistroHora | C34: setter | D34: no final | E34: Método encargado de colocar el valor al atributo tipoRegistroHora | F34: valorTipoRegistroHora | G34: Otro | H34: TipoRegistroHora | I34: Por referencia | J34: no final | K34: Nuevo valor del atributo tipoRegistroHora | L34: void
A35: public | B35: getHora | C35: getter | D35: no final | E35: Método encargado de obtener el valor del atributo hora | L35: Otro | M35: LocalTime
A36: public | B36: setHora | C36: setter | D36: no final | E36: Método encargado de colocar el valor al atributo hora | F36: valorHora | G36: Otro | H36: LocalTime | I36: Por referencia | J36: no final | K36: Nuevo valor del atributo hora | L36: void
A37: Métodos
A38: Modificador de aceso | B38: Nombre | C38: Tipo acceso método | D38: Tipo modificación método | E38: Descripción | F38: Parámetros | L38: Tipo dato de retorno | N38: Excepciones
F39: Nombre | G39: Tipo de dato | H39: ¿Cuál? | I39: Tipo parámetro | J39: Tipo modificación atributo | K39: Descripción | L39: Tipo de dato | M39: ¿Cuál?
A40: public | B40: definirRegistroHoraCita | C40: no static | D40: no final | E40: Comando que permite al barbero registrar, de forma opcional, la hora real de un momento de la cita | F40: cita | G40: Otro | H40: Cita | I40: Por referencia | J40: no final | K40: Referencia a qué cita pertenece este registro de hora real | L40: Otro | M40: RegistroHoraCita | N40: Generar una excepción indicándole al barbero cuáles datos del registro no cumplen con las reglas definidas; Generar una excepción indicándole al barbero que ya existe un registro de ese tipo para la cita; Generar una excepción indicándole al barbero que no se pueden registrar horas en una cita cancelada o con inasistencia; Generar una excepción indicándole al barbero que la hora no es coherente con las demás horas registradas de la cita; Si la multa por tardanza no se puede generar, registrar el error y deshacer el registro; Si el descuento no se puede aplicar, dejar el precioTotal sin cambios y registrar el error
F41: tipoRegistroHora | G41: Otro | H41: TipoRegistroHora | I41: Por referencia | J41: no final | K41: Referencia a qué tipo de hora real corresponde este registro
F42: hora | G42: Otro | H42: LocalTime | I42: Por referencia | J42: no final | K42: Representa la hora real en la que ocurrió el evento registrado
A43: public | B43: cambiarHoraRegistroHoraCita | C43: no static | D43: no final | E43: Permite al barbero corregir la hora de un registro de hora de una cita | F43: id | G43: Otro | H43: UUID | I43: Por referencia | J43: no final | K43: Corresponde al identificador del registro de hora | L43: Otro | M43: RegistroHoraCita | N43: Informar con un mensaje que no existe un registro de hora con el identificador enviado y por lo tanto no se puede realizar la operación; Generar una excepción indicándole al barbero que la hora no cumple con las reglas definidas; Generar una excepción indicándole al barbero que no se pueden cambiar horas de una cita cancelada o con inasistencia; Generar una excepción indicándole al barbero que la hora no es coherente con las demás horas registradas de la cita
F44: hora | G44: Otro | H44: LocalTime | I44: Por referencia | J44: no final | K44: Representa la hora real en la que ocurrió el evento registrado
A45: public | B45: consultarHoraLlegadaCliente | C45: no static | D45: no final | E45: Permite al barbero y al cliente consultar la hora de llegada del cliente en una cita | F45: cita | G45: Otro | H45: Cita | I45: Por referencia | J45: no final | K45: Referencia a qué cita pertenece este registro de hora real (filtro) | L45: Otro | M45: LocalTime | N45: No aplica
A46: public | B46: consultarHoraBarberoPreparado | C46: no static | D46: no final | E46: Permite al barbero y al cliente consultar la hora en que el barbero estuvo preparado en una cita | F46: cita | G46: Otro | H46: Cita | I46: Por referencia | J46: no final | K46: Referencia a qué cita pertenece este registro de hora real (filtro) | L46: Otro | M46: LocalTime | N46: No aplica
A47: public | B47: consultarHoraInicioAtencion | C47: no static | D47: no final | E47: Permite al barbero y al cliente consultar la hora de inicio de la atención en una cita | F47: cita | G47: Otro | H47: Cita | I47: Por referencia | J47: no final | K47: Referencia a qué cita pertenece este registro de hora real (filtro) | L47: Otro | M47: LocalTime | N47: No aplica
A48: public | B48: consultarHoraFinAtencion | C48: no static | D48: no final | E48: Permite al barbero y al cliente consultar la hora de finalización de la atención en una cita | F48: cita | G48: Otro | H48: Cita | I48: Por referencia | J48: no final | K48: Referencia a qué cita pertenece este registro de hora real (filtro) | L48: Otro | M48: LocalTime | N48: No aplica

Sheet Valores
A1: Estereotipo | B1: Relación | C1: Tipo relación | D1: Modificador acceso clase top level | E1: Tipo estructura | F1: Modificador acceso clase top level | G1: Tipo de dato | H1: Tipo acceso | I1: Tipo constructor | J1: Tipo parámetro | K1: Tipo método accesor | L1: Tipo de dato retorno método
A2: class | B2: Necesita de | C2: Asociación | D2: public | E2: final | F2: private | G2: byte/Byte | H2: static | I2: Defecto | J2: Por valor | K2: getter | L2: void
A3: abstract class | B3: Es usada por | C3: Agregación | D3: default | E3: no final | F3: protected | G3: short/Short | H3: no static | I3: Parametrizado | J3: Por referencia | K3: setter | L3: byte/Byte
A4: interface | C4: Composición | F4: default | G4: int/Integer | L4: short/Short
A5: enum | C5: Dependencia | F5: public | G5: long/Long | L5: int/Integer
A6: record | C6: Herencia | G6: float/Float | L6: long/Long
C7: Realización | G7: double/Double | L7: float/Float
G8: char/Character | L8: double/Double
G9: boolean/Boolean | L9: char/Character
G10: String | L10: boolean/Boolean
G11: Date | L11: String
G12: Otro | L12: Date
L13: Otro
