Workbook

Sheet Modelo de Dominio
A1: Ir a objetos de dominio >>>>

Sheet Objetos de Dominio
A1: <<<< Ir al modulo de dominio
A2: Nombre | B2: Descripcion | C2: Linea de vida | D2: Muestreo | E2: Caracterización | F2: Event Storming | G2: Politicas
A3: DiaSemana | B3: Representa cada uno de los días de la semana, incluyendo festivo, que se usa como catálogo para definir los horarios de la barbería y de cada barbero. | C3: 1 | D3: Ir al muestreo | E3: Ir a la caracterización | F3: Ir al Event Storming | G3: Ir a las políticas
A4: Estado | B4: Representa en qué situación puntual se encuentra una cita: agendada, finalizada, cancelada por alguna de las partes, con tardanza del cliente o del barbero, o con inasistencia del cliente. | C4: 1 | D4: Ir al muestreo | E4: Ir a la caracterización | F4: Ir al Event Storming | G4: Ir a las políticas
A5: Servicio | B5: Representa cada tipo de corte o arreglo que ofrece la barbería, definido por el dueño, para que luego cada barbero decida cuáles sabe hacer. | C5: 1 | D5: Ir al muestreo | E5: Ir a la caracterización | F5: Ir al Event Storming | G5: Ir a las políticas
A6: PrefijoCelular | B6: Representa el catálogo de prefijos telefónicos de país que el dueño habilita, y que son los únicos que barberos y clientes pueden usar en su número de celular. | C6: 1 | D6: Ir al muestreo | E6: Ir a la caracterización | F6: Ir al Event Storming | G6: Ir a las políticas
A7: TipoMulta | B7: Representa los tipos de multa que puede recibir un cliente: por tardanza o por inasistencia. | C7: 1 | D7: Ir al muestreo | E7: Ir a la caracterización | F7: Ir al Event Storming | G7: Ir a las políticas
A8: Barbero | B8: Representa a un trabajador de la barbería que atiende clientes según los servicios que sabe realizar, organiza su propio horario y tiene su agenda personal para atender todas las citas que valla teniendo. | C8: 2 | D8: Ir al muestreo | E8: Ir a la caracterización | F8: Ir al Event Storming | G8: Ir a las políticas
A9: Cliente | B9: Representa a la persona que solicita citas en la barbería. | C9: 2 | D9: Ir al muestreo | E9: Ir a la caracterización | F9: Ir al Event Storming | G9: Ir a las políticas
A10: HorarioBarberia | B10: Representa, día por día, a qué hora abre y cierra el negocio; es el límite dentro del cual debe caber el horario de cualquier barbero. | C10: 2 | D10: Ir al muestreo | E10: Ir a la caracterización | F10: Ir al Event Storming | G10: Ir a las políticas
A11: Bloqueo | B11: Representa los momentos en que el barbero no esta disponible para atender sus citas, el barbero establece la hora y la fecha en que empieza y termina ese estado de no disponible. | C11: 3 | D11: Ir al muestreo | E11: Ir a la caracterización | F11: Ir al Event Storming | G11: Ir a las políticas
A12: BarberoServicio | B12: Representa qué servicios sabe hacer cada barbero, cuánto se demora en realizarlos y cuánto tiempo extra usa de colchón, ya que no todos los barberos ofrecen los mismos servicios que están en la barbería. | C12: 3 | D12: Ir al muestreo | E12: Ir a la caracterización | F12: Ir al Event Storming | G12: Ir a las políticas
A13: HorarioBarbero | B13: Representa el día de la semana en que trabaja un barbero, junto con la hora en la que empieza y termina su jornada de trabajo. | C13: 3 | D13: Ir al muestreo | E13: Ir a la caracterización | F13: Ir al Event Storming | G13: Ir a las políticas
A14: Agenda | B14: Representa una fecha puntual en donde el barbero ve todas las citas que debe de atender ese día. | C14: 4 | D14: Ir al muestreo | E14: Ir a la caracterización | F14: Ir al Event Storming | G14: Ir a las políticas
... A17: Multa | B17: Representa la sanción económica que se le impone a un cliente por incumplir una cita, ya sea por llegar tarde fuera de tolerancia o por no presentarse, calculada a partir de la cita específica que la originó. | C17: 6 | D17: Ir al muestreo | E17: Ir a la caracterización | F17: Ir al Event Storming | G17: Ir a las políticas

Sheet C-DiaSemana
A1: <<<< Ir al modulo de dominio | B1: <<<< Ir a objetos de dominio
A2: Nombre atributo | B2: Descripción atributo | C2: Identificador del objeto de dominio | D2: Tipo de dato | E2: Obligatorio | F2: Longitud mínima (si aplica) | G2: Longitud máxima (si aplica) | H2: Precisión (si aplica) | I2: Rendondeo (si aplica) | J2: Rango inicial (si aplica) | K2: Rango final (si aplica) | L2: Formato (si aplica) | M2: Reglas especiales (si aplica) | N2: Dato calculado | O2: Aplica ajuste del dato (si aplica) | P2: Carácter de ajuste (si aplica) | Q2: Quitar espacios en blanco al inicio (si aplica) | R2: Quitar espacios en blanco al fin (si aplica) | S2: Dato sensible (si aplica) | T2: Valor por defecto (si aplica) | U2: Auto generado | V2: =A11 -> VerDiasDeLaSemana
A3: ='M-DiaSemana'!A3 -> id | B3: ='M-DiaSemana'!A2 -> Representa un identificador que hará unico cada objeto de dominio de este tipo, no se puede repetir | C3: Si | D3: Identificador único universal | E3: Si | F3: No aplica | G3: No aplica | H3: No aplica | I3: No aplica | J3: No aplica | K3: No aplica | L3: No aplica | M3: No aplica | N3: No | O3: No aplica | P3: No aplica | Q3: No aplica | R3: No aplica | S3: No | T3: UUID vacio | U3: Si | V3: No mostrar
A4: ='M-DiaSemana'!B3 -> nombre | B4: ='M-DiaSemana'!B2 -> Representa como se llama el dia de la semana, para los horarios | C4: No | D4: Alfanumérico | E4: Si | F4: 5 | G4: 9 | H4: No aplica | I4: No aplica | J4: No aplica | K4: No aplica | L4: No aplica | M4: Solo pueden ser los dias de la semana como Lunes, Martes, Miércoles, Jueves, Viernes, Sábado, Domingo y Festivo | N4: No | O4: No aplica | P4: No aplica | Q4: Si | R4: Si | S4: No | T4: Vacio | U4: No | V4: Mostrar
A6: Nombre combinación única | B6: Descripción | C6: Atributos involucrados
A7: ='M-DiaSemana'!C3 -> Combinación única | B7: ='M-DiaSemana'!C2 -> Combinacion única que indica que no puede existir más un dia de la semana con el mismo nombre | C7: nombre
A9: Responsabilidad | C9: Descripción | G9: Entradas | J9: Salida | O9: Políticas (Reglas de Negocio) | Q9: Excepción
G10: Parámetro | H10: Tipo de dato | I10: Descripción | J10: Tipo de Dato | K10: Descripción | O10: Política | P10: Descripción | Q10: Detalle | R10: ¿Qué hago?
A11: VerDiasDeLaSemana | C11: Permite consultar el catálogo de días de la semana, incluyendo festivo, para definir los horarios | J11: Lista<DiaSemana> | K11: Contiene todos los días de la semana

Sheet P-DiaSemana
A1: << Ir al modelo de dominio | B1: << Ir al listado de objetos de dominio | C1: << Ir a la caracterización del objeto de dominio | D1: Ir al muestreo de datos del objeto de dominio >> | E1: Ir al event storming del objeto de dominio >>
A2: Objeto de Dominio: | B2: ='Objetos de Dominio'!A3 -> DiaSemana
A3: Descripción: | B3: ='Objetos de Dominio'!B3 -> Representa cada uno de los días de la semana, incluyendo festivo, que se usa como catálogo para definir los horarios de la barbería y de cada barbero.
A4: Numero politica | B4: Descripcion politica | D4: Objeto responsable | E4: Regla responsable
B6: No aplica: es un catálogo de solo lectura, sin comandos que impliquen políticas de negocio propias

Sheet E-DiaSemana
A1: << Ir al modelo de dominio | C1: << Ir al listado de objetos de dominio | F1: << Ir a la caracterización del objeto de dominio | J1: Ir al muestreo de datos del objeto de dominio >>
A2: Objeto de Dominio: | B2: ='Objetos de Dominio'!A3 -> DiaSemana
A3: Descripción: | B3: ='Objetos de Dominio'!B3 -> Representa cada uno de los días de la semana, incluyendo festivo, que se usa como catálogo para definir los horarios de la barbería y de cada barbero.
A4: Actor | B4: Action/Command | D4: Entity/Aggregate/Object domain | E4: Read Model | G4: Business Rule/Policy | I4: External System | J4: Domain Event | K4: Hotspot/questions/Risk
A5: Actor | B5: Acción | C5: Descripción | D5: Objeto de dominio | E5: Información externa | G5: Políticas | I5: Sistema Externo | J5: Evento | K5: Aspectos por solucionar
E6: Información | F6: Descripción | G6: Número | H6: Descripción
A7: Dueño | B7: Ver los días de las semanas | C7: Permite consultar el catálogo de días de la semana, incluyendo festivo, disponibles para definir horarios | D7: =$B$2 -> DiaSemana | J7: Días de la semana consultados
A8: Barbero | B8: Ver los días de las semanas | C8: Permite consultar el catálogo de días de la semana, incluyendo festivo, disponibles para definir horarios | D8: =$B$2 -> DiaSemana | J8: Días de la semana consultados

Sheet M-DiaSemana
A1: <<<< Ir al modulo de dominio | B1: <<<< Ir a objetos de dominio
A2: Representa un identificador que hará unico cada objeto de dominio de este tipo, no se puede repetir | B2: Representa como se llama el dia de la semana, para los horarios | C2: Combinacion única que indica que no puede existir más un dia de la semana con el mismo nombre
A3: id | B3: nombre | C3: Combinación única
A4: 1 | B4: Lunes | C4: =B4 -> Lunes
A5: 2 | B5: Martes | C5: =B5 -> Martes
A6: 3 | B6: Miércoles | C6: =B6 -> Miércoles
A7: 4 | B7: Jueves | C7: =B7 -> Jueves
A8: 5 | B8: Viernes | C8: =B8 -> Viernes
A9: 6 | B9: Sábado | C9: =B9 -> Sábado
A10: 7 | B10: Domingo | C10: =B10 -> Domingo
A11: 8 | B11: Festivo | C11: =B11 -> Festivo
B17: Corresponde a la descripcion de los atributos
B18: Corresponde al identificador unico del objeto de dominio
B19: Corresponde a los datos que ingresa el usuario
B20: Corresponde a la combinacion única

Sheet C-Estado
A1: <<<< Ir al modulo de dominio | B1: <<<< Ir a objetos de dominio
A2: Nombre atributo | B2: Descripción atributo | C2: Identificador del objeto de dominio | D2: Tipo de dato | E2: Obligatorio | F2: Longitud mínima (si aplica) | G2: Longitud máxima (si aplica) | H2: Precisión (si aplica) | I2: Rendondeo (si aplica) | J2: Rango inicial (si aplica) | K2: Rango final (si aplica) | L2: Formato (si aplica) | M2: Reglas especiales (si aplica) | N2: Dato calculado | O2: Aplica ajuste del dato (si aplica) | P2: Carácter de ajuste (si aplica) | Q2: Quitar espacios en blanco al inicio (si aplica) | R2: Quitar espacios en blanco al fin (si aplica) | S2: Dato sensible (si aplica) | T2: Valor por defecto (si aplica) | U2: Auto generado | V2: =A12 -> consultarTodosLosEstados | W2: =A13 -> editarDescripcion | Y2: =A15 -> consultarDescripcion
A3: ='M-Estado'!A3 -> id | B3: ='M-Estado'!A2 -> Representa un identificador que hará unico cada objeto de dominio de este tipo, no se puede repetir | C3: Si | D3: Identificador único universal | E3: Si | F3: No aplica | G3: No aplica | H3: No aplica | I3: No aplica | J3: No aplica | K3: No aplica | L3: No aplica | M3: No aplica | N3: No | O3: No aplica | P3: No aplica | Q3: No aplica | R3: No aplica | S3: No aplica | T3: UUID vacio | U3: Si | V3: No mostrar | W3: Requerido | X3: No modificable | Y3: No mostrar
A4: ='M-Estado'!B3 -> nombre | B4: ='M-Estado'!B2 -> Representa como se llama el estado en el que se encuentra una cita puntual | C4: No | D4: Alfanumérico | E4: Si | F4: 4 | G4: 50 | H4: No aplica | I4: No aplica | J4: No aplica | K4: No aplica | L4: No aplica | M4: Solo se aceptan caracteres de letras de la 'a' a la 'z' y espacios en blanco | N4: No | O4: No aplica | P4: No aplica | Q4: Si | R4: Si | S4: No | T4: Vacio | U4: No | V4: Mostrar | W4: No requerido | X4: No modificable | Y4: No mostrar
A5: ='M-Estado'!C3 -> descripcion | B5: ='M-Estado'!C2 -> Representa el significado de que representa cada estado para la cita | C5: No | D5: Alfanumérico | E5: Si | F5: 10 | G5: 300 | H5: No aplica | I5: No aplica | J5: No aplica | K5: No aplica | L5: No aplica | M5: Solo se aceptan caracteres de letras de la 'a' a la 'z', caracteres con tilde y espacios en blanco | N5: No | O5: No aplica | P5: No aplica | Q5: Si | R5: Si | S5: No | T5: Vacio | U5: No | V5: No mostrar | W5: Requerido | X5: Modificable | Y5: Mostrar
A7: Nombre combinación única | B7: Descripción | C7: Atributos involucrados
A8: ='M-Estado'!D3 -> Combinación única | B8: ='M-Estado'!D2 -> Combinacion única que indica que no puede existir más un dia de la semana con el mismo nombre | C8: nombre
A10: Responsabilidad | C10: Descripción | G10: Entradas | J10: Salida | O10: Políticas (Reglas de Negocio) | Q10: Excepción
G11: Parámetro | H11: Tipo de dato | I11: Descripción | J11: Tipo de Dato | K11: Descripción | O11: Política | P11: Descripción | Q11: Detalle | R11: ¿Qué hago?
A12: consultarTodosLosEstados | C12: Permite consultar los estados posibles que puede tener una cita | J12: Lista<Estado> | K12: Contiene todos los estados que cumplen con el filtro enviado
A13: editarDescripcion | C13: Permite ajustar el texto descriptivo de un estado ya creado, sin cambiar su significado en el flujo de la cita | G13: id | H13: UUID | I13: Corresponde al identificador del estado que se va a editar | K13: La descripcion del estado se editó | O13: ='P-Estado'!A7 -> P-EST-0002 | P13: ='P-Estado'!B7 -> Asegurar que exista el estado con el id enviado | Q13: Informar con un mensaje que no existe un Estado con el identificador enviado y por lo tanto no es posible modificar la descripción | R13: Detener ejecución de la operación
G14: datos{descripcion} | H14: Estado | I14: Contiene la nueva descripción del estado | O14: ='P-Estado'!A6 -> P-EST-0001 | P14: ='P-Estado'!B6 -> Asegurar que los datos requeridos (descripción) sean válidos en tipo de dato, longitud, formato y rango | Q14: Generar una excepción indicándole al usuario cuáles datos de la descripción del estado no cumplen con las reglas definidas | R14: Detener operación
A15: consultarDescripcion | C15: Permite consultar la descripcion de un estado en especifico | G15: datos{nombre} | H15: Estado | I15: Contiene el nombre del estado | J15: String | K15: Contiene la información del estado consultado por su identificador | O15: ='P-Estado'!A7 -> P-EST-0002 | P15: ='P-Estado'!B7 -> Asegurar que exista el estado con el id enviado | Q15: Informar con un mensaje que no existe un Estado con el identificador enviado y por lo tanto no es posible modificar la descripción | R15: Detener ejecución de la operación

Sheet P-Estado
A1: << Ir al modelo de dominio | B1: << Ir al listado de objetos de dominio | C1: << Ir a la caracterización del objeto de dominio | D1: Ir al muestreo de datos del objeto de dominio >> | E1: Ir al event storming del objeto de dominio >>
A2: Objeto de Dominio: | B2: ='Objetos de Dominio'!A4 -> Estado
A3: Descripción: | B3: ='Objetos de Dominio'!B4 -> Representa en qué situación puntual se encuentra una cita: agendada, finalizada, cancelada por alguna de las partes, con tardanza del cliente o del barbero, o con inasistencia del cliente.
A4: Numero politica | B4: Descripcion politica | D4: Objeto responsable | E4: Regla responsable
A6: P-EST-0001 | B6: Asegurar que los datos requeridos (descripción) sean válidos en tipo de dato, longitud, formato y rango | D6: Estado
A7: P-EST-0002 | B7: Asegurar que exista el estado con el id enviado | D7: Estado

Sheet E-Estado
A1: << Ir al modelo de dominio | C1: << Ir al listado de objetos de dominio | F1: << Ir a la caracterización del objeto de dominio | J1: Ir al muestreo de datos del objeto de dominio >>
A2: Objeto de Dominio: | B2: ='Objetos de Dominio'!A4 -> Estado
A3: Descripción: | B3: ='Objetos de Dominio'!B4 -> Representa en qué situación puntual se encuentra una cita: agendada, finalizada, cancelada por alguna de las partes, con tardanza del cliente o del barbero, o con inasistencia del cliente.
A4: Actor | B4: Action/Command | D4: Entity/Aggregate/Object domain | E4: Read Model | G4: Business Rule/Policy | I4: External System | J4: Domain Event | K4: Hotspot/questions/Risk
A5: Actor | B5: Acción | C5: Descripción | D5: Objeto de dominio | E5: Información externa | G5: Políticas | I5: Sistema Externo | J5: Evento | K5: Aspectos por solucionar
E6: Información | F6: Descripción | G6: Número | H6: Descripción
A7: Dueño | B7: Ver estados de las citas | C7: Permite consultar los estados posibles que puede tener una cita | D7: =$B$2 -> Estado | J7: Estados consultados
A8: Barbero | B8: Ver estados de las citas | C8: Permite consultar los estados posibles que puede tener una cita | D8: =$B$2 -> Estado | J8: Estados consultados
A9: Cliente | B9: Ver estados de las citas | C9: Permite consultar los estados posibles que puede tener una cita | D9: =$B$2 -> Estado | J9: Estados consultados
A10: Dueño | B10: Editar descripción del estado | C10: Permite ajustar el texto descriptivo de un estado ya creado, sin cambiar su significado en el flujo de la cita | D10: =$B$2 -> Estado | G10: ='P-Estado'!A6 -> P-EST-0001 | H10: ='P-Estado'!B6 -> Asegurar que los datos requeridos (descripción) sean válidos en tipo de dato, longitud, formato y rango | J10: Descripción de estado actualizada
A11: Dueño | B11: Ver descripcion de un estado | C11: Permite consultar la descripcion de un estado en especifico | D11: =$B$2 -> Estado | J11: Descripción del estado consultada
A12: Barbero | B12: Ver descripcion de un estado | C12: Permite consultar la descripcion de un estado en especifico | D12: =$B$2 -> Estado | J12: Descripción del estado consultada
A13: Cliente | B13: Ver descripcion de un estado | C13: Permite consultar la descripcion de un estado en especifico | D13: =$B$2 -> Estado | J13: Descripción del estado consultada

Sheet M-Estado
A1: <<<< Ir al modulo de dominio | B1: <<<< Ir a objetos de dominio
A2: Representa un identificador que hará unico cada objeto de dominio de este tipo, no se puede repetir | B2: Representa como se llama el estado en el que se encuentra una cita puntual | C2: Representa el significado de que representa cada estado para la cita | D2: Combinacion única que indica que no puede existir más un dia de la semana con el mismo nombre
A3: id | B3: nombre | C3: descripcion | D3: Combinación única
A4: 1 | B4: Agendada | C4: La cita quedó registrada en la agenda del barbero y está a la espera de la fecha y hora acordadas. | D4: =B4 -> Agendada
A5: 2 | B5: Finalizada | C5: El barbero atendió al cliente y el servicio contratado se prestó por completo, sin tener ninguna sanción. | D5: =B5 -> Finalizada
A6: 3 | B6: Cancelada por el cliente | C6: El cliente decidió no asistir y anuló la cita antes de la fecha y hora programada. | D6: =B6 -> Cancelada por el cliente
A7: 4 | B7: Cancelada por el barbero | C7: El barbero anuló la cita antes de la fecha y hora programada, por ejemplo por una eventualidad. | D7: =B7 -> Cancelada por el barbero
A8: 5 | B8: El cliente se demoro | C8: El cliente llegó después de la hora acordada superando el tiempoEspera definido en la cita, lo que genera una multa de tipo Tardanza. | D8: =B8 -> El cliente se demoro
A9: 6 | B9: El barbero se demoro | C9: El barbero se demoró más de lo previsto en una cita anterior y empezó a atender al cliente superando el tiempoEspera definido en la cita, lo que le da un descuento al cliente. | D9: =B9 -> El barbero se demoro
A10: 7 | B10: Inasistencia del cliente | C10: El cliente nunca llegó a la cita: se alcanzó la hora estimada de finalización sin registrar su llegada, lo que genera una multa por el valor total de los servicios pedidos. | D10: =B10 -> Inasistencia del cliente
A11: 8 | B11: Cancelación | C11: La cita se anuló automáticamente porque la barbería cambió sus políticas de horario: al desactivarse el horario de la barbería se desactivaron los horarios de barbero y las agendas que dependían de él, y las citas que quedaron por fuera se cancelaron. | D11: =B11 -> Cancelación
B17: Corresponde a la descripcion de los atributos
B18: Corresponde al identificador unico del objeto de dominio
B19: Corresponde a los datos que ingresa el usuario
B20: Corresponde a la combinacion única

Sheet C-Servicio
A1: <<<< Ir al modulo de dominio | B1: <<<< Ir a objetos de dominio
A2: Nombre atributo | B2: Descripción atributo | C2: Identificador del objeto de dominio | D2: Tipo de dato | E2: Obligatorio | F2: Longitud mínima (si aplica) | G2: Longitud máxima (si aplica) | H2: Precisión (si aplica) | I2: Rendondeo (si aplica) | J2: Rango inicial (si aplica) | K2: Rango final (si aplica) | L2: Formato (si aplica) | M2: Reglas especiales (si aplica) | N2: Dato calculado | O2: Aplica ajuste del dato (si aplica) | P2: Carácter de ajuste (si aplica) | Q2: Quitar espacios en blanco al inicio (si aplica) | R2: Quitar espacios en blanco al fin (si aplica) | S2: Dato sensible (si aplica) | T2: Valor por defecto (si aplica) | U2: Auto generado
A3: ='M-Servicio'!A3 -> id | B3: ='M-Servicio'!A2 -> Representa un identificador que hará unico cada objeto de dominio de este tipo, no se puede repetir | C3: Si | D3: Identificador único universal | E3: Si | F3: No aplica | G3: No aplica | H3: No aplica | I3: No aplica | J3: No aplica | K3: No aplica | L3: No aplica | M3: No aplica | N3: No | O3: No aplica | P3: No aplica | Q3: No aplica | R3: No aplica | S3: No | T3: UUID vacio | U3: Si
A4: ='M-Servicio'!B3 -> nombre | B4: ='M-Servicio'!B2 -> Representa el nombre del servicio que va estar en la barberia, para que el barbero elija los servicios que el sabe hacer | C4: No | D4: Alfanumérico | E4: Si | F4: 3 | G4: 50 | H4: No aplica | I4: No aplica | J4: No aplica | K4: No aplica | L4: No aplica | M4: Solo se aceptan caracteres de letras de la 'a' a la 'z' y caracteres con tilde | N4: No | O4: No aplica | P4: No aplica | Q4: Si | R4: Si | S4: No | T4: Vacio | U4: No
A5: ='M-Servicio'!C3 -> descripcion | B5: ='M-Servicio'!C2 -> Representa una descripcion de que va a hacer cada servicio en la barberia, para que el barbero sepa que hace el servicio | C5: No | D5: Alfanumérico | E5: No | F5: 0 | G5: 200 | H5: No aplica | I5: No aplica | J5: No aplica | K5: No aplica | L5: No aplica | M5: Solo se aceptan caracteres de letras de la 'a' a la 'z', caracteres con tilde y espacios en blanco | N5: No | O5: No aplica | P5: No aplica | Q5: Si | R5: Si | S5: No | T5: Vacio | U5: No
A6: ='M-Servicio'!D3 -> precio | B6: ='M-Servicio'!D2 -> Representa cuanto va a valer el servicio en pesos colombianos | C6: No | D6: Entero | E6: Si | F6: No aplica | G6: No aplica | H6: No aplica | I6: No aplica | J6: 0 | K6: 2000000 | L6: No aplica | M6: No aplica | N6: No | O6: No aplica | P6: No aplica | Q6: No aplica | R6: No aplica | S6: No | T6: 0 | U6: No
A7: ='M-Servicio'!E3 -> disponible | B7: ='M-Servicio'!E2 -> Representa si el servicio sigue o no disponible en la barberia | C7: No | D7: Lógico | E7: No | F7: No aplica | G7: No aplica | H7: No aplica | I7: No aplica | J7: No aplica | K7: No aplica | L7: No aplica | M7: No aplica | N7: No | O7: No aplica | P7: No aplica | Q7: No aplica | R7: No aplica | S7: No | T7: Si | U7: No
A9: Nombre combinación única | B9: Descripción | C9: Atributos involucrados
A10: ='M-Servicio'!F3 -> Combinacion única | B10: ='M-Servicio'!F2 -> Combinacion única que indica que no puede existir más de un servicio con el mismo nombre | C10: =A4 -> nombre
A12: Responsabilidad | C12: Descripción | G12: Entradas | J12: Salida | O12: Políticas (Reglas de Negocio) | Q12: Excepción
G13: Parámetro | H13: Tipo de dato | I13: Descripción | J13: Tipo de Dato | K13: Descripción | O13: Política | P13: Descripción | Q13: Detalle | R13: ¿Qué hago?
A14: Ofrecer un servicio nuevo a la barbería | C14: Comando que permite registrar un nuevo tipo de servicio que la barbería pondrá a disposición de los barberos | G14: datos{nombre, descripcion, precio} | H14: Servicio | I14: Contiene la información requerida para registrar un nuevo servicio de la barbería | J14: Servicio | K14: Contiene la información del servicio registrado | O14: ='P-Servicio'!A6 -> P-SER-0001 | P14: ='P-Servicio'!B6 -> Asegurar que los datos requeridos del servicio (nombre, descripción, precio) sean válidos en tipo de dato, longitud, obligatoriedad, formato y rango | Q14: Generar una excepción indicándole al usuario cuáles datos del servicio no cumplen con las reglas definidas | R14: Detener operación
O15: ='P-Servicio'!A7 -> P-SER-0002 | P15: ='P-Servicio'!B7 -> Asegurar que no exista otro servicio registrado con el mismo nombre en la barbería | Q15: Generar una excepción indicándole al usuario que ya existe un servicio registrado con ese mismo nombre en la barbería | R15: Detener operación
A16: Editar un servicio | C16: Permite modificar todos los atibutos de un servicio, que son el nombre, la descripción y el precio | G16: id | H16: UUID | I16: Corresponde al identificador del servicio que se va a editar | J16: Servicio | K16: Contiene la información del servicio con sus datos actualizados | O16: ='P-Servicio'!A6 -> P-SER-0001 | P16: ='P-Servicio'!B6 -> Asegurar que los datos requeridos del servicio (nombre, descripción, precio) sean válidos en tipo de dato, longitud, obligatoriedad, formato y rango | Q16: Generar una excepción indicándole al usuario cuáles datos del servicio no cumplen con las reglas definidas | R16: Detener operación
G17: datos{nombre, descripcion, precio} | H17: Servicio | I17: Contiene los datos con los que se va a modificar el servicio | O17: ='P-Servicio'!A7 -> P-SER-0002 | P17: ='P-Servicio'!B7 -> Asegurar que no exista otro servicio registrado con el mismo nombre en la barbería | Q17: Generar una excepción indicándole al usuario que ya existe un servicio registrado con ese mismo nombre en la barbería | R17: Detener operación
A18: Ver servicios disponibles de la barbería | C18: Permite consultar el catálogo de servicios que ofrece la barbería | G18: filtro | H18: Servicio | I18: Contiene los filtros de consulta del catálogo de servicios | J18: Lista<Servicio> | K18: Contiene todos los servicios que cumplen con el filtro enviado
A19: Retirar un servicio de la barbería | C19: Permite dar de baja un servicio para que deje de ofrecerse a nuevos clientes | G19: id | H19: UUID | I19: Corresponde al identificador del servicio que se va a retirar | K19: No retorna ningún valor. En caso de error genera una excepción. | O19: ='P-Servicio'!A8 -> P-SER-0003 | P19: ='P-Servicio'!B8 -> Asegurar que el servicio a retirar no esté siendo ofrecido actualmente por ningún barbero vigente | Q19: Generar una excepción indicándole al usuario que el servicio no se puede retirar porque todavía lo ofrece al menos un barbero vigente | R19: Detener operación

Sheet P-Servicio
A1: << Ir al modelo de dominio | B1: << Ir al listado de objetos de dominio | C1: << Ir a la caracterización del objeto de dominio | D1: Ir al muestreo de datos del objeto de dominio >> | E1: Ir al event storming del objeto de dominio >>
A2: Objeto de Dominio: | B2: ='Objetos de Dominio'!A5 -> Servicio
A3: Descripción: | B3: ='Objetos de Dominio'!B5 -> Representa cada tipo de corte o arreglo que ofrece la barbería, definido por el dueño, para que luego cada barbero decida cuáles sabe hacer.
A4: Numero politica | B4: Descripcion politica | D4: Objeto responsable | E4: Regla responsable
A6: P-SER-0001 | B6: Asegurar que los datos requeridos del servicio (nombre, descripción, precio) sean válidos en tipo de dato, longitud, obligatoriedad, formato y rango | D6: Servicio
A7: P-SER-0002 | B7: Asegurar que no exista otro servicio registrado con el mismo nombre en la barbería | D7: Servicio
A8: P-SER-0003 | B8: Asegurar que el servicio a retirar no esté siendo ofrecido actualmente por ningún barbero vigente | D8: BarberoServicio

Sheet E-Servicio
A1: << Ir al modelo de dominio | C1: << Ir al listado de objetos de dominio | F1: << Ir a la caracterización del objeto de dominio | J1: Ir al muestreo de datos del objeto de dominio >>
A2: Objeto de Dominio: | B2: ='Objetos de Dominio'!A5 -> Servicio
A3: Descripción: | B3: ='Objetos de Dominio'!B5 -> Representa cada tipo de corte o arreglo que ofrece la barbería, definido por el dueño, para que luego cada barbero decida cuáles sabe hacer.
A4: Actor | B4: Action/Command | D4: Entity/Aggregate/Object domain | E4: Read Model | G4: Business Rule/Policy | I4: External System | J4: Domain Event | K4: Hotspot/questions/Risk
A5: Actor | B5: Acción | C5: Descripción | D5: Objeto de dominio | E5: Información externa | G5: Políticas | I5: Sistema Externo | J5: Evento | K5: Aspectos por solucionar
E6: Información | F6: Descripción | G6: Número | H6: Descripción
A7: Dueño | B7: Ofrecer un servicio nuevo a la barbería | C7: Comando que permite registrar un nuevo tipo de servicio que la barbería pondrá a disposición de los barberos | D7: =$B$2 -> Servicio | G7: ='P-Servicio'!A6 -> P-SER-0001 | H7: aquí | J7: Servicio ofrecido
G8: ='P-Servicio'!A7 -> P-SER-0002 | H8: aquí
A9: Dueño | B9: Editar un servicio | C9: Permite modificar todos los atibutos de un servicio, que son el nombre, la descripción y el precio | D9: =$B$2 -> Servicio | G9: ='P-Servicio'!A6 -> P-SER-0001 | H9: aquí | J9: Nombre, descripción, precio del servicio actualizados
G10: ='P-Servicio'!A7 -> P-SER-0002 | H10: aquí
A11: Dueño | B11: Ver servicios disponibles de la barbería | C11: Permite consultar el catálogo de servicios que ofrece la barbería | D11: =$B$2 -> Servicio | J11: Servicios consultados
A12: Barbero | B12: Ver servicios disponibles de la barbería | C12: Permite consultar el catálogo de servicios que ofrece la barbería | D12: =$B$2 -> Servicio | J12: Servicios consultados
A13: Cliente | B13: Ver servicios disponibles de la barbería | C13: Permite consultar el catálogo de servicios que ofrece la barbería | D13: =$B$2 -> Servicio | J13: Servicios consultados
A14: Dueño | B14: Retirar un servicio de la barbería | C14: Permite dar de baja un servicio para que deje de ofrecerse a nuevos clientes | D14: =$B$2 -> Servicio | G14: ='P-Servicio'!A8 -> P-SER-0003 | H14: aquí | J14: Servicio retirado

Sheet M-Servicio
A1: <<<< Ir al modulo de dominio | B1: <<<< Ir a objetos de dominio
A2: Representa un identificador que hará unico cada objeto de dominio de este tipo, no se puede repetir | B2: Representa el nombre del servicio que va estar en la barberia, para que el barbero elija los servicios que el sabe hacer | C2: Representa una descripcion de que va a hacer cada servicio en la barberia, para que el barbero sepa que hace el servicio | D2: Representa cuanto va a valer el servicio en pesos colombianos | E2: Representa si el servicio sigue o no disponible en la barberia | F2: Combinacion única que indica que no puede existir más de un servicio con el mismo nombre
A3: id | B3: nombre | C3: descripcion | D3: precio | E3: disponible | F3: Combinacion única
A4: 1 | B4: Motilada | C4: Corte de cabello completo con máquina y tijera, incluye lavado y secado | D4: 22000 | E4: si | F4: =B4 -> Motilada
A5: 2 | B5: Corte de barba | C5: Recorte de la barba con máquina para dejarla pareja y a la medida que pide el cliente | D5: 12000 | E5: si | F5: =B5 -> Corte de barba
A6: 3 | B6: Perfilada de barba | C6: Delineado de los bordes de la barba y el bigote con navaja, sin recortar el largo | D6: 15000 | E6: si | F6: =B6 -> Perfilada de barba
A7: 4 | B7: Arreglo completo de barba con toalla caliente | C7: Recorte, perfilado con navaja, toalla caliente, exfoliación y aceite para la barba | D7: 35000 | E7: si | F7: =B7 -> Arreglo completo de barba con toalla caliente
B13: Corresponde a la descripcion de los atributos
B14: Corresponde al identificador unico del objeto de dominio
B15: Corresponde a los datos que ingresa el usuario
B16: Corresponde a la combinacion única

Sheet C-PrefijoCelular
A1: <<<< Ir al modulo de dominio | B1: <<<< Ir a objetos de dominio
A2: Nombre atributo | B2: Descripción atributo | C2: Identificador del objeto de dominio | D2: Tipo de dato | E2: Obligatorio | F2: Longitud mínima (si aplica) | G2: Longitud máxima (si aplica) | H2: Precisión (si aplica) | I2: Rendondeo (si aplica) | J2: Rango inicial (si aplica) | K2: Rango final (si aplica) | L2: Formato (si aplica) | M2: Reglas especiales (si aplica) | N2: Dato calculado | O2: Aplica ajuste del dato (si aplica) | P2: Carácter de ajuste (si aplica) | Q2: Quitar espacios en blanco al inicio (si aplica) | R2: Quitar espacios en blanco al fin (si aplica) | S2: Dato sensible (si aplica) | T2: Valor por defecto (si aplica) | U2: Auto generado
A3: ='M-PrefijoCelular'!A3 -> id | B3: ='M-PrefijoCelular'!A2 -> Representa un identificador que hará unico cada objeto de dominio de este tipo, no se puede repetir | C3: Si | D3: Identificador único universal | E3: Si | F3: No aplica | G3: No aplica | H3: No aplica | I3: No aplica | J3: No aplica | K3: No aplica | L3: No aplica | M3: No aplica | N3: No | O3: No | P3: No aplica | Q3: No | R3: No | S3: No | T3: No aplica | U3: Si
A4: ='M-PrefijoCelular'!B3 -> prefijo | B4: ='M-PrefijoCelular'!B2 -> Representa el prefijo telefónico del país que el dueño habilita para que la barbería pueda atender números de ese país | C4: No | D4: Alfanumérico | E4: Si | F4: 2 | G4: 6 | H4: No aplica | I4: No aplica | J4: No aplica | K4: No aplica | L4: Simbolo + seguido de un número. Por ejemplo +57. Tambien el anterior puede ser seguido de un - y un numero. Por ejemplo +1-809 | M4: Solo se aceptan caracteres numericos del 0 al 9 y el carácter '+' y '-' | N4: No | O4: No | P4: No aplica | Q4: Si | R4: Si | S4: No | T4: +0 | U4: No
A6: Nombre combinación única | B6: Descripción | C6: Atributos involucrados
A7: ='M-PrefijoCelular'!C3 -> Combinación única | B7: ='M-PrefijoCelular'!C2 -> Combinacion única que indica que no puede existir más un mismo prefijo | C7: prefijo
A9: Responsabilidad | C9: Descripción | G9: Entradas | J9: Salida | O9: Políticas (Reglas de Negocio) | Q9: Excepción
G10: Parámetro | H10: Tipo de dato | I10: Descripción | J10: Tipo de Dato | K10: Descripción | O10: Política | P10: Descripción | Q10: Detalle | R10: ¿Qué hago?
A11: Registrar un prefijo de celular | C11: Comando que permite al dueño habilitar el prefijo de un país cuyos números va a atender la barbería | G11: datos{prefijo} | H11: PrefijoCelular | I11: Contiene la información requerida para habilitar un nuevo prefijo de país | J11: PrefijoCelular | K11: Contiene la información del prefijo de celular registrado | O11: ='P-PrefijoCelular'!A6 -> P-PRE-0001 | P11: ='P-PrefijoCelular'!B6 -> Asegurar que los datos requeridos (prefijo) sean válidos en tipo de dato, longitud, obligatoriedad y formato | Q11: Generar una excepción indicándole al usuario cuáles datos del prefijo no cumplen con las reglas definidas | R11: Detener operación
O12: ='P-PrefijoCelular'!A7 -> P-PRE-0002 | P12: ='P-PrefijoCelular'!B7 -> Asegurar que no exista otro prefijo de celular registrado con el mismo valor | Q12: Generar una excepción indicándole al usuario que ya existe un prefijo de celular registrado con ese mismo valor | R12: Detener operación
A13: Modificar un prefijo de celular registrado | C13: Permite al dueño corregir el valor de un prefijo que ya había habilitado | G13: id | H13: UUID | I13: Corresponde al identificador del prefijo que se va a modificar | J13: PrefijoCelular | K13: Contiene la información del prefijo de celular modificado | O13: ='P-PrefijoCelular'!A6 -> P-PRE-0001 | P13: ='P-PrefijoCelular'!B6 -> Asegurar que los datos requeridos (prefijo) sean válidos en tipo de dato, longitud, obligatoriedad y formato | Q13: Generar una excepción indicándole al usuario cuáles datos del prefijo no cumplen con las reglas definidas | R13: Detener operación
G14: datos{prefijo} | H14: PrefijoCelular | I14: Contiene el valor con el que se va a modificar el prefijo | O14: ='P-PrefijoCelular'!A7 -> P-PRE-0002 | P14: ='P-PrefijoCelular'!B7 -> Asegurar que no exista otro prefijo de celular registrado con el mismo valor | Q14: Generar una excepción indicándole al usuario que ya existe un prefijo de celular registrado con ese mismo valor | R14: Detener operación
A15: Retirar un prefijo de celular | C15: Permite al dueño quitar un prefijo para que la barbería deje de atender números de ese país | G15: id | H15: UUID | I15: Corresponde al identificador del prefijo que se va a retirar | K15: No retorna ningún valor. En caso de error genera una excepción. | O15: ='P-PrefijoCelular'!A8 -> P-PRE-0003 | P15: ='P-PrefijoCelular'!B8 -> Asegurar que el prefijo que se va a retirar no esté siendo usado por ningún barbero ni por ningún cliente | Q15: Generar una excepción indicándole al usuario que el prefijo no se puede retirar porque todavía lo usa algún barbero o algún cliente | R15: Detener operación
A16: Ver prefijos de celular | C16: Permite al dueño consultar el catálogo de prefijos telefónicos de país que tiene habilitados | G16: filtro | H16: PrefijoCelular | I16: Contiene los filtros de consulta del catálogo de prefijos | J16: Lista<PrefijoCelular> | K16: Contiene todos los prefijos de celular que cumplen con el filtro enviado

Sheet P-PrefijoCelular
A1: << Ir al modelo de dominio | B1: << Ir al listado de objetos de dominio | C1: << Ir a la caracterización del objeto de dominio | D1: Ir al muestreo de datos del objeto de dominio >> | E1: Ir al event storming del objeto de dominio >>
A2: Objeto de Dominio: | B2: ='Objetos de Dominio'!A6 -> PrefijoCelular
A3: Descripción: | B3: ='Objetos de Dominio'!B6 -> Representa el catálogo de prefijos telefónicos de país que el dueño habilita, y que son los únicos que barberos y clientes pueden usar en su número de celular.
A4: Numero politica | B4: Descripcion politica | D4: Objeto responsable | E4: Regla responsable
A6: P-PRE-0001 | B6: Asegurar que los datos requeridos (prefijo) sean válidos en tipo de dato, longitud, obligatoriedad y formato | D6: PrefijoCelular
A7: P-PRE-0002 | B7: Asegurar que no exista otro prefijo de celular registrado con el mismo valor | D7: PrefijoCelular
A8: P-PRE-0003 | B8: Asegurar que el prefijo que se va a retirar no esté siendo usado por ningún barbero ni por ningún cliente | D8: PrefijoCelular

Sheet E-PrefijoCelular
A1: << Ir al modelo de dominio | C1: << Ir al listado de objetos de dominio | F1: << Ir a la caracterización del objeto de dominio | J1: Ir al muestreo de datos del objeto de dominio >>
A2: Objeto de Dominio: | B2: ='Objetos de Dominio'!A6 -> PrefijoCelular
A3: Descripción: | B3: ='Objetos de Dominio'!B6 -> Representa el catálogo de prefijos telefónicos de país que el dueño habilita, y que son los únicos que barberos y clientes pueden usar en su número de celular.
A4: Actor | B4: Action/Command | D4: Entity/Aggregate/Object domain | E4: Read Model | G4: Business Rule/Policy | I4: External System | J4: Domain Event | K4: Hotspot/questions/Risk
A5: Actor | B5: Acción | C5: Descripción | D5: Objeto de dominio | E5: Información externa | G5: Políticas | I5: Sistema Externo | J5: Evento | K5: Aspectos por solucionar
E6: Información | F6: Descripción | G6: Número | H6: Descripción
A7: Dueño | B7: Registrar un prefijo de celular | C7: Comando que permite al dueño habilitar el prefijo de un país cuyos números va a atender la barbería | D7: =$B$2 -> PrefijoCelular | G7: ='P-PrefijoCelular'!A6 -> P-PRE-0001 | H7: ='P-PrefijoCelular'!B6 -> Asegurar que los datos requeridos (prefijo) sean válidos en tipo de dato, longitud, obligatoriedad y formato | J7: Prefijo de celular registrado
G8: ='P-PrefijoCelular'!A7 -> P-PRE-0002 | H8: ='P-PrefijoCelular'!B7 -> Asegurar que no exista otro prefijo de celular registrado con el mismo valor
A9: Dueño | B9: Modificar un prefijo de celular registrado | C9: Permite al dueño corregir el valor de un prefijo que ya había habilitado | D9: =$B$2 -> PrefijoCelular | G9: ='P-PrefijoCelular'!A6 -> P-PRE-0001 | H9: ='P-PrefijoCelular'!B6 -> Asegurar que los datos requeridos (prefijo) sean válidos en tipo de dato, longitud, obligatoriedad y formato | J9: Prefijo de celular modificado
G10: ='P-PrefijoCelular'!A7 -> P-PRE-0002 | H10: ='P-PrefijoCelular'!B7 -> Asegurar que no exista otro prefijo de celular registrado con el mismo valor
A11: Dueño | B11: Retirar un prefijo de celular | C11: Permite al dueño quitar un prefijo para que la barbería deje de atender números de ese país | D11: =$B$2 -> PrefijoCelular | G11: ='P-PrefijoCelular'!A8 -> P-PRE-0003 | H11: ='P-PrefijoCelular'!B8 -> Asegurar que el prefijo que se va a retirar no esté siendo usado por ningún barbero ni por ningún cliente | J11: Prefijo de celular retirado
A12: Dueño | B12: Ver prefijos de celular | C12: Permite al dueño consultar el catálogo de prefijos telefónicos de país que tiene habilitados | D12: =$B$2 -> PrefijoCelular | J12: Prefijos de celular consultados
A13: Barbero | B13: Ver prefijos de celular | C13: Permite consultar el catálogo de prefijos telefónicos de país disponibles | D13: =$B$2 -> PrefijoCelular | J13: Prefijos de celular consultados
A14: Cliente | B14: Ver prefijos de celular | C14: Permite consultar el catálogo de prefijos telefónicos de país disponibles | D14: =$B$2 -> PrefijoCelular | J14: Prefijos de celular consultados

Sheet M-PrefijoCelular
A1: <<<< Ir al modulo de dominio | B1: <<<< Ir a objetos de dominio
A2: Representa un identificador que hará unico cada objeto de dominio de este tipo, no se puede repetir | B2: Representa el prefijo telefónico del país que el dueño habilita para que la barbería pueda atender números de ese país | C2: Combinacion única que indica que no puede existir más un mismo prefijo
A3: id | B3: prefijo | C3: Combinación única
A4: 1 | B4: +57 | C4: =B4 -> +57
A5: 2 | B5: +91 | C5: =B5 -> +91
A6: 3 | B6: +593 | C6: =B6 -> +593
A7: 4 | B7: +58 | C7: =B7 -> +58
B13: Corresponde a la descripcion de los atributos
B14: Corresponde al identificador unico del objeto de dominio
B15: Corresponde a los datos que ingresa el usuario
B16: Corresponde a la combinacion única

Sheet C-TipoMulta
A1: <<<< Ir al modulo de dominio | B1: <<<< Ir a objetos de dominio
A2: Nombre atributo | B2: Descripción atributo | C2: Identificador del objeto de dominio | D2: Tipo de dato | E2: Obligatorio | F2: Longitud mínima (si aplica) | G2: Longitud máxima (si aplica) | H2: Precisión (si aplica) | I2: Rendondeo (si aplica) | J2: Rango inicial (si aplica) | K2: Rango final (si aplica) | L2: Formato (si aplica) | M2: Reglas especiales (si aplica) | N2: Dato calculado | O2: Aplica ajuste del dato (si aplica) | P2: Carácter de ajuste (si aplica) | Q2: Quitar espacios en blanco al inicio (si aplica) | R2: Quitar espacios en blanco al fin (si aplica) | S2: Dato sensible (si aplica) | T2: Valor por defecto (si aplica) | U2: Auto generado
A3: ='M-TipoMulta'!A3 -> id | B3: ='M-TipoMulta'!A2 -> Representa un identificador que hará unico cada objeto de dominio de este tipo, no se puede repetir | C3: Si | D3: Identificador único universal | E3: Si | F3: No aplica | G3: No aplica | H3: No aplica | I3: No aplica | J3: No aplica | K3: No aplica | L3: No aplica | M3: No aplica | N3: No | O3: No | P3: No aplica | Q3: No | R3: No | S3: No | T3: UUID vacio | U3: Si
A4: ='M-TipoMulta'!B3 -> nombre | B4: ='M-TipoMulta'!B2 -> Representa el nombre del tipo de multa | C4: No | D4: Alfanumérico | E4: Si | F4: 4 | G4: 50 | H4: No aplica | I4: No aplica | J4: No aplica | K4: No aplica | L4: No aplica | M4: No aplica | N4: No | O4: No | P4: No aplica | Q4: Si | R4: Si | S4: No | T4: Vacio | U4: No
A5: ='M-TipoMulta'!C3 -> descripcion | B5: ='M-TipoMulta'!C2 -> Representa que hace cada tipo de multa | C5: No | D5: Alfanumérico | E5: Si | F5: 10 | G5: 300 | H5: No aplica | I5: No aplica | J5: No aplica | K5: No aplica | L5: No aplica | M5: No aplica | N5: No | O5: No | P5: No aplica | Q5: Si | R5: Si | S5: No | T5: Vacio | U5: No
A7: Nombre combinación única | B7: Descripción | C7: Atributos involucrados
A8: ='M-TipoMulta'!D3 -> Combinación única | B8: ='M-TipoMulta'!D2 -> Combinación única indica que no puede existir más de un tipo de multa con el mismo nombre | C8: nombre
A10: Responsabilidad | C10: Descripción | G10: Entradas | J10: Salida | O10: Políticas (Reglas de Negocio) | Q10: Excepción
G11: Parámetro | H11: Tipo de dato | I11: Descripción | J11: Tipo de Dato | K11: Descripción | O11: Política | P11: Descripción | Q11: Detalle | R11: ¿Qué hago?
A12: Ver tipos de multa | C12: Permite consultar los tipos de multa que puede recibir un cliente | G12: filtro | H12: TipoMulta | I12: Contiene los filtros de consulta del catálogo de tipos de multa | J12: Lista<TipoMulta> | K12: Contiene todos los tipos de multa que cumplen con el filtro enviado

Sheet P-TipoMulta
A1: << Ir al modelo de dominio | B1: << Ir al listado de objetos de dominio | C1: << Ir a la caracterización del objeto de dominio | D1: Ir al muestreo de datos del objeto de dominio >> | E1: Ir al event storming del objeto de dominio >>
A2: Objeto de Dominio: | B2: ='Objetos de Dominio'!A7 -> TipoMulta
A3: Descripción: | B3: ='Objetos de Dominio'!B7 -> Representa los tipos de multa que puede recibir un cliente: por tardanza o por inasistencia.
A4: Numero politica | B4: Descripcion politica | D4: Objeto responsable | E4: Regla responsable
B6: No aplica: es un catálogo de solo lectura, sin comandos que impliquen políticas de negocio propias

Sheet E-TipoMulta
A1: << Ir al modelo de dominio | C1: << Ir al listado de objetos de dominio | F1: << Ir a la caracterización del objeto de dominio | J1: Ir al muestreo de datos del objeto de dominio >>
A2: Objeto de Dominio: | B2: ='Objetos de Dominio'!A7 -> TipoMulta
A3: Descripción: | B3: ='Objetos de Dominio'!B7 -> Representa los tipos de multa que puede recibir un cliente: por tardanza o por inasistencia.
A4: Actor | B4: Action/Command | D4: Entity/Aggregate/Object domain | E4: Read Model | G4: Business Rule/Policy | I4: External System | J4: Domain Event | K4: Hotspot/questions/Risk
A5: Actor | B5: Acción | C5: Descripción | D5: Objeto de dominio | E5: Información externa | G5: Políticas | I5: Sistema Externo | J5: Evento | K5: Aspectos por solucionar
E6: Información | F6: Descripción | G6: Número | H6: Descripción
A7: Dueño | B7: Ver tipos de multa | C7: Permite consultar los tipos de multa que puede recibir un cliente | D7: =$B$2 -> TipoMulta | J7: Tipos de multa consultados
A8: Barbero | B8: Ver tipos de multa | C8: Permite consultar los tipos de multa que puede recibir un cliente | D8: =$B$2 -> TipoMulta | J8: Tipos de multa consultados
A9: Cliente | B9: Ver tipos de multa | C9: Permite consultar los tipos de multa que puede recibir un cliente | D9: =$B$2 -> TipoMulta | J9: Tipos de multa consultados

Sheet M-TipoMulta
A1: <<<< Ir al modulo de dominio | B1: <<<< Ir a objetos de dominio
A2: Representa un identificador que hará unico cada objeto de dominio de este tipo, no se puede repetir | B2: Representa el nombre del tipo de multa | C2: Representa que hace cada tipo de multa | D2: Combinación única indica que no puede existir más de un tipo de multa con el mismo nombre
A3: id | B3: nombre | C3: descripcion | D3: Combinación única
A4: 1 | B4: Tardanza | C4: El cliente llegó a la cita después de la hora acordada, superando los minutos de tiempoEspera definidos en la cita. | D4: =B4 -> Tardanza
A5: 2 | B5: Inasistencia | C5: El cliente no se presentó a la cita agendada: se llegó a la hora estimada de finalización sin que hubiera registrado su llegada. | D5: =B5 -> Inasistencia
B11: Corresponde a la descripcion de los atributos
B12: Corresponde al identificador unico del objeto de dominio
B13: Corresponde a los datos que ingresa el usuario
B14: Corresponde a la combinacion única

Sheet C-Barbero
A1: <<<< Ir al modulo de dominio | B1: <<<< Ir a objetos de dominio
A2: Nombre atributo | B2: Descripción atributo | C2: Identificador del objeto de dominio | D2: Tipo de dato | E2: Obligatorio | F2: Longitud mínima (si aplica) | G2: Longitud máxima (si aplica) | H2: Precisión (si aplica) | I2: Rendondeo (si aplica) | J2: Rango inicial (si aplica) | K2: Rango final (si aplica) | L2: Formato (si aplica) | M2: Reglas especiales (si aplica) | N2: Dato calculado | O2: Aplica ajuste del dato (si aplica) | P2: Carácter de ajuste (si aplica) | Q2: Quitar espacios en blanco al inicio (si aplica) | R2: Quitar espacios en blanco al fin (si aplica) | S2: Dato sensible (si aplica) | T2: Valor por defecto (si aplica) | U2: Auto generado
A3: ='M-Barbero'!A3 -> id | B3: ='M-Barbero'!A2 -> Representa un identificador que hará unico cada objeto de dominio de este tipo, no se puede repetir | C3: Si | D3: Identificador único universal | E3: Si | F3: No aplica | G3: No aplica | H3: No aplica | I3: No aplica | J3: No aplica | K3: No aplica | L3: No aplica | M3: No aplica | N3: No | O3: No aplica | P3: No aplica | Q3: No | R3: No | S3: No | T3: UUID vacio | U3: Si
A4: ='M-Barbero'!B3 -> primerNombre | B4: ='M-Barbero'!B2 -> Representa el primer nombre del barbero que trabaja en barbería | C4: No | D4: Alfanumérico | E4: Si | F4: 3 | G4: 100 | H4: No aplica | I4: No aplica | J4: No aplica | K4: No aplica | L4: No aplica | M4: Solo se aceptan caracteres de letras de la 'a' a la 'z', caracteres con tilde y numeros del 0 al 9 | N4: No | O4: No | P4: No | Q4: Si | R4: Si | S4: No | T4: vacío | U4: No
A5: ='M-Barbero'!C3 -> segundoNombre | B5: ='M-Barbero'!C2 -> Representa el segundo nombre del barbero que trabaja en barbería | C5: No | D5: Alfanumérico | E5: No | F5: 3 | G5: 100 | H5: No aplica | I5: No aplica | J5: No aplica | K5: No aplica | L5: No aplica | M5: Solo se aceptan caracteres de letras de la 'a' a la 'z', caracteres con tilde y numeros del 0 al 9 | N5: No | O5: No | P5: No | Q5: Si | R5: Si | S5: No | T5: vacío | U5: No
A6: ='M-Barbero'!D3 -> primerApellido | B6: ='M-Barbero'!D2 -> Representa el primer apellido del barbero que trabaja en la barbería | C6: No | D6: Alfanumérico | E6: Si | F6: 3 | G6: 100 | H6: No aplica | I6: No aplica | J6: No aplica | K6: No aplica | L6: No aplica | M6: Solo se aceptan caracteres de letras de la 'a' a la 'z', caracteres con tilde y numeros del 0 al 9 | N6: No | O6: No | P6: No | Q6: Si | R6: Si | S6: No | T6: vacío | U6: No
A7: ='M-Barbero'!E3 -> segundoApellido | B7: ='M-Barbero'!E2 -> Representa el segundo apellido del barbero que trabaja en la barbería | C7: No | D7: Alfanumérico | E7: No | F7: 3 | G7: 100 | H7: No aplica | I7: No aplica | J7: No aplica | K7: No aplica | L7: No aplica | M7: Solo se aceptan caracteres de letras de la 'a' a la 'z', caracteres con tilde y numeros del 0 al 9 | N7: No | O7: No | P7: No | Q7: Si | R7: Si | S7: No | T7: vacío | U7: No
A8: ='M-Barbero'!F3 -> prefijo | B8: ='M-Barbero'!F2 -> Representa cual es el prefijo del numero de celular del barbero | C8: No | D8: PrefijoCelular | E8: Si | F8: No aplica | G8: No aplica | H8: No aplica | I8: No aplica | J8: No aplica | K8: No aplica | L8: No aplica | M8: Aplican las reglas del objeto referenciado | N8: No | O8: No aplica | P8: No aplica | Q8: No aplica | R8: No aplica | S8: No | T8: UUID vacio | U8: No
A9: ='M-Barbero'!G3 -> celular | B9: ='M-Barbero'!G2 -> Representa el número de celular del barbero, es el dato que el cliente necesita en caso de que tenga que contactarse con el | C9: No | D9: Alfanumérico | E9: Si | F9: 6 | G9: 15 | H9: No aplica | I9: No aplica | J9: No aplica | K9: No aplica | L9: No aplica | M9: Solo se aceptan caracteres de numeros del '0' al '9' | N9: No | O9: No aplica | P9: No aplica | Q9: Si | R9: Si | S9: Si | T9: 0 | U9: No
A10: ='M-Barbero'!I3 -> vigente | B10: ='M-Barbero'!I2 -> Representa si el barbero sigue o no trabajando en la barberia | C10: No | D10: Lógico | E10: No | F10: No aplica | G10: No aplica | H10: No aplica | I10: No aplica | J10: No aplica | K10: No aplica | L10: No aplica | M10: No aplica | N10: Si | O10: No aplica | P10: No aplica | Q10: No aplica | R10: No aplica | S10: No | T10: Si | U10: No
A11: ='M-Barbero'!J3 -> anticipacionEnHorasParaAgendarCita | B11: ='M-Barbero'!J2 -> Representa la parte en horas del tiempo mínimo de anticipación con el que un cliente debe pedirle una cita a este barbero. Junto con anticipacionEnMinutosParaAgendarCita forma el tiempo total de anticipación que exige el barbero | C11: No | D11: Entero | E11: No | F11: No aplica | G11: No aplica | H11: No aplica | I11: No aplica | J11: 0 | K11: 720 | L11: Horas | M11: No aplica | N11: No | O11: No aplica | P11: No aplica | Q11: No aplica | R11: No aplica | S11: No | T11: 0 | U11: No
A12: ='M-Barbero'!K3 -> anticipacionEnMinutosParaAgendarCita | B12: ='M-Barbero'!K2 -> Representa la parte en minutos del tiempo mínimo de anticipación con el que un cliente debe pedirle una cita a este barbero. Junto con anticipacionEnHorasParaAgendarCita forma el tiempo total de anticipación que exige el barbero | C12: No | D12: Entero | E12: No | F12: No aplica | G12: No aplica | H12: No aplica | I12: No aplica | J12: 0 | K12: 59 | L12: Minutos | M12: No aplica | N12: No | O12: No aplica | P12: No aplica | Q12: No aplica | R12: No aplica | S12: No | T12: 0 | U12: No
A14: Nombre combinación única | B14: Descripción | C14: Atributos involucrados
A15: ='M-Barbero'!L3 -> Combinación única 1 | B15: ='M-Barbero'!L2 -> Combinacion única que indica que no puede existir más de un barbero con el mismo prefijo de celular y número de celular | C15: =A8 -> prefijo
C16: =A9 -> celular
A18: Responsabilidad | C18: Descripción | G18: Entradas | J18: Salida | O18: Políticas (Reglas de Negocio) | Q18: Excepción
G19: Parámetro | H19: Tipo de dato | I19: Descripción | J19: Tipo de Dato | K19: Descripción | O19: Política | P19: Descripción | Q19: Detalle | R19: ¿Qué hago?
A20: Registrar barbero a la barbería | C20: Comando que permite el ingreso de un nuevo barbero a trabajar en la barbería | G20: datos{primerNombre, segundoNombre, primerApellido, segundoApellido, prefijoCelular, celular} | H20: Barbero | I20: Contiene la información requerida para registrar un nuevo barbero en la barbería | J20: Barbero | K20: Contiene la información del barbero registrado | O20: ='P-Barbero'!A6 -> P-BAR-0001 | P20: ='P-Barbero'!B6 -> Asegurar que los datos requeridos del barbero (nombre, apellido, prefijo de celular, celular, tiempos de anticipación) sean válidos en tipo de dato, longitud, obligatoriedad, formato y rango | Q20: Generar una excepción indicándole al usuario cuáles datos del barbero no cumplen con las reglas definidas | R20: Detener operación
O21: ='P-Barbero'!A7 -> P-BAR-0002 | P21: ='P-Barbero'!B7 -> Asegurar que el número de celular y prefijo de celular no esté siendo utilizado por otro barbero | Q21: Generar una excepción indicándole al usuario que ya existe otro barbero registrado con ese prefijo y número de celular | R21: Detener operación
A22: Editar contacto | C22: Permite al barbero actualizar su número de celular y su prefijo | G22: id | H22: UUID | I22: Corresponde al identificador del barbero que va a editar su contacto | J22: Barbero | K22: Contiene la información del barbero con su contacto actualizado | O22: ='P-Barbero'!A9 -> P-BAR-0004 | P22: ='P-Barbero'!B9 -> Asegurar que los datos requeridos del barbero para editar su contacto (prefijo de celular, celular) sean válidos en tipo de dato, longitud, obligatoriedad, formato y rango | Q22: Generar una excepción indicándole al usuario cuáles datos de contacto del barbero no cumplen con las reglas definidas | R22: Detener operación
G23: datos{prefijoCelular, celular} | H23: Barbero | I23: Contiene el nuevo prefijo y número de celular del barbero
A24: Editar tiempos de anticipación de citas | C24: Permite al barbero ajustar cuánta anticipación mínima exige para que le agenden una cita | G24: id | H24: UUID | I24: Corresponde al identificador del barbero que va a editar sus tiempos | J24: Barbero | K24: Contiene la información del barbero con sus tiempos de anticipación actualizados | O24: ='P-Barbero'!A10 -> P-BAR-0005 | P24: ='P-Barbero'!B10 -> Asegurar que los datos requeridos del barbero editar sus tiempos de anticipación (prefijo de celular, celular) sean válidos en tipo de dato, longitud, obligatoriedad, formato y rango | Q24: Generar una excepción indicándole al usuario cuáles tiempos de anticipación no cumplen con las reglas definidas | R24: Detener operación
G25: datos{anticipacionEnHorasParaAgendarCita, anticipacionEnMinutosParaAgendarCita} | H25: Barbero | I25: Contiene los nuevos tiempos de anticipación que exige el barbero
A26: Ver datos de un barbero | C26: Permite a un cliente ver los datos públicos de un barbero, como sus nombres, apellidos y su contacto | G26: id | H26: UUID | I26: Corresponde al identificador del barbero que se va a consultar | J26: Barbero | K26: Contiene la información del barbero consultado por su identificador
A27: Dejar de trabajar en la barbería | C27: Permite desactivar a un barbero para que ya no pueda recibir nuevas citas, sin borrar su historial | G27: id | H27: UUID | I27: Corresponde al identificador del barbero que va a dejar de trabajar | K27: No retorna ningún valor. En caso de error genera una excepción. | O27: ='P-Barbero'!A8 -> P-BAR-0003 | P27: ='P-Barbero'!B8 -> Asegurar que el barbero no tenga citas futuras pendientes antes de dejar de trabajar en la barbería | Q27: Generar una excepción indicándole al usuario que el barbero no puede dejar de trabajar porque todavía tiene citas futuras pendientes | R27: Detener operación
A28: Ver tiempos de anticipacion para las citas | C28: Permite al barbero ver su tiempo de anticipacion en horas y minutos para sus citas | G28: id | H28: UUID | I28: Corresponde al identificador del barbero que se va a consultar | J28: Barbero | K28: Contiene los tiempos de anticipación que exige el barbero consultado

Sheet P-Barbero
A1: << Ir al modelo de dominio | B1: << Ir al listado de objetos de dominio | C1: << Ir a la caracterización del objeto de dominio | D1: Ir al muestreo de datos del objeto de dominio >> | E1: Ir al event storming del objeto de dominio >>
A2: Objeto de Dominio: | B2: ='Objetos de Dominio'!A8 -> Barbero
A3: Descripción: | B3: ='Objetos de Dominio'!B8 -> Representa a un trabajador de la barbería que atiende clientes según los servicios que sabe realizar, organiza su propio horario y tiene su agenda personal para atender todas las citas que valla teniendo.
A4: Numero politica | B4: Descripcion politica | D4: Objeto responsable | E4: Regla responsable
A6: P-BAR-0001 | B6: Asegurar que los datos requeridos del barbero (nombre, apellido, prefijo de celular, celular, tiempos de anticipación) sean válidos en tipo de dato, longitud, obligatoriedad, formato y rango | D6: Barbero
A7: P-BAR-0002 | B7: Asegurar que el número de celular y prefijo de celular no esté siendo utilizado por otro barbero | D7: Barbero
A8: P-BAR-0003 | B8: Asegurar que el barbero no tenga citas futuras pendientes antes de dejar de trabajar en la barbería | D8: Cita
A9: P-BAR-0004 | B9: Asegurar que los datos requeridos del barbero para editar su contacto (prefijo de celular, celular) sean válidos en tipo de dato, longitud, obligatoriedad, formato y rango | D9: Barbero
A10: P-BAR-0005 | B10: Asegurar que los datos requeridos del barbero editar sus tiempos de anticipación (prefijo de celular, celular) sean válidos en tipo de dato, longitud, obligatoriedad, formato y rango | D10: Barbero

Sheet E-Barbero
A1: << Ir al modelo de dominio | C1: << Ir al listado de objetos de dominio | F1: << Ir a la caracterización del objeto de dominio | J1: Ir al muestreo de datos del objeto de dominio >>
A2: Objeto de Dominio: | B2: ='Objetos de Dominio'!A8 -> Barbero
A3: Descripción: | B3: ='Objetos de Dominio'!B8 -> Representa a un trabajador de la barbería que atiende clientes según los servicios que sabe realizar, organiza su propio horario y tiene su agenda personal para atender todas las citas que valla teniendo.
A4: Actor | B4: Action/Command | D4: Entity/Aggregate/Object domain | E4: Read Model | G4: Business Rule/Policy | I4: External System | J4: Domain Event | K4: Hotspot/questions/Risk
A5: Actor | B5: Acción | C5: Descripción | D5: Objeto de dominio | E5: Información externa | G5: Políticas | I5: Sistema Externo | J5: Evento | K5: Aspectos por solucionar
E6: Información | F6: Descripción | G6: Número | H6: Descripción
A7: Barbero | B7: Registrar barbero a la barbería | C7: Comando que permite el ingreso de un nuevo barbero a trabajar en la barbería | D7: =$B$2 -> Barbero | G7: ='P-Barbero'!A6 -> P-BAR-0001 | H7: aquí | J7: Barbero registrado
G8: ='P-Barbero'!A7 -> P-BAR-0002 | H8: aquí
A9: Barbero | B9: Editar contacto | C9: Permite al barbero actualizar su número de celular y su prefijo | D9: =$B$2 -> Barbero | G9: ='P-Barbero'!A9 -> P-BAR-0004 | H9: aquí | J9: Contacto de barbero actualizado
A10: Barbero | B10: Editar tiempos de anticipación de citas | C10: Permite al barbero ajustar cuánta anticipación mínima exige para que le agenden una cita | D10: =$B$2 -> Barbero | G10: ='P-Barbero'!A10 -> P-BAR-0005 | H10: aquí | J10: Tiempos de anticipación de barbero actualizados
A11: Cliente | B11: Ver datos de un barbero | C11: Permite a un cliente ver los datos públicos de un barbero, como sus nombres, apellidos y su contacto | D11: =$B$2 -> Barbero | J11: Datos de barbero visto
A12: Barbero | B12: Ver datos de un barbero | C12: Permite a un barbero ver los datos públicos de otro barbero, como sus nombres, apellidos y su contacto | D12: =$B$2 -> Barbero | J12: Datos de barbero visto
A13: Barbero | B13: Dejar de trabajar en la barbería | C13: Permite desactivar a un barbero para que ya no pueda recibir nuevas citas, sin borrar su historial | D13: =$B$2 -> Barbero | G13: ='P-Barbero'!A8 -> P-BAR-0003 | H13: aquí | J13: Barbero desactivado | K13: Mejor usar el efecto cascada si el barbero deja de trabajar todas las citas futuras que tenian se van a cancelar
A14: Barbero | B14: Ver tiempos de anticipacion para las citas | C14: Permite al barbero ver su tiempo de anticipacion en horas y minutos para sus citas | D14: =$B$2 -> Barbero

Sheet M-Barbero
A1: <<<< Ir al modulo de dominio | B1: <<<< Ir a objetos de dominio
A2: Representa un identificador que hará unico cada objeto de dominio de este tipo, no se puede repetir | B2: Representa el primer nombre del barbero que trabaja en barbería | C2: Representa el segundo nombre del barbero que trabaja en barbería | D2: Representa el primer apellido del barbero que trabaja en la barbería | E2: Representa el segundo apellido del barbero que trabaja en la barbería | F2: Representa cual es el prefijo del numero de celular del barbero | G2: Representa el número de celular del barbero, es el dato que el cliente necesita en caso de que tenga que contactarse con el | H2: Representa si el numero que ingreso el cliente es correcto o no | I2: Representa si el barbero sigue o no trabajando en la barberia | J2: Representa la parte en horas del tiempo mínimo de anticipación con el que un cliente debe pedirle una cita a este barbero. Junto con anticipacionEnMinutosParaAgendarCita forma el tiempo total de anticipación que exige el barbero | K2: Representa la parte en minutos del tiempo mínimo de anticipación con el que un cliente debe pedirle una cita a este barbero. Junto con anticipacionEnHorasParaAgendarCita forma el tiempo total de anticipación que exige el barbero | L2: Combinacion única que indica que no puede existir más de un barbero con el mismo prefijo de celular y número de celular
A3: id | B3: primerNombre | C3: segundoNombre | D3: primerApellido | E3: segundoApellido | F3: prefijo | G3: celular | H3: elNumeroCelularEsCorrecto | I3: vigente | J3: anticipacionEnHorasParaAgendarCita | K3: anticipacionEnMinutosParaAgendarCita | L3: Combinación única 1
A4: 1 | B4: Juan | C4: Fernando | D4: García | E4: Lopez | F4: ='M-PrefijoCelular'!C4 -> +57 | G4: 3245627890 | H4: Si | I4: si | J4: 24 | K4: 0 | L4: =_xlfn.CONCAT(F4,"-",G4) -> +57-3245627890
A5: 2 | B5: Juan | C5: David | D5: Ortiz | E5: Sanchez | F5: ='M-PrefijoCelular'!C4 -> +57 | G5: 3124518923 | H5: Si | I5: si | J5: 0 | K5: 30 | L5: =_xlfn.CONCAT(F5,"-",G5) -> +57-3124518923
A6: 3 | B6: Carlos | D6: Arbeladez | F6: ='M-PrefijoCelular'!C4 -> +57 | G6: 3214533321 | H6: Si | I6: si | J6: 1 | K6: 0 | L6: =_xlfn.CONCAT(F6,"-",G6) -> +57-3214533321
A7: 4 | B7: Andres | D7: Ramirez | E7: Patiño | F7: ='M-PrefijoCelular'!C5 -> +91 | G7: 9876543210 | H7: Si | I7: no | J7: 0 | K7: 0 | L7: =_xlfn.CONCAT(F7,"-",G7) -> +91-9876543210
A8: 5 | B8: Juan | C8: Carlos | D8: Zambrano | E8: Perez | F8: ='M-PrefijoCelular'!C6 -> +593 | G8: 998765432 | H8: Si | I8: no | J8: 2 | K8: 0 | L8: =_xlfn.CONCAT(F8,"-",G8) -> +593-998765432
B14: Corresponde a la descripcion de los atributos
B15: Corresponde al identificador unico del objeto de dominio
B16: Corresponde a las referencias de otros objetos de dominio
B17: Corresponde a los datos calculados por el sistema
B18: Corresponde a los datos que ingresa el usuario
B19: Corresponde a la combinacion única

Sheet C-Cliente
A1: <<<< Ir al modulo de dominio | B1: <<<< Ir a objetos de dominio
A2: Nombre atributo | B2: Descripción atributo | C2: Identificador del objeto de dominio | D2: Tipo de dato | E2: Obligatorio | F2: Longitud mínima (si aplica) | G2: Longitud máxima (si aplica) | H2: Precisión (si aplica) | I2: Rendondeo (si aplica) | J2: Rango inicial (si aplica) | K2: Rango final (si aplica) | L2: Formato (si aplica) | M2: Reglas especiales (si aplica) | N2: Dato calculado | O2: Aplica ajuste del dato (si aplica) | P2: Carácter de ajuste (si aplica) | Q2: Quitar espacios en blanco al inicio (si aplica) | R2: Quitar espacios en blanco al fin (si aplica) | S2: Dato sensible (si aplica) | T2: Valor por defecto (si aplica) | U2: Auto generado
A3: ='M-Cliente'!A3 -> id | B3: ='M-Cliente'!A2 -> Representa un identificador que hará unico cada objeto de dominio de este tipo, no se puede repetir | C3: Si | D3: Identificador único universal | E3: Si | F3: No aplica | G3: No aplica | H3: No aplica | I3: No aplica | J3: No aplica | K3: No aplica | L3: No aplica | M3: No aplica | N3: Si | O3: No | P3: No aplica | Q3: No aplica | R3: No aplica | S3: No | T3: UUID vacio | U3: Si
A4: ='M-Cliente'!B3 -> primerNombre | B4: ='M-Cliente'!B2 -> Representa el primer nombre de la persona, que va a estar llendo a la barberia para las citas | C4: No | D4: Alfanumérico | E4: Si | F4: 2 | G4: 50 | H4: No aplica | I4: No aplica | J4: No aplica | K4: No aplica | L4: No aplica | M4: Solo se aceptan caracteres de letras de la 'a' a la 'z', caracteres con tilde y numeros del 0 al 9 | N4: No | O4: No | P4: No | Q4: Si | R4: Si | S4: No | T4: Vacio | U4: No
A5: ='M-Cliente'!C3 -> segundoNombre | B5: ='M-Cliente'!C2 -> Representa el segundo nombre de la persona, que va a estar llendo a la barberia para las citas | C5: No | D5: Alfanumérico | E5: No | F5: 2 | G5: 50 | H5: No aplica | I5: No aplica | J5: No aplica | K5: No aplica | L5: No aplica | M5: Solo se aceptan caracteres de letras de la 'a' a la 'z', caracteres con tilde y numeros del 0 al 9 | N5: No | O5: No | P5: No | Q5: Si | R5: Si | S5: No | T5: Vacio | U5: No
A6: ='M-Cliente'!D3 -> primerApellido | B6: ='M-Cliente'!D2 -> Representa el primer apellido de la persona, que va a estar llendo a la barberia para las citas | C6: No | D6: Alfanumérico | E6: Si | F6: 2 | G6: 50 | H6: No aplica | I6: No aplica | J6: No aplica | K6: No aplica | L6: No aplica | M6: Solo se aceptan caracteres de letras de la 'a' a la 'z', caracteres con tilde y numeros del 0 al 9 | N6: No | O6: No | P6: No | Q6: Si | R6: Si | S6: No | T6: Vacio | U6: No
A7: ='M-Cliente'!E3 -> segundoApellido | B7: ='M-Cliente'!E2 -> Representa el segundo apellido de la persona, que va a estar llendo a la barberia para las citas | C7: No | D7: Alfanumérico | E7: No | F7: 2 | G7: 50 | H7: No aplica | I7: No aplica | J7: No aplica | K7: No aplica | L7: No aplica | M7: Solo se aceptan caracteres de letras de la 'a' a la 'z', caracteres con tilde y numeros del 0 al 9 | N7: No | O7: No | P7: No | Q7: Si | R7: Si | S7: No | T7: Vacio | U7: No
A8: ='M-Cliente'!F3 -> prefijoCelular | B8: ='M-Cliente'!F2 -> Representa cual es el prefijo del numero de celular del cliente | C8: No | D8: PrefijoCelular | E8: Si | F8: No aplica | G8: No aplica | H8: No aplica | I8: No aplica | J8: No aplica | K8: No aplica | L8: No aplica | M8: Aplican las reglas del objeto referenciado | N8: No | O8: No aplica | P8: No aplica | Q8: No aplica | R8: No aplica | S8: No | T8: UUID vacio | U8: No
A9: ='M-Cliente'!G3 -> celular | B9: ='M-Cliente'!G2 -> Representa el numero de celular del cliente, es el dato que el barbero necesita en caso de que tenga que contactarse con el | C9: No | D9: Alfanumérico | E9: Si | F9: 6 | G9: 15 | H9: No aplica | I9: No aplica | J9: No aplica | K9: No aplica | L9: No aplica | M9: Solo se aceptan caracteres de numeros del '0' al '9' | N9: No | O9: No aplica | P9: No aplica | Q9: Si | R9: Si | S9: Si | T9: 0 | U9: No
A10: ='M-Cliente'!H3 -> elNumeroCelularEsCorrecto | B10: ='M-Cliente'!H2 -> Representa si el numero que ingreso el cliente es correcto o no | C10: No | D10: Lógico | E10: Si | F10: No aplica | G10: No aplica | H10: No aplica | I10: No aplica | J10: No aplica | K10: No aplica | L10: No aplica | M10: No aplica | N10: No | O10: No aplica | P10: No aplica | Q10: No aplica | R10: No aplica | S10: No | T10: No | U10: No
A11: ='M-Cliente'!I3 -> estaVetado | B11: ='M-Cliente'!I2 -> Representa si el cliente esta en estado de veto o no, cuando el cliente esta vetado el sistema no va a permitir agendar citas con este cliente con ningun barbero | C11: No | D11: Lógico | E11: Si | F11: No aplica | G11: No aplica | H11: No aplica | I11: No aplica | J11: No aplica | K11: No aplica | L11: No aplica | M11: Se calcula a partir de multasSinPagar: basta con una multa sin pagar para que el cliente quede vetado y no pueda agendar; deja de estarlo en el momento en que la paga | N11: Si | O11: No | P11: No aplica | Q11: No aplica | R11: No aplica | S11: No | T11: No | U11: No
A13: Nombre combinación única | B13: Descripción | C13: Atributos involucrados
A14: ='M-Cliente'!J3 -> Combinación única 1 | B14: ='M-Cliente'!J2 -> Combinacion única que indica que no puede existir más de un cliente con el mismo prefijo de celular y número de celular | C14: =A8 -> prefijoCelular
C17: =A9 -> celular
A19: Responsabilidad | C19: Descripción | G19: Entradas | J19: Salida | O19: Políticas (Reglas de Negocio) | Q19: Excepción
G20: Parámetro | H20: Tipo de dato | I20: Descripción | J20: Tipo de Dato | K20: Descripción | O20: Política | P20: Descripción | Q20: Detalle | R20: ¿Qué hago?
A21: Registrar cliente a la barbería | C21: Comando que permite el registro de un nuevo cliente en la barbería | G21: datos{primerNombre, segundoNombre, primerApellido, segundoApellido, prefijoCelular, celular} | H21: Cliente | I21: Contiene la información requerida para registrar un nuevo cliente en la barbería | J21: Cliente | K21: Contiene la información del cliente registrado | O21: ='P-Cliente'!A6 -> P-CLI-0001 | P21: ='P-Cliente'!B6 -> Asegurar que los datos requeridos del cliente (nombres, apellidos, prefijo de celular, celular) sean válidos en tipo de dato, longitud, obligatoriedad, formato y rango | Q21: Generar una excepción indicándole al usuario cuáles datos del cliente no cumplen con las reglas definidas | R21: Detener operación
O22: ='P-Cliente'!A7 -> P-CLI-0002 | P22: ='P-Cliente'!B7 -> Asegurar que el número de celular y prefijo de celular no esté siendo utilizado por otro cliente | Q22: Generar una excepción indicándole al usuario que ya existe otro cliente registrado con ese prefijo y número de celular | R22: Detener operación
A23: Editar contacto | C23: Permite al cliente actualizar su número de celular y su prefijo | G23: id | H23: UUID | I23: Corresponde al identificador del cliente que va a editar su contacto | J23: Cliente | K23: Contiene la información del cliente con su contacto actualizado | O23: ='P-Cliente'!A8 -> P-CLI-0003 | P23: ='P-Cliente'!B8 -> Asegurar que los datos requeridos del cliente para editar su contacto (prefijo de celular y celular) sean válidos en tipo de dato, longitud, obligatoriedad, formato y rango | Q23: Generar una excepción indicándole al usuario cuáles datos de contacto del cliente no cumplen con las reglas definidas | R23: Detener operación
G24: datos{prefijoCelular, celular} | H24: Cliente | I24: Contiene el nuevo prefijo y número de celular del cliente
A25: Ver datos de un cliente | C25: Permite a un barbero ver los datos de un cliente que le va a pedir una cita | G25: id | H25: UUID | I25: Corresponde al identificador del cliente que se va a consultar | J25: Cliente | K25: Contiene la información del cliente consultado por su identificador
A26: Ver estado de vetado | C26: Permite al cliente ver si tiene alguna multa sin pagar que le impida agendar nuevas citas | G26: id | H26: UUID | I26: Corresponde al identificador del cliente que se va a consultar | J26: Lógico | K26: Indica si el cliente está vetado o no para agendar nuevas citas
A27: Ver cantidad de multas sin pagar | C27: Permite al cliente ver cuántas multas sin pagar tiene | G27: id | H27: UUID | I27: Corresponde al identificador del cliente que se va a consultar | J27: Entero | K27: Contiene la cantidad de multas sin pagar que tiene el cliente

Sheet P-Cliente
A1: << Ir al modelo de dominio | B1: << Ir al listado de objetos de dominio | C1: << Ir a la caracterización del objeto de dominio | D1: Ir al muestreo de datos del objeto de dominio >> | E1: Ir al event storming del objeto de dominio >>
A2: Objeto de Dominio: | B2: ='Objetos de Dominio'!A9 -> Cliente
A3: Descripción: | B3: ='Objetos de Dominio'!B9 -> Representa a la persona que solicita citas en la barbería.
A4: Numero politica | B4: Descripcion politica | D4: Objeto responsable | E4: Regla responsable
A6: P-CLI-0001 | B6: Asegurar que los datos requeridos del cliente (nombres, apellidos, prefijo de celular, celular) sean válidos en tipo de dato, longitud, obligatoriedad, formato y rango | D6: Cliente
A7: P-CLI-0002 | B7: Asegurar que el número de celular y prefijo de celular no esté siendo utilizado por otro cliente | D7: Cliente
A8: P-CLI-0003 | B8: Asegurar que los datos requeridos del cliente para editar su contacto (prefijo de celular y celular) sean válidos en tipo de dato, longitud, obligatoriedad, formato y rango | D8: Cliente
A9: P-CLI-0004 | B9: Asegurar que el cliente no tenga ninguna multa sin pagar antes de permitirle agendar una cita nueva; mientras la tenga permanece vetado | D9: Multa

Sheet E-Cliente
A1: << Ir al modelo de dominio | C1: << Ir al listado de objetos de dominio | F1: << Ir a la caracterización del objeto de dominio | J1: Ir al muestreo de datos del objeto de dominio >>
A2: Objeto de Dominio: | B2: ='Objetos de Dominio'!A9 -> Cliente
A3: Descripción: | B3: ='Objetos de Dominio'!B9 -> Representa a la persona que solicita citas en la barbería.
A4: Actor | B4: Action/Command | D4: Entity/Aggregate/Object domain | E4: Read Model | G4: Business Rule/Policy | I4: External System | J4: Domain Event | K4: Hotspot/questions/Risk
A5: Actor | B5: Acción | C5: Descripción | D5: Objeto de dominio | E5: Información externa | G5: Políticas | I5: Sistema Externo | J5: Evento | K5: Aspectos por solucionar
E6: Información | F6: Descripción | G6: Número | H6: Descripción
A7: Cliente | B7: Registrar cliente a la barbería | C7: Comando que permite el registro de un nuevo cliente en la barbería | D7: =$B$2 -> Cliente | E7: PrefijoCelular | F7: Permite asignar el prefijo de país del número de celular del cliente. | G7: ='P-Cliente'!A6 -> P-CLI-0001 | H7: ='P-Cliente'!B6 -> Asegurar que los datos requeridos del cliente (nombres, apellidos, prefijo de celular, celular) sean válidos en tipo de dato, longitud, obligatoriedad, formato y rango | J7: Cliente registrado
G8: ='P-Cliente'!A7 -> P-CLI-0002 | H8: ='P-Cliente'!B7 -> Asegurar que el número de celular y prefijo de celular no esté siendo utilizado por otro cliente
A9: Cliente | B9: Editar contacto | C9: Permite al cliente actualizar su número de celular y su prefijo | D9: =$B$2 -> Cliente | E9: PrefijoCelular | F9: Permite actualizar el prefijo de país del número de celular. | G9: ='P-Cliente'!A8 -> P-CLI-0003 | H9: ='P-Cliente'!B8 -> Asegurar que los datos requeridos del cliente para editar su contacto (prefijo de celular y celular) sean válidos en tipo de dato, longitud, obligatoriedad, formato y rango | J9: Contacto de cliente actualizado
A10: Barbero | B10: Ver datos de un cliente | C10: Permite a un barbero ver los datos de un cliente que le va a pedir una cita | D10: =$B$2 -> Cliente | E10: PrefijoCelular | F10: Permite mostrar el número de celular completo con su prefijo. | J10: Datos del cliente vistos
A11: Cliente | B11: Ver estado de vetado | C11: Permite al cliente ver si tiene alguna multa sin pagar que le impida agendar nuevas citas | D11: =$B$2 -> Cliente | E11: Multa | F11: Permite conocer si el cliente tiene multas sin pagar. | J11: Estado de veto del cliente visto
A12: Cliente | B12: Ver cantidad de multas sin pagar | C12: Permite al cliente ver cuántas multas sin pagar tiene | D12: =$B$2 -> Cliente | E12: Multa | F12: Permite contar las multas del cliente que siguen sin pagar. | J12: Multas sin pagar del cliente vistas

Sheet M-Cliente
A1: <<<< Ir al modulo de dominio | B1: <<<< Ir a objetos de dominio
A2: Representa un identificador que hará unico cada objeto de dominio de este tipo, no se puede repetir | B2: Representa el primer nombre de la persona, que va a estar llendo a la barberia para las citas | C2: Representa el segundo nombre de la persona, que va a estar llendo a la barberia para las citas | D2: Representa el primer apellido de la persona, que va a estar llendo a la barberia para las citas | E2: Representa el segundo apellido de la persona, que va a estar llendo a la barberia para las citas | F2: Representa cual es el prefijo del numero de celular del cliente | G2: Representa el numero de celular del cliente, es el dato que el barbero necesita en caso de que tenga que contactarse con el | H2: Representa si el numero que ingreso el cliente es correcto o no | I2: Representa si el cliente esta en estado de veto o no, cuando el cliente esta vetado el sistema no va a permitir agendar citas con este cliente con ningun barbero | J2: Combinacion única que indica que no puede existir más de un cliente con el mismo prefijo de celular y número de celular
A3: id | B3: primerNombre | C3: segundoNombre | D3: primerApellido | E3: segundoApellido | F3: prefijoCelular | G3: celular | H3: elNumeroCelularEsCorrecto | I3: estaVetado | J3: Combinación única 1
A4: 1 | B4: Juan | D4: Gómez | F4: ='M-PrefijoCelular'!C4 -> +57 | G4: 3234528921 | H4: Si | I4: no | J4: =_xlfn.CONCAT(F4,"-",G4) -> +57-3234528921
A5: 2 | B5: Jose | C5: Miguel | D5: Ramirez | E5: Perez | F5: ='M-PrefijoCelular'!C4 -> +57 | G5: 3161657782 | H5: Si | I5: no | J5: =_xlfn.CONCAT(F5,"-",G5) -> +57-3161657782
A6: 3 | B6: Simon | D6: Ochoa | E6: Ramirez | F6: ='M-PrefijoCelular'!C4 -> +57 | G6: 3119884321 | H6: Si | I6: no | J6: =_xlfn.CONCAT(F6,"-",G6) -> +57-3119884321
A7: 4 | B7: Alexis | D7: Gallego | F7: ='M-PrefijoCelular'!C7 -> +58 | G7: 4127359182 | H7: Si | I7: no | J7: =_xlfn.CONCAT(F7,"-",G7) -> +58-4127359182
A8: 5 | B8: Kevin | C8: Andrés | D8: Muñoz | E8: Salazar | F8: ='M-PrefijoCelular'!C4 -> +57 | G8: 3005544332 | H8: Si | I8: si | J8: =_xlfn.CONCAT(F8,"-",G8) -> +57-3005544332
B14: Corresponde a la descripcion de los atributos
B15: Corresponde al identificador unico del objeto de dominio
B16: Corresponde a las referencias de otros objetos de dominio
B17: Corresponde a los datos calculados por el sistema
B18: Corresponde a los datos que ingresa el usuario
B19: Corresponde a la combinacion única

Sheet C-HorarioBarberia
A1: <<<< Ir al modulo de dominio | B1: <<<< Ir a objetos de dominio
A2: Nombre atributo | B2: Descripción atributo | C2: Identificador del objeto de dominio | D2: Tipo de dato | E2: Obligatorio | F2: Longitud mínima (si aplica) | G2: Longitud máxima (si aplica) | H2: Precisión (si aplica) | I2: Rendondeo (si aplica) | J2: Rango inicial (si aplica) | K2: Rango final (si aplica) | L2: Formato (si aplica) | M2: Reglas especiales (si aplica) | N2: Dato calculado | O2: Aplica ajuste del dato (si aplica) | P2: Carácter de ajuste (si aplica) | Q2: Quitar espacios en blanco al inicio (si aplica) | R2: Quitar espacios en blanco al fin (si aplica) | S2: Dato sensible (si aplica) | T2: Valor por defecto (si aplica) | U2: Auto generado
A3: ='M-HorarioBarberia'!A3 -> id | B3: ='M-HorarioBarberia'!A2 -> Representa un identificador que hará unico cada objeto de dominio de este tipo, no se puede repetir | C3: Si | D3: Identificador único universal | E3: Si | F3: No aplica | G3: No aplica | H3: No aplica | I3: No aplica | J3: No aplica | K3: No aplica | L3: No aplica | M3: No aplica | N3: No | O3: No | P3: No aplica | Q3: No aplica | R3: No aplica | S3: No | T3: UUID vacio | U3: Si
A4: ='M-HorarioBarberia'!B3 -> diaDeLaSemana | B4: ='M-HorarioBarberia'!B2 -> Representa el día de la semana en el que la barberia abre | C4: No | D4: DiaSemana | E4: Si | F4: No aplica | G4: No aplica | H4: No aplica | I4: No aplica | J4: No aplica | K4: No aplica | L4: No aplica | M4: Aplican las reglas del objeto referenciado | N4: No | O4: No | P4: No aplica | Q4: No aplica | R4: No aplica | S4: No | T4: UUID vacio | U4: No
A5: ='M-HorarioBarberia'!C3 -> horaApertura | B5: ='M-HorarioBarberia'!C2 -> Representa la hora a la que abre la barbería | C5: No | D5: Hora | E5: No | F5: No aplica | G5: No aplica | H5: No aplica | I5: No aplica | J5: No aplica | K5: No aplica | L5: No aplica | M5: No aplica | N5: No | O5: No | P5: No aplica | Q5: No aplica | R5: No aplica | S5: No | T5: 00:00 | U5: No
A6: ='M-HorarioBarberia'!D3 -> horaCierre | B6: ='M-HorarioBarberia'!D2 -> Representa la hora a la que cierra la barbería | C6: No | D6: Hora | E6: Si | F6: No aplica | G6: No aplica | H6: No aplica | I6: No aplica | J6: No aplica | K6: No aplica | L6: No aplica | M6: Debe ser mayor a horaApertura | N6: No | O6: No | P6: No aplica | Q6: No aplica | R6: No aplica | S6: No | T6: 00:00 | U6: No
A7: ='M-HorarioBarberia'!E3 -> fechaCreacion | B7: ='M-HorarioBarberia'!E2 -> Representa la fecha en el que el dueño definio el horario de la barberia. Es un dato calculado que toma la fecha del sistema en ese momento | C7: No | D7: Fecha | E7: Si | F7: No aplica | G7: No aplica | H7: No aplica | I7: No aplica | J7: No aplica | K7: No aplica | L7: No aplica | M7: No aplica | N7: Si | O7: No | P7: No aplica | Q7: No aplica | R7: No aplica | S7: No | T7: 1/01/1000 | U7: No
A8: ='M-HorarioBarberia'!F3 -> fechaDesactivacion | B8: ='M-HorarioBarberia'!F2 -> Representa la fecha en la que este horario dejó de estar vigente, dueño. Es un dato calculado que toma la fecha del sistema en ese momento | C8: No | D8: Fecha | E8: No | F8: No aplica | G8: No aplica | H8: No aplica | I8: No aplica | J8: No aplica | K8: No aplica | L8: No aplica | M8: No aplica | N8: Si | O8: No | P8: No aplica | Q8: No aplica | R8: No aplica | S8: No | T8: 1/01/1000 | U8: No
A9: ='M-HorarioBarberia'!G3 -> vigente | B9: ='M-HorarioBarberia'!G2 -> Representa si este horario lo sigue o no vigente en la barberia. Una vez que el dueño desactive el horario de la barberia, no se puede volver a cambiar | C9: No | D9: Lógico | E9: No | F9: No aplica | G9: No aplica | H9: No aplica | I9: No aplica | J9: No aplica | K9: No aplica | L9: No aplica | M9: No aplica | N9: No | O9: No | P9: No aplica | Q9: No aplica | R9: No aplica | S9: No | T9: Si | U9: No
A11: Nombre combinación única | B11: Descripción | C11: Atributos involucrados
A12: ='M-HorarioBarberia'!H3 -> Combinación única | B12: ='M-HorarioBarberia'!H2 -> Combinacion única que indica que no puede existir más de un horario con la misma barberia, dia de la semana, hora de apertura y cierre | C12: =A4 -> diaDeLaSemana
C13: =A5 -> horaApertura
C14: =A6 -> horaCierre
C15: =A7 -> fechaCreacion
C16: =A8 -> fechaDesactivacion
C17: =A9 -> vigente
A19: Responsabilidad | C19: Descripción | G19: Entradas | J19: Salida | O19: Políticas (Reglas de Negocio) | Q19: Excepción
G20: Parámetro | H20: Tipo de dato | I20: Descripción | J20: Tipo de Dato | K20: Descripción | O20: Política | P20: Descripción | Q20: Detalle | R20: ¿Qué hago?
A21: Definir un horario de la barbería | C21: Comando que permite registrar la hora de apertura y cierre de la barbería para un día de la semana | G21: datos{diaDeLaSemana, horaApertura, horaCierre} | H21: HorarioBarberia | I21: Contiene la información requerida para registrar el horario de la barbería para un día | J21: HorarioBarberia | K21: Contiene la información del horario de la barbería registrado | O21: ='P-HorarioBarberia'!A6 -> P-HBA-0001 | P21: ='P-HorarioBarberia'!B6 -> Asegurar que los datos requeridos (día de la semana, hora de apertura, hora de cierre) sean válidos en tipo de dato, obligatoriedad, formato y rango, y que la hora de cierre sea mayor a la hora de apertura | Q21: Generar una excepción indicándole al usuario cuáles datos del horario de la barbería no cumplen con las reglas definidas | R21: Detener operación
O22: ='P-HorarioBarberia'!A7 -> P-HBA-0002 | P22: ='P-HorarioBarberia'!B7 -> Asegurar que no exista otro horario vigente definido para el mismo día de la semana, que se cruze con las horas de apertura y cierre | Q22: Generar una excepción indicándole al usuario que ya existe un horario vigente para ese día que se cruza con las horas indicadas | R22: Detener operación
A23: Ver horarios de la barbería | C23: Permite al dueño consultar los horarios de apertura y cierre definidos para cada día de la semana | G23: filtro | H23: HorarioBarberia | I23: Contiene los filtros de consulta de los horarios de la barbería | J23: Lista<HorarioBarberia> | K23: Contiene todos los horarios de la barbería que cumplen con el filtro enviado
A24: Desactivar horario de barbería | C24: Permite desactivar el horario en el que la barberia ya no abrira | G24: id | H24: UUID | I24: Corresponde al identificador del horario de la barbería que se va a desactivar | K24: No retorna ningún valor. En caso de error genera una excepción. | O24: ='P-HorarioBarberia'!A8 -> P-HBA-0003 | P24: ='P-HorarioBarberia'!B8 -> Al desactivar un horario de barbería, desactivar en cascada todos los horarios de barbero que dependen de ese día | Q24: Si la desactivación en cascada de los horarios de barbero falla, revertir la desactivación del horario de la barbería e informar el error | R24: Continuar operación
O25: ='P-HorarioBarberia'!A9 -> P-HBA-0004 | P25: ='P-HorarioBarberia'!B9 -> Al desactivarse un horario de barbero por la cascada, desactivar también las agendas futuras que se habían generado a partir de ese horario | Q25: Si la desactivación de las agendas futuras falla, revertir toda la cascada e informar el error | R25: Continuar operación
O26: ='P-HorarioBarberia'!A10 -> P-HBA-0005 | P26: ='P-HorarioBarberia'!B10 -> Cancelar las citas futuras que quedaron en esas agendas, dejándolas en el estado Cancelación por cambio de políticas de la barbería | Q26: Si la cancelación de las citas futuras falla, revertir toda la cascada e informar el error | R26: Continuar operación

Sheet P-HorarioBarberia
A1: << Ir al modelo de dominio | B1: << Ir al listado de objetos de dominio | C1: << Ir a la caracterización del objeto de dominio | D1: Ir al muestreo de datos del objeto de dominio >> | E1: Ir al event storming del objeto de dominio >>
A2: Objeto de Dominio: | B2: ='Objetos de Dominio'!A10 -> HorarioBarberia
A3: Descripción: | B3: ='Objetos de Dominio'!B10 -> Representa, día por día, a qué hora abre y cierra el negocio; es el límite dentro del cual debe caber el horario de cualquier barbero.
A4: Numero politica | B4: Descripcion politica | D4: Objeto responsable | E4: Regla responsable
A6: P-HBA-0001 | B6: Asegurar que los datos requeridos (día de la semana, hora de apertura, hora de cierre) sean válidos en tipo de dato, obligatoriedad, formato y rango, y que la hora de cierre sea mayor a la hora de apertura | D6: HorarioBarberia
A7: P-HBA-0002 | B7: Asegurar que no exista otro horario vigente definido para el mismo día de la semana, que se cruze con las horas de apertura y cierre | D7: HorarioBarberia
A8: P-HBA-0003 | B8: Al desactivar un horario de barbería, desactivar en cascada todos los horarios de barbero que dependen de ese día | D8: HorarioBarbero
A9: P-HBA-0004 | B9: Al desactivarse un horario de barbero por la cascada, desactivar también las agendas futuras que se habían generado a partir de ese horario | D9: Agenda
A10: P-HBA-0005 | B10: Cancelar las citas futuras que quedaron en esas agendas, dejándolas en el estado Cancelación por cambio de políticas de la barbería | D10: Cita

Sheet E-HorarioBarberia
A1: << Ir al modelo de dominio | C1: << Ir al listado de objetos de dominio | F1: << Ir a la caracterización del objeto de dominio | J1: Ir al muestreo de datos del objeto de dominio >>
A2: Objeto de Dominio: | B2: ='Objetos de Dominio'!A10 -> HorarioBarberia
A3: Descripción: | B3: ='Objetos de Dominio'!B10 -> Representa, día por día, a qué hora abre y cierra el negocio; es el límite dentro del cual debe caber el horario de cualquier barbero.
A4: Actor | B4: Action/Command | D4: Entity/Aggregate/Object domain | E4: Read Model | G4: Business Rule/Policy | I4: External System | J4: Domain Event | K4: Hotspot/questions/Risk
A5: Actor | B5: Acción | C5: Descripción | D5: Objeto de dominio | E5: Información externa | G5: Políticas | I5: Sistema Externo | J5: Evento | K5: Aspectos por solucionar
E6: Información | F6: Descripción | G6: Número | H6: Descripción
A7: Dueño | B7: Definir un horario de la barbería | C7: Comando que permite registrar la hora de apertura y cierre de la barbería para un día de la semana | D7: =$B$2 -> HorarioBarberia | G7: ='P-HorarioBarberia'!A6 -> P-HBA-0001 | H7: ='P-HorarioBarberia'!B6 -> Asegurar que los datos requeridos (día de la semana, hora de apertura, hora de cierre) sean válidos en tipo de dato, obligatoriedad, formato y rango, y que la hora de cierre sea mayor a la hora de apertura | J7: Horario de barbería definido
G8: ='P-HorarioBarberia'!A7 -> P-HBA-0002 | H8: ='P-HorarioBarberia'!B7 -> Asegurar que no exista otro horario vigente definido para el mismo día de la semana, que se cruze con las horas de apertura y cierre
A9: Dueño | B9: Ver horarios de la barbería | C9: Permite al dueño consultar los horarios de apertura y cierre definidos para cada día de la semana | D9: =$B$2 -> HorarioBarberia | J9: Horarios de barbería consultados
A10: Barbero | B10: Ver horarios de la barbería | C10: Permite al barbero consultar los horarios de apertura y cierre definidos para cada día de la semana | D10: =$B$2 -> HorarioBarberia | J10: Horarios de barbería consultados
A11: Cliente | B11: Ver horarios de la barbería | C11: Permite al cliente consultar los horarios de apertura y cierre definidos para cada día de la semana | D11: =$B$2 -> HorarioBarberia | J11: Horarios de barbería consultados
A12: Dueño | B12: Desactivar horario de barbería | C12: Permite desactivar el horario en el que la barberia ya no abrira | D12: =$B$2 -> HorarioBarberia | E12: HorarioBarbero | F12: Permite identificar los horarios de barbero que dependen de ese día para desactivarlos. | G12: ='P-HorarioBarberia'!A8 -> P-HBA-0003 | H12: ='P-HorarioBarberia'!B8 -> Al desactivar un horario de barbería, desactivar en cascada todos los horarios de barbero que dependen de ese día | J12: Horario de barbería desactivado
E13: Agenda | F13: Permite identificar las agendas futuras generadas por esos horarios para desactivarlas. | G13: ='P-HorarioBarberia'!A9 -> P-HBA-0004 | H13: ='P-HorarioBarberia'!B9 -> Al desactivarse un horario de barbero por la cascada, desactivar también las agendas futuras que se habían generado a partir de ese horario
E14: Cita | F14: Permite identificar las citas futuras que quedan en esas agendas para cancelarlas. | G14: ='P-HorarioBarberia'!A10 -> P-HBA-0005 | H14: ='P-HorarioBarberia'!B10 -> Cancelar las citas futuras que quedaron en esas agendas, dejándolas en el estado Cancelación por cambio de políticas de la barbería
E15: Estado | F15: Permite dejar esas citas en el estado Cancelación.

Sheet M-HorarioBarberia
A1: <<<< Ir al modulo de dominio | B1: <<<< Ir a objetos de dominio
A2: Representa un identificador que hará unico cada objeto de dominio de este tipo, no se puede repetir | B2: Representa el día de la semana en el que la barberia abre | C2: Representa la hora a la que abre la barbería | D2: Representa la hora a la que cierra la barbería | E2: Representa la fecha en el que el dueño definio el horario de la barberia. Es un dato calculado que toma la fecha del sistema en ese momento | F2: Representa la fecha en la que este horario dejó de estar vigente, dueño. Es un dato calculado que toma la fecha del sistema en ese momento | G2: Representa si este horario lo sigue o no vigente en la barberia. Una vez que el dueño desactive el horario de la barberia, no se puede volver a cambiar | H2: Combinacion única que indica que no puede existir más de un horario con la misma barberia, dia de la semana, hora de apertura y cierre
A3: id | B3: diaDeLaSemana | C3: horaApertura | D3: horaCierre | E3: fechaCreacion | F3: fechaDesactivacion | G3: vigente | H3: Combinación única
A4: 1 | B4: ='M-DiaSemana'!C4 -> Lunes | C4: 0.375 | D4: 0.79166667 | E4: 45242 | F4: 1/01/1000 | G4: Si | H4: =_xlfn.CONCAT(B4,"-",TEXT(C4,"hh:mm"),"-",TEXT(D4,"hh:mm"),"-",TEXT(E4,"dd/mm/yyyy"),"-",TEXT(F4,"dd/mm/yyyy")) -> Lunes-09:00-19:00-12/11/2023-1/01/1000
A5: 2 | B5: ='M-DiaSemana'!C5 -> Martes | C5: 0.375 | D5: 0.79166667 | E5: 45242 | F5: 1/01/1000 | G5: Si | H5: =_xlfn.CONCAT(B5,"-",TEXT(C5,"hh:mm"),"-",TEXT(D5,"hh:mm"),"-",TEXT(E5,"dd/mm/yyyy"),"-",TEXT(F5,"dd/mm/yyyy")) -> Martes-09:00-19:00-12/11/2023-1/01/1000
A6: 3 | B6: ='M-DiaSemana'!C6 -> Miércoles | C6: 0.375 | D6: 0.79166667 | E6: 45242 | F6: 1/01/1000 | G6: Si | H6: =_xlfn.CONCAT(B6,"-",TEXT(C6,"hh:mm"),"-",TEXT(D6,"hh:mm"),"-",TEXT(E6,"dd/mm/yyyy"),"-",TEXT(F6,"dd/mm/yyyy")) -> Miércoles-09:00-19:00-12/11/2023-1/01/1000
A7: 4 | B7: ='M-DiaSemana'!C7 -> Jueves | C7: 0.375 | D7: 0.79166667 | E7: 45242 | F7: 1/01/1000 | G7: Si | H7: =_xlfn.CONCAT(B7,"-",TEXT(C7,"hh:mm"),"-",TEXT(D7,"hh:mm"),"-",TEXT(E7,"dd/mm/yyyy"),"-",TEXT(F7,"dd/mm/yyyy")) -> Jueves-09:00-19:00-12/11/2023-1/01/1000
A8: 5 | B8: ='M-DiaSemana'!C8 -> Viernes | C8: 0.375 | D8: 0.79166667 | E8: 45242 | F8: 1/01/1000 | G8: Si | H8: =_xlfn.CONCAT(B8,"-",TEXT(C8,"hh:mm"),"-",TEXT(D8,"hh:mm"),"-",TEXT(E8,"dd/mm/yyyy"),"-",TEXT(F8,"dd/mm/yyyy")) -> Viernes-09:00-19:00-12/11/2023-1/01/1000
A9: 6 | B9: ='M-DiaSemana'!C9 -> Sábado | C9: 0.33333333 | D9: 0.875 | E9: 45638 | F9: 1/01/1000 | G9: Si | H9: =_xlfn.CONCAT(B9,"-",TEXT(C9,"hh:mm"),"-",TEXT(D9,"hh:mm"),"-",TEXT(E9,"dd/mm/yyyy"),"-",TEXT(F9,"dd/mm/yyyy")) -> Sábado-08:00-21:00-12/12/2024-1/01/1000
A10: 7 | B10: ='M-DiaSemana'!C11 -> Festivo | C10: 0.41666667 | D10: 0.625 | E10: 45638 | F10: 1/01/1000 | G10: Si | H10: =_xlfn.CONCAT(B10,"-",TEXT(C10,"hh:mm"),"-",TEXT(D10,"hh:mm"),"-",TEXT(E10,"dd/mm/yyyy"),"-",TEXT(F10,"dd/mm/yyyy")) -> Festivo-10:00-15:00-12/12/2024-1/01/1000
B16: Corresponde a la descripcion de los atributos
B17: Corresponde al identificador unico del objeto de dominio
B18: Corresponde a las referencias de otros objetos de dominio
B19: Corresponde a los datos calculados por el sistema
B20: Corresponde a los datos que ingresa el usuario
B21: Corresponde a la combinacion única

Sheet C-Bloqueo
A1: <<<< Ir al modulo de dominio | B1: <<<< Ir a objetos de dominio
A2: Nombre atributo | B2: Descripción atributo | C2: Identificador del objeto de dominio | D2: Tipo de dato | E2: Obligatorio | F2: Longitud mínima (si aplica) | G2: Longitud máxima (si aplica) | H2: Precisión (si aplica) | I2: Rendondeo (si aplica) | J2: Rango inicial (si aplica) | K2: Rango final (si aplica) | L2: Formato (si aplica) | M2: Reglas especiales (si aplica) | N2: Dato calculado | O2: Aplica ajuste del dato (si aplica) | P2: Carácter de ajuste (si aplica) | Q2: Quitar espacios en blanco al inicio (si aplica) | R2: Quitar espacios en blanco al fin (si aplica) | S2: Dato sensible (si aplica) | T2: Valor por defecto (si aplica) | U2: Auto generado
A3: ='M-Bloqueo'!A3 -> id | B3: ='M-Bloqueo'!A2 -> Representa un identificador que hará unico cada objeto de dominio de este tipo, no se puede repetir | C3: Si | D3: Identificador único universal | E3: Si | F3: No aplica | G3: No aplica | H3: No aplica | I3: No aplica | J3: No aplica | K3: No aplica | L3: No aplica | M3: No aplica | N3: No | O3: No | P3: No aplica | Q3: No | R3: No | S3: No | T3: UUID vacio | U3: Si
A4: ='M-Bloqueo'!B3 -> barbero | B4: ='M-Bloqueo'!B2 -> Referencia a qué barbero le pertence este bloqueo | C4: No | D4: Barbero | E4: Si | F4: No aplica | G4: No aplica | H4: No aplica | I4: No aplica | J4: No aplica | K4: No aplica | L4: No aplica | M4: Aplican las reglas del objeto referenciado | N4: No | O4: No aplica | P4: No aplica | Q4: No aplica | R4: No aplica | S4: No | T4: UUID vacio | U4: No
A5: ='M-Bloqueo'!C3 -> fechaHoraInicio | B5: ='M-Bloqueo'!C2 -> Representa la fecha y hora en el que el barbero empieza a no estar disponible para atender las citas | C5: No | D5: Fecha hora | E5: Si | F5: No aplica | G5: No aplica | H5: No aplica | I5: No aplica | J5: No aplica | K5: No aplica | L5: No aplica | M5: No aplica | N5: No | O5: No aplica | P5: No aplica | Q5: No aplica | R5: No aplica | S5: No | T5: 01/01/1000 00:00 | U5: No
A6: ='M-Bloqueo'!D3 -> fechaHoraFinal | B6: ='M-Bloqueo'!D2 -> Representa la fecha y hora en el que el barbero empieza estar disponible nuevamente para atender las citas | C6: No | D6: Fecha hora | E6: Si | F6: No aplica | G6: No aplica | H6: No aplica | I6: No aplica | J6: No aplica | K6: No aplica | L6: No aplica | M6: Debe ser posterior a fechaHoraInicio | N6: No | O6: No aplica | P6: No aplica | Q6: No aplica | R6: No aplica | S6: No | T6: 01/01/1000 00:00 | U6: No
A8: Nombre combinación única | B8: Descripción | C8: Atributos involucrados
A9: ='M-Bloqueo'!E3 -> Combinación única | B9: ='M-Bloqueo'!E2 -> Combinación única que indica que un mismo barbero no puede tener dos bloqueos con la misma fecha y hora de inicio y la misma fecha y hora final | C9: =A4 -> barbero
C10: =A5 -> fechaHoraInicio
C11: =A6 -> fechaHoraFinal
A13: Responsabilidad | C13: Descripción | G13: Entradas | J13: Salida | O13: Políticas (Reglas de Negocio) | Q13: Excepción
G14: Parámetro | H14: Tipo de dato | I14: Descripción | J14: Tipo de Dato | K14: Descripción | O14: Política | P14: Descripción | Q14: Detalle | R14: ¿Qué hago?
A15: Definir un bloque de no disponible | C15: Comando que permite a un barbero asiganar un espacio de no disponibilidad para atender sus citas | G15: datos{barbero, fechaHoraInicio, fechaHoraFinal} | H15: Bloqueo | I15: Contiene la información requerida para registrar un nuevo bloqueo del barbero | J15: Bloqueo | K15: Contiene la información del bloqueo registrado | O15: ='P-Bloqueo'!A6 -> P-BLO-0001 | P15: ='P-Bloqueo'!B6 -> Asegurar que los datos requeridos (fecha y hora de inicio, fecha y hora de fin) sean válidos en tipo de dato, obligatoriedad, formato y rango, y que la fecha y hora de fin sea mayor a la fecha y hora de inicio | Q15: Generar una excepción indicándole al usuario cuáles datos del bloqueo no cumplen con las reglas definidas | R15: Detener operación
O16: ='P-Bloqueo'!A7 -> P-BLO-0002 | P16: ='P-Bloqueo'!B7 -> Rechazar el bloqueo si ya existen citas agendadas dentro de ese mismo rango elegido, en lugar de cancelarlas automáticamente | Q16: Generar una excepción indicándole al usuario que ese rango no se puede bloquear porque ya tiene citas agendadas | R16: Detener operación
O17: ='P-Bloqueo'!A10 -> P-BLO-0005 | P17: ='P-Bloqueo'!B10 -> Asegurar que el bloqueo no se solape con otro bloqueo suyo | Q17: Generar una excepción indicándole al usuario que el rango se solapa con otro bloqueo suyo | R17: Detener operación
A18: Eliminar un bloqueo | C18: Permite a un barbero liberar un espacio de su agenda que había bloqueado previamente | G18: id | H18: UUID | I18: Corresponde al identificador del bloqueo que se va a eliminar | K18: No retorna ningún valor. En caso de error genera una excepción. | O18: ='P-Bloqueo'!A9 -> P-BLO-0004 | P18: ='P-Bloqueo'!B9 -> Asegurar que el bloqueo que se va a editar o eliminar le pertenezca al mismo barbero que hace la solicitud | Q18: Generar una excepción indicándole al usuario que el bloqueo no le pertenece | R18: Detener operación
A19: Ver bloqueos en una fecha | C19: Permite a un barbero ver los espacios que tiene bloqueados en una fecha dada | G19: filtro{barbero, fecha} | H19: Bloqueo | I19: Contiene el barbero y la fecha por los cuales se van a consultar los bloqueos | J19: Lista<Bloqueo> | K19: Contiene todos los bloqueos del barbero en esa fecha
A20: Ver bloqueo en una fecha y hora de inicio | C20: Permite al sistema ver si hay o no un bloqueo en una fecha y hora, en el que empieza el bloqueo, para que el determine luego si el cliente puede agenda una cita en ese momento | G20: filtro{barbero, fechaHoraInicio} | H20: Bloqueo | I20: Contiene el barbero y la fecha y hora por las cuales se va a consultar el bloqueo | J20: Bloqueo | K20: Contiene el bloqueo que cubre esa fecha y hora, si existe
A21: Editar un bloqueo | C21: Permite al barbero poder editar la fecha y hora en que inicia o termina | G21: id | H21: UUID | I21: Corresponde al identificador del bloqueo que se va a editar | J21: Bloqueo | K21: Contiene la información del bloqueo con su rango actualizado | O21: ='P-Bloqueo'!A8 -> P-BLO-0003 | P21: ='P-Bloqueo'!B8 -> Asegurar que los datos requeridos para editar el bloqueo (fecha y hora de inicio, fecha y hora de fin) sean válidos en tipo de dato, obligatoriedad, formato y rango, y que la fecha y hora de fin sea mayor a la de inicio | Q21: Generar una excepción indicándole al usuario cuáles datos del bloqueo que se va a editar no cumplen con las reglas definidas | R21: Detener operación
G22: datos{fechaHoraInicio, fechaHoraFinal} | H22: Bloqueo | I22: Contiene el nuevo rango con el que se va a modificar el bloqueo | O22: ='P-Bloqueo'!A7 -> P-BLO-0002 | P22: ='P-Bloqueo'!B7 -> Rechazar el bloqueo si ya existen citas agendadas dentro de ese mismo rango elegido, en lugar de cancelarlas automáticamente | Q22: Generar una excepción indicándole al usuario que ese rango no se puede bloquear porque ya tiene citas agendadas | R22: Detener operación

Sheet P-Bloqueo
A1: << Ir al modelo de dominio | B1: << Ir al listado de objetos de dominio | C1: << Ir a la caracterización del objeto de dominio | D1: Ir al muestreo de datos del objeto de dominio >> | E1: Ir al event storming del objeto de dominio >>
A2: Objeto de Dominio: | B2: ='Objetos de Dominio'!A11 -> Bloqueo
A3: Descripción: | B3: ='Objetos de Dominio'!B11 -> Representa los momentos en que el barbero no esta disponible para atender sus citas, el barbero establece la hora y la fecha en que empieza y termina ese estado de no disponible.
A4: Numero politica | B4: Descripcion politica | D4: Objeto responsable | E4: Regla responsable
A6: P-BLO-0001 | B6: Asegurar que los datos requeridos (fecha y hora de inicio, fecha y hora de fin) sean válidos en tipo de dato, obligatoriedad, formato y rango, y que la fecha y hora de fin sea mayor a la fecha y hora de inicio | D6: Bloqueo
A7: P-BLO-0002 | B7: Rechazar el bloqueo si ya existen citas agendadas dentro de ese mismo rango elegido, en lugar de cancelarlas automáticamente | D7: Cita
A8: P-BLO-0003 | B8: Asegurar que los datos requeridos para editar el bloqueo (fecha y hora de inicio, fecha y hora de fin) sean válidos en tipo de dato, obligatoriedad, formato y rango, y que la fecha y hora de fin sea mayor a la de inicio | D8: Bloqueo
A9: P-BLO-0004 | B9: Asegurar que el bloqueo que se va a editar o eliminar le pertenezca al mismo barbero que hace la solicitud | D9: Bloqueo
A10: P-BLO-0005 | B10: Asegurar que el bloqueo no se solape con otro bloqueo suyo | D10: HorarioBarbero

Sheet E-Bloqueo
A1: << Ir al modelo de dominio | C1: << Ir al listado de objetos de dominio | F1: << Ir a la caracterización del objeto de dominio | J1: Ir al muestreo de datos del objeto de dominio >>
A2: Objeto de Dominio: | B2: ='Objetos de Dominio'!A11 -> Bloqueo
A3: Descripción: | B3: ='Objetos de Dominio'!B11 -> Representa los momentos en que el barbero no esta disponible para atender sus citas, el barbero establece la hora y la fecha en que empieza y termina ese estado de no disponible.
A4: Actor | B4: Action/Command | D4: Entity/Aggregate/Object domain | E4: Read Model | G4: Business Rule/Policy | I4: External System | J4: Domain Event | K4: Hotspot/questions/Risk
A5: Actor | B5: Acción | C5: Descripción | D5: Objeto de dominio | E5: Información externa | G5: Políticas | I5: Sistema Externo | J5: Evento | K5: Aspectos por solucionar
E6: Información | F6: Descripción | G6: Número | H6: Descripción
A7: Barbero | B7: Definir un bloque de no disponible | C7: Comando que permite a un barbero asiganar un espacio de no disponibilidad para atender sus citas | D7: =$B$2 -> Bloqueo | E7: Cita | F7: Permite verificar que no haya citas ya agendadas dentro del rango que se va a bloquear. | G7: ='P-Bloqueo'!A6 -> P-BLO-0001 | H7: ='P-Bloqueo'!B6 -> Asegurar que los datos requeridos (fecha y hora de inicio, fecha y hora de fin) sean válidos en tipo de dato, obligatoriedad, formato y rango, y que la fecha y hora de fin sea mayor a la fecha y hora de inicio | J7: Bloqueo registrado
E8: HorarioBarbero | F8: Permite verificar que el bloqueo caiga dentro de la jornada del barbero. | G8: ='P-Bloqueo'!A7 -> P-BLO-0002 | H8: ='P-Bloqueo'!B7 -> Rechazar el bloqueo si ya existen citas agendadas dentro de ese mismo rango elegido, en lugar de cancelarlas automáticamente
E9: Barbero | F9: Permite identificar de qué barbero es el bloqueo. | G9: ='P-Bloqueo'!A10 -> P-BLO-0005 | H9: ='P-Bloqueo'!B10 -> Asegurar que el bloqueo no se solape con otro bloqueo suyo
A10: Barbero | B10: Eliminar un bloqueo | C10: Permite a un barbero liberar un espacio de su agenda que había bloqueado previamente | D10: =$B$2 -> Bloqueo | G10: ='P-Bloqueo'!A9 -> P-BLO-0004 | H10: ='P-Bloqueo'!B9 -> Asegurar que el bloqueo que se va a editar o eliminar le pertenezca al mismo barbero que hace la solicitud | J10: Bloqueo cancelado
A11: Barbero | B11: Ver bloqueos en una fecha | C11: Permite a un barbero ver los espacios que tiene bloqueados en una fecha dada | D11: =$B$2 -> Bloqueo | J11: Bloqueos vistos
A12: Sistema | B12: Ver bloqueo en una fecha y hora de inicio | C12: Permite al sistema ver si hay o no un bloqueo en una fecha y hora, en el que empieza el bloqueo, para que el determine luego si el cliente puede agenda una cita en ese momento | D12: =$B$2 -> Bloqueo | J12: Bloqueo visto
A13: Barbero | B13: Editar un bloqueo | C13: Permite al barbero poder editar la fecha y hora en que inicia o termina | D13: =$B$2 -> Bloqueo | E13: Cita | F13: Permite verificar que el nuevo rango no choque con citas ya agendadas. | G13: ='P-Bloqueo'!A8 -> P-BLO-0003 | H13: ='P-Bloqueo'!B8 -> Asegurar que los datos requeridos para editar el bloqueo (fecha y hora de inicio, fecha y hora de fin) sean válidos en tipo de dato, obligatoriedad, formato y rango, y que la fecha y hora de fin sea mayor a la de inicio | J13: Bloqueo editado
G14: ='P-Bloqueo'!A7 -> P-BLO-0002 | H14: ='P-Bloqueo'!B7 -> Rechazar el bloqueo si ya existen citas agendadas dentro de ese mismo rango elegido, en lugar de cancelarlas automáticamente

Sheet M-Bloqueo
A1: <<<< Ir al modulo de dominio | B1: <<<< Ir a objetos de dominio
A2: Representa un identificador que hará unico cada objeto de dominio de este tipo, no se puede repetir | B2: Referencia a qué barbero le pertence este bloqueo | C2: Representa la fecha y hora en el que el barbero empieza a no estar disponible para atender las citas | D2: Representa la fecha y hora en el que el barbero empieza estar disponible nuevamente para atender las citas | E2: Combinación única que indica que un mismo barbero no puede tener dos bloqueos con la misma fecha y hora de inicio y la misma fecha y hora final
A3: id | B3: barbero | C3: fechaHoraInicio | D3: fechaHoraFinal | E3: Combinación única
A4: 1 | B4: ='M-Barbero'!L4 -> +57-3245627890 | C4: 46188.5 | D4: 46188.542 | E4: =_xlfn.CONCAT(B4,"-",TEXT(C4,"dd/mm/yyyy hh:mm"),"-",TEXT(D4,"dd/mm/yyyy hh:mm")) -> +57-3245627890-15/06/2026 12:00-15/06/2026 13:00
A5: 2 | B5: ='M-Barbero'!L5 -> +57-3124518923 | C5: 46189.417 | D5: 46189.438 | E5: =_xlfn.CONCAT(B5,"-",TEXT(C5,"dd/mm/yyyy hh:mm"),"-",TEXT(D5,"dd/mm/yyyy hh:mm")) -> +57-3124518923-16/06/2026 10:00-16/06/2026 10:30
A6: 3 | B6: ='M-Barbero'!L6 -> +57-3214533321 | C6: 46191.583 | D6: 46191.625 | E6: =_xlfn.CONCAT(B6,"-",TEXT(C6,"dd/mm/yyyy hh:mm"),"-",TEXT(D6,"dd/mm/yyyy hh:mm")) -> +57-3214533321-18/06/2026 14:00-18/06/2026 15:00
A7: 4 | B7: ='M-Barbero'!L7 -> +91-9876543210 | C7: 46193.375 | D7: 46193.396 | E7: =_xlfn.CONCAT(B7,"-",TEXT(C7,"dd/mm/yyyy hh:mm"),"-",TEXT(D7,"dd/mm/yyyy hh:mm")) -> +91-9876543210-20/06/2026 09:00-20/06/2026 09:30
A8: 5 | B8: ='M-Barbero'!L7 -> +91-9876543210 | C8: 46195.667 | D8: 46195.698 | E8: =_xlfn.CONCAT(B8,"-",TEXT(C8,"dd/mm/yyyy hh:mm"),"-",TEXT(D8,"dd/mm/yyyy hh:mm")) -> +91-9876543210-22/06/2026 16:00-22/06/2026 16:45
B14: Corresponde a la descripcion de los atributos
B15: Corresponde al identificador unico del objeto de dominio
B16: Corresponde a las referencias de otros objetos de dominio
B17: Corresponde a los datos que ingresa el usuario
B18: Corresponde a la combinacion única

Sheet C-BarberoServicio
A1: <<<< Ir al modulo de dominio | B1: <<<< Ir a objetos de dominio
A2: Nombre atributo | B2: Descripción atributo | C2: Identificador del objeto de dominio | D2: Tipo de dato | E2: Obligatorio | F2: Longitud mínima (si aplica) | G2: Longitud máxima (si aplica) | H2: Precisión (si aplica) | I2: Rendondeo (si aplica) | J2: Rango inicial (si aplica) | K2: Rango final (si aplica) | L2: Formato (si aplica) | M2: Reglas especiales (si aplica) | N2: Dato calculado | O2: Aplica ajuste del dato (si aplica) | P2: Carácter de ajuste (si aplica) | Q2: Quitar espacios en blanco al inicio (si aplica) | R2: Quitar espacios en blanco al fin (si aplica) | S2: Dato sensible (si aplica) | T2: Valor por defecto (si aplica) | U2: Auto generado
A3: ='M-BarberoServicio'!A3 -> id | B3: ='M-BarberoServicio'!A2 -> Representa un identificador que hará unico cada objeto de dominio de este tipo, no se puede repetir | C3: Si | D3: Identificador único universal | E3: Si | F3: No aplica | G3: No aplica | H3: No aplica | I3: No aplica | J3: No aplica | K3: No aplica | L3: No aplica | M3: No aplica | N3: No | O3: No aplica | P3: No aplica | Q3: No aplica | R3: No aplica | S3: No | T3: UUID vacio | U3: Si
A4: ='M-BarberoServicio'!B3 -> barbero | B4: ='M-BarberoServicio'!B2 -> Representa el nombre y apellidos del barbero | C4: No | D4: Barbero | E4: Si | F4: No aplica | G4: No aplica | H4: No aplica | I4: No aplica | J4: No aplica | K4: No aplica | L4: No aplica | M4: Aplican las reglas del objeto referenciado | N4: No | O4: No aplica | P4: No aplica | Q4: No aplica | R4: No aplica | S4: No | T4: UUID vacio | U4: No
A5: ='M-BarberoServicio'!C3 -> servicio | B5: ='M-BarberoServicio'!C2 -> Representa el nombre del servicio de la barberia | C5: No | D5: Servicio | E5: Si | F5: No aplica | G5: No aplica | H5: No aplica | I5: No aplica | J5: No aplica | K5: No aplica | L5: No aplica | M5: Aplican las reglas del objeto referenciado | N5: No | O5: No aplica | P5: No aplica | Q5: No aplica | R5: No aplica | S5: No | T5: UUID vacio | U5: No
A6: ='M-BarberoServicio'!D3 -> duracionEnHoras | B6: ='M-BarberoServicio'!D2 -> Representa la cantidad de horas que un barbero tarda en realizar un servicio, esta duracion el barbero debe de ser consiente de cuanto se demora en realizarlo | C6: No | D6: Entero | E6: No | F6: No aplica | G6: No aplica | H6: No aplica | I6: No aplica | J6: 0 | K6: 3 | L6: No aplica | M6: No aplica | N6: No | O6: No aplica | P6: No aplica | Q6: No aplica | R6: No aplica | S6: No | T6: 0 | U6: No
A7: ='M-BarberoServicio'!E3 -> duracionEnMinutos | B7: ='M-BarberoServicio'!E2 -> Representa la cantidad de minutos que un barbero tarda en realizar un servicio, esta duracion el barbero debe de ser consiente de cuanto se demora en realizarlo | C7: No | D7: Entero | E7: No | F7: No aplica | G7: No aplica | H7: No aplica | I7: No aplica | J7: 0 | K7: 59 | L7: No aplica | M7: No aplica | N7: No | O7: No aplica | P7: No aplica | Q7: No aplica | R7: No aplica | S7: No | T7: 0 | U7: No
A8: ='M-BarberoServicio'!F3 -> tiempoExtra | B8: ='M-BarberoServicio'!F2 -> Representa la cantidad de minutos que un barbero pone de tiempo extra en las citas de su agenda, cada barbero usa este tiempo porque hay ocaciones que la cita se puede demorar más de lo previsto. Este tiempo les ayuda a evitar que se les retrase la agenda | C8: No | D8: Entero | E8: No | F8: No aplica | G8: No aplica | H8: No aplica | I8: No aplica | J8: 0 | K8: 59 | L8: No aplica | M8: No aplica | N8: No | O8: No aplica | P8: No aplica | Q8: No aplica | R8: No aplica | S8: No | T8: 0 | U8: No
A9: ='M-BarberoServicio'!G3 -> vigente | B9: ='M-BarberoServicio'!G2 -> Representa si el barbero sigue o no presentando el servicio en la barbería | C9: No | D9: Lógico | E9: No | F9: No aplica | G9: No aplica | H9: No aplica | I9: No aplica | J9: No aplica | K9: No aplica | L9: No aplica | M9: No aplica | N9: No | O9: No aplica | P9: No aplica | Q9: No aplica | R9: No aplica | S9: No | T9: Si | U9: No
A11: Nombre combinación única | B11: Descripción | C11: Atributos involucrados
A12: ='M-BarberoServicio'!H3 -> Combinación única | B12: ='M-BarberoServicio'!H2 -> Combinación única que indica que un mismo barbero no puede aparecer dos veces ofreciendo el mismo servicio | C12: barbero
C13: servicio
A15: Responsabilidad | C15: Descripción | G15: Entradas | J15: Salida | O15: Políticas (Reglas de Negocio) | Q15: Excepción
G16: Parámetro | H16: Tipo de dato | I16: Descripción | J16: Tipo de Dato | K16: Descripción | O16: Política | P16: Descripción | Q16: Detalle | R16: ¿Qué hago?
A17: Habilitar un servicio para el barbero | C17: Comando que permite a un barbero indicar que sabe realizar un servicio del catálogo, con su duración y colchón | G17: datos{barbero, servicio, duracionEnHoras, duracionEnMinutos, tiempoExtra} | H17: BarberoServicio | I17: Contiene la información requerida para habilitarle un servicio a un barbero | J17: BarberoServicio | K17: Contiene la información del servicio habilitado para el barbero | O17: ='P-BarberoServicio'!A6 -> P-BSE-0001 | P17: ='P-BarberoServicio'!B6 -> Asegurar que los datos requeridos (duración en horas, duración en minutos, tiempo extra) sean válidos en tipo de dato, obligatoriedad y rango | Q17: Generar una excepción indicándole al usuario cuáles tiempos del servicio no cumplen con las reglas definidas | R17: Detener operación
O18: ='P-BarberoServicio'!A7 -> P-BSE-0002 | P18: ='P-BarberoServicio'!B7 -> Asegurar que el barbero no tenga ya habilitado ese mismo servicio | Q18: Generar una excepción indicándole al usuario que el barbero ya tiene habilitado ese mismo servicio | R18: Detener operación
A19: Ajustar los tiempos de un servicio del barbero | C19: Permite modificar la duración y el tiempo extra que un barbero usa para un servicio ya habilitado | G19: id | H19: UUID | I19: Corresponde al identificador del servicio del barbero que se va a ajustar | J19: BarberoServicio | K19: Contiene la información del servicio del barbero con sus tiempos actualizados | O19: ='P-BarberoServicio'!A6 -> P-BSE-0001 | P19: ='P-BarberoServicio'!B6 -> Asegurar que los datos requeridos (duración en horas, duración en minutos, tiempo extra) sean válidos en tipo de dato, obligatoriedad y rango | Q19: Generar una excepción indicándole al usuario cuáles tiempos del servicio no cumplen con las reglas definidas | R19: Detener operación
G20: datos{duracionEnHoras, duracionEnMinutos, tiempoExtra} | H20: BarberoServicio | I20: Contiene los nuevos tiempos con los que se va a modificar el servicio
A21: Ver servicios elegidos | C21: Permite a un barbero consultar los servicios que tiene habilitados | G21: filtro{barbero} | H21: BarberoServicio | I21: Contiene el barbero por el cual se van a consultar sus servicios habilitados | J21: Lista<BarberoServicio> | K21: Contiene todos los servicios que el barbero tiene habilitados
A22: Ver servicios de un barbero | C22: Permite a un cliente consultar qué servicios ofrece un barbero en particular | G22: filtro{barbero} | H22: BarberoServicio | I22: Contiene el barbero por el cual se van a consultar los servicios que ofrece | J22: Lista<BarberoServicio> | K22: Contiene todos los servicios vigentes que ofrece ese barbero
A23: Dejar de prestar el servicio para el catálogo | C23: Permite a un barbero desactivar un servicio que ya no quiere seguir ofreciendo | G23: id | H23: UUID | I23: Corresponde al identificador del servicio del barbero que se va a desactivar | K23: No retorna ningún valor. En caso de error genera una excepción.

Sheet P-BarberoServicio
A1: << Ir al modelo de dominio | B1: << Ir al listado de objetos de dominio | C1: << Ir a la caracterización del objeto de dominio | D1: Ir al muestreo de datos del objeto de dominio >> | E1: Ir al event storming del objeto de dominio >>
A2: Objeto de Dominio: | B2: ='Objetos de Dominio'!A12 -> BarberoServicio
A3: Descripción: | B3: ='Objetos de Dominio'!B12 -> Representa qué servicios sabe hacer cada barbero, cuánto se demora en realizarlos y cuánto tiempo extra usa de colchón, ya que no todos los barberos ofrecen los mismos servicios que están en la barbería.
A4: Numero politica | B4: Descripcion politica | D4: Objeto responsable | E4: Regla responsable
A6: P-BSE-0001 | B6: Asegurar que los datos requeridos (duración en horas, duración en minutos, tiempo extra) sean válidos en tipo de dato, obligatoriedad y rango | D6: BarberoServicio
A7: P-BSE-0002 | B7: Asegurar que el barbero no tenga ya habilitado ese mismo servicio | D7: BarberoServicio

Sheet E-BarberoServicio
A1: << Ir al modelo de dominio | C1: << Ir al listado de objetos de dominio | F1: << Ir a la caracterización del objeto de dominio | J1: Ir al muestreo de datos del objeto de dominio >>
A2: Objeto de Dominio: | B2: ='Objetos de Dominio'!A12 -> BarberoServicio
A3: Descripción: | B3: ='Objetos de Dominio'!B12 -> Representa qué servicios sabe hacer cada barbero, cuánto se demora en realizarlos y cuánto tiempo extra usa de colchón, ya que no todos los barberos ofrecen los mismos servicios que están en la barbería.
A4: Actor | B4: Action/Command | D4: Entity/Aggregate/Object domain | E4: Read Model | G4: Business Rule/Policy | I4: External System | J4: Domain Event | K4: Hotspot/questions/Risk
A5: Actor | B5: Acción | C5: Descripción | D5: Objeto de dominio | E5: Información externa | G5: Políticas | I5: Sistema Externo | J5: Evento | K5: Aspectos por solucionar
E6: Información | F6: Descripción | G6: Número | H6: Descripción
A7: Barbero | B7: Habilitar un servicio para el barbero | C7: Comando que permite a un barbero indicar que sabe realizar un servicio del catálogo, con su duración y colchón | D7: =$B$2 -> BarberoServicio | G7: ='P-BarberoServicio'!A6 -> P-BSE-0001 | H7: aquí | J7: Servicio habilitado para barbero
G8: ='P-BarberoServicio'!A7 -> P-BSE-0002 | H8: aquí
A9: Barbero | B9: Ajustar los tiempos de un servicio del barbero | C9: Permite modificar la duración y el tiempo extra que un barbero usa para un servicio ya habilitado | D9: =$B$2 -> BarberoServicio | G9: ='P-BarberoServicio'!A6 -> P-BSE-0001 | H9: aquí | J9: Tiempos de servicio de barbero actualizados
A10: Barbero | B10: Ver servicios elegidos | C10: Permite a un barbero consultar los servicios que tiene habilitados | D10: =$B$2 -> BarberoServicio | J10: Servicios de barbero consultados
A11: Cliente | B11: Ver servicios de un barbero | C11: Permite a un cliente consultar qué servicios ofrece un barbero en particular | D11: =$B$2 -> BarberoServicio | J11: Servicios de barbero consultados
A12: Barbero | B12: Dejar de prestar el servicio para el catálogo | C12: Permite a un barbero desactivar un servicio que ya no quiere seguir ofreciendo | D12: =$B$2 -> BarberoServicio | J12: Servicio de barbero desactivado

Sheet M-BarberoServicio
A1: <<<< Ir al modulo de dominio | B1: <<<< Ir a objetos de dominio
A2: Representa un identificador que hará unico cada objeto de dominio de este tipo, no se puede repetir | B2: Representa el nombre y apellidos del barbero | C2: Representa el nombre del servicio de la barberia | D2: Representa la cantidad de horas que un barbero tarda en realizar un servicio, esta duracion el barbero debe de ser consiente de cuanto se demora en realizarlo | E2: Representa la cantidad de minutos que un barbero tarda en realizar un servicio, esta duracion el barbero debe de ser consiente de cuanto se demora en realizarlo | F2: Representa la cantidad de minutos que un barbero pone de tiempo extra en las citas de su agenda, cada barbero usa este tiempo porque hay ocaciones que la cita se puede demorar más de lo previsto. Este tiempo les ayuda a evitar que se les retrase la agenda | G2: Representa si el barbero sigue o no presentando el servicio en la barbería | H2: Combinación única que indica que un mismo barbero no puede aparecer dos veces ofreciendo el mismo servicio
A3: id | B3: barbero | C3: servicio | D3: duracionEnHoras | E3: duracionEnMinutos | F3: tiempoExtra | G3: vigente | H3: Combinación única
A4: 1 | B4: =_xlfn.CONCAT('M-Barbero'!B4," ",'M-Barbero'!D4) -> Juan García | C4: ='M-Servicio'!B4 -> Motilada | D4: 0 | E4: 45 | F4: 15 | G4: si | H4: =_xlfn.CONCAT(B4,"-",C4) -> Juan García-Motilada
A5: 2 | B5: =_xlfn.CONCAT('M-Barbero'!B5," ",'M-Barbero'!D5) -> Juan Ortiz | C5: ='M-Servicio'!B5 -> Corte de barba | D5: 0 | E5: 10 | F5: 5 | G5: si | H5: =_xlfn.CONCAT(B5,"-",C5) -> Juan Ortiz-Corte de barba
A6: 3 | B6: =_xlfn.CONCAT('M-Barbero'!B6," ",'M-Barbero'!D6) -> Carlos Arbeladez | C6: ='M-Servicio'!B6 -> Perfilada de barba | D6: 0 | E6: 15 | F6: 5 | G6: si | H6: =_xlfn.CONCAT(B6,"-",C6) -> Carlos Arbeladez-Perfilada de barba
A7: 4 | B7: =_xlfn.CONCAT('M-Barbero'!B7," ",'M-Barbero'!D7) -> Andres Ramirez | C7: ='M-Servicio'!B7 -> Arreglo completo de barba con toalla caliente | D7: 0 | E7: 40 | F7: 10 | G7: si | H7: =_xlfn.CONCAT(B7,"-",C7) -> Andres Ramirez-Arreglo completo de barba con toalla caliente
A8: 5 | B8: =_xlfn.CONCAT('M-Barbero'!B5," ",'M-Barbero'!D5) -> Juan Ortiz | C8: ='M-Servicio'!B4 -> Motilada | D8: 0 | E8: 40 | F8: 10 | G8: si | H8: =_xlfn.CONCAT(B8,"-",C8) -> Juan Ortiz-Motilada
A9: 6 | B9: =_xlfn.CONCAT('M-Barbero'!B6," ",'M-Barbero'!D6) -> Carlos Arbeladez | C9: ='M-Servicio'!B5 -> Corte de barba | D9: 0 | E9: 15 | F9: 5 | G9: si | H9: =_xlfn.CONCAT(B9,"-",C9) -> Carlos Arbeladez-Corte de barba
A10: 7 | B10: =_xlfn.CONCAT('M-Barbero'!B4," ",'M-Barbero'!D4) -> Juan García | C10: ='M-Servicio'!B6 -> Perfilada de barba | D10: 0 | E10: 20 | F10: 5 | G10: si | H10: =_xlfn.CONCAT(B10,"-",C10) -> Juan García-Perfilada de barba
A11: 8 | B11: =_xlfn.CONCAT('M-Barbero'!B7," ",'M-Barbero'!D7) -> Andres Ramirez | C11: ='M-Servicio'!B4 -> Motilada | D11: 0 | E11: 50 | F11: 15 | G11: si | H11: =_xlfn.CONCAT(B11,"-",C11) -> Andres Ramirez-Motilada
A12: 9 | B12: =_xlfn.CONCAT('M-Barbero'!B8," ",'M-Barbero'!D8) -> Juan Zambrano | C12: ='M-Servicio'!B5 -> Corte de barba | D12: 0 | E12: 12 | F12: 5 | G12: si | H12: =_xlfn.CONCAT(B12,"-",C12) -> Juan Zambrano-Corte de barba
B14: Corresponde a la descripcion de los atributos
B15: Corresponde al identificador unico del objeto de dominio
B16: Corresponde a las referencias de otros objetos de dominio
B17: Corresponde a los datos que ingresa el usuario
B18: Corresponde a la combinacion única

Sheet C-HorarioBarbero
A1: <<<< Ir al modulo de dominio | B1: <<<< Ir a objetos de dominio
A2: Nombre atributo | B2: Descripción atributo | C2: Identificador del objeto de dominio | D2: Tipo de dato | E2: Obligatorio | F2: Longitud mínima (si aplica) | G2: Longitud máxima (si aplica) | H2: Precisión (si aplica) | I2: Rendondeo (si aplica) | J2: Rango inicial (si aplica) | K2: Rango final (si aplica) | L2: Formato (si aplica) | M2: Reglas especiales (si aplica) | N2: Dato calculado | O2: Aplica ajuste del dato (si aplica) | P2: Carácter de ajuste (si aplica) | Q2: Quitar espacios en blanco al inicio (si aplica) | R2: Quitar espacios en blanco al fin (si aplica) | S2: Dato sensible (si aplica) | T2: Valor por defecto (si aplica) | U2: Auto generado
A3: ='M-HorarioBarbero'!A3 -> id | B3: ='M-HorarioBarbero'!A2 -> Representa un identificador que hará unico cada objeto de dominio de este tipo, no se puede repetir | C3: Si | D3: Identificador único universal | E3: Si | F3: No aplica | G3: No aplica | H3: No aplica | I3: No aplica | J3: No aplica | K3: No aplica | L3: No aplica | M3: No aplica | N3: No | O3: No | P3: No aplica | Q3: No | R3: No | S3: No | T3: UUID vacio | U3: Si
A4: ='M-HorarioBarbero'!B3 -> barbero | B4: ='M-HorarioBarbero'!B2 -> Referencia a que barbero va a ser dueño de este horario | C4: No | D4: Barbero | E4: Si | F4: No aplica | G4: No aplica | H4: No aplica | I4: No aplica | J4: No aplica | K4: No aplica | L4: No aplica | M4: Aplican las reglas del objeto referenciado | N4: No | O4: No aplica | P4: No aplica | Q4: No aplica | R4: No aplica | S4: No | T4: UUID vacio | U4: No
A5: ='M-HorarioBarbero'!C3 -> horarioDeLaBarberia | B5: ='M-HorarioBarbero'!C2 -> Hace referencia a la agenda del barbero en la que queda guardado este horario de trabajo | C5: No | D5: HorarioBarberia | E5: Si | F5: No aplica | G5: No aplica | H5: No aplica | I5: No aplica | J5: No aplica | K5: No aplica | L5: No aplica | M5: Aplican las reglas del objeto referenciado | N5: No | O5: No aplica | P5: No aplica | Q5: No aplica | R5: No aplica | S5: No | T5: UUID vacio | U5: No
A6: ='M-HorarioBarbero'!D3 -> horaInicio | B6: ='M-HorarioBarbero'!D2 -> Representa la hora en la que el barbero empieza a estar disponible ese dia | C6: No | D6: Hora | E6: Si | F6: No aplica | G6: No aplica | H6: No aplica | I6: No aplica | J6: No aplica | K6: No aplica | L6: hh:mm | M6: Debe estar dentro del rango de horarioDeLaBarberia | N6: No | O6: No aplica | P6: No aplica | Q6: No aplica | R6: No aplica | S6: No | T6: 00:00 | U6: No
A7: ='M-HorarioBarbero'!E3 -> horaFinal | B7: ='M-HorarioBarbero'!E2 -> Representa la hora en la que el barbero deja de estar disponible ese día. | C7: No | D7: Hora | E7: Si | F7: No aplica | G7: No aplica | H7: No aplica | I7: No aplica | J7: No aplica | K7: No aplica | L7: hh:mm | M7: Debe ser mayor a horaInicio y estar dentro del rango de horarioDeLaBarberia | N7: No | O7: No aplica | P7: No aplica | Q7: No aplica | R7: No aplica | S7: No | T7: 00:00 | U7: No
A8: ='M-HorarioBarbero'!F3 -> fechaCreacion | B8: ='M-HorarioBarbero'!F2 -> Representa la fecha en el que el barbero creo su horario. Es un dato calculado que toma la fecha de hoy cuando el barbero la crea | C8: No | D8: Fecha | E8: Si | F8: No aplica | G8: No aplica | H8: No aplica | I8: No aplica | J8: No aplica | K8: No aplica | L8: dd/mm/aaaa | M8: Toma la fecha del sistema en el momento en que el barbero crea este horario | N8: Si | O8: No aplica | P8: No aplica | Q8: No aplica | R8: No aplica | S8: No | T8: 01/01/1000 | U8: No
A9: ='M-HorarioBarbero'!G3 -> fechaDesactivacion | B9: ='M-HorarioBarbero'!G2 -> Representa la fecha en la que este horario dejó de estar vigente, ya sea porque el barbero lo retiró o porque se desactivó el horario de la barbería del que depende. Es un dato calculado que toma la fecha del sistema en ese momento. | C9: No | D9: Fecha | E9: No | F9: No aplica | G9: No aplica | H9: No aplica | I9: No aplica | J9: No aplica | K9: No aplica | L9: dd/mm/aaaa | M9: Toma la fecha del sistema en el momento en que el barbero desactiva este horario. Su valor por defecto es 01/01/1000 mientras siga vigente | N9: Si | O9: No aplica | P9: No aplica | Q9: No aplica | R9: No aplica | S9: No | T9: 01/01/1000 | U9: No
A10: ='M-HorarioBarbero'!H3 -> vigente | B10: ='M-HorarioBarbero'!H2 -> Representa si este horario lo sigue o no usando el barbero. Una vez que el barbero cambie este estado a no vigente, no se puede volver a cambiar | C10: No | D10: Lógico | E10: Si | F10: No aplica | G10: No aplica | H10: No aplica | I10: No aplica | J10: No aplica | K10: No aplica | L10: No aplica | M10: Una vez se cambia a No, no puede volver a cambiar a Si | N10: No | O10: No aplica | P10: No aplica | Q10: No aplica | R10: No aplica | S10: No | T10: Si | U10: No
A12: Nombre combinación única | B12: Descripción | C12: Atributos involucrados
A13: ='M-HorarioBarbero'!I3 -> Combinación única | B13: ='M-HorarioBarbero'!I2 -> Combinación única que indica que un mismo barbero no puede tener dos horarios con el mismo día de la barbería, la misma hora de inicio y la misma hora final. No incluye vigente porque la identidad de un horario no puede cambiar cuando se desactiva | C13: =A4 -> barbero
C14: =A5 -> horarioDeLaBarberia
C15: =A6 -> horaInicio
C16: =A7 -> horaFinal
C17: =A10 -> vigente
A19: Responsabilidad | C19: Descripción | G19: Entradas | J19: Salida | O19: Políticas (Reglas de Negocio) | Q19: Excepción
G20: Parámetro | H20: Tipo de dato | I20: Descripción | J20: Tipo de Dato | K20: Descripción | O20: Política | P20: Descripción | Q20: Detalle | R20: ¿Qué hago?
A21: Definir mi horario de trabajo | C21: Comando que permite a un barbero registrar el día de la semana y las horas en que trabaja | G21: datos{barbero, horarioDeLaBarberia, horaInicio, horaFinal} | H21: HorarioBarbero | I21: Contiene la información requerida para registrar el horario de trabajo del barbero | J21: HorarioBarbero | K21: Contiene la información del horario de trabajo registrado | O21: ='P-HorarioBarbero'!A6 -> P-HBO-0001 | P21: ='P-HorarioBarbero'!B6 -> Asegurar que los datos requeridos (día de la semana, hora de inicio, hora de fin) sean válidos en tipo de dato, obligatoriedad, formato y rango, y que la hora de fin sea mayor a la hora de inicio | Q21: Generar una excepción indicándole al usuario cuáles datos del horario de trabajo no cumplen con las reglas definidas | R21: Detener operación
O22: ='P-HorarioBarbero'!A7 -> P-HBO-0002 | P22: ='P-HorarioBarbero'!B7 -> Asegurar que el horario de trabajo esté dentro del horario de apertura y cierre de la barbería para ese día | Q22: Generar una excepción indicándole al usuario que el horario de trabajo queda por fuera del horario de apertura y cierre de la barbería para ese día | R22: Detener operación
A23: Ver mis horarios definidos | C23: Permite a un barbero consultar los horarios de trabajo que ha definido | G23: filtro{barbero} | H23: HorarioBarbero | I23: Contiene el barbero por el cual se van a consultar sus horarios de trabajo | J23: Lista<HorarioBarbero> | K23: Contiene todos los horarios de trabajo que el barbero tiene definidos
A24: Desactivar horario de trabajo | C24: Permite a un barbero desactivar un horario para dejar de trabajar ese día de la semana, desactivando en cascada lo que dependía de él | G24: id | H24: UUID | I24: Corresponde al identificador del horario de trabajo que se va a desactivar | K24: No retorna ningún valor. En caso de error genera una excepción. | O24: ='P-HorarioBarbero'!A8 -> P-HBO-0003 | P24: ='P-HorarioBarbero'!B8 -> Al desactivar un horario de trabajo del barbero, desactivar en cascada las agendas futuras que se habían generado a partir de ese horario | Q24: Si la desactivación de las agendas futuras falla, revertir la desactivación del horario de trabajo e informar el error | R24: Continuar operación
O25: ='P-HorarioBarbero'!A9 -> P-HBO-0004 | P25: ='P-HorarioBarbero'!B9 -> Cancelar las citas futuras que quedaron en esas agendas, dejándolas en el estado Cancelación por cambio de las políticas de horario de la barbería | Q25: Si la cancelación de las citas futuras falla, revertir toda la cascada e informar el error | R25: Continuar operación
O26: ='P-HorarioBarbero'!A10 -> P-HBO-0005 | P26: ='P-HorarioBarbero'!B10 -> Liberar los bloqueos futuros que el barbero tenía dentro de la jornada del horario que se desactiva, porque ya no hay disponibilidad que bloquear | Q26: Si la liberación de los bloqueos futuros falla, registrar el error sin revertir la desactivación | R26: Continuar operación
A27: Ver horarios de trabajo de un barbero | C27: Permite a un cliente consultar en qué días y horas trabaja un barbero | G27: filtro{barbero} | H27: HorarioBarbero | I27: Contiene el barbero por el cual se van a consultar sus horarios de trabajo | J27: Lista<HorarioBarbero> | K27: Contiene todos los horarios de trabajo vigentes de ese barbero

Sheet P-HorarioBarbero
A1: << Ir al modelo de dominio | B1: << Ir al listado de objetos de dominio | C1: << Ir a la caracterización del objeto de dominio | D1: Ir al muestreo de datos del objeto de dominio >> | E1: Ir al event storming del objeto de dominio >>
A2: Objeto de Dominio: | B2: ='Objetos de Dominio'!A13 -> HorarioBarbero
A3: Descripción: | B3: ='Objetos de Dominio'!B13 -> Representa el día de la semana en que trabaja un barbero, junto con la hora en la que empieza y termina su jornada de trabajo.
A4: Numero politica | B4: Descripcion politica | D4: Objeto responsable | E4: Regla responsable
A6: P-HBO-0001 | B6: Asegurar que los datos requeridos (día de la semana, hora de inicio, hora de fin) sean válidos en tipo de dato, obligatoriedad, formato y rango, y que la hora de fin sea mayor a la hora de inicio | D6: HorarioBarbero
A7: P-HBO-0002 | B7: Asegurar que el horario de trabajo esté dentro del horario de apertura y cierre de la barbería para ese día | D7: HorarioBarberia
A8: P-HBO-0003 | B8: Al desactivar un horario de trabajo del barbero, desactivar en cascada las agendas futuras que se habían generado a partir de ese horario | D8: Agenda
A9: P-HBO-0004 | B9: Cancelar las citas futuras que quedaron en esas agendas, dejándolas en el estado Cancelación por cambio de las políticas de horario de la barbería | D9: Cita
A10: P-HBO-0005 | B10: Liberar los bloqueos futuros que el barbero tenía dentro de la jornada del horario que se desactiva, porque ya no hay disponibilidad que bloquear | D10: Bloqueo

Sheet E-HorarioBarbero
A1: << Ir al modelo de dominio | C1: << Ir al listado de objetos de dominio | F1: << Ir a la caracterización del objeto de dominio | J1: Ir al muestreo de datos del objeto de dominio >>
A2: Objeto de Dominio: | B2: ='Objetos de Dominio'!A13 -> HorarioBarbero
A3: Descripción: | B3: ='Objetos de Dominio'!B13 -> Representa el día de la semana en que trabaja un barbero, junto con la hora en la que empieza y termina su jornada de trabajo.
A4: Actor | B4: Action/Command | D4: Entity/Aggregate/Object domain | E4: Read Model | G4: Business Rule/Policy | I4: External System | J4: Domain Event | K4: Hotspot/questions/Risk
A5: Actor | B5: Acción | C5: Descripción | D5: Objeto de dominio | E5: Información externa | G5: Políticas | I5: Sistema Externo | J5: Evento | K5: Aspectos por solucionar
E6: Información | F6: Descripción | G6: Número | H6: Descripción
A7: Barbero | B7: Definir mi horario de trabajo | C7: Comando que permite a un barbero registrar el día de la semana y las horas en que trabaja | D7: =$B$2 -> HorarioBarbero | G7: ='P-HorarioBarbero'!A6 -> P-HBO-0001 | H7: aquí | J7: Horario de barbero definido
G8: ='P-HorarioBarbero'!A7 -> P-HBO-0002 | H8: aquí
A9: Barbero | B9: Ver mis horarios definidos | C9: Permite a un barbero consultar los horarios de trabajo que ha definido | D9: =$B$2 -> HorarioBarbero | J9: Horarios de barbero consultados
A10: Barbero | B10: Desactivar horario de trabajo | C10: Permite a un barbero desactivar un horario para dejar de trabajar ese día de la semana, desactivando en cascada lo que dependía de él | D10: =$B$2 -> HorarioBarbero | E10: Agenda | F10: Permite identificar las agendas futuras generadas por ese horario para desactivarlas. | G10: ='P-HorarioBarbero'!A8 -> P-HBO-0003 | H10: ='P-HorarioBarbero'!B8 -> Al desactivar un horario de trabajo del barbero, desactivar en cascada las agendas futuras que se habían generado a partir de ese horario | J10: Horario de barbero desactivado
E11: Cita | F11: Permite identificar las citas futuras que quedan en esas agendas para cancelarlas. | G11: ='P-HorarioBarbero'!A9 -> P-HBO-0004 | H11: ='P-HorarioBarbero'!B9 -> Cancelar las citas futuras que quedaron en esas agendas, dejándolas en el estado Cancelación por cambio de las políticas de horario de la barbería
E12: Bloqueo | F12: Permite identificar los bloqueos futuros del barbero dentro de esa jornada para liberarlos. | G12: ='P-HorarioBarbero'!A10 -> P-HBO-0005 | H12: ='P-HorarioBarbero'!B10 -> Liberar los bloqueos futuros que el barbero tenía dentro de la jornada del horario que se desactiva, porque ya no hay disponibilidad que bloquear
E13: Estado | F13: Permite dejar esas citas en el estado Cancelación.
A14: Cliente | B14: Ver horarios de trabajo de un barbero | C14: Permite a un cliente consultar en qué días y horas trabaja un barbero | D14: =$B$2 -> HorarioBarbero | J14: Horarios de barbero consultados

Sheet M-HorarioBarbero
A1: <<<< Ir al modulo de dominio | B1: <<<< Ir a objetos de dominio
A2: Representa un identificador que hará unico cada objeto de dominio de este tipo, no se puede repetir | B2: Referencia a que barbero va a ser dueño de este horario | C2: Hace referencia a la agenda del barbero en la que queda guardado este horario de trabajo | D2: Representa la hora en la que el barbero empieza a estar disponible ese dia | E2: Representa la hora en la que el barbero deja de estar disponible ese día. | F2: Representa la fecha en el que el barbero creo su horario. Es un dato calculado que toma la fecha de hoy cuando el barbero la crea | G2: Representa la fecha en la que este horario dejó de estar vigente, ya sea porque el barbero lo retiró o porque se desactivó el horario de la barbería del que depende. Es un dato calculado que toma la fecha del sistema en ese momento. | H2: Representa si este horario lo sigue o no usando el barbero. Una vez que el barbero cambie este estado a no vigente, no se puede volver a cambiar | I2: Combinación única que indica que un mismo barbero no puede tener dos horarios con el mismo día de la barbería, la misma hora de inicio y la misma hora final. No incluye vigente porque la identidad de un horario no puede cambiar cuando se desactiva
A3: id | B3: barbero | C3: horarioDeLaBarberia | D3: horaInicio | E3: horaFinal | F3: fechaCreacion | G3: fechaDesactivacion | H3: vigente | I3: Combinación única
A4: 1 | B4: ='M-Barbero'!L4 -> +57-3245627890 | C4: ='M-HorarioBarberia'!H4 -> Lunes-09:00-19:00-12/11/2023-1/01/1000 | D4: 0.41666667 | E4: 0.66666667 | F4: 45780 | G4: 1/01/1000 | H4: si | I4: =_xlfn.CONCAT(B4,"-",C4,"-",TEXT(D4,"hh:mm"),"-",TEXT(E4,"hh:mm")) -> +57-3245627890-Lunes-09:00-19:00-12/11/2023-1/01/1000-10:00-16:00
A5: 2 | B5: ='M-Barbero'!L5 -> +57-3124518923 | C5: ='M-HorarioBarberia'!H5 -> Martes-09:00-19:00-12/11/2023-1/01/1000 | D5: 0.375 | E5: 0.625 | F5: 45718 | G5: 1/01/1000 | H5: si | I5: =_xlfn.CONCAT(B5,"-",C5,"-",TEXT(D5,"hh:mm"),"-",TEXT(E5,"hh:mm")) -> +57-3124518923-Martes-09:00-19:00-12/11/2023-1/01/1000-09:00-15:00
A6: 3 | B6: ='M-Barbero'!L6 -> +57-3214533321 | C6: ='M-HorarioBarberia'!H7 -> Jueves-09:00-19:00-12/11/2023-1/01/1000 | D6: 0.54166667 | E6: 0.79166667 | F6: 44917 | G6: 1/01/1000 | H6: si | I6: =_xlfn.CONCAT(B6,"-",C6,"-",TEXT(D6,"hh:mm"),"-",TEXT(E6,"hh:mm")) -> +57-3214533321-Jueves-09:00-19:00-12/11/2023-1/01/1000-13:00-19:00
A7: 4 | B7: ='M-Barbero'!L7 -> +91-9876543210 | C7: ='M-HorarioBarberia'!H9 -> Sábado-08:00-21:00-12/12/2024-1/01/1000 | D7: 0.33333333 | E7: 0.58333333 | F7: 45915 | G7: 46023 | H7: no | I7: =_xlfn.CONCAT(B7,"-",C7,"-",TEXT(D7,"hh:mm"),"-",TEXT(E7,"hh:mm")) -> +91-9876543210-Sábado-08:00-21:00-12/12/2024-1/01/1000-08:00-14:00
A8: 5 | B8: ='M-Barbero'!L7 -> +91-9876543210 | C8: ='M-HorarioBarberia'!H10 -> Festivo-10:00-15:00-12/12/2024-1/01/1000 | D8: 0.5 | E8: 0.625 | F8: 46054 | G8: 46083 | H8: no | I8: =_xlfn.CONCAT(B8,"-",C8,"-",TEXT(D8,"hh:mm"),"-",TEXT(E8,"hh:mm")) -> +91-9876543210-Festivo-10:00-15:00-12/12/2024-1/01/1000-12:00-15:00
B14: Corresponde a la descripcion de los atributos
B15: Corresponde al identificador unico del objeto de dominio
B16: Corresponde a las referencias de otros objetos de dominio
B17: Corresponde a los datos calculados por el sistema
B18: Corresponde a los datos que ingresa el usuario
B19: Corresponde a la combinacion única

Sheet C-Agenda
A1: <<<< Ir al modulo de dominio | B1: <<<< Ir a objetos de dominio
A2: Nombre atributo | B2: Descripción atributo | C2: Identificador del objeto de dominio | D2: Tipo de dato | E2: Obligatorio | F2: Longitud mínima (si aplica) | G2: Longitud máxima (si aplica) | H2: Precisión (si aplica) | I2: Rendondeo (si aplica) | J2: Rango inicial (si aplica) | K2: Rango final (si aplica) | L2: Formato (si aplica) | M2: Reglas especiales (si aplica) | N2: Dato calculado | O2: Aplica ajuste del dato (si aplica) | P2: Carácter de ajuste (si aplica) | Q2: Quitar espacios en blanco al inicio (si aplica) | R2: Quitar espacios en blanco al fin (si aplica) | S2: Dato sensible (si aplica) | T2: Valor por defecto (si aplica) | U2: Auto generado
A3: ='M-Agenda'!A3 -> id | B3: ='M-Agenda'!A2 -> Representa un identificador que hará unico cada objeto de dominio de este tipo, no se puede repetir | C3: Si | D3: Identificador único universal | E3: Si | F3: No aplica | G3: No aplica | H3: No aplica | I3: No aplica | J3: No aplica | K3: No aplica | L3: No aplica | M3: No aplica | N3: No | O3: No | P3: No aplica | Q3: No | R3: No | S3: No | T3: UUID vacio | U3: Si
A4: ='M-Agenda'!B3 -> horarioDelBarbero | B4: ='M-Agenda'!B2 -> Hace referencia al horario de trabajo del barbero (día de la semana, hora de inicio y hora final) al que pertenece esta agenda | C4: No | D4: HorarioBarbero | E4: Si | F4: No aplica | G4: No aplica | H4: No aplica | I4: No aplica | J4: No aplica | K4: No aplica | L4: No aplica | M4: Aplican las reglas del objeto referenciado | N4: No | O4: No aplica | P4: No aplica | Q4: No aplica | R4: No aplica | S4: No | T4: UUID vacio | U4: No
A5: ='M-Agenda'!C3 -> fecha | B5: ='M-Agenda'!C2 -> Representa la fecha específica en el que la agenda va a guardar las citas de ese barbero | C5: No | D5: Fecha | E5: Si | F5: No aplica | G5: No aplica | H5: No aplica | I5: No aplica | J5: No aplica | K5: No aplica | L5: No aplica | M5: No aplica | N5: No | O5: No aplica | P5: No aplica | Q5: No aplica | R5: No aplica | S5: No | T5: 01/01/1000 | U5: Si
A7: Nombre combinación única | B7: Descripción | C7: Atributos involucrados
A8: ='M-Agenda'!D3 -> Combinación única | B8: ='M-Agenda'!D2 -> Combinación única que indica que un mismo horario de barbero no puede tener más de una agenda para el mismo día | C8: =A4 -> horarioDelBarbero
C9: =A5 -> fecha
A11: Responsabilidad | C11: Descripción | G11: Entradas | J11: Salida | O11: Políticas (Reglas de Negocio) | Q11: Excepción
G12: Parámetro | H12: Tipo de dato | I12: Descripción | J12: Tipo de Dato | K12: Descripción | O12: Política | P12: Descripción | Q12: Detalle | R12: ¿Qué hago?
A13: Abrir la agenda de un barbero para una fecha | C13: Comando que crea la agenda del día para un barbero y pueda saber que citas debe de atender | G13: datos{horarioDelBarbero, fecha} | H13: Agenda | I13: Contiene la información requerida para abrirle la agenda del día a un barbero | J13: Agenda | K13: Contiene la información de la agenda abierta | O13: ='P-Agenda'!A6 -> P-AGE-0001 | P13: ='P-Agenda'!B6 -> Asegurar que no exista ya una agenda para ese mismo horario de barbero y esa misma fecha | Q13: Generar una excepción indicándole al usuario que ya existe una agenda para ese horario de barbero y esa misma fecha | R13: Detener operación
O14: ='P-Agenda'!A7 -> P-AGE-0002 | P14: ='P-Agenda'!B7 -> Asegurar que el barbero esté vigente antes de abrirle una nueva agenda | Q14: Generar una excepción indicándole al usuario que no se le puede abrir agenda porque el barbero no está vigente | R14: Detener operación
A15: Consultar la disponibilidad de un barbero para una fecha | C15: Permite a un cliente ver qué espacios le quedan libres a un barbero en una fecha, descontando sus citas ya agendadas y sus bloqueos | G15: filtro{barbero, fecha} | H15: Agenda | I15: Contiene el barbero y la fecha por los cuales se va a consultar la disponibilidad | J15: Lista<Hora> | K15: Contiene los espacios libres del barbero en esa fecha, descontando sus citas y sus bloqueos | O15: ='P-Agenda'!A8 -> P-AGE-0003 | P15: ='P-Agenda'!B8 -> Al consultar la disponibilidad de una agenda, descontar de la jornada del barbero las horas que ya tienen una cita y las que están cubiertas por un bloqueo | Q15: Si no se pueden descontar las citas o los bloqueos, informar que la disponibilidad no se pudo calcular | R15: Detener operación
A16: Consultar las citas de un barbero para una fecha | C16: Permite consultar todas las citas agrupadas en la agenda de un barbero para una fecha puntual | G16: filtro{barbero, fecha} | H16: Agenda | I16: Contiene el barbero y la fecha por los cuales se van a consultar las citas | J16: Lista<Cita> | K16: Contiene todas las citas agrupadas en la agenda del barbero para esa fecha

Sheet P-Agenda
A1: << Ir al modelo de dominio | B1: << Ir al listado de objetos de dominio | C1: << Ir a la caracterización del objeto de dominio | D1: Ir al muestreo de datos del objeto de dominio >> | E1: Ir al event storming del objeto de dominio >>
A2: Objeto de Dominio: | B2: ='Objetos de Dominio'!A14 -> Agenda
A3: Descripción: | B3: ='Objetos de Dominio'!B14 -> Representa una fecha puntual en donde el barbero ve todas las citas que debe de atender ese día.
A4: Numero politica | B4: Descripcion politica | D4: Objeto responsable | E4: Regla responsable
A6: P-AGE-0001 | B6: Asegurar que no exista ya una agenda para ese mismo horario de barbero y esa misma fecha | D6: Agenda
A7: P-AGE-0002 | B7: Asegurar que el barbero esté vigente antes de abrirle una nueva agenda | D7: Barbero
A8: P-AGE-0003 | B8: Al consultar la disponibilidad de una agenda, descontar de la jornada del barbero las horas que ya tienen una cita y las que están cubiertas por un bloqueo | D8: Agenda

Sheet E-Agenda
A1: << Ir al modelo de dominio | C1: << Ir al listado de objetos de dominio | F1: << Ir a la caracterización del objeto de dominio | J1: Ir al muestreo de datos del objeto de dominio >>
A2: Objeto de Dominio: | B2: ='Objetos de Dominio'!A14 -> Agenda
A3: Descripción: | B3: ='Objetos de Dominio'!B14 -> Representa una fecha puntual en donde el barbero ve todas las citas que debe de atender ese día.
A4: Actor | B4: Action/Command | D4: Entity/Aggregate/Object domain | E4: Read Model | G4: Business Rule/Policy | I4: External System | J4: Domain Event | K4: Hotspot/questions/Risk
A5: Actor | B5: Acción | C5: Descripción | D5: Objeto de dominio | E5: Información externa | G5: Políticas | I5: Sistema Externo | J5: Evento | K5: Aspectos por solucionar
E6: Información | F6: Descripción | G6: Número | H6: Descripción
A7: Sistema | B7: Abrir la agenda de un barbero para una fecha | C7: Comando que crea la agenda del día para un barbero y pueda saber que citas debe de atender | D7: =$B$2 -> Agenda | E7: Barbero | F7: Permite verificar que el barbero esté vigente antes de abrirle la agenda. | G7: ='P-Agenda'!A6 -> P-AGE-0001 | H7: ='P-Agenda'!B6 -> Asegurar que no exista ya una agenda para ese mismo horario de barbero y esa misma fecha | J7: Agenda abierta
E8: HorarioBarbero | F8: Permite conocer la jornada de trabajo del barbero para esa fecha. | G8: ='P-Agenda'!A7 -> P-AGE-0002 | H8: ='P-Agenda'!B7 -> Asegurar que el barbero esté vigente antes de abrirle una nueva agenda
A9: Cliente | B9: Consultar la disponibilidad de un barbero para una fecha | C9: Permite a un cliente ver qué espacios le quedan libres a un barbero en una fecha, descontando sus citas ya agendadas y sus bloqueos | D9: =$B$2 -> Agenda | E9: Cita | F9: Permite conocer las horas de esa fecha que ya están ocupadas por una cita. | G9: ='P-Agenda'!A8 -> P-AGE-0003 | H9: ='P-Agenda'!B8 -> Al consultar la disponibilidad de una agenda, descontar de la jornada del barbero las horas que ya tienen una cita y las que están cubiertas por un bloqueo | J9: Disponibilidad de barbero consultada
E10: Bloqueo | F10: Permite conocer las horas de esa fecha en las que el barbero no está disponible.
A11: Barbero | B11: Consultar las citas de un barbero para una fecha | C11: Permite consultar todas las citas agrupadas en la agenda de un barbero para una fecha puntual | D11: =$B$2 -> Agenda | J11: Citas de agenda consultadas
A12: Cliente | B12: Consultar las citas de un barbero para una fecha | C12: Permite consultar todas las citas agrupadas en la agenda de un barbero para una fecha puntual | D12: =$B$2 -> Agenda | J12: Citas de agenda consultadas

Sheet M-Agenda
A1: <<<< Ir al modulo de dominio | B1: <<<< Ir a objetos de dominio
A2: Representa un identificador que hará unico cada objeto de dominio de este tipo, no se puede repetir | B2: Hace referencia al horario de trabajo del barbero (día de la semana, hora de inicio y hora final) al que pertenece esta agenda | C2: Representa la fecha específica en el que la agenda va a guardar las citas de ese barbero | D2: Combinación única que indica que un mismo horario de barbero no puede tener más de una agenda para el mismo día
A3: id | B3: horarioDelBarbero | C3: fecha | D3: Combinación única
A4: 1 | B4: ='M-HorarioBarbero'!I4 -> +57-3245627890-Lunes-09:00-19:00-12/11/2023-1/01/1000-10:00-16:00 | C4: 46265 | D4: =_xlfn.CONCAT(B4,"-",TEXT(C4,"dd/mm/yyyy")) -> +57-3245627890-Lunes-09:00-19:00-12/11/2023-1/01/1000-10:00-16:00-31/08/2026
A5: 2 | B5: ='M-HorarioBarbero'!I5 -> +57-3124518923-Martes-09:00-19:00-12/11/2023-1/01/1000-09:00-15:00 | C5: 46091 | D5: =_xlfn.CONCAT(B5,"-",TEXT(C5,"dd/mm/yyyy")) -> +57-3124518923-Martes-09:00-19:00-12/11/2023-1/01/1000-09:00-15:00-10/03/2026
A6: 3 | B6: ='M-HorarioBarbero'!I6 -> +57-3214533321-Jueves-09:00-19:00-12/11/2023-1/01/1000-13:00-19:00 | C6: 46156 | D6: =_xlfn.CONCAT(B6,"-",TEXT(C6,"dd/mm/yyyy")) -> +57-3214533321-Jueves-09:00-19:00-12/11/2023-1/01/1000-13:00-19:00-14/05/2026
A7: 4 | B7: ='M-HorarioBarbero'!I8 -> +91-9876543210-Festivo-10:00-15:00-12/12/2024-1/01/1000-12:00-15:00 | C7: 46073 | D7: =_xlfn.CONCAT(B7,"-",TEXT(C7,"dd/mm/yyyy")) -> +91-9876543210-Festivo-10:00-15:00-12/12/2024-1/01/1000-12:00-15:00-20/02/2026
A8: 5 | B8: ='M-HorarioBarbero'!I7 -> +91-9876543210-Sábado-08:00-21:00-12/12/2024-1/01/1000-08:00-14:00 | C8: 45983 | D8: =_xlfn.CONCAT(B8,"-",TEXT(C8,"dd/mm/yyyy")) -> +91-9876543210-Sábado-08:00-21:00-12/12/2024-1/01/1000-08:00-14:00-22/11/2025
A9: 6 | B9: ='M-HorarioBarbero'!I6 -> +57-3214533321-Jueves-09:00-19:00-12/11/2023-1/01/1000-13:00-19:00 | C9: 46240 | D9: =_xlfn.CONCAT(B9,"-",TEXT(C9,"dd/mm/yyyy")) -> +57-3214533321-Jueves-09:00-19:00-12/11/2023-1/01/1000-13:00-19:00-06/08/2026
A10: 7 | B10: ='M-HorarioBarbero'!I4 -> +57-3245627890-Lunes-09:00-19:00-12/11/2023-1/01/1000-10:00-16:00 | C10: 46174 | D10: =_xlfn.CONCAT(B10,"-",TEXT(C10,"dd/mm/yyyy")) -> +57-3245627890-Lunes-09:00-19:00-12/11/2023-1/01/1000-10:00-16:00-01/06/2026
A11: 8 | B11: ='M-HorarioBarbero'!I5 -> +57-3124518923-Martes-09:00-19:00-12/11/2023-1/01/1000-09:00-15:00 | C11: 46189 | D11: =_xlfn.CONCAT(B11,"-",TEXT(C11,"dd/mm/yyyy")) -> +57-3124518923-Martes-09:00-19:00-12/11/2023-1/01/1000-09:00-15:00-16/06/2026
A12: 9 | B12: ='M-HorarioBarbero'!I6 -> +57-3214533321-Jueves-09:00-19:00-12/11/2023-1/01/1000-13:00-19:00 | C12: 46205 | D12: =_xlfn.CONCAT(B12,"-",TEXT(C12,"dd/mm/yyyy")) -> +57-3214533321-Jueves-09:00-19:00-12/11/2023-1/01/1000-13:00-19:00-02/07/2026
B18: Corresponde a la descripcion de los atributos
B19: Corresponde al identificador unico del objeto de dominio
B20: Corresponde a las referencias de otros objetos de dominio
B21: Corresponde a los datos auto generados por el sistema
B22: Corresponde a la combinacion única

Sheet C-Cita
A1: <<<< Ir al modulo de dominio | B1: <<<< Ir a objetos de dominio
A2: Nombre atributo | B2: Descripción atributo | C2: Identificador del objeto de dominio | D2: Tipo de dato | E2: Obligatorio | F2: Longitud mínima (si aplica) | G2: Longitud máxima (si aplica) | H2: Precisión (si aplica) | I2: Rendondeo (si aplica) | J2: Rango inicial (si aplica) | K2: Rango final (si aplica) | L2: Formato (si aplica) | M2: Reglas especiales (si aplica) | N2: Dato calculado | O2: Aplica ajuste del dato (si aplica) | P2: Carácter de ajuste (si aplica) | Q2: Quitar espacios en blanco al inicio (si aplica) | R2: Quitar espacios en blanco al fin (si aplica) | S2: Dato sensible (si aplica) | T2: Valor por defecto (si aplica) | U2: Auto generado
A3: ='M-Cita'!A3 -> id | B3: ='M-Cita'!A2 -> Representa un identificador que hará unico cada objeto de dominio de este tipo, no se puede repetir | C3: Si | D3: Identificador único universal | E3: Si | F3: No aplica | G3: No aplica | H3: No aplica | I3: No aplica | J3: No aplica | K3: No aplica | L3: No aplica | M3: No aplica | N3: No | O3: No | P3: No aplica | Q3: No | R3: No | S3: No | T3: UUID vacio | U3: Si
A4: ='M-Cita'!B3 -> cliente | B4: ='M-Cita'!B2 -> Representa a cuál cliente le pertenece esta cita | C4: No | D4: Cliente | E4: Si | F4: No aplica | G4: No aplica | H4: No aplica | I4: No aplica | J4: No aplica | K4: No aplica | L4: No aplica | M4: Se muestra el nombre completo del cliente, no una combinación única, únicamente para lectura humana en el muestreo | N4: No | O4: No aplica | P4: No aplica | Q4: No aplica | R4: No aplica | S4: No | T4: UUID vacio | U4: No
A5: ='M-Cita'!C3 -> agenda | B5: ='M-Cita'!C2 -> Referencia en cual agenda va a estar esta cita | C5: No | D5: Agenda | E5: Si | F5: No aplica | G5: No aplica | H5: No aplica | I5: No aplica | J5: No aplica | K5: No aplica | L5: No aplica | M5: Aplican las reglas del objeto referenciado | N5: No | O5: No aplica | P5: No aplica | Q5: No aplica | R5: No aplica | S5: No | T5: UUID vacio | U5: No
A6: ='M-Cita'!D3 -> estado | B6: ='M-Cita'!D2 -> Representa en qué estado se encuentra esta cita puntual: agendada, finalizada, cancelada, con tardanza del cliente o del barbero, o inasistencia | C6: No | D6: Estado | E6: Si | F6: No aplica | G6: No aplica | H6: No aplica | I6: No aplica | J6: No aplica | K6: No aplica | L6: No aplica | M6: Aplican las reglas del objeto referenciado | N6: No | O6: No aplica | P6: No aplica | Q6: No aplica | R6: No aplica | S6: No | T6: UUID vacio | U6: No
A7: ='M-Cita'!E3 -> horaInicio | B7: ='M-Cita'!E2 -> Representa la hora en la que se va a realizar la cita al cliente | C7: No | D7: Hora | E7: No | F7: No aplica | G7: No aplica | H7: No aplica | I7: No aplica | J7: No aplica | K7: No aplica | L7: No aplica | M7: Debe de estar dentro del horario de trabajo del barbero | N7: No | O7: No aplica | P7: No aplica | Q7: No aplica | R7: No aplica | S7: No | T7: 00:00 | U7: No
A8: ='M-Cita'!F3 -> horaFinEstimada | B8: ='M-Cita'!F2 -> Representa la hora en la que se espera que termine la cita, sumando horaInicio más la duración total de los servicios pedidos. Es un dato calculado | C8: No | D8: Hora | E8: Si | F8: No aplica | G8: No aplica | H8: No aplica | I8: No aplica | J8: No aplica | K8: No aplica | L8: No aplica | M8: horaInicio + duracion (en minutos) y debe de estar dentro del horario de trabajo del barbero | N8: Si | O8: No aplica | P8: No aplica | Q8: No aplica | R8: No aplica | S8: No | T8: 00:00 | U8: No
A9: ='M-Cita'!G3 -> horaLlegadaCliente | B9: ='M-Cita'!G2 -> Representa la hora real en la que el cliente llegó a la barbería para esta cita. Su valor por defecto es 00:00 y es permitido: significa que el cliente aún no ha llegado | C9: No | D9: Hora | E9: No | F9: No aplica | G9: No aplica | H9: No aplica | I9: No aplica | J9: No aplica | K9: No aplica | L9: No aplica | M9: No aplica | N9: No | O9: No aplica | P9: No aplica | Q9: No aplica | R9: No aplica | S9: No | T9: 00:00 | U9: No
A10: ='M-Cita'!H3 -> horaDelBarberoPreparado | B10: ='M-Cita'!H2 -> Representa la hora real en la que el barbero quedó listo y disponible para empezar a atender esta cita. Su valor por defecto es 00:00 y es permitido: significa que el barbero aún no se ha preparado | C10: No | D10: Hora | E10: No | F10: No aplica | G10: No aplica | H10: No aplica | I10: No aplica | J10: No aplica | K10: No aplica | L10: No aplica | M10: No aplica | N10: No | O10: No aplica | P10: No aplica | Q10: No aplica | R10: No aplica | S10: No | T10: 00:00 | U10: No
A11: ='M-Cita'!I3 -> horaInicioAtencion | B11: ='M-Cita'!I2 -> Representa la hora real en la que el barbero empezó a atender al cliente. Su valor por defecto es 00:00 y es permitido: significa que la atención aún no ha comenzado | C11: No | D11: Hora | E11: No | F11: No aplica | G11: No aplica | H11: No aplica | I11: No aplica | J11: No aplica | K11: No aplica | L11: No aplica | M11: No aplica | N11: No | O11: No aplica | P11: No aplica | Q11: No aplica | R11: No aplica | S11: No | T11: 00:00 | U11: No
A12: ='M-Cita'!J3 -> horaFinAtencion | B12: ='M-Cita'!J2 -> Representa la hora real en la que el barbero terminó de atender al cliente. Su valor por defecto es 00:00 y es permitido: significa que la atención aún no ha terminado | C12: No | D12: Hora | E12: No | F12: No aplica | G12: No aplica | H12: No aplica | I12: No aplica | J12: No aplica | K12: No aplica | L12: No aplica | M12: No aplica | N12: No | O12: No aplica | P12: No aplica | Q12: No aplica | R12: No aplica | S12: No | T12: 00:00 | U12: No
A13: ='M-Cita'!K3 -> duracionHoras | B13: ='M-Cita'!K2 -> Representa la cantidad total de horas que va a durar la cita, sumando la duración de cada servicio pedido más el tiempo extra de cada uno. Es un dato calculado | C13: No | D13: Entero | E13: No | F13: No aplica | G13: No aplica | H13: No aplica | I13: No aplica | J13: 0 | K13: 3 | L13: No aplica | M13: Resulta de dividir entre 60 la suma de duracionServicio + tiempoExtra de todos los CitaServicio de esta cita (parte en horas) | N13: Si | O13: No aplica | P13: No aplica | Q13: No aplica | R13: No aplica | S13: No | T13: 0 | U13: No
A14: ='M-Cita'!L3 -> duracionMinutos | B14: ='M-Cita'!L2 -> Representa la cantidad total de minutos que va a durar la cita, sumando la duración de cada servicio pedido más el tiempo extra de cada uno. Es un dato calculado | C14: No | D14: Entero | E14: No | F14: No aplica | G14: No aplica | H14: No aplica | I14: No aplica | J14: 0 | K14: 59 | L14: No aplica | M14: Resto en minutos de dividir entre 60 la suma de duracionServicio + tiempoExtra de todos los CitaServicio de esta cita (parte en minutos) | N14: Si | O14: No aplica | P14: No aplica | Q14: No aplica | R14: No aplica | S14: No | T14: 0 | U14: No
A15: ='M-Cita'!M3 -> minutosTardanzaCliente | B15: ='M-Cita'!M2 -> Representa cuántos minutos después de horaInicio llegó el cliente. Si llegó a tiempo o aún no ha llegado su valor es 0. Es un dato calculado | C15: No | D15: Entero | E15: No | F15: No aplica | G15: No aplica | H15: No aplica | I15: No aplica | J15: 0 | K15: 300 | L15: No aplica | M15: Si horaLlegadaCliente es 00:00 (no ha llegado), 0. Si no, MAX(0, horaLlegadaCliente - horaInicio) en minutos | N15: Si | O15: No aplica | P15: No aplica | Q15: No aplica | R15: No aplica | S15: No | T15: 0 | U15: No
A16: ='M-Cita'!N3 -> minutosDemoraBarbero | B16: ='M-Cita'!N2 -> Representa cuántos minutos después de la llegada del cliente empezó el barbero a atenderlo. Si no hubo demora su valor es 0. Es un dato calculado | C16: No | D16: Entero | E16: No | F16: No aplica | G16: No aplica | H16: No aplica | I16: No aplica | J16: 0 | K16: 300 | L16: No aplica | M16: Si horaInicioAtencion es 00:00 (no ha empezado), 0. Si no, MAX(0, horaInicioAtencion - MAX(horaLlegadaCliente, horaInicio)) en minutos | N16: Si | O16: No aplica | P16: No aplica | Q16: No aplica | R16: No aplica | S16: No | T16: 0 | U16: No
A17: ='M-Cita'!O3 -> porcentajeDescuento | B17: ='M-Cita'!O2 -> Representa el descuento que el barbero le concede al cliente por haberse demorado en atenderlo; solo se descuenta del precioTotal cuando la cita queda en el estado "El barbero se demoro" | C17: No | D17: Entero | E17: No | F17: No aplica | G17: No aplica | H17: No aplica | I17: No aplica | J17: 0 | K17: 100 | L17: No aplica | M17: Lo define el barbero y queda congelado en la cita; solo se descuenta del precioTotal cuando la cita queda en el estado "El barbero se demoro" | N17: No | O17: No aplica | P17: No aplica | Q17: No aplica | R17: No aplica | S17: No | T17: 0 | U17: No
A18: ='M-Cita'!P3 -> multa | B18: ='M-Cita'!P2 -> Representa el precio de sancion, en caso de que el cliente se demore | C18: No | D18: Entero | E18: No | F18: No aplica | G18: No aplica | H18: No aplica | I18: No aplica | J18: 0 | K18: 100000 | L18: No aplica | M18: Lo define el barbero al momento de agendar la cita y queda congelado en ella; es el valor que se le cobra al cliente si su tardanza supera el tiempoEspera de esta misma cita | N18: No | O18: No aplica | P18: No aplica | Q18: No aplica | R18: No aplica | S18: No | T18: 0 | U18: No
A19: ='M-Cita'!Q3 -> tiempoEspera | B19: ='M-Cita'!Q2 -> Representa la cantidad de minutos en el que el barbero puede esperar a un cliente, después de este tiempo de espera se le hace una sanción por retraso. Si el barbero se pasa de este tiempo se le da el descuento al cliente | C19: No | D19: Entero | E19: No | F19: No aplica | G19: No aplica | H19: No aplica | I19: No aplica | J19: 0 | K19: 60 | L19: No aplica | M19: Es el mismo margen para las dos partes: si el cliente lo supera se le genera una Multa de tipo Tardanza por el valor de multa, y si el barbero lo supera se le aplica al cliente el porcentajeDescuento sobre el precioTotal | N19: No | O19: No aplica | P19: No aplica | Q19: No aplica | R19: No aplica | S19: No | T19: 0 | U19: No
A20: ='M-Cita'!R3 -> precioTotal | B20: ='M-Cita'!R2 -> Representa cuánto debe pagar el cliente por los servicios de esta cita: la suma del precioServicio de todos sus CitaServicio, al que solo se le aplica el porcentajeDescuento cuando la cita quedó en el estado "El barbero se demoro" | C20: No | D20: Entero | E20: Si | F20: No aplica | G20: No aplica | H20: No aplica | I20: No aplica | J20: 0 | K20: 3000000 | L20: No aplica | M20: Suma del precioServicio de todos los CitaServicio de esta cita. Si el estado de la cita es "El barbero se demoro" se le resta el porcentajeDescuento; en cualquier otro estado se cobra la suma completa | N20: Si | O20: No aplica | P20: No aplica | Q20: No aplica | R20: No aplica | S20: No | T20: 0 | U20: No
A22: Nombre combinación única | B22: Descripción | C22: Atributos involucrados
A23: ='M-Cita'!S3 -> Combinación única | B23: ='M-Cita'!S2 -> Combinación única que indica que una misma agenda no puede tener dos citas que empiecen a la misma hora | C23: =A5 -> agenda
C24: =A7 -> horaInicio
A26: Responsabilidad | C26: Descripción | G26: Entradas | J26: Salida | O26: Políticas (Reglas de Negocio) | Q26: Excepción
G27: Parámetro | H27: Tipo de dato | I27: Descripción | J27: Tipo de Dato | K27: Descripción | O27: Política | P27: Descripción | Q27: Detalle | R27: ¿Qué hago?
A28: Pedir cita | C28: Comando que permite a un cliente solicitar una cita con un barbero, en una fecha y hora puntual, con uno o más servicios | G28: datos{cliente, agenda, horaInicio, servicios} | H28: Cita | I28: Contiene la información requerida para agendar una nueva cita con un barbero | J28: Cita | K28: Contiene la información de la cita agendada | O28: ='P-Cita'!A6 -> P-CIT-0001 | P28: ='P-Cita'!B6 -> Asegurar que los datos requeridos (hora de inicio, servicios solicitados) sean válidos en tipo de dato, obligatoriedad, formato y rango | Q28: Generar una excepción indicándole al usuario cuáles datos de la cita no cumplen con las reglas definidas | R28: Detener operación
O29: ='P-Cita'!A7 -> P-CIT-0002 | P29: ='P-Cita'!B7 -> Asegurar que el cliente no esté vetado antes de permitirle agendar | Q29: Generar una excepción indicándole al usuario que no puede agendar porque el cliente está vetado | R29: Detener operación
O30: ='P-Cita'!A8 -> P-CIT-0003 | P30: ='P-Cita'!B8 -> Asegurar que la agenda tenga disponibilidad y que la hora solicitada quepa dentro del horario del barbero sin solaparse con otra cita o bloqueo | Q30: Generar una excepción indicándole al usuario que el barbero no tiene disponibilidad en la hora solicitada | R30: Detener operación
O31: ='P-Cita'!A19 -> P-CIT-0014 | P31: ='P-Cita'!B19 -> Asegurar que la hora solicitada no caiga dentro de ningún bloqueo del barbero, ni que la cita se extienda sobre uno | Q31: Generar una excepción indicándole al usuario que la hora solicitada cae dentro de un bloqueo del barbero | R31: Detener operación
O32: ='P-Cita'!A9 -> P-CIT-0004 | P32: ='P-Cita'!B9 -> Asegurar que cada servicio solicitado esté habilitado para ese barbero | Q32: Generar una excepción indicándole al usuario que alguno de los servicios pedidos no está habilitado para ese barbero | R32: Detener operación
O33: ='P-Cita'!A18 -> P-CIT-0013 | P33: ='P-Cita'!B18 -> Asegurar que todos los servicios pedidos en la cita correspondan a un mismo barbero, porque una cita la atiende un único barbero de principio a fin | Q33: Generar una excepción indicándole al usuario que los servicios pedidos pertenecen a más de un barbero | R33: Detener operación
O34: ='P-Cita'!A10 -> P-CIT-0005 | P34: ='P-Cita'!B10 -> Asegurar que la cita se solicite con al menos la anticipación mínima definida por el barbero | Q34: Generar una excepción indicándole al usuario que la cita no cumple con la anticipación mínima que exige el barbero | R34: Detener operación
O35: ='P-Cita'!A11 -> P-CIT-0006 | P35: ='P-Cita'!B11 -> Congelar en la cita el valor de multa, el tiempoEspera y el porcentajeDescuento en el momento de agendarla, para que un cambio posterior no altere citas ya registradas | Q35: Si los valores de multa, tiempoEspera y porcentajeDescuento no se pueden congelar, no registrar la cita | R35: Detener operación
A36: Reprogramar la cita | C36: Permite a un cliente cambiar la fecha, hora o barbero de una cita que aún no ha ocurrido | G36: id | H36: UUID | I36: Corresponde al identificador de la cita que se va a reprogramar | J36: Cita | K36: Contiene la información de la cita reprogramada | O36: ='P-Cita'!A8 -> P-CIT-0003 | P36: ='P-Cita'!B8 -> Asegurar que la agenda tenga disponibilidad y que la hora solicitada quepa dentro del horario del barbero sin solaparse con otra cita o bloqueo | Q36: Generar una excepción indicándole al usuario que el barbero no tiene disponibilidad en la hora solicitada | R36: Detener operación
G37: datos{agenda, horaInicio} | H37: Cita | I37: Contiene la nueva agenda y hora con las que se va a reprogramar la cita | O37: ='P-Cita'!A19 -> P-CIT-0014 | P37: ='P-Cita'!B19 -> Asegurar que la hora solicitada no caiga dentro de ningún bloqueo del barbero, ni que la cita se extienda sobre uno | Q37: Generar una excepción indicándole al usuario que la hora solicitada cae dentro de un bloqueo del barbero | R37: Detener operación
O38: ='P-Cita'!A10 -> P-CIT-0005 | P38: ='P-Cita'!B10 -> Asegurar que la cita se solicite con al menos la anticipación mínima definida por el barbero | Q38: Generar una excepción indicándole al usuario que la cita no cumple con la anticipación mínima que exige el barbero | R38: Detener operación
A39: Cancelar la cita por decisión del cliente | C39: Permite a un cliente cancelar una cita antes de que ocurra, siempre que falten 2 horas o más para su horaInicio | G39: id | H39: UUID | I39: Corresponde al identificador de la cita que el cliente va a cancelar | J39: Cita | K39: Contiene la cita en el estado Cancelada por el cliente | O39: ='P-Cita'!A16 -> P-CIT-0011 | P39: ='P-Cita'!B16 -> Rechazar la cancelación cuando falten menos de 2 horas para la horaInicio de la cita: en ese caso el sistema no le permite al cliente cancelarla y la cita se mantiene | Q39: Generar una excepción indicándole al cliente que ya no puede cancelar la cita porque faltan menos de 2 horas para su horaInicio | R39: Detener operación
A40: Cancelar la cita por decisión del barbero | C40: Permite a un barbero cancelar una cita antes de que ocurra | G40: id | H40: UUID | I40: Corresponde al identificador de la cita que el barbero va a cancelar | J40: Cita | K40: Contiene la cita en el estado Cancelada por el barbero | O40: ='P-Cita'!A17 -> P-CIT-0012 | P40: ='P-Cita'!B17 -> Asegurar que el barbero cancele la cita con al menos 2 horas de anticipación frente a su horaInicio | Q40: Generar una excepción indicándole al barbero que ya no puede cancelar la cita porque faltan menos de 2 horas para su horaInicio | R40: Detener operación
A41: Registrar llegada del cliente | C41: Permite al barbero marcar la hora real en que el cliente llegó a su cita | G41: id | H41: UUID | I41: Corresponde al identificador de la cita a la que llegó el cliente | J41: Cita | K41: Contiene la cita con la hora de llegada del cliente registrada | O41: ='P-Cita'!A15 -> P-CIT-0010 | P41: ='P-Cita'!B15 -> Si minutosTardanzaCliente supera el tiempoEspera de la cita, generar una Multa de tipo Tardanza por el valor de multa de esa misma cita | Q41: Si la multa por tardanza no se puede generar, registrar el error y dejar la tardanza sin multa | R41: Continuar operación
G42: horaLlegadaCliente | H42: Hora | I42: Contiene la hora real en la que el cliente llegó a la barbería
A43: Iniciar la atención del cliente | C43: Permite al barbero marcar el inicio real de la atención de la cita | G43: id | H43: UUID | I43: Corresponde al identificador de la cita que se va a iniciar | J43: Cita | K43: Contiene la cita con la hora de inicio de la atención registrada | O43: ='P-Cita'!A14 -> P-CIT-0009 | P43: ='P-Cita'!B14 -> Si minutosDemoraBarbero supera el tiempoEspera de la cita, aplicar el porcentajeDescuento de esa misma cita sobre su precioTotal | Q43: Si el descuento no se puede aplicar, dejar el precioTotal sin descuento y registrar el error | R43: Continuar operación
G44: horaInicioAtencion | H44: Hora | I44: Contiene la hora real en la que el barbero empezó a atender
A45: Finalizar la atención del cliente | C45: Permite al barbero marcar el fin real de la atención y cerrar la cita | G45: id | H45: UUID | I45: Corresponde al identificador de la cita que se va a cerrar | J45: Cita | K45: Contiene la cita finalizada con su duración y su precioTotal calculados | O45: ='P-Cita'!A12 -> P-CIT-0007 | P45: ='P-Cita'!B12 -> Al finalizar la atención, calcular minutosTardanzaCliente, minutosDemoraBarbero, duración y precioTotal a partir de los tiempos realmente registrados | Q45: Si los tiempos y el precioTotal no se pueden calcular, no cerrar la cita e informar el error | R45: Detener operación
G46: horaFinAtencion | H46: Hora | I46: Contiene la hora real en la que el barbero terminó de atender
A47: Registrar la inasistencia del cliente | C47: Permite al barbero indicar que el cliente nunca llegó a la cita | G47: id | H47: UUID | I47: Corresponde al identificador de la cita a la que el cliente no asistió | J47: Cita | K47: Contiene la cita en el estado Inasistencia del cliente | O47: ='P-Cita'!A13 -> P-CIT-0008 | P47: ='P-Cita'!B13 -> Generar una Multa por el valor total de los servicios pedidos | Q47: Si la multa no se puede generar, registrar el error y dejar la inasistencia pendiente de multa | R47: Continuar operación

Sheet P-Cita
A1: << Ir al modelo de dominio | B1: << Ir al listado de objetos de dominio | C1: << Ir a la caracterización del objeto de dominio | D1: Ir al muestreo de datos del objeto de dominio >> | E1: Ir al event storming del objeto de dominio >>
A2: Objeto de Dominio: | B2: ='Objetos de Dominio'!A15 -> Cita
A3: Descripción: | B3: ='Objetos de Dominio'!B15 -> Representa la reserva de un cliente con un barbero para un fecha y hora puntual, con los servicios pedidos, su estado, y lo que realmente ocurrió (llegada, atención, tardanzas).
A4: Numero politica | B4: Descripcion politica | D4: Objeto responsable | E4: Regla responsable
A6: P-CIT-0001 | B6: Asegurar que los datos requeridos (hora de inicio, servicios solicitados) sean válidos en tipo de dato, obligatoriedad, formato y rango | D6: Cita
A7: P-CIT-0002 | B7: Asegurar que el cliente no esté vetado antes de permitirle agendar | D7: Cliente
A8: P-CIT-0003 | B8: Asegurar que la agenda tenga disponibilidad y que la hora solicitada quepa dentro del horario del barbero sin solaparse con otra cita o bloqueo | D8: Agenda
A9: P-CIT-0004 | B9: Asegurar que cada servicio solicitado esté habilitado para ese barbero | D9: BarberoServicio
A10: P-CIT-0005 | B10: Asegurar que la cita se solicite con al menos la anticipación mínima definida por el barbero | D10: Barbero
A11: P-CIT-0006 | B11: Congelar en la cita el valor de multa, el tiempoEspera y el porcentajeDescuento en el momento de agendarla, para que un cambio posterior no altere citas ya registradas | D11: Cita
A12: P-CIT-0007 | B12: Al finalizar la atención, calcular minutosTardanzaCliente, minutosDemoraBarbero, duración y precioTotal a partir de los tiempos realmente registrados | D12: CitaServicio
A13: P-CIT-0008 | B13: Generar una Multa por el valor total de los servicios pedidos | D13: Multa
A14: P-CIT-0009 | B14: Si minutosDemoraBarbero supera el tiempoEspera de la cita, aplicar el porcentajeDescuento de esa misma cita sobre su precioTotal | D14: Cita
A15: P-CIT-0010 | B15: Si minutosTardanzaCliente supera el tiempoEspera de la cita, generar una Multa de tipo Tardanza por el valor de multa de esa misma cita | D15: Multa
A16: P-CIT-0011 | B16: Rechazar la cancelación cuando falten menos de 2 horas para la horaInicio de la cita: en ese caso el sistema no le permite al cliente cancelarla y la cita se mantiene | D16: Cita
A17: P-CIT-0012 | B17: Asegurar que el barbero cancele la cita con al menos 2 horas de anticipación frente a su horaInicio | D17: Cita
... A19: P-CIT-0014 | B19: Asegurar que la hora solicitada no caiga dentro de ningún bloqueo del barbero, ni que la cita se extienda sobre uno | D19: Bloqueo

Sheet E-Cita
A1: << Ir al modelo de dominio | C1: << Ir al listado de objetos de dominio | F1: << Ir a la caracterización del objeto de dominio | J1: Ir al muestreo de datos del objeto de dominio >>
A2: Objeto de Dominio: | B2: ='Objetos de Dominio'!A15 -> Cita
A3: Descripción: | B3: ='Objetos de Dominio'!B15 -> Representa la reserva de un cliente con un barbero para un fecha y hora puntual, con los servicios pedidos, su estado, y lo que realmente ocurrió (llegada, atención, tardanzas).
A4: Actor | B4: Action/Command | D4: Entity/Aggregate/Object domain | E4: Read Model | G4: Business Rule/Policy | I4: External System | J4: Domain Event | K4: Hotspot/questions/Risk
A5: Actor | B5: Acción | C5: Descripción | D5: Objeto de dominio | E5: Información externa | G5: Políticas | I5: Sistema Externo | J5: Evento | K5: Aspectos por solucionar
E6: Información | F6: Descripción | G6: Número | H6: Descripción
A7: Cliente | B7: Pedir cita | C7: Comando que permite a un cliente solicitar una cita con un barbero, en una fecha y hora puntual, con uno o más servicios | D7: =$B$2 -> Cita | E7: Cliente | F7: Permite identificar quién solicita la cita y verificar que no esté vetado. | G7: ='P-Cita'!A6 -> P-CIT-0001 | H7: ='P-Cita'!B6 -> Asegurar que los datos requeridos (hora de inicio, servicios solicitados) sean válidos en tipo de dato, obligatoriedad, formato y rango | J7: Cita agendada | K7: ¿Cuántos servicios como máximo puede pedir un cliente en una misma cita? Aún no hay un límite definido, lo que deja sin techo real la duración total de una cita
E8: Agenda | F8: Permite conocer la disponibilidad del barbero en la fecha solicitada. | G8: ='P-Cita'!A7 -> P-CIT-0002 | H8: ='P-Cita'!B7 -> Asegurar que el cliente no esté vetado antes de permitirle agendar
E9: Bloqueo | F9: Permite conocer los rangos de tiempo en los que el barbero no está disponible. | G9: ='P-Cita'!A8 -> P-CIT-0003 | H9: ='P-Cita'!B8 -> Asegurar que la agenda tenga disponibilidad y que la hora solicitada quepa dentro del horario del barbero sin solaparse con otra cita o bloqueo
E10: HorarioBarbero | F10: Permite verificar que la hora solicitada esté dentro de la jornada del barbero. | G10: ='P-Cita'!A19 -> P-CIT-0014 | H10: ='P-Cita'!B19 -> Asegurar que la hora solicitada no caiga dentro de ningún bloqueo del barbero, ni que la cita se extienda sobre uno
E11: BarberoServicio | F11: Permite seleccionar los servicios de ese barbero y conocer su duración. | G11: ='P-Cita'!A9 -> P-CIT-0004 | H11: ='P-Cita'!B9 -> Asegurar que cada servicio solicitado esté habilitado para ese barbero
E12: Barbero | F12: Permite conocer la anticipación mínima que el barbero exige para agendar. | G12: ='P-Cita'!A18 -> P-CIT-0013 | H12: ='P-Cita'!B18 -> Asegurar que todos los servicios pedidos en la cita correspondan a un mismo barbero, porque una cita la atiende un único barbero de principio a fin
E13: Estado | F13: Permite asignar el estado inicial de la cita. | G13: ='P-Cita'!A10 -> P-CIT-0005 | H13: ='P-Cita'!B10 -> Asegurar que la cita se solicite con al menos la anticipación mínima definida por el barbero
G14: ='P-Cita'!A11 -> P-CIT-0006 | H14: ='P-Cita'!B11 -> Congelar en la cita el valor de multa, el tiempoEspera y el porcentajeDescuento en el momento de agendarla, para que un cambio posterior no altere citas ya registradas
A15: Cliente | B15: Reprogramar la cita | C15: Permite a un cliente cambiar la fecha, hora o barbero de una cita que aún no ha ocurrido | D15: =$B$2 -> Cita | E15: Agenda | F15: Permite conocer la disponibilidad del barbero en la nueva fecha. | G15: ='P-Cita'!A8 -> P-CIT-0003 | H15: ='P-Cita'!B8 -> Asegurar que la agenda tenga disponibilidad y que la hora solicitada quepa dentro del horario del barbero sin solaparse con otra cita o bloqueo | J15: Cita reprogramada
E16: Bloqueo | F16: Permite verificar que la nueva hora no caiga en un bloqueo del barbero. | G16: ='P-Cita'!A19 -> P-CIT-0014 | H16: ='P-Cita'!B19 -> Asegurar que la hora solicitada no caiga dentro de ningún bloqueo del barbero, ni que la cita se extienda sobre uno
E17: Barbero | F17: Permite verificar que la nueva hora respete su anticipación mínima. | G17: ='P-Cita'!A10 -> P-CIT-0005 | H17: ='P-Cita'!B10 -> Asegurar que la cita se solicite con al menos la anticipación mínima definida por el barbero
A18: Cliente | B18: Cancelar la cita por decisión del cliente | C18: Permite a un cliente cancelar una cita antes de que ocurra, siempre que falten 2 horas o más para su horaInicio | D18: =$B$2 -> Cita | E18: Estado | F18: Permite cambiar el estado a cancelada por el cliente cuando la cancelación es aceptada. | G18: ='P-Cita'!A16 -> P-CIT-0011 | H18: ='P-Cita'!B16 -> Rechazar la cancelación cuando falten menos de 2 horas para la horaInicio de la cita: en ese caso el sistema no le permite al cliente cancelarla y la cita se mantiene | J18: Cita cancelada por el cliente
A19: Barbero | B19: Cancelar la cita por decisión del barbero | C19: Permite a un barbero cancelar una cita antes de que ocurra | D19: =$B$2 -> Cita | E19: Estado | F19: Permite cambiar el estado a cancelada por el barbero. | G19: ='P-Cita'!A17 -> P-CIT-0012 | H19: ='P-Cita'!B17 -> Asegurar que el barbero cancele la cita con al menos 2 horas de anticipación frente a su horaInicio | J19: Cita cancelada por el barbero
A20: Barbero | B20: Registrar llegada del cliente | C20: Permite al barbero marcar la hora real en que el cliente llegó a su cita | D20: =$B$2 -> Cita | E20: Estado | F20: Permite cambiar el estado cuando la tardanza del cliente supera el tiempo de espera. | G20: ='P-Cita'!A15 -> P-CIT-0010 | H20: ='P-Cita'!B15 -> Si minutosTardanzaCliente supera el tiempoEspera de la cita, generar una Multa de tipo Tardanza por el valor de multa de esa misma cita | J20: Llegada de cliente registrada
A21: Barbero | B21: Iniciar la atención del cliente | C21: Permite al barbero marcar el inicio real de la atención de la cita | D21: =$B$2 -> Cita | E21: Estado | F21: Permite cambiar el estado cuando la demora del barbero supera el tiempo de espera. | G21: ='P-Cita'!A14 -> P-CIT-0009 | H21: ='P-Cita'!B14 -> Si minutosDemoraBarbero supera el tiempoEspera de la cita, aplicar el porcentajeDescuento de esa misma cita sobre su precioTotal | J21: Atención de cliente iniciada
A22: Barbero | B22: Finalizar la atención del cliente | C22: Permite al barbero marcar el fin real de la atención y cerrar la cita | D22: =$B$2 -> Cita | E22: CitaServicio | F22: Permite conocer los servicios prestados para calcular la duración y el precioTotal. | G22: ='P-Cita'!A12 -> P-CIT-0007 | H22: ='P-Cita'!B12 -> Al finalizar la atención, calcular minutosTardanzaCliente, minutosDemoraBarbero, duración y precioTotal a partir de los tiempos realmente registrados | J22: Atención de cliente finalizada
A23: Barbero | B23: Registrar la inasistencia del cliente | C23: Permite al barbero indicar que el cliente nunca llegó a la cita | D23: =$B$2 -> Cita | E23: Multa | F23: Permite generar la multa por inasistencia con el precioTotal de la cita. | G23: ='P-Cita'!A13 -> P-CIT-0008 | H23: ='P-Cita'!B13 -> Generar una Multa por el valor total de los servicios pedidos | J23: Inasistencia de cliente registrada
A24: Sistema | B24: Registrar la inasistencia del cliente | C24: Permite al sistema indicar que el cliente nunca llegó a la cita | D24: =$B$2 -> Cita | E24: Multa | F24: Permite generar la multa por inasistencia con el precioTotal de la cita. | G24: ='P-Cita'!A13 -> P-CIT-0008 | H24: ='P-Cita'!B13 -> Generar una Multa por el valor total de los servicios pedidos | J24: Inasistencia de cliente registrada

Sheet M-Cita
A1: <<<< Ir al modulo de dominio | B1: <<<< Ir a objetos de dominio
A2: Representa un identificador que hará unico cada objeto de dominio de este tipo, no se puede repetir | B2: Representa a cuál cliente le pertenece esta cita | C2: Referencia en cual agenda va a estar esta cita | D2: Representa en qué estado se encuentra esta cita puntual: agendada, finalizada, cancelada, con tardanza del cliente o del barbero, o inasistencia | E2: Representa la hora en la que se va a realizar la cita al cliente | F2: Representa la hora en la que se espera que termine la cita, sumando horaInicio más la duración total de los servicios pedidos. Es un dato calculado | G2: Representa la hora real en la que el cliente llegó a la barbería para esta cita. Su valor por defecto es 00:00 y es permitido: significa que el cliente aún no ha llegado | H2: Representa la hora real en la que el barbero quedó listo y disponible para empezar a atender esta cita. Su valor por defecto es 00:00 y es permitido: significa que el barbero aún no se ha preparado | I2: Representa la hora real en la que el barbero empezó a atender al cliente. Su valor por defecto es 00:00 y es permitido: significa que la atención aún no ha comenzado | J2: Representa la hora real en la que el barbero terminó de atender al cliente. Su valor por defecto es 00:00 y es permitido: significa que la atención aún no ha terminado | K2: Representa la cantidad total de horas que va a durar la cita, sumando la duración de cada servicio pedido más el tiempo extra de cada uno. Es un dato calculado | L2: Representa la cantidad total de minutos que va a durar la cita, sumando la duración de cada servicio pedido más el tiempo extra de cada uno. Es un dato calculado | M2: Representa cuántos minutos después de horaInicio llegó el cliente. Si llegó a tiempo o aún no ha llegado su valor es 0. Es un dato calculado | N2: Representa cuántos minutos después de la llegada del cliente empezó el barbero a atenderlo. Si no hubo demora su valor es 0. Es un dato calculado | O2: Representa el descuento que el barbero le concede al cliente por haberse demorado en atenderlo; solo se descuenta del precioTotal cuando la cita queda en el estado "El barbero se demoro" | P2: Representa el precio de sancion, en caso de que el cliente se demore | Q2: Representa la cantidad de minutos en el que el barbero puede esperar a un cliente, después de este tiempo de espera se le hace una sanción por retraso. Si el barbero se pasa de este tiempo se le da el descuento al cliente | R2: Representa cuánto debe pagar el cliente por los servicios de esta cita: la suma del precioServicio de todos sus CitaServicio, al que solo se le aplica el porcentajeDescuento cuando la cita quedó en el estado "El barbero se demoro" | S2: Combinación única que indica que una misma agenda no puede tener dos citas que empiecen a la misma hora
A3: id | B3: cliente | C3: agenda | D3: estado | E3: horaInicio | F3: horaFinEstimada | G3: horaLlegadaCliente | H3: horaDelBarberoPreparado | I3: horaInicioAtencion | J3: horaFinAtencion | K3: duracionHoras | L3: duracionMinutos | M3: minutosTardanzaCliente | N3: minutosDemoraBarbero | O3: porcentajeDescuento | P3: multa | Q3: tiempoEspera | R3: precioTotal | S3: Combinación única
A4: 1 | B4: ='M-Cliente'!J4 -> +57-3234528921 | C4: ='M-Agenda'!D4 -> +57-3245627890-Lunes-09:00-19:00-12/11/2023-1/01/1000-10:00-16:00-31/08/2026 | D4: ='M-Estado'!D4 -> Agendada | E4: 0.41666667 | F4: =E4+TIME(K4,L4,0) -> 0.45833333 | G4: 0 | H4: 0 | I4: 0 | J4: 0 | K4: =INT((SUMIF('M-CitaServicio'!$B$4:$B$14,S4,'M-CitaServicio'!$F$4:$F$14)+SUMIF('M-CitaServicio'!$B$4:$B$14,S4,'M-CitaServicio'!$G$4:$G$14))/60) -> 1 | L4: =MOD((SUMIF('M-CitaServicio'!$B$4:$B$14,S4,'M-CitaServicio'!$F$4:$F$14)+SUMIF('M-CitaServicio'!$B$4:$B$14,S4,'M-CitaServicio'!$G$4:$G$14)),60) -> 0 | M4: =IF(G4=TIME(0,0,0),0,ROUND(MAX(0,(G4-E4)*1440),0)) -> 0 | N4: =IF(I4=TIME(0,0,0),0,ROUND(MAX(0,(I4-MAX(G4,E4))*1440),0)) -> 0 | O4: 10 | P4: 10000 | Q4: 10 | R4: =SUMIF('M-CitaServicio'!$B$4:$B$14,S4,'M-CitaServicio'!$D$4:$D$14)*(1-IF(D4='M-Estado'!$D$9,O4,0)/100) -> 22000 | S4: =_xlfn.CONCAT(C4,"-",TEXT(E4,"hh:mm")) -> +57-3245627890-Lunes-09:00-19:00-12/11/2023-1/01/1000-10:00-16:00-31/08/2026-10:00
A5: 2 | B5: ='M-Cliente'!J5 -> +57-3161657782 | C5: ='M-Agenda'!D5 -> +57-3124518923-Martes-09:00-19:00-12/11/2023-1/01/1000-09:00-15:00-10/03/2026 | D5: ='M-Estado'!D5 -> Finalizada | E5: 0.39583333 | F5: =E5+TIME(K5,L5,0) -> 0.40625 | G5: 0.39444444 | H5: 0.39236111 | I5: 0.39583333 | J5: 0.40625 | K5: =INT((SUMIF('M-CitaServicio'!$B$4:$B$14,S5,'M-CitaServicio'!$F$4:$F$14)+SUMIF('M-CitaServicio'!$B$4:$B$14,S5,'M-CitaServicio'!$G$4:$G$14))/60) -> 0 | L5: =MOD((SUMIF('M-CitaServicio'!$B$4:$B$14,S5,'M-CitaServicio'!$F$4:$F$14)+SUMIF('M-CitaServicio'!$B$4:$B$14,S5,'M-CitaServicio'!$G$4:$G$14)),60) -> 15 | M5: =IF(G5=TIME(0,0,0),0,ROUND(MAX(0,(G5-E5)*1440),0)) -> 0 | N5: =IF(I5=TIME(0,0,0),0,ROUND(MAX(0,(I5-MAX(G5,E5))*1440),0)) -> 0 | O5: 10 | P5: 10000 | Q5: 10 | R5: =SUMIF('M-CitaServicio'!$B$4:$B$14,S5,'M-CitaServicio'!$D$4:$D$14)*(1-IF(D5='M-Estado'!$D$9,O5,0)/100) -> 12000 | S5: =_xlfn.CONCAT(C5,"-",TEXT(E5,"hh:mm")) -> +57-3124518923-Martes-09:00-19:00-12/11/2023-1/01/1000-09:00-15:00-10/03/2026-09:30
A6: 3 | B6: ='M-Cliente'!J6 -> +57-3119884321 | C6: ='M-Agenda'!D6 -> +57-3214533321-Jueves-09:00-19:00-12/11/2023-1/01/1000-13:00-19:00-14/05/2026 | D6: ='M-Estado'!D8 -> El cliente se demoro | E6: 0.54166667 | F6: =E6+TIME(K6,L6,0) -> 0.55555556 | G6: 0.55208333 | H6: 0.54305556 | I6: 0.55208333 | J6: 0.56597222 | K6: =INT((SUMIF('M-CitaServicio'!$B$4:$B$14,S6,'M-CitaServicio'!$F$4:$F$14)+SUMIF('M-CitaServicio'!$B$4:$B$14,S6,'M-CitaServicio'!$G$4:$G$14))/60) -> 0 | L6: =MOD((SUMIF('M-CitaServicio'!$B$4:$B$14,S6,'M-CitaServicio'!$F$4:$F$14)+SUMIF('M-CitaServicio'!$B$4:$B$14,S6,'M-CitaServicio'!$G$4:$G$14)),60) -> 20 | M6: =IF(G6=TIME(0,0,0),0,ROUND(MAX(0,(G6-E6)*1440),0)) -> 15 | N6: =IF(I6=TIME(0,0,0),0,ROUND(MAX(0,(I6-MAX(G6,E6))*1440),0)) -> 0 | O6: 10 | P6: 10000 | Q6: 10 | R6: =SUMIF('M-CitaServicio'!$B$4:$B$14,S6,'M-CitaServicio'!$D$4:$D$14)*(1-IF(D6='M-Estado'!$D$9,O6,0)/100) -> 15000 | S6: =_xlfn.CONCAT(C6,"-",TEXT(E6,"hh:mm")) -> +57-3214533321-Jueves-09:00-19:00-12/11/2023-1/01/1000-13:00-19:00-14/05/2026-13:00
A7: 4 | B7: ='M-Cliente'!J7 -> +58-4127359182 | C7: ='M-Agenda'!D8 -> +91-9876543210-Sábado-08:00-21:00-12/12/2024-1/01/1000-08:00-14:00-22/11/2025 | D7: ='M-Estado'!D10 -> Inasistencia del cliente | E7: 0.54166667 | F7: =E7+TIME(K7,L7,0) -> 0.57638889 | G7: 0 | H7: 0.52777778 | I7: 0 | J7: 0 | K7: =INT((SUMIF('M-CitaServicio'!$B$4:$B$14,S7,'M-CitaServicio'!$F$4:$F$14)+SUMIF('M-CitaServicio'!$B$4:$B$14,S7,'M-CitaServicio'!$G$4:$G$14))/60) -> 0 | L7: =MOD((SUMIF('M-CitaServicio'!$B$4:$B$14,S7,'M-CitaServicio'!$F$4:$F$14)+SUMIF('M-CitaServicio'!$B$4:$B$14,S7,'M-CitaServicio'!$G$4:$G$14)),60) -> 50 | M7: =IF(G7=TIME(0,0,0),0,ROUND(MAX(0,(G7-E7)*1440),0)) -> 0 | N7: =IF(I7=TIME(0,0,0),0,ROUND(MAX(0,(I7-MAX(G7,E7))*1440),0)) -> 0 | O7: 10 | P7: 12000 | Q7: 15 | R7: =SUMIF('M-CitaServicio'!$B$4:$B$14,S7,'M-CitaServicio'!$D$4:$D$14)*(1-IF(D7='M-Estado'!$D$9,O7,0)/100) -> 35000 | S7: =_xlfn.CONCAT(C7,"-",TEXT(E7,"hh:mm")) -> +91-9876543210-Sábado-08:00-21:00-12/12/2024-1/01/1000-08:00-14:00-22/11/2025-13:00
A8: 5 | B8: ='M-Cliente'!J7 -> +58-4127359182 | C8: ='M-Agenda'!D9 -> +57-3214533321-Jueves-09:00-19:00-12/11/2023-1/01/1000-13:00-19:00-06/08/2026 | D8: ='M-Estado'!D9 -> El barbero se demoro | E8: 0.75 | F8: =E8+TIME(K8,L8,0) -> 0.76388889 | G8: 0.74861111 | H8: 0.76388889 | I8: 0.76388889 | J8: 0.77777778 | K8: =INT((SUMIF('M-CitaServicio'!$B$4:$B$14,S8,'M-CitaServicio'!$F$4:$F$14)+SUMIF('M-CitaServicio'!$B$4:$B$14,S8,'M-CitaServicio'!$G$4:$G$14))/60) -> 0 | L8: =MOD((SUMIF('M-CitaServicio'!$B$4:$B$14,S8,'M-CitaServicio'!$F$4:$F$14)+SUMIF('M-CitaServicio'!$B$4:$B$14,S8,'M-CitaServicio'!$G$4:$G$14)),60) -> 20 | M8: =IF(G8=TIME(0,0,0),0,ROUND(MAX(0,(G8-E8)*1440),0)) -> 0 | N8: =IF(I8=TIME(0,0,0),0,ROUND(MAX(0,(I8-MAX(G8,E8))*1440),0)) -> 20 | O8: 10 | P8: 10000 | Q8: 10 | R8: =SUMIF('M-CitaServicio'!$B$4:$B$14,S8,'M-CitaServicio'!$D$4:$D$14)*(1-IF(D8='M-Estado'!$D$9,O8,0)/100) -> 10800 | S8: =_xlfn.CONCAT(C8,"-",TEXT(E8,"hh:mm")) -> +57-3214533321-Jueves-09:00-19:00-12/11/2023-1/01/1000-13:00-19:00-06/08/2026-18:00
A9: 6 | B9: ='M-Cliente'!J4 -> +57-3234528921 | C9: ='M-Agenda'!D7 -> +91-9876543210-Festivo-10:00-15:00-12/12/2024-1/01/1000-12:00-15:00-20/02/2026 | D9: ='M-Estado'!D5 -> Finalizada | E9: 0.58333333 | F9: =E9+TIME(K9,L9,0) -> 0.61805556 | G9: 0.58194444 | H9: 0.58333333 | I9: 0.58333333 | J9: 0.61805556 | K9: =INT((SUMIF('M-CitaServicio'!$B$4:$B$14,S9,'M-CitaServicio'!$F$4:$F$14)+SUMIF('M-CitaServicio'!$B$4:$B$14,S9,'M-CitaServicio'!$G$4:$G$14))/60) -> 0 | L9: =MOD((SUMIF('M-CitaServicio'!$B$4:$B$14,S9,'M-CitaServicio'!$F$4:$F$14)+SUMIF('M-CitaServicio'!$B$4:$B$14,S9,'M-CitaServicio'!$G$4:$G$14)),60) -> 50 | M9: =IF(G9=TIME(0,0,0),0,ROUND(MAX(0,(G9-E9)*1440),0)) -> 0 | N9: =IF(I9=TIME(0,0,0),0,ROUND(MAX(0,(I9-MAX(G9,E9))*1440),0)) -> 0 | O9: 10 | P9: 10000 | Q9: 10 | R9: =SUMIF('M-CitaServicio'!$B$4:$B$14,S9,'M-CitaServicio'!$D$4:$D$14)*(1-IF(D9='M-Estado'!$D$9,O9,0)/100) -> 35000 | S9: =_xlfn.CONCAT(C9,"-",TEXT(E9,"hh:mm")) -> +91-9876543210-Festivo-10:00-15:00-12/12/2024-1/01/1000-12:00-15:00-20/02/2026-14:00
A10: 7 | B10: ='M-Cliente'!J8 -> +57-3005544332 | C10: ='M-Agenda'!D10 -> +57-3245627890-Lunes-09:00-19:00-12/11/2023-1/01/1000-10:00-16:00-01/06/2026 | D10: ='M-Estado'!D10 -> Inasistencia del cliente | E10: 0.41666667 | F10: =E10+TIME(K10,L10,0) -> 0.45833333 | G10: 0 | H10: 0 | I10: 0 | J10: 0 | K10: =INT((SUMIF('M-CitaServicio'!$B$4:$B$14,S10,'M-CitaServicio'!$F$4:$F$14)+SUMIF('M-CitaServicio'!$B$4:$B$14,S10,'M-CitaServicio'!$G$4:$G$14))/60) -> 1 | L10: =MOD((SUMIF('M-CitaServicio'!$B$4:$B$14,S10,'M-CitaServicio'!$F$4:$F$14)+SUMIF('M-CitaServicio'!$B$4:$B$14,S10,'M-CitaServicio'!$G$4:$G$14)),60) -> 0 | M10: =IF(G10=TIME(0,0,0),0,ROUND(MAX(0,(G10-E10)*1440),0)) -> 0 | N10: =IF(I10=TIME(0,0,0),0,ROUND(MAX(0,(I10-MAX(G10,E10))*1440),0)) -> 0 | O10: 10 | P10: 12000 | Q10: 15 | R10: =SUMIF('M-CitaServicio'!$B$4:$B$14,S10,'M-CitaServicio'!$D$4:$D$14)*(1-IF(D10='M-Estado'!$D$9,O10,0)/100) -> 22000 | S10: =_xlfn.CONCAT(C10,"-",TEXT(E10,"hh:mm")) -> +57-3245627890-Lunes-09:00-19:00-12/11/2023-1/01/1000-10:00-16:00-01/06/2026-10:00
A11: 8 | B11: ='M-Cliente'!J8 -> +57-3005544332 | C11: ='M-Agenda'!D11 -> +57-3124518923-Martes-09:00-19:00-12/11/2023-1/01/1000-09:00-15:00-16/06/2026 | D11: ='M-Estado'!D10 -> Inasistencia del cliente | E11: 0.375 | F11: =E11+TIME(K11,L11,0) -> 0.38541667 | G11: 0 | H11: 0 | I11: 0 | J11: 0 | K11: =INT((SUMIF('M-CitaServicio'!$B$4:$B$14,S11,'M-CitaServicio'!$F$4:$F$14)+SUMIF('M-CitaServicio'!$B$4:$B$14,S11,'M-CitaServicio'!$G$4:$G$14))/60) -> 0 | L11: =MOD((SUMIF('M-CitaServicio'!$B$4:$B$14,S11,'M-CitaServicio'!$F$4:$F$14)+SUMIF('M-CitaServicio'!$B$4:$B$14,S11,'M-CitaServicio'!$G$4:$G$14)),60) -> 15 | M11: =IF(G11=TIME(0,0,0),0,ROUND(MAX(0,(G11-E11)*1440),0)) -> 0 | N11: =IF(I11=TIME(0,0,0),0,ROUND(MAX(0,(I11-MAX(G11,E11))*1440),0)) -> 0 | O11: 5 | P11: 10000 | Q11: 10 | R11: =SUMIF('M-CitaServicio'!$B$4:$B$14,S11,'M-CitaServicio'!$D$4:$D$14)*(1-IF(D11='M-Estado'!$D$9,O11,0)/100) -> 12000 | S11: =_xlfn.CONCAT(C11,"-",TEXT(E11,"hh:mm")) -> +57-3124518923-Martes-09:00-19:00-12/11/2023-1/01/1000-09:00-15:00-16/06/2026-09:00
A12: 9 | B12: ='M-Cliente'!J8 -> +57-3005544332 | C12: ='M-Agenda'!D12 -> +57-3214533321-Jueves-09:00-19:00-12/11/2023-1/01/1000-13:00-19:00-02/07/2026 | D12: ='M-Estado'!D10 -> Inasistencia del cliente | E12: 0.625 | F12: =E12+TIME(K12,L12,0) -> 0.63888889 | G12: 0 | H12: 0 | I12: 0 | J12: 0 | K12: =INT((SUMIF('M-CitaServicio'!$B$4:$B$14,S12,'M-CitaServicio'!$F$4:$F$14)+SUMIF('M-CitaServicio'!$B$4:$B$14,S12,'M-CitaServicio'!$G$4:$G$14))/60) -> 0 | L12: =MOD((SUMIF('M-CitaServicio'!$B$4:$B$14,S12,'M-CitaServicio'!$F$4:$F$14)+SUMIF('M-CitaServicio'!$B$4:$B$14,S12,'M-CitaServicio'!$G$4:$G$14)),60) -> 20 | M12: =IF(G12=TIME(0,0,0),0,ROUND(MAX(0,(G12-E12)*1440),0)) -> 0 | N12: =IF(I12=TIME(0,0,0),0,ROUND(MAX(0,(I12-MAX(G12,E12))*1440),0)) -> 0 | O12: 15 | P12: 10000 | Q12: 10 | R12: =SUMIF('M-CitaServicio'!$B$4:$B$14,S12,'M-CitaServicio'!$D$4:$D$14)*(1-IF(D12='M-Estado'!$D$9,O12,0)/100) -> 15000 | S12: =_xlfn.CONCAT(C12,"-",TEXT(E12,"hh:mm")) -> +57-3214533321-Jueves-09:00-19:00-12/11/2023-1/01/1000-13:00-19:00-02/07/2026-15:00
A13: 10 | B13: ='M-Cliente'!J5 -> +57-3161657782 | C13: ='M-Agenda'!D6 -> +57-3214533321-Jueves-09:00-19:00-12/11/2023-1/01/1000-13:00-19:00-14/05/2026 | D13: ='M-Estado'!D5 -> Finalizada | E13: 0.5625 | F13: =E13+TIME(K13,L13,0) -> 0.59027778 | G13: 0.56111111 | H13: 0.55902778 | I13: 0.5625 | J13: 0.59027778 | K13: =INT((SUMIF('M-CitaServicio'!$B$4:$B$14,S13,'M-CitaServicio'!$F$4:$F$14)+SUMIF('M-CitaServicio'!$B$4:$B$14,S13,'M-CitaServicio'!$G$4:$G$14))/60) -> 0 | L13: =MOD((SUMIF('M-CitaServicio'!$B$4:$B$14,S13,'M-CitaServicio'!$F$4:$F$14)+SUMIF('M-CitaServicio'!$B$4:$B$14,S13,'M-CitaServicio'!$G$4:$G$14)),60) -> 40 | M13: =IF(G13=TIME(0,0,0),0,ROUND(MAX(0,(G13-E13)*1440),0)) -> 0 | N13: =IF(I13=TIME(0,0,0),0,ROUND(MAX(0,(I13-MAX(G13,E13))*1440),0)) -> 0 | O13: 0 | P13: 10000 | Q13: 15 | R13: =SUMIF('M-CitaServicio'!$B$4:$B$14,S13,'M-CitaServicio'!$D$4:$D$14)*(1-IF(D13='M-Estado'!$D$9,O13,0)/100) -> 27000 | S13: =_xlfn.CONCAT(C13,"-",TEXT(E13,"hh:mm")) -> +57-3214533321-Jueves-09:00-19:00-12/11/2023-1/01/1000-13:00-19:00-14/05/2026-13:30
B19: Corresponde a la descripcion de los atributos
B20: Corresponde al identificador unico del objeto de dominio
B21: Corresponde a las referencias de otros objetos de dominio
B22: Corresponde a los datos calculados por el sistema
B23: Corresponde a los datos que ingresa el usuario
B24: Corresponde a la combinacion única

Sheet C-CitaServicio
A1: <<<< Ir al modulo de dominio | B1: <<<< Ir a objetos de dominio
A2: Nombre atributo | B2: Descripción atributo | C2: Identificador del objeto de dominio | D2: Tipo de dato | E2: Obligatorio | F2: Longitud mínima (si aplica) | G2: Longitud máxima (si aplica) | H2: Precisión (si aplica) | I2: Rendondeo (si aplica) | J2: Rango inicial (si aplica) | K2: Rango final (si aplica) | L2: Formato (si aplica) | M2: Reglas especiales (si aplica) | N2: Dato calculado | O2: Aplica ajuste del dato (si aplica) | P2: Carácter de ajuste (si aplica) | Q2: Quitar espacios en blanco al inicio (si aplica) | R2: Quitar espacios en blanco al fin (si aplica) | S2: Dato sensible (si aplica) | T2: Valor por defecto (si aplica) | U2: Auto generado
A3: ='M-CitaServicio'!A3 -> id | B3: ='M-CitaServicio'!A2 -> Representa un identificador que hará unico cada objeto de dominio de este tipo, no se puede repetir | C3: Si | D3: Identificador único universal | E3: Si | F3: No aplica | G3: No aplica | H3: No aplica | I3: No aplica | J3: No aplica | K3: No aplica | L3: No aplica | M3: No aplica | N3: No | O3: No | P3: No aplica | Q3: No | R3: No | S3: No | T3: UUID vacio | U3: Si
A4: ='M-CitaServicio'!B3 -> cita | B4: ='M-CitaServicio'!B2 -> Hace referencia a la cita a la que pertenece este servicio pedido | C4: No | D4: Cita | E4: Si | F4: No aplica | G4: No aplica | H4: No aplica | I4: No aplica | J4: No aplica | K4: No aplica | L4: No aplica | M4: Aplican las reglas del objeto referenciado | N4: No | O4: No aplica | P4: No aplica | Q4: No aplica | R4: No aplica | S4: No | T4: UUID vacio | U4: No
A5: ='M-CitaServicio'!C3 -> barberoServicio | B5: ='M-CitaServicio'!C2 -> Hace referencia a qué servicio, de qué barbero específico, se pidió en esta cita. No se referencia el Servicio directamente porque un barbero podría no ofrecerlo | C5: No | D5: BarberoServicio | E5: Si | F5: No aplica | G5: No aplica | H5: No aplica | I5: No aplica | J5: No aplica | K5: No aplica | L5: No aplica | M5: Aplican las reglas del objeto referenciado | N5: No | O5: No aplica | P5: No aplica | Q5: No aplica | R5: No aplica | S5: No | T5: UUID vacio | U5: No
A6: ='M-CitaServicio'!D3 -> precioServicio | B6: ='M-CitaServicio'!D2 -> Representa el precio que tenía el servicio en el momento en que se agendó esta cita. Es un dato auto generado: copia de Servicio.precio, para que cambios futuros en el precio del catálogo no alteren una cita ya registrada | C6: No | D6: Entero | E6: Si | F6: No aplica | G6: No aplica | H6: No aplica | I6: No aplica | J6: 0 | K6: 2000000 | L6: No aplica | M6: Copia de Servicio.precio en el momento de agendar la cita | N6: No | O6: No aplica | P6: No aplica | Q6: No aplica | R6: No aplica | S6: No | T6: 0 | U6: Si
A7: ='M-CitaServicio'!E3 -> duracionEnHorasElServicio | B7: ='M-CitaServicio'!E2 -> Representa la duración en horas que tenía el servicio para ese barbero en el momento en que se agendó esta cita. Es un dato auto generado: copia de BarberoServicio.duracionServicio | C7: No | D7: Entero | E7: Si | F7: No aplica | G7: No aplica | H7: No aplica | I7: No aplica | J7: 0 | K7: 3 | L7: No aplica | M7: Copia de BarberoServicio.duracionEnHoras en el momento de agendar la cita | N7: No | O7: No aplica | P7: No aplica | Q7: No aplica | R7: No aplica | S7: No | T7: 0 | U7: Si
A8: ='M-CitaServicio'!F3 -> duracionEnMinutosElServicio | B8: ='M-CitaServicio'!F2 -> Representa la duración en minutos que tenía el servicio para ese barbero en el momento en que se agendó esta cita. Es un dato auto generado: copia de BarberoServicio.duracionServicio | C8: No | D8: Entero | E8: Si | F8: No aplica | G8: No aplica | H8: No aplica | I8: No aplica | J8: 0 | K8: 59 | L8: No aplica | M8: Copia de BarberoServicio.duracionServicio en el momento de agendar la cita | N8: No | O8: No aplica | P8: No aplica | Q8: No aplica | R8: No aplica | S8: No | T8: 0 | U8: Si
A9: ='M-CitaServicio'!G3 -> tiempoExtra | B9: ='M-CitaServicio'!G2 -> Representa el tiempo extra en minutos que ese barbero tenía configurado para este servicio en el momento en que se agendó la cita. Es un dato auto generado: copia de BarberoServicio.tiempoExtra, para que cambios futuros en el tiempo extra no alteren una cita ya registrada | C9: No | D9: Entero | E9: Si | F9: No aplica | G9: No aplica | H9: No aplica | I9: No aplica | J9: 0 | K9: 59 | L9: No aplica | M9: Copia de BarberoServicio.tiempoExtra en el momento de agendar la cita | N9: No | O9: No aplica | P9: No aplica | Q9: No aplica | R9: No aplica | S9: No | T9: 0 | U9: Si
A11: Nombre combinación única | B11: Descripción | C11: Atributos involucrados
