Workbook

Sheet Modelo de Dominio
A1: Ir a objetos de dominio >>>>

Sheet Objetos de Dominio
A1: <<<< Ir al modulo de dominio
A2: Nombre | B2: Descripcion | C2: Linea de vida | D2: Muestreo | E2: Caracterización | F2: Event Storming | G2: Politicas
A3: Bloqueo | B3: Representa los momentos en que el barbero no esta disponible para atender sus citas | C3: 1 | D3: Ir al muestreo | E3: Ir a la caracterización | F3: Ir al Event Storming | G3: Ir a las políticas
A4: DiaSemana | B4: Representa cada uno de los días de la semana, incluyendo festivo, que se usa como catálogo para definir los horarios de la barbería y de cada barbero | C4: 1 | D4: Ir al muestreo | E4: Ir a la caracterización | F4: Ir al Event Storming | G4: Ir a las políticas
A5: Estado | B5: Representa en qué situación puntual se encuentra una cita: agendada, finalizada, cancelada por alguna de las partes, con tardanza del cliente o del barbero, o con inasistencia del cliente | C5: 1 | D5: Ir al muestreo | E5: Ir a la caracterización | F5: Ir al Event Storming | G5: Ir a las políticas
A6: Servicio | B6: Representa cada tipo de corte o arreglo que ofrece la barbería, definido por el dueño, para que luego cada barbero decida cuáles sabe hacer | C6: 1 | D6: Ir al muestreo | E6: Ir a la caracterización | F6: Ir al Event Storming | G6: Ir a las políticas
A7: Regla | B7: Representa las políticas de la barbería frente al incumplimiento de clientes y barberos: tolerancias de tardanza, monto de la multa fija, número máximo de multas sin pagar antes del veto, y el descuento que se da cuando el barbero se demora | C7: 1 | D7: Ir al muestreo | E7: Ir a la caracterización | F7: Ir al Event Storming | G7: Ir a las políticas
A8: PrefijoCelular | B8: Representa el catálogo de prefijos telefónicos de país disponibles para el número de celular de barberos y clientes | C8: 1 | D8: Ir al muestreo | E8: Ir a la caracterización | F8: Ir al Event Storming | G8: Ir a las políticas
A9: TipoMulta | B9: Representa los tipos de multa que puede recibir un cliente: por tardanza o por inasistencia | C9: 1 | D9: Ir al muestreo | E9: Ir a la caracterización | F9: Ir al Event Storming | G9: Ir a las políticas
A10: Barbero | B10: Representa a un trabajador de la barbería que atiende clientes según los servicios que sabe realizar, organiza su propio horario y tiene su agenda personal | C10: 2 | D10: Ir al muestreo | E10: Ir a la caracterización | F10: Ir al Event Storming | G10: Ir a las políticas
A11: Cliente | B11: Representa a la persona que solicita citas en la barbería con un barbero. Guarda su historial de multas sin pagar para saber si está o no vetado | C11: 2 | D11: Ir al muestreo | E11: Ir a la caracterización | F11: Ir al Event Storming | G11: Ir a las políticas
A12: HorarioBarberia | B12: Representa, día por día, a qué hora abre y cierra el negocio; es el límite dentro del cual debe caber el horario de cualquier barbero | C12: 2 | D12: Ir al muestreo | E12: Ir a la caracterización | F12: Ir al Event Storming | G12: Ir a las políticas
A13: BarberoServicio | B13: Representa qué servicios sabe hacer cada barbero, cuánto se demora en realizarlos y cuánto tiempo extra usa de colchón, ya que no todos los barberos ofrecen los mismos servicios | C13: 3 | D13: Ir al muestreo | E13: Ir a la caracterización | F13: Ir al Event Storming | G13: Ir a las políticas
A14: HorarioBarbero | B14: Representa el día de la semana en que trabaja un barbero, junto con la hora en la que empieza y termina su jornada | C14: 3 | D14: Ir al muestreo | E14: Ir a la caracterización | F14: Ir al Event Storming | G14: Ir a las políticas
... A18: Multa | B18: Representa la sanción económica que se le impone a un cliente por incumplir una cita, ya sea por llegar tarde fuera de tolerancia o por no presentarse, calculada a partir de la cita específica que la originó | C18: 6 | D18: Ir al muestreo | E18: Ir a la caracterización | F18: Ir al Event Storming | G18: Ir a las políticas

Sheet C-Bloqueo
A1: <<<< Ir al modulo de dominio | B1: <<<< Ir a objetos de dominio
A2: Nombre atributo | B2: Descripción atributo | C2: Identificador del objeto de dominio | D2: Tipo de dato | E2: Obligatorio | F2: Longitud mínima (si aplica) | G2: Longitud máxima (si aplica) | H2: Precisión (si aplica) | I2: Rendondeo (si aplica) | J2: Rango inicial (si aplica) | K2: Rango final (si aplica) | L2: Formato (si aplica) | M2: Reglas especiales (si aplica) | N2: Dato calculado | O2: Aplica ajuste del dato (si aplica) | P2: Carácter de ajuste (si aplica) | Q2: Quitar espacios en blanco al inicio (si aplica) | R2: Quitar espacios en blanco al fin (si aplica) | S2: Dato sensible (si aplica) | T2: Valor por defecto (si aplica) | U2: Auto generado
A3: ='M-Bloqueo'!A3 -> id | B3: ='M-Bloqueo'!A2 -> Representa un identificador que hará unico cada objeto de dominio de este tipo, no se puede repetir | C3: Si | D3: Identificador único universal | E3: Si | F3: No aplica | G3: No aplica | H3: No aplica | I3: No aplica | J3: No aplica | K3: No aplica | L3: No aplica | M3: No aplica | N3: No | O3: No | P3: No aplica | Q3: No | R3: No | S3: No | T3: UUID vacio | U3: Si
A4: ='M-Bloqueo'!B3 -> barbero | B4: ='M-Bloqueo'!B2 -> Referencia a qué barbero le pertence este bloqueo | C4: No | D4: Barbero | E4: Si | F4: No aplica | G4: No aplica | H4: No aplica | I4: No aplica | J4: No aplica | K4: No aplica | L4: No aplica | M4: Aplican las reglas del objeto referenciado | N4: No | O4: No aplica | P4: No aplica | Q4: No aplica | R4: No aplica | S4: No | T4: UUID vacio | U4: No
A5: ='M-Bloqueo'!C3 -> fechaHoraInicio | B5: ='M-Bloqueo'!C2 -> Representa la fecha y hora en el que el barbero empieza a no estar disponible para atender las citas | C5: No | D5: Fecha hora | E5: Si | F5: No aplica | G5: No aplica | H5: No aplica | I5: No aplica | J5: No aplica | K5: No aplica | L5: No aplica | M5: No aplica | N5: No | O5: No aplica | P5: No aplica | Q5: No aplica | R5: No aplica | S5: No | T5: 01/01/1000 00:00 | U5: No
A6: ='M-Bloqueo'!D3 -> fechaHoraFinal | B6: ='M-Bloqueo'!D2 -> Representa la fecha y hora en el que el barbero empieza estar disponible nuevamente para atender las citas | C6: No | D6: Fecha hora | E6: Si | F6: No aplica | G6: No aplica | H6: No aplica | I6: No aplica | J6: No aplica | K6: No aplica | L6: No aplica | M6: Debe ser posterior a fechaHoraInicio | N6: No | O6: No aplica | P6: No aplica | Q6: No aplica | R6: No aplica | S6: No | T6: 01/01/1000 00:00 | U6: No
A8: Nombre combinación única | B8: Descripción | C8: Atributos involucrados
A9: ='M-Bloqueo'!E3 -> Combinación única | B9: ='M-Bloqueo'!E2 -> Combinación única que indica que un mismo barbero no puede tener dos bloqueos con la misma fecha y hora de inicio y la misma fecha y hora final | C9: =A4 -> barbero
C10: =A5 -> fechaHoraInicio
C11: =A6 -> fechaHoraFinal

Sheet P-Bloqueo
A1: << Ir al modelo de dominio | B1: << Ir al listado de objetos de dominio | C1: << Ir a la caracterización del objeto de dominio | D1: Ir al muestreo de datos del objeto de dominio >> | E1: Ir al event storming del objeto de dominio >>
A2: Objeto de Dominio: | B2: ='Objetos de Dominio'!A3 -> Bloqueo
A3: Descripción: | B3: ='Objetos de Dominio'!B3 -> Representa los momentos en que el barbero no esta disponible para atender sus citas
A4: Numero politica | B4: Descripcion politica | D4: Objeto responsable | E4: Regla responsable
A6: P-BLO-0001 | B6: Asegurar que los datos requeridos (fecha y hora de inicio, fecha y hora de fin) sean válidos en tipo de dato, obligatoriedad, formato y rango, y que la fecha y hora de fin sea mayor a la fecha y hora de inicio | D6: Bloqueo
A7: P-BLO-0002 | B7: Rechazar el bloqueo si ya existen citas agendadas dentro de ese mismo rango elegido, en lugar de cancelarlas automáticamente | D7: Cita
A8: P-BLO-0003 | B8: Asegurar que los datos requeridos (fecha y hora de inicio, fecha y hora de fin) sean válidos en tipo de dato, obligatoriedad, formato y rango, y que la fecha y hora de fin sea mayor a la fecha y hora de inicio | D8: Bloqueo

Sheet E-Bloqueo
A1: << Ir al modelo de dominio | C1: << Ir al listado de objetos de dominio | F1: << Ir a la caracterización del objeto de dominio | J1: Ir al muestreo de datos del objeto de dominio >>
A2: Objeto de Dominio: | B2: ='Objetos de Dominio'!A3 -> Bloqueo
A3: Descripción: | B3: ='Objetos de Dominio'!B3 -> Representa los momentos en que el barbero no esta disponible para atender sus citas
A4: Actor | B4: Action/Command | D4: Entity/Aggregate/Object domain | E4: Read Model | G4: Business Rule/Policy | I4: External System | J4: Domain Event | K4: Hotspot/questions/Risk
A5: Actor | B5: Acción | C5: Descripción | D5: Objeto de dominio | E5: Información externa | G5: Políticas | I5: Sistema Externo | J5: Evento | K5: Aspectos por solucionar
E6: Información | F6: Descripción | G6: Número | H6: Descripción
A7: Barbero | B7: Definir un bloque de no disponible | C7: Comando que permite a un barbero asiganar un espacio de no disponibilidad para atender sus citas | D7: =$B$2 -> Bloqueo | G7: ='P-Bloqueo'!A6 -> P-BLO-0001 | H7: aquí | J7: Bloqueo registrado
G8: ='P-Bloqueo'!A7 -> P-BLO-0002 | H8: aquí
A9: Barbero | B9: Eliminar un bloqueo | C9: Permite a un barbero liberar un espacio de su agenda que había bloqueado previamente | D9: =$B$2 -> Bloqueo | J9: Bloqueo cancelado
A10: Barbero | B10: Ver bloqueos en una fecha | C10: Permite a un barbero ver los espacios que tiene bloqueados en una fecha dada | D10: =$B$2 -> Bloqueo | J10: Bloqueos vistos
A11: Sistema | B11: Ver bloqueo en una fecha y hora | C11: Permite al sistema ver si hay o no un bloqueo en una fecha y hora, para que el determine luego si el cliente puede agenda una cita en ese momento | D11: =$B$2 -> Bloqueo | J11: Bloqueo visto
A12: Barbero | D12: =$B$2 -> Bloqueo

Sheet M-Bloqueo
A1: <<<< Ir al modulo de dominio | B1: <<<< Ir a objetos de dominio
A2: Representa un identificador que hará unico cada objeto de dominio de este tipo, no se puede repetir | B2: Referencia a qué barbero le pertence este bloqueo | C2: Representa la fecha y hora en el que el barbero empieza a no estar disponible para atender las citas | D2: Representa la fecha y hora en el que el barbero empieza estar disponible nuevamente para atender las citas | E2: Combinación única que indica que un mismo barbero no puede tener dos bloqueos con la misma fecha y hora de inicio y la misma fecha y hora final
A3: id | B3: barbero | C3: fechaHoraInicio | D3: fechaHoraFinal | E3: Combinación única
A4: 1 | B4: ='M-Barbero'!K4 -> +57-3245627890 | C4: 46188.5 | D4: 46188.542 | E4: =_xlfn.CONCAT(B4,"-",TEXT(C4,"dd/mm/yyyy hh:mm"),"-",TEXT(D4,"dd/mm/yyyy hh:mm")) -> +57-3245627890-15/06/2026 12:00-15/06/2026 13:00
A5: 2 | B5: ='M-Barbero'!K5 -> +57-3124518923 | C5: 46189.417 | D5: 46189.438 | E5: =_xlfn.CONCAT(B5,"-",TEXT(C5,"dd/mm/yyyy hh:mm"),"-",TEXT(D5,"dd/mm/yyyy hh:mm")) -> +57-3124518923-16/06/2026 10:00-16/06/2026 10:30
A6: 3 | B6: ='M-Barbero'!K6 -> +57-3214533321 | C6: 46191.583 | D6: 46191.625 | E6: =_xlfn.CONCAT(B6,"-",TEXT(C6,"dd/mm/yyyy hh:mm"),"-",TEXT(D6,"dd/mm/yyyy hh:mm")) -> +57-3214533321-18/06/2026 14:00-18/06/2026 15:00
A7: 4 | B7: ='M-Barbero'!K7 -> +91-9876543210 | C7: 46193.375 | D7: 46193.396 | E7: =_xlfn.CONCAT(B7,"-",TEXT(C7,"dd/mm/yyyy hh:mm"),"-",TEXT(D7,"dd/mm/yyyy hh:mm")) -> +91-9876543210-20/06/2026 09:00-20/06/2026 09:30
A8: 5 | B8: ='M-Barbero'!K7 -> +91-9876543210 | C8: 46195.667 | D8: 46195.698 | E8: =_xlfn.CONCAT(B8,"-",TEXT(C8,"dd/mm/yyyy hh:mm"),"-",TEXT(D8,"dd/mm/yyyy hh:mm")) -> +91-9876543210-22/06/2026 16:00-22/06/2026 16:45
B14: Corresponde a la descripcion de los atributos
B15: Corresponde al identificador unico del objeto de dominio
B16: Corresponde a referencias de objetos de dominio
B17: Corresponde a los datos de tipo fecha hora
B18: Corresponde a la combinacion única

Sheet C-DiaSemana
A1: <<<< Ir al modulo de dominio | B1: <<<< Ir a objetos de dominio
A2: Nombre atributo | B2: Descripción atributo | C2: Identificador del objeto de dominio | D2: Tipo de dato | E2: Obligatorio | F2: Longitud mínima (si aplica) | G2: Longitud máxima (si aplica) | H2: Precisión (si aplica) | I2: Rendondeo (si aplica) | J2: Rango inicial (si aplica) | K2: Rango final (si aplica) | L2: Formato (si aplica) | M2: Reglas especiales (si aplica) | N2: Dato calculado | O2: Aplica ajuste del dato (si aplica) | P2: Carácter de ajuste (si aplica) | Q2: Quitar espacios en blanco al inicio (si aplica) | R2: Quitar espacios en blanco al fin (si aplica) | S2: Dato sensible (si aplica) | T2: Valor por defecto (si aplica) | U2: Auto generado
A3: ='M-DiaSemana'!A3 -> id | B3: ='M-DiaSemana'!A2 -> Representa un identificador que hará unico cada objeto de dominio de este tipo, no se puede repetir | C3: Si | D3: Identificador único universal | E3: Si | F3: No aplica | G3: No aplica | H3: No aplica | I3: No aplica | J3: No aplica | K3: No aplica | L3: No aplica | M3: No aplica | N3: No | O3: No aplica | P3: No aplica | Q3: No aplica | R3: No aplica | S3: No | T3: UUID vacio | U3: Si
A4: ='M-DiaSemana'!B3 -> nombre | B4: ='M-DiaSemana'!B2 -> Representa como se llama el dia de la semana, para los horarios | C4: No | D4: Alfanumérico | E4: Si | F4: 5 | G4: 9 | H4: No aplica | I4: No aplica | J4: No aplica | K4: No aplica | L4: No aplica | M4: Solo pueden ser los dias de la semana como Lunes, Martes, Miércoles, Jueves, Viernes, Sábado, Domingo y Festivo | N4: No | O4: No aplica | P4: No aplica | Q4: Si | R4: Si | S4: No | T4: Vacio | U4: No
A6: Nombre combinación única | B6: Descripción | C6: Atributos involucrados
A7: ='M-DiaSemana'!C3 -> Combinación única | B7: ='M-DiaSemana'!C2 -> Combinacion única que indica que no puede existir más un dia de la semana con el mismo nombre | C7: nombre

Sheet P-DiaSemana
A1: << Ir al modelo de dominio | B1: << Ir al listado de objetos de dominio | C1: << Ir a la caracterización del objeto de dominio | D1: Ir al muestreo de datos del objeto de dominio >> | E1: Ir al event storming del objeto de dominio >>
A2: Objeto de Dominio: | B2: ='Objetos de Dominio'!A4 -> DiaSemana
A3: Descripción: | B3: ='Objetos de Dominio'!B4 -> Representa cada uno de los días de la semana, incluyendo festivo, que se usa como catálogo para definir los horarios de la barbería y de cada barbero
A4: Numero politica | B4: Descripcion politica | D4: Objeto responsable | E4: Regla responsable
B6: No aplica: es un catálogo de solo lectura, sin comandos que impliquen políticas de negocio propias

Sheet E-DiaSemana
A1: << Ir al modelo de dominio | C1: << Ir al listado de objetos de dominio | F1: << Ir a la caracterización del objeto de dominio | J1: Ir al muestreo de datos del objeto de dominio >>
A2: Objeto de Dominio: | B2: ='Objetos de Dominio'!A4 -> DiaSemana
A3: Descripción: | B3: ='Objetos de Dominio'!B4 -> Representa cada uno de los días de la semana, incluyendo festivo, que se usa como catálogo para definir los horarios de la barbería y de cada barbero
A4: Actor | B4: Action/Command | D4: Entity/Aggregate/Object domain | E4: Read Model | G4: Business Rule/Policy | I4: External System | J4: Domain Event | K4: Hotspot/questions/Risk
A5: Actor | B5: Acción | C5: Descripción | D5: Objeto de dominio | E5: Información externa | G5: Políticas | I5: Sistema Externo | J5: Evento | K5: Aspectos por solucionar
E6: Información | F6: Descripción | G6: Número | H6: Descripción
A7: Dueño | B7: Ver los días de las semanas | C7: Permite consultar el catálogo de días de la semana, incluyendo festivo, disponibles para definir horarios | D7: =$B$2 -> DiaSemana | J7: Días de la semana consultados
A8: Barbero | B8: Ver los días de las semanas | C8: Permite consultar el catálogo de días de la semana, incluyendo festivo, disponibles para definir horarios | D8: =$B$2 -> DiaSemana | J8: Días de la semana consultados

Sheet M-DiaSemana
A1: <<<< Ir al modulo de dominio | B1: <<<< Ir a objetos de dominio
A2: Representa un identificador que hará unico cada objeto de dominio de este tipo, no se puede repetir | B2: Representa como se llama el dia de la semana, para los horarios | C2: Combinacion única que indica que no puede existir más un dia de la semana con el mismo nombre
A3: id | B3: nombre | C3: Combinación única
A4: 1 | B4: Lunes | C4: =B4 -> Lunes
A5: 2 | B5: Martes | C5: =B5 -> Martes
A6: 3 | B6: Miércoles | C6: =B6 -> Miércoles
A7: 4 | B7: Jueves | C7: =B7 -> Jueves
A8: 5 | B8: Viernes | C8: =B8 -> Viernes
A9: 6 | B9: Sábado | C9: =B9 -> Sábado
A10: 7 | B10: Domingo | C10: =B10 -> Domingo
A11: 8 | B11: Festivo | C11: =B11 -> Festivo
B17: Corresponde a la descripcion de los atributos
B18: Corresponde al identificador unico del objeto de dominio
B19: Corresponde a los datos de tipo alfanumerico
B20: Corresponde a la combinacion única

Sheet C-Estado
A1: <<<< Ir al modulo de dominio | B1: <<<< Ir a objetos de dominio
A2: Nombre atributo | B2: Descripción atributo | C2: Identificador del objeto de dominio | D2: Tipo de dato | E2: Obligatorio | F2: Longitud mínima (si aplica) | G2: Longitud máxima (si aplica) | H2: Precisión (si aplica) | I2: Rendondeo (si aplica) | J2: Rango inicial (si aplica) | K2: Rango final (si aplica) | L2: Formato (si aplica) | M2: Reglas especiales (si aplica) | N2: Dato calculado | O2: Aplica ajuste del dato (si aplica) | P2: Carácter de ajuste (si aplica) | Q2: Quitar espacios en blanco al inicio (si aplica) | R2: Quitar espacios en blanco al fin (si aplica) | S2: Dato sensible (si aplica) | T2: Valor por defecto (si aplica) | U2: Auto generado
A3: ='M-Estado'!A3 -> id | B3: ='M-Estado'!A2 -> Representa un identificador que hará unico cada objeto de dominio de este tipo, no se puede repetir | C3: Si | D3: Identificador único universal | E3: Si | F3: No aplica | G3: No aplica | H3: No aplica | I3: No aplica | J3: No aplica | K3: No aplica | L3: No aplica | M3: No aplica | N3: No | O3: No aplica | P3: No aplica | Q3: No aplica | R3: No aplica | S3: No aplica | T3: UUID vacio | U3: Si
A4: ='M-Estado'!B3 -> nombre | B4: ='M-Estado'!B2 -> Representa como se llama el estado en el que se encuentra una cita puntual | C4: No | D4: Alfanumérico | E4: Si | F4: 4 | G4: 50 | H4: No aplica | I4: No aplica | J4: No aplica | K4: No aplica | L4: No aplica | M4: Solo se aceptan caracteres de letras de la 'a' a la 'z' y espacios en blanco | N4: No | O4: No aplica | P4: No aplica | Q4: Si | R4: Si | S4: No | T4: Vacio | U4: No
A5: ='M-Estado'!C3 -> descripcion | B5: ='M-Estado'!C2 -> Representa el significado de que representa cada estado para la cita | C5: No | D5: Alfanumérico | E5: Si | F5: 10 | G5: 300 | H5: No aplica | I5: No aplica | J5: No aplica | K5: No aplica | L5: No aplica | M5: Solo se aceptan caracteres de letras de la 'a' a la 'z', caracteres con tilde y espacios en blanco | N5: No | O5: No aplica | P5: No aplica | Q5: Si | R5: Si | S5: No | T5: Vacio | U5: No
A7: Nombre combinación única | B7: Descripción | C7: Atributos involucrados
A8: ='M-Estado'!D3 -> Combinación única | B8: ='M-Estado'!D2 -> Combinacion única que indica que no puede existir más un dia de la semana con el mismo nombre | C8: nombre

Sheet P-Estado
A1: << Ir al modelo de dominio | B1: << Ir al listado de objetos de dominio | C1: << Ir a la caracterización del objeto de dominio | D1: Ir al muestreo de datos del objeto de dominio >> | E1: Ir al event storming del objeto de dominio >>
A2: Objeto de Dominio: | B2: ='Objetos de Dominio'!A5 -> Estado
A3: Descripción: | B3: ='Objetos de Dominio'!B5 -> Representa en qué situación puntual se encuentra una cita: agendada, finalizada, cancelada por alguna de las partes, con tardanza del cliente o del barbero, o con inasistencia del cliente
A4: Numero politica | B4: Descripcion politica | D4: Objeto responsable | E4: Regla responsable
A6: P-EST-0001 | B6: Asegurar que los datos requeridos (descripción) sean válidos en tipo de dato, longitud, formato y rango | D6: Estado

Sheet E-Estado
A1: << Ir al modelo de dominio | C1: << Ir al listado de objetos de dominio | F1: << Ir a la caracterización del objeto de dominio | J1: Ir al muestreo de datos del objeto de dominio >>
A2: Objeto de Dominio: | B2: ='Objetos de Dominio'!A5 -> Estado
A3: Descripción: | B3: ='Objetos de Dominio'!B5 -> Representa en qué situación puntual se encuentra una cita: agendada, finalizada, cancelada por alguna de las partes, con tardanza del cliente o del barbero, o con inasistencia del cliente
A4: Actor | B4: Action/Command | D4: Entity/Aggregate/Object domain | E4: Read Model | G4: Business Rule/Policy | I4: External System | J4: Domain Event | K4: Hotspot/questions/Risk
A5: Actor | B5: Acción | C5: Descripción | D5: Objeto de dominio | E5: Información externa | G5: Políticas | I5: Sistema Externo | J5: Evento | K5: Aspectos por solucionar
E6: Información | F6: Descripción | G6: Número | H6: Descripción
A7: Dueño | B7: Ver estados creados | C7: Permite consultar los estados posibles que puede tener una cita | D7: =$B$2 -> Estado | J7: Estados consultados
A8: Barbero | B8: Ver estados creados | C8: Permite consultar los estados posibles que puede tener una cita | D8: =$B$2 -> Estado | J8: Estados consultados
A9: Cliente | B9: Ver estados creados | C9: Permite consultar los estados posibles que puede tener una cita | D9: =$B$2 -> Estado | J9: Estados consultados
A10: Dueño | B10: Editar descripción del estado | C10: Permite ajustar el texto descriptivo de un estado ya creado, sin cambiar su significado en el flujo de la cita | D10: =$B$2 -> Estado | G10: ='P-Estado'!A6 -> P-EST-0001 | H10: aquí | J10: Descripción de estado actualizada
A11: Dueño | B11: Ver descripcion de un estado | C11: Permite consultar la descripcion de un estado en especifico | D11: =$B$2 -> Estado | J11: Descripción del estado consultada
A12: Barbero | B12: Ver descripcion de un estado | C12: Permite consultar la descripcion de un estado en especifico | D12: =$B$2 -> Estado | J12: Descripción del estado consultada
A13: Cliente | B13: Ver descripcion de un estado | C13: Permite consultar la descripcion de un estado en especifico | D13: =$B$2 -> Estado | J13: Descripción del estado consultada

Sheet M-Estado
A1: <<<< Ir al modulo de dominio | B1: <<<< Ir a objetos de dominio
A2: Representa un identificador que hará unico cada objeto de dominio de este tipo, no se puede repetir | B2: Representa como se llama el estado en el que se encuentra una cita puntual | C2: Representa el significado de que representa cada estado para la cita | D2: Combinacion única que indica que no puede existir más un dia de la semana con el mismo nombre
A3: id | B3: nombre | C3: descripcion | D3: Combinación única
A4: 1 | B4: Agendada | C4: La cita quedó registrada en la agenda del barbero y está a la espera de la fecha y hora acordadas. | D4: =B4 -> Agendada
A5: 2 | B5: Finalizada | C5: El barbero atendió al cliente y el servicio contratado se prestó por completo. | D5: =B5 -> Finalizada
A6: 3 | B6: Cancelada por el cliente | C6: El cliente decidió no asistir y anuló la cita antes de la fecha y hora programada. | D6: =B6 -> Cancelada por el cliente
A7: 4 | B7: Cancelada por el barbero | C7: El barbero anuló la cita antes de la fecha y hora programada, por ejemplo por una eventualidad. | D7: =B7 -> Cancelada por el barbero
A8: 5 | B8: El cliente se demoro | C8: El cliente llegó después de la hora acordada superando la toleranciaTardanzaCliente definida en Regla, lo que genera una multa. | D8: =B8 -> El cliente se demoro
A9: 6 | B9: El barbero se demoro | C9: El barbero se demoró más de lo previsto en una cita anterior y no pudo atender al cliente a la hora acordada, dándole un descuento en compensación según Regla. | D9: =B9 -> El barbero se demoro
A10: 7 | B10: Inasistencia del cliente | C10: El cliente nunca llegó a la cita: se alcanzó la hora estimada de finalización sin registrar su llegada, lo que genera una multa por el valor total de los servicios pedidos. | D10: =B10 -> Inasistencia del cliente
A11: 8 | B11: Inasistencia del barbero | C11: El barbero nunca inició la atención de la cita: se alcanzó la hora estimada de finalización sin que el barbero hubiera atendido al cliente, lo que da lugar a un descuento en la próxima cita del cliente como compensación. | D11: =B11 -> Inasistencia del barbero
B17: Corresponde a la descripcion de los atributos
B18: Corresponde al identificador unico del objeto de dominio
B19: Corresponde a los datos de tipo alfanumerico
B20: Corresponde a la combinacion única

Sheet C-Servicio
A1: <<<< Ir al modulo de dominio | B1: <<<< Ir a objetos de dominio
A2: Nombre atributo | B2: Descripción atributo | C2: Identificador del objeto de dominio | D2: Tipo de dato | E2: Obligatorio | F2: Longitud mínima (si aplica) | G2: Longitud máxima (si aplica) | H2: Precisión (si aplica) | I2: Rendondeo (si aplica) | J2: Rango inicial (si aplica) | K2: Rango final (si aplica) | L2: Formato (si aplica) | M2: Reglas especiales (si aplica) | N2: Dato calculado | O2: Aplica ajuste del dato (si aplica) | P2: Carácter de ajuste (si aplica) | Q2: Quitar espacios en blanco al inicio (si aplica) | R2: Quitar espacios en blanco al fin (si aplica) | S2: Dato sensible (si aplica) | T2: Valor por defecto (si aplica) | U2: Auto generado
A3: ='M-Servicio'!A3 -> id | B3: ='M-Servicio'!A2 -> Representa un identificador que hará unico cada objeto de dominio de este tipo, no se puede repetir | C3: Si | D3: Identificador único universal | E3: Si | F3: No aplica | G3: No aplica | H3: No aplica | I3: No aplica | J3: No aplica | K3: No aplica | L3: No aplica | M3: No aplica | N3: No | O3: No aplica | P3: No aplica | Q3: No aplica | R3: No aplica | S3: No | T3: UUID vacio | U3: Si
A4: ='M-Servicio'!B3 -> nombre | B4: ='M-Servicio'!B2 -> Representa el nombre del servicio que va estar en la barberia, para que el barbero elija los servicios que el sabe hacer | C4: No | D4: Alfanumérico | E4: Si | F4: 3 | G4: 50 | H4: No aplica | I4: No aplica | J4: No aplica | K4: No aplica | L4: No aplica | M4: Solo se aceptan caracteres de letras de la 'a' a la 'z' y caracteres con tilde | N4: No | O4: No aplica | P4: No aplica | Q4: Si | R4: Si | S4: No | T4: Vacio | U4: No
A5: ='M-Servicio'!C3 -> descripcion | B5: ='M-Servicio'!C2 -> Representa una descripcion de que va a hacer cada servicio en la barberia, para que el barbero sepa que hace el servicio | C5: No | D5: Alfanumérico | E5: No | F5: 0 | G5: 200 | H5: No aplica | I5: No aplica | J5: No aplica | K5: No aplica | L5: No aplica | M5: Solo se aceptan caracteres de letras de la 'a' a la 'z', caracteres con tilde y espacios en blanco | N5: No | O5: No aplica | P5: No aplica | Q5: Si | R5: Si | S5: No | T5: Vacio | U5: No
A6: ='M-Servicio'!D3 -> precio | B6: ='M-Servicio'!D2 -> Representa cuanto va a valer el servicio en pesos colombianos | C6: No | D6: Entero | E6: Si | F6: No aplica | G6: No aplica | H6: No aplica | I6: No aplica | J6: 0 | K6: 2000000 | L6: No aplica | M6: No aplica | N6: No | O6: No aplica | P6: No aplica | Q6: No aplica | R6: No aplica | S6: No | T6: 0 | U6: No
A7: ='M-Servicio'!E3 -> disponible | B7: ='M-Servicio'!E2 -> Representa si el servicio sigue o no disponible en la barberia | C7: No | D7: Lógico | E7: No | F7: No aplica | G7: No aplica | H7: No aplica | I7: No aplica | J7: No aplica | K7: No aplica | L7: No aplica | M7: No aplica | N7: No | O7: No aplica | P7: No aplica | Q7: No aplica | R7: No aplica | S7: No | T7: Si | U7: No
A9: Nombre combinación única | B9: Descripción | C9: Atributos involucrados
A10: ='M-Servicio'!F3 -> Combinacion única | B10: ='M-Servicio'!F2 -> Combinacion única que indica que no puede existir más de un servicio con el mismo nombre | C10: =A4 -> nombre

Sheet P-Servicio
A1: << Ir al modelo de dominio | B1: << Ir al listado de objetos de dominio | C1: << Ir a la caracterización del objeto de dominio | D1: Ir al muestreo de datos del objeto de dominio >> | E1: Ir al event storming del objeto de dominio >>
A2: Objeto de Dominio: | B2: ='Objetos de Dominio'!A6 -> Servicio
A3: Descripción: | B3: ='Objetos de Dominio'!B6 -> Representa cada tipo de corte o arreglo que ofrece la barbería, definido por el dueño, para que luego cada barbero decida cuáles sabe hacer
A4: Numero politica | B4: Descripcion politica | D4: Objeto responsable | E4: Regla responsable
A6: P-SER-0001 | B6: Asegurar que los datos requeridos del servicio (nombre, descripción, precio) sean válidos en tipo de dato, longitud, obligatoriedad, formato y rango | D6: Servicio
A7: P-SER-0002 | B7: Asegurar que no exista otro servicio registrado con el mismo nombre en la barbería | D7: Servicio
A8: P-SER-0003 | B8: Asegurar que el servicio a retirar no esté siendo ofrecido actualmente por ningún barbero vigente | D8: BarberoServicio

Sheet E-Servicio
A1: << Ir al modelo de dominio | C1: << Ir al listado de objetos de dominio | F1: << Ir a la caracterización del objeto de dominio | J1: Ir al muestreo de datos del objeto de dominio >>
A2: Objeto de Dominio: | B2: ='Objetos de Dominio'!A6 -> Servicio
A3: Descripción: | B3: ='Objetos de Dominio'!B6 -> Representa cada tipo de corte o arreglo que ofrece la barbería, definido por el dueño, para que luego cada barbero decida cuáles sabe hacer
A4: Actor | B4: Action/Command | D4: Entity/Aggregate/Object domain | E4: Read Model | G4: Business Rule/Policy | I4: External System | J4: Domain Event | K4: Hotspot/questions/Risk
A5: Actor | B5: Acción | C5: Descripción | D5: Objeto de dominio | E5: Información externa | G5: Políticas | I5: Sistema Externo | J5: Evento | K5: Aspectos por solucionar
E6: Información | F6: Descripción | G6: Número | H6: Descripción
A7: Dueño | B7: Ofrecer un servicio nuevo a la barbería | C7: Comando que permite registrar un nuevo tipo de servicio que la barbería pondrá a disposición de los barberos | D7: =$B$2 -> Servicio | G7: ='P-Servicio'!A6 -> P-SER-0001 | H7: aquí | J7: Servicio ofrecido
G8: ='P-Servicio'!A7 -> P-SER-0002 | H8: aquí
A9: Dueño | B9: Editar un servicio | C9: Permite modificar todos los atibutos de un servicio, que son el nombre, la descripción y el precio | D9: =$B$2 -> Servicio | G9: ='P-Servicio'!A6 -> P-SER-0001 | H9: aquí | J9: Nombre, descripción, precio del servicio actualizados
G10: ='P-Servicio'!A7 -> P-SER-0002 | H10: aquí
A11: Dueño | B11: Ver servicios disponibles de la barbería | C11: Permite consultar el catálogo de servicios que ofrece la barbería | D11: =$B$2 -> Servicio | J11: Servicios consultados
A12: Barbero | B12: Ver servicios disponibles de la barbería | C12: Permite consultar el catálogo de servicios que ofrece la barbería | D12: =$B$2 -> Servicio | J12: Servicios consultados
A13: Cliente | B13: Ver servicios disponibles de la barbería | C13: Permite consultar el catálogo de servicios que ofrece la barbería | D13: =$B$2 -> Servicio | J13: Servicios consultados
A14: Dueño | B14: Retirar un servicio de la barbería | C14: Permite dar de baja un servicio para que deje de ofrecerse a nuevos clientes | D14: =$B$2 -> Servicio | G14: ='P-Servicio'!A8 -> P-SER-0003 | H14: aquí | J14: Servicio retirado

Sheet M-Servicio
A1: <<<< Ir al modulo de dominio | B1: <<<< Ir a objetos de dominio
A2: Representa un identificador que hará unico cada objeto de dominio de este tipo, no se puede repetir | B2: Representa el nombre del servicio que va estar en la barberia, para que el barbero elija los servicios que el sabe hacer | C2: Representa una descripcion de que va a hacer cada servicio en la barberia, para que el barbero sepa que hace el servicio | D2: Representa cuanto va a valer el servicio en pesos colombianos | E2: Representa si el servicio sigue o no disponible en la barberia | F2: Combinacion única que indica que no puede existir más de un servicio con el mismo nombre
A3: id | B3: nombre | C3: descripcion | D3: precio | E3: disponible | F3: Combinacion única
A4: 1 | B4: Motilada | C4: Corte de cabello completo con máquina y tijera, incluye lavado y secado | D4: 22000 | E4: si | F4: =B4 -> Motilada
A5: 2 | B5: Corte de barba | C5: Recorte de la barba con máquina para dejarla pareja y a la medida que pide el cliente | D5: 12000 | E5: si | F5: =B5 -> Corte de barba
A6: 3 | B6: Perfilada de barba | C6: Delineado de los bordes de la barba y el bigote con navaja, sin recortar el largo | D6: 15000 | E6: si | F6: =B6 -> Perfilada de barba
A7: 4 | B7: Arreglo completo de barba con toalla caliente | C7: Recorte, perfilado con navaja, toalla caliente, exfoliación y aceite para la barba | D7: 35000 | E7: si | F7: =B7 -> Arreglo completo de barba con toalla caliente
B13: Corresponde a la descripcion de los atributos
B14: Corresponde al identificador unico del objeto de dominio
B15: Corresponde a los datos de referencia de otros objetos de dominio
B16: Corresponde a los datos de tipo alfanumerico
B17: Corresponde a los datos de tipo entero
B18: Corresponde a los datos de tipo logico
B19: Corresponde a la combinacion única

Sheet C-Regla
A1: <<<< Ir al modulo de dominio | B1: <<<< Ir a objetos de dominio
A2: Nombre atributo | B2: Descripción atributo | C2: Identificador del objeto de dominio | D2: Tipo de dato | E2: Obligatorio | F2: Longitud mínima (si aplica) | G2: Longitud máxima (si aplica) | H2: Precisión (si aplica) | I2: Rendondeo (si aplica) | J2: Rango inicial (si aplica) | K2: Rango final (si aplica) | L2: Formato (si aplica) | M2: Reglas especiales (si aplica) | N2: Dato calculado | O2: Aplica ajuste del dato (si aplica) | P2: Carácter de ajuste (si aplica) | Q2: Quitar espacios en blanco al inicio (si aplica) | R2: Quitar espacios en blanco al fin (si aplica) | S2: Dato sensible (si aplica) | T2: Valor por defecto (si aplica) | U2: Auto generado
A3: ='M-Regla'!A3 -> id | B3: ='M-Regla'!A2 -> Representa un identificador que hará unico cada objeto de dominio de este tipo, no se puede repetir | C3: Si | D3: Identificador único universal | E3: Si | F3: No aplica | G3: No aplica | H3: No aplica | I3: No aplica | J3: No aplica | K3: No aplica | L3: No aplica | M3: No aplica | N3: No | O3: No aplica | P3: No aplica | Q3: No | R3: No | S3: No | T3: UUID vacio | U3: Si
A4: ='M-Regla'!B3 -> toleranciaTardanzaCliente | B4: ='M-Regla'!B2 -> Representa la cantidad de minutos maxima que un cliente puede llegar tarde | C4: No | D4: Entero | E4: No | F4: No aplica | G4: No aplica | H4: No aplica | I4: No aplica | J4: 0 | K4: 59 | L4: No aplica | M4: No aplica | N4: No | O4: No aplica | P4: No aplica | Q4: No aplica | R4: No aplica | S4: No | T4: 0 | U4: No
A5: ='M-Regla'!C3 -> montoMultaTardanzaCliente | B5: ='M-Regla'!C2 -> Representa la cantidad de dinero que el cliente debe de pagar en pesos colombianos, por superar la toleranciaTardanza | C5: No | D5: Entero | E5: No | F5: No aplica | G5: No aplica | H5: No aplica | I5: No aplica | J5: 0 | K5: 1000000 | L5: No aplica | M5: No aplica | N5: No | O5: No aplica | P5: No aplica | Q5: No aplica | R5: No aplica | S5: No | T5: 0 | U5: No
A6: ='M-Regla'!D3 -> numeroMultasMaxima | B6: ='M-Regla'!D2 -> Representa la maxima de multas que pueda tener un cliente sin pagar, a partir de esta cantidad se le hace un veto al cliente | C6: No | D6: Entero | E6: No | F6: No aplica | G6: No aplica | H6: No aplica | I6: No aplica | J6: 0 | K6: 100 | L6: No aplica | M6: No aplica | N6: No | O6: No aplica | P6: No aplica | Q6: No aplica | R6: No aplica | S6: No | T6: 0 | U6: No
A7: ='M-Regla'!E3 -> toleranciaTardanzaBarbero | B7: ='M-Regla'!E2 -> Representa la cantidad de minutos que un barbero puede demorarse en atender a un cliente, en caso de que el barbero se demore mas de lo previsto en su cita anterior | C7: No | D7: Entero | E7: No | F7: No aplica | G7: No aplica | H7: No aplica | I7: No aplica | J7: 0 | K7: 59 | L7: No aplica | M7: No aplica | N7: No | O7: No aplica | P7: No aplica | Q7: No aplica | R7: No aplica | S7: No | T7: 0 | U7: No
A8: ='M-Regla'!F3 -> porcentajeDescuentoCita | B8: ='M-Regla'!F2 -> Representa la cantidad cuanto descuento va a tener un cliente en la cita con el barbero, como recompesa por esperar al barbero mas de la tolerancia permitida | C8: No | D8: Entero | E8: No | F8: No aplica | G8: No aplica | H8: No aplica | I8: No aplica | J8: 0 | K8: 100 | L8: No aplica | M8: No aplica | N8: No | O8: No aplica | P8: No aplica | Q8: No aplica | R8: No aplica | S8: No | T8: 0 | U8: No
A9: ='M-Regla'!G3 -> tiempoEnHorasAnticipacionDelBarberoParaCancelarUnaCita | B9: ='M-Regla'!G2 -> Representa la parte en horas del tiempo mínimo de anticipación con el que un barbero pueda cancelar una cita con el cliente. El barbero no podrá cancelar la cita cuando falte menos del tiempo indicado | C9: No | D9: Entero | E9: No | F9: No aplica | G9: No aplica | H9: No aplica | I9: No aplica | J9: 0 | K9: 720 | L9: No aplica | M9: No aplica | N9: No | O9: No aplica | P9: No aplica | Q9: No aplica | R9: No aplica | S9: No | T9: 0 | U9: No
A10: ='M-Regla'!H3 -> tiempoEnMinutosAnticipacionDelBarberoParaCancelarUnaCita | B10: ='M-Regla'!H2 -> Representa la parte en minutos del tiempo mínimo de anticipación con el que un barbero puede cancelar una cita con el cliente. El barbero no podrá cancelar la cita cuando falte menos del tiempo indicado | C10: No | D10: Entero | E10: No | F10: No aplica | G10: No aplica | H10: No aplica | I10: No aplica | J10: 0 | K10: 59 | L10: No aplica | M10: No aplica | N10: No | O10: No aplica | P10: No aplica | Q10: No aplica | R10: No aplica | S10: No | T10: 0 | U10: No
A11: ='M-Regla'!I3 -> tiempoEnHorasAnticipacionDelClienteParaCancelarUnaCita | B11: ='M-Regla'!I2 -> Representa la parte en horas del tiempo mínimo de anticipación con el que un cliente puede cancelar una cita con el barbero. El cliente no podrá cancelar la cita cuando falte menos del tiempo indicado | C11: No | D11: Entero | E11: No | F11: No aplica | G11: No aplica | H11: No aplica | I11: No aplica | J11: 0 | K11: 720 | L11: No aplica | M11: No aplica | N11: No | O11: No aplica | P11: No aplica | Q11: No aplica | R11: No aplica | S11: No | T11: 0 | U11: No
A12: ='M-Regla'!J3 -> tiempoEnMinutosAnticipacionDelClienteParaCancelarUnaCita | B12: ='M-Regla'!J2 -> Representa la parte en minutos del tiempo mínimo de anticipación con el que un cliente puede cancelar una cita con el barbero. El cliente no podrá cancelar la cita cuando falte menos del tiempo indicado | C12: No | D12: Entero | E12: No | F12: No aplica | G12: No aplica | H12: No aplica | I12: No aplica | J12: 0 | K12: 59 | L12: No aplica | M12: No aplica | N12: No | O12: No aplica | P12: No aplica | Q12: No aplica | R12: No aplica | S12: No | T12: 0 | U12: No

Sheet P-Regla
A1: << Ir al modelo de dominio | B1: << Ir al listado de objetos de dominio | C1: << Ir a la caracterización del objeto de dominio | D1: Ir al muestreo de datos del objeto de dominio >> | E1: Ir al event storming del objeto de dominio >>
A2: Objeto de Dominio: | B2: ='Objetos de Dominio'!A7 -> Regla
A3: Descripción: | B3: ='Objetos de Dominio'!B7 -> Representa las políticas de la barbería frente al incumplimiento de clientes y barberos: tolerancias de tardanza, monto de la multa fija, número máximo de multas sin pagar antes del veto, y el descuento que se da cuando el barbero se demora
A4: Numero politica | B4: Descripcion politica | D4: Objeto responsable | E4: Regla responsable
A6: P-REG-0001 | B6: Asegurar que los datos requeridos (tolerancias de tardanza, monto de multa, número máximo de multas, porcentaje de descuento, tiempos de anticipación) sean válidos en tipo de dato y rango | D6: Regla

Sheet E-Regla
A1: << Ir al modelo de dominio | C1: << Ir al listado de objetos de dominio | F1: << Ir a la caracterización del objeto de dominio | J1: Ir al muestreo de datos del objeto de dominio >>
A2: Objeto de Dominio: | B2: ='Objetos de Dominio'!A7 -> Regla
A3: Descripción: | B3: ='Objetos de Dominio'!B7 -> Representa las políticas de la barbería frente al incumplimiento de clientes y barberos: tolerancias de tardanza, monto de la multa fija, número máximo de multas sin pagar antes del veto, y el descuento que se da cuando el barbero se demora
A4: Actor | B4: Action/Command | D4: Entity/Aggregate/Object domain | E4: Read Model | G4: Business Rule/Policy | I4: External System | J4: Domain Event | K4: Hotspot/questions/Risk
A5: Actor | B5: Acción | C5: Descripción | D5: Objeto de dominio | E5: Información externa | G5: Políticas | I5: Sistema Externo | J5: Evento | K5: Aspectos por solucionar
E6: Información | F6: Descripción | G6: Número | H6: Descripción
A7: Dueño | B7: Definir las políticas de la barbería | C7: Comando que permite registrar por primera vez los parámetros de negocio: tolerancias de tardanza, monto de multa, número máximo de multas, descuento por demora del barbero y tiempos de anticipacion para cancelar una cita | D7: =$B$2 -> Regla | G7: ='P-Regla'!A6 -> P-REG-0001 | H7: aquí | J7: Políticas de la barbería definidas
A8: Dueño | B8: Modificar las políticas | C8: Permite ajustar los parámetros de negocio ya definidos | D8: =$B$2 -> Regla | G8: ='P-Regla'!A6 -> P-REG-0001 | H8: aquí | J8: Políticas de la barbería actualizadas
A9: Dueño | B9: Ver la regla definida | C9: Permite consultar los parámetros de negocio vigentes de la barbería | D9: =$B$2 -> Regla | J9: Regla consultada
A10: Barbero | B10: Ver la regla definida | C10: Permite consultar los parámetros de negocio vigentes de la barbería | D10: =$B$2 -> Regla | J10: Regla consultada
A11: Cliente | B11: Ver la regla definida | C11: Permite consultar los parámetros de negocio vigentes de la barbería | D11: =$B$2 -> Regla | J11: Regla consultada

Sheet M-Regla
A1: <<<< Ir al modulo de dominio | B1: <<<< Ir a objetos de dominio
A2: Representa un identificador que hará unico cada objeto de dominio de este tipo, no se puede repetir | B2: Representa la cantidad de minutos maxima que un cliente puede llegar tarde | C2: Representa la cantidad de dinero que el cliente debe de pagar en pesos colombianos, por superar la toleranciaTardanza | D2: Representa la maxima de multas que pueda tener un cliente sin pagar, a partir de esta cantidad se le hace un veto al cliente | E2: Representa la cantidad de minutos que un barbero puede demorarse en atender a un cliente, en caso de que el barbero se demore mas de lo previsto en su cita anterior | F2: Representa la cantidad cuanto descuento va a tener un cliente en la cita con el barbero, como recompesa por esperar al barbero mas de la tolerancia permitida | G2: Representa la parte en horas del tiempo mínimo de anticipación con el que un barbero pueda cancelar una cita con el cliente. El barbero no podrá cancelar la cita cuando falte menos del tiempo indicado | H2: Representa la parte en minutos del tiempo mínimo de anticipación con el que un barbero puede cancelar una cita con el cliente. El barbero no podrá cancelar la cita cuando falte menos del tiempo indicado | I2: Representa la parte en horas del tiempo mínimo de anticipación con el que un cliente puede cancelar una cita con el barbero. El cliente no podrá cancelar la cita cuando falte menos del tiempo indicado | J2: Representa la parte en minutos del tiempo mínimo de anticipación con el que un cliente puede cancelar una cita con el barbero. El cliente no podrá cancelar la cita cuando falte menos del tiempo indicado
A3: id | B3: toleranciaTardanzaCliente | C3: montoMultaTardanzaCliente | D3: numeroMultasMaxima | E3: toleranciaTardanzaBarbero | F3: porcentajeDescuentoCita | G3: tiempoEnHorasAnticipacionDelBarberoParaCancelarUnaCita | H3: tiempoEnMinutosAnticipacionDelBarberoParaCancelarUnaCita | I3: tiempoEnHorasAnticipacionDelClienteParaCancelarUnaCita | J3: tiempoEnMinutosAnticipacionDelClienteParaCancelarUnaCita
A4: 1 | B4: 10 | C4: 10000 | D4: 3 | E4: 15 | F4: 10 | G4: 1 | H4: 0 | I4: 1 | J4: 0
B10: Corresponde a la descripcion de los atributos
B11: Corresponde al identificador unico del objeto de dominio
B12: Corresponde a los datos de tipo entero

Sheet C-PrefijoCelular
A1: <<<< Ir al modulo de dominio | B1: <<<< Ir a objetos de dominio
A2: Nombre atributo | B2: Descripción atributo | C2: Identificador del objeto de dominio | D2: Tipo de dato | E2: Obligatorio | F2: Longitud mínima (si aplica) | G2: Longitud máxima (si aplica) | H2: Precisión (si aplica) | I2: Rendondeo (si aplica) | J2: Rango inicial (si aplica) | K2: Rango final (si aplica) | L2: Formato (si aplica) | M2: Reglas especiales (si aplica) | N2: Dato calculado | O2: Aplica ajuste del dato (si aplica) | P2: Carácter de ajuste (si aplica) | Q2: Quitar espacios en blanco al inicio (si aplica) | R2: Quitar espacios en blanco al fin (si aplica) | S2: Dato sensible (si aplica) | T2: Valor por defecto (si aplica) | U2: Auto generado
A3: ='M-PrefijoCelular'!A3 -> id | B3: ='M-PrefijoCelular'!A2 -> Representa un identificador que hará unico cada objeto de dominio de este tipo, no se puede repetir | C3: Si | D3: Identificador único universal | E3: Si | F3: No aplica | G3: No aplica | H3: No aplica | I3: No aplica | J3: No aplica | K3: No aplica | L3: No aplica | M3: No aplica | N3: No | O3: No | P3: No aplica | Q3: No | R3: No | S3: No | T3: No aplica | U3: Si
A4: ='M-PrefijoCelular'!B3 -> prefijo | B4: ='M-PrefijoCelular'!B2 -> Representa el primer nombre del barbero que trabaja en barbería | C4: No | D4: Alfanumérico | E4: Si | F4: 2 | G4: 6 | H4: No aplica | I4: No aplica | J4: No aplica | K4: No aplica | L4: Simbolo + seguido de un número. Por ejemplo +57. Tambien el anterior puede ser seguido de un - y un numero. Por ejemplo +1-809 | M4: Solo se aceptan caracteres numericos del 0 al 9 y el carácter '+' y '-' | N4: No | O4: No | P4: No aplica | Q4: Si | R4: Si | S4: No | T4: +0 | U4: No
A6: Nombre combinación única | B6: Descripción | C6: Atributos involucrados
A7: ='M-PrefijoCelular'!C3 -> Combinación única | B7: ='M-PrefijoCelular'!C2 -> Combinacion única que indica que no puede existir más un mismo prefijo | C7: prefijo

Sheet P-PrefijoCelular
A1: << Ir al modelo de dominio | B1: << Ir al listado de objetos de dominio | C1: << Ir a la caracterización del objeto de dominio | D1: Ir al muestreo de datos del objeto de dominio >> | E1: Ir al event storming del objeto de dominio >>
A2: Objeto de Dominio: | B2: ='Objetos de Dominio'!A8 -> PrefijoCelular
A3: Descripción: | B3: ='Objetos de Dominio'!B8 -> Representa el catálogo de prefijos telefónicos de país disponibles para el número de celular de barberos y clientes
A4: Numero politica | B4: Descripcion politica | D4: Objeto responsable | E4: Regla responsable
B6: No aplica: es un catálogo de solo lectura, sin comandos que impliquen políticas de negocio propias

Sheet E-PrefijoCelular
A1: << Ir al modelo de dominio | C1: << Ir al listado de objetos de dominio | F1: << Ir a la caracterización del objeto de dominio | J1: Ir al muestreo de datos del objeto de dominio >>
A2: Objeto de Dominio: | B2: ='Objetos de Dominio'!A8 -> PrefijoCelular
A3: Descripción: | B3: ='Objetos de Dominio'!B8 -> Representa el catálogo de prefijos telefónicos de país disponibles para el número de celular de barberos y clientes
A4: Actor | B4: Action/Command | D4: Entity/Aggregate/Object domain | E4: Read Model | G4: Business Rule/Policy | I4: External System | J4: Domain Event | K4: Hotspot/questions/Risk
A5: Actor | B5: Acción | C5: Descripción | D5: Objeto de dominio | E5: Información externa | G5: Políticas | I5: Sistema Externo | J5: Evento | K5: Aspectos por solucionar
E6: Información | F6: Descripción | G6: Número | H6: Descripción
A7: Barbero | B7: Ver prefijos de celular | C7: Permite consultar el catálogo de prefijos telefónicos de país disponibles | D7: =$B$2 -> PrefijoCelular | J7: Prefijos de celular consultados
A8: Cliente | B8: Ver prefijos de celular | C8: Permite consultar el catálogo de prefijos telefónicos de país disponibles | D8: =$B$2 -> PrefijoCelular | J8: Prefijos de celular consultados

Sheet M-PrefijoCelular
A1: <<<< Ir al modulo de dominio | B1: <<<< Ir a objetos de dominio
A2: Representa un identificador que hará unico cada objeto de dominio de este tipo, no se puede repetir | B2: Representa el primer nombre del barbero que trabaja en barbería | C2: Combinacion única que indica que no puede existir más un mismo prefijo
A3: id | B3: prefijo | C3: Combinación única
A4: 1 | B4: +57 | C4: =B4 -> +57
A5: 2 | B5: +91 | C5: =B5 -> +91
A6: 3 | B6: +593 | C6: =B6 -> +593
A7: 4 | B7: +58 | C7: =B7 -> +58
B13: Corresponde a la descripcion de los atributos
B14: Corresponde al identificador unico del objeto de dominio
B15: Corresponde a los datos de tipo alfanumerico
B16: Corresponde a la combinacion única

Sheet C-TipoMulta
A1: <<<< Ir al modulo de dominio | B1: <<<< Ir a objetos de dominio
A2: Nombre atributo | B2: Descripción atributo | C2: Identificador del objeto de dominio | D2: Tipo de dato | E2: Obligatorio | F2: Longitud mínima (si aplica) | G2: Longitud máxima (si aplica) | H2: Precisión (si aplica) | I2: Rendondeo (si aplica) | J2: Rango inicial (si aplica) | K2: Rango final (si aplica) | L2: Formato (si aplica) | M2: Reglas especiales (si aplica) | N2: Dato calculado | O2: Aplica ajuste del dato (si aplica) | P2: Carácter de ajuste (si aplica) | Q2: Quitar espacios en blanco al inicio (si aplica) | R2: Quitar espacios en blanco al fin (si aplica) | S2: Dato sensible (si aplica) | T2: Valor por defecto (si aplica) | U2: Auto generado
A3: ='M-TipoMulta'!A3 -> id | B3: ='M-TipoMulta'!A2 -> Representa un identificador que hará unico cada objeto de dominio de este tipo, no se puede repetir | C3: Si | D3: Identificador único universal | E3: Si | F3: No aplica | G3: No aplica | H3: No aplica | I3: No aplica | J3: No aplica | K3: No aplica | L3: No aplica | M3: No aplica | N3: No | O3: No | P3: No aplica | Q3: No | R3: No | S3: No | T3: UUID vacio | U3: Si
A4: ='M-TipoMulta'!B3 -> nombre | B4: ='M-TipoMulta'!B2 -> Representa el nombre del tipo de multa | C4: No | D4: Alfanumérico | E4: Si | F4: 4 | G4: 50 | H4: No aplica | I4: No aplica | J4: No aplica | K4: No aplica | L4: No aplica | M4: No aplica | N4: No | O4: No | P4: No aplica | Q4: Si | R4: Si | S4: No | T4: Vacio | U4: No
A5: ='M-TipoMulta'!C3 -> descripcion | B5: ='M-TipoMulta'!C2 -> Representa que hace cada tipo de multa | C5: No | D5: Alfanumérico | E5: Si | F5: 10 | G5: 300 | H5: No aplica | I5: No aplica | J5: No aplica | K5: No aplica | L5: No aplica | M5: No aplica | N5: No | O5: No | P5: No aplica | Q5: Si | R5: Si | S5: No | T5: Vacio | U5: No
A7: Nombre combinación única | B7: Descripción | C7: Atributos involucrados
A8: ='M-TipoMulta'!D3 -> Combinación única | B8: ='M-TipoMulta'!D2 -> Combinación única indica que no puede existir más de un tipo de multa con el mismo nombre | C8: nombre

Sheet P-TipoMulta
A1: << Ir al modelo de dominio | B1: << Ir al listado de objetos de dominio | C1: << Ir a la caracterización del objeto de dominio | D1: Ir al muestreo de datos del objeto de dominio >> | E1: Ir al event storming del objeto de dominio >>
A2: Objeto de Dominio: | B2: ='Objetos de Dominio'!A9 -> TipoMulta
A3: Descripción: | B3: ='Objetos de Dominio'!B9 -> Representa los tipos de multa que puede recibir un cliente: por tardanza o por inasistencia
A4: Numero politica | B4: Descripcion politica | D4: Objeto responsable | E4: Regla responsable
B6: No aplica: es un catálogo de solo lectura, sin comandos que impliquen políticas de negocio propias

Sheet E-TipoMulta
A1: << Ir al modelo de dominio | C1: << Ir al listado de objetos de dominio | F1: << Ir a la caracterización del objeto de dominio | J1: Ir al muestreo de datos del objeto de dominio >>
A2: Objeto de Dominio: | B2: ='Objetos de Dominio'!A9 -> TipoMulta
A3: Descripción: | B3: ='Objetos de Dominio'!B9 -> Representa los tipos de multa que puede recibir un cliente: por tardanza o por inasistencia
A4: Actor | B4: Action/Command | D4: Entity/Aggregate/Object domain | E4: Read Model | G4: Business Rule/Policy | I4: External System | J4: Domain Event | K4: Hotspot/questions/Risk
A5: Actor | B5: Acción | C5: Descripción | D5: Objeto de dominio | E5: Información externa | G5: Políticas | I5: Sistema Externo | J5: Evento | K5: Aspectos por solucionar
E6: Información | F6: Descripción | G6: Número | H6: Descripción
A7: Dueño | B7: Ver tipos de multa | C7: Permite consultar los tipos de multa que puede recibir un cliente | D7: =$B$2 -> TipoMulta | J7: Tipos de multa consultados
A8: Barbero | B8: Ver tipos de multa | C8: Permite consultar los tipos de multa que puede recibir un cliente | D8: =$B$2 -> TipoMulta | J8: Tipos de multa consultados
A9: Cliente | B9: Ver tipos de multa | C9: Permite consultar los tipos de multa que puede recibir un cliente | D9: =$B$2 -> TipoMulta | J9: Tipos de multa consultados

Sheet M-TipoMulta
A1: <<<< Ir al modulo de dominio | B1: <<<< Ir a objetos de dominio
A2: Representa un identificador que hará unico cada objeto de dominio de este tipo, no se puede repetir | B2: Representa el nombre del tipo de multa | C2: Representa que hace cada tipo de multa | D2: Combinación única indica que no puede existir más de un tipo de multa con el mismo nombre
A3: id | B3: nombre | C3: descripcion | D3: Combinación única
A4: 1 | B4: Tardanza | C4: El cliente llegó a la cita después de la hora acordada, superando los minutos de toleranciaTardanzaCliente definidos en Regla. | D4: =B4 -> Tardanza
A5: 2 | B5: Inasistencia | C5: El cliente no se presentó a la cita agendada: se llegó a la hora estimada de finalización sin que hubiera registrado su llegada. | D5: =B5 -> Inasistencia
B11: Corresponde a la descripcion de los atributos
B12: Corresponde al identificador unico del objeto de dominio
B13: Corresponde a los datos de tipo texto
B14: Corresponde a los datos de tipo alfanumerico
B15: Corresponde a la combinacion única

Sheet C-Barbero
A1: <<<< Ir al modulo de dominio | B1: <<<< Ir a objetos de dominio
A2: Nombre atributo | B2: Descripción atributo | C2: Identificador del objeto de dominio | D2: Tipo de dato | E2: Obligatorio | F2: Longitud mínima (si aplica) | G2: Longitud máxima (si aplica) | H2: Precisión (si aplica) | I2: Rendondeo (si aplica) | J2: Rango inicial (si aplica) | K2: Rango final (si aplica) | L2: Formato (si aplica) | M2: Reglas especiales (si aplica) | N2: Dato calculado | O2: Aplica ajuste del dato (si aplica) | P2: Carácter de ajuste (si aplica) | Q2: Quitar espacios en blanco al inicio (si aplica) | R2: Quitar espacios en blanco al fin (si aplica) | S2: Dato sensible (si aplica) | T2: Valor por defecto (si aplica) | U2: Auto generado
A3: ='M-Barbero'!A3 -> id | B3: ='M-Barbero'!A2 -> Representa un identificador que hará unico cada objeto de dominio de este tipo, no se puede repetir | C3: Si | D3: Identificador único universal | E3: Si | F3: No aplica | G3: No aplica | H3: No aplica | I3: No aplica | J3: No aplica | K3: No aplica | L3: No aplica | M3: No aplica | N3: No | O3: No aplica | P3: No aplica | Q3: No | R3: No | S3: No | T3: UUID vacio | U3: Si
A4: ='M-Barbero'!B3 -> primerNombre | B4: ='M-Barbero'!B2 -> Representa el primer nombre del barbero que trabaja en barbería | C4: No | D4: Alfanumérico | E4: Si | F4: 3 | G4: 100 | H4: No aplica | I4: No aplica | J4: No aplica | K4: No aplica | L4: No aplica | M4: Solo se aceptan caracteres de letras de la 'a' a la 'z', caracteres con tilde y numeros del 0 al 9 | N4: No | O4: No | P4: No | Q4: Si | R4: Si | S4: No | T4: vacío | U4: No
A5: ='M-Barbero'!C3 -> segundoNombre | B5: ='M-Barbero'!C2 -> Representa el segundo nombre del barbero que trabaja en barbería | C5: No | D5: Alfanumérico | E5: No | F5: 3 | G5: 100 | H5: No aplica | I5: No aplica | J5: No aplica | K5: No aplica | L5: No aplica | M5: Solo se aceptan caracteres de letras de la 'a' a la 'z', caracteres con tilde y numeros del 0 al 9 | N5: No | O5: No | P5: No | Q5: Si | R5: Si | S5: No | T5: vacío | U5: No
A6: ='M-Barbero'!D3 -> primerApellido | B6: ='M-Barbero'!D2 -> Representa el primer apellido del barbero que trabaja en la barbería | C6: No | D6: Alfanumérico | E6: Si | F6: 3 | G6: 100 | H6: No aplica | I6: No aplica | J6: No aplica | K6: No aplica | L6: No aplica | M6: Solo se aceptan caracteres de letras de la 'a' a la 'z', caracteres con tilde y numeros del 0 al 9 | N6: No | O6: No | P6: No | Q6: Si | R6: Si | S6: No | T6: vacío | U6: No
A7: ='M-Barbero'!E3 -> segundoApellido | B7: ='M-Barbero'!E2 -> Representa el segundo apellido del barbero que trabaja en la barbería | C7: No | D7: Alfanumérico | E7: No | F7: 3 | G7: 100 | H7: No aplica | I7: No aplica | J7: No aplica | K7: No aplica | L7: No aplica | M7: Solo se aceptan caracteres de letras de la 'a' a la 'z', caracteres con tilde y numeros del 0 al 9 | N7: No | O7: No | P7: No | Q7: Si | R7: Si | S7: No | T7: vacío | U7: No
A8: ='M-Barbero'!F3 -> prefijo | B8: ='M-Barbero'!F2 -> Representa cual es el prefijo del numero de celular del barbero | C8: No | D8: PrefijoCelular | E8: Si | F8: No aplica | G8: No aplica | H8: No aplica | I8: No aplica | J8: No aplica | K8: No aplica | L8: No aplica | M8: No aplica | N8: No | O8: No aplica | P8: No aplica | Q8: No aplica | R8: No aplica | S8: No | T8: UUID vacio | U8: No
A9: ='M-Barbero'!G3 -> celular | B9: ='M-Barbero'!G2 -> Representa el número de celular del barbero, es el dato que el cliente necesita en caso de que tenga que contactarse con el | C9: No | D9: Entero | E9: Si | F9: No aplica | G9: No aplica | H9: No aplica | I9: No aplica | J9: 1000000 | K9: 9999999999 | L9: Número telefónico, sin el prefijo de país | M9: No aplica | N9: No | O9: No aplica | P9: No aplica | Q9: No aplica | R9: No aplica | S9: Si | T9: 0 | U9: No
A10: ='M-Barbero'!H3 -> vigente | B10: ='M-Barbero'!H2 -> Representa si el barbero sigue o no trabajando en la barberia | C10: No | D10: Lógico | E10: No | F10: No aplica | G10: No aplica | H10: No aplica | I10: No aplica | J10: No aplica | K10: No aplica | L10: No aplica | M10: No aplica | N10: Si | O10: No aplica | P10: No aplica | Q10: No aplica | R10: No aplica | S10: No | T10: Si | U10: No
A11: ='M-Barbero'!I3 -> anticipacionEnHorasParaAgendarCita | B11: ='M-Barbero'!I2 -> Representa la parte en horas del tiempo mínimo de anticipación con el que un cliente debe pedirle una cita a este barbero. Junto con anticipacionEnMinutosParaAgendarCita forma el tiempo total de anticipación que exige el barbero | C11: No | D11: Entero | E11: No | F11: No aplica | G11: No aplica | H11: No aplica | I11: No aplica | J11: 0 | K11: 720 | L11: Horas | M11: No aplica | N11: No | O11: No aplica | P11: No aplica | Q11: No aplica | R11: No aplica | S11: No | T11: 0 | U11: No
A12: ='M-Barbero'!J3 -> anticipacionEnMinutosParaAgendarCita | B12: ='M-Barbero'!J2 -> Representa la parte en minutos del tiempo mínimo de anticipación con el que un cliente debe pedirle una cita a este barbero. Junto con anticipacionEnHorasParaAgendarCita forma el tiempo total de anticipación que exige el barbero | C12: No | D12: Entero | E12: No | F12: No aplica | G12: No aplica | H12: No aplica | I12: No aplica | J12: 0 | K12: 59 | L12: Minutos | M12: No aplica | N12: No | O12: No aplica | P12: No aplica | Q12: No aplica | R12: No aplica | S12: No | T12: 0 | U12: No
A14: Nombre combinación única | B14: Descripción | C14: Atributos involucrados
A15: ='M-Barbero'!K3 -> Combinación única 1 | B15: ='M-Barbero'!K2 -> Combinacion única que indica que no puede existir más de un barbero con el mismo prefijo de celular y número de celular | C15: =A8 -> prefijo
C16: =A9 -> celular

Sheet P-Barbero
A1: << Ir al modelo de dominio | B1: << Ir al listado de objetos de dominio | C1: << Ir a la caracterización del objeto de dominio | D1: Ir al muestreo de datos del objeto de dominio >> | E1: Ir al event storming del objeto de dominio >>
A2: Objeto de Dominio: | B2: ='Objetos de Dominio'!A10 -> Barbero
A3: Descripción: | B3: ='Objetos de Dominio'!B10 -> Representa a un trabajador de la barbería que atiende clientes según los servicios que sabe realizar, organiza su propio horario y tiene su agenda personal
A4: Numero politica | B4: Descripcion politica | D4: Objeto responsable | E4: Regla responsable
A6: P-BAR-0001 | B6: Asegurar que los datos requeridos del barbero (nombre, apellido, prefijo de celular, celular, tiempos de anticipación) sean válidos en tipo de dato, longitud, obligatoriedad, formato y rango | D6: Barbero
A7: P-BAR-0002 | B7: Asegurar que el número de celular y prefijo de celular no esté siendo utilizado por otro barbero | D7: Barbero
A8: P-BAR-0003 | B8: Asegurar que el barbero no tenga citas futuras pendientes antes de dejar de trabajar en la barbería | D8: Cita
A9: P-BAR-0004 | B9: Asegurar que los datos requeridos del barbero para editar su contacto (prefijo de celular, celular) sean válidos en tipo de dato, longitud, obligatoriedad, formato y rango | D9: Barbero
A10: P-BAR-0005 | B10: Asegurar que los datos requeridos del barbero editar sus tiempos de anticipación (prefijo de celular, celular) sean válidos en tipo de dato, longitud, obligatoriedad, formato y rango | D10: Barbero

Sheet E-Barbero
A1: << Ir al modelo de dominio | C1: << Ir al listado de objetos de dominio | F1: << Ir a la caracterización del objeto de dominio | J1: Ir al muestreo de datos del objeto de dominio >>
A2: Objeto de Dominio: | B2: ='Objetos de Dominio'!A10 -> Barbero
A3: Descripción: | B3: ='Objetos de Dominio'!B10 -> Representa a un trabajador de la barbería que atiende clientes según los servicios que sabe realizar, organiza su propio horario y tiene su agenda personal
A4: Actor | B4: Action/Command | D4: Entity/Aggregate/Object domain | E4: Read Model | G4: Business Rule/Policy | I4: External System | J4: Domain Event | K4: Hotspot/questions/Risk
A5: Actor | B5: Acción | C5: Descripción | D5: Objeto de dominio | E5: Información externa | G5: Políticas | I5: Sistema Externo | J5: Evento | K5: Aspectos por solucionar
E6: Información | F6: Descripción | G6: Número | H6: Descripción
A7: Barbero | B7: Registrar barbero a la barbería | C7: Comando que permite el ingreso de un nuevo barbero a trabajar en la barbería | D7: =$B$2 -> Barbero | G7: ='P-Barbero'!A6 -> P-BAR-0001 | H7: aquí | J7: Barbero registrado
G8: ='P-Barbero'!A7 -> P-BAR-0002 | H8: aquí
A9: Barbero | B9: Editar contacto | C9: Permite al barbero actualizar su número de celular y su prefijo | D9: =$B$2 -> Barbero | G9: ='P-Barbero'!A9 -> P-BAR-0004 | H9: aquí | J9: Contacto de barbero actualizado
A10: Barbero | B10: Editar tiempos de anticipación de citas | C10: Permite al barbero ajustar cuánta anticipación mínima exige para que le agenden una cita | D10: =$B$2 -> Barbero | G10: ='P-Barbero'!A10 -> P-BAR-0005 | H10: aquí | J10: Tiempos de anticipación de barbero actualizados
A11: Cliente | B11: Ver datos de un barbero | C11: Permite a un cliente ver los datos públicos de un barbero, como sus nombres, apellidos y su contacto | D11: =$B$2 -> Barbero | J11: Datos de barbero visto
A12: Barbero | B12: Ver datos de un barbero | C12: Permite a un barbero ver los datos públicos de otro barbero, como sus nombres, apellidos y su contacto | D12: =$B$2 -> Barbero | J12: Datos de barbero visto
A13: Barbero | B13: Dejar de trabajar en la barbería | C13: Permite desactivar a un barbero para que ya no pueda recibir nuevas citas, sin borrar su historial | D13: =$B$2 -> Barbero | G13: ='P-Barbero'!A8 -> P-BAR-0003 | H13: aquí | J13: Barbero desactivado | K13: Mejor usar el efecto cascada si el barbero deja de trabajar todas las citas futuras que tenian se van a cancelar
A14: Barbero | B14: Ver tiempos de anticipacion para las citas | C14: Permite al barbero ver su tiempo de anticipacion en horas y minutos para sus citas | D14: =$B$2 -> Barbero

Sheet M-Barbero
A1: <<<< Ir al modulo de dominio | B1: <<<< Ir a objetos de dominio
A2: Representa un identificador que hará unico cada objeto de dominio de este tipo, no se puede repetir | B2: Representa el primer nombre del barbero que trabaja en barbería | C2: Representa el segundo nombre del barbero que trabaja en barbería | D2: Representa el primer apellido del barbero que trabaja en la barbería | E2: Representa el segundo apellido del barbero que trabaja en la barbería | F2: Representa cual es el prefijo del numero de celular del barbero | G2: Representa el número de celular del barbero, es el dato que el cliente necesita en caso de que tenga que contactarse con el | H2: Representa si el barbero sigue o no trabajando en la barberia | I2: Representa la parte en horas del tiempo mínimo de anticipación con el que un cliente debe pedirle una cita a este barbero. Junto con anticipacionEnMinutosParaAgendarCita forma el tiempo total de anticipación que exige el barbero | J2: Representa la parte en minutos del tiempo mínimo de anticipación con el que un cliente debe pedirle una cita a este barbero. Junto con anticipacionEnHorasParaAgendarCita forma el tiempo total de anticipación que exige el barbero | K2: Combinacion única que indica que no puede existir más de un barbero con el mismo prefijo de celular y número de celular
A3: id | B3: primerNombre | C3: segundoNombre | D3: primerApellido | E3: segundoApellido | F3: prefijo | G3: celular | H3: vigente | I3: anticipacionEnHorasParaAgendarCita | J3: anticipacionEnMinutosParaAgendarCita | K3: Combinación única 1
A4: 1 | B4: Juan | C4: Fernando | D4: García | E4: Lopez | F4: ='M-PrefijoCelular'!C4 -> +57 | G4: 3245627890 | H4: si | I4: 24 | J4: 0 | K4: =_xlfn.CONCAT(F4,"-",G4) -> +57-3245627890
A5: 2 | B5: Juan | C5: David | D5: Ortiz | E5: Sanchez | F5: ='M-PrefijoCelular'!C4 -> +57 | G5: 3124518923 | H5: si | I5: 0 | J5: 30 | K5: =_xlfn.CONCAT(F5,"-",G5) -> +57-3124518923
A6: 3 | B6: Carlos | D6: Arbeladez | F6: ='M-PrefijoCelular'!C4 -> +57 | G6: 3214533321 | H6: si | I6: 1 | J6: 0 | K6: =_xlfn.CONCAT(F6,"-",G6) -> +57-3214533321
A7: 4 | B7: Andres | D7: Ramirez | E7: Patiño | F7: ='M-PrefijoCelular'!C5 -> +91 | G7: 9876543210 | H7: no | I7: 0 | J7: 0 | K7: =_xlfn.CONCAT(F7,"-",G7) -> +91-9876543210
A8: 5 | B8: Juan | C8: Carlos | D8: Zambrano | E8: Perez | F8: ='M-PrefijoCelular'!C6 -> +593 | G8: 998765432 | H8: no | I8: 2 | J8: 0 | K8: =_xlfn.CONCAT(F8,"-",G8) -> +593-998765432
B14: Corresponde a la descripcion de los atributos
B15: Corresponde al identificador unico del objeto de dominio
B16: Corresponde a los datos de tipo alfanumerico
B17: Corresponde a referencias de objetos de dominio
B18: Corresponde a los datos de tipo entero
B19: Corresponde a los datos de tipo lógico
B20: Corresponde a la combinacion única 1

Sheet C-Cliente
A1: <<<< Ir al modulo de dominio | B1: <<<< Ir a objetos de dominio
A2: Nombre atributo | B2: Descripción atributo | C2: Identificador del objeto de dominio | D2: Tipo de dato | E2: Obligatorio | F2: Longitud mínima (si aplica) | G2: Longitud máxima (si aplica) | H2: Precisión (si aplica) | I2: Rendondeo (si aplica) | J2: Rango inicial (si aplica) | K2: Rango final (si aplica) | L2: Formato (si aplica) | M2: Reglas especiales (si aplica) | N2: Dato calculado | O2: Aplica ajuste del dato (si aplica) | P2: Carácter de ajuste (si aplica) | Q2: Quitar espacios en blanco al inicio (si aplica) | R2: Quitar espacios en blanco al fin (si aplica) | S2: Dato sensible (si aplica) | T2: Valor por defecto (si aplica) | U2: Auto generado
A3: ='M-Cliente'!A3 -> id | B3: ='M-Cliente'!A2 -> Representa un identificador que hará unico cada objeto de dominio de este tipo, no se puede repetir | C3: Si | D3: Identificador único universal | E3: Si | F3: No aplica | G3: No aplica | H3: No aplica | I3: No aplica | J3: No aplica | K3: No aplica | L3: No aplica | M3: No aplica | N3: Si | O3: No | P3: No aplica | Q3: No aplica | R3: No aplica | S3: No | T3: UUID vacio | U3: Si
A4: ='M-Cliente'!B3 -> primerNombre | B4: ='M-Cliente'!B2 -> Representa el primer nombre de la persona, que va a estar llendo a la barberia para las citas | C4: No | D4: Alfanumérico | E4: Si | F4: 2 | G4: 50 | H4: No aplica | I4: No aplica | J4: No aplica | K4: No aplica | L4: No aplica | M4: Solo se aceptan caracteres de letras de la 'a' a la 'z', caracteres con tilde y numeros del 0 al 9 | N4: No | O4: No | P4: No | Q4: Si | R4: Si | S4: No | T4: Vacio | U4: No
A5: ='M-Cliente'!C3 -> segundoNombre | B5: ='M-Cliente'!C2 -> Representa el segundo nombre de la persona, que va a estar llendo a la barberia para las citas | C5: No | D5: Alfanumérico | E5: No | F5: 2 | G5: 50 | H5: No aplica | I5: No aplica | J5: No aplica | K5: No aplica | L5: No aplica | M5: Solo se aceptan caracteres de letras de la 'a' a la 'z', caracteres con tilde y numeros del 0 al 9 | N5: No | O5: No | P5: No | Q5: Si | R5: Si | S5: No | T5: Vacio | U5: No
A6: ='M-Cliente'!D3 -> primerApellido | B6: ='M-Cliente'!D2 -> Representa el primer apellido de la persona, que va a estar llendo a la barberia para las citas | C6: No | D6: Alfanumérico | E6: Si | F6: 2 | G6: 50 | H6: No aplica | I6: No aplica | J6: No aplica | K6: No aplica | L6: No aplica | M6: Solo se aceptan caracteres de letras de la 'a' a la 'z', caracteres con tilde y numeros del 0 al 9 | N6: No | O6: No | P6: No | Q6: Si | R6: Si | S6: No | T6: Vacio | U6: No
A7: ='M-Cliente'!E3 -> segundoApellido | B7: ='M-Cliente'!E2 -> Representa el segundo apellido de la persona, que va a estar llendo a la barberia para las citas | C7: No | D7: Alfanumérico | E7: No | F7: 2 | G7: 50 | H7: No aplica | I7: No aplica | J7: No aplica | K7: No aplica | L7: No aplica | M7: Solo se aceptan caracteres de letras de la 'a' a la 'z', caracteres con tilde y numeros del 0 al 9 | N7: No | O7: No | P7: No | Q7: Si | R7: Si | S7: No | T7: Vacio | U7: No
A8: ='M-Cliente'!F3 -> prefijoCelular | B8: ='M-Cliente'!F2 -> Representa cual es el prefijo del numero de celular del cliente | C8: No | D8: PrefijoCelular | E8: Si | F8: 2 | G8: 4 | H8: No aplica | I8: No aplica | J8: No aplica | K8: No aplica | L8: El mismo formato del objeto referenciado | M8: Aplican las reglas del objeto referenciado | N8: No | O8: No | P8: No aplica | Q8: No | R8: No | S8: Si | T8: UUID vacio | U8: No
A9: ='M-Cliente'!G3 -> celular | B9: ='M-Cliente'!G2 -> Representa el numero de celular del cliente, es el dato que el barbero necesita en caso de que tenga que contactarse con el | C9: No | D9: Alfanumérico | E9: Si | F9: 4 | G9: 15 | H9: No aplica | I9: No aplica | J9: No aplica | K9: No aplica | L9: Deben de ser solo números que cumplan un número de teléfono válido | M9: No aplica | N9: No | O9: No | P9: No | Q9: Si | R9: Si | S9: Si | T9: 0 | U9: No
A10: ='M-Cliente'!I3 -> multasSinPagar | B10: ='M-Cliente'!I2 -> Representa la cantidad de multas que tiene sin pagar en las citas que ha tenido, ya sea multa por tardanza o por no llegar | C10: No | D10: Entero | E10: Si | F10: No aplica | G10: No aplica | H10: No aplica | I10: No aplica | J10: 0 | K10: 3 | L10: No aplica | M10: Se calcula contando las Multa del cliente donde pagada='no' | N10: Si | O10: No | P10: No aplica | Q10: No aplica | R10: No aplica | S10: No | T10: 0 | U10: No
A11: ='M-Cliente'!J3 -> estaVetado | B11: ='M-Cliente'!J2 -> Representa si el cliente esta en estado de veto o no, cuando el cliente esta vetado el sistema no va a permitir agendar citas con este cliente con ningun barbero | C11: No | D11: Lógico | E11: Si | F11: No aplica | G11: No aplica | H11: No aplica | I11: No aplica | J11: No aplica | K11: No aplica | L11: No aplica | M11: Se calcula comparando multasSinPagar contra Regla.numeroMultasMaxima; si multasSinPagar alcanza ese máximo, el cliente queda vetado | N11: Si | O11: No | P11: No aplica | Q11: No aplica | R11: No aplica | S11: No | T11: No | U11: No
A12: ='M-Cliente'!K3 -> cantidadDeDescuentoCitas | B12: ='M-Cliente'!K2 -> Representa la cantidad de citas que un cliente va a tener con descuento, cada inasistencia que un barbero le haga al cliente se le suma un descuento a la proxima cita | C12: No | D12: Entero | E12: Si | F12: No aplica | G12: No aplica | H12: No aplica | I12: No aplica | J12: 0 | K12: 1000 | L12: No aplica | M12: Se calcula contando cuántas citas con inasistencia del barbero ha tenido el cliente | N12: Si | O12: No | P12: No aplica | Q12: No aplica | R12: No aplica | S12: No | T12: 0 | U12: No
A14: Nombre combinación única | B14: Descripción | C14: Atributos involucrados
A15: ='M-Cliente'!L3 -> Combinación única 1 | B15: ='M-Cliente'!L2 -> Combinacion única que indica que no puede existir más de un cliente con el mismo prefijo de celular y número de celular | C15: =A8 -> prefijoCelular
C18: =A9 -> celular

Sheet P-Cliente
A1: << Ir al modelo de dominio | B1: << Ir al listado de objetos de dominio | C1: << Ir a la caracterización del objeto de dominio | D1: Ir al muestreo de datos del objeto de dominio >> | E1: Ir al event storming del objeto de dominio >>
A2: Objeto de Dominio: | B2: ='Objetos de Dominio'!A11 -> Cliente
A3: Descripción: | B3: ='Objetos de Dominio'!B11 -> Representa a la persona que solicita citas en la barbería con un barbero. Guarda su historial de multas sin pagar para saber si está o no vetado
A4: Numero politica | B4: Descripcion politica | D4: Objeto responsable | E4: Regla responsable
A6: P-CLI-0001 | B6: Asegurar que los datos requeridos del cliente (nombres, apellidos, prefijo de celular, celular) sean válidos en tipo de dato, longitud, obligatoriedad, formato y rango | D6: Cliente
A7: P-CLI-0002 | B7: Asegurar que el número de celular y prefijo de celular no esté siendo utilizado por otro cliente | D7: Cliente
A8: P-CLI-0003 | B8: Asegurar que los datos requeridos del cliente para editar su contacto (prefijo de celular y celular) sean válidos en tipo de dato, longitud, obligatoriedad, formato y rango | D8: Cliente

Sheet E-Cliente
A1: << Ir al modelo de dominio | C1: << Ir al listado de objetos de dominio | F1: << Ir a la caracterización del objeto de dominio | J1: Ir al muestreo de datos del objeto de dominio >>
A2: Objeto de Dominio: | B2: ='Objetos de Dominio'!A11 -> Cliente
A3: Descripción: | B3: ='Objetos de Dominio'!B11 -> Representa a la persona que solicita citas en la barbería con un barbero. Guarda su historial de multas sin pagar para saber si está o no vetado
A4: Actor | B4: Action/Command | D4: Entity/Aggregate/Object domain | E4: Read Model | G4: Business Rule/Policy | I4: External System | J4: Domain Event | K4: Hotspot/questions/Risk
A5: Actor | B5: Acción | C5: Descripción | D5: Objeto de dominio | E5: Información externa | G5: Políticas | I5: Sistema Externo | J5: Evento | K5: Aspectos por solucionar
E6: Información | F6: Descripción | G6: Número | H6: Descripción
A7: Cliente | B7: Registrar cliente a la barbería | C7: Comando que permite el registro de un nuevo cliente en la barbería | D7: =$B$2 -> Cliente | G7: ='P-Cliente'!A6 -> P-CLI-0001 | H7: aquí | J7: Cliente registrado
G8: ='P-Cliente'!A7 -> P-CLI-0002 | H8: aquí
A9: Cliente | B9: Editar contacto | C9: Permite al cliente actualizar su número de celular y su prefijo | D9: =$B$2 -> Cliente | G9: ='P-Cliente'!A8 -> P-CLI-0003 | H9: aquí | J9: Contacto de cliente actualizado
A10: Barbero | B10: Ver datos de un cliente | C10: Permite a un barbero ver los datos de un cliente que le va a pedir una cita | D10: =$B$2 -> Cliente | J10: Datos del cliente vistos
A11: Cliente | B11: Ver estado de vetado | C11: Permite al cliente ver si tiene tantas multas sin pagar que ya no puede agendar nuevas citas | D11: =$B$2 -> Cliente | J11: Estado de veto del cliente visto
A12: Cliente | B12: Ver cantidad de descuentos para las citas | C12: Permite al cliente ver cuántos descuentos acumulados tiene disponibles por demoras del barbero | D12: =$B$2 -> Cliente | J12: Descuentos del cliente vistos
A13: Cliente | B13: Ver cantidad de multas sin pagar | C13: Permite al cliente ver cuántas multas sin pagar tiene | D13: =$B$2 -> Cliente | J13: Multas sin pagar del cliente vistas

Sheet M-Cliente
A1: <<<< Ir al modulo de dominio | B1: <<<< Ir a objetos de dominio
A2: Representa un identificador que hará unico cada objeto de dominio de este tipo, no se puede repetir | B2: Representa el primer nombre de la persona, que va a estar llendo a la barberia para las citas | C2: Representa el segundo nombre de la persona, que va a estar llendo a la barberia para las citas | D2: Representa el primer apellido de la persona, que va a estar llendo a la barberia para las citas | E2: Representa el segundo apellido de la persona, que va a estar llendo a la barberia para las citas | F2: Representa cual es el prefijo del numero de celular del cliente | G2: Representa el numero de celular del cliente, es el dato que el barbero necesita en caso de que tenga que contactarse con el | H2: Representa si el numero que ingreso el cliente es correcto o no | I2: Representa la cantidad de multas que tiene sin pagar en las citas que ha tenido, ya sea multa por tardanza o por no llegar | J2: Representa si el cliente esta en estado de veto o no, cuando el cliente esta vetado el sistema no va a permitir agendar citas con este cliente con ningun barbero | K2: Representa la cantidad de citas que un cliente va a tener con descuento, cada inasistencia que un barbero le haga al cliente se le suma un descuento a la proxima cita | L2: Combinacion única que indica que no puede existir más de un cliente con el mismo prefijo de celular y número de celular
A3: id | B3: primerNombre | C3: segundoNombre | D3: primerApellido | E3: segundoApellido | F3: prefijoCelular | G3: celular | H3: elNumeroCelularEsCorrecto | I3: multasSinPagar | J3: estaVetado | K3: cantidadDeDescuentoCitas | L3: Combinación única 1
A4: 1 | B4: Juan | D4: Gómez | F4: ='M-PrefijoCelular'!C4 -> +57 | G4: 3234528921 | H4: Si | I4: 0 | J4: no | K4: 0 | L4: =_xlfn.CONCAT(F4,"-",G4) -> +57-3234528921
A5: 2 | B5: Jose | C5: Miguel | D5: Ramirez | E5: Perez | F5: ='M-PrefijoCelular'!C4 -> +57 | G5: 3161657782 | H5: Si | I5: 0 | J5: no | K5: 0 | L5: =_xlfn.CONCAT(F5,"-",G5) -> +57-3161657782
A6: 3 | B6: Simon | D6: Ochoa | E6: Ramirez | F6: ='M-PrefijoCelular'!C4 -> +57 | G6: 3119884321 | H6: Si | I6: 0 | J6: no | K6: 0 | L6: =_xlfn.CONCAT(F6,"-",G6) -> +57-3119884321
A7: 4 | B7: Alexis | D7: Gallego | F7: ='M-PrefijoCelular'!C7 -> +58 | G7: 4127359182 | H7: Si | I7: 1 | J7: no | K7: 1 | L7: =_xlfn.CONCAT(F7,"-",G7) -> +58-4127359182
A8: 5 | B8: Kevin | C8: Andrés | D8: Muñoz | E8: Salazar | F8: ='M-PrefijoCelular'!C4 -> +57 | G8: 3005544332 | H8: Si | I8: 3 | J8: si | K8: 0 | L8: =_xlfn.CONCAT(F8,"-",G8) -> +57-3005544332
B14: Corresponde a la descripcion de los atributos
B15: Corresponde al identificador unico del objeto de dominio
B16: Corresponde a los datos de tipo alfanumerico
B17: Corresponde a referencias de objetos de dominio
B18: Corresponde a los datos calculados por el sistema
B19: Corresponde a la combinacion única

Sheet C-HorarioBarberia
A1: <<<< Ir al modulo de dominio | B1: <<<< Ir a objetos de dominio
A2: Nombre atributo | B2: Descripción atributo | C2: Identificador del objeto de dominio | D2: Tipo de dato | E2: Obligatorio | F2: Longitud mínima (si aplica) | G2: Longitud máxima (si aplica) | H2: Precisión (si aplica) | I2: Rendondeo (si aplica) | J2: Rango inicial (si aplica) | K2: Rango final (si aplica) | L2: Formato (si aplica) | M2: Reglas especiales (si aplica) | N2: Dato calculado | O2: Aplica ajuste del dato (si aplica) | P2: Carácter de ajuste (si aplica) | Q2: Quitar espacios en blanco al inicio (si aplica) | R2: Quitar espacios en blanco al fin (si aplica) | S2: Dato sensible (si aplica) | T2: Valor por defecto (si aplica) | U2: Auto generado
A3: ='M-HorarioBarberia'!A3 -> id | B3: ='M-HorarioBarberia'!A2 -> Representa un identificador que hará unico cada objeto de dominio de este tipo, no se puede repetir | C3: Si | D3: Identificador único universal | E3: Si | F3: No aplica | G3: No aplica | H3: No aplica | I3: No aplica | J3: No aplica | K3: No aplica | L3: No aplica | M3: No aplica | N3: No | O3: No | P3: No aplica | Q3: No aplica | R3: No aplica | S3: No | T3: UUID vacio | U3: Si
A4: ='M-HorarioBarberia'!B3 -> diaDeLaSemana | B4: ='M-HorarioBarberia'!B2 -> Representa el día de la semana en el que la barberia abre | C4: No | D4: DiaSemana | E4: Si | F4: No aplica | G4: No aplica | H4: No aplica | I4: No aplica | J4: No aplica | K4: No aplica | L4: No aplica | M4: Aplican las reglas del objeto referenciado | N4: No | O4: No | P4: No aplica | Q4: No aplica | R4: No aplica | S4: No | T4: UUID vacio | U4: No
A5: ='M-HorarioBarberia'!C3 -> horaApertura | B5: ='M-HorarioBarberia'!C2 -> Representa la hora a la que abre la barbería | C5: No | D5: Hora | E5: No | F5: No aplica | G5: No aplica | H5: No aplica | I5: No aplica | J5: No aplica | K5: No aplica | L5: No aplica | M5: No aplica | N5: No | O5: No | P5: No aplica | Q5: No aplica | R5: No aplica | S5: No | T5: 00:00 | U5: No
A6: ='M-HorarioBarberia'!D3 -> horaCierre | B6: ='M-HorarioBarberia'!D2 -> Representa la hora a la que cierra la barbería | C6: No | D6: Hora | E6: Si | F6: No aplica | G6: No aplica | H6: No aplica | I6: No aplica | J6: No aplica | K6: No aplica | L6: No aplica | M6: Debe ser mayor a horaApertura | N6: No | O6: No | P6: No aplica | Q6: No aplica | R6: No aplica | S6: No | T6: 00:00 | U6: No
A7: ='M-HorarioBarberia'!E3 -> fechaCreacion | B7: ='M-HorarioBarberia'!E2 -> Representa la fecha en el que el dueño definio el horario de la barberia. Es un dato calculado que toma la fecha del sistema en ese momento | C7: No | D7: Fecha | E7: Si | F7: No aplica | G7: No aplica | H7: No aplica | I7: No aplica | J7: No aplica | K7: No aplica | L7: No aplica | M7: No aplica | N7: Si | O7: No | P7: No aplica | Q7: No aplica | R7: No aplica | S7: No | T7: 1/01/1000 | U7: No
A8: ='M-HorarioBarberia'!F3 -> fechaDesactivacion | B8: ='M-HorarioBarberia'!F2 -> Representa la fecha en la que este horario dejó de estar vigente, dueño. Es un dato calculado que toma la fecha del sistema en ese momento | C8: No | D8: Fecha | E8: No | F8: No aplica | G8: No aplica | H8: No aplica | I8: No aplica | J8: No aplica | K8: No aplica | L8: No aplica | M8: No aplica | N8: Si | O8: No | P8: No aplica | Q8: No aplica | R8: No aplica | S8: No | T8: 1/01/1000 | U8: No
A9: ='M-HorarioBarberia'!G3 -> vigente | B9: ='M-HorarioBarberia'!G2 -> Representa si este horario lo sigue o no vigente en la barberia. Una vez que el dueño desactive el horario de la barberia, no se puede volver a cambiar | C9: No | D9: Lógico | E9: No | F9: No aplica | G9: No aplica | H9: No aplica | I9: No aplica | J9: No aplica | K9: No aplica | L9: No aplica | M9: No aplica | N9: No | O9: No | P9: No aplica | Q9: No aplica | R9: No aplica | S9: No | T9: Si | U9: No
A11: Nombre combinación única | B11: Descripción | C11: Atributos involucrados
A12: ='M-HorarioBarberia'!H3 -> Combinación única | B12: ='M-HorarioBarberia'!H2 -> Combinacion única que indica que no puede existir más de un horario con la misma barberia, dia de la semana, hora de apertura y cierre | C12: =A4 -> diaDeLaSemana
C13: =A5 -> horaApertura
C14: =A6 -> horaCierre
C15: =A7 -> fechaCreacion
C16: =A8 -> fechaDesactivacion
C17: =A9 -> vigente

Sheet P-HorarioBarberia
A1: << Ir al modelo de dominio | B1: << Ir al listado de objetos de dominio | C1: << Ir a la caracterización del objeto de dominio | D1: Ir al muestreo de datos del objeto de dominio >> | E1: Ir al event storming del objeto de dominio >>
A2: Objeto de Dominio: | B2: ='Objetos de Dominio'!A12 -> HorarioBarberia
A3: Descripción: | B3: ='Objetos de Dominio'!B12 -> Representa, día por día, a qué hora abre y cierra el negocio; es el límite dentro del cual debe caber el horario de cualquier barbero
A4: Numero politica | B4: Descripcion politica | D4: Objeto responsable | E4: Regla responsable
A6: P-HBA-0001 | B6: Asegurar que los datos requeridos (día de la semana, hora de apertura, hora de cierre) sean válidos en tipo de dato, obligatoriedad, formato y rango, y que la hora de cierre sea mayor a la hora de apertura | D6: HorarioBarberia
A7: P-HBA-0002 | B7: Asegurar que no exista otro horario vigente definido para el mismo día de la semana, que se cruze con las horas de apertura y cierre | D7: HorarioBarberia
A8: P-HBA-0003 | B8: Al desactivar un horario de barbería, desactivar en cascada los horarios de barbero que dependen de él y cancelar las citas futuras que queden fuera de horario | D8: HorarioBarbero
C14: Pensar si se cancela todo o los barberos debe de cancelarlo manualmente
C15: O si es mejor que se haga todo automatico
C16: Como influnye en las lineas de vida posteriores

Sheet E-HorarioBarberia
A1: << Ir al modelo de dominio | C1: << Ir al listado de objetos de dominio | F1: << Ir a la caracterización del objeto de dominio | J1: Ir al muestreo de datos del objeto de dominio >>
A2: Objeto de Dominio: | B2: ='Objetos de Dominio'!A12 -> HorarioBarberia
A3: Descripción: | B3: ='Objetos de Dominio'!B12 -> Representa, día por día, a qué hora abre y cierra el negocio; es el límite dentro del cual debe caber el horario de cualquier barbero
A4: Actor | B4: Action/Command | D4: Entity/Aggregate/Object domain | E4: Read Model | G4: Business Rule/Policy | I4: External System | J4: Domain Event | K4: Hotspot/questions/Risk
A5: Actor | B5: Acción | C5: Descripción | D5: Objeto de dominio | E5: Información externa | G5: Políticas | I5: Sistema Externo | J5: Evento | K5: Aspectos por solucionar
E6: Información | F6: Descripción | G6: Número | H6: Descripción
A7: Dueño | B7: Definir un horario de la barbería | C7: Comando que permite registrar la hora de apertura y cierre de la barbería para un día de la semana | D7: =$B$2 -> HorarioBarberia | G7: ='P-HorarioBarberia'!A6 -> P-HBA-0001 | H7: aquí | J7: Horario de barbería definido
G8: ='P-HorarioBarberia'!A7 -> P-HBA-0002 | H8: aquí
A9: Dueño | B9: Ver horarios de la barbería | C9: Permite al dueño consultar los horarios de apertura y cierre definidos para cada día de la semana | D9: =$B$2 -> HorarioBarberia | J9: Horarios de barbería consultados
A10: Barbero | B10: Ver horarios de la barbería | C10: Permite al barbero consultar los horarios de apertura y cierre definidos para cada día de la semana | D10: =$B$2 -> HorarioBarberia | J10: Horarios de barbería consultados
A11: Cliente | B11: Ver horarios de la barbería | C11: Permite al cliente consultar los horarios de apertura y cierre definidos para cada día de la semana | D11: =$B$2 -> HorarioBarberia | J11: Horarios de barbería consultados
A12: Dueño | B12: Desactivar horario de barbería | C12: Permite desactivar el horario en el que la barberia ya no abrira | D12: =$B$2 -> HorarioBarberia | G12: ='P-HorarioBarberia'!A8 -> P-HBA-0003 | H12: aquí | J12: Horario de barbería desactivado | K12: Cascada de desactivación (HorarioBarbero y Cita futuras) propuesta pero aún no implementada

Sheet M-HorarioBarberia
A1: <<<< Ir al modulo de dominio | B1: <<<< Ir a objetos de dominio
A2: Representa un identificador que hará unico cada objeto de dominio de este tipo, no se puede repetir | B2: Representa el día de la semana en el que la barberia abre | C2: Representa la hora a la que abre la barbería | D2: Representa la hora a la que cierra la barbería | E2: Representa la fecha en el que el dueño definio el horario de la barberia. Es un dato calculado que toma la fecha del sistema en ese momento | F2: Representa la fecha en la que este horario dejó de estar vigente, dueño. Es un dato calculado que toma la fecha del sistema en ese momento | G2: Representa si este horario lo sigue o no vigente en la barberia. Una vez que el dueño desactive el horario de la barberia, no se puede volver a cambiar | H2: Combinacion única que indica que no puede existir más de un horario con la misma barberia, dia de la semana, hora de apertura y cierre
A3: id | B3: diaDeLaSemana | C3: horaApertura | D3: horaCierre | E3: fechaCreacion | F3: fechaDesactivacion | G3: vigente | H3: Combinación única
A4: 1 | B4: ='M-DiaSemana'!C4 -> Lunes | C4: 0.375 | D4: 0.79166667 | E4: 45242 | F4: 1/01/1000 | G4: Si | H4: =_xlfn.CONCAT(B4,"-",TEXT(C4,"hh:mm"),"-",TEXT(D4,"hh:mm"),"-",TEXT(E4,"dd/mm/yyyy"),"-",TEXT(F4,"dd/mm/yyyy")) -> Lunes-09:00-19:00-12/11/2023-1/01/1000
A5: 2 | B5: ='M-DiaSemana'!C5 -> Martes | C5: 0.375 | D5: 0.79166667 | E5: 45242 | F5: 1/01/1000 | G5: Si | H5: =_xlfn.CONCAT(B5,"-",TEXT(C5,"hh:mm"),"-",TEXT(D5,"hh:mm"),"-",TEXT(E5,"dd/mm/yyyy"),"-",TEXT(F5,"dd/mm/yyyy")) -> Martes-09:00-19:00-12/11/2023-1/01/1000
A6: 3 | B6: ='M-DiaSemana'!C6 -> Miércoles | C6: 0.375 | D6: 0.79166667 | E6: 45242 | F6: 1/01/1000 | G6: Si | H6: =_xlfn.CONCAT(B6,"-",TEXT(C6,"hh:mm"),"-",TEXT(D6,"hh:mm"),"-",TEXT(E6,"dd/mm/yyyy"),"-",TEXT(F6,"dd/mm/yyyy")) -> Miércoles-09:00-19:00-12/11/2023-1/01/1000
A7: 4 | B7: ='M-DiaSemana'!C7 -> Jueves | C7: 0.375 | D7: 0.79166667 | E7: 45242 | F7: 1/01/1000 | G7: Si | H7: =_xlfn.CONCAT(B7,"-",TEXT(C7,"hh:mm"),"-",TEXT(D7,"hh:mm"),"-",TEXT(E7,"dd/mm/yyyy"),"-",TEXT(F7,"dd/mm/yyyy")) -> Jueves-09:00-19:00-12/11/2023-1/01/1000
A8: 5 | B8: ='M-DiaSemana'!C8 -> Viernes | C8: 0.375 | D8: 0.79166667 | E8: 45242 | F8: 1/01/1000 | G8: Si | H8: =_xlfn.CONCAT(B8,"-",TEXT(C8,"hh:mm"),"-",TEXT(D8,"hh:mm"),"-",TEXT(E8,"dd/mm/yyyy"),"-",TEXT(F8,"dd/mm/yyyy")) -> Viernes-09:00-19:00-12/11/2023-1/01/1000
A9: 6 | B9: ='M-DiaSemana'!C9 -> Sábado | C9: 0.33333333 | D9: 0.875 | E9: 45638 | F9: 1/01/1000 | G9: Si | H9: =_xlfn.CONCAT(B9,"-",TEXT(C9,"hh:mm"),"-",TEXT(D9,"hh:mm"),"-",TEXT(E9,"dd/mm/yyyy"),"-",TEXT(F9,"dd/mm/yyyy")) -> Sábado-08:00-21:00-12/12/2024-1/01/1000
A10: 7 | B10: ='M-DiaSemana'!C11 -> Festivo | C10: 0.41666667 | D10: 0.625 | E10: 45638 | F10: 1/01/1000 | G10: Si | H10: =_xlfn.CONCAT(B10,"-",TEXT(C10,"hh:mm"),"-",TEXT(D10,"hh:mm"),"-",TEXT(E10,"dd/mm/yyyy"),"-",TEXT(F10,"dd/mm/yyyy")) -> Festivo-10:00-15:00-12/12/2024-1/01/1000
B16: Corresponde a la descripcion de los atributos
B17: Corresponde al identificador unico del objeto de dominio
B18: Corresponde a referencias de objetos de dominio
B19: Corresponde a los datos de tipo hora
B20: Corresponde a los datos calculados por el sistema
B21: Corresponde a los datos tipo logico
B22: Corresponde a la combinacion única

Sheet C-BarberoServicio
A1: <<<< Ir al modulo de dominio | B1: <<<< Ir a objetos de dominio
A2: Nombre atributo | B2: Descripción atributo | C2: Identificador del objeto de dominio | D2: Tipo de dato | E2: Obligatorio | F2: Longitud mínima (si aplica) | G2: Longitud máxima (si aplica) | H2: Precisión (si aplica) | I2: Rendondeo (si aplica) | J2: Rango inicial (si aplica) | K2: Rango final (si aplica) | L2: Formato (si aplica) | M2: Reglas especiales (si aplica) | N2: Dato calculado | O2: Aplica ajuste del dato (si aplica) | P2: Carácter de ajuste (si aplica) | Q2: Quitar espacios en blanco al inicio (si aplica) | R2: Quitar espacios en blanco al fin (si aplica) | S2: Dato sensible (si aplica) | T2: Valor por defecto (si aplica) | U2: Auto generado
A3: ='M-BarberoServicio'!A3 -> id | B3: ='M-BarberoServicio'!A2 -> Representa un identificador que hará unico cada objeto de dominio de este tipo, no se puede repetir | C3: Si | D3: Identificador único universal | E3: Si | F3: No aplica | G3: No aplica | H3: No aplica | I3: No aplica | J3: No aplica | K3: No aplica | L3: No aplica | M3: No aplica | N3: No | O3: No aplica | P3: No aplica | Q3: No aplica | R3: No aplica | S3: No | T3: UUID vacio | U3: Si
A4: ='M-BarberoServicio'!B3 -> barbero | B4: ='M-BarberoServicio'!B2 -> Representa el nombre y apellidos del barbero | C4: No | D4: Barbero | E4: Si | F4: No aplica | G4: No aplica | H4: No aplica | I4: No aplica | J4: No aplica | K4: No aplica | L4: No aplica | M4: Aplican las reglas del objeto referenciado | N4: No | O4: No aplica | P4: No aplica | Q4: No aplica | R4: No aplica | S4: No | T4: UUID vacio | U4: No
A5: ='M-BarberoServicio'!C3 -> servicio | B5: ='M-BarberoServicio'!C2 -> Representa el nombre del servicio de la barberia | C5: No | D5: Servicio | E5: Si | F5: No aplica | G5: No aplica | H5: No aplica | I5: No aplica | J5: No aplica | K5: No aplica | L5: No aplica | M5: Aplican las reglas del objeto referenciado | N5: No | O5: No aplica | P5: No aplica | Q5: No aplica | R5: No aplica | S5: No | T5: UUID vacio | U5: No
A6: ='M-BarberoServicio'!D3 -> duracionEnHoras | B6: ='M-BarberoServicio'!D2 -> Representa la cantidad de horas que un barbero tarda en realizar un servicio, esta duracion el barbero debe de ser consiente de cuanto se demora en realizarlo | C6: No | D6: Entero | E6: No | F6: No aplica | G6: No aplica | H6: No aplica | I6: No aplica | J6: 0 | K6: 3 | L6: No aplica | M6: No aplica | N6: No | O6: No aplica | P6: No aplica | Q6: No aplica | R6: No aplica | S6: No | T6: 0 | U6: No
A7: ='M-BarberoServicio'!E3 -> duracionEnMinutos | B7: ='M-BarberoServicio'!E2 -> Representa la cantidad de minutos que un barbero tarda en realizar un servicio, esta duracion el barbero debe de ser consiente de cuanto se demora en realizarlo | C7: No | D7: Entero | E7: No | F7: No aplica | G7: No aplica | H7: No aplica | I7: No aplica | J7: 0 | K7: 59 | L7: No aplica | M7: No aplica | N7: No | O7: No aplica | P7: No aplica | Q7: No aplica | R7: No aplica | S7: No | T7: 0 | U7: No
A8: ='M-BarberoServicio'!F3 -> tiempoExtra | B8: ='M-BarberoServicio'!F2 -> Representa la cantidad de minutos que un barbero pone de tiempo extra en las citas de su agenda, cada barbero usa este tiempo porque hay ocaciones que la cita se puede demorar más de lo previsto. Este tiempo les ayuda a evitar que se les retrase la agenda | C8: No | D8: Entero | E8: No | F8: No aplica | G8: No aplica | H8: No aplica | I8: No aplica | J8: 0 | K8: 59 | L8: No aplica | M8: No aplica | N8: No | O8: No aplica | P8: No aplica | Q8: No aplica | R8: No aplica | S8: No | T8: 0 | U8: No
A9: ='M-BarberoServicio'!G3 -> vigente | B9: ='M-BarberoServicio'!G2 -> Representa si el barbero sigue o no presentando el servicio en la barbería | C9: No | D9: Lógico | E9: No | F9: No aplica | G9: No aplica | H9: No aplica | I9: No aplica | J9: No aplica | K9: No aplica | L9: No aplica | M9: No aplica | N9: No | O9: No aplica | P9: No aplica | Q9: No aplica | R9: No aplica | S9: No | T9: Si | U9: No
A11: Nombre combinación única | B11: Descripción | C11: Atributos involucrados
A12: ='M-BarberoServicio'!H3 -> Combinación única | B12: ='M-BarberoServicio'!H2 -> Combinación única que indica que un mismo barbero no puede aparecer dos veces ofreciendo el mismo servicio | C12: barbero
C13: servicio

Sheet P-BarberoServicio
A1: << Ir al modelo de dominio | B1: << Ir al listado de objetos de dominio | C1: << Ir a la caracterización del objeto de dominio | D1: Ir al muestreo de datos del objeto de dominio >> | E1: Ir al event storming del objeto de dominio >>
A2: Objeto de Dominio: | B2: ='Objetos de Dominio'!A13 -> BarberoServicio
A3: Descripción: | B3: ='Objetos de Dominio'!B13 -> Representa qué servicios sabe hacer cada barbero, cuánto se demora en realizarlos y cuánto tiempo extra usa de colchón, ya que no todos los barberos ofrecen los mismos servicios
A4: Numero politica | B4: Descripcion politica | D4: Objeto responsable | E4: Regla responsable
A6: P-BSE-0001 | B6: Asegurar que los datos requeridos (duración en horas, duración en minutos, tiempo extra) sean válidos en tipo de dato, obligatoriedad y rango | D6: BarberoServicio
A7: P-BSE-0002 | B7: Asegurar que el barbero no tenga ya habilitado ese mismo servicio | D7: BarberoServicio

Sheet E-BarberoServicio
A1: << Ir al modelo de dominio | C1: << Ir al listado de objetos de dominio | F1: << Ir a la caracterización del objeto de dominio | J1: Ir al muestreo de datos del objeto de dominio >>
A2: Objeto de Dominio: | B2: ='Objetos de Dominio'!A13 -> BarberoServicio
A3: Descripción: | B3: ='Objetos de Dominio'!B13 -> Representa qué servicios sabe hacer cada barbero, cuánto se demora en realizarlos y cuánto tiempo extra usa de colchón, ya que no todos los barberos ofrecen los mismos servicios
A4: Actor | B4: Action/Command | D4: Entity/Aggregate/Object domain | E4: Read Model | G4: Business Rule/Policy | I4: External System | J4: Domain Event | K4: Hotspot/questions/Risk
A5: Actor | B5: Acción | C5: Descripción | D5: Objeto de dominio | E5: Información externa | G5: Políticas | I5: Sistema Externo | J5: Evento | K5: Aspectos por solucionar
E6: Información | F6: Descripción | G6: Número | H6: Descripción
A7: Barbero | B7: Habilitar un servicio para el barbero | C7: Comando que permite a un barbero indicar que sabe realizar un servicio del catálogo, con su duración y colchón | D7: =$B$2 -> BarberoServicio | G7: ='P-BarberoServicio'!A6 -> P-BSE-0001 | H7: aquí | J7: Servicio habilitado para barbero
G8: ='P-BarberoServicio'!A7 -> P-BSE-0002 | H8: aquí
A9: Barbero | B9: Ajustar los tiempos de un servicio del barbero | C9: Permite modificar la duración y el tiempo extra que un barbero usa para un servicio ya habilitado | D9: =$B$2 -> BarberoServicio | G9: ='P-BarberoServicio'!A6 -> P-BSE-0001 | H9: aquí | J9: Tiempos de servicio de barbero actualizados
A10: Barbero | B10: Ver servicios elegidos | C10: Permite a un barbero consultar los servicios que tiene habilitados | D10: =$B$2 -> BarberoServicio | J10: Servicios de barbero consultados
A11: Cliente | B11: Ver servicios de un barbero | C11: Permite a un cliente consultar qué servicios ofrece un barbero en particular | D11: =$B$2 -> BarberoServicio | J11: Servicios de barbero consultados
A12: Barbero | B12: Dejar de prestar el servicio para el catálogo | C12: Permite a un barbero desactivar un servicio que ya no quiere seguir ofreciendo | D12: =$B$2 -> BarberoServicio | J12: Servicio de barbero desactivado

Sheet M-BarberoServicio
A1: <<<< Ir al modulo de dominio | B1: <<<< Ir a objetos de dominio
A2: Representa un identificador que hará unico cada objeto de dominio de este tipo, no se puede repetir | B2: Representa el nombre y apellidos del barbero | C2: Representa el nombre del servicio de la barberia | D2: Representa la cantidad de horas que un barbero tarda en realizar un servicio, esta duracion el barbero debe de ser consiente de cuanto se demora en realizarlo | E2: Representa la cantidad de minutos que un barbero tarda en realizar un servicio, esta duracion el barbero debe de ser consiente de cuanto se demora en realizarlo | F2: Representa la cantidad de minutos que un barbero pone de tiempo extra en las citas de su agenda, cada barbero usa este tiempo porque hay ocaciones que la cita se puede demorar más de lo previsto. Este tiempo les ayuda a evitar que se les retrase la agenda | G2: Representa si el barbero sigue o no presentando el servicio en la barbería | H2: Combinación única que indica que un mismo barbero no puede aparecer dos veces ofreciendo el mismo servicio
A3: id | B3: barbero | C3: servicio | D3: duracionEnHoras | E3: duracionEnMinutos | F3: tiempoExtra | G3: vigente | H3: Combinación única
A4: 1 | B4: =_xlfn.CONCAT('M-Barbero'!B4," ",'M-Barbero'!D4) -> Juan García | C4: ='M-Servicio'!B4 -> Motilada | D4: 0 | E4: 45 | F4: 15 | G4: si | H4: =_xlfn.CONCAT(B4,"-",C4) -> Juan García-Motilada
A5: 2 | B5: =_xlfn.CONCAT('M-Barbero'!B5," ",'M-Barbero'!D5) -> Juan Ortiz | C5: ='M-Servicio'!B5 -> Corte de barba | D5: 0 | E5: 10 | F5: 5 | G5: si | H5: =_xlfn.CONCAT(B5,"-",C5) -> Juan Ortiz-Corte de barba
A6: 3 | B6: =_xlfn.CONCAT('M-Barbero'!B6," ",'M-Barbero'!D6) -> Carlos Arbeladez | C6: ='M-Servicio'!B6 -> Perfilada de barba | D6: 0 | E6: 15 | F6: 5 | G6: si | H6: =_xlfn.CONCAT(B6,"-",C6) -> Carlos Arbeladez-Perfilada de barba
A7: 4 | B7: =_xlfn.CONCAT('M-Barbero'!B7," ",'M-Barbero'!D7) -> Andres Ramirez | C7: ='M-Servicio'!B7 -> Arreglo completo de barba con toalla caliente | D7: 0 | E7: 40 | F7: 10 | G7: si | H7: =_xlfn.CONCAT(B7,"-",C7) -> Andres Ramirez-Arreglo completo de barba con toalla caliente
A8: 5 | B8: =_xlfn.CONCAT('M-Barbero'!B5," ",'M-Barbero'!D5) -> Juan Ortiz | C8: ='M-Servicio'!B4 -> Motilada | D8: 0 | E8: 40 | F8: 10 | G8: si | H8: =_xlfn.CONCAT(B8,"-",C8) -> Juan Ortiz-Motilada
A9: 6 | B9: =_xlfn.CONCAT('M-Barbero'!B6," ",'M-Barbero'!D6) -> Carlos Arbeladez | C9: ='M-Servicio'!B5 -> Corte de barba | D9: 0 | E9: 15 | F9: 5 | G9: si | H9: =_xlfn.CONCAT(B9,"-",C9) -> Carlos Arbeladez-Corte de barba
A10: 7 | B10: =_xlfn.CONCAT('M-Barbero'!B4," ",'M-Barbero'!D4) -> Juan García | C10: ='M-Servicio'!B6 -> Perfilada de barba | D10: 0 | E10: 20 | F10: 5 | G10: si | H10: =_xlfn.CONCAT(B10,"-",C10) -> Juan García-Perfilada de barba
A11: 8 | B11: =_xlfn.CONCAT('M-Barbero'!B7," ",'M-Barbero'!D7) -> Andres Ramirez | C11: ='M-Servicio'!B4 -> Motilada | D11: 0 | E11: 50 | F11: 15 | G11: si | H11: =_xlfn.CONCAT(B11,"-",C11) -> Andres Ramirez-Motilada
A12: 9 | B12: =_xlfn.CONCAT('M-Barbero'!B8," ",'M-Barbero'!D8) -> Juan Zambrano | C12: ='M-Servicio'!B5 -> Corte de barba | D12: 0 | E12: 12 | F12: 5 | G12: si | H12: =_xlfn.CONCAT(B12,"-",C12) -> Juan Zambrano-Corte de barba

Sheet C-HorarioBarbero
A1: <<<< Ir al modulo de dominio | B1: <<<< Ir a objetos de dominio
A2: Nombre atributo | B2: Descripción atributo | C2: Identificador del objeto de dominio | D2: Tipo de dato | E2: Obligatorio | F2: Longitud mínima (si aplica) | G2: Longitud máxima (si aplica) | H2: Precisión (si aplica) | I2: Rendondeo (si aplica) | J2: Rango inicial (si aplica) | K2: Rango final (si aplica) | L2: Formato (si aplica) | M2: Reglas especiales (si aplica) | N2: Dato calculado | O2: Aplica ajuste del dato (si aplica) | P2: Carácter de ajuste (si aplica) | Q2: Quitar espacios en blanco al inicio (si aplica) | R2: Quitar espacios en blanco al fin (si aplica) | S2: Dato sensible (si aplica) | T2: Valor por defecto (si aplica) | U2: Auto generado
A3: ='M-HorarioBarbero'!A3 -> id | B3: ='M-HorarioBarbero'!A2 -> Representa un identificador que hará unico cada objeto de dominio de este tipo, no se puede repetir | C3: Si | D3: Identificador único universal | E3: Si | F3: No aplica | G3: No aplica | H3: No aplica | I3: No aplica | J3: No aplica | K3: No aplica | L3: No aplica | M3: No aplica | N3: No | O3: No | P3: No aplica | Q3: No | R3: No | S3: No | T3: UUID vacio | U3: Si
A4: ='M-HorarioBarbero'!B3 -> barbero | B4: ='M-HorarioBarbero'!B2 -> Referencia a que barbero va a ser dueño de este horario | C4: No | D4: Barbero | E4: Si | F4: No aplica | G4: No aplica | H4: No aplica | I4: No aplica | J4: No aplica | K4: No aplica | L4: No aplica | M4: Aplican las reglas del objeto referenciado | N4: No | O4: No aplica | P4: No aplica | Q4: No aplica | R4: No aplica | S4: No | T4: UUID vacio | U4: No
A5: ='M-HorarioBarbero'!C3 -> horarioDeLaBarberia | B5: ='M-HorarioBarbero'!C2 -> Hace referencia a la agenda del barbero en la que queda guardado este horario de trabajo | C5: No | D5: HorarioBarberia | E5: Si | F5: No aplica | G5: No aplica | H5: No aplica | I5: No aplica | J5: No aplica | K5: No aplica | L5: No aplica | M5: Aplican las reglas del objeto referenciado | N5: No | O5: No aplica | P5: No aplica | Q5: No aplica | R5: No aplica | S5: No | T5: UUID vacio | U5: No
A6: ='M-HorarioBarbero'!D3 -> horaInicio | B6: ='M-HorarioBarbero'!D2 -> Representa la hora en la que el barbero empieza a estar disponible ese dia | C6: No | D6: Hora | E6: Si | F6: No aplica | G6: No aplica | H6: No aplica | I6: No aplica | J6: No aplica | K6: No aplica | L6: hh:mm | M6: Debe estar dentro del rango de horarioDeLaBarberia | N6: No | O6: No aplica | P6: No aplica | Q6: No aplica | R6: No aplica | S6: No | T6: 00:00 | U6: No
A7: ='M-HorarioBarbero'!E3 -> horaFinal | B7: ='M-HorarioBarbero'!E2 -> Representa la hora en la que el barbero deja de estar disponible ese día. | C7: No | D7: Hora | E7: Si | F7: No aplica | G7: No aplica | H7: No aplica | I7: No aplica | J7: No aplica | K7: No aplica | L7: hh:mm | M7: Debe ser mayor a horaInicio y estar dentro del rango de horarioDeLaBarberia | N7: No | O7: No aplica | P7: No aplica | Q7: No aplica | R7: No aplica | S7: No | T7: 00:00 | U7: No
A8: ='M-HorarioBarbero'!F3 -> fechaCreacion | B8: ='M-HorarioBarbero'!F2 -> Representa la fecha en el que el barbero creo su horario. Es un dato calculado que toma la fecha de hoy cuando el barbero la crea | C8: No | D8: Fecha | E8: Si | F8: No aplica | G8: No aplica | H8: No aplica | I8: No aplica | J8: No aplica | K8: No aplica | L8: dd/mm/aaaa | M8: Toma la fecha del sistema en el momento en que el barbero crea este horario | N8: Si | O8: No aplica | P8: No aplica | Q8: No aplica | R8: No aplica | S8: No | T8: 01/01/1000 | U8: No
A9: ='M-HorarioBarbero'!G3 -> fechaDesactivacion | B9: ='M-HorarioBarbero'!G2 -> Representa la fecha en la que este horario dejó de estar vigente, ya sea porque el barbero lo retiró o porque se desactivó el horario de la barbería del que depende. Es un dato calculado que toma la fecha del sistema en ese momento. | C9: No | D9: Fecha | E9: No | F9: No aplica | G9: No aplica | H9: No aplica | I9: No aplica | J9: No aplica | K9: No aplica | L9: dd/mm/aaaa | M9: Toma la fecha del sistema en el momento en que el barbero desactiva este horario. Su valor por defecto es 01/01/1000 mientras siga vigente | N9: Si | O9: No aplica | P9: No aplica | Q9: No aplica | R9: No aplica | S9: No | T9: 01/01/1000 | U9: No
A10: ='M-HorarioBarbero'!H3 -> vigente | B10: ='M-HorarioBarbero'!H2 -> Representa si este horario lo sigue o no usando el barbero. Una vez que el barbero cambie este estado a no vigente, no se puede volver a cambiar | C10: No | D10: Lógico | E10: Si | F10: No aplica | G10: No aplica | H10: No aplica | I10: No aplica | J10: No aplica | K10: No aplica | L10: No aplica | M10: Una vez se cambia a No, no puede volver a cambiar a Si | N10: No | O10: No aplica | P10: No aplica | Q10: No aplica | R10: No aplica | S10: No | T10: Si | U10: No
A12: Nombre combinación única | B12: Descripción | C12: Atributos involucrados
A13: ='M-HorarioBarbero'!I3 -> Combinación única | B13: ='M-HorarioBarbero'!I2 -> Combinación única que indica que un mismo barbero no puede tener dos horarios con el mismo día de la barbería, la misma hora de inicio y la misma hora final. No incluye vigente porque la identidad de un horario no puede cambiar cuando se desactiva | C13: =A4 -> barbero
C14: =A5 -> horarioDeLaBarberia
C15: =A6 -> horaInicio
C16: =A7 -> horaFinal
C17: =A10 -> vigente

Sheet P-HorarioBarbero
A1: << Ir al modelo de dominio | B1: << Ir al listado de objetos de dominio | C1: << Ir a la caracterización del objeto de dominio | D1: Ir al muestreo de datos del objeto de dominio >> | E1: Ir al event storming del objeto de dominio >>
A2: Objeto de Dominio: | B2: ='Objetos de Dominio'!A14 -> HorarioBarbero
A3: Descripción: | B3: ='Objetos de Dominio'!B14 -> Representa el día de la semana en que trabaja un barbero, junto con la hora en la que empieza y termina su jornada
A4: Numero politica | B4: Descripcion politica | D4: Objeto responsable | E4: Regla responsable
A6: P-HBO-0001 | B6: Asegurar que los datos requeridos (día de la semana, hora de inicio, hora de fin) sean válidos en tipo de dato, obligatoriedad, formato y rango, y que la hora de fin sea mayor a la hora de inicio | D6: HorarioBarbero
A7: P-HBO-0002 | B7: Asegurar que el horario de trabajo esté dentro del horario de apertura y cierre de la barbería para ese día | D7: HorarioBarberia
A8: P-HBO-0003 | B8: Al desactivar un horario de barbero, cancelar las citas futuras que dependan de las agendas generadas por ese horario | D8: Agenda

Sheet E-HorarioBarbero
A1: << Ir al modelo de dominio | C1: << Ir al listado de objetos de dominio | F1: << Ir a la caracterización del objeto de dominio | J1: Ir al muestreo de datos del objeto de dominio >>
A2: Objeto de Dominio: | B2: ='Objetos de Dominio'!A14 -> HorarioBarbero
A3: Descripción: | B3: ='Objetos de Dominio'!B14 -> Representa el día de la semana en que trabaja un barbero, junto con la hora en la que empieza y termina su jornada
A4: Actor | B4: Action/Command | D4: Entity/Aggregate/Object domain | E4: Read Model | G4: Business Rule/Policy | I4: External System | J4: Domain Event | K4: Hotspot/questions/Risk
A5: Actor | B5: Acción | C5: Descripción | D5: Objeto de dominio | E5: Información externa | G5: Políticas | I5: Sistema Externo | J5: Evento | K5: Aspectos por solucionar
E6: Información | F6: Descripción | G6: Número | H6: Descripción
A7: Barbero | B7: Definir mi horario de trabajo | C7: Comando que permite a un barbero registrar el día de la semana y las horas en que trabaja | D7: =$B$2 -> HorarioBarbero | G7: ='P-HorarioBarbero'!A6 -> P-HBO-0001 | H7: aquí | J7: Horario de barbero definido
G8: ='P-HorarioBarbero'!A7 -> P-HBO-0002 | H8: aquí
A9: Barbero | B9: Ver mis horarios definidos | C9: Permite a un barbero consultar los horarios de trabajo que ha definido | D9: =$B$2 -> HorarioBarbero | J9: Horarios de barbero consultados
A10: Barbero | B10: Desactivar horario de trabajo | C10: Permite a un barbero desactivar un horario para dejar de trabajar ese día de la semana | D10: =$B$2 -> HorarioBarbero | G10: ='P-HorarioBarbero'!A8 -> P-HBO-0003 | H10: aquí | J10: Horario de barbero desactivado
A11: Cliente | B11: Ver horarios de trabajo de un barbero | C11: Permite a un cliente consultar en qué días y horas trabaja un barbero | D11: =$B$2 -> HorarioBarbero | J11: Horarios de barbero consultados

Sheet M-HorarioBarbero
A1: <<<< Ir al modulo de dominio | B1: <<<< Ir a objetos de dominio
A2: Representa un identificador que hará unico cada objeto de dominio de este tipo, no se puede repetir | B2: Referencia a que barbero va a ser dueño de este horario | C2: Hace referencia a la agenda del barbero en la que queda guardado este horario de trabajo | D2: Representa la hora en la que el barbero empieza a estar disponible ese dia | E2: Representa la hora en la que el barbero deja de estar disponible ese día. | F2: Representa la fecha en el que el barbero creo su horario. Es un dato calculado que toma la fecha de hoy cuando el barbero la crea | G2: Representa la fecha en la que este horario dejó de estar vigente, ya sea porque el barbero lo retiró o porque se desactivó el horario de la barbería del que depende. Es un dato calculado que toma la fecha del sistema en ese momento. | H2: Representa si este horario lo sigue o no usando el barbero. Una vez que el barbero cambie este estado a no vigente, no se puede volver a cambiar | I2: Combinación única que indica que un mismo barbero no puede tener dos horarios con el mismo día de la barbería, la misma hora de inicio y la misma hora final. No incluye vigente porque la identidad de un horario no puede cambiar cuando se desactiva
A3: id | B3: barbero | C3: horarioDeLaBarberia | D3: horaInicio | E3: horaFinal | F3: fechaCreacion | G3: fechaDesactivacion | H3: vigente | I3: Combinación única
A4: 1 | B4: ='M-Barbero'!K4 -> +57-3245627890 | C4: ='M-HorarioBarberia'!H4 -> Lunes-09:00-19:00-12/11/2023-1/01/1000 | D4: 0.41666667 | E4: 0.66666667 | F4: 45780 | G4: 1/01/1000 | H4: si | I4: =_xlfn.CONCAT(B4,"-",C4,"-",TEXT(D4,"hh:mm"),"-",TEXT(E4,"hh:mm")) -> +57-3245627890-Lunes-09:00-19:00-12/11/2023-1/01/1000-10:00-16:00
A5: 2 | B5: ='M-Barbero'!K5 -> +57-3124518923 | C5: ='M-HorarioBarberia'!H5 -> Martes-09:00-19:00-12/11/2023-1/01/1000 | D5: 0.375 | E5: 0.625 | F5: 45718 | G5: 1/01/1000 | H5: si | I5: =_xlfn.CONCAT(B5,"-",C5,"-",TEXT(D5,"hh:mm"),"-",TEXT(E5,"hh:mm")) -> +57-3124518923-Martes-09:00-19:00-12/11/2023-1/01/1000-09:00-15:00
A6: 3 | B6: ='M-Barbero'!K6 -> +57-3214533321 | C6: ='M-HorarioBarberia'!H7 -> Jueves-09:00-19:00-12/11/2023-1/01/1000 | D6: 0.54166667 | E6: 0.79166667 | F6: 44917 | G6: 1/01/1000 | H6: si | I6: =_xlfn.CONCAT(B6,"-",C6,"-",TEXT(D6,"hh:mm"),"-",TEXT(E6,"hh:mm")) -> +57-3214533321-Jueves-09:00-19:00-12/11/2023-1/01/1000-13:00-19:00
A7: 4 | B7: ='M-Barbero'!K7 -> +91-9876543210 | C7: ='M-HorarioBarberia'!H9 -> Sábado-08:00-21:00-12/12/2024-1/01/1000 | D7: 0.33333333 | E7: 0.58333333 | F7: 45915 | G7: 46023 | H7: no | I7: =_xlfn.CONCAT(B7,"-",C7,"-",TEXT(D7,"hh:mm"),"-",TEXT(E7,"hh:mm")) -> +91-9876543210-Sábado-08:00-21:00-12/12/2024-1/01/1000-08:00-14:00
A8: 5 | B8: ='M-Barbero'!K7 -> +91-9876543210 | C8: ='M-HorarioBarberia'!H10 -> Festivo-10:00-15:00-12/12/2024-1/01/1000 | D8: 0.5 | E8: 0.625 | F8: 46054 | G8: 46083 | H8: no | I8: =_xlfn.CONCAT(B8,"-",C8,"-",TEXT(D8,"hh:mm"),"-",TEXT(E8,"hh:mm")) -> +91-9876543210-Festivo-10:00-15:00-12/12/2024-1/01/1000-12:00-15:00
B14: Corresponde a la descripcion de los atributos
B15: Corresponde al identificador unico del objeto de dominio
B16: Corresponde a referencias de objetos de dominio
B17: Corresponde a los datos de tipo alfanumerico
B18: Corresponde a los datos de tipo hora
B19: Corresponde a los datos calculados
B20: Corresponde a los datos tipo logico
B21: Corresponde a la combinacion única

Sheet C-Agenda
A1: <<<< Ir al modulo de dominio | B1: <<<< Ir a objetos de dominio
A2: Nombre atributo | B2: Descripción atributo | C2: Identificador del objeto de dominio | D2: Tipo de dato | E2: Obligatorio | F2: Longitud mínima (si aplica) | G2: Longitud máxima (si aplica) | H2: Precisión (si aplica) | I2: Rendondeo (si aplica) | J2: Rango inicial (si aplica) | K2: Rango final (si aplica) | L2: Formato (si aplica) | M2: Reglas especiales (si aplica) | N2: Dato calculado | O2: Aplica ajuste del dato (si aplica) | P2: Carácter de ajuste (si aplica) | Q2: Quitar espacios en blanco al inicio (si aplica) | R2: Quitar espacios en blanco al fin (si aplica) | S2: Dato sensible (si aplica) | T2: Valor por defecto (si aplica) | U2: Auto generado
A3: ='M-Agenda'!A3 -> id | B3: ='M-Agenda'!A2 -> Representa un identificador que hará unico cada objeto de dominio de este tipo, no se puede repetir | C3: Si | D3: Identificador único universal | E3: Si | F3: No aplica | G3: No aplica | H3: No aplica | I3: No aplica | J3: No aplica | K3: No aplica | L3: No aplica | M3: No aplica | N3: No | O3: No | P3: No aplica | Q3: No | R3: No | S3: No | T3: UUID vacio | U3: Si
A4: ='M-Agenda'!B3 -> horarioDelBarbero | B4: ='M-Agenda'!B2 -> Hace referencia al horario de trabajo del barbero (día de la semana, hora de inicio y hora final) al que pertenece esta agenda | C4: No | D4: HorarioBarbero | E4: Si | F4: No aplica | G4: No aplica | H4: No aplica | I4: No aplica | J4: No aplica | K4: No aplica | L4: No aplica | M4: Aplican las reglas del objeto referenciado | N4: No | O4: No aplica | P4: No aplica | Q4: No aplica | R4: No aplica | S4: No | T4: UUID vacio | U4: No
A5: ='M-Agenda'!C3 -> fecha | B5: ='M-Agenda'!C2 -> Representa la fecha específica en el que la agenda va a guardar las citas de ese barbero | C5: No | D5: Fecha | E5: Si | F5: No aplica | G5: No aplica | H5: No aplica | I5: No aplica | J5: No aplica | K5: No aplica | L5: No aplica | M5: No aplica | N5: No | O5: No aplica | P5: No aplica | Q5: No aplica | R5: No aplica | S5: No | T5: 01/01/1000 | U5: Si
A7: Nombre combinación única | B7: Descripción | C7: Atributos involucrados
A8: ='M-Agenda'!D3 -> Combinación única | B8: ='M-Agenda'!D2 -> Combinación única que indica que un mismo horario de barbero no puede tener más de una agenda para el mismo día | C8: =A4 -> horarioDelBarbero
C9: =A5 -> fecha

Sheet P-Agenda
A1: << Ir al modelo de dominio | B1: << Ir al listado de objetos de dominio | C1: << Ir a la caracterización del objeto de dominio | D1: Ir al muestreo de datos del objeto de dominio >> | E1: Ir al event storming del objeto de dominio >>
A2: Objeto de Dominio: | B2: ='Objetos de Dominio'!A15 -> Agenda
A3: Descripción: | B3: ='Objetos de Dominio'!B15 -> Representa un día puntual del calendario en el que un barbero, según su horario de trabajo, va a recibir citas. Es donde se agrupan todas las citas de ese barbero para ese día
A4: Numero politica | B4: Descripcion politica | D4: Objeto responsable | E4: Regla responsable
A6: P-AGE-0001 | B6: Asegurar que no exista ya una agenda para ese mismo horario de barbero y esa misma fecha | D6: Agenda
A7: P-AGE-0002 | B7: Asegurar que el barbero esté vigente antes de abrirle una nueva agenda | D7: Barbero

Sheet E-Agenda
A1: << Ir al modelo de dominio | C1: << Ir al listado de objetos de dominio | F1: << Ir a la caracterización del objeto de dominio | J1: Ir al muestreo de datos del objeto de dominio >>
A2: Objeto de Dominio: | B2: ='Objetos de Dominio'!A15 -> Agenda
A3: Descripción: | B3: ='Objetos de Dominio'!B15 -> Representa un día puntual del calendario en el que un barbero, según su horario de trabajo, va a recibir citas. Es donde se agrupan todas las citas de ese barbero para ese día
A4: Actor | B4: Action/Command | D4: Entity/Aggregate/Object domain | E4: Read Model | G4: Business Rule/Policy | I4: External System | J4: Domain Event | K4: Hotspot/questions/Risk
A5: Actor | B5: Acción | C5: Descripción | D5: Objeto de dominio | E5: Información externa | G5: Políticas | I5: Sistema Externo | J5: Evento | K5: Aspectos por solucionar
E6: Información | F6: Descripción | G6: Número | H6: Descripción
A7: Sistema | B7: Abrir la agenda de un barbero para una fecha | C7: Comando que crea la agenda del día para un barbero, a partir de su horario de trabajo vigente | D7: =$B$2 -> Agenda | G7: ='P-Agenda'!A6 -> P-AGE-0001 | H7: aquí | J7: Agenda abierta
G8: ='P-Agenda'!A7 -> P-AGE-0002 | H8: aquí
A9: Cliente | B9: Consultar la disponibilidad de un barbero para una fecha | C9: Permite a un cliente ver si un barbero tiene espacio disponible en una fecha puntual | D9: =$B$2 -> Agenda | J9: Disponibilidad de barbero consultada
A10: Barbero | B10: Consultar las citas de un barbero para una fecha | C10: Permite consultar todas las citas agrupadas en la agenda de un barbero para una fecha puntual | D10: =$B$2 -> Agenda | J10: Citas de agenda consultadas
A11: Cliente | B11: Consultar las citas de un barbero para una fecha | C11: Permite consultar todas las citas agrupadas en la agenda de un barbero para una fecha puntual | D11: =$B$2 -> Agenda | J11: Citas de agenda consultadas

Sheet M-Agenda
A1: <<<< Ir al modulo de dominio | B1: <<<< Ir a objetos de dominio
A2: Representa un identificador que hará unico cada objeto de dominio de este tipo, no se puede repetir | B2: Hace referencia al horario de trabajo del barbero (día de la semana, hora de inicio y hora final) al que pertenece esta agenda | C2: Representa la fecha específica en el que la agenda va a guardar las citas de ese barbero | D2: Combinación única que indica que un mismo horario de barbero no puede tener más de una agenda para el mismo día
A3: id | B3: horarioDelBarbero | C3: fecha | D3: Combinación única
A4: 1 | B4: ='M-HorarioBarbero'!I4 -> +57-3245627890-Lunes-09:00-19:00-12/11/2023-1/01/1000-10:00-16:00 | C4: 46265 | D4: =_xlfn.CONCAT(B4,"-",TEXT(C4,"dd/mm/yyyy")) -> +57-3245627890-Lunes-09:00-19:00-12/11/2023-1/01/1000-10:00-16:00-31/08/2026
A5: 2 | B5: ='M-HorarioBarbero'!I5 -> +57-3124518923-Martes-09:00-19:00-12/11/2023-1/01/1000-09:00-15:00 | C5: 46091 | D5: =_xlfn.CONCAT(B5,"-",TEXT(C5,"dd/mm/yyyy")) -> +57-3124518923-Martes-09:00-19:00-12/11/2023-1/01/1000-09:00-15:00-10/03/2026
A6: 3 | B6: ='M-HorarioBarbero'!I6 -> +57-3214533321-Jueves-09:00-19:00-12/11/2023-1/01/1000-13:00-19:00 | C6: 46156 | D6: =_xlfn.CONCAT(B6,"-",TEXT(C6,"dd/mm/yyyy")) -> +57-3214533321-Jueves-09:00-19:00-12/11/2023-1/01/1000-13:00-19:00-14/05/2026
A7: 4 | B7: ='M-HorarioBarbero'!I8 -> +91-9876543210-Festivo-10:00-15:00-12/12/2024-1/01/1000-12:00-15:00 | C7: 46073 | D7: =_xlfn.CONCAT(B7,"-",TEXT(C7,"dd/mm/yyyy")) -> +91-9876543210-Festivo-10:00-15:00-12/12/2024-1/01/1000-12:00-15:00-20/02/2026
A8: 5 | B8: ='M-HorarioBarbero'!I7 -> +91-9876543210-Sábado-08:00-21:00-12/12/2024-1/01/1000-08:00-14:00 | C8: 45983 | D8: =_xlfn.CONCAT(B8,"-",TEXT(C8,"dd/mm/yyyy")) -> +91-9876543210-Sábado-08:00-21:00-12/12/2024-1/01/1000-08:00-14:00-22/11/2025
A9: 6 | B9: ='M-HorarioBarbero'!I6 -> +57-3214533321-Jueves-09:00-19:00-12/11/2023-1/01/1000-13:00-19:00 | C9: 46240 | D9: =_xlfn.CONCAT(B9,"-",TEXT(C9,"dd/mm/yyyy")) -> +57-3214533321-Jueves-09:00-19:00-12/11/2023-1/01/1000-13:00-19:00-06/08/2026
A10: 7 | B10: ='M-HorarioBarbero'!I4 -> +57-3245627890-Lunes-09:00-19:00-12/11/2023-1/01/1000-10:00-16:00 | C10: 46174 | D10: =_xlfn.CONCAT(B10,"-",TEXT(C10,"dd/mm/yyyy")) -> +57-3245627890-Lunes-09:00-19:00-12/11/2023-1/01/1000-10:00-16:00-01/06/2026
A11: 8 | B11: ='M-HorarioBarbero'!I5 -> +57-3124518923-Martes-09:00-19:00-12/11/2023-1/01/1000-09:00-15:00 | C11: 46189 | D11: =_xlfn.CONCAT(B11,"-",TEXT(C11,"dd/mm/yyyy")) -> +57-3124518923-Martes-09:00-19:00-12/11/2023-1/01/1000-09:00-15:00-16/06/2026
A12: 9 | B12: ='M-HorarioBarbero'!I6 -> +57-3214533321-Jueves-09:00-19:00-12/11/2023-1/01/1000-13:00-19:00 | C12: 46205 | D12: =_xlfn.CONCAT(B12,"-",TEXT(C12,"dd/mm/yyyy")) -> +57-3214533321-Jueves-09:00-19:00-12/11/2023-1/01/1000-13:00-19:00-02/07/2026
B18: Corresponde a la descripcion de los atributos
B19: Corresponde al identificador unico del objeto de dominio
B20: Corresponde a referencias de objetos de dominio
B21: Corresponde a los datos de tipo fecha
B22: Corresponde a la combinacion única

Sheet C-Cita
A1: <<<< Ir al modulo de dominio | B1: <<<< Ir a objetos de dominio
A2: Nombre atributo | B2: Descripción atributo | C2: Identificador del objeto de dominio | D2: Tipo de dato | E2: Obligatorio | F2: Longitud mínima (si aplica) | G2: Longitud máxima (si aplica) | H2: Precisión (si aplica) | I2: Rendondeo (si aplica) | J2: Rango inicial (si aplica) | K2: Rango final (si aplica) | L2: Formato (si aplica) | M2: Reglas especiales (si aplica) | N2: Dato calculado | O2: Aplica ajuste del dato (si aplica) | P2: Carácter de ajuste (si aplica) | Q2: Quitar espacios en blanco al inicio (si aplica) | R2: Quitar espacios en blanco al fin (si aplica) | S2: Dato sensible (si aplica) | T2: Valor por defecto (si aplica) | U2: Auto generado
A3: ='M-Cita'!A3 -> id | B3: ='M-Cita'!A2 -> Representa un identificador que hará unico cada objeto de dominio de este tipo, no se puede repetir | C3: Si | D3: Identificador único universal | E3: Si | F3: No aplica | G3: No aplica | H3: No aplica | I3: No aplica | J3: No aplica | K3: No aplica | L3: No aplica | M3: No aplica | N3: No | O3: No | P3: No aplica | Q3: No | R3: No | S3: No | T3: UUID vacio | U3: Si
A4: ='M-Cita'!B3 -> cliente | B4: ='M-Cita'!B2 -> Representa a cuál cliente le pertenece esta cita | C4: No | D4: Cliente | E4: Si | F4: No aplica | G4: No aplica | H4: No aplica | I4: No aplica | J4: No aplica | K4: No aplica | L4: No aplica | M4: Se muestra el nombre completo del cliente, no una combinación única, únicamente para lectura humana en el muestreo | N4: No | O4: No aplica | P4: No aplica | Q4: No aplica | R4: No aplica | S4: No | T4: UUID vacio | U4: No
A5: ='M-Cita'!C3 -> agenda | B5: ='M-Cita'!C2 -> Referencia en cual agenda va a estar esta cita | C5: No | D5: Agenda | E5: Si | F5: No aplica | G5: No aplica | H5: No aplica | I5: No aplica | J5: No aplica | K5: No aplica | L5: No aplica | M5: Aplican las reglas del objeto referenciado | N5: No | O5: No aplica | P5: No aplica | Q5: No aplica | R5: No aplica | S5: No | T5: UUID vacio | U5: No
A6: ='M-Cita'!D3 -> regla | B6: ='M-Cita'!D2 -> Hace referencia a la Regla vigente de la barbería en el momento de agendar; de ahí salen las tolerancias, el monto de multa fija y el porcentaje de descuento que aplican a esta cita | C6: No | D6: Regla | E6: Si | F6: No aplica | G6: No aplica | H6: No aplica | I6: No aplica | J6: No aplica | K6: No aplica | L6: No aplica | M6: Congela la Regla vigente al momento de agendar | N6: No | O6: No aplica | P6: No aplica | Q6: No aplica | R6: No aplica | S6: No | T6: UUID vacio | U6: No
A7: ='M-Cita'!E3 -> estado | B7: ='M-Cita'!E2 -> Representa en qué estado se encuentra esta cita puntual: agendada, finalizada, cancelada, con tardanza del cliente o del barbero, o inasistencia | C7: No | D7: Estado | E7: Si | F7: No aplica | G7: No aplica | H7: No aplica | I7: No aplica | J7: No aplica | K7: No aplica | L7: No aplica | M7: Aplican las reglas del objeto referenciado | N7: No | O7: No aplica | P7: No aplica | Q7: No aplica | R7: No aplica | S7: No | T7: UUID vacio | U7: No
A8: ='M-Cita'!F3 -> horaInicio | B8: ='M-Cita'!F2 -> Representa la hora en la que se va a realizar la cita al cliente | C8: No | D8: Hora | E8: No | F8: No aplica | G8: No aplica | H8: No aplica | I8: No aplica | J8: No aplica | K8: No aplica | L8: No aplica | M8: Debe de estar dentro del horario de trabajo del barbero | N8: No | O8: No aplica | P8: No aplica | Q8: No aplica | R8: No aplica | S8: No | T8: 00:00 | U8: No
A9: ='M-Cita'!G3 -> horaFinEstimada | B9: ='M-Cita'!G2 -> Representa la hora en la que se espera que termine la cita, sumando horaInicio más la duración total de los servicios pedidos. Es un dato calculado | C9: No | D9: Hora | E9: Si | F9: No aplica | G9: No aplica | H9: No aplica | I9: No aplica | J9: No aplica | K9: No aplica | L9: No aplica | M9: horaInicio + duracion (en minutos) y debe de estar dentro del horario de trabajo del barbero | N9: Si | O9: No aplica | P9: No aplica | Q9: No aplica | R9: No aplica | S9: No | T9: 00:00 | U9: No
A10: ='M-Cita'!H3 -> horaLlegadaCliente | B10: ='M-Cita'!H2 -> Representa la hora real en la que el cliente llegó a la barbería para esta cita. Su valor por defecto es 00:00 y es permitido: significa que el cliente aún no ha llegado | C10: No | D10: Hora | E10: No | F10: No aplica | G10: No aplica | H10: No aplica | I10: No aplica | J10: No aplica | K10: No aplica | L10: No aplica | M10: No aplica | N10: No | O10: No aplica | P10: No aplica | Q10: No aplica | R10: No aplica | S10: No | T10: 00:00 | U10: No
A11: ='M-Cita'!I3 -> horaDelBarberoPreparado | B11: ='M-Cita'!I2 -> Representa la hora real en la que el barbero quedó listo y disponible para empezar a atender esta cita. Su valor por defecto es 00:00 y es permitido: significa que el barbero aún no se ha preparado | C11: No | D11: Hora | E11: No | F11: No aplica | G11: No aplica | H11: No aplica | I11: No aplica | J11: No aplica | K11: No aplica | L11: No aplica | M11: No aplica | N11: No | O11: No aplica | P11: No aplica | Q11: No aplica | R11: No aplica | S11: No | T11: 00:00 | U11: No
A12: ='M-Cita'!J3 -> horaInicioAtencion | B12: ='M-Cita'!J2 -> Representa la hora real en la que el barbero empezó a atender al cliente. Su valor por defecto es 00:00 y es permitido: significa que la atención aún no ha comenzado | C12: No | D12: Hora | E12: No | F12: No aplica | G12: No aplica | H12: No aplica | I12: No aplica | J12: No aplica | K12: No aplica | L12: No aplica | M12: No aplica | N12: No | O12: No aplica | P12: No aplica | Q12: No aplica | R12: No aplica | S12: No | T12: 00:00 | U12: No
A13: ='M-Cita'!K3 -> horaFinAtencion | B13: ='M-Cita'!K2 -> Representa la hora real en la que el barbero terminó de atender al cliente. Su valor por defecto es 00:00 y es permitido: significa que la atención aún no ha terminado | C13: No | D13: Hora | E13: No | F13: No aplica | G13: No aplica | H13: No aplica | I13: No aplica | J13: No aplica | K13: No aplica | L13: No aplica | M13: No aplica | N13: No | O13: No aplica | P13: No aplica | Q13: No aplica | R13: No aplica | S13: No | T13: 00:00 | U13: No
A14: ='M-Cita'!L3 -> duracionHoras | B14: ='M-Cita'!L2 -> Representa la cantidad total de horas que va a durar la cita, sumando la duración de cada servicio pedido más el tiempo extra de cada uno. Es un dato calculado | C14: No | D14: Entero | E14: No | F14: No aplica | G14: No aplica | H14: No aplica | I14: No aplica | J14: 0 | K14: 3 | L14: No aplica | M14: Resulta de dividir entre 60 la suma de duracionServicio + tiempoExtra de todos los CitaServicio de esta cita (parte en horas) | N14: Si | O14: No aplica | P14: No aplica | Q14: No aplica | R14: No aplica | S14: No | T14: 0 | U14: No
A15: ='M-Cita'!M3 -> duracionMinutos | B15: ='M-Cita'!M2 -> Representa la cantidad total de minutos que va a durar la cita, sumando la duración de cada servicio pedido más el tiempo extra de cada uno. Es un dato calculado | C15: No | D15: Entero | E15: No | F15: No aplica | G15: No aplica | H15: No aplica | I15: No aplica | J15: 0 | K15: 59 | L15: No aplica | M15: Resto en minutos de dividir entre 60 la suma de duracionServicio + tiempoExtra de todos los CitaServicio de esta cita (parte en minutos) | N15: Si | O15: No aplica | P15: No aplica | Q15: No aplica | R15: No aplica | S15: No | T15: 0 | U15: No
A16: ='M-Cita'!N3 -> minutosTardanzaCliente | B16: ='M-Cita'!N2 -> Representa cuántos minutos después de horaInicio llegó el cliente. Si llegó a tiempo o aún no ha llegado su valor es 0. Es un dato calculado | C16: No | D16: Entero | E16: No | F16: No aplica | G16: No aplica | H16: No aplica | I16: No aplica | J16: 0 | K16: 300 | L16: No aplica | M16: Si horaLlegadaCliente es 00:00 (no ha llegado), 0. Si no, MAX(0, horaLlegadaCliente - horaInicio) en minutos | N16: Si | O16: No aplica | P16: No aplica | Q16: No aplica | R16: No aplica | S16: No | T16: 0 | U16: No
A17: ='M-Cita'!O3 -> minutosDemoraBarbero | B17: ='M-Cita'!O2 -> Representa cuántos minutos después de la llegada del cliente empezó el barbero a atenderlo. Si no hubo demora su valor es 0. Es un dato calculado | C17: No | D17: Entero | E17: No | F17: No aplica | G17: No aplica | H17: No aplica | I17: No aplica | J17: 0 | K17: 300 | L17: No aplica | M17: Si horaInicioAtencion es 00:00 (no ha empezado), 0. Si no, MAX(0, horaInicioAtencion - MAX(horaLlegadaCliente, horaInicio)) en minutos | N17: Si | O17: No aplica | P17: No aplica | Q17: No aplica | R17: No aplica | S17: No | T17: 0 | U17: No
A18: ='M-Cita'!P3 -> porcentajeDescuentoAplicado | B18: ='M-Cita'!P2 -> Representa el porcentaje de descuento aplicado al cliente en esta cita, cuando minutosDemoraBarbero supera la toleranciaTardanzaBarbero de Regla. Su valor por defecto es 0 y es permitido. Es un dato auto generado: copia de Regla.porcentajeDescuentoCita | C18: No | D18: Entero | E18: No | F18: No aplica | G18: No aplica | H18: No aplica | I18: No aplica | J18: 0 | K18: 100 | L18: No aplica | M18: Copia de Regla.porcentajeDescuentoCita, únicamente cuando minutosDemoraBarbero supera Regla.toleranciaTardanzaBarbero | N18: No | O18: No aplica | P18: No aplica | Q18: No aplica | R18: No aplica | S18: No | T18: 0 | U18: Si
A19: ='M-Cita'!Q3 -> precioFinal | B19: ='M-Cita'!Q2 -> Representa cuánto debe pagar el cliente por los servicios de esta cita: la suma de los precios de sus CitaServicio, menos el descuento si aplicó. Es un dato calculado | C19: No | D19: Entero | E19: Si | F19: No aplica | G19: No aplica | H19: No aplica | I19: No aplica | J19: 0 | K19: 3000000 | L19: No aplica | M19: Suma de precioServicio de todos los CitaServicio de esta cita, menos el descuento (precioTotal * porcentajeDescuentoAplicado / 100) | N19: Si | O19: No aplica | P19: No aplica | Q19: No aplica | R19: No aplica | S19: No | T19: 0 | U19: No
A21: Nombre combinación única | B21: Descripción | C21: Atributos involucrados
A22: ='M-Cita'!R3 -> Combinación única | B22: ='M-Cita'!R2 -> Combinación única que indica que una misma agenda no puede tener dos citas que empiecen a la misma hora | C22: =A5 -> agenda
C23: =A8 -> horaInicio

Sheet P-Cita
A1: << Ir al modelo de dominio | B1: << Ir al listado de objetos de dominio | C1: << Ir a la caracterización del objeto de dominio | D1: Ir al muestreo de datos del objeto de dominio >> | E1: Ir al event storming del objeto de dominio >>
A2: Objeto de Dominio: | B2: ='Objetos de Dominio'!A16 -> Cita
A3: Descripción: | B3: ='Objetos de Dominio'!B16 -> Representa la reserva de un cliente con un barbero para un día y hora puntual, con los servicios pedidos, su estado, y lo que realmente ocurrió (llegada, atención, tardanzas)
A4: Numero politica | B4: Descripcion politica | D4: Objeto responsable | E4: Regla responsable
A6: P-CIT-0001 | B6: Asegurar que los datos requeridos (hora de inicio, servicios solicitados) sean válidos en tipo de dato, obligatoriedad, formato y rango | D6: Cita
A7: P-CIT-0002 | B7: Asegurar que el cliente no esté vetado antes de permitirle agendar | D7: Cliente
A8: P-CIT-0003 | B8: Asegurar que la agenda tenga disponibilidad y que la hora solicitada quepa dentro del horario del barbero sin solaparse con otra cita o bloqueo | D8: Agenda
A9: P-CIT-0004 | B9: Asegurar que cada servicio solicitado esté habilitado para ese barbero | D9: BarberoServicio
A10: P-CIT-0005 | B10: Asegurar que la cita se solicite con al menos la anticipación mínima definida por el barbero | D10: Barbero
A11: P-CIT-0006 | B11: Congelar la Regla vigente en el momento de agendar la cita | D11: Regla
A12: P-CIT-0007 | B12: Al finalizar la atención, calcular minutosTardanzaCliente, minutosDemoraBarbero, duración y precioFinal a partir de los tiempos realmente registrados | D12: CitaServicio
A13: P-CIT-0008 | B13: Si la inasistencia es del cliente, generar una Multa por el valor total de los servicios pedidos | D13: Multa
A14: P-CIT-0009 | B14: Si la demora del barbero supera la tolerancia definida en la Regla, aplicar el descuento correspondiente a la próxima cita del cliente | D14: Regla

Sheet E-Cita
A1: << Ir al modelo de dominio | C1: << Ir al listado de objetos de dominio | F1: << Ir a la caracterización del objeto de dominio | J1: Ir al muestreo de datos del objeto de dominio >>
A2: Objeto de Dominio: | B2: ='Objetos de Dominio'!A16 -> Cita
A3: Descripción: | B3: ='Objetos de Dominio'!B16 -> Representa la reserva de un cliente con un barbero para un día y hora puntual, con los servicios pedidos, su estado, y lo que realmente ocurrió (llegada, atención, tardanzas)
A4: Actor | B4: Action/Command | D4: Entity/Aggregate/Object domain | E4: Read Model | G4: Business Rule/Policy | I4: External System | J4: Domain Event | K4: Hotspot/questions/Risk
A5: Actor | B5: Acción | C5: Descripción | D5: Objeto de dominio | E5: Información externa | G5: Políticas | I5: Sistema Externo | J5: Evento | K5: Aspectos por solucionar
E6: Información | F6: Descripción | G6: Número | H6: Descripción
A7: Cliente | B7: Pedir cita | C7: Comando que permite a un cliente solicitar una cita con un barbero, en una fecha y hora puntual, con uno o más servicios | D7: =$B$2 -> Cita | E7: Disponibilidad de la agenda y servicios habilitados del barbero | F7: Se consulta la agenda del barbero y los servicios que tiene habilitados, con su duración, para validar y armar la cita | G7: ='P-Cita'!A6 -> P-CIT-0001 | H7: aquí | J7: Cita agendada | K7: ¿Cuántos servicios como máximo puede pedir un cliente en una misma cita? Aún no hay un límite definido, lo que deja sin techo real la duración total de una cita
G8: ='P-Cita'!A7 -> P-CIT-0002 | H8: aquí
G9: ='P-Cita'!A8 -> P-CIT-0003 | H9: aquí
G10: ='P-Cita'!A9 -> P-CIT-0004 | H10: aquí
G11: ='P-Cita'!A10 -> P-CIT-0005 | H11: aquí
G12: ='P-Cita'!A11 -> P-CIT-0006 | H12: aquí
A13: Cliente | B13: Reprogramar la cita | C13: Permite a un cliente cambiar la fecha, hora o barbero de una cita que aún no ha ocurrido | D13: =$B$2 -> Cita | G13: ='P-Cita'!A8 -> P-CIT-0003 | H13: aquí | J13: Cita reprogramada
G14: ='P-Cita'!A10 -> P-CIT-0005 | H14: aquí
A15: Cliente | B15: Cancelar la cita por decisión del cliente | C15: Permite a un cliente cancelar una cita antes de que ocurra | D15: =$B$2 -> Cita | J15: Cita cancelada por el cliente | K15: No está resuelto si cancelar por decisión del cliente debe generar una Multa cuando se hace fuera de un tiempo mínimo de anticipación
A16: Barbero | B16: Cancelar la cita por decisión del barbero | C16: Permite a un barbero cancelar una cita antes de que ocurra | D16: =$B$2 -> Cita | J16: Cita cancelada por el barbero
A17: Barbero | B17: Registrar llegada del cliente | C17: Permite al barbero marcar la hora real en que el cliente llegó a su cita | D17: =$B$2 -> Cita | J17: Llegada de cliente registrada
A18: Barbero | B18: Iniciar la atención del cliente | C18: Permite al barbero marcar el inicio real de la atención de la cita | D18: =$B$2 -> Cita | J18: Atención de cliente iniciada
A19: Barbero | B19: Finalizar la atención del cliente | C19: Permite al barbero marcar el fin real de la atención y cerrar la cita | D19: =$B$2 -> Cita | G19: ='P-Cita'!A12 -> P-CIT-0007 | H19: aquí | J19: Atención de cliente finalizada
A20: Barbero | B20: Registrar la inasistencia del cliente | C20: Permite al barbero indicar que el cliente nunca llegó a la cita | D20: =$B$2 -> Cita | G20: ='P-Cita'!A13 -> P-CIT-0008 | H20: aquí | J20: Inasistencia de cliente registrada
A21: Sistema | B21: Registrar la inasistencia del barbero | C21: Marca automáticamente que el barbero nunca inició la atención de la cita | D21: =$B$2 -> Cita | G21: ='P-Cita'!A14 -> P-CIT-0009 | H21: aquí | J21: Inasistencia de barbero registrada

Sheet M-Cita
A1: <<<< Ir al modulo de dominio | B1: <<<< Ir a objetos de dominio
A2: Representa un identificador que hará unico cada objeto de dominio de este tipo, no se puede repetir | B2: Representa a cuál cliente le pertenece esta cita | C2: Referencia en cual agenda va a estar esta cita | D2: Hace referencia a la Regla vigente de la barbería en el momento de agendar; de ahí salen las tolerancias, el monto de multa fija y el porcentaje de descuento que aplican a esta cita | E2: Representa en qué estado se encuentra esta cita puntual: agendada, finalizada, cancelada, con tardanza del cliente o del barbero, o inasistencia | F2: Representa la hora en la que se va a realizar la cita al cliente | G2: Representa la hora en la que se espera que termine la cita, sumando horaInicio más la duración total de los servicios pedidos. Es un dato calculado | H2: Representa la hora real en la que el cliente llegó a la barbería para esta cita. Su valor por defecto es 00:00 y es permitido: significa que el cliente aún no ha llegado | I2: Representa la hora real en la que el barbero quedó listo y disponible para empezar a atender esta cita. Su valor por defecto es 00:00 y es permitido: significa que el barbero aún no se ha preparado | J2: Representa la hora real en la que el barbero empezó a atender al cliente. Su valor por defecto es 00:00 y es permitido: significa que la atención aún no ha comenzado | K2: Representa la hora real en la que el barbero terminó de atender al cliente. Su valor por defecto es 00:00 y es permitido: significa que la atención aún no ha terminado | L2: Representa la cantidad total de horas que va a durar la cita, sumando la duración de cada servicio pedido más el tiempo extra de cada uno. Es un dato calculado | M2: Representa la cantidad total de minutos que va a durar la cita, sumando la duración de cada servicio pedido más el tiempo extra de cada uno. Es un dato calculado | N2: Representa cuántos minutos después de horaInicio llegó el cliente. Si llegó a tiempo o aún no ha llegado su valor es 0. Es un dato calculado | O2: Representa cuántos minutos después de la llegada del cliente empezó el barbero a atenderlo. Si no hubo demora su valor es 0. Es un dato calculado | P2: Representa el porcentaje de descuento aplicado al cliente en esta cita, cuando minutosDemoraBarbero supera la toleranciaTardanzaBarbero de Regla. Su valor por defecto es 0 y es permitido. Es un dato auto generado: copia de Regla.porcentajeDescuentoCita | Q2: Representa cuánto debe pagar el cliente por los servicios de esta cita: la suma de los precios de sus CitaServicio, menos el descuento si aplicó. Es un dato calculado | R2: Combinación única que indica que una misma agenda no puede tener dos citas que empiecen a la misma hora
A3: id | B3: cliente | C3: agenda | D3: regla | E3: estado | F3: horaInicio | G3: horaFinEstimada | H3: horaLlegadaCliente | I3: horaDelBarberoPreparado | J3: horaInicioAtencion | K3: horaFinAtencion | L3: duracionHoras | M3: duracionMinutos | N3: minutosTardanzaCliente | O3: minutosDemoraBarbero | P3: porcentajeDescuentoAplicado | Q3: precioFinal | R3: Combinación única
A4: 1 | B4: ='M-Cliente'!L4 -> +57-3234528921 | C4: ='M-Agenda'!D4 -> +57-3245627890-Lunes-09:00-19:00-12/11/2023-1/01/1000-10:00-16:00-31/08/2026 | D4: ='M-Regla'!A4 -> 1 | E4: ='M-Estado'!D4 -> Agendada | F4: 0.41666667 | G4: =F4+TIME(L4,M4,0) -> 0.45833333 | H4: 0 | I4: 0 | J4: 0 | K4: 0 | L4: =INT((SUMIF('M-CitaServicio'!$B$4:$B$14,R4,'M-CitaServicio'!$F$4:$F$14)+SUMIF('M-CitaServicio'!$B$4:$B$14,R4,'M-CitaServicio'!$G$4:$G$14))/60) -> 1 | M4: =MOD((SUMIF('M-CitaServicio'!$B$4:$B$14,R4,'M-CitaServicio'!$F$4:$F$14)+SUMIF('M-CitaServicio'!$B$4:$B$14,R4,'M-CitaServicio'!$G$4:$G$14)),60) -> 0 | N4: =IF(H4=TIME(0,0,0),0,ROUND(MAX(0,(H4-F4)*1440),0)) -> 0 | O4: =IF(J4=TIME(0,0,0),0,ROUND(MAX(0,(J4-MAX(H4,F4))*1440),0)) -> 0 | P4: 0 | Q4: =SUMIF('M-CitaServicio'!$B$4:$B$14,R4,'M-CitaServicio'!$D$4:$D$14)*(1-P4/100) -> 22000 | R4: =_xlfn.CONCAT(C4,"-",TEXT(F4,"hh:mm")) -> +57-3245627890-Lunes-09:00-19:00-12/11/2023-1/01/1000-10:00-16:00-31/08/2026-10:00
A5: 2 | B5: ='M-Cliente'!L5 -> +57-3161657782 | C5: ='M-Agenda'!D5 -> +57-3124518923-Martes-09:00-19:00-12/11/2023-1/01/1000-09:00-15:00-10/03/2026 | D5: ='M-Regla'!A4 -> 1 | E5: ='M-Estado'!D5 -> Finalizada | F5: 0.39583333 | G5: =F5+TIME(L5,M5,0) -> 0.40625 | H5: 0.39444444 | I5: 0.39236111 | J5: 0.39583333 | K5: 0.40625 | L5: =INT((SUMIF('M-CitaServicio'!$B$4:$B$14,R5,'M-CitaServicio'!$F$4:$F$14)+SUMIF('M-CitaServicio'!$B$4:$B$14,R5,'M-CitaServicio'!$G$4:$G$14))/60) -> 0 | M5: =MOD((SUMIF('M-CitaServicio'!$B$4:$B$14,R5,'M-CitaServicio'!$F$4:$F$14)+SUMIF('M-CitaServicio'!$B$4:$B$14,R5,'M-CitaServicio'!$G$4:$G$14)),60) -> 15 | N5: =IF(H5=TIME(0,0,0),0,ROUND(MAX(0,(H5-F5)*1440),0)) -> 0 | O5: =IF(J5=TIME(0,0,0),0,ROUND(MAX(0,(J5-MAX(H5,F5))*1440),0)) -> 0 | P5: 0 | Q5: =SUMIF('M-CitaServicio'!$B$4:$B$14,R5,'M-CitaServicio'!$D$4:$D$14)*(1-P5/100) -> 12000 | R5: =_xlfn.CONCAT(C5,"-",TEXT(F5,"hh:mm")) -> +57-3124518923-Martes-09:00-19:00-12/11/2023-1/01/1000-09:00-15:00-10/03/2026-09:30
A6: 3 | B6: ='M-Cliente'!L6 -> +57-3119884321 | C6: ='M-Agenda'!D6 -> +57-3214533321-Jueves-09:00-19:00-12/11/2023-1/01/1000-13:00-19:00-14/05/2026 | D6: ='M-Regla'!A4 -> 1 | E6: ='M-Estado'!D8 -> El cliente se demoro | F6: 0.54166667 | G6: =F6+TIME(L6,M6,0) -> 0.55555556 | H6: 0.55208333 | I6: 0.54305556 | J6: 0.55208333 | K6: 0.56597222 | L6: =INT((SUMIF('M-CitaServicio'!$B$4:$B$14,R6,'M-CitaServicio'!$F$4:$F$14)+SUMIF('M-CitaServicio'!$B$4:$B$14,R6,'M-CitaServicio'!$G$4:$G$14))/60) -> 0 | M6: =MOD((SUMIF('M-CitaServicio'!$B$4:$B$14,R6,'M-CitaServicio'!$F$4:$F$14)+SUMIF('M-CitaServicio'!$B$4:$B$14,R6,'M-CitaServicio'!$G$4:$G$14)),60) -> 20 | N6: =IF(H6=TIME(0,0,0),0,ROUND(MAX(0,(H6-F6)*1440),0)) -> 15 | O6: =IF(J6=TIME(0,0,0),0,ROUND(MAX(0,(J6-MAX(H6,F6))*1440),0)) -> 0 | P6: 0 | Q6: =SUMIF('M-CitaServicio'!$B$4:$B$14,R6,'M-CitaServicio'!$D$4:$D$14)*(1-P6/100) -> 15000 | R6: =_xlfn.CONCAT(C6,"-",TEXT(F6,"hh:mm")) -> +57-3214533321-Jueves-09:00-19:00-12/11/2023-1/01/1000-13:00-19:00-14/05/2026-13:00
A7: 4 | B7: ='M-Cliente'!L7 -> +58-4127359182 | C7: ='M-Agenda'!D8 -> +91-9876543210-Sábado-08:00-21:00-12/12/2024-1/01/1000-08:00-14:00-22/11/2025 | D7: ='M-Regla'!A4 -> 1 | E7: ='M-Estado'!D10 -> Inasistencia del cliente | F7: 0.54166667 | G7: =F7+TIME(L7,M7,0) -> 0.57638889 | H7: 0 | I7: 0.52777778 | J7: 0 | K7: 0 | L7: =INT((SUMIF('M-CitaServicio'!$B$4:$B$14,R7,'M-CitaServicio'!$F$4:$F$14)+SUMIF('M-CitaServicio'!$B$4:$B$14,R7,'M-CitaServicio'!$G$4:$G$14))/60) -> 0 | M7: =MOD((SUMIF('M-CitaServicio'!$B$4:$B$14,R7,'M-CitaServicio'!$F$4:$F$14)+SUMIF('M-CitaServicio'!$B$4:$B$14,R7,'M-CitaServicio'!$G$4:$G$14)),60) -> 50 | N7: =IF(H7=TIME(0,0,0),0,ROUND(MAX(0,(H7-F7)*1440),0)) -> 0 | O7: =IF(J7=TIME(0,0,0),0,ROUND(MAX(0,(J7-MAX(H7,F7))*1440),0)) -> 0 | P7: 0 | Q7: =SUMIF('M-CitaServicio'!$B$4:$B$14,R7,'M-CitaServicio'!$D$4:$D$14)*(1-P7/100) -> 35000 | R7: =_xlfn.CONCAT(C7,"-",TEXT(F7,"hh:mm")) -> +91-9876543210-Sábado-08:00-21:00-12/12/2024-1/01/1000-08:00-14:00-22/11/2025-13:00
A8: 5 | B8: ='M-Cliente'!L7 -> +58-4127359182 | C8: ='M-Agenda'!D9 -> +57-3214533321-Jueves-09:00-19:00-12/11/2023-1/01/1000-13:00-19:00-06/08/2026 | D8: ='M-Regla'!A4 -> 1 | E8: ='M-Estado'!D9 -> El barbero se demoro | F8: 0.75 | G8: =F8+TIME(L8,M8,0) -> 0.76388889 | H8: 0.74861111 | I8: 0.76388889 | J8: 0.76388889 | K8: 0.77777778 | L8: =INT((SUMIF('M-CitaServicio'!$B$4:$B$14,R8,'M-CitaServicio'!$F$4:$F$14)+SUMIF('M-CitaServicio'!$B$4:$B$14,R8,'M-CitaServicio'!$G$4:$G$14))/60) -> 0 | M8: =MOD((SUMIF('M-CitaServicio'!$B$4:$B$14,R8,'M-CitaServicio'!$F$4:$F$14)+SUMIF('M-CitaServicio'!$B$4:$B$14,R8,'M-CitaServicio'!$G$4:$G$14)),60) -> 20 | N8: =IF(H8=TIME(0,0,0),0,ROUND(MAX(0,(H8-F8)*1440),0)) -> 0 | O8: =IF(J8=TIME(0,0,0),0,ROUND(MAX(0,(J8-MAX(H8,F8))*1440),0)) -> 20 | P8: 10 | Q8: =SUMIF('M-CitaServicio'!$B$4:$B$14,R8,'M-CitaServicio'!$D$4:$D$14)*(1-P8/100) -> 10800 | R8: =_xlfn.CONCAT(C8,"-",TEXT(F8,"hh:mm")) -> +57-3214533321-Jueves-09:00-19:00-12/11/2023-1/01/1000-13:00-19:00-06/08/2026-18:00
A9: 6 | B9: ='M-Cliente'!L4 -> +57-3234528921 | C9: ='M-Agenda'!D7 -> +91-9876543210-Festivo-10:00-15:00-12/12/2024-1/01/1000-12:00-15:00-20/02/2026 | D9: ='M-Regla'!A4 -> 1 | E9: ='M-Estado'!D5 -> Finalizada | F9: 0.58333333 | G9: =F9+TIME(L9,M9,0) -> 0.61805556 | H9: 0.58194444 | I9: 0.58333333 | J9: 0.58333333 | K9: 0.61805556 | L9: =INT((SUMIF('M-CitaServicio'!$B$4:$B$14,R9,'M-CitaServicio'!$F$4:$F$14)+SUMIF('M-CitaServicio'!$B$4:$B$14,R9,'M-CitaServicio'!$G$4:$G$14))/60) -> 0 | M9: =MOD((SUMIF('M-CitaServicio'!$B$4:$B$14,R9,'M-CitaServicio'!$F$4:$F$14)+SUMIF('M-CitaServicio'!$B$4:$B$14,R9,'M-CitaServicio'!$G$4:$G$14)),60) -> 50 | N9: =IF(H9=TIME(0,0,0),0,ROUND(MAX(0,(H9-F9)*1440),0)) -> 0 | O9: =IF(J9=TIME(0,0,0),0,ROUND(MAX(0,(J9-MAX(H9,F9))*1440),0)) -> 0 | P9: 0 | Q9: =SUMIF('M-CitaServicio'!$B$4:$B$14,R9,'M-CitaServicio'!$D$4:$D$14)*(1-P9/100) -> 35000 | R9: =_xlfn.CONCAT(C9,"-",TEXT(F9,"hh:mm")) -> +91-9876543210-Festivo-10:00-15:00-12/12/2024-1/01/1000-12:00-15:00-20/02/2026-14:00
A10: 7 | B10: ='M-Cliente'!L8 -> +57-3005544332 | C10: ='M-Agenda'!D10 -> +57-3245627890-Lunes-09:00-19:00-12/11/2023-1/01/1000-10:00-16:00-01/06/2026 | D10: ='M-Regla'!A4 -> 1 | E10: ='M-Estado'!D10 -> Inasistencia del cliente | F10: 0.41666667 | G10: =F10+TIME(L10,M10,0) -> 0.45833333 | H10: 0 | I10: 0 | J10: 0 | K10: 0 | L10: =INT((SUMIF('M-CitaServicio'!$B$4:$B$14,R10,'M-CitaServicio'!$F$4:$F$14)+SUMIF('M-CitaServicio'!$B$4:$B$14,R10,'M-CitaServicio'!$G$4:$G$14))/60) -> 1 | M10: =MOD((SUMIF('M-CitaServicio'!$B$4:$B$14,R10,'M-CitaServicio'!$F$4:$F$14)+SUMIF('M-CitaServicio'!$B$4:$B$14,R10,'M-CitaServicio'!$G$4:$G$14)),60) -> 0 | N10: =IF(H10=TIME(0,0,0),0,ROUND(MAX(0,(H10-F10)*1440),0)) -> 0 | O10: =IF(J10=TIME(0,0,0),0,ROUND(MAX(0,(J10-MAX(H10,F10))*1440),0)) -> 0 | P10: 0 | Q10: =SUMIF('M-CitaServicio'!$B$4:$B$14,R10,'M-CitaServicio'!$D$4:$D$14)*(1-P10/100) -> 22000 | R10: =_xlfn.CONCAT(C10,"-",TEXT(F10,"hh:mm")) -> +57-3245627890-Lunes-09:00-19:00-12/11/2023-1/01/1000-10:00-16:00-01/06/2026-10:00
A11: 8 | B11: ='M-Cliente'!L8 -> +57-3005544332 | C11: ='M-Agenda'!D11 -> +57-3124518923-Martes-09:00-19:00-12/11/2023-1/01/1000-09:00-15:00-16/06/2026 | D11: ='M-Regla'!A4 -> 1 | E11: ='M-Estado'!D10 -> Inasistencia del cliente | F11: 0.375 | G11: =F11+TIME(L11,M11,0) -> 0.38541667 | H11: 0 | I11: 0 | J11: 0 | K11: 0 | L11: =INT((SUMIF('M-CitaServicio'!$B$4:$B$14,R11,'M-CitaServicio'!$F$4:$F$14)+SUMIF('M-CitaServicio'!$B$4:$B$14,R11,'M-CitaServicio'!$G$4:$G$14))/60) -> 0 | M11: =MOD((SUMIF('M-CitaServicio'!$B$4:$B$14,R11,'M-CitaServicio'!$F$4:$F$14)+SUMIF('M-CitaServicio'!$B$4:$B$14,R11,'M-CitaServicio'!$G$4:$G$14)),60) -> 15 | N11: =IF(H11=TIME(0,0,0),0,ROUND(MAX(0,(H11-F11)*1440),0)) -> 0 | O11: =IF(J11=TIME(0,0,0),0,ROUND(MAX(0,(J11-MAX(H11,F11))*1440),0)) -> 0 | P11: 0 | Q11: =SUMIF('M-CitaServicio'!$B$4:$B$14,R11,'M-CitaServicio'!$D$4:$D$14)*(1-P11/100) -> 12000 | R11: =_xlfn.CONCAT(C11,"-",TEXT(F11,"hh:mm")) -> +57-3124518923-Martes-09:00-19:00-12/11/2023-1/01/1000-09:00-15:00-16/06/2026-09:00
A12: 9 | B12: ='M-Cliente'!L8 -> +57-3005544332 | C12: ='M-Agenda'!D12 -> +57-3214533321-Jueves-09:00-19:00-12/11/2023-1/01/1000-13:00-19:00-02/07/2026 | D12: ='M-Regla'!A4 -> 1 | E12: ='M-Estado'!D10 -> Inasistencia del cliente | F12: 0.625 | G12: =F12+TIME(L12,M12,0) -> 0.63888889 | H12: 0 | I12: 0 | J12: 0 | K12: 0 | L12: =INT((SUMIF('M-CitaServicio'!$B$4:$B$14,R12,'M-CitaServicio'!$F$4:$F$14)+SUMIF('M-CitaServicio'!$B$4:$B$14,R12,'M-CitaServicio'!$G$4:$G$14))/60) -> 0 | M12: =MOD((SUMIF('M-CitaServicio'!$B$4:$B$14,R12,'M-CitaServicio'!$F$4:$F$14)+SUMIF('M-CitaServicio'!$B$4:$B$14,R12,'M-CitaServicio'!$G$4:$G$14)),60) -> 20 | N12: =IF(H12=TIME(0,0,0),0,ROUND(MAX(0,(H12-F12)*1440),0)) -> 0 | O12: =IF(J12=TIME(0,0,0),0,ROUND(MAX(0,(J12-MAX(H12,F12))*1440),0)) -> 0 | P12: 0 | Q12: =SUMIF('M-CitaServicio'!$B$4:$B$14,R12,'M-CitaServicio'!$D$4:$D$14)*(1-P12/100) -> 15000 | R12: =_xlfn.CONCAT(C12,"-",TEXT(F12,"hh:mm")) -> +57-3214533321-Jueves-09:00-19:00-12/11/2023-1/01/1000-13:00-19:00-02/07/2026-15:00
A13: 10 | B13: ='M-Cliente'!L5 -> +57-3161657782 | C13: ='M-Agenda'!D6 -> +57-3214533321-Jueves-09:00-19:00-12/11/2023-1/01/1000-13:00-19:00-14/05/2026 | D13: ='M-Regla'!A4 -> 1 | E13: ='M-Estado'!D5 -> Finalizada | F13: 0.5625 | G13: =F13+TIME(L13,M13,0) -> 0.59027778 | H13: 0.56111111 | I13: 0.55902778 | J13: 0.5625 | K13: 0.59027778 | L13: =INT((SUMIF('M-CitaServicio'!$B$4:$B$14,R13,'M-CitaServicio'!$F$4:$F$14)+SUMIF('M-CitaServicio'!$B$4:$B$14,R13,'M-CitaServicio'!$G$4:$G$14))/60) -> 0 | M13: =MOD((SUMIF('M-CitaServicio'!$B$4:$B$14,R13,'M-CitaServicio'!$F$4:$F$14)+SUMIF('M-CitaServicio'!$B$4:$B$14,R13,'M-CitaServicio'!$G$4:$G$14)),60) -> 40 | N13: =IF(H13=TIME(0,0,0),0,ROUND(MAX(0,(H13-F13)*1440),0)) -> 0 | O13: =IF(J13=TIME(0,0,0),0,ROUND(MAX(0,(J13-MAX(H13,F13))*1440),0)) -> 0 | P13: 0 | Q13: =SUMIF('M-CitaServicio'!$B$4:$B$14,R13,'M-CitaServicio'!$D$4:$D$14)*(1-P13/100) -> 27000 | R13: =_xlfn.CONCAT(C13,"-",TEXT(F13,"hh:mm")) -> +57-3214533321-Jueves-09:00-19:00-12/11/2023-1/01/1000-13:00-19:00-14/05/2026-13:30
B19: Corresponde a la descripcion de los atributos
B20: Corresponde al identificador unico del objeto de dominio
B21: Corresponde a referencias de objetos de dominio
B22: Corresponde a los datos de tipo alfanumerico
B23: Corresponde a los datos de tipo hora
B24: Corresponde a los datos calculados por el sistema
B25: Corresponde a la combinacion única

Sheet C-CitaServicio
A1: <<<< Ir al modulo de dominio | B1: <<<< Ir a objetos de dominio
A2: Nombre atributo | B2: Descripción atributo | C2: Identificador del objeto de dominio | D2: Tipo de dato | E2: Obligatorio | F2: Longitud mínima (si aplica) | G2: Longitud máxima (si aplica) | H2: Precisión (si aplica) | I2: Rendondeo (si aplica) | J2: Rango inicial (si aplica) | K2: Rango final (si aplica) | L2: Formato (si aplica) | M2: Reglas especiales (si aplica) | N2: Dato calculado | O2: Aplica ajuste del dato (si aplica) | P2: Carácter de ajuste (si aplica) | Q2: Quitar espacios en blanco al inicio (si aplica) | R2: Quitar espacios en blanco al fin (si aplica) | S2: Dato sensible (si aplica) | T2: Valor por defecto (si aplica) | U2: Auto generado
A3: ='M-CitaServicio'!A3 -> id | B3: ='M-CitaServicio'!A2 -> Representa un identificador que hará unico cada objeto de dominio de este tipo, no se puede repetir | C3: Si | D3: Identificador único universal | E3: Si | F3: No aplica | G3: No aplica | H3: No aplica | I3: No aplica | J3: No aplica | K3: No aplica | L3: No aplica | M3: No aplica | N3: No | O3: No | P3: No aplica | Q3: No | R3: No | S3: No | T3: UUID vacio | U3: Si
A4: ='M-CitaServicio'!B3 -> cita | B4: ='M-CitaServicio'!B2 -> Hace referencia a la cita a la que pertenece este servicio pedido | C4: No | D4: Cita | E4: Si | F4: No aplica | G4: No aplica | H4: No aplica | I4: No aplica | J4: No aplica | K4: No aplica | L4: No aplica | M4: Aplican las reglas del objeto referenciado | N4: No | O4: No aplica | P4: No aplica | Q4: No aplica | R4: No aplica | S4: No | T4: UUID vacio | U4: No
A5: ='M-CitaServicio'!C3 -> barberoServicio | B5: ='M-CitaServicio'!C2 -> Hace referencia a qué servicio, de qué barbero específico, se pidió en esta cita. No se referencia el Servicio directamente porque un barbero podría no ofrecerlo | C5: No | D5: BarberoServicio | E5: Si | F5: No aplica | G5: No aplica | H5: No aplica | I5: No aplica | J5: No aplica | K5: No aplica | L5: No aplica | M5: Aplican las reglas del objeto referenciado | N5: No | O5: No aplica | P5: No aplica | Q5: No aplica | R5: No aplica | S5: No | T5: UUID vacio | U5: No
A6: ='M-CitaServicio'!D3 -> precioServicio | B6: ='M-CitaServicio'!D2 -> Representa el precio que tenía el servicio en el momento en que se agendó esta cita. Es un dato auto generado: copia de Servicio.precio, para que cambios futuros en el precio del catálogo no alteren una cita ya registrada | C6: No | D6: Entero | E6: Si | F6: No aplica | G6: No aplica | H6: No aplica | I6: No aplica | J6: 0 | K6: 2000000 | L6: No aplica | M6: Copia de Servicio.precio en el momento de agendar la cita | N6: No | O6: No aplica | P6: No aplica | Q6: No aplica | R6: No aplica | S6: No | T6: 0 | U6: Si
A7: ='M-CitaServicio'!E3 -> duracionEnHorasElServicio | B7: ='M-CitaServicio'!E2 -> Representa la duración en horas que tenía el servicio para ese barbero en el momento en que se agendó esta cita. Es un dato auto generado: copia de BarberoServicio.duracionServicio | C7: No | D7: Entero | E7: Si | F7: No aplica | G7: No aplica | H7: No aplica | I7: No aplica | J7: 0 | K7: 3 | L7: No aplica | M7: Copia de BarberoServicio.duracionEnHoras en el momento de agendar la cita | N7: No | O7: No aplica | P7: No aplica | Q7: No aplica | R7: No aplica | S7: No | T7: 0 | U7: Si
A8: ='M-CitaServicio'!F3 -> duracionEnMinutosElServicio | B8: ='M-CitaServicio'!F2 -> Representa la duración en minutos que tenía el servicio para ese barbero en el momento en que se agendó esta cita. Es un dato auto generado: copia de BarberoServicio.duracionServicio | C8: No | D8: Entero | E8: Si | F8: No aplica | G8: No aplica | H8: No aplica | I8: No aplica | J8: 0 | K8: 59 | L8: No aplica | M8: Copia de BarberoServicio.duracionServicio en el momento de agendar la cita | N8: No | O8: No aplica | P8: No aplica | Q8: No aplica | R8: No aplica | S8: No | T8: 0 | U8: Si
A9: ='M-CitaServicio'!G3 -> tiempoExtra | B9: ='M-CitaServicio'!G2 -> Representa el tiempo extra en minutos que ese barbero tenía configurado para este servicio en el momento en que se agendó la cita. Es un dato auto generado: copia de BarberoServicio.tiempoExtra, para que cambios futuros en el tiempo extra no alteren una cita ya registrada | C9: No | D9: Entero | E9: Si | F9: No aplica | G9: No aplica | H9: No aplica | I9: No aplica | J9: 0 | K9: 59 | L9: No aplica | M9: Copia de BarberoServicio.tiempoExtra en el momento de agendar la cita | N9: No | O9: No aplica | P9: No aplica | Q9: No aplica | R9: No aplica | S9: No | T9: 0 | U9: Si
A11: Nombre combinación única | B11: Descripción | C11: Atributos involucrados
A12: ='M-CitaServicio'!H3 -> Combinación única | B12: ='M-CitaServicio'!H2 -> Combinación única que indica que un mismo servicio no se puede pedir dos veces en la misma cita, es decir que CitaServicio no puede tener la misma cita y el barberoServicio | C12: =A4 -> cita
C13: =A5 -> barberoServicio

Sheet P-CitaServicio
A1: << Ir al modelo de dominio | B1: << Ir al listado de objetos de dominio | C1: << Ir a la caracterización del objeto de dominio | D1: Ir al muestreo de datos del objeto de dominio >> | E1: Ir al event storming del objeto de dominio >>
A2: Objeto de Dominio: | B2: ='Objetos de Dominio'!A17 -> CitaServicio
A3: Descripción: | B3: ='Objetos de Dominio'!B17 -> Representa cada servicio incluido dentro de una cita puntual, guardando el precio y la duración que tenía ese servicio para ese barbero en el momento exacto en que se agendó, para que cambios futuros en el catálogo no alteren citas ya registradas
A4: Numero politica | B4: Descripcion politica | D4: Objeto responsable | E4: Regla responsable
B6: No aplica: es un catálogo de solo lectura, sin comandos que impliquen políticas de negocio propias

Sheet E-CitaServicio
A1: << Ir al modelo de dominio | C1: << Ir al listado de objetos de dominio | F1: << Ir a la caracterización del objeto de dominio | J1: Ir al muestreo de datos del objeto de dominio >>
A2: Objeto de Dominio: | B2: ='Objetos de Dominio'!A17 -> CitaServicio
A3: Descripción: | B3: ='Objetos de Dominio'!B17 -> Representa cada servicio incluido dentro de una cita puntual, guardando el precio y la duración que tenía ese servicio para ese barbero en el momento exacto en que se agendó, para que cambios futuros en el catálogo no alteren citas ya registradas
A4: Actor | B4: Action/Command | D4: Entity/Aggregate/Object domain | E4: Read Model | G4: Business Rule/Policy | I4: External System | J4: Domain Event | K4: Hotspot/questions/Risk
A5: Actor | B5: Acción | C5: Descripción | D5: Objeto de dominio | E5: Información externa | G5: Políticas | I5: Sistema Externo | J5: Evento | K5: Aspectos por solucionar
E6: Información | F6: Descripción | G6: Número | H6: Descripción
A7: Barbero | B7: Consultar los servicios de una cita | C7: Permite ver qué servicios fueron pedidos dentro de una cita puntual | D7: =$B$2 -> CitaServicio | J7: Servicios de cita consultados
A8: Cliente | B8: Consultar los servicios de una cita | C8: Permite ver qué servicios fueron pedidos dentro de una cita puntual | D8: =$B$2 -> CitaServicio | J8: Servicios de cita consultados
A9: Barbero | B9: Ver precio de cada servicio | C9: Permite consultar el precio que quedó congelado para cada servicio de una cita en el momento en que se agendó | D9: =$B$2 -> CitaServicio | J9: Precio de servicio de cita consultado
A10: Cliente | B10: Ver precio de cada servicio | C10: Permite consultar el precio que quedó congelado para cada servicio de una cita en el momento en que se agendó | D10: =$B$2 -> CitaServicio | J10: Precio de servicio de cita consultado

Sheet M-CitaServicio
A1: <<<< Ir al modulo de dominio | B1: <<<< Ir a objetos de dominio
A2: Representa un identificador que hará unico cada objeto de dominio de este tipo, no se puede repetir | B2: Hace referencia a la cita a la que pertenece este servicio pedido | C2: Hace referencia a qué servicio, de qué barbero específico, se pidió en esta cita. No se referencia el Servicio directamente porque un barbero podría no ofrecerlo | D2: Representa el precio que tenía el servicio en el momento en que se agendó esta cita. Es un dato auto generado: copia de Servicio.precio, para que cambios futuros en el precio del catálogo no alteren una cita ya registrada | E2: Representa la duración en horas que tenía el servicio para ese barbero en el momento en que se agendó esta cita. Es un dato auto generado: copia de BarberoServicio.duracionServicio | F2: Representa la duración en minutos que tenía el servicio para ese barbero en el momento en que se agendó esta cita. Es un dato auto generado: copia de BarberoServicio.duracionServicio | G2: Representa el tiempo extra en minutos que ese barbero tenía configurado para este servicio en el momento en que se agendó la cita. Es un dato auto generado: copia de BarberoServicio.tiempoExtra, para que cambios futuros en el tiempo extra no alteren una cita ya registrada | H2: Combinación única que indica que un mismo servicio no se puede pedir dos veces en la misma cita, es decir que CitaServicio no puede tener la misma cita y el barberoServicio
A3: id | B3: cita | C3: barberoServicio | D3: precioServicio | E3: duracionEnHorasElServicio | F3: duracionEnMinutosElServicio | G3: tiempoExtra | H3: Combinación única
A4: 1 | B4: ='M-Cita'!R4 -> +57-3245627890-Lunes-09:00-19:00-12/11/2023-1/01/1000-10:00-16:00-31/08/2026-10:00 | C4: ='M-BarberoServicio'!H4 -> Juan García-Motilada | D4: ='M-Servicio'!D4 -> 22000 | E4: ='M-BarberoServicio'!D4 -> 0 | F4: ='M-BarberoServicio'!E4 -> 45 | G4: ='M-BarberoServicio'!F4 -> 15 | H4: =_xlfn.CONCAT(B4,"-",C4) -> +57-3245627890-Lunes-09:00-19:00-12/11/2023-1/01/1000-10:00-16:00-31/08/2026-10:00-Juan García-Motilada
A5: 2 | B5: ='M-Cita'!R5 -> +57-3124518923-Martes-09:00-19:00-12/11/2023-1/01/1000-09:00-15:00-10/03/2026-09:30 | C5: ='M-BarberoServicio'!H5 -> Juan Ortiz-Corte de barba | D5: ='M-Servicio'!D5 -> 12000 | E5: ='M-BarberoServicio'!D5 -> 0 | F5: ='M-BarberoServicio'!E5 -> 10 | G5: ='M-BarberoServicio'!F5 -> 5 | H5: =_xlfn.CONCAT(B5,"-",C5) -> +57-3124518923-Martes-09:00-19:00-12/11/2023-1/01/1000-09:00-15:00-10/03/2026-09:30-Juan Ortiz-Corte de barba
A6: 3 | B6: ='M-Cita'!R6 -> +57-3214533321-Jueves-09:00-19:00-12/11/2023-1/01/1000-13:00-19:00-14/05/2026-13:00 | C6: ='M-BarberoServicio'!H6 -> Carlos Arbeladez-Perfilada de barba | D6: ='M-Servicio'!D6 -> 15000 | E6: ='M-BarberoServicio'!D6 -> 0 | F6: ='M-BarberoServicio'!E6 -> 15 | G6: ='M-BarberoServicio'!F6 -> 5 | H6: =_xlfn.CONCAT(B6,"-",C6) -> +57-3214533321-Jueves-09:00-19:00-12/11/2023-1/01/1000-13:00-19:00-14/05/2026-13:00-Carlos Arbeladez-Perfilada de barba
A7: 4 | B7: ='M-Cita'!R7 -> +91-9876543210-Sábado-08:00-21:00-12/12/2024-1/01/1000-08:00-14:00-22/11/2025-13:00 | C7: ='M-BarberoServicio'!H7 -> Andres Ramirez-Arreglo completo de barba con toalla caliente | D7: ='M-Servicio'!D7 -> 35000 | E7: ='M-BarberoServicio'!D7 -> 0 | F7: ='M-BarberoServicio'!E7 -> 40 | G7: ='M-BarberoServicio'!F7 -> 10 | H7: =_xlfn.CONCAT(B7,"-",C7) -> +91-9876543210-Sábado-08:00-21:00-12/12/2024-1/01/1000-08:00-14:00-22/11/2025-13:00-Andres Ramirez-Arreglo completo de barba con toalla caliente
A8: 5 | B8: ='M-Cita'!R8 -> +57-3214533321-Jueves-09:00-19:00-12/11/2023-1/01/1000-13:00-19:00-06/08/2026-18:00 | C8: ='M-BarberoServicio'!H9 -> Carlos Arbeladez-Corte de barba | D8: ='M-Servicio'!D5 -> 12000 | E8: ='M-BarberoServicio'!D9 -> 0 | F8: ='M-BarberoServicio'!E9 -> 15 | G8: ='M-BarberoServicio'!F9 -> 5 | H8: =_xlfn.CONCAT(B8,"-",C8) -> +57-3214533321-Jueves-09:00-19:00-12/11/2023-1/01/1000-13:00-19:00-06/08/2026-18:00-Carlos Arbeladez-Corte de barba
A9: 6 | B9: ='M-Cita'!R9 -> +91-9876543210-Festivo-10:00-15:00-12/12/2024-1/01/1000-12:00-15:00-20/02/2026-14:00 | C9: ='M-BarberoServicio'!H7 -> Andres Ramirez-Arreglo completo de barba con toalla caliente | D9: ='M-Servicio'!D7 -> 35000 | E9: ='M-BarberoServicio'!D7 -> 0 | F9: ='M-BarberoServicio'!E7 -> 40 | G9: ='M-BarberoServicio'!F7 -> 10 | H9: =_xlfn.CONCAT(B9,"-",C9) -> +91-9876543210-Festivo-10:00-15:00-12/12/2024-1/01/1000-12:00-15:00-20/02/2026-14:00-Andres Ramirez-Arreglo completo de barba con toalla caliente
A10: 7 | B10: ='M-Cita'!R10 -> +57-3245627890-Lunes-09:00-19:00-12/11/2023-1/01/1000-10:00-16:00-01/06/2026-10:00 | C10: ='M-BarberoServicio'!H4 -> Juan García-Motilada | D10: ='M-Servicio'!D4 -> 22000 | E10: ='M-BarberoServicio'!D4 -> 0 | F10: ='M-BarberoServicio'!E4 -> 45 | G10: ='M-BarberoServicio'!F4 -> 15 | H10: =_xlfn.CONCAT(B10,"-",C10) -> +57-3245627890-Lunes-09:00-19:00-12/11/2023-1/01/1000-10:00-16:00-01/06/2026-10:00-Juan García-Motilada
A11: 8 | B11: ='M-Cita'!R11 -> +57-3124518923-Martes-09:00-19:00-12/11/2023-1/01/1000-09:00-15:00-16/06/2026-09:00 | C11: ='M-BarberoServicio'!H5 -> Juan Ortiz-Corte de barba | D11: ='M-Servicio'!D5 -> 12000 | E11: ='M-BarberoServicio'!D5 -> 0 | F11: ='M-BarberoServicio'!E5 -> 10 | G11: ='M-BarberoServicio'!F5 -> 5 | H11: =_xlfn.CONCAT(B11,"-",C11) -> +57-3124518923-Martes-09:00-19:00-12/11/2023-1/01/1000-09:00-15:00-16/06/2026-09:00-Juan Ortiz-Corte de barba
A12: 9 | B12: ='M-Cita'!R12 -> +57-3214533321-Jueves-09:00-19:00-12/11/2023-1/01/1000-13:00-19:00-02/07/2026-15:00 | C12: ='M-BarberoServicio'!H6 -> Carlos Arbeladez-Perfilada de barba | D12: ='M-Servicio'!D6 -> 15000 | E12: ='M-BarberoServicio'!D6 -> 0 | F12: ='M-BarberoServicio'!E6 -> 15 | G12: ='M-BarberoServicio'!F6 -> 5 | H12: =_xlfn.CONCAT(B12,"-",C12) -> +57-3214533321-Jueves-09:00-19:00-12/11/2023-1/01/1000-13:00-19:00-02/07/2026-15:00-Carlos Arbeladez-Perfilada de barba
A13: 10 | B13: ='M-Cita'!R13 -> +57-3214533321-Jueves-09:00-19:00-12/11/2023-1/01/1000-13:00-19:00-14/05/2026-13:30 | C13: ='M-BarberoServicio'!H6 -> Carlos Arbeladez-Perfilada de barba | D13: ='M-Servicio'!D6 -> 15000 | E13: ='M-BarberoServicio'!D6 -> 0 | F13: ='M-BarberoServicio'!E6 -> 15 | G13: ='M-BarberoServicio'!F6 -> 5 | H13: =_xlfn.CONCAT(B13,"-",C13) -> +57-3214533321-Jueves-09:00-19:00-12/11/2023-1/01/1000-13:00-19:00-14/05/2026-13:30-Carlos Arbeladez-Perfilada de barba
A14: 11 | B14: ='M-Cita'!R13 -> +57-3214533321-Jueves-09:00-19:00-12/11/2023-1/01/1000-13:00-19:00-14/05/2026-13:30 | C14: ='M-BarberoServicio'!H9 -> Carlos Arbeladez-Corte de barba | D14: ='M-Servicio'!D5 -> 12000 | E14: ='M-BarberoServicio'!D9 -> 0 | F14: ='M-BarberoServicio'!E9 -> 15 | G14: ='M-BarberoServicio'!F9 -> 5 | H14: =_xlfn.CONCAT(B14,"-",C14) -> +57-3214533321-Jueves-09:00-19:00-12/11/2023-1/01/1000-13:00-19:00-14/05/2026-13:30-Carlos Arbeladez-Corte de barba
B20: Corresponde a la descripcion de los atributos
B21: Corresponde al identificador unico del objeto de dominio
B22: Corresponde a referencias de objetos de dominio
B23: Corresponde a los datos de tipo entero
B24: Corresponde a la combinacion única

Sheet C-Multa
A1: <<<< Ir al modulo de dominio | B1: <<<< Ir a objetos de dominio
A2: Nombre atributo | B2: Descripción atributo | C2: Identificador del objeto de dominio | D2: Tipo de dato | E2: Obligatorio | F2: Longitud mínima (si aplica) | G2: Longitud máxima (si aplica) | H2: Precisión (si aplica) | I2: Rendondeo (si aplica) | J2: Rango inicial (si aplica) | K2: Rango final (si aplica) | L2: Formato (si aplica) | M2: Reglas especiales (si aplica) | N2: Dato calculado | O2: Aplica ajuste del dato (si aplica) | P2: Carácter de ajuste (si aplica) | Q2: Quitar espacios en blanco al inicio (si aplica) | R2: Quitar espacios en blanco al fin (si aplica) | S2: Dato sensible (si aplica) | T2: Valor por defecto (si aplica) | U2: Auto generado
A3: ='M-Multa'!A3 -> id | B3: ='M-Multa'!A2 -> Representa un identificador que hará unico cada objeto de dominio de este tipo, no se puede repetir | C3: Si | D3: Identificador único universal | E3: Si | F3: No aplica | G3: No aplica | H3: No aplica | I3: No aplica | J3: No aplica | K3: No aplica | L3: No aplica | M3: No aplica | N3: No | O3: No aplica | P3: No aplica | Q3: No aplica | R3: No aplica | S3: No | T3: UUID vacio | U3: Si
A4: ='M-Multa'!B3 -> cita | B4: ='M-Multa'!B2 -> Hace referencia a la cita puntual que el cliente incumplió (llegando tarde fuera de la tolerancia o no presentándose), de esa cita es de donde sale el valor de monto si fue el caso de no presentase | C4: No | D4: Cita | E4: Si | F4: No aplica | G4: No aplica | H4: No aplica | I4: No aplica | J4: No aplica | K4: No aplica | L4: No aplica | M4: Aplican las reglas del objeto referenciado | N4: No | O4: No aplica | P4: No aplica | Q4: No aplica | R4: No aplica | S4: No | T4: UUID vacio | U4: No
A5: ='M-Multa'!C3 -> tipo | B5: ='M-Multa'!C2 -> Hace referencia al tipo de multa -tardanza o inasistencia- según lo que haya ocurrido con la cita | C5: No | D5: TipoMulta | E5: Si | F5: No aplica | G5: No aplica | H5: No aplica | I5: No aplica | J5: No aplica | K5: No aplica | L5: No aplica | M5: Aplican las reglas del objeto referenciado | N5: No | O5: No aplica | P5: No aplica | Q5: No aplica | R5: No aplica | S5: No | T5: UUID vacio | U5: No
A6: ='M-Multa'!D3 -> monto | B6: ='M-Multa'!D2 -> Representa cuánto dinero en pesos colombianos debe pagar el cliente por esta multa. Es un dato auto generado: si el tipo es Tardanza copia el monto fijo de Regla.montoMultaTardanzaCliente; si el tipo es Inasistencia copia el precioFinal de la Cita incumplida | C6: No | D6: Entero | E6: Si | F6: No aplica | G6: No aplica | H6: No aplica | I6: No aplica | J6: 0 | K6: 1000000 | L6: No aplica | M6: Si tipo=Tardanza copia Regla.montoMultaTardanzaCliente; si tipo=Inasistencia copia Cita.precioFinal | N6: No | O6: No aplica | P6: No aplica | Q6: No aplica | R6: No aplica | S6: No | T6: 0 | U6: Si
A7: ='M-Multa'!E3 -> horaGeneracion | B7: ='M-Multa'!E2 -> Representa la hora en la que el sistema generó esta multa: si es por tardanza, en el momento en que el cliente llega superando la tolerancia; si es por inasistencia, en la hora estimada de finalización de la cita sin que el cliente haya llegado. El día es el mismo día de la agenda de la cita que la originó | C7: No | D7: Hora | E7: Si | F7: No aplica | G7: No aplica | H7: No aplica | I7: No aplica | J7: No aplica | K7: No aplica | L7: No aplica | M7: Si tipo=Tardanza copia Cita.horaLlegadaCliente; si tipo=Inasistencia copia Cita.horaFinEstimada | N7: No | O7: No aplica | P7: No aplica | Q7: No aplica | R7: No aplica | S7: No | T7: 00:00 | U7: Si
A8: ='M-Multa'!F3 -> fechaHoraPago | B8: ='M-Multa'!F2 -> Representa la fecha y hora en la que el cliente pagó esta multa. Su valor por defecto es 01/01/1000 00:00 y es permitido: significa que la multa sigue sin pagar | C8: No | D8: Fecha y Hora | E8: No | F8: No aplica | G8: No aplica | H8: No aplica | I8: No aplica | J8: No aplica | K8: No aplica | L8: No aplica | M8: No aplica | N8: No | O8: No aplica | P8: No aplica | Q8: No aplica | R8: No aplica | S8: No | T8: 01/01/1000 00:00 | U8: No
A9: ='M-Multa'!G3 -> pagada | B9: ='M-Multa'!G2 -> Representa si el cliente ya pagó o no esta multa, es el dato que se revisa para decidir si un cliente llega al número de multas sin pagar que activa el veto | C9: No | D9: Lógico | E9: Si | F9: No aplica | G9: No aplica | H9: No aplica | I9: No aplica | J9: No aplica | K9: No aplica | L9: No aplica | M9: No aplica | N9: No | O9: No aplica | P9: No aplica | Q9: No aplica | R9: No aplica | S9: No | T9: No | U9: No
A11: Nombre combinación única | B11: Descripción | C11: Atributos involucrados
A12: ='M-Multa'!H3 -> Combinación única | B12: ='M-Multa'!H2 -> Combinación única que indica que una misma cita no puede generar más de una multa | C12: =A4 -> cita

Sheet P-Multa
A1: << Ir al modelo de dominio | B1: << Ir al listado de objetos de dominio | C1: << Ir a la caracterización del objeto de dominio | D1: Ir al muestreo de datos del objeto de dominio >> | E1: Ir al event storming del objeto de dominio >>
A2: Objeto de Dominio: | B2: ='Objetos de Dominio'!A18 -> Multa
A3: Descripción: | B3: ='Objetos de Dominio'!B18 -> Representa la sanción económica que se le impone a un cliente por incumplir una cita, ya sea por llegar tarde fuera de tolerancia o por no presentarse, calculada a partir de la cita específica que la originó
A4: Numero politica | B4: Descripcion politica | D4: Objeto responsable | E4: Regla responsable
A6: P-MUL-0001 | B6: Congelar el motivo (tipo de multa) y el monto en el momento de generarse, copiando desde Regla o desde el precioFinal de la Cita, sin recalcular después | D6: Cita
A7: P-MUL-0002 | B7: Asegurar que la multa no esté ya pagada antes de registrar un nuevo pago | D7: Multa

Sheet E-Multa
A1: << Ir al modelo de dominio | C1: << Ir al listado de objetos de dominio | F1: << Ir a la caracterización del objeto de dominio | J1: Ir al muestreo de datos del objeto de dominio >>
A2: Objeto de Dominio: | B2: ='Objetos de Dominio'!A18 -> Multa
A3: Descripción: | B3: ='Objetos de Dominio'!B18 -> Representa la sanción económica que se le impone a un cliente por incumplir una cita, ya sea por llegar tarde fuera de tolerancia o por no presentarse, calculada a partir de la cita específica que la originó
A4: Actor | B4: Action/Command | D4: Entity/Aggregate/Object domain | E4: Read Model | G4: Business Rule/Policy | I4: External System | J4: Domain Event | K4: Hotspot/questions/Risk
A5: Actor | B5: Acción | C5: Descripción | D5: Objeto de dominio | E5: Información externa | G5: Políticas | I5: Sistema Externo | J5: Evento | K5: Aspectos por solucionar
E6: Información | F6: Descripción | G6: Número | H6: Descripción
A7: Sistema | B7: Imponer una multa al cliente | C7: Genera automáticamente una multa a un cliente cuando se registra una inasistencia o una tardanza fuera de tolerancia | D7: =$B$2 -> Multa | G7: ='P-Multa'!A6 -> P-MUL-0001 | H7: aquí | J7: Multa impuesta
A8: Cliente | B8: Ver todas mis multas | C8: Permite a un cliente consultar el historial de multas que se le han impuesto | D8: =$B$2 -> Multa | J8: Multas consultadas
A9: Barbero | B9: Registrar el pago de una multa | C9: Permite al barbero marcar que un cliente ya pagó una multa pendiente | D9: =$B$2 -> Multa | G9: ='P-Multa'!A7 -> P-MUL-0002 | H9: aquí | J9: Multa pagada

Sheet M-Multa
A1: <<<< Ir al modulo de dominio | B1: <<<< Ir a objetos de dominio
A2: Representa un identificador que hará unico cada objeto de dominio de este tipo, no se puede repetir | B2: Hace referencia a la cita puntual que el cliente incumplió (llegando tarde fuera de la tolerancia o no presentándose), de esa cita es de donde sale el valor de monto si fue el caso de no presentase | C2: Hace referencia al tipo de multa -tardanza o inasistencia- según lo que haya ocurrido con la cita | D2: Representa cuánto dinero en pesos colombianos debe pagar el cliente por esta multa. Es un dato auto generado: si el tipo es Tardanza copia el monto fijo de Regla.montoMultaTardanzaCliente; si el tipo es Inasistencia copia el precioFinal de la Cita incumplida | E2: Representa la hora en la que el sistema generó esta multa: si es por tardanza, en el momento en que el cliente llega superando la tolerancia; si es por inasistencia, en la hora estimada de finalización de la cita sin que el cliente haya llegado. El día es el mismo día de la agenda de la cita que la originó | F2: Representa la fecha y hora en la que el cliente pagó esta multa. Su valor por defecto es 01/01/1000 00:00 y es permitido: significa que la multa sigue sin pagar | G2: Representa si el cliente ya pagó o no esta multa, es el dato que se revisa para decidir si un cliente llega al número de multas sin pagar que activa el veto | H2: Combinación única que indica que una misma cita no puede generar más de una multa
A3: id | B3: cita | C3: tipo | D3: monto | E3: horaGeneracion | F3: fechaHoraPago | G3: pagada | H3: Combinación única
A4: 1 | B4: ='M-Cita'!R6 -> +57-3214533321-Jueves-09:00-19:00-12/11/2023-1/01/1000-13:00-19:00-14/05/2026-13:00 | C4: ='M-TipoMulta'!D4 -> Tardanza | D4: ='M-Regla'!C4 -> 10000 | E4: ='M-Cita'!H6 -> 0.55208333 | F4: 46233.417 | G4: si | H4: =B4 -> +57-3214533321-Jueves-09:00-19:00-12/11/2023-1/01/1000-13:00-19:00-14/05/2026-13:00
A5: 2 | B5: ='M-Cita'!R7 -> +91-9876543210-Sábado-08:00-21:00-12/12/2024-1/01/1000-08:00-14:00-22/11/2025-13:00 | C5: ='M-TipoMulta'!D5 -> Inasistencia | D5: ='M-Cita'!Q7 -> 35000 | E5: ='M-Cita'!G7 -> 0.57638889 | F5: 1/01/1000 00:00 | G5: no | H5: =B5 -> +91-9876543210-Sábado-08:00-21:00-12/12/2024-1/01/1000-08:00-14:00-22/11/2025-13:00
A6: 3 | B6: ='M-Cita'!R10 -> +57-3245627890-Lunes-09:00-19:00-12/11/2023-1/01/1000-10:00-16:00-01/06/2026-10:00 | C6: ='M-TipoMulta'!D5 -> Inasistencia | D6: ='M-Cita'!Q10 -> 22000 | E6: ='M-Cita'!G10 -> 0.45833333 | F6: 1/01/1000 00:00 | G6: no | H6: =B6 -> +57-3245627890-Lunes-09:00-19:00-12/11/2023-1/01/1000-10:00-16:00-01/06/2026-10:00
A7: 4 | B7: ='M-Cita'!R11 -> +57-3124518923-Martes-09:00-19:00-12/11/2023-1/01/1000-09:00-15:00-16/06/2026-09:00 | C7: ='M-TipoMulta'!D5 -> Inasistencia | D7: ='M-Cita'!Q11 -> 12000 | E7: ='M-Cita'!G11 -> 0.38541667 | F7: 1/01/1000 00:00 | G7: no | H7: =B7 -> +57-3124518923-Martes-09:00-19:00-12/11/2023-1/01/1000-09:00-15:00-16/06/2026-09:00
A8: 5 | B8: ='M-Cita'!R12 -> +57-3214533321-Jueves-09:00-19:00-12/11/2023-1/01/1000-13:00-19:00-02/07/2026-15:00 | C8: ='M-TipoMulta'!D5 -> Inasistencia | D8: ='M-Cita'!Q12 -> 15000 | E8: ='M-Cita'!G12 -> 0.63888889 | F8: 1/01/1000 00:00 | G8: no | H8: =B8 -> +57-3214533321-Jueves-09:00-19:00-12/11/2023-1/01/1000-13:00-19:00-02/07/2026-15:00
B14: Corresponde a la descripcion de los atributos
B15: Corresponde al identificador unico del objeto de dominio
B16: Corresponde a los datos de referencia de otros objetos de dominio
B17: Corresponde a los datos tipo entero
B18: Corresponde a los datos tipo hora
B19: Corresponde a los datos tipo fecha hora
B20: Corresponde a los datos de tipo logico
B21: Corresponde a la combinacion única
