Workbook

Sheet Modelo de Dominio
A1: Ir a objetos de dominio >>>>

Sheet Objetos de Dominio
A1: <<<< Ir al modulo de dominio
A2: Nombre | B2: Descripcion | C2: Linea de vida | D2: Muestreo | E2: Caracterización | F2: Event Storming | G2: Politicas
A3: Barberia | B3: Representa la cadena o marca comercial de barbería, dueña de una o varias sedes. | C3: 1 | D3: Ir al muestreo | E3: Ir a la caracterización | F3: Ir al Event Storming | G3: Ir a las políticas
A4: DiaSemana | B4: Representa cada uno de los días de la semana, incluyendo festivo, que se usa como catálogo para definir los horarios de la barbería y de cada barbero. | C4: 1 | D4: Ir al muestreo | E4: Ir a la caracterización | F4: Ir al Event Storming | G4: Ir a las políticas
A5: Departamento | B5: Representa cada uno de los departamentos del país en los que se encuentran las ciudades donde la barbería puede tener sedes. | C5: 1 | D5: Ir al muestreo | E5: Ir a la caracterización | F5: Ir al Event Storming | G5: Ir a las políticas
A6: Estado | B6: Representa en qué situación puntual se encuentra una cita: agendada, finalizada, cancelada por alguna de las partes, con tardanza del cliente o del barbero, o con inasistencia del cliente. | C6: 1 | D6: Ir al muestreo | E6: Ir a la caracterización | F6: Ir al Event Storming | G6: Ir a las políticas
A7: PrefijoCelular | B7: Representa el catálogo de prefijos telefónicos de país que el administrador habilita, y que son los únicos que barberos y clientes pueden usar en su número de celular. | C7: 1 | D7: Ir al muestreo | E7: Ir a la caracterización | F7: Ir al Event Storming | G7: Ir a las políticas
A8: TipoMulta | B8: Representa los tipos de multa que puede recibir un cliente: por tardanza o por inasistencia. | C8: 1 | D8: Ir al muestreo | E8: Ir a la caracterización | F8: Ir al Event Storming | G8: Ir a las políticas
A9: TipoRegistroHora | B9: Representa el catálogo de los distintos momentos en que se puede registrar una hora real durante una cita: llegada del cliente, barbero preparado, inicio y fin de la atención. | C9: 1 | D9: Ir al muestreo | E9: Ir a la caracterización | F9: Ir al Event Storming | G9: Ir a las políticas
A10: Cliente | B10: Representa a la persona que solicita citas en la barbería. | C10: 2 | D10: Ir al muestreo | E10: Ir a la caracterización | F10: Ir al Event Storming | G10: Ir a las políticas
A11: Ciudad | B11: Representa cada una de las ciudades, pertenecientes a un departamento, en las que puede estar ubicada una sede de la barbería. | C11: 2 | D11: Ir al muestreo | E11: Ir a la caracterización | F11: Ir al Event Storming | G11: Ir a las políticas
A12: Sede | B12: Representa cada una de las sucursales físicas de una barbería, ubicada en una ciudad puntual, donde se ofrecen los servicios y trabajan los barberos. | C12: 3 | D12: Ir al muestreo | E12: Ir a la caracterización | F12: Ir al Event Storming | G12: Ir a las políticas
A13: Barbero | B13: Representa a un trabajador de la barbería que atiende clientes según los servicios que sabe realizar, organiza su propio horario y tiene su agenda personal para atender todas las citas que valla teniendo. | C13: 4 | D13: Ir al muestreo | E13: Ir a la caracterización | F13: Ir al Event Storming | G13: Ir a las políticas
A14: HorarioBarberia | B14: Representa, día por día, a qué hora abre y cierra el negocio; es el límite dentro del cual debe caber el horario de cualquier barbero. | C14: 4 | D14: Ir al muestreo | E14: Ir a la caracterización | F14: Ir al Event Storming | G14: Ir a las políticas
... A23: RegistroHoraCita | B23: Representa cada hora real registrada durante una cita puntual, según el tipo de momento al que corresponde (llegada del cliente, barbero preparado, inicio o fin de la atención). | C23: 8 | D23: Ir al muestreo | E23: Ir a la caracterización | F23: Ir al Event Storming | G23: Ir a las políticas

Sheet C-Barberia
A1: <<<< Ir al modulo de dominio | B1: <<<< Ir a objetos de dominio
A2: Nombre atributo | B2: Descripción atributo | C2: Identificador del objeto de dominio | D2: Tipo de dato | E2: Obligatorio | F2: Longitud mínima (si aplica) | G2: Longitud máxima (si aplica) | H2: Precisión (si aplica) | I2: Rendondeo (si aplica) | J2: Rango inicial (si aplica) | K2: Rango final (si aplica) | L2: Formato (si aplica) | M2: Reglas especiales (si aplica) | N2: Dato calculado | O2: Aplica ajuste del dato (si aplica) | P2: Carácter de ajuste (si aplica) | Q2: Quitar espacios en blanco al inicio (si aplica) | R2: Quitar espacios en blanco al fin (si aplica) | S2: Dato sensible (si aplica) | T2: Valor por defecto (si aplica) | U2: Auto generado | V2: =A12 -> registrarBarberia | W2: =A14 -> consultarDatosBarberia | X2: =A15 -> consultarNombreBarberia | Y2: =A16 -> cambiarNombreBarberia | AA2: =A18 -> darDeBajaBarberia
A3: ='M-Barberia'!A3 -> id | B3: ='M-Barberia'!A2 -> Representa un identificador que hará unico cada objeto de dominio de este tipo, no se puede repetir | C3: Si | D3: Identificador único universal | E3: Si | F3: No aplica | G3: No aplica | H3: No aplica | I3: No aplica | J3: No aplica | K3: No aplica | L3: No aplica | M3: No aplica | N3: No | O3: No aplica | P3: No aplica | Q3: No aplica | R3: No aplica | S3: No | T3: UUID vacio | U3: Si | V3: No requerido | W3: No mostrar | X3: No mostrar | Y3: Requerido | Z3: No modificable | AA3: Requerido
A4: ='M-Barberia'!B3 -> nombre | B4: ='M-Barberia'!B2 -> Representa el nombre comercial de la cadena de barbería, dueña de una o varias sedes | C4: No | D4: Alfanumérico | E4: Si | F4: 2 | G4: 50 | H4: No aplica | I4: No aplica | J4: No aplica | K4: No aplica | L4: No aplica | M4: Se aceptan todos los caracterez | N4: No | O4: No aplica | P4: No aplica | Q4: Si | R4: Si | S4: No | T4: Vacio | U4: No | V4: Requerido | W4: Mostrar | X4: Mostrar | Y4: Requerido | Z4: Modificable | AA4: No requerido
A5: ='M-Barberia'!C3 -> nit | B5: ='M-Barberia'!C2 -> Representa el número de identificación tributaria (NIT) que identifica legalmente a la barbería como empresa | C5: No | D5: Alfanumérico | E5: Si | F5: 10 | G5: 12 | H5: No aplica | I5: No aplica | J5: No aplica | K5: No aplica | L5: El usuario debe ingresar entre 8 y 10 dígitos, seguido de un guion (-), seguido de 1 dígito | M5: Solo se aceptan numeros del 0 al 9 y el '-' | N5: No | O5: No aplica | P5: No aplica | Q5: Si | R5: Si | S5: No | T5: Vacio | U5: No | V5: Requerido | W5: Mostrar | X5: No mostrar | Y5: No requerido | Z5: No modificable | AA5: No requerido
A7: Nombre combinación única | B7: Descripción | C7: Atributos involucrados
A8: ='M-Barberia'!D3 -> Combinación única | B8: ='M-Barberia'!D2 -> Combinación única que indica que no puede existir más de una barbería con el mismo NIT | C8: =A5 -> nit
A10: Responsabilidad | C10: Descripción | G10: Entradas | J10: Salida | O10: Políticas (Reglas de Negocio) | Q10: Excepción
G11: Parámetro | H11: Tipo de dato | I11: Descripción | J11: Tipo de Dato | K11: Descripción | O11: Política | P11: Descripción | Q11: Detalle | R11: ¿Qué hago?
A12: registrarBarberia | C12: Comando que permite registrar una nueva barbería con su nombre y nit | G12: datos{nombre, nit} | H12: Barberia | I12: Contiene la información requerida para registrar la barbería | J12: Barberia | K12: Contiene la información de la barbería registrada | O12: ='P-Barberia'!A6 -> P-BRA-0001 | P12: ='P-Barberia'!B6 -> Asegurar que los datos requeridos de la barbería (nombre, nit) sean válidos en tipo de dato, longitud, obligatoriedad, formato y rango | Q12: Generar una excepción indicándole al administrador que los datos no cumplen | R12: Detener operación
O13: ='P-Barberia'!A7 -> P-BRA-0002 | P13: ='P-Barberia'!B7 -> Asegurar que no exista otra barbería registrada con el mismo nit | Q13: Generar una excepción indicándole al administrador que ya existe una barbería con ese nit | R13: Detener operación
A14: consultarDatosBarberia | C14: Permite al administrador consultar el nombre y el nit de la barbería | G14: id | H14: UUID | I14: Corresponde al identificador de la barbería que se va a consultar | J14: Barberia | K14: Contiene el nombre y el nit de la barbería | O14: ='P-Barberia'!A8 -> P-BRA-0003 | P14: ='P-Barberia'!B8 -> Asegurar que exista la barbería con el id enviado | Q14: Informar con un mensaje que no existe una barbería con el identificador enviado y por lo tanto no se puede realizar la operación | R14: Detener operación
A15: consultarNombreBarberia | C15: Permite al barbero y al cliente consultar el nombre de la barbería | G15: id | H15: UUID | I15: Corresponde al identificador de la barbería que se va a consultar | J15: Alfanumérico | K15: Contiene el nombre de la barbería | O15: ='P-Barberia'!A8 -> P-BRA-0003 | P15: ='P-Barberia'!B8 -> Asegurar que exista la barbería con el id enviado | Q15: Informar con un mensaje que no existe una barbería con el identificador enviado y por lo tanto no se puede realizar la operación | R15: Detener operación
A16: cambiarNombreBarberia | C16: Permite al administrador cambiar el nombre comercial de la barbería | G16: id | H16: UUID | I16: Corresponde al identificador de la barbería | J16: Barberia | K16: Contiene la barbería con su nombre actualizado | O16: ='P-Barberia'!A8 -> P-BRA-0003 | P16: ='P-Barberia'!B8 -> Asegurar que exista la barbería con el id enviado | Q16: Informar con un mensaje que no existe una barbería con el identificador enviado y por lo tanto no se puede realizar la operación | R16: Detener operación
G17: datos{nombre} | H17: Barberia | I17: Contiene el nuevo nombre de la barbería | O17: ='P-Barberia'!A6 -> P-BRA-0001 | P17: ='P-Barberia'!B6 -> Asegurar que los datos requeridos de la barbería (nombre, nit) sean válidos en tipo de dato, longitud, obligatoriedad, formato y rango | Q17: Generar una excepción indicándole al administrador cuáles datos de la barbería no cumplen con las reglas definidas | R17: Detener operación
A18: darDeBajaBarberia | C18: Permite al administrador eliminar la barbería del sistema cuando ya no tiene sedes registradas | G18: id | H18: UUID | I18: Corresponde al identificador de la barbería que se va a dar de baja | J18: No retorna ningún valor. En caso de error genera una excepción. | O18: ='P-Barberia'!A8 -> P-BRA-0003 | P18: ='P-Barberia'!B8 -> Asegurar que exista la barbería con el id enviado | Q18: Informar con un mensaje que no existe una barbería con el identificador enviado y por lo tanto no se puede realizar la operación | R18: Detener operación

Sheet P-Barberia
A1: << Ir al modelo de dominio | B1: << Ir al listado de objetos de dominio | C1: << Ir a la caracterización del objeto de dominio | D1: Ir al muestreo de datos del objeto de dominio >> | E1: Ir al event storming del objeto de dominio >>
A2: Objeto de Dominio: | B2: ='Objetos de Dominio'!A3 -> Barberia
A3: Descripción: | B3: ='Objetos de Dominio'!B3 -> Representa la cadena o marca comercial de barbería, dueña de una o varias sedes.
A4: Numero politica | B4: Descripcion politica | D4: Objeto responsable | E4: Regla responsable
A6: P-BRA-0001 | B6: Asegurar que los datos requeridos de la barbería (nombre, nit) sean válidos en tipo de dato, longitud, obligatoriedad, formato y rango | D6: Barberia
A7: P-BRA-0002 | B7: Asegurar que no exista otra barbería registrada con el mismo nit | D7: Barberia
A8: P-BRA-0003 | B8: Asegurar que exista la barbería con el id enviado | D8: Barberia

Sheet E-Barberia
A1: << Ir al modelo de dominio | C1: << Ir al listado de objetos de dominio | F1: << Ir a la caracterización del objeto de dominio | J1: Ir al muestreo de datos del objeto de dominio >>
A2: Objeto de Dominio: | B2: ='Objetos de Dominio'!A3 -> Barberia
A3: Descripción: | B3: ='Objetos de Dominio'!B3 -> Representa la cadena o marca comercial de barbería, dueña de una o varias sedes.
A4: Actor | B4: Action/Command | D4: Entity/Aggregate/Object domain | E4: Read Model | G4: Business Rule/Policy | I4: External System | J4: Domain Event | K4: Hotspot/questions/Risk
A5: Actor | B5: Acción | C5: Descripción | D5: Objeto de dominio | E5: Información externa | G5: Políticas | I5: Sistema Externo | J5: Evento | K5: Aspectos por solucionar
E6: Información | F6: Descripción | G6: Número | H6: Descripción
A7: Administrador | B7: Registrar barberia | C7: Comando que permite al administrador registrar una nueva barbería con su nombre y nit | D7: =$B$2 -> Barberia | G7: ='P-Barberia'!A6 -> P-BRA-0001 | H7: ='P-Barberia'!B6 -> Asegurar que los datos requeridos de la barbería (nombre, nit) sean válidos en tipo de dato, longitud, obligatoriedad, formato y rango | J7: Barbería registrada
G8: ='P-Barberia'!A7 -> P-BRA-0002 | H8: ='P-Barberia'!B7 -> Asegurar que no exista otra barbería registrada con el mismo nit
A9: Administrador | B9: Ver nombre y nit de la barberia | C9: Permite al administrador consultar el nombre y el nit de la barbería | D9: =$B$2 -> Barberia | J9: Nombre y nit de barbería consultados
A10: Barbero | B10: Ver nombre de la barberia | C10: Permite al barbero consultar el nombre de la barbería | D10: =$B$2 -> Barberia | J10: Nombre de barbería consultado
A11: Cliente | B11: Ver nombre de la barberia | C11: Permite al cliente consultar el nombre de la barbería | D11: =$B$2 -> Barberia | J11: Nombre de barbería consultado
A12: Administrador | B12: Cambiar nombre de la barberia | C12: Permite al administrador cambiar el nombre comercial de la barbería | D12: =$B$2 -> Barberia | G12: ='P-Barberia'!A8 -> P-BRA-0003 | H12: ='P-Barberia'!B8 -> Asegurar que exista la barbería con el id enviado | J12: Nombre de barbería cambiado
G13: ='P-Barberia'!A6 -> P-BRA-0001 | H13: ='P-Barberia'!B6 -> Asegurar que los datos requeridos de la barbería (nombre, nit) sean válidos en tipo de dato, longitud, obligatoriedad, formato y rango
A14: Administrador | B14: Dar de baja la barberia | C14: Permite al administrador eliminar la barbería del sistema, como si nunca hubiera existido, cuando ya no tiene sedes registradas | D14: =$B$2 -> Barberia | J14: Barbería eliminada

Sheet M-Barberia
A1: <<<< Ir al modulo de dominio | B1: <<<< Ir a objetos de dominio
A2: Representa un identificador que hará unico cada objeto de dominio de este tipo, no se puede repetir | B2: Representa el nombre comercial de la cadena de barbería, dueña de una o varias sedes | C2: Representa el número de identificación tributaria (NIT) que identifica legalmente a la barbería como empresa | D2: Combinación única que indica que no puede existir más de una barbería con el mismo NIT
A3: id | B3: nombre | C3: nit | D3: Combinación única
A4: 1 | B4: BarberClub | C4: 900123456-7 | D4: =C4 -> 900123456-7
A5: 2 | B5: Corte y Estilo | C5: 900654321-9 | D5: =C5 -> 900654321-9
B11: Corresponde a la descripcion de los atributos
B12: Corresponde al identificador unico del objeto de dominio
B13: Corresponde a los datos que ingresa el usuario
B14: Corresponde a la combinacion única

Sheet C-DiaSemana
A1: <<<< Ir al modulo de dominio | B1: <<<< Ir a objetos de dominio
A2: Nombre atributo | B2: Descripción atributo | C2: Identificador del objeto de dominio | D2: Tipo de dato | E2: Obligatorio | F2: Longitud mínima (si aplica) | G2: Longitud máxima (si aplica) | H2: Precisión (si aplica) | I2: Rendondeo (si aplica) | J2: Rango inicial (si aplica) | K2: Rango final (si aplica) | L2: Formato (si aplica) | M2: Reglas especiales (si aplica) | N2: Dato calculado | O2: Aplica ajuste del dato (si aplica) | P2: Carácter de ajuste (si aplica) | Q2: Quitar espacios en blanco al inicio (si aplica) | R2: Quitar espacios en blanco al fin (si aplica) | S2: Dato sensible (si aplica) | T2: Valor por defecto (si aplica) | U2: Auto generado | V2: =A11 -> VerDiasDeLaSemana
A3: ='M-DiaSemana'!A3 -> id | B3: ='M-DiaSemana'!A2 -> Representa un identificador que hará unico cada objeto de dominio de este tipo, no se puede repetir | C3: Si | D3: Identificador único universal | E3: Si | F3: No aplica | G3: No aplica | H3: No aplica | I3: No aplica | J3: No aplica | K3: No aplica | L3: No aplica | M3: No aplica | N3: No | O3: No aplica | P3: No aplica | Q3: No aplica | R3: No aplica | S3: No | T3: UUID vacio | U3: Si | V3: No mostrar
A4: ='M-DiaSemana'!B3 -> nombre | B4: ='M-DiaSemana'!B2 -> Representa como se llama el dia de la semana, para los horarios | C4: No | D4: Alfanumérico | E4: Si | F4: 5 | G4: 9 | H4: No aplica | I4: No aplica | J4: No aplica | K4: No aplica | L4: No aplica | M4: Solo pueden ser los dias de la semana como Lunes, Martes, Miércoles, Jueves, Viernes, Sábado, Domingo y Festivo | N4: No | O4: No aplica | P4: No aplica | Q4: Si | R4: Si | S4: No | T4: Vacio | U4: No | V4: Mostrar
A6: Nombre combinación única | B6: Descripción | C6: Atributos involucrados
A7: ='M-DiaSemana'!C3 -> Combinación única | B7: ='M-DiaSemana'!C2 -> Combinacion única que indica que no puede existir más un dia de la semana con el mismo nombre | C7: nombre
A9: Responsabilidad | C9: Descripción | G9: Entradas | J9: Salida | O9: Políticas (Reglas de Negocio) | Q9: Excepción
G10: Parámetro | H10: Tipo de dato | I10: Descripción | J10: Tipo de Dato | K10: Descripción | O10: Política | P10: Descripción | Q10: Detalle | R10: ¿Qué hago?
A11: VerDiasDeLaSemana | C11: Permite consultar el catálogo de días de la semana, incluyendo festivo, para definir los horarios | J11: Lista<DiaSemana> | K11: Contiene todos los días de la semana

Sheet P-DiaSemana
A1: << Ir al modelo de dominio | B1: << Ir al listado de objetos de dominio | C1: << Ir a la caracterización del objeto de dominio | D1: Ir al muestreo de datos del objeto de dominio >> | E1: Ir al event storming del objeto de dominio >>
A2: Objeto de Dominio: | B2: ='Objetos de Dominio'!A4 -> DiaSemana
A3: Descripción: | B3: ='Objetos de Dominio'!B4 -> Representa cada uno de los días de la semana, incluyendo festivo, que se usa como catálogo para definir los horarios de la barbería y de cada barbero.
A4: Numero politica | B4: Descripcion politica | D4: Objeto responsable | E4: Regla responsable
B6: No aplica: es un catálogo de solo lectura, sin comandos que impliquen políticas de negocio propias

Sheet E-DiaSemana
A1: << Ir al modelo de dominio | C1: << Ir al listado de objetos de dominio | F1: << Ir a la caracterización del objeto de dominio | J1: Ir al muestreo de datos del objeto de dominio >>
A2: Objeto de Dominio: | B2: ='Objetos de Dominio'!A4 -> DiaSemana
A3: Descripción: | B3: ='Objetos de Dominio'!B4 -> Representa cada uno de los días de la semana, incluyendo festivo, que se usa como catálogo para definir los horarios de la barbería y de cada barbero.
A4: Actor | B4: Action/Command | D4: Entity/Aggregate/Object domain | E4: Read Model | G4: Business Rule/Policy | I4: External System | J4: Domain Event | K4: Hotspot/questions/Risk
A5: Actor | B5: Acción | C5: Descripción | D5: Objeto de dominio | E5: Información externa | G5: Políticas | I5: Sistema Externo | J5: Evento | K5: Aspectos por solucionar
E6: Información | F6: Descripción | G6: Número | H6: Descripción
A7: Administrador | B7: Ver los días de las semanas | C7: Permite consultar el catálogo de días de la semana, incluyendo festivo, disponibles para definir horarios | D7: =$B$2 -> DiaSemana | J7: Días de la semana consultados
A8: Barbero | B8: Ver los días de las semanas | C8: Permite consultar el catálogo de días de la semana, incluyendo festivo, disponibles para definir horarios | D8: =$B$2 -> DiaSemana | J8: Días de la semana consultados

Sheet M-DiaSemana
A1: <<<< Ir al modulo de dominio | B1: <<<< Ir a objetos de dominio
A2: Representa un identificador que hará unico cada objeto de dominio de este tipo, no se puede repetir | B2: Representa como se llama el dia de la semana, para los horarios | C2: Combinacion única que indica que no puede existir más un dia de la semana con el mismo nombre
A3: id | B3: nombre | C3: Combinación única
A4: 1 | B4: Lunes | C4: =B4 -> Lunes
A5: 2 | B5: Martes | C5: =B5 -> Martes
A6: 3 | B6: Miércoles | C6: =B6 -> Miércoles
A7: 4 | B7: Jueves | C7: =B7 -> Jueves
A8: 5 | B8: Viernes | C8: =B8 -> Viernes
A9: 6 | B9: Sábado | C9: =B9 -> Sábado
A10: 7 | B10: Domingo | C10: =B10 -> Domingo
A11: 8 | B11: Festivo | C11: =B11 -> Festivo
B17: Corresponde a la descripcion de los atributos
B18: Corresponde al identificador unico del objeto de dominio
B19: Corresponde a los datos que ingresa el usuario
B20: Corresponde a la combinacion única

Sheet C-Departamento
A1: <<<< Ir al modulo de dominio | B1: <<<< Ir a objetos de dominio
A2: Nombre atributo | B2: Descripción atributo | C2: Identificador del objeto de dominio | D2: Tipo de dato | E2: Obligatorio | F2: Longitud mínima (si aplica) | G2: Longitud máxima (si aplica) | H2: Precisión (si aplica) | I2: Rendondeo (si aplica) | J2: Rango inicial (si aplica) | K2: Rango final (si aplica) | L2: Formato (si aplica) | M2: Reglas especiales (si aplica) | N2: Dato calculado | O2: Aplica ajuste del dato (si aplica) | P2: Carácter de ajuste (si aplica) | Q2: Quitar espacios en blanco al inicio (si aplica) | R2: Quitar espacios en blanco al fin (si aplica) | S2: Dato sensible (si aplica) | T2: Valor por defecto (si aplica) | U2: Auto generado | V2: =A11 -> consultarDepartamentos
A3: ='M-Departamento'!A3 -> id | B3: ='M-Departamento'!A2 -> Representa un identificador que hará unico cada objeto de dominio de este tipo, no se puede repetir | C3: Si | D3: Identificador único universal | E3: Si | F3: No aplica | G3: No aplica | H3: No aplica | I3: No aplica | J3: No aplica | K3: No aplica | L3: No aplica | M3: No aplica | N3: No | O3: No aplica | P3: No aplica | Q3: No aplica | R3: No aplica | S3: No | T3: UUID vacio | U3: Si | V3: No mostrar
A4: ='M-Departamento'!B3 -> nombre | B4: ='M-Departamento'!B2 -> Representa el nombre del departamento en el que están ubicadas las ciudades donde la barbería puede tener sedes | C4: No | D4: Alfanumérico | E4: Si | F4: 4 | G4: 60 | H4: No aplica | I4: No aplica | J4: No aplica | K4: No aplica | L4: No aplica | M4: Permite caracterez de la 'a' a la 'z' minusculas y mayusculas, con espacios en blanco y esas letras pero con tilde | N4: No | O4: No aplica | P4: No aplica | Q4: Si | R4: Si | S4: No | T4: Vacio | U4: No | V4: Mostrar
A6: Nombre combinación única | B6: Descripción | C6: Atributos involucrados
A7: ='M-Departamento'!C3 -> Combinación única | B7: ='M-Departamento'!C2 -> Combinación única que indica que no puede existir más de un departamento con el mismo nombre | C7: =A4 -> nombre
A9: Responsabilidad | C9: Descripción | G9: Entradas | J9: Salida | O9: Políticas (Reglas de Negocio) | Q9: Excepción
G10: Parámetro | H10: Tipo de dato | I10: Descripción | J10: Tipo de Dato | K10: Descripción | O10: Política | P10: Descripción | Q10: Detalle | R10: ¿Qué hago?
A11: consultarDepartamentos | C11: Permite consultar el catálogo de departamentos disponibles | J11: Lista<Departamento> | K11: Contiene todos los departamentos registrados

Sheet P-Departamento
A1: << Ir al modelo de dominio | B1: << Ir al listado de objetos de dominio | C1: << Ir a la caracterización del objeto de dominio | D1: Ir al muestreo de datos del objeto de dominio >> | E1: Ir al event storming del objeto de dominio >>
A2: Objeto de Dominio: | B2: ='Objetos de Dominio'!A5 -> Departamento
A3: Descripción: | B3: ='Objetos de Dominio'!B5 -> Representa cada uno de los departamentos del país en los que se encuentran las ciudades donde la barbería puede tener sedes.
A4: Numero politica | B4: Descripcion politica | D4: Objeto responsable | E4: Regla responsable
B6: No aplica: es un catálogo de solo lectura, sin comandos que impliquen políticas de negocio propias

Sheet E-Departamento
A1: << Ir al modelo de dominio | C1: << Ir al listado de objetos de dominio | F1: << Ir a la caracterización del objeto de dominio | J1: Ir al muestreo de datos del objeto de dominio >>
A2: Objeto de Dominio: | B2: ='Objetos de Dominio'!A5 -> Departamento
A3: Descripción: | B3: ='Objetos de Dominio'!B5 -> Representa cada uno de los departamentos del país en los que se encuentran las ciudades donde la barbería puede tener sedes.
A4: Actor | B4: Action/Command | D4: Entity/Aggregate/Object domain | E4: Read Model | G4: Business Rule/Policy | I4: External System | J4: Domain Event | K4: Hotspot/questions/Risk
A5: Actor | B5: Acción | C5: Descripción | D5: Objeto de dominio | E5: Información externa | G5: Políticas | I5: Sistema Externo | J5: Evento | K5: Aspectos por solucionar
E6: Información | F6: Descripción | G6: Número | H6: Descripción
A7: Administrador | B7: Ver los departamentos | C7: Permite consultar el catálogo de departamentos en los que se pueden ubicar las ciudades de las sedes | D7: =$B$2 -> Departamento | J7: Departamentos consultados

Sheet M-Departamento
A1: <<<< Ir al modulo de dominio | B1: <<<< Ir a objetos de dominio
A2: Representa un identificador que hará unico cada objeto de dominio de este tipo, no se puede repetir | B2: Representa el nombre del departamento en el que están ubicadas las ciudades donde la barbería puede tener sedes | C2: Combinación única que indica que no puede existir más de un departamento con el mismo nombre
A3: id | B3: nombre | C3: Combinación única
A4: 1 | B4: Antioquia | C4: =B4 -> Antioquia
A5: 2 | B5: Cundinamarca | C5: =B5 -> Cundinamarca
A6: 3 | B6: Valle del Cauca | C6: =B6 -> Valle del Cauca
A7: 4 | B7: Atlántico | C7: =B7 -> Atlántico
A8: 5 | B8: Santander | C8: =B8 -> Santander
B14: Corresponde a la descripcion de los atributos
B15: Corresponde al identificador unico del objeto de dominio
B16: Corresponde a los datos de libre ingreso
B17: Corresponde a la combinacion única

Sheet C-Estado
A1: <<<< Ir al modulo de dominio | B1: <<<< Ir a objetos de dominio
A2: Nombre atributo | B2: Descripción atributo | C2: Identificador del objeto de dominio | D2: Tipo de dato | E2: Obligatorio | F2: Longitud mínima (si aplica) | G2: Longitud máxima (si aplica) | H2: Precisión (si aplica) | I2: Rendondeo (si aplica) | J2: Rango inicial (si aplica) | K2: Rango final (si aplica) | L2: Formato (si aplica) | M2: Reglas especiales (si aplica) | N2: Dato calculado | O2: Aplica ajuste del dato (si aplica) | P2: Carácter de ajuste (si aplica) | Q2: Quitar espacios en blanco al inicio (si aplica) | R2: Quitar espacios en blanco al fin (si aplica) | S2: Dato sensible (si aplica) | T2: Valor por defecto (si aplica) | U2: Auto generado | V2: =A12 -> consultarTodosLosEstados | W2: =A13 -> editarDescripcion | X2: 'C-Estado'!A13 | Y2: =A15 -> consultarDescripcion
A3: ='M-Estado'!A3 -> id | B3: ='M-Estado'!A2 -> Representa un identificador que hará unico cada objeto de dominio de este tipo, no se puede repetir | C3: Si | D3: Identificador único universal | E3: Si | F3: No aplica | G3: No aplica | H3: No aplica | I3: No aplica | J3: No aplica | K3: No aplica | L3: No aplica | M3: No aplica | N3: No | O3: No aplica | P3: No aplica | Q3: No aplica | R3: No aplica | S3: No aplica | T3: UUID vacio | U3: Si | V3: No mostrar | W3: Requerido | X3: No modificable | Y3: No mostrar
A4: ='M-Estado'!B3 -> nombre | B4: ='M-Estado'!B2 -> Representa como se llama el estado en el que se encuentra una cita puntual | C4: No | D4: Alfanumérico | E4: Si | F4: 4 | G4: 50 | H4: No aplica | I4: No aplica | J4: No aplica | K4: No aplica | L4: No aplica | M4: Solo se aceptan caracteres de letras de la 'a' a la 'z' y espacios en blanco | N4: No | O4: No aplica | P4: No aplica | Q4: Si | R4: Si | S4: No | T4: Vacio | U4: No | V4: Mostrar | W4: No requerido | X4: No modificable | Y4: No mostrar
A5: ='M-Estado'!C3 -> descripcion | B5: ='M-Estado'!C2 -> Representa el significado de que representa cada estado para la cita | C5: No | D5: Alfanumérico | E5: Si | F5: 10 | G5: 300 | H5: No aplica | I5: No aplica | J5: No aplica | K5: No aplica | L5: No aplica | M5: Solo se aceptan caracteres de letras de la 'a' a la 'z', caracteres con tilde y espacios en blanco | N5: No | O5: No aplica | P5: No aplica | Q5: Si | R5: Si | S5: No | T5: Vacio | U5: No | V5: No mostrar | W5: Requerido | X5: Modificable | Y5: Mostrar
A7: Nombre combinación única | B7: Descripción | C7: Atributos involucrados
A8: ='M-Estado'!D3 -> Combinación única | B8: ='M-Estado'!D2 -> Combinacion única que indica que no puede existir más un dia de la semana con el mismo nombre | C8: nombre
A10: Responsabilidad | C10: Descripción | G10: Entradas | J10: Salida | O10: Políticas (Reglas de Negocio) | Q10: Excepción
G11: Parámetro | H11: Tipo de dato | I11: Descripción | J11: Tipo de Dato | K11: Descripción | O11: Política | P11: Descripción | Q11: Detalle | R11: ¿Qué hago?
A12: consultarTodosLosEstados | C12: Permite consultar los estados posibles que puede tener una cita | J12: Lista<Estado> | K12: Contiene todos los estados que cumplen con el filtro enviado
A13: editarDescripcion | C13: Permite ajustar el texto descriptivo de un estado ya creado, sin cambiar su significado en el flujo de la cita | G13: id | H13: UUID | I13: Corresponde al identificador del estado que se va a editar | K13: La descripcion del estado se editó | O13: ='P-Estado'!A7 -> P-EST-0002 | P13: ='P-Estado'!B7 -> Asegurar que exista el estado con el id enviado | Q13: Informar con un mensaje que no existe un estado con el identificador enviado y por lo tanto no es posible modificar la descripción | R13: Detener ejecución de la operación
G14: datos{descripcion} | H14: Estado | I14: Contiene la nueva descripción del estado | O14: ='P-Estado'!A6 -> P-EST-0001 | P14: ='P-Estado'!B6 -> Asegurar que los datos requeridos (descripción) sean válidos en tipo de dato, longitud, formato y rango | Q14: Generar una excepción indicándole al usuario cuáles datos de la descripción del estado no cumplen con las reglas definidas | R14: Detener operación
A15: consultarDescripcion | C15: Permite consultar la descripcion de un estado en especifico | G15: datos{nombre} | H15: Estado | I15: Contiene el nombre del estado | J15: Alfanumérico | K15: Contiene la información del estado consultado por su identificador | O15: ='P-Estado'!A7 -> P-EST-0002 | P15: ='P-Estado'!B7 -> Asegurar que exista el estado con el id enviado | Q15: Informar con un mensaje que no existe un Estado con el identificador enviado y por lo tanto no es posible modificar la descripción | R15: Detener ejecución de la operación

Sheet P-Estado
A1: << Ir al modelo de dominio | B1: << Ir al listado de objetos de dominio | C1: << Ir a la caracterización del objeto de dominio | D1: Ir al muestreo de datos del objeto de dominio >> | E1: Ir al event storming del objeto de dominio >>
A2: Objeto de Dominio: | B2: ='Objetos de Dominio'!A6 -> Estado
A3: Descripción: | B3: ='Objetos de Dominio'!B6 -> Representa en qué situación puntual se encuentra una cita: agendada, finalizada, cancelada por alguna de las partes, con tardanza del cliente o del barbero, o con inasistencia del cliente.
A4: Numero politica | B4: Descripcion politica | D4: Objeto responsable | E4: Regla responsable
A6: P-EST-0001 | B6: Asegurar que los datos requeridos (descripción) sean válidos en tipo de dato, longitud, formato y rango | D6: Estado
A7: P-EST-0002 | B7: Asegurar que exista el estado con el id enviado | D7: Estado

Sheet E-Estado
A1: << Ir al modelo de dominio | C1: << Ir al listado de objetos de dominio | F1: << Ir a la caracterización del objeto de dominio | J1: Ir al muestreo de datos del objeto de dominio >>
A2: Objeto de Dominio: | B2: ='Objetos de Dominio'!A6 -> Estado
A3: Descripción: | B3: ='Objetos de Dominio'!B6 -> Representa en qué situación puntual se encuentra una cita: agendada, finalizada, cancelada por alguna de las partes, con tardanza del cliente o del barbero, o con inasistencia del cliente.
A4: Actor | B4: Action/Command | D4: Entity/Aggregate/Object domain | E4: Read Model | G4: Business Rule/Policy | I4: External System | J4: Domain Event | K4: Hotspot/questions/Risk
A5: Actor | B5: Acción | C5: Descripción | D5: Objeto de dominio | E5: Información externa | G5: Políticas | I5: Sistema Externo | J5: Evento | K5: Aspectos por solucionar
E6: Información | F6: Descripción | G6: Número | H6: Descripción
A7: Administrador | B7: Ver estados de las citas | C7: Permite consultar los estados posibles que puede tener una cita | D7: =$B$2 -> Estado | J7: Estados consultados
A8: Barbero | B8: Ver estados de las citas | C8: Permite consultar los estados posibles que puede tener una cita | D8: =$B$2 -> Estado | J8: Estados consultados
A9: Cliente | B9: Ver estados de las citas | C9: Permite consultar los estados posibles que puede tener una cita | D9: =$B$2 -> Estado | J9: Estados consultados
A10: Administrador | B10: Editar descripción del estado | C10: Permite ajustar el texto descriptivo de un estado ya creado, sin cambiar su significado en el flujo de la cita | D10: =$B$2 -> Estado | G10: ='P-Estado'!A6 -> P-EST-0001 | H10: ='P-Estado'!B6 -> Asegurar que los datos requeridos (descripción) sean válidos en tipo de dato, longitud, formato y rango | J10: Descripción de estado actualizada
A11: Administrador | B11: Ver descripcion de un estado | C11: Permite consultar la descripcion de un estado en especifico | D11: =$B$2 -> Estado | J11: Descripción del estado consultada
A12: Barbero | B12: Ver descripcion de un estado | C12: Permite consultar la descripcion de un estado en especifico | D12: =$B$2 -> Estado | J12: Descripción del estado consultada
A13: Cliente | B13: Ver descripcion de un estado | C13: Permite consultar la descripcion de un estado en especifico | D13: =$B$2 -> Estado | J13: Descripción del estado consultada

Sheet M-Estado
A1: <<<< Ir al modulo de dominio | B1: <<<< Ir a objetos de dominio
A2: Representa un identificador que hará unico cada objeto de dominio de este tipo, no se puede repetir | B2: Representa como se llama el estado en el que se encuentra una cita puntual | C2: Representa el significado de que representa cada estado para la cita | D2: Combinacion única que indica que no puede existir más un dia de la semana con el mismo nombre
A3: id | B3: nombre | C3: descripcion | D3: Combinación única
A4: 1 | B4: Agendada | C4: La cita quedó registrada en la agenda del barbero y está a la espera de la fecha y hora acordadas. | D4: =B4 -> Agendada
A5: 2 | B5: Finalizada | C5: El barbero atendió al cliente y el servicio contratado se prestó por completo, sin tener ninguna sanción. | D5: =B5 -> Finalizada
A6: 3 | B6: Cancelada por el cliente | C6: El cliente decidió no asistir y anuló la cita antes de la fecha y hora programada. | D6: =B6 -> Cancelada por el cliente
A7: 4 | B7: Cancelada por el barbero | C7: El barbero anuló la cita antes de la fecha y hora programada, por ejemplo por una eventualidad. | D7: =B7 -> Cancelada por el barbero
A8: 5 | B8: El cliente se demoro | C8: El cliente llegó después de la hora acordada superando el tiempoEspera definido en la cita, lo que genera una multa de tipo Tardanza. | D8: =B8 -> El cliente se demoro
A9: 6 | B9: El barbero se demoro | C9: El barbero se demoró más de lo previsto en una cita anterior y empezó a atender al cliente superando el tiempoEspera definido en la cita, lo que le da un descuento al cliente. | D9: =B9 -> El barbero se demoro
A10: 7 | B10: Inasistencia del cliente | C10: El cliente nunca llegó a la cita: se alcanzó la hora estimada de finalización sin registrar su llegada, lo que genera una multa por el valor total de los servicios pedidos. | D10: =B10 -> Inasistencia del cliente
A11: 8 | B11: Cancelación | C11: La cita se anuló automáticamente porque la barbería cambió sus políticas de horario: al desactivarse el horario de la barbería se desactivaron los horarios de barbero y las agendas que dependían de él, y las citas que quedaron por fuera se cancelaron. | D11: =B11 -> Cancelación
B17: Corresponde a la descripcion de los atributos
B18: Corresponde al identificador unico del objeto de dominio
B19: Corresponde a los datos del objeto de dominio
B20: Corresponde a la combinacion única

Sheet C-PrefijoCelular
A1: <<<< Ir al modulo de dominio | B1: <<<< Ir a objetos de dominio
A2: Nombre atributo | B2: Descripción atributo | C2: Identificador del objeto de dominio | D2: Tipo de dato | E2: Obligatorio | F2: Longitud mínima (si aplica) | G2: Longitud máxima (si aplica) | H2: Precisión (si aplica) | I2: Rendondeo (si aplica) | J2: Rango inicial (si aplica) | K2: Rango final (si aplica) | L2: Formato (si aplica) | M2: Reglas especiales (si aplica) | N2: Dato calculado | O2: Aplica ajuste del dato (si aplica) | P2: Carácter de ajuste (si aplica) | Q2: Quitar espacios en blanco al inicio (si aplica) | R2: Quitar espacios en blanco al fin (si aplica) | S2: Dato sensible (si aplica) | T2: Valor por defecto (si aplica) | U2: Auto generado | V2: =A11 -> consultarPrefijosCelular
A3: ='M-PrefijoCelular'!A3 -> id | B3: ='M-PrefijoCelular'!A2 -> Representa un identificador que hará unico cada objeto de dominio de este tipo, no se puede repetir | C3: Si | D3: Identificador único universal | E3: Si | F3: No aplica | G3: No aplica | H3: No aplica | I3: No aplica | J3: No aplica | K3: No aplica | L3: No aplica | M3: No aplica | N3: No | O3: No | P3: No aplica | Q3: No | R3: No | S3: No | T3: No aplica | U3: Si | V3: No mostrar
A4: ='M-PrefijoCelular'!B3 -> prefijo | B4: ='M-PrefijoCelular'!B2 -> Representa el prefijo telefónico del país que el administrador habilita para que la barbería pueda atender números de ese país | C4: No | D4: Alfanumérico | E4: Si | F4: 2 | G4: 6 | H4: No aplica | I4: No aplica | J4: No aplica | K4: No aplica | L4: Simbolo + seguido de un número. Por ejemplo +57. Tambien el anterior puede ser seguido de un - y un numero. Por ejemplo +1-809 | M4: Solo se aceptan caracteres numericos del 0 al 9 y el carácter '+' y '-' | N4: No | O4: No | P4: No aplica | Q4: Si | R4: Si | S4: No | T4: +0 | U4: No | V4: Mostrar
A6: Nombre combinación única | B6: Descripción | C6: Atributos involucrados
A7: ='M-PrefijoCelular'!C3 -> Combinación única | B7: ='M-PrefijoCelular'!C2 -> Combinacion única que indica que no puede existir más un mismo prefijo | C7: prefijo
A9: Responsabilidad | C9: Descripción | G9: Entradas | J9: Salida | O9: Políticas (Reglas de Negocio) | Q9: Excepción
G10: Parámetro | H10: Tipo de dato | I10: Descripción | J10: Tipo de Dato | K10: Descripción | O10: Política | P10: Descripción | Q10: Detalle | R10: ¿Qué hago?
A11: consultarPrefijosCelular | C11: Permite al administrador consultar el catálogo de prefijos telefónicos de país que tiene habilitados | J11: Lista<PrefijoCelular> | K11: Contiene todos los prefijos de celular registrados

Sheet P-PrefijoCelular
A1: << Ir al modelo de dominio | B1: << Ir al listado de objetos de dominio | C1: << Ir a la caracterización del objeto de dominio | D1: Ir al muestreo de datos del objeto de dominio >> | E1: Ir al event storming del objeto de dominio >>
A2: Objeto de Dominio: | B2: ='Objetos de Dominio'!A7 -> PrefijoCelular
A3: Descripción: | B3: ='Objetos de Dominio'!B7 -> Representa el catálogo de prefijos telefónicos de país que el administrador habilita, y que son los únicos que barberos y clientes pueden usar en su número de celular.
A4: Numero politica | B4: Descripcion politica | D4: Objeto responsable | E4: Regla responsable
B6: No aplica: es un catálogo de solo lectura, sin comandos que impliquen políticas de negocio propias

Sheet E-PrefijoCelular
A1: << Ir al modelo de dominio | C1: << Ir al listado de objetos de dominio | F1: << Ir a la caracterización del objeto de dominio | J1: Ir al muestreo de datos del objeto de dominio >>
A2: Objeto de Dominio: | B2: ='Objetos de Dominio'!A7 -> PrefijoCelular
A3: Descripción: | B3: ='Objetos de Dominio'!B7 -> Representa el catálogo de prefijos telefónicos de país que el administrador habilita, y que son los únicos que barberos y clientes pueden usar en su número de celular.
A4: Actor | B4: Action/Command | D4: Entity/Aggregate/Object domain | E4: Read Model | G4: Business Rule/Policy | I4: External System | J4: Domain Event | K4: Hotspot/questions/Risk
A5: Actor | B5: Acción | C5: Descripción | D5: Objeto de dominio | E5: Información externa | G5: Políticas | I5: Sistema Externo | J5: Evento | K5: Aspectos por solucionar
E6: Información | F6: Descripción | G6: Número | H6: Descripción
A7: Administrador | B7: Ver prefijos de celular | C7: Permite al administrador consultar el catálogo de prefijos telefónicos de país que tiene habilitados | D7: =$B$2 -> PrefijoCelular | J7: Prefijos de celular consultados
A8: Barbero | B8: Ver prefijos de celular | C8: Permite consultar el catálogo de prefijos telefónicos de país disponibles | D8: =$B$2 -> PrefijoCelular | J8: Prefijos de celular consultados
A9: Cliente | B9: Ver prefijos de celular | C9: Permite consultar el catálogo de prefijos telefónicos de país disponibles | D9: =$B$2 -> PrefijoCelular | J9: Prefijos de celular consultados

Sheet M-PrefijoCelular
A1: <<<< Ir al modulo de dominio | B1: <<<< Ir a objetos de dominio
A2: Representa un identificador que hará unico cada objeto de dominio de este tipo, no se puede repetir | B2: Representa el prefijo telefónico del país que el administrador habilita para que la barbería pueda atender números de ese país | C2: Combinacion única que indica que no puede existir más un mismo prefijo
A3: id | B3: prefijo | C3: Combinación única
A4: 1 | B4: +57 | C4: =B4 -> +57
A5: 2 | B5: +91 | C5: =B5 -> +91
A6: 3 | B6: +593 | C6: =B6 -> +593
A7: 4 | B7: +58 | C7: =B7 -> +58
B13: Corresponde a la descripcion de los atributos
B14: Corresponde al identificador unico del objeto de dominio
B15: Corresponde a los datos que ingresa el usuario
B16: Corresponde a la combinacion única

Sheet C-TipoMulta
A1: <<<< Ir al modulo de dominio | B1: <<<< Ir a objetos de dominio
A2: Nombre atributo | B2: Descripción atributo | C2: Identificador del objeto de dominio | D2: Tipo de dato | E2: Obligatorio | F2: Longitud mínima (si aplica) | G2: Longitud máxima (si aplica) | H2: Precisión (si aplica) | I2: Rendondeo (si aplica) | J2: Rango inicial (si aplica) | K2: Rango final (si aplica) | L2: Formato (si aplica) | M2: Reglas especiales (si aplica) | N2: Dato calculado | O2: Aplica ajuste del dato (si aplica) | P2: Carácter de ajuste (si aplica) | Q2: Quitar espacios en blanco al inicio (si aplica) | R2: Quitar espacios en blanco al fin (si aplica) | S2: Dato sensible (si aplica) | T2: Valor por defecto (si aplica) | U2: Auto generado | V2: =A12 -> consultarTodosLosTiposMulta
A3: ='M-TipoMulta'!A3 -> id | B3: ='M-TipoMulta'!A2 -> Representa un identificador que hará unico cada objeto de dominio de este tipo, no se puede repetir | C3: Si | D3: Identificador único universal | E3: Si | F3: No aplica | G3: No aplica | H3: No aplica | I3: No aplica | J3: No aplica | K3: No aplica | L3: No aplica | M3: No aplica | N3: No | O3: No | P3: No aplica | Q3: No | R3: No | S3: No | T3: UUID vacio | U3: Si | V3: No mostrar
A4: ='M-TipoMulta'!B3 -> nombre | B4: ='M-TipoMulta'!B2 -> Representa el nombre del tipo de multa | C4: No | D4: Alfanumérico | E4: Si | F4: 4 | G4: 50 | H4: No aplica | I4: No aplica | J4: No aplica | K4: No aplica | L4: No aplica | M4: No aplica | N4: No | O4: No | P4: No aplica | Q4: Si | R4: Si | S4: No | T4: Vacio | U4: No | V4: Mostrar
A5: ='M-TipoMulta'!C3 -> descripcion | B5: ='M-TipoMulta'!C2 -> Representa que hace cada tipo de multa | C5: No | D5: Alfanumérico | E5: Si | F5: 10 | G5: 300 | H5: No aplica | I5: No aplica | J5: No aplica | K5: No aplica | L5: No aplica | M5: No aplica | N5: No | O5: No | P5: No aplica | Q5: Si | R5: Si | S5: No | T5: Vacio | U5: No | V5: Mostrar
A7: Nombre combinación única | B7: Descripción | C7: Atributos involucrados
A8: ='M-TipoMulta'!D3 -> Combinación única | B8: ='M-TipoMulta'!D2 -> Combinación única indica que no puede existir más de un tipo de multa con el mismo nombre | C8: nombre
A10: Responsabilidad | C10: Descripción | G10: Entradas | J10: Salida | O10: Políticas (Reglas de Negocio) | Q10: Excepción
G11: Parámetro | H11: Tipo de dato | I11: Descripción | J11: Tipo de Dato | K11: Descripción | O11: Política | P11: Descripción | Q11: Detalle | R11: ¿Qué hago?
A12: consultarTodosLosTiposMulta | C12: Permite consultar los tipos de multa que puede recibir un cliente | J12: Lista<TipoMulta> | K12: Contiene todos los tipos de multa que hay

Sheet P-TipoMulta
A1: << Ir al modelo de dominio | B1: << Ir al listado de objetos de dominio | C1: << Ir a la caracterización del objeto de dominio | D1: Ir al muestreo de datos del objeto de dominio >> | E1: Ir al event storming del objeto de dominio >>
A2: Objeto de Dominio: | B2: ='Objetos de Dominio'!A8 -> TipoMulta
A3: Descripción: | B3: ='Objetos de Dominio'!B8 -> Representa los tipos de multa que puede recibir un cliente: por tardanza o por inasistencia.
A4: Numero politica | B4: Descripcion politica | D4: Objeto responsable | E4: Regla responsable
B6: No aplica: es un catálogo de solo lectura, sin comandos que impliquen políticas de negocio propias

Sheet E-TipoMulta
A1: << Ir al modelo de dominio | C1: << Ir al listado de objetos de dominio | F1: << Ir a la caracterización del objeto de dominio | J1: Ir al muestreo de datos del objeto de dominio >>
A2: Objeto de Dominio: | B2: ='Objetos de Dominio'!A8 -> TipoMulta
A3: Descripción: | B3: ='Objetos de Dominio'!B8 -> Representa los tipos de multa que puede recibir un cliente: por tardanza o por inasistencia.
A4: Actor | B4: Action/Command | D4: Entity/Aggregate/Object domain | E4: Read Model | G4: Business Rule/Policy | I4: External System | J4: Domain Event | K4: Hotspot/questions/Risk
A5: Actor | B5: Acción | C5: Descripción | D5: Objeto de dominio | E5: Información externa | G5: Políticas | I5: Sistema Externo | J5: Evento | K5: Aspectos por solucionar
E6: Información | F6: Descripción | G6: Número | H6: Descripción
A7: Administrador | B7: Ver tipos de multa | C7: Permite consultar los tipos de multa que puede recibir un cliente | D7: =$B$2 -> TipoMulta | J7: Tipos de multa consultados
A8: Barbero | B8: Ver tipos de multa | C8: Permite consultar los tipos de multa que puede recibir un cliente | D8: =$B$2 -> TipoMulta | J8: Tipos de multa consultados
A9: Cliente | B9: Ver tipos de multa | C9: Permite consultar los tipos de multa que puede recibir un cliente | D9: =$B$2 -> TipoMulta | J9: Tipos de multa consultados

Sheet M-TipoMulta
A1: <<<< Ir al modulo de dominio | B1: <<<< Ir a objetos de dominio
A2: Representa un identificador que hará unico cada objeto de dominio de este tipo, no se puede repetir | B2: Representa el nombre del tipo de multa | C2: Representa que hace cada tipo de multa | D2: Combinación única indica que no puede existir más de un tipo de multa con el mismo nombre
A3: id | B3: nombre | C3: descripcion | D3: Combinación única
A4: 1 | B4: Tardanza | C4: El cliente llegó a la cita después de la hora acordada, superando los minutos de tiempoEspera definidos en la cita. | D4: =B4 -> Tardanza
A5: 2 | B5: Inasistencia | C5: El cliente no se presentó a la cita agendada: se llegó a la hora estimada de finalización sin que hubiera registrado su llegada. | D5: =B5 -> Inasistencia
B11: Corresponde a la descripcion de los atributos
B12: Corresponde al identificador unico del objeto de dominio
B13: Corresponde a los datos del objeto de dominio
B14: Corresponde a la combinacion única

Sheet C-TipoRegistroHora
A1: <<<< Ir al modulo de dominio | B1: <<<< Ir a objetos de dominio
A2: Nombre atributo | B2: Descripción atributo | C2: Identificador del objeto de dominio | D2: Tipo de dato | E2: Obligatorio | F2: Longitud mínima (si aplica) | G2: Longitud máxima (si aplica) | H2: Precisión (si aplica) | I2: Rendondeo (si aplica) | J2: Rango inicial (si aplica) | K2: Rango final (si aplica) | L2: Formato (si aplica) | M2: Reglas especiales (si aplica) | N2: Dato calculado | O2: Aplica ajuste del dato (si aplica) | P2: Carácter de ajuste (si aplica) | Q2: Quitar espacios en blanco al inicio (si aplica) | R2: Quitar espacios en blanco al fin (si aplica) | S2: Dato sensible (si aplica) | T2: Valor por defecto (si aplica) | U2: Auto generado | V2: =A11 -> consultarTiposRegistroHora
A3: ='M-TipoRegistroHora'!A3 -> id | B3: ='M-TipoRegistroHora'!A2 -> Representa un identificador que hará unico cada objeto de dominio de este tipo, no se puede repetir | C3: Si | D3: Identificador único universal | E3: Si | F3: No aplica | G3: No aplica | H3: No aplica | I3: No aplica | J3: No aplica | K3: No aplica | L3: No aplica | M3: No aplica | N3: No | O3: No aplica | P3: No aplica | Q3: No aplica | R3: No aplica | S3: No | T3: UUID vacio | U3: Si | V3: No mostrar
A4: ='M-TipoRegistroHora'!B3 -> nombre | B4: ='M-TipoRegistroHora'!B2 -> Representa el nombre del tipo de hora real que se puede registrar durante una cita | C4: No | D4: Alfanumérico | E4: Si | F4: 15 | G4: 20 | H4: No aplica | I4: No aplica | J4: No aplica | K4: No aplica | L4: No aplica | M4: Permite los caracteres de la 'a' a la 'z', incluidas mayusculas, espacios en blanco y todas las letras con tilde | N4: No | O4: No aplica | P4: No aplica | Q4: Si | R4: Si | S4: No | T4: Vacio | U4: No | V4: Mostrar
A6: Nombre combinación única | B6: Descripción | C6: Atributos involucrados
A7: ='M-TipoRegistroHora'!C3 -> Combinación única | B7: ='M-TipoRegistroHora'!C2 -> Combinación única que indica que no puede existir más de un tipo de registro de hora con el mismo nombre | C7: =A4 -> nombre
A9: Responsabilidad | C9: Descripción | G9: Entradas | J9: Salida | O9: Políticas (Reglas de Negocio) | Q9: Excepción
G10: Parámetro | H10: Tipo de dato | I10: Descripción | J10: Tipo de Dato | K10: Descripción | O10: Política | P10: Descripción | Q10: Detalle | R10: ¿Qué hago?
A11: consultarTiposRegistroHora | C11: Permite consultar el catálogo de tipos de registro de hora de una cita | J11: Lista<TipoRegistroHora> | K11: Contiene todos los tipos de registro de hora

Sheet P-TipoRegistroHora
A1: << Ir al modelo de dominio | B1: << Ir al listado de objetos de dominio | C1: << Ir a la caracterización del objeto de dominio | D1: Ir al muestreo de datos del objeto de dominio >> | E1: Ir al event storming del objeto de dominio >>
A2: Objeto de Dominio: | B2: ='Objetos de Dominio'!A9 -> TipoRegistroHora
A3: Descripción: | B3: ='Objetos de Dominio'!B9 -> Representa el catálogo de los distintos momentos en que se puede registrar una hora real durante una cita: llegada del cliente, barbero preparado, inicio y fin de la atención.
A4: Numero politica | B4: Descripcion politica | D4: Objeto responsable | E4: Regla responsable
B6: No aplica: es un catálogo de solo lectura, sin comandos que impliquen políticas de negocio propias

Sheet E-TipoRegistroHora
A1: << Ir al modelo de dominio | C1: << Ir al listado de objetos de dominio | F1: << Ir a la caracterización del objeto de dominio | J1: Ir al muestreo de datos del objeto de dominio >>
A2: Objeto de Dominio: | B2: ='Objetos de Dominio'!A9 -> TipoRegistroHora
A3: Descripción: | B3: ='Objetos de Dominio'!B9 -> Representa el catálogo de los distintos momentos en que se puede registrar una hora real durante una cita: llegada del cliente, barbero preparado, inicio y fin de la atención.
A4: Actor | B4: Action/Command | D4: Entity/Aggregate/Object domain | E4: Read Model | G4: Business Rule/Policy | I4: External System | J4: Domain Event | K4: Hotspot/questions/Risk
A5: Actor | B5: Acción | C5: Descripción | D5: Objeto de dominio | E5: Información externa | G5: Políticas | I5: Sistema Externo | J5: Evento | K5: Aspectos por solucionar
E6: Información | F6: Descripción | G6: Número | H6: Descripción
A7: Sistema | B7: Ver tipos de registro de hora para la cita | C7: Permite consultar el catálogo de tipos de registro de hora de una cita (llegada del cliente, barbero preparado, inicio y fin de la atención) | D7: =$B$2 -> TipoRegistroHora | J7: Tipos de registro de hora consultados
A8: Barbero | B8: Ver tipos de registro de hora para la cita | C8: Permite consultar el catálogo de tipos de registro de hora de una cita (llegada del cliente, barbero preparado, inicio y fin de la atención) | D8: =$B$2 -> TipoRegistroHora | J8: Tipos de registro de hora consultados

Sheet M-TipoRegistroHora
A1: <<<< Ir al modulo de dominio | B1: <<<< Ir a objetos de dominio
A2: Representa un identificador que hará unico cada objeto de dominio de este tipo, no se puede repetir | B2: Representa el nombre del tipo de hora real que se puede registrar durante una cita | C2: Combinación única que indica que no puede existir más de un tipo de registro de hora con el mismo nombre
A3: id | B3: nombre | C3: Combinación única
A4: 1 | B4: Llegada del cliente | C4: =B4 -> Llegada del cliente
A5: 2 | B5: Barbero preparado | C5: =B5 -> Barbero preparado
A6: 3 | B6: Inicio de atención | C6: =B6 -> Inicio de atención
A7: 4 | B7: Fin de atención | C7: =B7 -> Fin de atención
B13: Corresponde a la descripcion de los atributos
B14: Corresponde al identificador unico del objeto de dominio
B15: Corresponde a los datos del objeto de dominio
B16: Corresponde a la combinacion única

Sheet C-Cliente
A1: <<<< Ir al modulo de dominio | B1: <<<< Ir a objetos de dominio
A2: Nombre atributo | B2: Descripción atributo | C2: Identificador del objeto de dominio | D2: Tipo de dato | E2: Obligatorio | F2: Longitud mínima (si aplica) | G2: Longitud máxima (si aplica) | H2: Precisión (si aplica) | I2: Rendondeo (si aplica) | J2: Rango inicial (si aplica) | K2: Rango final (si aplica) | L2: Formato (si aplica) | M2: Reglas especiales (si aplica) | N2: Dato calculado | O2: Aplica ajuste del dato (si aplica) | P2: Carácter de ajuste (si aplica) | Q2: Quitar espacios en blanco al inicio (si aplica) | R2: Quitar espacios en blanco al fin (si aplica) | S2: Dato sensible (si aplica) | T2: Valor por defecto (si aplica) | U2: Auto generado | V2: =A21 -> registrarCliente | W2: =A23 -> editarContactoCliente | Y2: =A26 -> consultarDatosCliente | Z2: =A27 -> consultarEstadoVetoCliente | AA2: =A28 -> consultarCantidadMultasSinPagar | AB2: =A29 -> vetarCliente | AD2: =A31 -> quitarVetoCliente
A3: ='M-Cliente'!A3 -> id | B3: ='M-Cliente'!A2 -> Representa un identificador que hará unico cada objeto de dominio de este tipo, no se puede repetir | C3: Si | D3: Identificador único universal | E3: Si | F3: No aplica | G3: No aplica | H3: No aplica | I3: No aplica | J3: No aplica | K3: No aplica | L3: No aplica | M3: No aplica | N3: Si | O3: No | P3: No aplica | Q3: No aplica | R3: No aplica | S3: No | T3: UUID vacio | U3: Si | V3: No requerido | W3: Requerido | X3: No modificable | Y3: No mostrar | Z3: No mostrar | AA3: No mostrar | AB3: Requerido | AC3: No modificable | AD3: Requerido | AE3: No modificable
A4: ='M-Cliente'!B3 -> primerNombre | B4: ='M-Cliente'!B2 -> Representa el primer nombre de la persona, que va a estar llendo a la barberia para las citas | C4: No | D4: Alfanumérico | E4: Si | F4: 3 | G4: 50 | H4: No aplica | I4: No aplica | J4: No aplica | K4: No aplica | L4: No aplica | M4: Solo se aceptan caracteres de letras de la 'a' a la 'z', caracteres con tilde y numeros del 0 al 9 | N4: No | O4: No | P4: No | Q4: Si | R4: Si | S4: No | T4: Vacio | U4: No | V4: Requerido | W4: No requerido | X4: No modificable | Y4: Mostrar | Z4: No mostrar | AA4: No mostrar | AB4: No requerido | AC4: No modificable | AD4: No requerido | AE4: No modificable
A5: ='M-Cliente'!C3 -> segundoNombre | B5: ='M-Cliente'!C2 -> Representa el segundo nombre de la persona, que va a estar llendo a la barberia para las citas | C5: No | D5: Alfanumérico | E5: No | F5: 0 | G5: 50 | H5: No aplica | I5: No aplica | J5: No aplica | K5: No aplica | L5: No aplica | M5: Solo se aceptan caracteres de letras de la 'a' a la 'z', caracteres con tilde y numeros del 0 al 9 | N5: No | O5: No | P5: No | Q5: Si | R5: Si | S5: No | T5: Vacio | U5: No | V5: No requerido | W5: No requerido | X5: No modificable | Y5: Mostrar | Z5: No mostrar | AA5: No mostrar | AB5: No requerido | AC5: No modificable | AD5: No requerido | AE5: No modificable
A6: ='M-Cliente'!D3 -> primerApellido | B6: ='M-Cliente'!D2 -> Representa el primer apellido de la persona, que va a estar llendo a la barberia para las citas | C6: No | D6: Alfanumérico | E6: Si | F6: 3 | G6: 50 | H6: No aplica | I6: No aplica | J6: No aplica | K6: No aplica | L6: No aplica | M6: Solo se aceptan caracteres de letras de la 'a' a la 'z', caracteres con tilde y numeros del 0 al 9 | N6: No | O6: No | P6: No | Q6: Si | R6: Si | S6: No | T6: Vacio | U6: No | V6: Requerido | W6: No requerido | X6: No modificable | Y6: Mostrar | Z6: No mostrar | AA6: No mostrar | AB6: No requerido | AC6: No modificable | AD6: No requerido | AE6: No modificable
A7: ='M-Cliente'!E3 -> segundoApellido | B7: ='M-Cliente'!E2 -> Representa el segundo apellido de la persona, que va a estar llendo a la barberia para las citas | C7: No | D7: Alfanumérico | E7: No | F7: 0 | G7: 50 | H7: No aplica | I7: No aplica | J7: No aplica | K7: No aplica | L7: No aplica | M7: Solo se aceptan caracteres de letras de la 'a' a la 'z', caracteres con tilde y numeros del 0 al 9 | N7: No | O7: No | P7: No | Q7: Si | R7: Si | S7: No | T7: Vacio | U7: No | V7: No requerido | W7: No requerido | X7: No modificable | Y7: Mostrar | Z7: No mostrar | AA7: No mostrar | AB7: No requerido | AC7: No modificable | AD7: No requerido | AE7: No modificable
A8: ='M-Cliente'!F3 -> prefijoCelular | B8: ='M-Cliente'!F2 -> Representa cual es el prefijo del numero de celular del cliente | C8: No | D8: PrefijoCelular | E8: Si | F8: No aplica | G8: No aplica | H8: No aplica | I8: No aplica | J8: No aplica | K8: No aplica | L8: No aplica | M8: Aplican las reglas del objeto referenciado | N8: No | O8: No aplica | P8: No aplica | Q8: No aplica | R8: No aplica | S8: No | T8: UUID vacio | U8: No | V8: Requerido | W8: Requerido | X8: Modificable | Y8: Mostrar | Z8: No mostrar | AA8: No mostrar | AB8: No requerido | AC8: No modificable | AD8: No requerido | AE8: No modificable
A9: ='M-Cliente'!G3 -> celular | B9: ='M-Cliente'!G2 -> Representa el numero de celular del cliente, es el dato que el barbero necesita en caso de que tenga que contactarse con el | C9: No | D9: Alfanumérico | E9: Si | F9: 6 | G9: 15 | H9: No aplica | I9: No aplica | J9: No aplica | K9: No aplica | L9: No aplica | M9: Solo se aceptan caracteres de numeros del '0' al '9' | N9: No | O9: No aplica | P9: No aplica | Q9: Si | R9: Si | S9: Si | T9: 0 | U9: No | V9: Requerido | W9: Requerido | X9: Modificable | Y9: Mostrar | Z9: No mostrar | AA9: No mostrar | AB9: No requerido | AC9: No modificable | AD9: No requerido | AE9: No modificable
A10: ='M-Cliente'!H3 -> elNumeroCelularEsCorrecto | B10: ='M-Cliente'!H2 -> Representa si el numero que ingreso el cliente es correcto o no | C10: No | D10: Lógico | E10: Si | F10: No aplica | G10: No aplica | H10: No aplica | I10: No aplica | J10: No aplica | K10: No aplica | L10: No aplica | M10: No aplica | N10: No | O10: No aplica | P10: No aplica | Q10: No aplica | R10: No aplica | S10: No | T10: No | U10: No | V10: No requerido | W10: No requerido | X10: Modificable | Y10: Mostrar | Z10: No mostrar | AA10: No mostrar | AB10: No requerido | AC10: No modificable | AD10: No requerido | AE10: No modificable
A11: ='M-Cliente'!I3 -> estaVetado | B11: ='M-Cliente'!I2 -> Representa si el cliente esta en estado de veto o no, cuando el cliente esta vetado el sistema no va a permitir agendar citas con este cliente con ningun barbero | C11: No | D11: Lógico | E11: Si | F11: No aplica | G11: No aplica | H11: No aplica | I11: No aplica | J11: No aplica | K11: No aplica | L11: No aplica | M11: Se calcula a partir de multasSinPagar: basta con una multa sin pagar para que el cliente quede vetado y no pueda agendar; deja de estarlo en el momento en que la paga | N11: Si | O11: No | P11: No aplica | Q11: No aplica | R11: No aplica | S11: No | T11: No | U11: No | V11: No requerido | W11: No requerido | X11: No modificable | Y11: Mostrar | Z11: Mostrar | AA11: No mostrar | AB11: No requerido | AC11: Modificable | AD11: No requerido | AE11: Modificable
A13: Nombre combinación única | B13: Descripción | C13: Atributos involucrados
A14: ='M-Cliente'!J3 -> Combinación única 1 | B14: ='M-Cliente'!J2 -> Combinacion única que indica que no puede existir más de un cliente con el mismo prefijo de celular y número de celular | C14: =A8 -> prefijoCelular
C17: =A9 -> celular
A19: Responsabilidad | C19: Descripción | G19: Entradas | J19: Salida | O19: Políticas (Reglas de Negocio) | Q19: Excepción
G20: Parámetro | H20: Tipo de dato | I20: Descripción | J20: Tipo de Dato | K20: Descripción | O20: Política | P20: Descripción | Q20: Detalle | R20: ¿Qué hago?
A21: registrarCliente | C21: Comando que permite el registro de un nuevo cliente en la barbería | G21: datos{primerNombre, segundoNombre, primerApellido, segundoApellido, prefijoCelular, celular} | H21: Cliente | I21: Contiene la información requerida para registrar un nuevo cliente en la barbería | J21: Cliente | K21: Contiene la información del cliente registrado | O21: ='P-Cliente'!A6 -> P-CLI-0001 | P21: ='P-Cliente'!B6 -> Asegurar que los datos requeridos del cliente (nombres, apellidos, prefijo de celular, celular) sean válidos en tipo de dato, longitud, obligatoriedad, formato y rango | Q21: Generar una excepción indicándole al usuario cuáles datos del cliente no cumplen con las reglas definidas | R21: Detener operación
O22: ='P-Cliente'!A7 -> P-CLI-0002 | P22: ='P-Cliente'!B7 -> Asegurar que el número de celular y prefijo de celular no esté siendo utilizado por otro cliente | Q22: Generar una excepción indicándole al usuario que ya existe otro cliente registrado con ese prefijo y número de celular | R22: Detener operación
A23: editarContactoCliente | C23: Permite al cliente actualizar su número de celular y su prefijo | G23: id | H23: UUID | I23: Corresponde al identificador del cliente que va a editar su contacto | J23: Cliente | K23: Contiene la información del cliente con su contacto actualizado | O23: ='P-Cliente'!A10 -> P-CLI-0005 | P23: ='P-Cliente'!B10 -> Asegurar que exista el cliente con el id enviado | Q23: Informar con un mensaje que no existe un cliente con el identificador enviado y por lo tanto no es posible editar el contacto del cliente | R23: Detener operación
G24: datos{prefijoCelular, celular} | H24: Cliente | I24: Contiene el nuevo prefijo y número de celular del cliente | O24: ='P-Cliente'!A8 -> P-CLI-0003 | P24: ='P-Cliente'!B8 -> Asegurar que los datos requeridos del cliente para editar su contacto (prefijo de celular y celular) sean válidos en tipo de dato, longitud, obligatoriedad, formato y rango | Q24: Generar una excepción indicándole al usuario cuáles datos de contacto del cliente no cumplen con las reglas definidas | R24: Detener operación
A26: consultarDatosCliente | C26: Permite a un barbero ver los datos de un cliente que le va a pedir una cita | G26: id | H26: UUID | I26: Corresponde al identificador del cliente que se va a consultar | J26: Cliente | K26: Contiene la información del cliente consultado por su identificador | O26: ='P-Cliente'!A10 -> P-CLI-0005 | P26: ='P-Cliente'!B10 -> Asegurar que exista el cliente con el id enviado | Q26: Informar con un mensaje que no existe un cliente con el identificador enviado y por lo tanto no es posible llevar a cabo la operación | R26: Detener operación
A27: consultarEstadoVetoCliente | C27: Permite al cliente ver si tiene alguna multa sin pagar que le impida agendar nuevas citas | G27: id | H27: UUID | I27: Corresponde al identificador del cliente que se va a consultar | J27: Lógico | K27: Indica si el cliente está vetado o no para agendar nuevas citas | O27: ='P-Cliente'!A10 -> P-CLI-0005 | P27: ='P-Cliente'!B10 -> Asegurar que exista el cliente con el id enviado | Q27: Informar con un mensaje que no existe un cliente con el identificador enviado y por lo tanto no es posible llevar a cabo la operación | R27: Detener operación
A28: consultarCantidadMultasSinPagar | C28: Permite al cliente ver cuántas multas sin pagar tiene | G28: id | H28: UUID | I28: Corresponde al identificador del cliente que se va a consultar | J28: Entero | K28: Contiene la cantidad de multas sin pagar que tiene el cliente | O28: ='P-Cliente'!A10 -> P-CLI-0005 | P28: ='P-Cliente'!B10 -> Asegurar que exista el cliente con el id enviado | Q28: Informar con un mensaje que no existe un cliente con el identificador enviado y por lo tanto no es posible llevar a cabo la operación | R28: Detener operación
A29: vetarCliente | C29: Permite al sistema vetar a un cliente que tiene multas sin pagar, para que no pueda agendar nuevas citas | G29: id | H29: UUID | I29: Corresponde al identificador del cliente que se va a vetar | J29: No retorna ningún valor. En caso de error genera una excepción. | O29: ='P-Cliente'!A10 -> P-CLI-0005 | P29: ='P-Cliente'!B10 -> Asegurar que exista el cliente con el id enviado | Q29: Informar con un mensaje que no existe un cliente con el identificador enviado | R29: Detener operación
O30: ='P-Cliente'!A11 -> P-CLI-0006 | P30: ='P-Cliente'!B11 -> Asegurar que el cliente tenga al menos una multa sin pagar; si la tiene, se le debe dar el veto | Q30: No dar el veto porque el cliente no tiene multas sin pagar | R30: Detener operación
A31: quitarVetoCliente | C31: Permite al sistema quitar el veto a un cliente cuando ya no tiene multas sin pagar | G31: id | H31: UUID | I31: Corresponde al identificador del cliente al que se le va a quitar el veto | J31: No retorna ningún valor. En caso de error genera una excepción. | O31: ='P-Cliente'!A10 -> P-CLI-0005 | P31: ='P-Cliente'!B10 -> Asegurar que exista el cliente con el id enviado | Q31: Informar con un mensaje que no existe un cliente con el identificador enviado | R31: Detener operación
O32: ='P-Cliente'!A12 -> P-CLI-0007 | P32: ='P-Cliente'!B12 -> Asegurar que el cliente ya no tenga ninguna multa sin pagar; si es así, se le debe quitar el veto | Q32: No quitar el veto porque el cliente todavía tiene multas sin pagar | R32: Detener operación

Sheet P-Cliente
A1: << Ir al modelo de dominio | B1: << Ir al listado de objetos de dominio | C1: << Ir a la caracterización del objeto de dominio | D1: Ir al muestreo de datos del objeto de dominio >> | E1: Ir al event storming del objeto de dominio >>
A2: Objeto de Dominio: | B2: ='Objetos de Dominio'!A10 -> Cliente
A3: Descripción: | B3: ='Objetos de Dominio'!B10 -> Representa a la persona que solicita citas en la barbería.
A4: Numero politica | B4: Descripcion politica | D4: Objeto responsable | E4: Regla responsable
A6: P-CLI-0001 | B6: Asegurar que los datos requeridos del cliente (nombres, apellidos, prefijo de celular, celular) sean válidos en tipo de dato, longitud, obligatoriedad, formato y rango | D6: Cliente
A7: P-CLI-0002 | B7: Asegurar que el número de celular y prefijo de celular no esté siendo utilizado por otro cliente | D7: Cliente
A8: P-CLI-0003 | B8: Asegurar que los datos requeridos del cliente para editar su contacto (prefijo de celular y celular) sean válidos en tipo de dato, longitud, obligatoriedad, formato y rango | D8: Cliente
A9: P-CLI-0004 | B9: Asegurar que el cliente no tenga ninguna multa sin pagar antes de permitirle agendar una cita nueva; mientras la tenga permanece vetado | D9: Multa
A10: P-CLI-0005 | B10: Asegurar que exista el cliente con el id enviado | D10: Cliente
A11: P-CLI-0006 | B11: Asegurar que el cliente tenga al menos una multa sin pagar; si la tiene, se le debe dar el veto | D11: Multa
A12: P-CLI-0007 | B12: Asegurar que el cliente ya no tenga ninguna multa sin pagar; si es así, se le debe quitar el veto | D12: Multa

Sheet E-Cliente
A1: << Ir al modelo de dominio | C1: << Ir al listado de objetos de dominio | F1: << Ir a la caracterización del objeto de dominio | J1: Ir al muestreo de datos del objeto de dominio >>
A2: Objeto de Dominio: | B2: ='Objetos de Dominio'!A10 -> Cliente
A3: Descripción: | B3: ='Objetos de Dominio'!B10 -> Representa a la persona que solicita citas en la barbería.
A4: Actor | B4: Action/Command | D4: Entity/Aggregate/Object domain | E4: Read Model | G4: Business Rule/Policy | I4: External System | J4: Domain Event | K4: Hotspot/questions/Risk
A5: Actor | B5: Acción | C5: Descripción | D5: Objeto de dominio | E5: Información externa | G5: Políticas | I5: Sistema Externo | J5: Evento | K5: Aspectos por solucionar
E6: Información | F6: Descripción | G6: Número | H6: Descripción
A7: Cliente | B7: Registrar cliente a la barbería | C7: Comando que permite el registro de un nuevo cliente en la barbería | D7: =$B$2 -> Cliente | E7: PrefijoCelular | F7: Permite asignar el prefijo de país del número de celular del cliente. | G7: ='P-Cliente'!A6 -> P-CLI-0001 | H7: ='P-Cliente'!B6 -> Asegurar que los datos requeridos del cliente (nombres, apellidos, prefijo de celular, celular) sean válidos en tipo de dato, longitud, obligatoriedad, formato y rango | I7: WhatsApp | J7: Cliente registrado
G8: ='P-Cliente'!A7 -> P-CLI-0002 | H8: ='P-Cliente'!B7 -> Asegurar que el número de celular y prefijo de celular no esté siendo utilizado por otro cliente
A9: Cliente | B9: Editar contacto | C9: Permite al cliente actualizar su número de celular y su prefijo | D9: =$B$2 -> Cliente | E9: PrefijoCelular | F9: Permite actualizar el prefijo de país del número de celular. | G9: ='P-Cliente'!A8 -> P-CLI-0003 | H9: ='P-Cliente'!B8 -> Asegurar que los datos requeridos del cliente para editar su contacto (prefijo de celular y celular) sean válidos en tipo de dato, longitud, obligatoriedad, formato y rango | J9: Contacto de cliente actualizado
A10: Barbero | B10: Ver datos de un cliente | C10: Permite a un barbero ver los datos de un cliente que le va a pedir una cita | D10: =$B$2 -> Cliente | E10: PrefijoCelular | F10: Permite mostrar el número de celular completo con su prefijo. | J10: Datos del cliente vistos
A11: Cliente | B11: Ver estado de vetado | C11: Permite al cliente ver si tiene alguna multa sin pagar que le impida agendar nuevas citas | D11: =$B$2 -> Cliente | J11: Estado de veto del cliente visto
A12: Cliente | B12: Ver cantidad de multas sin pagar | C12: Permite al cliente ver cuántas multas sin pagar tiene | D12: =$B$2 -> Cliente | E12: Multa | F12: Permite contar las multas del cliente que siguen sin pagar. | J12: Multas sin pagar del cliente vistas
A13: Sistema | B13: Dar veto a un cliente | C13: Permite al sistema vetar a un cliente | D13: Cliente | E13: Multa | F13: Permite consultar las multas del cliente que siguen sin pagar (pagada = no). | G13: ='P-Cliente'!A11 -> P-CLI-0006 | H13: ='P-Cliente'!B11 -> Asegurar que el cliente tenga al menos una multa sin pagar; si la tiene, se le debe dar el veto | J13: Cliente vetado
A14: Sistema | B14: Quitar veto a un cliente | C14: Permite al sistema quitar el veto a un cliente cuando ya pagó todas sus multas | D14: Cliente | E14: Multa | F14: Permite consultar si el cliente todavía tiene multas sin pagar (pagada = no). | G14: ='P-Cliente'!A12 -> P-CLI-0007 | H14: ='P-Cliente'!B12 -> Asegurar que el cliente ya no tenga ninguna multa sin pagar; si es así, se le debe quitar el veto | J14: Veto de cliente retirado

Sheet M-Cliente
A1: <<<< Ir al modulo de dominio | B1: <<<< Ir a objetos de dominio
A2: Representa un identificador que hará unico cada objeto de dominio de este tipo, no se puede repetir | B2: Representa el primer nombre de la persona, que va a estar llendo a la barberia para las citas | C2: Representa el segundo nombre de la persona, que va a estar llendo a la barberia para las citas | D2: Representa el primer apellido de la persona, que va a estar llendo a la barberia para las citas | E2: Representa el segundo apellido de la persona, que va a estar llendo a la barberia para las citas | F2: Representa cual es el prefijo del numero de celular del cliente | G2: Representa el numero de celular del cliente, es el dato que el barbero necesita en caso de que tenga que contactarse con el | H2: Representa si el numero que ingreso el cliente es correcto o no | I2: Representa si el cliente esta en estado de veto o no, cuando el cliente esta vetado el sistema no va a permitir agendar citas con este cliente con ningun barbero | J2: Combinacion única que indica que no puede existir más de un cliente con el mismo prefijo de celular y número de celular
A3: id | B3: primerNombre | C3: segundoNombre | D3: primerApellido | E3: segundoApellido | F3: prefijoCelular | G3: celular | H3: elNumeroCelularEsCorrecto | I3: estaVetado | J3: Combinación única 1
A4: 1 | B4: Juan | D4: Gómez | F4: ='M-PrefijoCelular'!C4 -> +57 | G4: 3234528921 | H4: Si | I4: no | J4: =_xlfn.CONCAT(F4,"-",G4) -> +57-3234528921
A5: 2 | B5: Jose | C5: Miguel | D5: Ramirez | E5: Perez | F5: ='M-PrefijoCelular'!C4 -> +57 | G5: 3161657782 | H5: Si | I5: no | J5: =_xlfn.CONCAT(F5,"-",G5) -> +57-3161657782
A6: 3 | B6: Simon | D6: Ochoa | E6: Ramirez | F6: ='M-PrefijoCelular'!C4 -> +57 | G6: 3119884321 | H6: Si | I6: no | J6: =_xlfn.CONCAT(F6,"-",G6) -> +57-3119884321
A7: 4 | B7: Alexis | D7: Gallego | F7: ='M-PrefijoCelular'!C7 -> +58 | G7: 4127359182 | H7: Si | I7: no | J7: =_xlfn.CONCAT(F7,"-",G7) -> +58-4127359182
A8: 5 | B8: Kevin | C8: Andrés | D8: Muñoz | E8: Salazar | F8: ='M-PrefijoCelular'!C4 -> +57 | G8: 3005544332 | H8: Si | I8: si | J8: =_xlfn.CONCAT(F8,"-",G8) -> +57-3005544332
B14: Corresponde a la descripcion de los atributos
B15: Corresponde al identificador unico del objeto de dominio
B16: Corresponde a las referencias de otros objetos de dominio
B17: Corresponde a los datos calculados por el sistema
B18: Corresponde a los datos que ingresa el usuario
B19: Corresponde a la combinacion única

Sheet C-Ciudad
A1: <<<< Ir al modulo de dominio | B1: <<<< Ir a objetos de dominio
A2: Nombre atributo | B2: Descripción atributo | C2: Identificador del objeto de dominio | D2: Tipo de dato | E2: Obligatorio | F2: Longitud mínima (si aplica) | G2: Longitud máxima (si aplica) | H2: Precisión (si aplica) | I2: Rendondeo (si aplica) | J2: Rango inicial (si aplica) | K2: Rango final (si aplica) | L2: Formato (si aplica) | M2: Reglas especiales (si aplica) | N2: Dato calculado | O2: Aplica ajuste del dato (si aplica) | P2: Carácter de ajuste (si aplica) | Q2: Quitar espacios en blanco al inicio (si aplica) | R2: Quitar espacios en blanco al fin (si aplica) | S2: Dato sensible (si aplica) | T2: Valor por defecto (si aplica) | U2: Auto generado | V2: =A13 -> consultarCiudades
A3: ='M-Ciudad'!A3 -> id | B3: ='M-Ciudad'!A2 -> Representa un identificador que hará unico cada objeto de dominio de este tipo, no se puede repetir | C3: Si | D3: Identificador único universal | E3: Si | F3: No aplica | G3: No aplica | H3: No aplica | I3: No aplica | J3: No aplica | K3: No aplica | L3: No aplica | M3: No aplica | N3: No | O3: No aplica | P3: No aplica | Q3: No aplica | R3: No aplica | S3: No | T3: UUID vacio | U3: Si | V3: No mostrar
A4: ='M-Ciudad'!B3 -> nombre | B4: ='M-Ciudad'!B2 -> Representa el nombre de la ciudad en la que puede estar ubicada una sede de la barbería | C4: No | D4: Alfanumérico | E4: Si | F4: 3 | G4: 30 | H4: No aplica | I4: No aplica | J4: No aplica | K4: No aplica | L4: No aplica | M4: Permite caracterez de la 'a' a la 'z' minusculas y mayusculas, con espacios en blanco y esas letras pero con tilde | N4: No | O4: No aplica | P4: No aplica | Q4: Si | R4: Si | S4: No | T4: Vacio | U4: No | V4: Mostrar
A5: ='M-Ciudad'!C3 -> departamento | B5: ='M-Ciudad'!C2 -> Representa a qué departamento pertenece esta ciudad | C5: No | D5: Departamento | E5: Si | F5: No aplica | G5: No aplica | H5: No aplica | I5: No aplica | J5: No aplica | K5: No aplica | L5: No aplica | M5: Aplican las reglas del objeto referenciado | N5: No | O5: No aplica | P5: No aplica | Q5: No aplica | R5: No aplica | S5: No | T5: UUID vacio | U5: No | V5: Mostrar
A7: Nombre combinación única | B7: Descripción | C7: Atributos involucrados
A8: ='M-Ciudad'!D3 -> Combinación única | B8: ='M-Ciudad'!D2 -> Combinación única que indica que no puede existir más de una ciudad con el mismo nombre dentro de un mismo departamento | C8: =A4 -> nombre
C9: =A5 -> departamento
A11: Responsabilidad | C11: Descripción | G11: Entradas | J11: Salida | O11: Políticas (Reglas de Negocio) | Q11: Excepción
G12: Parámetro | H12: Tipo de dato | I12: Descripción | J12: Tipo de Dato | K12: Descripción | O12: Política | P12: Descripción | Q12: Detalle | R12: ¿Qué hago?
A13: consultarCiudades | C13: Permite consultar el catálogo de ciudades con su departamento | J13: Lista<Ciudad> | K13: Contiene todas las ciudades registradas con su departamento

Sheet P-Ciudad
A1: << Ir al modelo de dominio | B1: << Ir al listado de objetos de dominio | C1: << Ir a la caracterización del objeto de dominio | D1: Ir al muestreo de datos del objeto de dominio >> | E1: Ir al event storming del objeto de dominio >>
A2: Objeto de Dominio: | B2: ='Objetos de Dominio'!A11 -> Ciudad
A3: Descripción: | B3: ='Objetos de Dominio'!B11 -> Representa cada una de las ciudades, pertenecientes a un departamento, en las que puede estar ubicada una sede de la barbería.
A4: Numero politica | B4: Descripcion politica | D4: Objeto responsable | E4: Regla responsable
B6: No aplica: es un catálogo de solo lectura, sin comandos que impliquen políticas de negocio propias

Sheet E-Ciudad
A1: << Ir al modelo de dominio | C1: << Ir al listado de objetos de dominio | F1: << Ir a la caracterización del objeto de dominio | J1: Ir al muestreo de datos del objeto de dominio >>
A2: Objeto de Dominio: | B2: ='Objetos de Dominio'!A11 -> Ciudad
A3: Descripción: | B3: ='Objetos de Dominio'!B11 -> Representa cada una de las ciudades, pertenecientes a un departamento, en las que puede estar ubicada una sede de la barbería.
A4: Actor | B4: Action/Command | D4: Entity/Aggregate/Object domain | E4: Read Model | G4: Business Rule/Policy | I4: External System | J4: Domain Event | K4: Hotspot/questions/Risk
A5: Actor | B5: Acción | C5: Descripción | D5: Objeto de dominio | E5: Información externa | G5: Políticas | I5: Sistema Externo | J5: Evento | K5: Aspectos por solucionar
E6: Información | F6: Descripción | G6: Número | H6: Descripción
A7: Administrador | B7: Ver las ciudades | C7: Permite consultar el catálogo de ciudades, con su departamento, en las que se pueden ubicar las sedes | D7: =$B$2 -> Ciudad | E7: Departamento | F7: Permite mostrar el departamento al que pertenece cada ciudad. | J7: Ciudades consultadas

Sheet M-Ciudad
A1: <<<< Ir al modulo de dominio | B1: <<<< Ir a objetos de dominio
A2: Representa un identificador que hará unico cada objeto de dominio de este tipo, no se puede repetir | B2: Representa el nombre de la ciudad en la que puede estar ubicada una sede de la barbería | C2: Representa a qué departamento pertenece esta ciudad | D2: Combinación única que indica que no puede existir más de una ciudad con el mismo nombre dentro de un mismo departamento
A3: id | B3: nombre | C3: departamento | D3: Combinación única
A4: 1 | B4: Medellín | C4: ='M-Departamento'!C4 -> Antioquia | D4: =_xlfn.CONCAT(B4,"-",C4) -> Medellín-Antioquia
A5: 2 | B5: Rionegro | C5: ='M-Departamento'!C4 -> Antioquia | D5: =_xlfn.CONCAT(B5,"-",C5) -> Rionegro-Antioquia
A6: 3 | B6: Bogotá | C6: ='M-Departamento'!C5 -> Cundinamarca | D6: =_xlfn.CONCAT(B6,"-",C6) -> Bogotá-Cundinamarca
A7: 4 | B7: Cali | C7: ='M-Departamento'!C6 -> Valle del Cauca | D7: =_xlfn.CONCAT(B7,"-",C7) -> Cali-Valle del Cauca
A8: 5 | B8: Barranquilla | C8: ='M-Departamento'!C7 -> Atlántico | D8: =_xlfn.CONCAT(B8,"-",C8) -> Barranquilla-Atlántico
B14: Corresponde a la descripcion de los atributos
B15: Corresponde al identificador unico del objeto de dominio
B16: Corresponde a las referencias de otros objetos de dominio
B17: Corresponde a los datos de libre ingreso
B18: Corresponde a la combinacion única

Sheet C-Sede
A1: <<<< Ir al modulo de dominio | B1: <<<< Ir a objetos de dominio
A2: Nombre atributo | B2: Descripción atributo | C2: Identificador del objeto de dominio | D2: Tipo de dato | E2: Obligatorio | F2: Longitud mínima (si aplica) | G2: Longitud máxima (si aplica) | H2: Precisión (si aplica) | I2: Rendondeo (si aplica) | J2: Rango inicial (si aplica) | K2: Rango final (si aplica) | L2: Formato (si aplica) | M2: Reglas especiales (si aplica) | N2: Dato calculado | O2: Aplica ajuste del dato (si aplica) | P2: Carácter de ajuste (si aplica) | Q2: Quitar espacios en blanco al inicio (si aplica) | R2: Quitar espacios en blanco al fin (si aplica) | S2: Dato sensible (si aplica) | T2: Valor por defecto (si aplica) | U2: Auto generado | V2: =A15 -> registrarSede | W2: =A17 -> consultarDatosSede | X2: =A18 -> cambiarNombreSede | Z2: =A21 -> cambiarDireccionSede | AB2: =A23 -> darDeBajaSede
A3: ='M-Sede'!A3 -> id | B3: ='M-Sede'!A2 -> Representa un identificador que hará unico cada objeto de dominio de este tipo, no se puede repetir | C3: Si | D3: Identificador único universal | E3: Si | F3: No aplica | G3: No aplica | H3: No aplica | I3: No aplica | J3: No aplica | K3: No aplica | L3: No aplica | M3: No aplica | N3: No | O3: No aplica | P3: No aplica | Q3: No aplica | R3: No aplica | S3: No | T3: UUID vacio | U3: Si | V3: No requerido | W3: No mostrar | X3: Requerido | Y3: No modificable | Z3: Requerido | AA3: No modificable | AB3: Requerido
A4: ='M-Sede'!B3 -> ciudad | B4: ='M-Sede'!B2 -> Representa a qué ciudad pertenece esta sede | C4: No | D4: Ciudad | E4: Si | F4: No aplica | G4: No aplica | H4: No aplica | I4: No aplica | J4: No aplica | K4: No aplica | L4: No aplica | M4: Aplican las reglas del objeto referenciado | N4: No | O4: No aplica | P4: No aplica | Q4: No aplica | R4: No aplica | S4: No | T4: UUID vacio | U4: No | V4: Requerido | W4: Mostrar | X4: No requerido | Y4: No modificable | Z4: No requerido | AA4: No modificable | AB4: No requerido
A5: ='M-Sede'!C3 -> barberia | B5: ='M-Sede'!C2 -> Representa a qué barbería pertenece esta sede | C5: No | D5: Barberia | E5: Si | F5: No aplica | G5: No aplica | H5: No aplica | I5: No aplica | J5: No aplica | K5: No aplica | L5: No aplica | M5: Aplican las reglas del objeto referenciado | N5: No | O5: No aplica | P5: No aplica | Q5: No aplica | R5: No aplica | S5: No | T5: UUID vacio | U5: No | V5: Requerido | W5: No mostrar | X5: No requerido | Y5: No modificable | Z5: No requerido | AA5: No modificable | AB5: No requerido
A6: ='M-Sede'!D3 -> nombre | B6: ='M-Sede'!D2 -> Representa el nombre con el que se identifica esta sede dentro de la barbería a la que pertenece | C6: No | D6: Alfanumérico | E6: Si | F6: 2 | G6: 50 | H6: No aplica | I6: No aplica | J6: No aplica | K6: No aplica | L6: No aplica | M6: Pensarlo | N6: No | O6: No aplica | P6: No aplica | Q6: Si | R6: Si | S6: No | T6: Vacio | U6: No | V6: Requerido | W6: Mostrar | X6: Requerido | Y6: Modificable | Z6: No requerido | AA6: No modificable | AB6: No requerido
A7: ='M-Sede'!E3 -> direccion | B7: ='M-Sede'!E2 -> Representa la dirección física en la que está ubicada esta sede | C7: No | D7: Alfanumérico | E7: Si | F7: 5 | G7: 100 | H7: No aplica | I7: No aplica | J7: No aplica | K7: No aplica | L7: Tipo de vía + número de vía + letra/sufijo (si aplica) + # + número de vía generadora + letra/sufijo (si aplica) + - + número de placa + complemento (si aplica). Por ejemplo: Carrera 30A # 10-21 Apartamento 201 | M7: Permite caracterez de la 'a' a la 'z' minusculas y mayusculas, espacios en blanco y el carácter '#' | N7: No | O7: No aplica | P7: No aplica | Q7: Si | R7: Si | S7: No | T7: Vacio | U7: No | V7: Requerido | W7: Mostrar | X7: No requerido | Y7: No modificable | Z7: Requerido | AA7: Modificable | AB7: No requerido
A9: Nombre combinación única | B9: Descripción | C9: Atributos involucrados
A10: ='M-Sede'!F3 -> Combinación única | B10: ='M-Sede'!F2 -> Combinación única que indica que una misma barbería no puede tener dos sedes con el mismo nombre | C10: =A5 -> barberia
C11: =A6 -> nombre
A13: Responsabilidad | C13: Descripción | G13: Entradas | J13: Salida | O13: Políticas (Reglas de Negocio) | Q13: Excepción
G14: Parámetro | H14: Tipo de dato | I14: Descripción | J14: Tipo de Dato | K14: Descripción | O14: Política | P14: Descripción | Q14: Detalle | R14: ¿Qué hago?
A15: registrarSede | C15: Comando que permite registrar una nueva sede de una barbería en una ciudad | G15: datos{barberia, ciudad, nombre, direccion} | H15: Sede | I15: Contiene la información requerida para registrar la sede | J15: Sede | K15: Contiene la información de la sede registrada | O15: ='P-Sede'!A6 -> P-SED-0001 | P15: ='P-Sede'!B6 -> Asegurar que los datos requeridos de la sede (barbería, ciudad, nombre, dirección) sean válidos en tipo de dato, longitud, obligatoriedad, formato y rango | Q15: Generar una excepción indicándole al administrador cuáles datos de la sede no cumplen con las reglas definidas | R15: Detener operación
O16: ='P-Sede'!A7 -> P-SED-0002 | P16: ='P-Sede'!B7 -> Asegurar que no exista otra sede con el mismo nombre en la misma barbería | Q16: Generar una excepción indicándole al administrador que ya existe una sede con ese nombre en la barbería | R16: Detener operación
A17: consultarDatosSede | C17: Permite consultar el nombre y la dirección de una sede | G17: id | H17: UUID | I17: Corresponde al identificador de la sede que se va a consultar | J17: Sede | K17: Contiene el nombre, la dirección y la ciudad de la sede | O17: ='P-Sede'!A8 -> P-SED-0003 | P17: ='P-Sede'!B8 -> Asegurar que exista la sede con el id enviado | Q17: Informar con un mensaje que no existe una sede con el identificador enviado y por lo tanto no se puede realizar la operación | R17: Detener operación
A18: cambiarNombreSede | C18: Permite al administrador cambiar el nombre de la sede | G18: id | H18: UUID | I18: Corresponde al identificador de la sede | J18: Sede | K18: Contiene la sede con su nombre actualizado | O18: ='P-Sede'!A8 -> P-SED-0003 | P18: ='P-Sede'!B8 -> Asegurar que exista la sede con el id enviado | Q18: Informar con un mensaje que no existe una sede con el identificador enviado y por lo tanto no se puede realizar la operación | R18: Detener operación
G19: datos{nombre} | H19: Sede | I19: Contiene el nuevo nombre de la sede | O19: ='P-Sede'!A6 -> P-SED-0001 | P19: ='P-Sede'!B6 -> Asegurar que los datos requeridos de la sede (barbería, ciudad, nombre, dirección) sean válidos en tipo de dato, longitud, obligatoriedad, formato y rango | Q19: Generar una excepción indicándole al administrador cuáles datos de la sede no cumplen con las reglas definidas | R19: Detener operación
O20: ='P-Sede'!A7 -> P-SED-0002 | P20: ='P-Sede'!B7 -> Asegurar que no exista otra sede con el mismo nombre en la misma barbería | Q20: Generar una excepción indicándole al administrador que ya existe una sede con ese nombre en la barbería | R20: Detener operación
A21: cambiarDireccionSede | C21: Permite al administrador cambiar la dirección de la sede | G21: id | H21: UUID | I21: Corresponde al identificador de la sede | J21: Sede | K21: Contiene la sede con su dirección actualizada | O21: ='P-Sede'!A8 -> P-SED-0003 | P21: ='P-Sede'!B8 -> Asegurar que exista la sede con el id enviado | Q21: Informar con un mensaje que no existe una sede con el identificador enviado y por lo tanto no se puede realizar la operación | R21: Detener operación
G22: datos{direccion} | H22: Sede | I22: Contiene la nueva dirección de la sede | O22: ='P-Sede'!A6 -> P-SED-0001 | P22: ='P-Sede'!B6 -> Asegurar que los datos requeridos de la sede (barbería, ciudad, nombre, dirección) sean válidos en tipo de dato, longitud, obligatoriedad, formato y rango | Q22: Generar una excepción indicándole al administrador cuáles datos de la sede no cumplen con las reglas definidas | R22: Detener operación
A23: darDeBajaSede | C23: Permite al administrador dar de baja una sede para que deje de operar | G23: id | H23: UUID | I23: Corresponde al identificador de la sede que se va a dar de baja | J23: No retorna ningún valor. En caso de error genera una excepción. | O23: ='P-Sede'!A8 -> P-SED-0003 | P23: ='P-Sede'!B8 -> Asegurar que exista la sede con el id enviado | Q23: Informar con un mensaje que no existe una sede con el identificador enviado y por lo tanto no se puede realizar la operación | R23: Detener operación
O24: ='P-Sede'!A9 -> P-SED-0004 | P24: ='P-Sede'!B9 -> Asegurar que la sede no tenga barberos trabajando actualmente en ella antes de darla de baja | Q24: Generar una excepción indicándole al administrador que la sede todavía tiene barberos trabajando en ella | R24: Detener operación
O25: ='P-Sede'!A10 -> P-SED-0005 | P25: ='P-Sede'!B10 -> Asegurar que la sede no tenga citas futuras en estado Agendada antes de darla de baja; las citas pasadas se conservan como historial | Q25: Generar una excepción indicándole al administrador que la sede tiene citas futuras agendadas | R25: Detener operación

Sheet P-Sede
A1: << Ir al modelo de dominio | B1: << Ir al listado de objetos de dominio | C1: << Ir a la caracterización del objeto de dominio | D1: Ir al muestreo de datos del objeto de dominio >> | E1: Ir al event storming del objeto de dominio >>
A2: Objeto de Dominio: | B2: ='Objetos de Dominio'!A12 -> Sede
A3: Descripción: | B3: ='Objetos de Dominio'!B12 -> Representa cada una de las sucursales físicas de una barbería, ubicada en una ciudad puntual, donde se ofrecen los servicios y trabajan los barberos.
A4: Numero politica | B4: Descripcion politica | D4: Objeto responsable | E4: Regla responsable
A6: P-SED-0001 | B6: Asegurar que los datos requeridos de la sede (barbería, ciudad, nombre, dirección) sean válidos en tipo de dato, longitud, obligatoriedad, formato y rango | D6: Sede
A7: P-SED-0002 | B7: Asegurar que no exista otra sede con el mismo nombre en la misma barbería | D7: Sede
A8: P-SED-0003 | B8: Asegurar que exista la sede con el id enviado | D8: Sede
A9: P-SED-0004 | B9: Asegurar que la sede no tenga barberos trabajando actualmente en ella antes de darla de baja | D9: Barbero
A10: P-SED-0005 | B10: Asegurar que la sede no tenga citas futuras en estado Agendada antes de darla de baja; las citas pasadas se conservan como historial | D10: Cita

Sheet E-Sede
A1: << Ir al modelo de dominio | C1: << Ir al listado de objetos de dominio | F1: << Ir a la caracterización del objeto de dominio | J1: Ir al muestreo de datos del objeto de dominio >>
A2: Objeto de Dominio: | B2: ='Objetos de Dominio'!A12 -> Sede
A3: Descripción: | B3: ='Objetos de Dominio'!B12 -> Representa cada una de las sucursales físicas de una barbería, ubicada en una ciudad puntual, donde se ofrecen los servicios y trabajan los barberos.
A4: Actor | B4: Action/Command | D4: Entity/Aggregate/Object domain | E4: Read Model | G4: Business Rule/Policy | I4: External System | J4: Domain Event | K4: Hotspot/questions/Risk
A5: Actor | B5: Acción | C5: Descripción | D5: Objeto de dominio | E5: Información externa | G5: Políticas | I5: Sistema Externo | J5: Evento | K5: Aspectos por solucionar
E6: Información | F6: Descripción | G6: Número | H6: Descripción
A7: Administrador | B7: Registrar sede | C7: Comando que permite al administrador registrar una nueva sede de una barbería en una ciudad | D7: =$B$2 -> Sede | E7: Barberia | F7: Permite asociar la sede a la barbería a la que pertenece. | G7: ='P-Sede'!A6 -> P-SED-0001 | H7: ='P-Sede'!B6 -> Asegurar que los datos requeridos de la sede (barbería, ciudad, nombre, dirección) sean válidos en tipo de dato, longitud, obligatoriedad, formato y rango | J7: Sede registrada
E8: Ciudad | F8: Permite asignar la ciudad donde queda la sede. | G8: ='P-Sede'!A7 -> P-SED-0002 | H8: ='P-Sede'!B7 -> Asegurar que no exista otra sede con el mismo nombre en la misma barbería
A9: Administrador | B9: Ver nombre y direccion de la sede | C9: Permite al administrador consultar el nombre y la dirección de la sede | D9: =$B$2 -> Sede | E9: Ciudad | F9: Permite mostrar la ciudad en la que queda la sede. | J9: Nombre y dirección de sede consultados
A10: Barbero | B10: Ver nombre y direccion de la sede | C10: Permite al barbero consultar el nombre y la dirección de la sede | D10: =$B$2 -> Sede | E10: Ciudad | F10: Permite mostrar la ciudad en la que queda la sede. | J10: Nombre y dirección de sede consultados
A11: Cliente | B11: Ver nombre y direccion de la sede | C11: Permite al cliente consultar el nombre y la dirección de la sede | D11: =$B$2 -> Sede | E11: Ciudad | F11: Permite mostrar la ciudad en la que queda la sede. | J11: Nombre y dirección de sede consultados
A12: Administrador | B12: Cambiar nombre de la sede | C12: Permite al administrador cambiar el nombre de la sede | D12: =$B$2 -> Sede | G12: ='P-Sede'!A8 -> P-SED-0003 | H12: ='P-Sede'!B8 -> Asegurar que exista la sede con el id enviado | J12: Nombre de sede cambiado
G13: ='P-Sede'!A6 -> P-SED-0001 | H13: ='P-Sede'!B6 -> Asegurar que los datos requeridos de la sede (barbería, ciudad, nombre, dirección) sean válidos en tipo de dato, longitud, obligatoriedad, formato y rango
G14: ='P-Sede'!A7 -> P-SED-0002 | H14: ='P-Sede'!B7 -> Asegurar que no exista otra sede con el mismo nombre en la misma barbería
A15: Administrador | B15: Cambiar la direccion de la sede | C15: Permite al administrador cambiar la dirección de la sede | D15: =$B$2 -> Sede | G15: ='P-Sede'!A8 -> P-SED-0003 | H15: ='P-Sede'!B8 -> Asegurar que exista la sede con el id enviado | J15: Dirección de sede cambiada
G16: ='P-Sede'!A6 -> P-SED-0001 | H16: ='P-Sede'!B6 -> Asegurar que los datos requeridos de la sede (barbería, ciudad, nombre, dirección) sean válidos en tipo de dato, longitud, obligatoriedad, formato y rango
A17: Administrador | B17: Dar de baja la sede | C17: Permite al administrador dar de baja una sede para que deje de operar | D17: =$B$2 -> Sede | E17: Barbero | F17: Permite verificar que ningún barbero trabaje actualmente en la sede. | G17: ='P-Sede'!A8 -> P-SED-0003 | H17: ='P-Sede'!B8 -> Asegurar que exista la sede con el id enviado | J17: Sede dada de baja | K17: Pensarlo: Sede no tiene un atributo que indique si está activa (ej. vigente). Definir si se agrega para conservar el historial o si dar de baja elimina el registro.
E18: Cita | F18: Permite verificar que no existan citas futuras agendadas en la sede. | G18: ='P-Sede'!A9 -> P-SED-0004 | H18: ='P-Sede'!B9 -> Asegurar que la sede no tenga barberos trabajando actualmente en ella antes de darla de baja
E19: Agenda | F19: Permite conocer la fecha de cada cita para identificar cuáles son futuras (fecha y horaInicio posteriores al momento actual). | G19: ='P-Sede'!A10 -> P-SED-0005 | H19: ='P-Sede'!B10 -> Asegurar que la sede no tenga citas futuras en estado Agendada antes de darla de baja; las citas pasadas se conservan como historial

Sheet M-Sede
A1: <<<< Ir al modulo de dominio | B1: <<<< Ir a objetos de dominio
A2: Representa un identificador que hará unico cada objeto de dominio de este tipo, no se puede repetir | B2: Representa a qué ciudad pertenece esta sede | C2: Representa a qué barbería pertenece esta sede | D2: Representa el nombre con el que se identifica esta sede dentro de la barbería a la que pertenece | E2: Representa la dirección física en la que está ubicada esta sede | F2: Combinación única que indica que una misma barbería no puede tener dos sedes con el mismo nombre
A3: id | B3: ciudad | C3: barberia | D3: nombre | E3: direccion | F3: Combinación única
A4: 1 | B4: ='M-Ciudad'!D4 -> Medellín-Antioquia | C4: ='M-Barberia'!D4 -> 900123456-7 | D4: Sede Poblado | E4: Cra 43A #10-25 | F4: =_xlfn.CONCAT(C4,"-",D4) -> 900123456-7-Sede Poblado
A5: 2 | B5: ='M-Ciudad'!D4 -> Medellín-Antioquia | C5: ='M-Barberia'!D4 -> 900123456-7 | D5: Sede Laureles | E5: Cl 33 #70-12 | F5: =_xlfn.CONCAT(C5,"-",D5) -> 900123456-7-Sede Laureles
A6: 3 | B6: ='M-Ciudad'!D5 -> Rionegro-Antioquia | C6: ='M-Barberia'!D4 -> 900123456-7 | D6: Sede Rionegro | E6: Cl 45 #50-30 | F6: =_xlfn.CONCAT(C6,"-",D6) -> 900123456-7-Sede Rionegro
A7: 4 | B7: ='M-Ciudad'!D6 -> Bogotá-Cundinamarca | C7: ='M-Barberia'!D5 -> 900654321-9 | D7: Sede Centro | E7: Cra 7 #24-18 | F7: =_xlfn.CONCAT(C7,"-",D7) -> 900654321-9-Sede Centro
B13: Corresponde a la descripcion de los atributos
B14: Corresponde al identificador unico del objeto de dominio
B15: Corresponde a las referencias de otros objetos de dominio
B16: Corresponde a los datos que ingresa el administrador
B17: Corresponde a la combinacion única

Sheet C-Barbero
A1: <<<< Ir al modulo de dominio | B1: <<<< Ir a objetos de dominio
A2: Nombre atributo | B2: Descripción atributo | C2: Identificador del objeto de dominio | D2: Tipo de dato | E2: Obligatorio | F2: Longitud mínima (si aplica) | G2: Longitud máxima (si aplica) | H2: Precisión (si aplica) | I2: Rendondeo (si aplica) | J2: Rango inicial (si aplica) | K2: Rango final (si aplica) | L2: Formato (si aplica) | M2: Reglas especiales (si aplica) | N2: Dato calculado | O2: Aplica ajuste del dato (si aplica) | P2: Carácter de ajuste (si aplica) | Q2: Quitar espacios en blanco al inicio (si aplica) | R2: Quitar espacios en blanco al fin (si aplica) | S2: Dato sensible (si aplica) | T2: Valor por defecto (si aplica) | U2: Auto generado | V2: =A20 -> registrarBarbero | W2: =A23 -> editarContactoBarbero | Y2: =A26 -> consultarDatosBarbero | Z2: =A27 -> desactivarBarbero | AB2: =A29 -> reactivarBarbero | AD2: =A30 -> cambiarSedeDeTrabajoBarbero | AF2: =A32 -> consultarServiciosSedeBarbero
A3: ='M-Barbero'!A3 -> id | B3: ='M-Barbero'!A2 -> Representa un identificador que hará unico cada objeto de dominio de este tipo, no se puede repetir | C3: Si | D3: Identificador único universal | E3: Si | F3: No aplica | G3: No aplica | H3: No aplica | I3: No aplica | J3: No aplica | K3: No aplica | L3: No aplica | M3: No aplica | N3: No | O3: No aplica | P3: No aplica | Q3: No | R3: No | S3: No | T3: UUID vacio | U3: Si | V3: No requerido | W3: Requerido | X3: No modificable | Y3: No mostrar | Z3: Requerido | AA3: No modificable | AB3: Requerido | AC3: No modificable | AD3: Requerido | AE3: No modificable | AF3: Requerido
A4: ='M-Barbero'!B3 -> primerNombre | B4: ='M-Barbero'!B2 -> Representa el primer nombre del barbero que trabaja en barbería | C4: No | D4: Alfanumérico | E4: Si | F4: 3 | G4: 50 | H4: No aplica | I4: No aplica | J4: No aplica | K4: No aplica | L4: No aplica | M4: Solo se aceptan caracteres de letras de la 'a' a la 'z', caracteres con tilde y numeros del 0 al 9 | N4: No | O4: No | P4: No | Q4: Si | R4: Si | S4: No | T4: vacío | U4: No | V4: Requerido | W4: No requerido | X4: No modificable | Y4: Mostrar | Z4: No requerido | AA4: No modificable | AB4: No requerido | AC4: No modificable | AD4: No requerido | AE4: No modificable | AF4: No mostrar
A5: ='M-Barbero'!C3 -> segundoNombre | B5: ='M-Barbero'!C2 -> Representa el segundo nombre del barbero que trabaja en barbería | C5: No | D5: Alfanumérico | E5: No | F5: 0 | G5: 50 | H5: No aplica | I5: No aplica | J5: No aplica | K5: No aplica | L5: No aplica | M5: Solo se aceptan caracteres de letras de la 'a' a la 'z', caracteres con tilde y numeros del 0 al 9 | N5: No | O5: No | P5: No | Q5: Si | R5: Si | S5: No | T5: vacío | U5: No | V5: No requerido | W5: No requerido | X5: No modificable | Y5: Mostrar | Z5: No requerido | AA5: No modificable | AB5: No requerido | AC5: No modificable | AD5: No requerido | AE5: No modificable | AF5: No mostrar
A6: ='M-Barbero'!D3 -> primerApellido | B6: ='M-Barbero'!D2 -> Representa el primer apellido del barbero que trabaja en la barbería | C6: No | D6: Alfanumérico | E6: Si | F6: 3 | G6: 50 | H6: No aplica | I6: No aplica | J6: No aplica | K6: No aplica | L6: No aplica | M6: Solo se aceptan caracteres de letras de la 'a' a la 'z', caracteres con tilde y numeros del 0 al 9 | N6: No | O6: No | P6: No | Q6: Si | R6: Si | S6: No | T6: vacío | U6: No | V6: Requerido | W6: No requerido | X6: No modificable | Y6: Mostrar | Z6: No requerido | AA6: No modificable | AB6: No requerido | AC6: No modificable | AD6: No requerido | AE6: No modificable | AF6: No mostrar
A7: ='M-Barbero'!E3 -> segundoApellido | B7: ='M-Barbero'!E2 -> Representa el segundo apellido del barbero que trabaja en la barbería | C7: No | D7: Alfanumérico | E7: No | F7: 0 | G7: 50 | H7: No aplica | I7: No aplica | J7: No aplica | K7: No aplica | L7: No aplica | M7: Solo se aceptan caracteres de letras de la 'a' a la 'z', caracteres con tilde y numeros del 0 al 9 | N7: No | O7: No | P7: No | Q7: Si | R7: Si | S7: No | T7: vacío | U7: No | V7: No requerido | W7: No requerido | X7: No modificable | Y7: Mostrar | Z7: No requerido | AA7: No modificable | AB7: No requerido | AC7: No modificable | AD7: No requerido | AE7: No modificable | AF7: No mostrar
A8: ='M-Barbero'!F3 -> prefijo | B8: ='M-Barbero'!F2 -> Representa cual es el prefijo del numero de celular del barbero | C8: No | D8: PrefijoCelular | E8: Si | F8: No aplica | G8: No aplica | H8: No aplica | I8: No aplica | J8: No aplica | K8: No aplica | L8: No aplica | M8: Aplican las reglas del objeto referenciado | N8: No | O8: No aplica | P8: No aplica | Q8: No aplica | R8: No aplica | S8: No | T8: UUID vacio | U8: No | V8: Requerido | W8: Requerido | X8: Modificable | Y8: Mostrar | Z8: No requerido | AA8: No modificable | AB8: No requerido | AC8: No modificable | AD8: No requerido | AE8: No modificable | AF8: No mostrar
A9: ='M-Barbero'!G3 -> celular | B9: ='M-Barbero'!G2 -> Representa el número de celular del barbero, es el dato que el cliente necesita en caso de que tenga que contactarse con el | C9: No | D9: Alfanumérico | E9: Si | F9: 6 | G9: 15 | H9: No aplica | I9: No aplica | J9: No aplica | K9: No aplica | L9: No aplica | M9: Solo se aceptan caracteres de numeros del '0' al '9' | N9: No | O9: No aplica | P9: No aplica | Q9: Si | R9: Si | S9: Si | T9: 0 | U9: No | V9: Requerido | W9: Requerido | X9: Modificable | Y9: Mostrar | Z9: No requerido | AA9: No modificable | AB9: No requerido | AC9: No modificable | AD9: No requerido | AE9: No modificable | AF9: No mostrar
A10: ='M-Barbero'!H3 -> elNumeroCelularEsCorrecto | B10: ='M-Barbero'!H2 -> Representa si el numero que ingreso el cliente es correcto o no | C10: No | D10: Lógico | E10: Si | F10: No aplica | G10: No aplica | H10: No aplica | I10: No aplica | J10: No aplica | K10: No aplica | L10: No aplica | M10: El barbero debe de poner un si en este atributo | N10: No | O10: No aplica | P10: No aplica | Q10: No aplica | R10: No aplica | S10: No | T10: No | U10: No | V10: Requerido | W10: No requerido | X10: No modificable | Y10: No mostrar | Z10: Requerido | AA10: Modificable | AB10: Requerido | AC10: Modificable | AD10: No requerido | AE10: No modificable | AF10: No mostrar
A11: ='M-Barbero'!I3 -> vigente | B11: ='M-Barbero'!I2 -> Representa si el barbero sigue o no trabajando en la barberia | C11: No | D11: Lógico | E11: Si | F11: No aplica | G11: No aplica | H11: No aplica | I11: No aplica | J11: No aplica | K11: No aplica | L11: No aplica | M11: No aplica | N11: Si | O11: No aplica | P11: No aplica | Q11: No aplica | R11: No aplica | S11: No | T11: Si | U11: Si | V11: No requerido | W11: No requerido | X11: No modificable | Y11: Mostrar | Z11: No requerido | AA11: No modificable | AB11: No requerido | AC11: No modificable | AD11: No requerido | AE11: No modificable | AF11: No mostrar
A12: ='M-Barbero'!J3 -> sedeDeTrabajo | B12: ='M-Barbero'!J2 -> Representa cual es la sede y la barberia donde trabaja el barbero | C12: No | D12: Sede | E12: Si | F12: No aplica | G12: No aplica | H12: No aplica | I12: No aplica | J12: No aplica | K12: No aplica | L12: No aplica | M12: Aplican las reglas del objeto referenciado | N12: No | O12: No aplica | P12: No aplica | Q12: No aplica | R12: No aplica | S12: No | T12: UUID vacio | U12: No | V12: Requerido | W12: No requerido | X12: No modificable | Y12: Mostrar | Z12: No requerido | AA12: No modificable | AB12: No requerido | AC12: No modificable | AD12: Requerido | AE12: Modificable | AF12: No mostrar
A14: Nombre combinación única | B14: Descripción | C14: Atributos involucrados
A15: ='M-Barbero'!K3 -> Combinación única 1 | B15: ='M-Barbero'!K2 -> Combinacion única que indica que no puede existir más de un barbero con el mismo prefijo de celular y número de celular | C15: =A8 -> prefijo
C16: =A9 -> celular
A18: Responsabilidad | C18: Descripción | G18: Entradas | J18: Salida | O18: Políticas (Reglas de Negocio) | Q18: Excepción
G19: Parámetro | H19: Tipo de dato | I19: Descripción | J19: Tipo de Dato | K19: Descripción | O19: Política | P19: Descripción | Q19: Detalle | R19: ¿Qué hago?
A20: registrarBarbero | C20: Comando que permite el ingreso de un nuevo barbero a trabajar en la barbería | G20: datos{primerNombre, segundoNombre, primerApellido, segundoApellido, prefijoCelular, celular, elNumeroCelularEsCorrecto, sedeDeTrabajo} | H20: Barbero | I20: Contiene la información requerida para registrar un nuevo barbero en la barbería | J20: Barbero | K20: Contiene la información del barbero registrado | O20: ='P-Barbero'!A6 -> P-BAR-0001 | P20: ='P-Barbero'!B6 -> Asegurar que los datos requeridos del barbero (nombre, apellido, prefijo de celular, celular, sede de trabajo) sean válidos en tipo de dato, longitud, obligatoriedad, formato y rango | Q20: Generar una excepción indicándole al barbero que los datos ingresados no son válidos | R20: Detener operación
O21: ='P-Barbero'!A7 -> P-BAR-0002 | P21: ='P-Barbero'!B7 -> Asegurar que el número de celular y prefijo de celular no esté siendo utilizado por otro barbero | Q21: Generar una excepción indicándole al usuario que ya existe otro barbero registrado con ese prefijo y número de celular | R21: Detener operación
O22: ='P-Barbero'!A10 -> P-BAR-0006 | P22: ='P-Barbero'!B10 -> Asegurar que el barbero halla puesto un si en el atributo elNumeroCelularEsCorrecto | Q22: Generar una excepción indicándole al barbero que ponga si en elNumeroCelularEsCorrecto | R22: Detener operación
A23: editarContactoBarbero | C23: Permite al barbero actualizar su número de celular y su prefijo | G23: id | H23: UUID | I23: Corresponde al identificador del barbero que va a editar su contacto | J23: Barbero | K23: Contiene la información del barbero con su contacto actualizado | O23: ='P-Barbero'!A11 -> P-BAR-0007 | P23: ='P-Barbero'!B11 -> Asegurar que exista el barbero con el id enviado | Q23: Informar con un mensaje que no existe un barbero con el identificador enviado y por lo tanto no es posible editar el contacto del barbero | R23: Detener operación
G24: datos{prefijoCelular, celular} | H24: Barbero | I24: Contiene el nuevo prefijo y número de celular del barbero | O24: ='P-Barbero'!A9 -> P-BAR-0004 | P24: ='P-Barbero'!B9 -> Asegurar que los datos requeridos del barbero para editar su contacto (prefijo de celular, celular) sean válidos en tipo de dato, longitud, obligatoriedad, formato y rango | Q24: Generar una excepción indicándole al usuario cuáles datos de contacto del barbero no cumplen con las reglas definidas | R24: Detener operación
A26: consultarDatosBarbero | C26: Permite a un cliente ver los datos públicos de un barbero, como sus nombres, apellidos y su contacto | G26: id | H26: UUID | I26: Corresponde al identificador del barbero que se va a consultar | J26: Barbero | K26: Contiene la información del barbero consultado por su identificador | O26: ='P-Barbero'!A11 -> P-BAR-0007 | P26: ='P-Barbero'!B11 -> Asegurar que exista el barbero con el id enviado | Q26: Informar con un mensaje que no existe un barbero con el identificador enviado y por lo tanto no es posible consultar los datos | R26: Detener operación
A27: desactivarBarbero | C27: Permite desactivar a un barbero para que ya no pueda recibir nuevas citas | G27: id | H27: UUID | I27: Corresponde al identificador del barbero que va a dejar de trabajar | J27: No retorna ningún valor. En caso de error genera una excepción. | O27: ='P-Barbero'!A8 -> P-BAR-0003 | P27: ='P-Barbero'!B8 -> Asegurar que el barbero no tenga citas futuras pendientes antes de dejar de trabajar en la barbería | Q27: Generar una excepción indicándole al usuario que el barbero no puede dejar de trabajar porque todavía tiene citas futuras pendientes | R27: Detener operación
O28: ='P-Barbero'!A11 -> P-BAR-0007 | P28: ='P-Barbero'!B11 -> Asegurar que exista el barbero con el id enviado | Q28: Informar con un mensaje que no existe un barbero con el identificador enviado y por lo tanto no es posible desactivar el barbero | R28: Detener operación
A29: reactivarBarbero | C29: Permite activar a un barbero para que ya pueda volver a recibir citas de sus clientes | G29: id | H29: UUID | I29: Corresponde al identificador del barbero que va a dejar de trabajar | J29: No retorna ningún valor. En caso de error genera una excepción. | O29: ='P-Barbero'!A11 -> P-BAR-0007 | P29: ='P-Barbero'!B11 -> Asegurar que exista el barbero con el id enviado | Q29: Informar con un mensaje que no existe un barbero con el identificador enviado y por lo tanto no es posible reactivar el barbero | R29: Detener operación
A30: cambiarSedeDeTrabajoBarbero | C30: Permite al barbero cambiar la sede en la que trabaja, que puede pertenecer a otra barbería, sin modificar sus citas pasadas | G30: id | H30: UUID | I30: Corresponde al identificador del barbero que va a cambiar de sede | J30: Barbero | K30: Contiene la información del barbero con su nueva sede de trabajo | O30: ='P-Barbero'!A11 -> P-BAR-0007 | P30: ='P-Barbero'!B11 -> Asegurar que exista el barbero con el id enviado | Q30: Informar con un mensaje que no existe un barbero con el identificador enviado | R30: Detener operación
G31: datos{sedeDeTrabajo} | H31: Barbero | I31: Contiene la nueva sede en la que va a trabajar el barbero | O31: ='P-Barbero'!A12 -> P-BAR-0008 | P31: ='P-Barbero'!B12 -> Asegurar que el barbero no tenga citas futuras en estado Agendada antes de cambiar de sede o de barbería | Q31: Generar una excepción indicándole al barbero que no puede cambiar de sede o de barbería porque tiene citas futuras agendadas | R31: Detener operación
A32: consultarServiciosSedeBarbero | C32: Permite al barbero consultar únicamente los servicios disponibles de la sede en la que trabaja | G32: id | H32: UUID | I32: Corresponde al identificador del barbero que consulta los servicios | J32: Lista<Servicio> | K32: Contiene los servicios disponibles de la sede de trabajo del barbero | O32: ='P-Barbero'!A11 -> P-BAR-0007 | P32: ='P-Barbero'!B11 -> Asegurar que exista el barbero con el id enviado | Q32: Informar con un mensaje que no existe un barbero con el identificador enviado y por lo tanto no se puede realizar la operación | R32: Detener operación
O33: ='P-Servicio'!A13 -> P-SER-0008 | P33: ='P-Servicio'!B13 -> Asegurar que el barbero solo pueda consultar los servicios disponibles de la sede en la que trabaja actualmente (su sedeDeTrabajo) | Q33: Generar una excepción indicándole al barbero que solo puede consultar los servicios de su sede de trabajo | R33: Detener operación

Sheet P-Barbero
A1: << Ir al modelo de dominio | B1: << Ir al listado de objetos de dominio | C1: << Ir a la caracterización del objeto de dominio | D1: Ir al muestreo de datos del objeto de dominio >> | E1: Ir al event storming del objeto de dominio >>
A2: Objeto de Dominio: | B2: ='Objetos de Dominio'!A13 -> Barbero
A3: Descripción: | B3: ='Objetos de Dominio'!B13 -> Representa a un trabajador de la barbería que atiende clientes según los servicios que sabe realizar, organiza su propio horario y tiene su agenda personal para atender todas las citas que valla teniendo.
A4: Numero politica | B4: Descripcion politica | D4: Objeto responsable | E4: Regla responsable
A6: P-BAR-0001 | B6: Asegurar que los datos requeridos del barbero (nombre, apellido, prefijo de celular, celular, sede de trabajo) sean válidos en tipo de dato, longitud, obligatoriedad, formato y rango | D6: Barbero
A7: P-BAR-0002 | B7: Asegurar que el número de celular y prefijo de celular no esté siendo utilizado por otro barbero | D7: Barbero
A8: P-BAR-0003 | B8: Asegurar que el barbero no tenga citas futuras pendientes antes de dejar de trabajar en la barbería | D8: Cita
A9: P-BAR-0004 | B9: Asegurar que los datos requeridos del barbero para editar su contacto (prefijo de celular, celular) sean válidos en tipo de dato, longitud, obligatoriedad, formato y rango | D9: Barbero
A10: P-BAR-0006 | B10: Asegurar que el barbero halla puesto un si en el atributo elNumeroCelularEsCorrecto | D10: Barbero
A11: P-BAR-0007 | B11: Asegurar que exista el barbero con el id enviado | D11: Barbero
A12: P-BAR-0008 | B12: Asegurar que el barbero no tenga citas futuras en estado Agendada antes de cambiar de sede o de barbería | D12: Cita

Sheet E-Barbero
A1: << Ir al modelo de dominio | C1: << Ir al listado de objetos de dominio | F1: << Ir a la caracterización del objeto de dominio | J1: Ir al muestreo de datos del objeto de dominio >>
A2: Objeto de Dominio: | B2: ='Objetos de Dominio'!A13 -> Barbero
A3: Descripción: | B3: ='Objetos de Dominio'!B13 -> Representa a un trabajador de la barbería que atiende clientes según los servicios que sabe realizar, organiza su propio horario y tiene su agenda personal para atender todas las citas que valla teniendo.
A4: Actor | B4: Action/Command | D4: Entity/Aggregate/Object domain | E4: Read Model | G4: Business Rule/Policy | I4: External System | J4: Domain Event | K4: Hotspot/questions/Risk
A5: Actor | B5: Acción | C5: Descripción | D5: Objeto de dominio | E5: Información externa | G5: Políticas | I5: Sistema Externo | J5: Evento | K5: Aspectos por solucionar
E6: Información | F6: Descripción | G6: Número | H6: Descripción
A7: Administrador | B7: Registrar barbero a la barbería | C7: Comando que permite el ingreso de un nuevo barbero a trabajar en la barbería | D7: Barbero | G7: ='P-Barbero'!A6 -> P-BAR-0001 | H7: aquí | I7: WhatsApp | J7: Barbero registrado
G8: ='P-Barbero'!A7 -> P-BAR-0002 | H8: aquí
A9: Barbero | B9: Editar contacto | C9: Permite al barbero actualizar su número de celular y su prefijo | D9: Barbero | G9: ='P-Barbero'!A9 -> P-BAR-0004 | H9: aquí | J9: Contacto de barbero actualizado
A10: Cliente | B10: Ver datos de un barbero | C10: Permite a un cliente ver los datos públicos de un barbero, como sus nombres, apellidos y su contacto | D10: Barbero | J10: Datos de barbero visto
A11: Barbero | B11: Ver datos de un barbero | C11: Permite a un barbero ver los datos públicos de otro barbero, como sus nombres, apellidos y su contacto | J11: Datos de barbero visto
A12: Barbero | B12: Dejar de trabajar en la barbería | C12: Permite desactivar a un barbero para que ya no pueda recibir nuevas citas, sin borrar su historial | D12: Barbero | E12: Cita | F12: Permite identificar las citas del barbero que siguen en estado Agendada. | G12: ='P-Barbero'!A8 -> P-BAR-0003 | H12: aquí | J12: Barbero desactivado
E13: Agenda | F13: Permite conocer la fecha de cada cita para identificar cuáles son futuras (fecha y horaInicio posteriores al momento actual).
A14: Barbero | B14: Volver a trabajar en la barbería | C14: Permite reactivar a un barbero para que pueda volver a recibir nuevas citas | D14: Barbero | J14: Barbero activado
A15: Barbero | B15: Cambiar de sede o de barbería | C15: Permite al barbero cambiar la sede en la que trabaja, que puede pertenecer a otra barbería | D15: Barbero | E15: Sede | F15: Permite identificar la nueva sede de trabajo y la barbería a la que pertenece. | G15: ='P-Barbero'!A12 -> P-BAR-0008 | H15: aquí | J15: Sede de trabajo del barbero cambiada
E16: Agenda | F16: Permite conocer la fecha de cada cita para identificar cuáles son futuras (fecha y horaInicio posteriores al momento actual).
E17: Cita | F17: Permite identificar las citas del barbero que siguen en estado Agendada

Sheet M-Barbero
A1: <<<< Ir al modulo de dominio | B1: <<<< Ir a objetos de dominio
A2: Representa un identificador que hará unico cada objeto de dominio de este tipo, no se puede repetir | B2: Representa el primer nombre del barbero que trabaja en barbería | C2: Representa el segundo nombre del barbero que trabaja en barbería | D2: Representa el primer apellido del barbero que trabaja en la barbería | E2: Representa el segundo apellido del barbero que trabaja en la barbería | F2: Representa cual es el prefijo del numero de celular del barbero | G2: Representa el número de celular del barbero, es el dato que el cliente necesita en caso de que tenga que contactarse con el | H2: Representa si el numero que ingreso el cliente es correcto o no | I2: Representa si el barbero sigue o no trabajando en la barberia | J2: Representa cual es la sede y la barberia donde trabaja el barbero | K2: Combinacion única que indica que no puede existir más de un barbero con el mismo prefijo de celular y número de celular
A3: id | B3: primerNombre | C3: segundoNombre | D3: primerApellido | E3: segundoApellido | F3: prefijo | G3: celular | H3: elNumeroCelularEsCorrecto | I3: vigente | J3: sedeDeTrabajo | K3: Combinación única 1
A4: 1 | B4: Juan | C4: Fernando | D4: García | E4: Lopez | F4: ='M-PrefijoCelular'!C4 -> +57 | G4: 3245627890 | H4: Si | I4: si | J4: ='M-Sede'!F4 -> 900123456-7-Sede Poblado | K4: =_xlfn.CONCAT(F4,"-",G4) -> +57-3245627890
A5: 2 | B5: Juan | C5: David | D5: Ortiz | E5: Sanchez | F5: ='M-PrefijoCelular'!C4 -> +57 | G5: 3124518923 | H5: Si | I5: si | J5: ='M-Sede'!F4 -> 900123456-7-Sede Poblado | K5: =_xlfn.CONCAT(F5,"-",G5) -> +57-3124518923
A6: 3 | B6: Carlos | D6: Arbeladez | F6: ='M-PrefijoCelular'!C4 -> +57 | G6: 3214533321 | H6: Si | I6: si | J6: ='M-Sede'!F4 -> 900123456-7-Sede Poblado | K6: =_xlfn.CONCAT(F6,"-",G6) -> +57-3214533321
A7: 4 | B7: Andres | D7: Ramirez | E7: Patiño | F7: ='M-PrefijoCelular'!C5 -> +91 | G7: 9876543210 | H7: Si | I7: no | J7: ='M-Sede'!F4 -> 900123456-7-Sede Poblado | K7: =_xlfn.CONCAT(F7,"-",G7) -> +91-9876543210
A8: 5 | B8: Juan | C8: Carlos | D8: Zambrano | E8: Perez | F8: ='M-PrefijoCelular'!C6 -> +593 | G8: 998765432 | H8: Si | I8: no | J8: ='M-Sede'!F4 -> 900123456-7-Sede Poblado | K8: =_xlfn.CONCAT(F8,"-",G8) -> +593-998765432
B14: Corresponde a la descripcion de los atributos
B15: Corresponde al identificador unico del objeto de dominio
B16: Corresponde a las referencias de otros objetos de dominio
B17: Corresponde a los datos auto generados por el sistema
B18: Corresponde a los datos que ingresa el usuario
B19: Corresponde a la combinacion única

Sheet C-HorarioBarberia
A1: <<<< Ir al modulo de dominio | B1: <<<< Ir a objetos de dominio
A2: Nombre atributo | B2: Descripción atributo | C2: Identificador del objeto de dominio | D2: Tipo de dato | E2: Obligatorio | F2: Longitud mínima (si aplica) | G2: Longitud máxima (si aplica) | H2: Precisión (si aplica) | I2: Rendondeo (si aplica) | J2: Rango inicial (si aplica) | K2: Rango final (si aplica) | L2: Formato (si aplica) | M2: Reglas especiales (si aplica) | N2: Dato calculado | O2: Aplica ajuste del dato (si aplica) | P2: Carácter de ajuste (si aplica) | Q2: Quitar espacios en blanco al inicio (si aplica) | R2: Quitar espacios en blanco al fin (si aplica) | S2: Dato sensible (si aplica) | T2: Valor por defecto (si aplica) | U2: Auto generado | V2: =A23 -> definirHorarioBarberia | W2: =A26 -> consultarHorariosBarberia | X2: =A27 -> desactivarHorarioBarberia
A3: ='M-HorarioBarberia'!A3 -> id | B3: ='M-HorarioBarberia'!A2 -> Representa un identificador que hará unico cada objeto de dominio de este tipo, no se puede repetir | C3: Si | D3: Identificador único universal | E3: Si | F3: No aplica | G3: No aplica | H3: No aplica | I3: No aplica | J3: No aplica | K3: No aplica | L3: No aplica | M3: No aplica | N3: No | O3: No aplica | P3: No aplica | Q3: No aplica | R3: No aplica | S3: No | T3: UUID vacio | U3: Si | V3: No requerido | W3: No mostrar | X3: Requerido
A4: ='M-HorarioBarberia'!B3 -> sedeDeLaBarberia | B4: ='M-HorarioBarberia'!B2 -> Representa a cual barberia y sede pertenece el horario de apertura y cierre | C4: No | D4: Sede | E4: Si | F4: No aplica | G4: No aplica | H4: No aplica | I4: No aplica | J4: No aplica | K4: No aplica | L4: No aplica | M4: Aplican las reglas del objeto referenciado | N4: No | O4: No aplica | P4: No aplica | Q4: No aplica | R4: No aplica | S4: No | T4: UUID vacio | U4: No | V4: Requerido | W4: Mostrar | X4: No requerido
A5: ='M-HorarioBarberia'!C3 -> diaDeLaSemana | B5: ='M-HorarioBarberia'!C2 -> Representa el día de la semana en el que la barberia abre | C5: No | D5: DiaSemana | E5: Si | F5: No aplica | G5: No aplica | H5: No aplica | I5: No aplica | J5: No aplica | K5: No aplica | L5: No aplica | M5: Aplican las reglas del objeto referenciado | N5: No | O5: No aplica | P5: No aplica | Q5: No aplica | R5: No aplica | S5: No | T5: UUID vacio | U5: No | V5: Requerido | W5: Mostrar | X5: No requerido
A6: ='M-HorarioBarberia'!D3 -> horaApertura | B6: ='M-HorarioBarberia'!D2 -> Representa la hora a la que abre la barbería | C6: No | D6: Hora | E6: Si | F6: No aplica | G6: No aplica | H6: No aplica | I6: No aplica | J6: No aplica | K6: No aplica | L6: No aplica | M6: No aplica | N6: No | O6: No | P6: No aplica | Q6: No aplica | R6: No aplica | S6: No | T6: 00:00 | U6: No | V6: Requerido | W6: Mostrar | X6: No requerido
A7: ='M-HorarioBarberia'!E3 -> horaCierre | B7: ='M-HorarioBarberia'!E2 -> Representa la hora a la que cierra la barbería | C7: No | D7: Hora | E7: Si | F7: No aplica | G7: No aplica | H7: No aplica | I7: No aplica | J7: No aplica | K7: No aplica | L7: No aplica | M7: Debe ser mayor a horaApertura | N7: No | O7: No | P7: No aplica | Q7: No aplica | R7: No aplica | S7: No | T7: 00:00 | U7: No | V7: Requerido | W7: Mostrar | X7: No requerido
A8: ='M-HorarioBarberia'!F3 -> fechaCreacion | B8: ='M-HorarioBarberia'!F2 -> Representa la fecha en el que el administrador definio el horario de la barberia. Es un dato calculado que toma la fecha del sistema en ese momento | C8: No | D8: Fecha | E8: Si | F8: No aplica | G8: No aplica | H8: No aplica | I8: No aplica | J8: No aplica | K8: No aplica | L8: No aplica | M8: No aplica | N8: No | O8: No | P8: No aplica | Q8: No aplica | R8: No aplica | S8: No | T8: 1/01/1000 | U8: Si | V8: No requerido | W8: No mostrar | X8: No requerido
A9: ='M-HorarioBarberia'!G3 -> fechaDesactivacion | B9: ='M-HorarioBarberia'!G2 -> Representa la fecha en la que este horario dejó de estar vigente. Es un dato calculado que toma la fecha del sistema en ese momento | C9: No | D9: Fecha | E9: No | F9: No aplica | G9: No aplica | H9: No aplica | I9: No aplica | J9: No aplica | K9: No aplica | L9: No aplica | M9: No aplica | N9: No | O9: No | P9: No aplica | Q9: No aplica | R9: No aplica | S9: No | T9: 1/01/1000 | U9: Si | V9: No requerido | W9: No mostrar | X9: No requerido
A10: ='M-HorarioBarberia'!H3 -> vigente | B10: ='M-HorarioBarberia'!H2 -> Representa si este horario lo sigue o no vigente en la barberia. Una vez que el administrador desactive el horario de la barberia, no se puede volver a cambiar | C10: No | D10: Lógico | E10: Si | F10: No aplica | G10: No aplica | H10: No aplica | I10: No aplica | J10: No aplica | K10: No aplica | L10: No aplica | M10: Una vez que vigente se ponga como no, no se puede volver a cambiar | N10: No | O10: No | P10: No aplica | Q10: No aplica | R10: No aplica | S10: No | T10: Si | U10: Si | V10: No requerido | W10: No mostrar | X10: No requerido
A12: Nombre combinación única | B12: Descripción | C12: Atributos involucrados
A13: ='M-HorarioBarberia'!I3 -> Combinación única | B13: ='M-HorarioBarberia'!I2 -> Combinación única que indica que, entre los horarios vigentes, no puede existir más de un horario para la sede de una barberia el mismo día de la semana con la misma hora de apertura, la misma hora de cierre, fecha de creacion y fecha de desactivacion | C13: =A4 -> sedeDeLaBarberia
C14: =A5 -> diaDeLaSemana
C15: =A6 -> horaApertura
C16: =A7 -> horaCierre
C17: =A8 -> fechaCreacion
C18: =A9 -> fechaDesactivacion
A21: Responsabilidad | C21: Descripción | G21: Entradas | J21: Salida | O21: Políticas (Reglas de Negocio) | Q21: Excepción
G22: Parámetro | H22: Tipo de dato | I22: Descripción | J22: Tipo de Dato | K22: Descripción | O22: Política | P22: Descripción | Q22: Detalle | R22: ¿Qué hago?
A23: definirHorarioBarberia | C23: Comando que permite registrar la hora de apertura y cierre de la barbería para un día de la semana | G23: datos{sedeDeLaBarberia, diaDeLaSemana, horaApertura, horaCierre} | H23: HorarioBarberia | I23: Contiene la información requerida para registrar el horario de la barbería para un día | J23: HorarioBarberia | K23: Contiene la información del horario de la barbería registrado | O23: ='P-HorarioBarberia'!A6 -> P-HBA-0001 | P23: ='P-HorarioBarberia'!B6 -> Asegurar que los datos requeridos (sede de la barbería, día de la semana, hora de apertura, hora de cierre) sean válidos en tipo de dato, longitud, obligatoriedad, formato y rango | Q23: Generar una excepción indicándole al administrador que los datos no cumplen con las reglas definidas | R23: Detener operación
O24: ='P-HorarioBarberia'!A7 -> P-HBA-0002 | P24: ='P-HorarioBarberia'!B7 -> Asegurar que no exista otro horario vigente para la misma sede de la barbería y el mismo día de la semana; un mismo día puede tener varios horarios siempre que sus periodos de vigencia (fecha de creación y fecha de desactivación) sean distintos | Q24: Generar una excepción indicándole al administrador que ya existe un horario vigente para ese día que se cruza con las horas indicadas | R24: Detener operación
O25: ='P-HorarioBarberia'!A11 -> P-HBA-0006 | P25: ='P-HorarioBarberia'!B11 -> Asegurar que la hora de cierre sea mayor a la hora de apertura | Q25: Generar una excepción indicandole al administrador que la hora de cierre debe de ser mayor a la hora de apertura | R25: Detener operación
A26: consultarHorariosBarberia | C26: Permite al administrador consultar los horarios de apertura y cierre definidos para cada día de la semana | J26: Lista<HorarioBarberia> | K26: Contiene todos los horarios de la barbería vigentes
A27: desactivarHorarioBarberia | C27: Permite desactivar el horario en el que la barberia ya no abrira | G27: id | H27: UUID | I27: Corresponde al identificador del horario de la barbería que se va a desactivar | J27: No retorna ningún valor. En caso de error genera una excepción. | O27: ='P-HorarioBarberia'!A8 -> P-HBA-0003 | P27: ='P-HorarioBarberia'!B8 -> Asegurar que queden desactivados todos los horarios de barbero que dependen del horario de la barbería que se está desactivando | Q27: Si alguno de los horarios de barbero no pudo ser desactivado, revertir toda la operación e informar el error | R27: Detener operación
O28: ='P-HorarioBarberia'!A9 -> P-HBA-0004 | P28: ='P-HorarioBarberia'!B9 -> Asegurar que queden canceladas, en el estado Cancelación por cambio de políticas de la barbería, todas las citas futuras asociadas a las agendas de los horarios de barbero desactivados. Se consideran futuras las citas cuya agenda tenga una fecha posterior a la fecha actual | Q28: Si alguna de las citas futuras no pudo ser cancelada, revertir toda la operación e informar el error | R28: Detener operación
O29: ='P-HorarioBarberia'!A10 -> P-HBA-0005 | P29: ='P-HorarioBarberia'!B10 -> Asegurar que exista el horario de la barbería con el id enviado | Q29: Informar con un mensaje que no existe un horario de la barbería con el identificador enviado y por lo tanto no es posible llevar a cabo la operación | R29: Detener operación
O30: ='P-HorarioBarberia'!A12 -> P-HBA-0007 | P30: ='P-HorarioBarberia'!B12 -> Asegurar que el horario de la barbería que se va a desactivar se encuentre vigente | Q30: Informar con un mensaje que ese horario de la barbería ya se encuentra desactivado y por lo tanto no puede volver a desactivarse | R30: Detener operación

Sheet P-HorarioBarberia
A1: << Ir al modelo de dominio | B1: << Ir al listado de objetos de dominio | C1: << Ir a la caracterización del objeto de dominio | D1: Ir al muestreo de datos del objeto de dominio >> | E1: Ir al event storming del objeto de dominio >>
A2: Objeto de Dominio: | B2: ='Objetos de Dominio'!A14 -> HorarioBarberia
A3: Descripción: | B3: ='Objetos de Dominio'!B14 -> Representa, día por día, a qué hora abre y cierra el negocio; es el límite dentro del cual debe caber el horario de cualquier barbero.
A4: Numero politica | B4: Descripcion politica | D4: Objeto responsable | E4: Regla responsable
A6: P-HBA-0001 | B6: Asegurar que los datos requeridos (sede de la barbería, día de la semana, hora de apertura, hora de cierre) sean válidos en tipo de dato, longitud, obligatoriedad, formato y rango | D6: HorarioBarberia
A7: P-HBA-0002 | B7: Asegurar que no exista otro horario vigente para la misma sede de la barbería y el mismo día de la semana; un mismo día puede tener varios horarios siempre que sus periodos de vigencia (fecha de creación y fecha de desactivación) sean distintos | D7: HorarioBarberia
A8: P-HBA-0003 | B8: Asegurar que queden desactivados todos los horarios de barbero que dependen del horario de la barbería que se está desactivando | D8: HorarioBarbero
A9: P-HBA-0004 | B9: Asegurar que queden canceladas, en el estado Cancelación por cambio de políticas de la barbería, todas las citas futuras asociadas a las agendas de los horarios de barbero desactivados. Se consideran futuras las citas cuya agenda tenga una fecha posterior a la fecha actual | D9: Cita
A10: P-HBA-0005 | B10: Asegurar que exista el horario de la barbería con el id enviado | D10: HorarioBarberia
A11: P-HBA-0006 | B11: Asegurar que la hora de cierre sea mayor a la hora de apertura | D11: HorarioBarberia
A12: P-HBA-0007 | B12: Asegurar que el horario de la barbería que se va a desactivar se encuentre vigente | D12: HorarioBarberia

Sheet E-HorarioBarberia
A1: << Ir al modelo de dominio | C1: << Ir al listado de objetos de dominio | F1: << Ir a la caracterización del objeto de dominio | J1: Ir al muestreo de datos del objeto de dominio >>
A2: Objeto de Dominio: | B2: ='Objetos de Dominio'!A14 -> HorarioBarberia
A3: Descripción: | B3: ='Objetos de Dominio'!B14 -> Representa, día por día, a qué hora abre y cierra el negocio; es el límite dentro del cual debe caber el horario de cualquier barbero.
A4: Actor | B4: Action/Command | D4: Entity/Aggregate/Object domain | E4: Read Model | G4: Business Rule/Policy | I4: External System | J4: Domain Event | K4: Hotspot/questions/Risk
A5: Actor | B5: Acción | C5: Descripción | D5: Objeto de dominio | E5: Información externa | G5: Políticas | I5: Sistema Externo | J5: Evento | K5: Aspectos por solucionar
E6: Información | F6: Descripción | G6: Número | H6: Descripción
A7: Administrador | B7: Definir un horario de la barbería | C7: Comando que permite registrar la hora de apertura y cierre de la barbería para un día de la semana | D7: =$B$2 -> HorarioBarberia | G7: ='P-HorarioBarberia'!A6 -> P-HBA-0001 | H7: ='P-HorarioBarberia'!B6 -> Asegurar que los datos requeridos (sede de la barbería, día de la semana, hora de apertura, hora de cierre) sean válidos en tipo de dato, longitud, obligatoriedad, formato y rango | J7: Horario de barbería definido
G8: ='P-HorarioBarberia'!A7 -> P-HBA-0002 | H8: ='P-HorarioBarberia'!B7 -> Asegurar que no exista otro horario vigente para la misma sede de la barbería y el mismo día de la semana; un mismo día puede tener varios horarios siempre que sus periodos de vigencia (fecha de creación y fecha de desactivación) sean distintos
G9: ='P-HorarioBarberia'!A11 -> P-HBA-0006 | H9: ='P-HorarioBarberia'!B11 -> Asegurar que la hora de cierre sea mayor a la hora de apertura
A10: Administrador | B10: Ver horarios de la barbería | C10: Permite al administrador consultar los horarios de apertura y cierre definidos para cada día de la semana | D10: =$B$2 -> HorarioBarberia | J10: Horarios de barbería consultados
A11: Barbero | B11: Ver horarios de la barbería | C11: Permite al barbero consultar los horarios de apertura y cierre definidos para cada día de la semana | D11: =$B$2 -> HorarioBarberia | J11: Horarios de barbería consultados
A12: Cliente | B12: Ver horarios de la barbería | C12: Permite al cliente consultar los horarios de apertura y cierre definidos para cada día de la semana | D12: =$B$2 -> HorarioBarberia | J12: Horarios de barbería consultados
A13: Administrador | B13: Desactivar horario de barbería | C13: Permite desactivar el horario en el que la barberia ya no abrira | D13: =$B$2 -> HorarioBarberia | E13: HorarioBarbero | F13: Permite identificar los horarios de barbero que dependen de ese día para desactivarlos. | G13: ='P-HorarioBarberia'!A8 -> P-HBA-0003 | H13: ='P-HorarioBarberia'!B8 -> Asegurar que queden desactivados todos los horarios de barbero que dependen del horario de la barbería que se está desactivando | J13: Horario de barbería desactivado
E14: Agenda | F14: Permite identificar las citas futuras que quedaron en las agendas de los horarios de barbero desactivados. La agenda no se modifica: solo se recorre para llegar a las citas. | G14: ='P-HorarioBarberia'!A9 -> P-HBA-0004 | H14: ='P-HorarioBarberia'!B9 -> Asegurar que queden canceladas, en el estado Cancelación por cambio de políticas de la barbería, todas las citas futuras asociadas a las agendas de los horarios de barbero desactivados. Se consideran futuras las citas cuya agenda tenga una fecha posterior a la fecha actual
E15: Cita | F15: Permite identificar las citas futuras que se deben cancelar.
E16: Estado | F16: Permite dejar esas citas en el estado Cancelación. | G16: ='P-HorarioBarberia'!A12 -> P-HBA-0007 | H16: ='P-HorarioBarberia'!B12 -> Asegurar que el horario de la barbería que se va a desactivar se encuentre vigente

Sheet M-HorarioBarberia
A1: <<<< Ir al modulo de dominio | B1: <<<< Ir a objetos de dominio
A2: Representa un identificador que hará unico cada objeto de dominio de este tipo, no se puede repetir | B2: Representa a cual barberia y sede pertenece el horario de apertura y cierre | C2: Representa el día de la semana en el que la barberia abre | D2: Representa la hora a la que abre la barbería | E2: Representa la hora a la que cierra la barbería | F2: Representa la fecha en el que el administrador definio el horario de la barberia. Es un dato calculado que toma la fecha del sistema en ese momento | G2: Representa la fecha en la que este horario dejó de estar vigente. Es un dato calculado que toma la fecha del sistema en ese momento | H2: Representa si este horario lo sigue o no vigente en la barberia. Una vez que el administrador desactive el horario de la barberia, no se puede volver a cambiar | I2: Combinación única que indica que, entre los horarios vigentes, no puede existir más de un horario para la sede de una barberia el mismo día de la semana con la misma hora de apertura, la misma hora de cierre, fecha de creacion y fecha de desactivacion
A3: id | B3: sedeDeLaBarberia | C3: diaDeLaSemana | D3: horaApertura | E3: horaCierre | F3: fechaCreacion | G3: fechaDesactivacion | H3: vigente | I3: Combinación única
A4: 1 | B4: ='M-Sede'!F4 -> 900123456-7-Sede Poblado | C4: ='M-DiaSemana'!C4 -> Lunes | D4: 0.375 | E4: 0.79166667 | F4: 45242 | G4: 1/01/1000 | H4: Si | I4: =_xlfn.CONCAT(B4,"-",C4,"-",TEXT(D4,"hh:mm"),"-",TEXT(E4,"hh:mm"),"-",TEXT(F4,"dd/mm/yyyy"),"-",TEXT(G4,"dd/mm/yyyy")) -> 900123456-7-Sede Poblado-Lunes-09:00-19:00-12/11/2023-1/01/1000
A5: 2 | B5: ='M-Sede'!F4 -> 900123456-7-Sede Poblado | C5: ='M-DiaSemana'!C5 -> Martes | D5: 0.375 | E5: 0.79166667 | F5: 45242 | G5: 1/01/1000 | H5: Si | I5: =_xlfn.CONCAT(B5,"-",C5,"-",TEXT(D5,"hh:mm"),"-",TEXT(E5,"hh:mm"),"-",TEXT(F5,"dd/mm/yyyy"),"-",TEXT(G5,"dd/mm/yyyy")) -> 900123456-7-Sede Poblado-Martes-09:00-19:00-12/11/2023-1/01/1000
A6: 3 | B6: ='M-Sede'!F4 -> 900123456-7-Sede Poblado | C6: ='M-DiaSemana'!C6 -> Miércoles | D6: 0.375 | E6: 0.79166667 | F6: 45242 | G6: 1/01/1000 | H6: Si | I6: =_xlfn.CONCAT(B6,"-",C6,"-",TEXT(D6,"hh:mm"),"-",TEXT(E6,"hh:mm"),"-",TEXT(F6,"dd/mm/yyyy"),"-",TEXT(G6,"dd/mm/yyyy")) -> 900123456-7-Sede Poblado-Miércoles-09:00-19:00-12/11/2023-1/01/1000
A7: 4 | B7: ='M-Sede'!F4 -> 900123456-7-Sede Poblado | C7: ='M-DiaSemana'!C7 -> Jueves | D7: 0.375 | E7: 0.79166667 | F7: 45242 | G7: 1/01/1000 | H7: Si | I7: =_xlfn.CONCAT(B7,"-",C7,"-",TEXT(D7,"hh:mm"),"-",TEXT(E7,"hh:mm"),"-",TEXT(F7,"dd/mm/yyyy"),"-",TEXT(G7,"dd/mm/yyyy")) -> 900123456-7-Sede Poblado-Jueves-09:00-19:00-12/11/2023-1/01/1000
A8: 5 | B8: ='M-Sede'!F4 -> 900123456-7-Sede Poblado | C8: ='M-DiaSemana'!C8 -> Viernes | D8: 0.375 | E8: 0.79166667 | F8: 45242 | G8: 1/01/1000 | H8: Si | I8: =_xlfn.CONCAT(B8,"-",C8,"-",TEXT(D8,"hh:mm"),"-",TEXT(E8,"hh:mm"),"-",TEXT(F8,"dd/mm/yyyy"),"-",TEXT(G8,"dd/mm/yyyy")) -> 900123456-7-Sede Poblado-Viernes-09:00-19:00-12/11/2023-1/01/1000
A9: 6 | B9: ='M-Sede'!F4 -> 900123456-7-Sede Poblado | C9: ='M-DiaSemana'!C9 -> Sábado | D9: 0.33333333 | E9: 0.875 | F9: 45638 | G9: 1/01/1000 | H9: Si | I9: =_xlfn.CONCAT(B9,"-",C9,"-",TEXT(D9,"hh:mm"),"-",TEXT(E9,"hh:mm"),"-",TEXT(F9,"dd/mm/yyyy"),"-",TEXT(G9,"dd/mm/yyyy")) -> 900123456-7-Sede Poblado-Sábado-08:00-21:00-12/12/2024-1/01/1000
A10: 7 | B10: ='M-Sede'!F4 -> 900123456-7-Sede Poblado | C10: ='M-DiaSemana'!C11 -> Festivo | D10: 0.41666667 | E10: 0.625 | F10: 45638 | G10: 1/01/1000 | H10: Si | I10: =_xlfn.CONCAT(B10,"-",C10,"-",TEXT(D10,"hh:mm"),"-",TEXT(E10,"hh:mm"),"-",TEXT(F10,"dd/mm/yyyy"),"-",TEXT(G10,"dd/mm/yyyy")) -> 900123456-7-Sede Poblado-Festivo-10:00-15:00-12/12/2024-1/01/1000
B16: Corresponde a la descripcion de los atributos
B17: Corresponde al identificador unico del objeto de dominio
B18: Corresponde a las referencias de otros objetos de dominio
B19: Corresponde a los datos auto generados por el sistema
B20: Corresponde a los datos que ingresa el administrador
B21: Corresponde a la combinacion única

Sheet C-Servicio
A1: <<<< Ir al modulo de dominio | B1: <<<< Ir a objetos de dominio
A2: Nombre atributo | B2: Descripción atributo | C2: Identificador del objeto de dominio | D2: Tipo de dato | E2: Obligatorio | F2: Longitud mínima (si aplica) | G2: Longitud máxima (si aplica) | H2: Precisión (si aplica) | I2: Rendondeo (si aplica) | J2: Rango inicial (si aplica) | K2: Rango final (si aplica) | L2: Formato (si aplica) | M2: Reglas especiales (si aplica) | N2: Dato calculado | O2: Aplica ajuste del dato (si aplica) | P2: Carácter de ajuste (si aplica) | Q2: Quitar espacios en blanco al inicio (si aplica) | R2: Quitar espacios en blanco al fin (si aplica) | S2: Dato sensible (si aplica) | T2: Valor por defecto (si aplica) | U2: Auto generado | V2: =A16 -> ofrecerServicioNuevo | W2: =A18 -> editarServicio | Y2: =A21 -> consultarServiciosDisponibles | Z2: =A22 -> retirarServicio | AB2: =A26 -> reactivarServicio | AD2: =A28 -> consultarServiciosNoDisponibles
A3: ='M-Servicio'!A3 -> id | B3: ='M-Servicio'!A2 -> Representa un identificador que hará unico cada objeto de dominio de este tipo, no se puede repetir | C3: Si | D3: Identificador único universal | E3: Si | F3: No aplica | G3: No aplica | H3: No aplica | I3: No aplica | J3: No aplica | K3: No aplica | L3: No aplica | M3: No aplica | N3: No | O3: No aplica | P3: No aplica | Q3: No aplica | R3: No aplica | S3: No | T3: UUID vacio | U3: Si | V3: No requerido | W3: Requerido | X3: No modificable | Y3: No mostrar | Z3: Requerido | AA3: No modificable | AB3: Requerido | AC3: No modificable | AD3: No mostrar
A4: ='M-Servicio'!B3 -> sedeDeLaBarberia | B4: ='M-Servicio'!B2 -> Representa a cual barberia y sede va a pertenecer el servicio | C4: No | D4: Sede | E4: Si | F4: No aplica | G4: No aplica | H4: No aplica | I4: No aplica | J4: No aplica | K4: No aplica | L4: No aplica | M4: Aplican las reglas del objeto referenciado | N4: No | O4: No aplica | P4: No aplica | Q4: No aplica | R4: No aplica | S4: No | T4: UUID vacio | U4: No | V4: Requerido | W4: No requerido | X4: No modificable | Y4: No mostrar | Z4: No requerido | AA4: No modificable | AB4: No requerido | AC4: No modificable | AD4: No mostrar
A5: ='M-Servicio'!C3 -> nombre | B5: ='M-Servicio'!C2 -> Representa el nombre del servicio que va estar en la barberia, para que el barbero elija los servicios que el sabe hacer | C5: No | D5: Alfanumérico | E5: Si | F5: 3 | G5: 50 | H5: No aplica | I5: No aplica | J5: No aplica | K5: No aplica | L5: No aplica | M5: Solo se aceptan caracteres de letras de la 'a' a la 'z' y caracteres con tilde | N5: No | O5: No aplica | P5: No aplica | Q5: Si | R5: Si | S5: No | T5: Vacio | U5: No | V5: Requerido | W5: Requerido | X5: Modificable | Y5: Mostrar | Z5: No requerido | AA5: No modificable | AB5: No requerido | AC5: No modificable | AD5: Mostrar
A6: ='M-Servicio'!D3 -> descripcion | B6: ='M-Servicio'!D2 -> Representa una descripcion de que va a hacer cada servicio en la barberia, para que el barbero sepa que hace el servicio | C6: No | D6: Alfanumérico | E6: No | F6: 0 | G6: 200 | H6: No aplica | I6: No aplica | J6: No aplica | K6: No aplica | L6: No aplica | M6: Solo se aceptan caracteres de letras de la 'a' a la 'z', caracteres con tilde y espacios en blanco | N6: No | O6: No aplica | P6: No aplica | Q6: Si | R6: Si | S6: No | T6: Vacio | U6: No | V6: Requerido | W6: Requerido | X6: Modificable | Y6: Mostrar | Z6: No requerido | AA6: No modificable | AB6: No requerido | AC6: No modificable | AD6: Mostrar
A7: ='M-Servicio'!E3 -> precio | B7: ='M-Servicio'!E2 -> Representa cuanto va a valer el servicio en pesos colombianos | C7: No | D7: Entero | E7: Si | F7: No aplica | G7: No aplica | H7: No aplica | I7: No aplica | J7: 0 | K7: 2000000 | L7: No aplica | M7: No aplica | N7: No | O7: No aplica | P7: No aplica | Q7: No aplica | R7: No aplica | S7: No | T7: 0 | U7: No | V7: Requerido | W7: Requerido | X7: Modificable | Y7: Mostrar | Z7: No requerido | AA7: No modificable | AB7: No requerido | AC7: No modificable | AD7: Mostrar
A8: ='M-Servicio'!F3 -> disponible | B8: ='M-Servicio'!F2 -> Representa si el servicio sigue o no disponible en la barberia | C8: No | D8: Lógico | E8: Si | F8: No aplica | G8: No aplica | H8: No aplica | I8: No aplica | J8: No aplica | K8: No aplica | L8: No aplica | M8: No aplica | N8: No | O8: No aplica | P8: No aplica | Q8: No aplica | R8: No aplica | S8: No | T8: Si | U8: Si | V8: No requerido | W8: No requerido | X8: No modificable | Y8: No mostrar | Z8: No requerido | AA8: Modificable | AB8: No requerido | AC8: Modificable | AD8: No mostrar
A10: Nombre combinación única | B10: Descripción | C10: Atributos involucrados
A11: ='M-Servicio'!G3 -> Combinacion única | B11: ='M-Servicio'!G2 -> Combinacion única que indica que no puede existir más de un servicio con el mismo nombre en la misma barberia y sede | C11: =A4 -> sedeDeLaBarberia
C12: =A5 -> nombre
A14: Responsabilidad | C14: Descripción | G14: Entradas | J14: Salida | O14: Políticas (Reglas de Negocio) | Q14: Excepción
G15: Parámetro | H15: Tipo de dato | I15: Descripción | J15: Tipo de Dato | K15: Descripción | O15: Política | P15: Descripción | Q15: Detalle | R15: ¿Qué hago?
A16: ofrecerServicioNuevo | C16: Comando que permite registrar un nuevo tipo de servicio que la barbería pondrá a disposición de los barberos | G16: datos{sedeDeLaBarberia, nombre, descripcion, precio} | H16: Servicio | I16: Contiene la información requerida para registrar un nuevo servicio de la barbería | J16: Servicio | K16: Contiene la información del servicio registrado | O16: ='P-Servicio'!A6 -> P-SER-0001 | P16: ='P-Servicio'!B6 -> Asegurar que los datos requeridos del servicio (sede de la barbería, nombre, descripción, precio) sean válidos | Q16: Generar una excepción indicándole al usuario cuáles datos del servicio no cumplen con las reglas definidas | R16: Detener operación
O17: ='P-Servicio'!A7 -> P-SER-0002 | P17: ='P-Servicio'!B7 -> Asegurar que no exista otro servicio registrado con el mismo nombre en la misma sede de la barbería | Q17: Generar una excepción indicándole al usuario que ya existe un servicio registrado con ese mismo nombre en la barbería | R17: Detener operación
A18: editarServicio | C18: Permite modificar todos los atibutos de un servicio, que son el nombre, la descripción y el precio | G18: id | H18: UUID | I18: Corresponde al identificador del servicio que se va a editar | J18: Servicio | K18: Contiene la información del servicio con sus datos actualizados | O18: ='P-Servicio'!A9 -> P-SER-0004 | P18: ='P-Servicio'!B9 -> Asegurar que exista el servicio con el id enviado | Q18: Informar con un mensaje que no existe un servicio con el identificador enviado y por lo tanto no es posible modificar el servicio | R18: Detener operación
G19: datos{sedeDeLaBarberia, nombre, descripcion, precio} | H19: Servicio | I19: Contiene los datos con los que se va a modificar el servicio | O19: ='P-Servicio'!A6 -> P-SER-0001 | P19: ='P-Servicio'!B6 -> Asegurar que los datos requeridos del servicio (sede de la barbería, nombre, descripción, precio) sean válidos | Q19: Generar una excepción indicándole al usuario cuáles datos del servicio no cumplen con las reglas definidas | R19: Detener operación
O20: ='P-Servicio'!A7 -> P-SER-0002 | P20: ='P-Servicio'!B7 -> Asegurar que no exista otro servicio registrado con el mismo nombre en la misma sede de la barbería | Q20: Generar una excepción indicándole al usuario que ya existe un servicio registrado con ese mismo nombre en la barbería | R20: Detener operación
A21: consultarServiciosDisponibles | C21: Permite consultar el catálogo de servicios que ofrece la barbería | G21: filtro{sedeDeLaBarberia} | H21: Sede | I21: Contiene a la sede y barberia que se va a consultar los servicios | J21: Lista<Servicio> | K21: Contiene todos los servicios disponibles en la sede de la barberia que se esta consultando
A22: retirarServicio | C22: Permite retirar un servicio de la sede para que deje de ofrecerse a nuevos clientes y cancelar sus citas futuras | G22: id | H22: UUID | I22: Corresponde al identificador del servicio que se va a retirar | J22: No retorna ningún valor. En caso de error genera una excepción. | O22: ='P-Servicio'!A8 -> P-SER-0003 | P22: ='P-Servicio'!B8 -> Asegurar que el servicio a retirar no esté siendo ofrecido actualmente por ningún barbero vigente | Q22: Generar una excepción indicándole al usuario que el servicio no se puede retirar porque todavía lo ofrece al menos un barbero vigente | R22: Detener operación
O23: ='P-Servicio'!A9 -> P-SER-0004 | P23: ='P-Servicio'!B9 -> Asegurar que exista el servicio con el id enviado | Q23: Informar con un mensaje que no existe un servicio con el identificador enviado y por lo tanto no es posible desactivar el servicio | R23: Detener operación
O24: ='P-Servicio'!A11 -> P-SER-0006 | P24: ='P-Servicio'!B11 -> Asegurar que el servicio que se va a retirar no se encuentre retirado (disponible = si) | Q24: Generar una excepción indicándole al usuario que el servicio ya se encuentra retirado | R24: Detener operación
O25: ='P-Servicio'!A12 -> P-SER-0007 | P25: ='P-Servicio'!B12 -> Cuando el administrador retire un servicio de una sede de la barbería, las citas futuras en estado Agendada que incluyan ese servicio deben quedar canceladas en el estado Cancelación; las citas pasadas no se modifican | Q25: Si alguna de las citas futuras no pudo ser cancelada, revertir el retiro del servicio | R25: Detener operación
A26: reactivarServicio | C26: Permite volver a ofrecer un servicio que había sido retirado, para que vuelva a estar disponible para nuevos clientes en la sede de la barbería | G26: id | H26: UUID | I26: Corresponde al identificador del servicio que se va a volver a ofrecer | J26: No retorna ningún valor. En caso de error genera una excepción. | O26: ='P-Servicio'!A9 -> P-SER-0004 | P26: ='P-Servicio'!B9 -> Asegurar que exista el servicio con el id enviado | Q26: Informar con un mensaje que no existe un servicio con el identificador enviado | R26: Detener operación
O27: ='P-Servicio'!A10 -> P-SER-0005 | P27: ='P-Servicio'!B10 -> Asegurar que el servicio que se va a volver a ofrecer se encuentre retirado (disponible = no) | Q27: Generar una excepción indicándole al usuario que el servicio ya se encuentra disponible | R27: Detener operación
A28: consultarServiciosNoDisponibles | C28: Permite consultar el catálogo de servicios retirados en una sede de una barbería | G28: filtro{sedeDeLaBarberia} | H28: Sede | I28: Contiene la sede de la barbería que se va a consultar | J28: Lista<Servicio> | K28: Contiene todos los servicios retirados en la sede

Sheet P-Servicio
A1: << Ir al modelo de dominio | B1: << Ir al listado de objetos de dominio | C1: << Ir a la caracterización del objeto de dominio | D1: Ir al muestreo de datos del objeto de dominio >> | E1: Ir al event storming del objeto de dominio >>
A2: Objeto de Dominio: | B2: ='Objetos de Dominio'!A15 -> Servicio
A3: Descripción: | B3: ='Objetos de Dominio'!B15 -> Representa cada tipo de corte o arreglo que ofrece la barbería, definido por el administrador, para que luego cada barbero decida cuáles sabe hacer.
A4: Numero politica | B4: Descripcion politica | D4: Objeto responsable | E4: Regla responsable
A6: P-SER-0001 | B6: Asegurar que los datos requeridos del servicio (sede de la barbería, nombre, descripción, precio) sean válidos | D6: Servicio
A7: P-SER-0002 | B7: Asegurar que no exista otro servicio registrado con el mismo nombre en la misma sede de la barbería | D7: Servicio
A8: P-SER-0003 | B8: Asegurar que el servicio a retirar no esté siendo ofrecido actualmente por ningún barbero vigente | D8: BarberoServicio
A9: P-SER-0004 | B9: Asegurar que exista el servicio con el id enviado | D9: Servicio
A10: P-SER-0005 | B10: Asegurar que el servicio que se va a volver a ofrecer se encuentre retirado (disponible = no) | D10: Servicio
A11: P-SER-0006 | B11: Asegurar que el servicio que se va a retirar no se encuentre retirado (disponible = si) | D11: Servicio
A12: P-SER-0007 | B12: Cuando el administrador retire un servicio de una sede de la barbería, las citas futuras en estado Agendada que incluyan ese servicio deben quedar canceladas en el estado Cancelación; las citas pasadas no se modifican | D12: Cita
A13: P-SER-0008 | B13: Asegurar que el barbero solo pueda consultar los servicios disponibles de la sede en la que trabaja actualmente (su sedeDeTrabajo) | D13: Barbero

Sheet E-Servicio
A1: << Ir al modelo de dominio | C1: << Ir al listado de objetos de dominio | F1: << Ir a la caracterización del objeto de dominio | J1: Ir al muestreo de datos del objeto de dominio >>
A2: Objeto de Dominio: | B2: ='Objetos de Dominio'!A15 -> Servicio
A3: Descripción: | B3: ='Objetos de Dominio'!B15 -> Representa cada tipo de corte o arreglo que ofrece la barbería, definido por el administrador, para que luego cada barbero decida cuáles sabe hacer.
A4: Actor | B4: Action/Command | D4: Entity/Aggregate/Object domain | E4: Read Model | G4: Business Rule/Policy | I4: External System | J4: Domain Event | K4: Hotspot/questions/Risk
A5: Actor | B5: Acción | C5: Descripción | D5: Objeto de dominio | E5: Información externa | G5: Políticas | I5: Sistema Externo | J5: Evento | K5: Aspectos por solucionar
E6: Información | F6: Descripción | G6: Número | H6: Descripción
A7: Administrador | B7: Ofrecer un servicio nuevo a la barbería | C7: Comando que permite registrar un nuevo tipo de servicio que la sede de la barbería pondrá a disposición de los barberos | D7: =$B$2 -> Servicio | G7: ='P-Servicio'!A6 -> P-SER-0001 | H7: aquí | J7: Servicio ofrecido
G8: ='P-Servicio'!A7 -> P-SER-0002 | H8: aquí
A9: Administrador | B9: Editar un servicio | C9: Permite modificar todos los atibutos de un servicio, que son el nombre, la descripción y el precio | D9: =$B$2 -> Servicio | G9: ='P-Servicio'!A6 -> P-SER-0001 | H9: aquí | J9: Nombre, descripción, precio del servicio actualizados
G10: ='P-Servicio'!A7 -> P-SER-0002 | H10: aquí
A11: Administrador | B11: Ver servicios disponibles de la sede | C11: Permite consultar el catálogo de servicios que ofrece en una sede de una barberia | D11: =$B$2 -> Servicio | J11: Servicios consultados
A12: Barbero | B12: Ver servicios disponibles de la sede | C12: Permite consultar el catálogo de servicios que ofrece en una sede de una barberia | D12: =$B$2 -> Servicio | E12: Barbero | F12: Permite conocer la sede en la que trabaja actualmente el barbero. | G12: ='P-Servicio'!A13 -> P-SER-0008 | H12: aquí | J12: Servicios consultados
A13: Cliente | B13: Ver servicios disponibles de la sede | C13: Permite consultar el catálogo de servicios que ofrece en una sede de una barberia | D13: =$B$2 -> Servicio | J13: Servicios consultados
A14: Administrador | B14: Retirar un servicio de la sede de la barbería | C14: Permite retirar un servicio para que deje de ofrecerse a nuevos clientes | D14: =$B$2 -> Servicio | E14: CitaServicio | F14: Permite identificar las citas que incluyen el servicio que se va a retirar. | G14: ='P-Servicio'!A8 -> P-SER-0003 | H14: aquí | J14: Servicio retirado
E15: Cita | F15: Permite identificar cuáles de esas citas son futuras y siguen en estado Agendada. | G15: ='P-Servicio'!A11 -> P-SER-0006 | H15: aquí
E16: Agenda | F16: Permite conocer la fecha de cada cita para identificar cuáles son futuras (fecha y horaInicio posteriores al momento actual). | G16: ='P-Servicio'!A12 -> P-SER-0007 | H16: aquí
E17: Estado | F17: Permite dejar esas citas en el estado Cancelación.
A18: Administrador | B18: Volver a ofrecer un servicio en la sede de la barbería | C18: Permite volver a habilitar un servicio retirado para que esté disponible de nuevo para nuevos clientes | D18: =$B$2 -> Servicio | G18: ='P-Servicio'!A10 -> P-SER-0005 | H18: aquí | J18: Servicio reactivado
A19: Administrador | B19: Ver servicios no disponibles de la sede de la barberia | C19: Permite consultar el catálogo de servicios retirados en una sede de una barberia | D19: =$B$2 -> Servicio | J19: Servicios consultados

Sheet M-Servicio
A1: <<<< Ir al modulo de dominio | B1: <<<< Ir a objetos de dominio
A2: Representa un identificador que hará unico cada objeto de dominio de este tipo, no se puede repetir | B2: Representa a cual barberia y sede va a pertenecer el servicio | C2: Representa el nombre del servicio que va estar en la barberia, para que el barbero elija los servicios que el sabe hacer | D2: Representa una descripcion de que va a hacer cada servicio en la barberia, para que el barbero sepa que hace el servicio | E2: Representa cuanto va a valer el servicio en pesos colombianos | F2: Representa si el servicio sigue o no disponible en la barberia | G2: Combinacion única que indica que no puede existir más de un servicio con el mismo nombre en la misma barberia y sede
A3: id | B3: sedeDeLaBarberia | C3: nombre | D3: descripcion | E3: precio | F3: disponible | G3: Combinacion única
A4: 1 | B4: ='M-Sede'!F4 -> 900123456-7-Sede Poblado | C4: Motilada | D4: Corte de cabello completo con máquina y tijera, incluye lavado y secado | E4: 22000 | F4: si | G4: =_xlfn.CONCAT(B4,"-",C4) -> 900123456-7-Sede Poblado-Motilada
A5: 2 | B5: ='M-Sede'!F4 -> 900123456-7-Sede Poblado | C5: Corte de barba | D5: Recorte de la barba con máquina para dejarla pareja y a la medida que pide el cliente | E5: 12000 | F5: si | G5: =_xlfn.CONCAT(B5,"-",C5) -> 900123456-7-Sede Poblado-Corte de barba
A6: 3 | B6: ='M-Sede'!F4 -> 900123456-7-Sede Poblado | C6: Perfilada de barba | D6: Delineado de los bordes de la barba y el bigote con navaja, sin recortar el largo | E6: 15000 | F6: si | G6: =_xlfn.CONCAT(B6,"-",C6) -> 900123456-7-Sede Poblado-Perfilada de barba
A7: 4 | B7: ='M-Sede'!F4 -> 900123456-7-Sede Poblado | C7: Arreglo completo de barba con toalla caliente | D7: Recorte, perfilado con navaja, toalla caliente, exfoliación y aceite para la barba | E7: 35000 | F7: si | G7: =_xlfn.CONCAT(B7,"-",C7) -> 900123456-7-Sede Poblado-Arreglo completo de barba con toalla caliente
B13: Corresponde a la descripcion de los atributos
B14: Corresponde al identificador unico del objeto de dominio
B15: Corresponde a las referencias de otros objetos de dominio
B16: Corresponde a los datos que ingresa el usuario
B17: Corresponde a los datos auto generados por el sistema
B18: Corresponde a la combinacion única

Sheet C-BarberoServicio
A1: <<<< Ir al modulo de dominio | B1: <<<< Ir a objetos de dominio
A2: Nombre atributo | B2: Descripción atributo | C2: Identificador del objeto de dominio | D2: Tipo de dato | E2: Obligatorio | F2: Longitud mínima (si aplica) | G2: Longitud máxima (si aplica) | H2: Precisión (si aplica) | I2: Rendondeo (si aplica) | J2: Rango inicial (si aplica) | K2: Rango final (si aplica) | L2: Formato (si aplica) | M2: Reglas especiales (si aplica) | N2: Dato calculado | O2: Aplica ajuste del dato (si aplica) | P2: Carácter de ajuste (si aplica) | Q2: Quitar espacios en blanco al inicio (si aplica) | R2: Quitar espacios en blanco al fin (si aplica) | S2: Dato sensible (si aplica) | T2: Valor por defecto (si aplica) | U2: Auto generado | V2: =A17 -> habilitarServicioBarbero | W2: =A20 -> ajustarTiemposServicioBarbero | Y2: =A23 -> consultarServiciosElegidos | Z2: =A24 -> consultarServiciosDeBarbero | AA2: =A25 -> desactivarServicioBarbero | AB2: =A27 -> reactivarServicioBarbero
A3: ='M-BarberoServicio'!A3 -> id | B3: ='M-BarberoServicio'!A2 -> Representa un identificador que hará unico cada objeto de dominio de este tipo, no se puede repetir | C3: Si | D3: Identificador único universal | E3: Si | F3: No aplica | G3: No aplica | H3: No aplica | I3: No aplica | J3: No aplica | K3: No aplica | L3: No aplica | M3: No aplica | N3: No | O3: No aplica | P3: No aplica | Q3: No aplica | R3: No aplica | S3: No | T3: UUID vacio | U3: Si | V3: No requerido | W3: Requerido | X3: No modificable | Y3: No mostrar | Z3: No mostrar | AA3: Requerido | AB3: Requerido
A4: ='M-BarberoServicio'!B3 -> barbero | B4: ='M-BarberoServicio'!B2 -> Representa el nombre y apellidos del barbero | C4: No | D4: Barbero | E4: Si | F4: No aplica | G4: No aplica | H4: No aplica | I4: No aplica | J4: No aplica | K4: No aplica | L4: No aplica | M4: Aplican las reglas del objeto referenciado | N4: No | O4: No aplica | P4: No aplica | Q4: No aplica | R4: No aplica | S4: No | T4: UUID vacio | U4: No | V4: Requerido | W4: No requerido | X4: No modificable | Y4: No mostrar | Z4: Mostrar | AA4: No requerido | AB4: No requerido
A5: ='M-BarberoServicio'!C3 -> servicio | B5: ='M-BarberoServicio'!C2 -> Representa el nombre del servicio de la barberia | C5: No | D5: Servicio | E5: Si | F5: No aplica | G5: No aplica | H5: No aplica | I5: No aplica | J5: No aplica | K5: No aplica | L5: No aplica | M5: Aplican las reglas del objeto referenciado | N5: No | O5: No aplica | P5: No aplica | Q5: No aplica | R5: No aplica | S5: No | T5: UUID vacio | U5: No | V5: Requerido | W5: No requerido | X5: No modificable | Y5: Mostrar | Z5: Mostrar | AA5: No requerido | AB5: No requerido
A6: ='M-BarberoServicio'!D3 -> duracionEnHoras | B6: ='M-BarberoServicio'!D2 -> Representa la cantidad de horas que un barbero tarda en realizar un servicio, esta duracion el barbero debe de ser consiente de cuanto se demora en realizarlo | C6: No | D6: Entero | E6: Si | F6: No aplica | G6: No aplica | H6: No aplica | I6: No aplica | J6: 0 | K6: 3 | L6: No aplica | M6: No aplica | N6: No | O6: No aplica | P6: No aplica | Q6: No aplica | R6: No aplica | S6: No | T6: 0 | U6: No | V6: Requerido | W6: Requerido | X6: Modificable | Y6: Mostrar | Z6: No mostrar | AA6: No requerido | AB6: No requerido
A7: ='M-BarberoServicio'!E3 -> duracionEnMinutos | B7: ='M-BarberoServicio'!E2 -> Representa la cantidad de minutos que un barbero tarda en realizar un servicio, esta duracion el barbero debe de ser consiente de cuanto se demora en realizarlo | C7: No | D7: Entero | E7: Si | F7: No aplica | G7: No aplica | H7: No aplica | I7: No aplica | J7: 0 | K7: 59 | L7: No aplica | M7: No aplica | N7: No | O7: No aplica | P7: No aplica | Q7: No aplica | R7: No aplica | S7: No | T7: 0 | U7: No | V7: Requerido | W7: Requerido | X7: Modificable | Y7: Mostrar | Z7: No mostrar | AA7: No requerido | AB7: No requerido
A8: ='M-BarberoServicio'!F3 -> tiempoExtra | B8: ='M-BarberoServicio'!F2 -> Representa la cantidad de minutos que un barbero pone de tiempo extra en las citas de su agenda, cada barbero usa este tiempo porque hay ocaciones que la cita se puede demorar más de lo previsto. Este tiempo les ayuda a evitar que se les retrase la agenda | C8: No | D8: Entero | E8: Si | F8: No aplica | G8: No aplica | H8: No aplica | I8: No aplica | J8: 0 | K8: 59 | L8: No aplica | M8: No aplica | N8: No | O8: No aplica | P8: No aplica | Q8: No aplica | R8: No aplica | S8: No | T8: 0 | U8: No | V8: Requerido | W8: Requerido | X8: Modificable | Y8: Mostrar | Z8: No mostrar | AA8: No requerido | AB8: No requerido
A9: ='M-BarberoServicio'!G3 -> vigente | B9: ='M-BarberoServicio'!G2 -> Representa si el barbero sigue o no presentando el servicio en la barbería | C9: No | D9: Lógico | E9: Si | F9: No aplica | G9: No aplica | H9: No aplica | I9: No aplica | J9: No aplica | K9: No aplica | L9: No aplica | M9: No aplica | N9: No | O9: No aplica | P9: No aplica | Q9: No aplica | R9: No aplica | S9: No | T9: Si | U9: No | V9: No requerido | W9: No requerido | X9: No modificable | Y9: No mostrar | Z9: No mostrar | AA9: No requerido | AB9: No requerido
A11: Nombre combinación única | B11: Descripción | C11: Atributos involucrados
A12: ='M-BarberoServicio'!H3 -> Combinación única | B12: ='M-BarberoServicio'!H2 -> Combinación única que indica que un mismo barbero no puede aparecer dos veces ofreciendo el mismo servicio | C12: barbero
C13: servicio
A15: Responsabilidad | C15: Descripción | G15: Entradas | J15: Salida | O15: Políticas (Reglas de Negocio) | Q15: Excepción
G16: Parámetro | H16: Tipo de dato | I16: Descripción | J16: Tipo de Dato | K16: Descripción | O16: Política | P16: Descripción | Q16: Detalle | R16: ¿Qué hago?
A17: habilitarServicioBarbero | C17: Comando que permite a un barbero indicar que sabe realizar un servicio del catálogo, con su duración y colchón | G17: datos{barbero, servicio, duracionEnHoras, duracionEnMinutos, tiempoExtra} | H17: BarberoServicio | I17: Contiene la información requerida para habilitarle un servicio a un barbero | J17: BarberoServicio | K17: Contiene la información del servicio habilitado para el barbero | O17: ='P-BarberoServicio'!A6 -> P-BSE-0001 | P17: ='P-BarberoServicio'!B6 -> Asegurar que los datos requeridos (duración en horas, duración en minutos, tiempo extra) sean válidos en tipo de dato, obligatoriedad y rango | Q17: Generar una excepción indicándole al barbero que los datos no cumplen las reglas definidas | R17: Detener operación
O18: ='P-BarberoServicio'!A7 -> P-BSE-0002 | P18: ='P-BarberoServicio'!B7 -> Asegurar que el barbero no tenga ya definido ese mismo servicio | Q18: Generar una excepción indicándole el barbero ya tiene habilitado ese mismo servicio | R18: Detener operación
O19: ='P-BarberoServicio'!A9 -> P-BSE-0004 | P19: ='P-BarberoServicio'!B9 -> Asegurar que la suma del tiempo en horas y minutos de la realizacion del servicio por el barbero sea mayor a cero | Q19: Generar una excepción indicándole al barbero que los no se puede realizar un servicio en tiempo cero, es decir que debe de poner un timpio mayor a cer, ya que en la hora o en el minuto | R19: Detener operación
A20: ajustarTiemposServicioBarbero | C20: Permite modificar la duración y el tiempo extra que un barbero usa para un servicio ya habilitado | G20: id | H20: UUID | I20: Corresponde al identificador del servicio del barbero que se va a ajustar | J20: BarberoServicio | K20: Contiene la información del servicio del barbero con sus tiempos actualizados | O20: ='P-BarberoServicio'!A8 -> P-BSE-0003 | P20: ='P-BarberoServicio'!B8 -> Asegurar que exista el servicio definido del barbero con el id enviado | Q20: Informar con un mensaje que no existe un servicio habilitado del barbero con el identificador enviado y por lo tanto no es posible llevar a cabo la operación | R20: Detener operación
G21: datos{duracionEnHoras, duracionEnMinutos, tiempoExtra} | H21: BarberoServicio | I21: Contiene los nuevos tiempos con los que se va a modificar el servicio | O21: ='P-BarberoServicio'!A6 -> P-BSE-0001 | P21: ='P-BarberoServicio'!B6 -> Asegurar que los datos requeridos (duración en horas, duración en minutos, tiempo extra) sean válidos en tipo de dato, obligatoriedad y rango | Q21: Generar una excepción indicándole al barbero que los datos no cumplen las reglas definidas | R21: Detener operación
O22: ='P-BarberoServicio'!A9 -> P-BSE-0004 | P22: ='P-BarberoServicio'!B9 -> Asegurar que la suma del tiempo en horas y minutos de la realizacion del servicio por el barbero sea mayor a cero | Q22: Generar una excepción indicándole al barbero que los no se puede realizar un servicio en tiempo cero, es decir que debe de poner un timpio mayor a cer, ya que en la hora o en el minuto | R22: Detener operación
A23: consultarServiciosElegidos | C23: Permite a un barbero consultar los servicios que esten vigentes | G23: filtro{barbero} | H23: BarberoServicio | I23: Contiene el barbero por el cual se van a consultar sus servicios habilitados | J23: Lista<BarberoServicio> | K23: Contiene todos los servicios que el barbero tiene habilitados
A24: consultarServiciosDeBarbero | C24: Permite a un cliente consultar qué servicios ofrece un barbero en particular | G24: filtro{barbero} | H24: BarberoServicio | I24: Contiene el barbero por el cual se van a consultar los servicios que ofrece | J24: Lista<BarberoServicio> | K24: Contiene todos los servicios vigentes que ofrece ese barbero
A25: desactivarServicioBarbero | C25: Permite a un barbero desactivar un servicio que ya no quiere seguir ofreciendo | G25: id | H25: UUID | I25: Corresponde al identificador del servicio del barbero que se va a desactivar | J25: No retorna ningún valor. En caso de error genera una excepción. | O25: ='P-BarberoServicio'!A8 -> P-BSE-0003 | P25: ='P-BarberoServicio'!B8 -> Asegurar que exista el servicio definido del barbero con el id enviado | Q25: Informar con un mensaje que no existe un servicio habilitado del barbero con el identificador enviado y por lo tanto no es posible llevar a cabo la operación | R25: Detener operación
O26: ='P-BarberoServicio'!A10 -> P-BSE-0005 | P26: ='P-BarberoServicio'!B10 -> Asegurar que el estado de BarberoServicio este vigente | Q26: Informar al barbero que el servicio que quiere desactivar, ya se encuentra desactivado | R26: Detener operación
A27: reactivarServicioBarbero | C27: Permite a un barbero activar un servicio que ya se habia desactivado | G27: id | H27: UUID | I27: Corresponde al identificador del servicio del barbero que se va a desactivar | J27: No retorna ningún valor. En caso de error genera una excepción. | O27: ='P-BarberoServicio'!A8 -> P-BSE-0003 | P27: ='P-BarberoServicio'!B8 -> Asegurar que exista el servicio definido del barbero con el id enviado | Q27: Informar con un mensaje que no existe un servicio habilitado del barbero con el identificador enviado y por lo tanto no es posible llevar a cabo la operación | R27: Detener operación
O28: ='P-BarberoServicio'!A11 -> P-BSE-0006 | P28: ='P-BarberoServicio'!B11 -> Asegurar que el estado del BarberoServicio no este vigente | Q28: Informar al barbero que el servicio que quiere reactivar, ya se encuentra activado | R28: Detener operación

Sheet P-BarberoServicio
A1: << Ir al modelo de dominio | B1: << Ir al listado de objetos de dominio | C1: << Ir a la caracterización del objeto de dominio | D1: Ir al muestreo de datos del objeto de dominio >> | E1: Ir al event storming del objeto de dominio >>
A2: Objeto de Dominio: | B2: ='Objetos de Dominio'!A16 -> BarberoServicio
A3: Descripción: | B3: ='Objetos de Dominio'!B16 -> Representa qué servicios sabe hacer cada barbero, cuánto se demora en realizarlos y cuánto tiempo extra usa de colchón, ya que no todos los barberos ofrecen los mismos servicios que están en la barbería.
A4: Numero politica | B4: Descripcion politica | D4: Objeto responsable | E4: Regla responsable
A6: P-BSE-0001 | B6: Asegurar que los datos requeridos (duración en horas, duración en minutos, tiempo extra) sean válidos en tipo de dato, obligatoriedad y rango | D6: BarberoServicio
A7: P-BSE-0002 | B7: Asegurar que el barbero no tenga ya definido ese mismo servicio | D7: BarberoServicio
A8: P-BSE-0003 | B8: Asegurar que exista el servicio definido del barbero con el id enviado | D8: BarberoServicio
A9: P-BSE-0004 | B9: Asegurar que la suma del tiempo en horas y minutos de la realizacion del servicio por el barbero sea mayor a cero | D9: BarberoServicio
A10: P-BSE-0005 | B10: Asegurar que el estado de BarberoServicio este vigente | D10: BarberoServicio
A11: P-BSE-0006 | B11: Asegurar que el estado del BarberoServicio no este vigente | D11: BarberoServicio

Sheet E-BarberoServicio
A1: << Ir al modelo de dominio | C1: << Ir al listado de objetos de dominio | F1: << Ir a la caracterización del objeto de dominio | J1: Ir al muestreo de datos del objeto de dominio >>
A2: Objeto de Dominio: | B2: ='Objetos de Dominio'!A16 -> BarberoServicio
A3: Descripción: | B3: ='Objetos de Dominio'!B16 -> Representa qué servicios sabe hacer cada barbero, cuánto se demora en realizarlos y cuánto tiempo extra usa de colchón, ya que no todos los barberos ofrecen los mismos servicios que están en la barbería.
A4: Actor | B4: Action/Command | D4: Entity/Aggregate/Object domain | E4: Read Model | G4: Business Rule/Policy | I4: External System | J4: Domain Event | K4: Hotspot/questions/Risk
A5: Actor | B5: Acción | C5: Descripción | D5: Objeto de dominio | E5: Información externa | G5: Políticas | I5: Sistema Externo | J5: Evento | K5: Aspectos por solucionar
E6: Información | F6: Descripción | G6: Número | H6: Descripción
A7: Barbero | B7: Definir un servicio para el barbero | C7: Comando que permite a un barbero indicar que sabe realizar un servicio del catálogo, con su duración y colchón | D7: =$B$2 -> BarberoServicio | G7: ='P-BarberoServicio'!A6 -> P-BSE-0001 | H7: aquí | J7: Servicio habilitado para barbero
G8: ='P-BarberoServicio'!A7 -> P-BSE-0002 | H8: aquí
G9: ='P-BarberoServicio'!A9 -> P-BSE-0004 | H9: aquí
A10: Barbero | B10: Ajustar los tiempos de un servicio del barbero | C10: Permite modificar la duración y el tiempo extra que un barbero usa para un servicio ya habilitado | D10: =$B$2 -> BarberoServicio | G10: ='P-BarberoServicio'!A6 -> P-BSE-0001 | H10: aquí | J10: Tiempos de servicio de barbero actualizados
G11: ='P-BarberoServicio'!A9 -> P-BSE-0004 | H11: aquí
A12: Barbero | B12: Ver servicios elegidos | C12: Permite a un barbero consultar los servicios que tiene habilitados | D12: =$B$2 -> BarberoServicio | J12: Servicios de barbero consultados
A13: Cliente | B13: Ver servicios de un barbero | C13: Permite a un cliente consultar qué servicios ofrece un barbero en particular | D13: =$B$2 -> BarberoServicio | J13: Servicios de barbero consultados
A14: Barbero | B14: Dejar de prestar el servicio para el catálogo | C14: Permite a un barbero desactivar un servicio que ya no quiere seguir ofreciendo | D14: =$B$2 -> BarberoServicio | G14: ='P-BarberoServicio'!A10 -> P-BSE-0005 | H14: aquí | J14: Servicio de barbero desactivado
A15: Barbero | B15: Volver prestar el servicio para el catálogo | C15: Permite a un barbero desactivar un servicio que ya no quiere seguir ofreciendo | D15: =$B$2 -> BarberoServicio | G15: ='P-BarberoServicio'!A11 -> P-BSE-0006 | H15: aquí | J15: Servicio de barbero reactivado

Sheet M-BarberoServicio
A1: <<<< Ir al modulo de dominio | B1: <<<< Ir a objetos de dominio
A2: Representa un identificador que hará unico cada objeto de dominio de este tipo, no se puede repetir | B2: Representa el nombre y apellidos del barbero | C2: Representa el nombre del servicio de la barberia | D2: Representa la cantidad de horas que un barbero tarda en realizar un servicio, esta duracion el barbero debe de ser consiente de cuanto se demora en realizarlo | E2: Representa la cantidad de minutos que un barbero tarda en realizar un servicio, esta duracion el barbero debe de ser consiente de cuanto se demora en realizarlo | F2: Representa la cantidad de minutos que un barbero pone de tiempo extra en las citas de su agenda, cada barbero usa este tiempo porque hay ocaciones que la cita se puede demorar más de lo previsto. Este tiempo les ayuda a evitar que se les retrase la agenda | G2: Representa si el barbero sigue o no presentando el servicio en la barbería | H2: Combinación única que indica que un mismo barbero no puede aparecer dos veces ofreciendo el mismo servicio
A3: id | B3: barbero | C3: servicio | D3: duracionEnHoras | E3: duracionEnMinutos | F3: tiempoExtra | G3: vigente | H3: Combinación única
A4: 1 | B4: =_xlfn.CONCAT('M-Barbero'!B4," ",'M-Barbero'!D4) -> Juan García | C4: ='M-Servicio'!C4 -> Motilada | D4: 0 | E4: 45 | F4: 15 | G4: si | H4: =_xlfn.CONCAT(B4,"-",C4) -> Juan García-Motilada
A5: 2 | B5: =_xlfn.CONCAT('M-Barbero'!B5," ",'M-Barbero'!D5) -> Juan Ortiz | C5: ='M-Servicio'!C5 -> Corte de barba | D5: 0 | E5: 10 | F5: 5 | G5: si | H5: =_xlfn.CONCAT(B5,"-",C5) -> Juan Ortiz-Corte de barba
A6: 3 | B6: =_xlfn.CONCAT('M-Barbero'!B6," ",'M-Barbero'!D6) -> Carlos Arbeladez | C6: ='M-Servicio'!C6 -> Perfilada de barba | D6: 0 | E6: 15 | F6: 5 | G6: si | H6: =_xlfn.CONCAT(B6,"-",C6) -> Carlos Arbeladez-Perfilada de barba
A7: 4 | B7: =_xlfn.CONCAT('M-Barbero'!B7," ",'M-Barbero'!D7) -> Andres Ramirez | C7: ='M-Servicio'!C7 -> Arreglo completo de barba con toalla caliente | D7: 0 | E7: 40 | F7: 10 | G7: si | H7: =_xlfn.CONCAT(B7,"-",C7) -> Andres Ramirez-Arreglo completo de barba con toalla caliente
A8: 5 | B8: =_xlfn.CONCAT('M-Barbero'!B5," ",'M-Barbero'!D5) -> Juan Ortiz | C8: ='M-Servicio'!C4 -> Motilada | D8: 0 | E8: 40 | F8: 10 | G8: si | H8: =_xlfn.CONCAT(B8,"-",C8) -> Juan Ortiz-Motilada
A9: 6 | B9: =_xlfn.CONCAT('M-Barbero'!B6," ",'M-Barbero'!D6) -> Carlos Arbeladez | C9: ='M-Servicio'!C5 -> Corte de barba | D9: 0 | E9: 15 | F9: 5 | G9: si | H9: =_xlfn.CONCAT(B9,"-",C9) -> Carlos Arbeladez-Corte de barba
A10: 7 | B10: =_xlfn.CONCAT('M-Barbero'!B4," ",'M-Barbero'!D4) -> Juan García | C10: ='M-Servicio'!C6 -> Perfilada de barba | D10: 0 | E10: 20 | F10: 5 | G10: si | H10: =_xlfn.CONCAT(B10,"-",C10) -> Juan García-Perfilada de barba
A11: 8 | B11: =_xlfn.CONCAT('M-Barbero'!B7," ",'M-Barbero'!D7) -> Andres Ramirez | C11: ='M-Servicio'!C4 -> Motilada | D11: 0 | E11: 50 | F11: 15 | G11: si | H11: =_xlfn.CONCAT(B11,"-",C11) -> Andres Ramirez-Motilada
A12: 9 | B12: =_xlfn.CONCAT('M-Barbero'!B8," ",'M-Barbero'!D8) -> Juan Zambrano | C12: ='M-Servicio'!C5 -> Corte de barba | D12: 0 | E12: 12 | F12: 5 | G12: si | H12: =_xlfn.CONCAT(B12,"-",C12) -> Juan Zambrano-Corte de barba
B18: Corresponde a la descripcion de los atributos
B19: Corresponde al identificador unico del objeto de dominio
B20: Corresponde a las referencias de otros objetos de dominio
B21: Corresponde a los datos que ingresa el usuario
B22: Corresponde a los datos auto generados por el sistema
B23: Corresponde a la combinacion única

Sheet C-Bloqueo
A1: <<<< Ir al modulo de dominio | B1: <<<< Ir a objetos de dominio
A2: Nombre atributo | B2: Descripción atributo | C2: Identificador del objeto de dominio | D2: Tipo de dato | E2: Obligatorio | F2: Longitud mínima (si aplica) | G2: Longitud máxima (si aplica) | H2: Precisión (si aplica) | I2: Rendondeo (si aplica) | J2: Rango inicial (si aplica) | K2: Rango final (si aplica) | L2: Formato (si aplica) | M2: Reglas especiales (si aplica) | N2: Dato calculado | O2: Aplica ajuste del dato (si aplica) | P2: Carácter de ajuste (si aplica) | Q2: Quitar espacios en blanco al inicio (si aplica) | R2: Quitar espacios en blanco al fin (si aplica) | S2: Dato sensible (si aplica) | T2: Valor por defecto (si aplica) | U2: Auto generado | V2: =A15 -> definirBloqueo | W2: =A19 -> eliminarBloqueo | X2: =A21 -> consultarBloqueosPorFecha | Y2: =A22 -> consultarBloqueoPorFechaHora | Z2: =A23 -> editarBloqueo
A3: ='M-Bloqueo'!A3 -> id | B3: ='M-Bloqueo'!A2 -> Representa un identificador que hará unico cada objeto de dominio de este tipo, no se puede repetir | C3: Si | D3: Identificador único universal | E3: Si | F3: No aplica | G3: No aplica | H3: No aplica | I3: No aplica | J3: No aplica | K3: No aplica | L3: No aplica | M3: No aplica | N3: No | O3: No | P3: No aplica | Q3: No | R3: No | S3: No | T3: UUID vacio | U3: Si | V3: No requerido | W3: Requerido | X3: No mostrar | Y3: No mostrar | Z3: Requerido | AA3: No modificable
A4: ='M-Bloqueo'!B3 -> barbero | B4: ='M-Bloqueo'!B2 -> Referencia a qué barbero le pertence este bloqueo | C4: No | D4: Barbero | E4: Si | F4: No aplica | G4: No aplica | H4: No aplica | I4: No aplica | J4: No aplica | K4: No aplica | L4: No aplica | M4: Aplican las reglas del objeto referenciado | N4: No | O4: No aplica | P4: No aplica | Q4: No aplica | R4: No aplica | S4: No | T4: UUID vacio | U4: No | V4: Requerido | W4: No requerido | X4: No mostrar | Y4: No mostrar | Z4: No requerido | AA4: No modificable
A5: ='M-Bloqueo'!C3 -> fechaHoraInicio | B5: ='M-Bloqueo'!C2 -> Representa la fecha y hora en el que el barbero empieza a no estar disponible para atender las citas | C5: No | D5: Fecha hora | E5: Si | F5: No aplica | G5: No aplica | H5: No aplica | I5: No aplica | J5: No aplica | K5: No aplica | L5: No aplica | M5: No aplica | N5: No | O5: No aplica | P5: No aplica | Q5: No aplica | R5: No aplica | S5: No | T5: 01/01/1000 00:00 | U5: No | V5: Requerido | W5: No requerido | X5: Mostrar | Y5: Mostrar | Z5: Requerido | AA5: Modificable
A6: ='M-Bloqueo'!D3 -> fechaHoraFinal | B6: ='M-Bloqueo'!D2 -> Representa la fecha y hora en el que el barbero empieza estar disponible nuevamente para atender las citas | C6: No | D6: Fecha hora | E6: Si | F6: No aplica | G6: No aplica | H6: No aplica | I6: No aplica | J6: No aplica | K6: No aplica | L6: No aplica | M6: Debe ser posterior a fechaHoraInicio | N6: No | O6: No aplica | P6: No aplica | Q6: No aplica | R6: No aplica | S6: No | T6: 01/01/1000 00:00 | U6: No | V6: Requerido | W6: No requerido | X6: Mostrar | Y6: Mostrar | Z6: Requerido | AA6: Modificable
A8: Nombre combinación única | B8: Descripción | C8: Atributos involucrados
A9: ='M-Bloqueo'!E3 -> Combinación única | B9: ='M-Bloqueo'!E2 -> Combinación única que indica que un mismo barbero no puede tener dos bloqueos con la misma fecha y hora de inicio y la misma fecha y hora final | C9: =A4 -> barbero
C10: =A5 -> fechaHoraInicio
C11: =A6 -> fechaHoraFinal
A13: Responsabilidad | C13: Descripción | G13: Entradas | J13: Salida | O13: Políticas (Reglas de Negocio) | Q13: Excepción
G14: Parámetro | H14: Tipo de dato | I14: Descripción | J14: Tipo de Dato | K14: Descripción | O14: Política | P14: Descripción | Q14: Detalle | R14: ¿Qué hago?
A15: definirBloqueo | C15: Comando que permite a un barbero asignar un espacio de no disponibilidad para atender sus citas | G15: datos{barbero, fechaHoraInicio, fechaHoraFinal} | H15: Bloqueo | I15: Contiene la información requerida para registrar un nuevo bloqueo del barbero | J15: Bloqueo | K15: Contiene la información del bloqueo registrado | O15: ='P-Bloqueo'!A6 -> P-BLO-0001 | P15: ='P-Bloqueo'!B6 -> Asegurar que los datos requeridos (fecha y hora de inicio, fecha y hora de fin) sean válidos en tipo de dato, obligatoriedad, formato y rango | Q15: Generar una excepción indicándole al barbero que los datos no cumplen los datos requeridos | R15: Detener operación
O16: ='P-Bloqueo'!A7 -> P-BLO-0002 | P16: ='P-Bloqueo'!B7 -> Rechazar el bloqueo si ya existen citas agendadas dentro de ese mismo rango elegido | Q16: Generar una excepción indicándole al barbero que ese rango no se puede bloquear porque ya tiene citas agendadas | R16: Detener operación
O17: ='P-Bloqueo'!A10 -> P-BLO-0005 | P17: ='P-Bloqueo'!B10 -> Asegurar que el bloqueo no se cruze con otro bloqueo suyo | Q17: Generar una excepción indicándole al barbero que el rango se solapa con otro bloqueo suyo | R17: Detener operación
O18: ='P-Bloqueo'!A12 -> P-BLO-0007 | P18: ='P-Bloqueo'!B12 -> Asegurar que la fecha y hora de fin sea mayor a la fecha y hora de inicio | Q18: Generar una excepción indicandole al barbero que la fecha y hora de fin debe de ser mayor a la fecha y hora de inicio | R18: Detener operación
A19: eliminarBloqueo | C19: Permite a un barbero liberar un espacio de su agenda que había bloqueado previamente | G19: id | H19: UUID | I19: Corresponde al identificador del bloqueo que se va a eliminar | J19: No retorna ningún valor. En caso de error genera una excepción. | O19: ='P-Bloqueo'!A9 -> P-BLO-0004 | P19: ='P-Bloqueo'!B9 -> Asegurar que el bloqueo que se va a editar o eliminar le pertenezca al mismo barbero que hace la solicitud | Q19: Generar una excepción indicándole al usuario que el bloqueo no le pertenece | R19: Detener operación
O20: ='P-Bloqueo'!A11 -> P-BLO-0006 | P20: ='P-Bloqueo'!B11 -> Asegurar que exista el bloqueo con el id enviado | Q20: Informar con un mensaje que no existe un bloqueo con el identificador enviado y por lo tanto no es posible llevar a cabo la operación | R20: Detener operación
A21: consultarBloqueosPorFecha | C21: Permite a un barbero ver los espacios que tiene bloqueados en una fecha dada | G21: filtro{barbero, fecha} | H21: Bloqueo | I21: Contiene el barbero y la fecha por los cuales se van a consultar los bloqueos | J21: Lista<Bloqueo> | K21: Contiene todos los bloqueos del barbero en esa fecha
A22: consultarBloqueoPorFechaHora | C22: Permite al sistema ver si hay o no un bloqueo en una fecha y hora, en el que empieza el bloqueo, para que el determine luego si el cliente puede agenda una cita en ese momento | G22: filtro{barbero, fechaHoraInicio} | H22: Bloqueo | I22: Contiene el barbero y la fecha y hora por las cuales se va a consultar el bloqueo | J22: Bloqueo | K22: Contiene el bloqueo que cubre esa fecha y hora, si existe
A23: editarBloqueo | C23: Permite al barbero poder editar la fecha y hora en que inicia o termina | G23: id | H23: UUID | I23: Corresponde al identificador del bloqueo que se va a editar | J23: Bloqueo | K23: Contiene la información del bloqueo con su rango actualizado | O23: ='P-Bloqueo'!A11 -> P-BLO-0006 | P23: ='P-Bloqueo'!B11 -> Asegurar que exista el bloqueo con el id enviado | Q23: Informar con un mensaje que no existe un bloqueo con el identificador enviado y por lo tanto no es posible llevar a cabo la operación | R23: Detener operación
G24: datos{fechaHoraInicio, fechaHoraFinal} | H24: Bloqueo | I24: Contiene el nuevo rango con el que se va a modificar el bloqueo | O24: ='P-Bloqueo'!A8 -> P-BLO-0003 | P24: ='P-Bloqueo'!B8 -> Asegurar que los datos requeridos para editar el bloqueo (fecha y hora de inicio, fecha y hora de fin) sean válidos en tipo de dato, obligatoriedad, formato y rango, y que la fecha y hora de fin sea mayor a la de inicio | Q24: Generar una excepción indicándole al usuario cuáles datos del bloqueo que se va a editar no cumplen con las reglas definidas | R24: Detener operación
O25: ='P-Bloqueo'!A7 -> P-BLO-0002 | P25: ='P-Bloqueo'!B7 -> Rechazar el bloqueo si ya existen citas agendadas dentro de ese mismo rango elegido | Q25: Generar una excepción indicándole al usuario que ese rango no se puede bloquear porque ya tiene citas agendadas | R25: Detener operación

Sheet P-Bloqueo
A1: << Ir al modelo de dominio | B1: << Ir al listado de objetos de dominio | C1: << Ir a la caracterización del objeto de dominio | D1: Ir al muestreo de datos del objeto de dominio >> | E1: Ir al event storming del objeto de dominio >>
A2: Objeto de Dominio: | B2: ='Objetos de Dominio'!A17 -> Bloqueo
A3: Descripción: | B3: ='Objetos de Dominio'!B17 -> Representa los momentos en que el barbero no esta disponible para atender sus citas, el barbero establece la hora y la fecha en que empieza y termina ese estado de no disponible.
A4: Numero politica | B4: Descripcion politica | D4: Objeto responsable | E4: Regla responsable
A6: P-BLO-0001 | B6: Asegurar que los datos requeridos (fecha y hora de inicio, fecha y hora de fin) sean válidos en tipo de dato, obligatoriedad, formato y rango | D6: Bloqueo
A7: P-BLO-0002 | B7: Rechazar el bloqueo si ya existen citas agendadas dentro de ese mismo rango elegido | D7: Cita
A8: P-BLO-0003 | B8: Asegurar que los datos requeridos para editar el bloqueo (fecha y hora de inicio, fecha y hora de fin) sean válidos en tipo de dato, obligatoriedad, formato y rango, y que la fecha y hora de fin sea mayor a la de inicio | D8: Bloqueo
A9: P-BLO-0004 | B9: Asegurar que el bloqueo que se va a editar o eliminar le pertenezca al mismo barbero que hace la solicitud | D9: Bloqueo
A10: P-BLO-0005 | B10: Asegurar que el bloqueo no se cruze con otro bloqueo suyo | D10: HorarioBarbero
A11: P-BLO-0006 | B11: Asegurar que exista el bloqueo con el id enviado | D11: Bloqueo
A12: P-BLO-0007 | B12: Asegurar que la fecha y hora de fin sea mayor a la fecha y hora de inicio | D12: Bloqueo

Sheet E-Bloqueo
A1: << Ir al modelo de dominio | C1: << Ir al listado de objetos de dominio | F1: << Ir a la caracterización del objeto de dominio | J1: Ir al muestreo de datos del objeto de dominio >>
A2: Objeto de Dominio: | B2: ='Objetos de Dominio'!A17 -> Bloqueo
A3: Descripción: | B3: ='Objetos de Dominio'!B17 -> Representa los momentos en que el barbero no esta disponible para atender sus citas, el barbero establece la hora y la fecha en que empieza y termina ese estado de no disponible.
A4: Actor | B4: Action/Command | D4: Entity/Aggregate/Object domain | E4: Read Model | G4: Business Rule/Policy | I4: External System | J4: Domain Event | K4: Hotspot/questions/Risk
A5: Actor | B5: Acción | C5: Descripción | D5: Objeto de dominio | E5: Información externa | G5: Políticas | I5: Sistema Externo | J5: Evento | K5: Aspectos por solucionar
E6: Información | F6: Descripción | G6: Número | H6: Descripción
A7: Barbero | B7: Definir un bloque de no disponible | C7: Comando que permite a un barbero asiganar un espacio de no disponibilidad para atender sus citas | D7: =$B$2 -> Bloqueo | E7: HorarioBarbero | F7: Permite llegar de las agendas al barbero dueño de cada cita, ya que la cita no referencia al barbero directamente. | G7: ='P-Bloqueo'!A6 -> P-BLO-0001 | H7: ='P-Bloqueo'!B6 -> Asegurar que los datos requeridos (fecha y hora de inicio, fecha y hora de fin) sean válidos en tipo de dato, obligatoriedad, formato y rango | J7: Bloqueo registrado
E8: Agenda | F8: Permite conocer la fecha de cada cita, ya que la cita solo almacena horas. Es lo que hace comparable el rango del bloqueo contra las citas existentes. | G8: ='P-Bloqueo'!A7 -> P-BLO-0002 | H8: ='P-Bloqueo'!B7 -> Rechazar el bloqueo si ya existen citas agendadas dentro de ese mismo rango elegido
E9: Cita | F9: Permite verificar que no haya citas ya agendadas dentro del rango que se va a bloquear. | G9: ='P-Bloqueo'!A10 -> P-BLO-0005 | H9: ='P-Bloqueo'!B10 -> Asegurar que el bloqueo no se cruze con otro bloqueo suyo
E10: Estado | F10: Permite descartar las citas canceladas, que no deben impedir el bloqueo. | G10: ='P-Bloqueo'!A12 -> P-BLO-0007 | H10: ='P-Bloqueo'!B12 -> Asegurar que la fecha y hora de fin sea mayor a la fecha y hora de inicio
A11: Barbero | B11: Eliminar un bloqueo | C11: Permite a un barbero liberar un espacio de su agenda que había bloqueado previamente | D11: =$B$2 -> Bloqueo | G11: ='P-Bloqueo'!A9 -> P-BLO-0004 | H11: ='P-Bloqueo'!B9 -> Asegurar que el bloqueo que se va a editar o eliminar le pertenezca al mismo barbero que hace la solicitud | J11: Bloqueo cancelado
A12: Barbero | B12: Ver bloqueos en una fecha | C12: Permite a un barbero ver los espacios que tiene bloqueados en una fecha dada | D12: =$B$2 -> Bloqueo | J12: Bloqueos vistos
A13: Sistema | B13: Ver bloqueo en una fecha y hora de inicio | C13: Permite al sistema ver si hay o no un bloqueo en una fecha y hora, en el que empieza el bloqueo, para que el determine luego si el cliente puede agendar una cita en ese momento | D13: =$B$2 -> Bloqueo | J13: Bloqueo visto
A14: Barbero | B14: Ver bloqueo en una fecha y hora de inicio | C14: Permite al barbero ver si hay o no un bloqueo en una fecha y hora, en el que empieza el bloqueo, para que mire si el puso o no un bloqueo | D14: =$B$2 -> Bloqueo | J14: Bloqueo visto
A15: Barbero | B15: Editar un bloqueo | C15: Permite al barbero poder editar la fecha y hora en que inicia o termina | D15: =$B$2 -> Bloqueo | E15: HorarioBarbero | F15: Permite llegar de las agendas al barbero dueño de cada cita, ya que la cita no referencia al barbero directamente. | G15: ='P-Bloqueo'!A7 -> P-BLO-0002 | H15: ='P-Bloqueo'!B7 -> Rechazar el bloqueo si ya existen citas agendadas dentro de ese mismo rango elegido | J15: Bloqueo editado
E16: Agenda | F16: Permite conocer la fecha de cada cita, ya que la cita solo almacena horas. Es lo que hace comparable el rango del bloqueo contra las citas existentes.
E17: Cita | F17: Permite verificar que el nuevo rango no choque con citas ya agendadas. | G17: ='P-Bloqueo'!A8 -> P-BLO-0003 | H17: ='P-Bloqueo'!B8 -> Asegurar que los datos requeridos para editar el bloqueo (fecha y hora de inicio, fecha y hora de fin) sean válidos en tipo de dato, obligatoriedad, formato y rango, y que la fecha y hora de fin sea mayor a la de inicio
E18: Estado | F18: Permite descartar las citas canceladas, que no deben impedir el bloqueo.

Sheet M-Bloqueo
A1: <<<< Ir al modulo de dominio | B1: <<<< Ir a objetos de dominio
A2: Representa un identificador que hará unico cada objeto de dominio de este tipo, no se puede repetir | B2: Referencia a qué barbero le pertence este bloqueo | C2: Representa la fecha y hora en el que el barbero empieza a no estar disponible para atender las citas | D2: Representa la fecha y hora en el que el barbero empieza estar disponible nuevamente para atender las citas | E2: Combinación única que indica que un mismo barbero no puede tener dos bloqueos con la misma fecha y hora de inicio y la misma fecha y hora final
A3: id | B3: barbero | C3: fechaHoraInicio | D3: fechaHoraFinal | E3: Combinación única
A4: 1 | B4: ='M-Barbero'!K4 -> +57-3245627890 | C4: 46188.5 | D4: 46188.542 | E4: =_xlfn.CONCAT(B4,"-",TEXT(C4,"dd/mm/yyyy hh:mm"),"-",TEXT(D4,"dd/mm/yyyy hh:mm")) -> +57-3245627890-15/06/2026 12:00-15/06/2026 13:00
A5: 2 | B5: ='M-Barbero'!K5 -> +57-3124518923 | C5: 46189.417 | D5: 46189.438 | E5: =_xlfn.CONCAT(B5,"-",TEXT(C5,"dd/mm/yyyy hh:mm"),"-",TEXT(D5,"dd/mm/yyyy hh:mm")) -> +57-3124518923-16/06/2026 10:00-16/06/2026 10:30
A6: 3 | B6: ='M-Barbero'!K6 -> +57-3214533321 | C6: 46191.583 | D6: 46191.625 | E6: =_xlfn.CONCAT(B6,"-",TEXT(C6,"dd/mm/yyyy hh:mm"),"-",TEXT(D6,"dd/mm/yyyy hh:mm")) -> +57-3214533321-18/06/2026 14:00-18/06/2026 15:00
A7: 4 | B7: ='M-Barbero'!K7 -> +91-9876543210 | C7: 46193.375 | D7: 46193.396 | E7: =_xlfn.CONCAT(B7,"-",TEXT(C7,"dd/mm/yyyy hh:mm"),"-",TEXT(D7,"dd/mm/yyyy hh:mm")) -> +91-9876543210-20/06/2026 09:00-20/06/2026 09:30
A8: 5 | B8: ='M-Barbero'!K7 -> +91-9876543210 | C8: 46195.667 | D8: 46195.698 | E8: =_xlfn.CONCAT(B8,"-",TEXT(C8,"dd/mm/yyyy hh:mm"),"-",TEXT(D8,"dd/mm/yyyy hh:mm")) -> +91-9876543210-22/06/2026 16:00-22/06/2026 16:45
B14: Corresponde a la descripcion de los atributos
B15: Corresponde al identificador unico del objeto de dominio
B16: Corresponde a las referencias de otros objetos de dominio
B17: Corresponde a los datos que ingresa el usuario
B18: Corresponde a la combinacion única

Sheet C-HorarioBarbero
A1: <<<< Ir al modulo de dominio | B1: <<<< Ir a objetos de dominio
A2: Nombre atributo | B2: Descripción atributo | C2: Identificador del objeto de dominio | D2: Tipo de dato | E2: Obligatorio | F2: Longitud mínima (si aplica) | G2: Longitud máxima (si aplica) | H2: Precisión (si aplica) | I2: Rendondeo (si aplica) | J2: Rango inicial (si aplica) | K2: Rango final (si aplica) | L2: Formato (si aplica) | M2: Reglas especiales (si aplica) | N2: Dato calculado | O2: Aplica ajuste del dato (si aplica) | P2: Carácter de ajuste (si aplica) | Q2: Quitar espacios en blanco al inicio (si aplica) | R2: Quitar espacios en blanco al fin (si aplica) | S2: Dato sensible (si aplica) | T2: Valor por defecto (si aplica) | U2: Auto generado | V2: =A22 -> definirHorarioDeTrabajo | W2: =A25 -> consultarHorariosDefinidos | X2: =A26 -> desactivarHorarioDeTrabajo | Y2: =A29 -> consultarHorariosDeTrabajoDeBarbero
A3: ='M-HorarioBarbero'!A3 -> id | B3: ='M-HorarioBarbero'!A2 -> Representa un identificador que hará unico cada objeto de dominio de este tipo, no se puede repetir | C3: Si | D3: Identificador único universal | E3: Si | F3: No aplica | G3: No aplica | H3: No aplica | I3: No aplica | J3: No aplica | K3: No aplica | L3: No aplica | M3: No aplica | N3: No | O3: No | P3: No aplica | Q3: No | R3: No | S3: No | T3: UUID vacio | U3: Si | V3: No requerido | W3: No mostrar | X3: Requerido | Y3: No mostrar
A4: ='M-HorarioBarbero'!B3 -> barbero | B4: ='M-HorarioBarbero'!B2 -> Referencia a que barbero va a ser dueño de este horario | C4: No | D4: Barbero | E4: Si | F4: No aplica | G4: No aplica | H4: No aplica | I4: No aplica | J4: No aplica | K4: No aplica | L4: No aplica | M4: Aplican las reglas del objeto referenciado | N4: No | O4: No aplica | P4: No aplica | Q4: No aplica | R4: No aplica | S4: No | T4: UUID vacio | U4: No | V4: Requerido | W4: No mostrar | X4: No requerido | Y4: Mostrar
A5: ='M-HorarioBarbero'!C3 -> horarioDeLaBarberia | B5: ='M-HorarioBarbero'!C2 -> Hace referencia a la agenda del barbero en la que queda guardado este horario de trabajo | C5: No | D5: HorarioBarberia | E5: Si | F5: No aplica | G5: No aplica | H5: No aplica | I5: No aplica | J5: No aplica | K5: No aplica | L5: No aplica | M5: Aplican las reglas del objeto referenciado | N5: No | O5: No aplica | P5: No aplica | Q5: No aplica | R5: No aplica | S5: No | T5: UUID vacio | U5: No | V5: Requerido | W5: Mostrar | X5: No requerido | Y5: Mostrar
A6: ='M-HorarioBarbero'!D3 -> horaInicio | B6: ='M-HorarioBarbero'!D2 -> Representa la hora en la que el barbero empieza a estar disponible ese dia | C6: No | D6: Hora | E6: Si | F6: No aplica | G6: No aplica | H6: No aplica | I6: No aplica | J6: No aplica | K6: No aplica | L6: No aplica | M6: Debe estar dentro del rango de horarioDeLaBarberia | N6: No | O6: No aplica | P6: No aplica | Q6: No aplica | R6: No aplica | S6: No | T6: 00:00 | U6: No | V6: Requerido | W6: Mostrar | X6: No requerido | Y6: Mostrar
A7: ='M-HorarioBarbero'!E3 -> horaFinal | B7: ='M-HorarioBarbero'!E2 -> Representa la hora en la que el barbero deja de estar disponible ese día. | C7: No | D7: Hora | E7: Si | F7: No aplica | G7: No aplica | H7: No aplica | I7: No aplica | J7: No aplica | K7: No aplica | L7: No aplica | M7: Debe ser mayor a horaInicio y estar dentro del rango de horarioDeLaBarberia | N7: No | O7: No aplica | P7: No aplica | Q7: No aplica | R7: No aplica | S7: No | T7: 00:00 | U7: No | V7: Requerido | W7: Mostrar | X7: No requerido | Y7: Mostrar
A8: ='M-HorarioBarbero'!F3 -> fechaCreacion | B8: ='M-HorarioBarbero'!F2 -> Representa la fecha en el que el barbero creo su horario. Es un dato calculado que toma la fecha de hoy cuando el barbero la crea | C8: No | D8: Fecha | E8: Si | F8: No aplica | G8: No aplica | H8: No aplica | I8: No aplica | J8: No aplica | K8: No aplica | L8: No aplica | M8: Toma la fecha del sistema en el momento en que el barbero crea este horario | N8: Si | O8: No aplica | P8: No aplica | Q8: No aplica | R8: No aplica | S8: No | T8: 01/01/1000 | U8: Si | V8: No requerido | W8: Mostrar | X8: No requerido | Y8: No mostrar
A9: ='M-HorarioBarbero'!G3 -> fechaDesactivacion | B9: ='M-HorarioBarbero'!G2 -> Representa la fecha en la que este horario dejó de estar vigente, ya sea porque el barbero lo retiró o porque se desactivó el horario de la barbería del que depende. Es un dato calculado que toma la fecha del sistema en ese momento. | C9: No | D9: Fecha | E9: No | F9: No aplica | G9: No aplica | H9: No aplica | I9: No aplica | J9: No aplica | K9: No aplica | L9: No aplica | M9: Toma la fecha del sistema en el momento en que el barbero desactiva este horario. Su valor por defecto es 01/01/1000 mientras siga vigente | N9: Si | O9: No aplica | P9: No aplica | Q9: No aplica | R9: No aplica | S9: No | T9: 01/01/1000 | U9: Si | V9: No requerido | W9: Mostrar | X9: No requerido | Y9: No mostrar
A10: ='M-HorarioBarbero'!H3 -> vigente | B10: ='M-HorarioBarbero'!H2 -> Representa si este horario lo sigue o no usando el barbero. Una vez que el barbero cambie este estado a no vigente, no se puede volver a cambiar | C10: No | D10: Lógico | E10: Si | F10: No aplica | G10: No aplica | H10: No aplica | I10: No aplica | J10: No aplica | K10: No aplica | L10: No aplica | M10: Una vez se cambia a No, no puede volver a cambiar a Si | N10: No | O10: No aplica | P10: No aplica | Q10: No aplica | R10: No aplica | S10: No | T10: Si | U10: Si | V10: No requerido | W10: Mostrar | X10: No requerido | Y10: No mostrar
A12: Nombre combinación única | B12: Descripción | C12: Atributos involucrados
A13: ='M-HorarioBarbero'!I3 -> Combinación única | B13: ='M-HorarioBarbero'!I2 -> Combinación única que indica que un mismo barbero no puede tener dos horarios con el mismo día de la barbería, la misma hora de inicio, la misma hora final, misma fecha de creacion y de desactivacion | C13: =A4 -> barbero
C14: =A5 -> horarioDeLaBarberia
C15: =A6 -> horaInicio
C16: =A7 -> horaFinal
C17: =A8 -> fechaCreacion
C18: =A9 -> fechaDesactivacion
A20: Responsabilidad | C20: Descripción | G20: Entradas | J20: Salida | O20: Políticas (Reglas de Negocio) | Q20: Excepción
G21: Parámetro | H21: Tipo de dato | I21: Descripción | J21: Tipo de Dato | K21: Descripción | O21: Política | P21: Descripción | Q21: Detalle | R21: ¿Qué hago?
A22: definirHorarioDeTrabajo | C22: Comando que permite a un barbero registrar el día de la semana y las horas en que trabaja | G22: datos{barbero, horarioDeLaBarberia, horaInicio, horaFinal} | H22: HorarioBarbero | I22: Contiene la información requerida para registrar el horario de trabajo del barbero | J22: HorarioBarbero | K22: Contiene la información del horario de trabajo registrado | O22: ='P-HorarioBarbero'!A6 -> P-HBO-0001 | P22: ='P-HorarioBarbero'!B6 -> Asegurar que los datos requeridos (día de la semana, hora de inicio, hora de fin) sean válidos en tipo de dato, obligatoriedad, formato y rango | Q22: Generar una excepción indicándole al barbero que los datos no cumplen las reglas definidas | R22: Detener operación
O23: ='P-HorarioBarbero'!A7 -> P-HBO-0002 | P23: ='P-HorarioBarbero'!B7 -> Asegurar que el horario de trabajo esté dentro del horario de apertura y cierre de la barbería para ese día | Q23: Generar una excepción indicándole al usuario que el horario de trabajo queda por fuera del horario de apertura y cierre de la barbería para ese día | R23: Detener operación
O24: ='P-HorarioBarbero'!A10 -> P-HBO-0006 | P24: ='P-HorarioBarbero'!B10 -> Asegurar que la hora de fin sea mayor a la hora de inicio | Q24: Generar una excepción indicándole al barbero que la hora de fin debe ser mayor a la hora de inicio | R24: Detener operación
A25: consultarHorariosDefinidos | C25: Permite a un barbero consultar los horarios de trabajo que ha definido | G25: filtro{barbero} | H25: HorarioBarbero | I25: Contiene el barbero por el cual se van a consultar sus horarios de trabajo | J25: Lista<HorarioBarbero> | K25: Contiene todos los horarios de trabajo que el barbero tiene definidos
A26: desactivarHorarioDeTrabajo | C26: Permite a un barbero desactivar un horario para dejar de trabajar ese día de la semana, cancelando las citas futuras que dependían de él | G26: id | H26: UUID | I26: Corresponde al identificador del horario de trabajo que se va a desactivar | K26: No retorna ningún valor. En caso de error genera una excepción. | O26: ='P-HorarioBarbero'!A8 -> P-HBO-0004 | P26: ='P-HorarioBarbero'!B8 -> Asegurar que queden canceladas, en el estado Cancelación, todas las citas futuras asociadas a las agendas generadas a partir de ese horario de trabajo. Se consideran futuras las citas cuya agenda tenga una fecha posterior a la fecha actual | Q26: Si alguna de las citas futuras no pudo ser cancelada, revertir toda la operación e informar el error | R26: Detener operación
O27: ='P-HorarioBarbero'!A9 -> P-HBO-0005 | P27: ='P-HorarioBarbero'!B9 -> Asegurar que exista el horario de trabajo del barbero con el id enviado | Q27: Informar con un mensaje que no existe un horario de trabajo con el identificador enviado y por lo tanto no es posible llevar a cabo la operación | R27: Detener operación
