Workbook

Sheet Modelo de Dominio
A1: Ir a objetos de dominio >>>>

Sheet Objetos de Dominio
A1: <<<< Ir al modulo de dominio
A2: Nombre | B2: Descripcion | C2: Linea de vida | D2: Muestreo | E2: Caracterización | F2: Event Storming | G2: Politicas
A3: DiaSemana | B3: Representa cada uno de los días de la semana, incluyendo festivo, que se usa como catálogo para definir los horarios de la barbería y de cada barbero. | C3: 1 | D3: Ir al muestreo | E3: Ir a la caracterización | F3: Ir al Event Storming | G3: Ir a las políticas
A4: Estado | B4: Representa en qué situación puntual se encuentra una cita: agendada, finalizada, cancelada por alguna de las partes, con tardanza del cliente o del barbero, o con inasistencia del cliente. | C4: 1 | D4: Ir al muestreo | E4: Ir a la caracterización | F4: Ir al Event Storming | G4: Ir a las políticas
A5: Servicio | B5: Representa cada tipo de corte o arreglo que ofrece la barbería, definido por el dueño, para que luego cada barbero decida cuáles sabe hacer. | C5: 1 | D5: Ir al muestreo | E5: Ir a la caracterización | F5: Ir al Event Storming | G5: Ir a las políticas
A6: PrefijoCelular | B6: Representa el catálogo de prefijos telefónicos de país que el dueño habilita, y que son los únicos que barberos y clientes pueden usar en su número de celular. | C6: 1 | D6: Ir al muestreo | E6: Ir a la caracterización | F6: Ir al Event Storming | G6: Ir a las políticas
A7: TipoMulta | B7: Representa los tipos de multa que puede recibir un cliente: por tardanza o por inasistencia. | C7: 1 | D7: Ir al muestreo | E7: Ir a la caracterización | F7: Ir al Event Storming | G7: Ir a las políticas
A8: Barbero | B8: Representa a un trabajador de la barbería que atiende clientes según los servicios que sabe realizar, organiza su propio horario y tiene su agenda personal para atender todas las citas que valla teniendo. | C8: 2 | D8: Ir al muestreo | E8: Ir a la caracterización | F8: Ir al Event Storming | G8: Ir a las políticas
A9: Cliente | B9: Representa a la persona que solicita citas en la barbería. | C9: 2 | D9: Ir al muestreo | E9: Ir a la caracterización | F9: Ir al Event Storming | G9: Ir a las políticas
A10: HorarioBarberia | B10: Representa, día por día, a qué hora abre y cierra el negocio; es el límite dentro del cual debe caber el horario de cualquier barbero. | C10: 2 | D10: Ir al muestreo | E10: Ir a la caracterización | F10: Ir al Event Storming | G10: Ir a las políticas
A11: Bloqueo | B11: Representa los momentos en que el barbero no esta disponible para atender sus citas, el barbero establece la hora y la fecha en que empieza y termina ese estado de no disponible. | C11: 3 | D11: Ir al muestreo | E11: Ir a la caracterización | F11: Ir al Event Storming | G11: Ir a las políticas
A12: BarberoServicio | B12: Representa qué servicios sabe hacer cada barbero, cuánto se demora en realizarlos y cuánto tiempo extra usa de colchón, ya que no todos los barberos ofrecen los mismos servicios que están en la barbería. | C12: 3 | D12: Ir al muestreo | E12: Ir a la caracterización | F12: Ir al Event Storming | G12: Ir a las políticas
A13: HorarioBarbero | B13: Representa el día de la semana en que trabaja un barbero, junto con la hora en la que empieza y termina su jornada de trabajo. | C13: 3 | D13: Ir al muestreo | E13: Ir a la caracterización | F13: Ir al Event Storming | G13: Ir a las políticas
A14: Agenda | B14: Representa una fecha puntual en donde el barbero ve todas las citas que debe de atender ese día. | C14: 4 | D14: Ir al muestreo | E14: Ir a la caracterización | F14: Ir al Event Storming | G14: Ir a las políticas
... A17: Multa | B17: Representa la sanción económica que se le impone a un cliente por incumplir una cita, ya sea por llegar tarde fuera de tolerancia o por no presentarse, calculada a partir de la cita específica que la originó. | C17: 6 | D17: Ir al muestreo | E17: Ir a la caracterización | F17: Ir al Event Storming | G17: Ir a las políticas

Sheet C-DiaSemana
A1: <<<< Ir al modulo de dominio | B1: <<<< Ir a objetos de dominio
A2: Nombre atributo | B2: Descripción atributo | C2: Identificador del objeto de dominio | D2: Tipo de dato | E2: Obligatorio | F2: Longitud mínima (si aplica) | G2: Longitud máxima (si aplica) | H2: Precisión (si aplica) | I2: Rendondeo (si aplica) | J2: Rango inicial (si aplica) | K2: Rango final (si aplica) | L2: Formato (si aplica) | M2: Reglas especiales (si aplica) | N2: Dato calculado | O2: Aplica ajuste del dato (si aplica) | P2: Carácter de ajuste (si aplica) | Q2: Quitar espacios en blanco al inicio (si aplica) | R2: Quitar espacios en blanco al fin (si aplica) | S2: Dato sensible (si aplica) | T2: Valor por defecto (si aplica) | U2: Auto generado | V2: =A11 -> VerDiasDeLaSemana
A3: ='M-DiaSemana'!A3 -> id | B3: ='M-DiaSemana'!A2 -> Representa un identificador que hará unico cada objeto de dominio de este tipo, no se puede repetir | C3: Si | D3: Identificador único universal | E3: Si | F3: No aplica | G3: No aplica | H3: No aplica | I3: No aplica | J3: No aplica | K3: No aplica | L3: No aplica | M3: No aplica | N3: No | O3: No aplica | P3: No aplica | Q3: No aplica | R3: No aplica | S3: No | T3: UUID vacio | U3: Si | V3: No mostrar
A4: ='M-DiaSemana'!B3 -> nombre | B4: ='M-DiaSemana'!B2 -> Representa como se llama el dia de la semana, para los horarios | C4: No | D4: Alfanumérico | E4: Si | F4: 5 | G4: 9 | H4: No aplica | I4: No aplica | J4: No aplica | K4: No aplica | L4: No aplica | M4: Solo pueden ser los dias de la semana como Lunes, Martes, Miércoles, Jueves, Viernes, Sábado, Domingo y Festivo | N4: No | O4: No aplica | P4: No aplica | Q4: Si | R4: Si | S4: No | T4: Vacio | U4: No | V4: Mostrar
A6: Nombre combinación única | B6: Descripción | C6: Atributos involucrados
A7: ='M-DiaSemana'!C3 -> Combinación única | B7: ='M-DiaSemana'!C2 -> Combinacion única que indica que no puede existir más un dia de la semana con el mismo nombre | C7: nombre
A9: Responsabilidad | C9: Descripción | G9: Entradas | J9: Salida | O9: Políticas (Reglas de Negocio) | Q9: Excepción
G10: Parámetro | H10: Tipo de dato | I10: Descripción | J10: Tipo de Dato | K10: Descripción | O10: Política | P10: Descripción | Q10: Detalle | R10: ¿Qué hago?
A11: VerDiasDeLaSemana | C11: Permite consultar el catálogo de días de la semana, incluyendo festivo, para definir los horarios | J11: Lista<DiaSemana> | K11: Contiene todos los días de la semana

Sheet P-DiaSemana
A1: << Ir al modelo de dominio | B1: << Ir al listado de objetos de dominio | C1: << Ir a la caracterización del objeto de dominio | D1: Ir al muestreo de datos del objeto de dominio >> | E1: Ir al event storming del objeto de dominio >>
A2: Objeto de Dominio: | B2: ='Objetos de Dominio'!A3 -> DiaSemana
A3: Descripción: | B3: ='Objetos de Dominio'!B3 -> Representa cada uno de los días de la semana, incluyendo festivo, que se usa como catálogo para definir los horarios de la barbería y de cada barbero.
A4: Numero politica | B4: Descripcion politica | D4: Objeto responsable | E4: Regla responsable
B6: No aplica: es un catálogo de solo lectura, sin comandos que impliquen políticas de negocio propias

Sheet E-DiaSemana
A1: << Ir al modelo de dominio | C1: << Ir al listado de objetos de dominio | F1: << Ir a la caracterización del objeto de dominio | J1: Ir al muestreo de datos del objeto de dominio >>
A2: Objeto de Dominio: | B2: ='Objetos de Dominio'!A3 -> DiaSemana
A3: Descripción: | B3: ='Objetos de Dominio'!B3 -> Representa cada uno de los días de la semana, incluyendo festivo, que se usa como catálogo para definir los horarios de la barbería y de cada barbero.
A4: Actor | B4: Action/Command | D4: Entity/Aggregate/Object domain | E4: Read Model | G4: Business Rule/Policy | I4: External System | J4: Domain Event | K4: Hotspot/questions/Risk
A5: Actor | B5: Acción | C5: Descripción | D5: Objeto de dominio | E5: Información externa | G5: Políticas | I5: Sistema Externo | J5: Evento | K5: Aspectos por solucionar
E6: Información | F6: Descripción | G6: Número | H6: Descripción
A7: Dueño | B7: Ver los días de las semanas | C7: Permite consultar el catálogo de días de la semana, incluyendo festivo, disponibles para definir horarios | D7: =$B$2 -> DiaSemana | J7: Días de la semana consultados
A8: Barbero | B8: Ver los días de las semanas | C8: Permite consultar el catálogo de días de la semana, incluyendo festivo, disponibles para definir horarios | D8: =$B$2 -> DiaSemana | J8: Días de la semana consultados

Sheet M-DiaSemana
A1: <<<< Ir al modulo de dominio | B1: <<<< Ir a objetos de dominio
A2: Representa un identificador que hará unico cada objeto de dominio de este tipo, no se puede repetir | B2: Representa como se llama el dia de la semana, para los horarios | C2: Combinacion única que indica que no puede existir más un dia de la semana con el mismo nombre
A3: id | B3: nombre | C3: Combinación única
A4: 1 | B4: Lunes | C4: =B4 -> Lunes
A5: 2 | B5: Martes | C5: =B5 -> Martes
A6: 3 | B6: Miércoles | C6: =B6 -> Miércoles
A7: 4 | B7: Jueves | C7: =B7 -> Jueves
A8: 5 | B8: Viernes | C8: =B8 -> Viernes
A9: 6 | B9: Sábado | C9: =B9 -> Sábado
A10: 7 | B10: Domingo | C10: =B10 -> Domingo
A11: 8 | B11: Festivo | C11: =B11 -> Festivo
B17: Corresponde a la descripcion de los atributos
B18: Corresponde al identificador unico del objeto de dominio
B19: Corresponde a los datos que ingresa el usuario
B20: Corresponde a la combinacion única

Sheet C-Estado
A1: <<<< Ir al modulo de dominio | B1: <<<< Ir a objetos de dominio
A2: Nombre atributo | B2: Descripción atributo | C2: Identificador del objeto de dominio | D2: Tipo de dato | E2: Obligatorio | F2: Longitud mínima (si aplica) | G2: Longitud máxima (si aplica) | H2: Precisión (si aplica) | I2: Rendondeo (si aplica) | J2: Rango inicial (si aplica) | K2: Rango final (si aplica) | L2: Formato (si aplica) | M2: Reglas especiales (si aplica) | N2: Dato calculado | O2: Aplica ajuste del dato (si aplica) | P2: Carácter de ajuste (si aplica) | Q2: Quitar espacios en blanco al inicio (si aplica) | R2: Quitar espacios en blanco al fin (si aplica) | S2: Dato sensible (si aplica) | T2: Valor por defecto (si aplica) | U2: Auto generado | V2: =A12 -> consultarTodosLosEstados | W2: =A13 -> editarDescripcion | X2: 'C-Estado'!A13 | Y2: =A15 -> consultarDescripcion
A3: ='M-Estado'!A3 -> id | B3: ='M-Estado'!A2 -> Representa un identificador que hará unico cada objeto de dominio de este tipo, no se puede repetir | C3: Si | D3: Identificador único universal | E3: Si | F3: No aplica | G3: No aplica | H3: No aplica | I3: No aplica | J3: No aplica | K3: No aplica | L3: No aplica | M3: No aplica | N3: No | O3: No aplica | P3: No aplica | Q3: No aplica | R3: No aplica | S3: No aplica | T3: UUID vacio | U3: Si | V3: No mostrar | W3: Requerido | X3: No modificable | Y3: No mostrar
A4: ='M-Estado'!B3 -> nombre | B4: ='M-Estado'!B2 -> Representa como se llama el estado en el que se encuentra una cita puntual | C4: No | D4: Alfanumérico | E4: Si | F4: 4 | G4: 50 | H4: No aplica | I4: No aplica | J4: No aplica | K4: No aplica | L4: No aplica | M4: Solo se aceptan caracteres de letras de la 'a' a la 'z' y espacios en blanco | N4: No | O4: No aplica | P4: No aplica | Q4: Si | R4: Si | S4: No | T4: Vacio | U4: No | V4: Mostrar | W4: No requerido | X4: No modificable | Y4: No mostrar
A5: ='M-Estado'!C3 -> descripcion | B5: ='M-Estado'!C2 -> Representa el significado de que representa cada estado para la cita | C5: No | D5: Alfanumérico | E5: Si | F5: 10 | G5: 300 | H5: No aplica | I5: No aplica | J5: No aplica | K5: No aplica | L5: No aplica | M5: Solo se aceptan caracteres de letras de la 'a' a la 'z', caracteres con tilde y espacios en blanco | N5: No | O5: No aplica | P5: No aplica | Q5: Si | R5: Si | S5: No | T5: Vacio | U5: No | V5: No mostrar | W5: Requerido | X5: Modificable | Y5: Mostrar
A7: Nombre combinación única | B7: Descripción | C7: Atributos involucrados
A8: ='M-Estado'!D3 -> Combinación única | B8: ='M-Estado'!D2 -> Combinacion única que indica que no puede existir más un dia de la semana con el mismo nombre | C8: nombre
A10: Responsabilidad | C10: Descripción | G10: Entradas | J10: Salida | O10: Políticas (Reglas de Negocio) | Q10: Excepción
G11: Parámetro | H11: Tipo de dato | I11: Descripción | J11: Tipo de Dato | K11: Descripción | O11: Política | P11: Descripción | Q11: Detalle | R11: ¿Qué hago?
A12: consultarTodosLosEstados | C12: Permite consultar los estados posibles que puede tener una cita | J12: Lista<Estado> | K12: Contiene todos los estados que cumplen con el filtro enviado
A13: editarDescripcion | C13: Permite ajustar el texto descriptivo de un estado ya creado, sin cambiar su significado en el flujo de la cita | G13: id | H13: UUID | I13: Corresponde al identificador del estado que se va a editar | K13: La descripcion del estado se editó | O13: ='P-Estado'!A7 -> P-EST-0002 | P13: ='P-Estado'!B7 -> Asegurar que exista el estado con el id enviado | Q13: Informar con un mensaje que no existe un estado con el identificador enviado y por lo tanto no es posible modificar la descripción | R13: Detener ejecución de la operación
G14: datos{descripcion} | H14: Estado | I14: Contiene la nueva descripción del estado | O14: ='P-Estado'!A6 -> P-EST-0001 | P14: ='P-Estado'!B6 -> Asegurar que los datos requeridos (descripción) sean válidos en tipo de dato, longitud, formato y rango | Q14: Generar una excepción indicándole al usuario cuáles datos de la descripción del estado no cumplen con las reglas definidas | R14: Detener operación
A15: consultarDescripcion | C15: Permite consultar la descripcion de un estado en especifico | G15: datos{nombre} | H15: Estado | I15: Contiene el nombre del estado | J15: Alfanumérico | K15: Contiene la información del estado consultado por su identificador | O15: ='P-Estado'!A7 -> P-EST-0002 | P15: ='P-Estado'!B7 -> Asegurar que exista el estado con el id enviado | Q15: Informar con un mensaje que no existe un Estado con el identificador enviado y por lo tanto no es posible modificar la descripción | R15: Detener ejecución de la operación

Sheet P-Estado
A1: << Ir al modelo de dominio | B1: << Ir al listado de objetos de dominio | C1: << Ir a la caracterización del objeto de dominio | D1: Ir al muestreo de datos del objeto de dominio >> | E1: Ir al event storming del objeto de dominio >>
A2: Objeto de Dominio: | B2: ='Objetos de Dominio'!A4 -> Estado
A3: Descripción: | B3: ='Objetos de Dominio'!B4 -> Representa en qué situación puntual se encuentra una cita: agendada, finalizada, cancelada por alguna de las partes, con tardanza del cliente o del barbero, o con inasistencia del cliente.
A4: Numero politica | B4: Descripcion politica | D4: Objeto responsable | E4: Regla responsable
A6: P-EST-0001 | B6: Asegurar que los datos requeridos (descripción) sean válidos en tipo de dato, longitud, formato y rango | D6: Estado
A7: P-EST-0002 | B7: Asegurar que exista el estado con el id enviado | D7: Estado

Sheet E-Estado
A1: << Ir al modelo de dominio | C1: << Ir al listado de objetos de dominio | F1: << Ir a la caracterización del objeto de dominio | J1: Ir al muestreo de datos del objeto de dominio >>
A2: Objeto de Dominio: | B2: ='Objetos de Dominio'!A4 -> Estado
A3: Descripción: | B3: ='Objetos de Dominio'!B4 -> Representa en qué situación puntual se encuentra una cita: agendada, finalizada, cancelada por alguna de las partes, con tardanza del cliente o del barbero, o con inasistencia del cliente.
A4: Actor | B4: Action/Command | D4: Entity/Aggregate/Object domain | E4: Read Model | G4: Business Rule/Policy | I4: External System | J4: Domain Event | K4: Hotspot/questions/Risk
A5: Actor | B5: Acción | C5: Descripción | D5: Objeto de dominio | E5: Información externa | G5: Políticas | I5: Sistema Externo | J5: Evento | K5: Aspectos por solucionar
E6: Información | F6: Descripción | G6: Número | H6: Descripción
A7: Dueño | B7: Ver estados de las citas | C7: Permite consultar los estados posibles que puede tener una cita | D7: =$B$2 -> Estado | J7: Estados consultados
A8: Barbero | B8: Ver estados de las citas | C8: Permite consultar los estados posibles que puede tener una cita | D8: =$B$2 -> Estado | J8: Estados consultados
A9: Cliente | B9: Ver estados de las citas | C9: Permite consultar los estados posibles que puede tener una cita | D9: =$B$2 -> Estado | J9: Estados consultados
A10: Dueño | B10: Editar descripción del estado | C10: Permite ajustar el texto descriptivo de un estado ya creado, sin cambiar su significado en el flujo de la cita | D10: =$B$2 -> Estado | G10: ='P-Estado'!A6 -> P-EST-0001 | H10: ='P-Estado'!B6 -> Asegurar que los datos requeridos (descripción) sean válidos en tipo de dato, longitud, formato y rango | J10: Descripción de estado actualizada
A11: Dueño | B11: Ver descripcion de un estado | C11: Permite consultar la descripcion de un estado en especifico | D11: =$B$2 -> Estado | J11: Descripción del estado consultada
A12: Barbero | B12: Ver descripcion de un estado | C12: Permite consultar la descripcion de un estado en especifico | D12: =$B$2 -> Estado | J12: Descripción del estado consultada
A13: Cliente | B13: Ver descripcion de un estado | C13: Permite consultar la descripcion de un estado en especifico | D13: =$B$2 -> Estado | J13: Descripción del estado consultada

Sheet M-Estado
A1: <<<< Ir al modulo de dominio | B1: <<<< Ir a objetos de dominio
A2: Representa un identificador que hará unico cada objeto de dominio de este tipo, no se puede repetir | B2: Representa como se llama el estado en el que se encuentra una cita puntual | C2: Representa el significado de que representa cada estado para la cita | D2: Combinacion única que indica que no puede existir más un dia de la semana con el mismo nombre
A3: id | B3: nombre | C3: descripcion | D3: Combinación única
A4: 1 | B4: Agendada | C4: La cita quedó registrada en la agenda del barbero y está a la espera de la fecha y hora acordadas. | D4: =B4 -> Agendada
A5: 2 | B5: Finalizada | C5: El barbero atendió al cliente y el servicio contratado se prestó por completo, sin tener ninguna sanción. | D5: =B5 -> Finalizada
A6: 3 | B6: Cancelada por el cliente | C6: El cliente decidió no asistir y anuló la cita antes de la fecha y hora programada. | D6: =B6 -> Cancelada por el cliente
A7: 4 | B7: Cancelada por el barbero | C7: El barbero anuló la cita antes de la fecha y hora programada, por ejemplo por una eventualidad. | D7: =B7 -> Cancelada por el barbero
A8: 5 | B8: El cliente se demoro | C8: El cliente llegó después de la hora acordada superando el tiempoEspera definido en la cita, lo que genera una multa de tipo Tardanza. | D8: =B8 -> El cliente se demoro
A9: 6 | B9: El barbero se demoro | C9: El barbero se demoró más de lo previsto en una cita anterior y empezó a atender al cliente superando el tiempoEspera definido en la cita, lo que le da un descuento al cliente. | D9: =B9 -> El barbero se demoro
A10: 7 | B10: Inasistencia del cliente | C10: El cliente nunca llegó a la cita: se alcanzó la hora estimada de finalización sin registrar su llegada, lo que genera una multa por el valor total de los servicios pedidos. | D10: =B10 -> Inasistencia del cliente
A11: 8 | B11: Cancelación | C11: La cita se anuló automáticamente porque la barbería cambió sus políticas de horario: al desactivarse el horario de la barbería se desactivaron los horarios de barbero y las agendas que dependían de él, y las citas que quedaron por fuera se cancelaron. | D11: =B11 -> Cancelación
B17: Corresponde a la descripcion de los atributos
B18: Corresponde al identificador unico del objeto de dominio
B19: Corresponde a los datos que ingresa el usuario
B20: Corresponde a la combinacion única

Sheet C-Servicio
A1: <<<< Ir al modulo de dominio | B1: <<<< Ir a objetos de dominio
A2: Nombre atributo | B2: Descripción atributo | C2: Identificador del objeto de dominio | D2: Tipo de dato | E2: Obligatorio | F2: Longitud mínima (si aplica) | G2: Longitud máxima (si aplica) | H2: Precisión (si aplica) | I2: Rendondeo (si aplica) | J2: Rango inicial (si aplica) | K2: Rango final (si aplica) | L2: Formato (si aplica) | M2: Reglas especiales (si aplica) | N2: Dato calculado | O2: Aplica ajuste del dato (si aplica) | P2: Carácter de ajuste (si aplica) | Q2: Quitar espacios en blanco al inicio (si aplica) | R2: Quitar espacios en blanco al fin (si aplica) | S2: Dato sensible (si aplica) | T2: Valor por defecto (si aplica) | U2: Auto generado | V2: =A14 -> ofrecerServicioNuevo | W2: =A16 -> editarServicio | Y2: =A19 -> consultarServiciosDisponibles | Z2: =A20 -> retirarServicio
A3: ='M-Servicio'!A3 -> id | B3: ='M-Servicio'!A2 -> Representa un identificador que hará unico cada objeto de dominio de este tipo, no se puede repetir | C3: Si | D3: Identificador único universal | E3: Si | F3: No aplica | G3: No aplica | H3: No aplica | I3: No aplica | J3: No aplica | K3: No aplica | L3: No aplica | M3: No aplica | N3: No | O3: No aplica | P3: No aplica | Q3: No aplica | R3: No aplica | S3: No | T3: UUID vacio | U3: Si | V3: No requerido | W3: Requerido | X3: No modificable | Y3: No mostrar | Z3: Requerido
A4: ='M-Servicio'!B3 -> nombre | B4: ='M-Servicio'!B2 -> Representa el nombre del servicio que va estar en la barberia, para que el barbero elija los servicios que el sabe hacer | C4: No | D4: Alfanumérico | E4: Si | F4: 3 | G4: 50 | H4: No aplica | I4: No aplica | J4: No aplica | K4: No aplica | L4: No aplica | M4: Solo se aceptan caracteres de letras de la 'a' a la 'z' y caracteres con tilde | N4: No | O4: No aplica | P4: No aplica | Q4: Si | R4: Si | S4: No | T4: Vacio | U4: No | V4: Requerido | W4: Requerido | X4: Modificable | Y4: Mostrar | Z4: No requerido
A5: ='M-Servicio'!C3 -> descripcion | B5: ='M-Servicio'!C2 -> Representa una descripcion de que va a hacer cada servicio en la barberia, para que el barbero sepa que hace el servicio | C5: No | D5: Alfanumérico | E5: No | F5: 0 | G5: 200 | H5: No aplica | I5: No aplica | J5: No aplica | K5: No aplica | L5: No aplica | M5: Solo se aceptan caracteres de letras de la 'a' a la 'z', caracteres con tilde y espacios en blanco | N5: No | O5: No aplica | P5: No aplica | Q5: Si | R5: Si | S5: No | T5: Vacio | U5: No | V5: Requerido | W5: Requerido | X5: Modificable | Y5: Mostrar | Z5: No requerido
A6: ='M-Servicio'!D3 -> precio | B6: ='M-Servicio'!D2 -> Representa cuanto va a valer el servicio en pesos colombianos | C6: No | D6: Entero | E6: Si | F6: No aplica | G6: No aplica | H6: No aplica | I6: No aplica | J6: 0 | K6: 2000000 | L6: No aplica | M6: No aplica | N6: No | O6: No aplica | P6: No aplica | Q6: No aplica | R6: No aplica | S6: No | T6: 0 | U6: No | V6: Requerido | W6: Requerido | X6: Modificable | Y6: Mostrar | Z6: No requerido
A7: ='M-Servicio'!E3 -> disponible | B7: ='M-Servicio'!E2 -> Representa si el servicio sigue o no disponible en la barberia | C7: No | D7: Lógico | E7: Si | F7: No aplica | G7: No aplica | H7: No aplica | I7: No aplica | J7: No aplica | K7: No aplica | L7: No aplica | M7: No aplica | N7: No | O7: No aplica | P7: No aplica | Q7: No aplica | R7: No aplica | S7: No | T7: Si | U7: Si | V7: No requerido | W7: No requerido | X7: No modificable | Y7: No mostrar | Z7: No requerido
A9: Nombre combinación única | B9: Descripción | C9: Atributos involucrados
A10: ='M-Servicio'!F3 -> Combinacion única | B10: ='M-Servicio'!F2 -> Combinacion única que indica que no puede existir más de un servicio con el mismo nombre | C10: =A4 -> nombre
A12: Responsabilidad | C12: Descripción | G12: Entradas | J12: Salida | O12: Políticas (Reglas de Negocio) | Q12: Excepción
G13: Parámetro | H13: Tipo de dato | I13: Descripción | J13: Tipo de Dato | K13: Descripción | O13: Política | P13: Descripción | Q13: Detalle | R13: ¿Qué hago?
A14: ofrecerServicioNuevo | C14: Comando que permite registrar un nuevo tipo de servicio que la barbería pondrá a disposición de los barberos | G14: datos{nombre, descripcion, precio} | H14: Servicio | I14: Contiene la información requerida para registrar un nuevo servicio de la barbería | J14: Servicio | K14: Contiene la información del servicio registrado | O14: ='P-Servicio'!A6 -> P-SER-0001 | P14: ='P-Servicio'!B6 -> Asegurar que los datos requeridos del servicio (nombre, descripción, precio) sean válidos en tipo de dato, longitud, obligatoriedad, formato y rango | Q14: Generar una excepción indicándole al usuario cuáles datos del servicio no cumplen con las reglas definidas | R14: Detener operación
O15: ='P-Servicio'!A7 -> P-SER-0002 | P15: ='P-Servicio'!B7 -> Asegurar que no exista otro servicio registrado con el mismo nombre en la barbería | Q15: Generar una excepción indicándole al usuario que ya existe un servicio registrado con ese mismo nombre en la barbería | R15: Detener operación
A16: editarServicio | C16: Permite modificar todos los atibutos de un servicio, que son el nombre, la descripción y el precio | G16: id | H16: UUID | I16: Corresponde al identificador del servicio que se va a editar | J16: Servicio | K16: Contiene la información del servicio con sus datos actualizados | O16: ='P-Servicio'!A9 -> P-SER-0004 | P16: ='P-Servicio'!B9 -> Asegurar que exista el servicio con el id enviado | Q16: Informar con un mensaje que no existe un servicio con el identificador enviado y por lo tanto no es posible modificar el servicio | R16: Detener ejecución de la operación
G17: datos{nombre, descripcion, precio} | H17: Servicio | I17: Contiene los datos con los que se va a modificar el servicio | O17: ='P-Servicio'!A6 -> P-SER-0001 | P17: ='P-Servicio'!B6 -> Asegurar que los datos requeridos del servicio (nombre, descripción, precio) sean válidos en tipo de dato, longitud, obligatoriedad, formato y rango | Q17: Generar una excepción indicándole al usuario cuáles datos del servicio no cumplen con las reglas definidas | R17: Detener operación
O18: ='P-Servicio'!A7 -> P-SER-0002 | P18: ='P-Servicio'!B7 -> Asegurar que no exista otro servicio registrado con el mismo nombre en la barbería | Q18: Generar una excepción indicándole al usuario que ya existe un servicio registrado con ese mismo nombre en la barbería | R18: Detener operación
A19: consultarServiciosDisponibles | C19: Permite consultar el catálogo de servicios que ofrece la barbería | J19: Lista<Servicio> | K19: Contiene todos los servicios disponibles en la barberia
A20: retirarServicio | C20: Permite dar de baja un servicio para que deje de ofrecerse a nuevos clientes | G20: id | H20: UUID | I20: Corresponde al identificador del servicio que se va a retirar | K20: No retorna ningún valor. En caso de error genera una excepción. | O20: ='P-Servicio'!A8 -> P-SER-0003 | P20: ='P-Servicio'!B8 -> Asegurar que el servicio a retirar no esté siendo ofrecido actualmente por ningún barbero vigente | Q20: Generar una excepción indicándole al usuario que el servicio no se puede retirar porque todavía lo ofrece al menos un barbero vigente | R20: Detener operación
O21: ='P-Servicio'!A9 -> P-SER-0004 | P21: ='P-Servicio'!B9 -> Asegurar que exista el servicio con el id enviado | Q21: Informar con un mensaje que no existe un servicio con el identificador enviado y por lo tanto no es posible desactivar el servicio | R21: Detener operación

Sheet P-Servicio
A1: << Ir al modelo de dominio | B1: << Ir al listado de objetos de dominio | C1: << Ir a la caracterización del objeto de dominio | D1: Ir al muestreo de datos del objeto de dominio >> | E1: Ir al event storming del objeto de dominio >>
A2: Objeto de Dominio: | B2: ='Objetos de Dominio'!A5 -> Servicio
A3: Descripción: | B3: ='Objetos de Dominio'!B5 -> Representa cada tipo de corte o arreglo que ofrece la barbería, definido por el dueño, para que luego cada barbero decida cuáles sabe hacer.
A4: Numero politica | B4: Descripcion politica | D4: Objeto responsable | E4: Regla responsable
A6: P-SER-0001 | B6: Asegurar que los datos requeridos del servicio (nombre, descripción, precio) sean válidos en tipo de dato, longitud, obligatoriedad, formato y rango | D6: Servicio
A7: P-SER-0002 | B7: Asegurar que no exista otro servicio registrado con el mismo nombre en la barbería | D7: Servicio
A8: P-SER-0003 | B8: Asegurar que el servicio a retirar no esté siendo ofrecido actualmente por ningún barbero vigente | D8: BarberoServicio
A9: P-SER-0004 | B9: Asegurar que exista el servicio con el id enviado | D9: Servicio

Sheet E-Servicio
A1: << Ir al modelo de dominio | C1: << Ir al listado de objetos de dominio | F1: << Ir a la caracterización del objeto de dominio | J1: Ir al muestreo de datos del objeto de dominio >>
A2: Objeto de Dominio: | B2: ='Objetos de Dominio'!A5 -> Servicio
A3: Descripción: | B3: ='Objetos de Dominio'!B5 -> Representa cada tipo de corte o arreglo que ofrece la barbería, definido por el dueño, para que luego cada barbero decida cuáles sabe hacer.
A4: Actor | B4: Action/Command | D4: Entity/Aggregate/Object domain | E4: Read Model | G4: Business Rule/Policy | I4: External System | J4: Domain Event | K4: Hotspot/questions/Risk
A5: Actor | B5: Acción | C5: Descripción | D5: Objeto de dominio | E5: Información externa | G5: Políticas | I5: Sistema Externo | J5: Evento | K5: Aspectos por solucionar
E6: Información | F6: Descripción | G6: Número | H6: Descripción
A7: Dueño | B7: Ofrecer un servicio nuevo a la barbería | C7: Comando que permite registrar un nuevo tipo de servicio que la barbería pondrá a disposición de los barberos | D7: =$B$2 -> Servicio | G7: ='P-Servicio'!A6 -> P-SER-0001 | H7: aquí | J7: Servicio ofrecido
G8: ='P-Servicio'!A7 -> P-SER-0002 | H8: aquí
A9: Dueño | B9: Editar un servicio | C9: Permite modificar todos los atibutos de un servicio, que son el nombre, la descripción y el precio | D9: =$B$2 -> Servicio | G9: ='P-Servicio'!A6 -> P-SER-0001 | H9: aquí | J9: Nombre, descripción, precio del servicio actualizados
G10: ='P-Servicio'!A7 -> P-SER-0002 | H10: aquí
A11: Dueño | B11: Ver servicios disponibles de la barbería | C11: Permite consultar el catálogo de servicios que ofrece la barbería | D11: =$B$2 -> Servicio | J11: Servicios consultados
A12: Barbero | B12: Ver servicios disponibles de la barbería | C12: Permite consultar el catálogo de servicios que ofrece la barbería | D12: =$B$2 -> Servicio | J12: Servicios consultados
A13: Cliente | B13: Ver servicios disponibles de la barbería | C13: Permite consultar el catálogo de servicios que ofrece la barbería | D13: =$B$2 -> Servicio | J13: Servicios consultados
A14: Dueño | B14: Retirar un servicio de la barbería | C14: Permite dar de baja un servicio para que deje de ofrecerse a nuevos clientes | D14: =$B$2 -> Servicio | G14: ='P-Servicio'!A8 -> P-SER-0003 | H14: aquí | J14: Servicio retirado

Sheet M-Servicio
A1: <<<< Ir al modulo de dominio | B1: <<<< Ir a objetos de dominio
A2: Representa un identificador que hará unico cada objeto de dominio de este tipo, no se puede repetir | B2: Representa el nombre del servicio que va estar en la barberia, para que el barbero elija los servicios que el sabe hacer | C2: Representa una descripcion de que va a hacer cada servicio en la barberia, para que el barbero sepa que hace el servicio | D2: Representa cuanto va a valer el servicio en pesos colombianos | E2: Representa si el servicio sigue o no disponible en la barberia | F2: Combinacion única que indica que no puede existir más de un servicio con el mismo nombre
A3: id | B3: nombre | C3: descripcion | D3: precio | E3: disponible | F3: Combinacion única
A4: 1 | B4: Motilada | C4: Corte de cabello completo con máquina y tijera, incluye lavado y secado | D4: 22000 | E4: si | F4: =B4 -> Motilada
A5: 2 | B5: Corte de barba | C5: Recorte de la barba con máquina para dejarla pareja y a la medida que pide el cliente | D5: 12000 | E5: si | F5: =B5 -> Corte de barba
A6: 3 | B6: Perfilada de barba | C6: Delineado de los bordes de la barba y el bigote con navaja, sin recortar el largo | D6: 15000 | E6: si | F6: =B6 -> Perfilada de barba
A7: 4 | B7: Arreglo completo de barba con toalla caliente | C7: Recorte, perfilado con navaja, toalla caliente, exfoliación y aceite para la barba | D7: 35000 | E7: si | F7: =B7 -> Arreglo completo de barba con toalla caliente
B13: Corresponde a la descripcion de los atributos
B14: Corresponde al identificador unico del objeto de dominio
B15: Corresponde a los datos que ingresa el usuario
B16: Corresponde a los datos auto generados por el sistema
B17: Corresponde a la combinacion única

Sheet C-PrefijoCelular
A1: <<<< Ir al modulo de dominio | B1: <<<< Ir a objetos de dominio
A2: Nombre atributo | B2: Descripción atributo | C2: Identificador del objeto de dominio | D2: Tipo de dato | E2: Obligatorio | F2: Longitud mínima (si aplica) | G2: Longitud máxima (si aplica) | H2: Precisión (si aplica) | I2: Rendondeo (si aplica) | J2: Rango inicial (si aplica) | K2: Rango final (si aplica) | L2: Formato (si aplica) | M2: Reglas especiales (si aplica) | N2: Dato calculado | O2: Aplica ajuste del dato (si aplica) | P2: Carácter de ajuste (si aplica) | Q2: Quitar espacios en blanco al inicio (si aplica) | R2: Quitar espacios en blanco al fin (si aplica) | S2: Dato sensible (si aplica) | T2: Valor por defecto (si aplica) | U2: Auto generado | V2: =A11 -> registrarPrefijoCelular | W2: =A13 -> modificarPrefijoCelular | Y2: =A16 -> retirarPrefijoCelular | Z2: =A18 -> consultarPrefijosCelular
A3: ='M-PrefijoCelular'!A3 -> id | B3: ='M-PrefijoCelular'!A2 -> Representa un identificador que hará unico cada objeto de dominio de este tipo, no se puede repetir | C3: Si | D3: Identificador único universal | E3: Si | F3: No aplica | G3: No aplica | H3: No aplica | I3: No aplica | J3: No aplica | K3: No aplica | L3: No aplica | M3: No aplica | N3: No | O3: No | P3: No aplica | Q3: No | R3: No | S3: No | T3: No aplica | U3: Si | V3: No requerido | W3: Requerido | X3: No modificable | Y3: Requerido | Z3: No mostrar
A4: ='M-PrefijoCelular'!B3 -> prefijo | B4: ='M-PrefijoCelular'!B2 -> Representa el prefijo telefónico del país que el dueño habilita para que la barbería pueda atender números de ese país | C4: No | D4: Alfanumérico | E4: Si | F4: 2 | G4: 6 | H4: No aplica | I4: No aplica | J4: No aplica | K4: No aplica | L4: Simbolo + seguido de un número. Por ejemplo +57. Tambien el anterior puede ser seguido de un - y un numero. Por ejemplo +1-809 | M4: Solo se aceptan caracteres numericos del 0 al 9 y el carácter '+' y '-' | N4: No | O4: No | P4: No aplica | Q4: Si | R4: Si | S4: No | T4: +0 | U4: No | V4: Requerido | W4: Requerido | X4: Modificable | Y4: No requerido | Z4: Mostrar
A6: Nombre combinación única | B6: Descripción | C6: Atributos involucrados
A7: ='M-PrefijoCelular'!C3 -> Combinación única | B7: ='M-PrefijoCelular'!C2 -> Combinacion única que indica que no puede existir más un mismo prefijo | C7: prefijo
A9: Responsabilidad | C9: Descripción | G9: Entradas | J9: Salida | O9: Políticas (Reglas de Negocio) | Q9: Excepción
G10: Parámetro | H10: Tipo de dato | I10: Descripción | J10: Tipo de Dato | K10: Descripción | O10: Política | P10: Descripción | Q10: Detalle | R10: ¿Qué hago?
A11: registrarPrefijoCelular | C11: Comando que permite al dueño habilitar el prefijo de un país cuyos números va a atender la barbería | G11: datos{prefijo} | H11: PrefijoCelular | I11: Contiene la información requerida para habilitar un nuevo prefijo de país | J11: PrefijoCelular | K11: Contiene la información del prefijo de celular registrado | O11: ='P-PrefijoCelular'!A6 -> P-PRE-0001 | P11: ='P-PrefijoCelular'!B6 -> Asegurar que los datos requeridos (prefijo) sean válidos en tipo de dato, longitud, obligatoriedad, formato y regla especial | Q11: Generar una excepción indicándole al usuario que el prejo de celualr que envio no es válido | R11: Detener operación
O12: ='P-PrefijoCelular'!A7 -> P-PRE-0002 | P12: ='P-PrefijoCelular'!B7 -> Asegurar que no exista otro prefijo de celular registrado con el mismo valor | Q12: Generar una excepción indicándole al usuario que ya existe un prefijo de celular registrado con ese mismo valor | R12: Detener operación
A13: modificarPrefijoCelular | C13: Permite al dueño corregir el valor de un prefijo que ya había habilitado | G13: id | H13: UUID | I13: Corresponde al identificador del prefijo que se va a modificar | J13: PrefijoCelular | K13: Contiene la información del prefijo de celular modificado | O13: ='P-PrefijoCelular'!A9 -> P-PRE-0004 | P13: ='P-PrefijoCelular'!B9 -> Asegurar que exista el prefijo de celular con el id enviado | Q13: Informar con un mensaje que no existe un prefijo de celular con el identificador enviado y por lo tanto no es posible modificar el prefijo | R13: Detener operación
G14: datos{prefijo} | H14: PrefijoCelular | I14: Contiene el valor con el que se va a modificar el prefijo | O14: ='P-PrefijoCelular'!A6 -> P-PRE-0001 | P14: ='P-PrefijoCelular'!B6 -> Asegurar que los datos requeridos (prefijo) sean válidos en tipo de dato, longitud, obligatoriedad, formato y regla especial | Q14: Generar una excepción indicándole al usuario cuáles datos del prefijo no cumplen con las reglas definidas | R14: Detener operación
O15: ='P-PrefijoCelular'!A7 -> P-PRE-0002 | P15: ='P-PrefijoCelular'!B7 -> Asegurar que no exista otro prefijo de celular registrado con el mismo valor | Q15: Generar una excepción indicándole al usuario que ya existe un prefijo de celular registrado con ese mismo valor | R15: Detener operación
A16: retirarPrefijoCelular | C16: Permite al dueño quitar un prefijo para que la barbería deje de atender números de ese país | G16: id | H16: UUID | I16: Corresponde al identificador del prefijo que se va a retirar | K16: No retorna ningún valor. En caso de error genera una excepción. | O16: ='P-PrefijoCelular'!A8 -> P-PRE-0003 | P16: ='P-PrefijoCelular'!B8 -> Asegurar que el prefijo que se va a retirar no esté siendo usado por ningún barbero ni por ningún cliente | Q16: Generar una excepción indicándole al usuario que el prefijo no se puede retirar porque todavía lo usa algún barbero o algún cliente | R16: Detener operación
O17: ='P-PrefijoCelular'!A9 -> P-PRE-0004 | P17: ='P-PrefijoCelular'!B9 -> Asegurar que exista el prefijo de celular con el id enviado | Q17: Informar con un mensaje que no existe un prefijo de celular con el identificador enviado y por lo tanto no es posible dar de baja el prefijo | R17: Detener operación
A18: consultarPrefijosCelular | C18: Permite al dueño consultar el catálogo de prefijos telefónicos de país que tiene habilitados | J18: Lista<PrefijoCelular> | K18: Contiene todos los prefijos de celular registrados

Sheet P-PrefijoCelular
A1: << Ir al modelo de dominio | B1: << Ir al listado de objetos de dominio | C1: << Ir a la caracterización del objeto de dominio | D1: Ir al muestreo de datos del objeto de dominio >> | E1: Ir al event storming del objeto de dominio >>
A2: Objeto de Dominio: | B2: ='Objetos de Dominio'!A6 -> PrefijoCelular
A3: Descripción: | B3: ='Objetos de Dominio'!B6 -> Representa el catálogo de prefijos telefónicos de país que el dueño habilita, y que son los únicos que barberos y clientes pueden usar en su número de celular.
A4: Numero politica | B4: Descripcion politica | D4: Objeto responsable | E4: Regla responsable
A6: P-PRE-0001 | B6: Asegurar que los datos requeridos (prefijo) sean válidos en tipo de dato, longitud, obligatoriedad, formato y regla especial | D6: PrefijoCelular
A7: P-PRE-0002 | B7: Asegurar que no exista otro prefijo de celular registrado con el mismo valor | D7: PrefijoCelular
A8: P-PRE-0003 | B8: Asegurar que el prefijo que se va a retirar no esté siendo usado por ningún barbero ni por ningún cliente | D8: PrefijoCelular
A9: P-PRE-0004 | B9: Asegurar que exista el prefijo de celular con el id enviado | D9: PrefijoCelular

Sheet E-PrefijoCelular
A1: << Ir al modelo de dominio | C1: << Ir al listado de objetos de dominio | F1: << Ir a la caracterización del objeto de dominio | J1: Ir al muestreo de datos del objeto de dominio >>
A2: Objeto de Dominio: | B2: ='Objetos de Dominio'!A6 -> PrefijoCelular
A3: Descripción: | B3: ='Objetos de Dominio'!B6 -> Representa el catálogo de prefijos telefónicos de país que el dueño habilita, y que son los únicos que barberos y clientes pueden usar en su número de celular.
A4: Actor | B4: Action/Command | D4: Entity/Aggregate/Object domain | E4: Read Model | G4: Business Rule/Policy | I4: External System | J4: Domain Event | K4: Hotspot/questions/Risk
A5: Actor | B5: Acción | C5: Descripción | D5: Objeto de dominio | E5: Información externa | G5: Políticas | I5: Sistema Externo | J5: Evento | K5: Aspectos por solucionar
E6: Información | F6: Descripción | G6: Número | H6: Descripción
A7: Dueño | B7: Registrar un prefijo de celular | C7: Comando que permite al dueño habilitar el prefijo de un país cuyos números va a atender la barbería | D7: =$B$2 -> PrefijoCelular | G7: ='P-PrefijoCelular'!A6 -> P-PRE-0001 | H7: ='P-PrefijoCelular'!B6 -> Asegurar que los datos requeridos (prefijo) sean válidos en tipo de dato, longitud, obligatoriedad, formato y regla especial | J7: Prefijo de celular registrado
G8: ='P-PrefijoCelular'!A7 -> P-PRE-0002 | H8: ='P-PrefijoCelular'!B7 -> Asegurar que no exista otro prefijo de celular registrado con el mismo valor
A9: Dueño | B9: Modificar un prefijo de celular registrado | C9: Permite al dueño corregir el valor de un prefijo que ya había habilitado | D9: =$B$2 -> PrefijoCelular | G9: ='P-PrefijoCelular'!A6 -> P-PRE-0001 | H9: ='P-PrefijoCelular'!B6 -> Asegurar que los datos requeridos (prefijo) sean válidos en tipo de dato, longitud, obligatoriedad, formato y regla especial | J9: Prefijo de celular modificado
G10: ='P-PrefijoCelular'!A7 -> P-PRE-0002 | H10: ='P-PrefijoCelular'!B7 -> Asegurar que no exista otro prefijo de celular registrado con el mismo valor
A11: Dueño | B11: Retirar un prefijo de celular | C11: Permite al dueño quitar un prefijo para que la barbería deje de atender números de ese país | D11: =$B$2 -> PrefijoCelular | G11: ='P-PrefijoCelular'!A8 -> P-PRE-0003 | H11: ='P-PrefijoCelular'!B8 -> Asegurar que el prefijo que se va a retirar no esté siendo usado por ningún barbero ni por ningún cliente | J11: Prefijo de celular retirado
A12: Dueño | B12: Ver prefijos de celular | C12: Permite al dueño consultar el catálogo de prefijos telefónicos de país que tiene habilitados | D12: =$B$2 -> PrefijoCelular | J12: Prefijos de celular consultados
A13: Barbero | B13: Ver prefijos de celular | C13: Permite consultar el catálogo de prefijos telefónicos de país disponibles | D13: =$B$2 -> PrefijoCelular | J13: Prefijos de celular consultados
A14: Cliente | B14: Ver prefijos de celular | C14: Permite consultar el catálogo de prefijos telefónicos de país disponibles | D14: =$B$2 -> PrefijoCelular | J14: Prefijos de celular consultados

Sheet M-PrefijoCelular
A1: <<<< Ir al modulo de dominio | B1: <<<< Ir a objetos de dominio
A2: Representa un identificador que hará unico cada objeto de dominio de este tipo, no se puede repetir | B2: Representa el prefijo telefónico del país que el dueño habilita para que la barbería pueda atender números de ese país | C2: Combinacion única que indica que no puede existir más un mismo prefijo
A3: id | B3: prefijo | C3: Combinación única
A4: 1 | B4: +57 | C4: =B4 -> +57
A5: 2 | B5: +91 | C5: =B5 -> +91
A6: 3 | B6: +593 | C6: =B6 -> +593
A7: 4 | B7: +58 | C7: =B7 -> +58
B13: Corresponde a la descripcion de los atributos
B14: Corresponde al identificador unico del objeto de dominio
B15: Corresponde a los datos que ingresa el usuario
B16: Corresponde a la combinacion única

Sheet C-TipoMulta
A1: <<<< Ir al modulo de dominio | B1: <<<< Ir a objetos de dominio
A2: Nombre atributo | B2: Descripción atributo | C2: Identificador del objeto de dominio | D2: Tipo de dato | E2: Obligatorio | F2: Longitud mínima (si aplica) | G2: Longitud máxima (si aplica) | H2: Precisión (si aplica) | I2: Rendondeo (si aplica) | J2: Rango inicial (si aplica) | K2: Rango final (si aplica) | L2: Formato (si aplica) | M2: Reglas especiales (si aplica) | N2: Dato calculado | O2: Aplica ajuste del dato (si aplica) | P2: Carácter de ajuste (si aplica) | Q2: Quitar espacios en blanco al inicio (si aplica) | R2: Quitar espacios en blanco al fin (si aplica) | S2: Dato sensible (si aplica) | T2: Valor por defecto (si aplica) | U2: Auto generado | V2: =A12 -> consultarTodosLosTiposMulta
A3: ='M-TipoMulta'!A3 -> id | B3: ='M-TipoMulta'!A2 -> Representa un identificador que hará unico cada objeto de dominio de este tipo, no se puede repetir | C3: Si | D3: Identificador único universal | E3: Si | F3: No aplica | G3: No aplica | H3: No aplica | I3: No aplica | J3: No aplica | K3: No aplica | L3: No aplica | M3: No aplica | N3: No | O3: No | P3: No aplica | Q3: No | R3: No | S3: No | T3: UUID vacio | U3: Si | V3: No mostrar
A4: ='M-TipoMulta'!B3 -> nombre | B4: ='M-TipoMulta'!B2 -> Representa el nombre del tipo de multa | C4: No | D4: Alfanumérico | E4: Si | F4: 4 | G4: 50 | H4: No aplica | I4: No aplica | J4: No aplica | K4: No aplica | L4: No aplica | M4: No aplica | N4: No | O4: No | P4: No aplica | Q4: Si | R4: Si | S4: No | T4: Vacio | U4: No | V4: Mostrar
A5: ='M-TipoMulta'!C3 -> descripcion | B5: ='M-TipoMulta'!C2 -> Representa que hace cada tipo de multa | C5: No | D5: Alfanumérico | E5: Si | F5: 10 | G5: 300 | H5: No aplica | I5: No aplica | J5: No aplica | K5: No aplica | L5: No aplica | M5: No aplica | N5: No | O5: No | P5: No aplica | Q5: Si | R5: Si | S5: No | T5: Vacio | U5: No | V5: Mostrar
A7: Nombre combinación única | B7: Descripción | C7: Atributos involucrados
A8: ='M-TipoMulta'!D3 -> Combinación única | B8: ='M-TipoMulta'!D2 -> Combinación única indica que no puede existir más de un tipo de multa con el mismo nombre | C8: nombre
A10: Responsabilidad | C10: Descripción | G10: Entradas | J10: Salida | O10: Políticas (Reglas de Negocio) | Q10: Excepción
G11: Parámetro | H11: Tipo de dato | I11: Descripción | J11: Tipo de Dato | K11: Descripción | O11: Política | P11: Descripción | Q11: Detalle | R11: ¿Qué hago?
A12: consultarTodosLosTiposMulta | C12: Permite consultar los tipos de multa que puede recibir un cliente | J12: Lista<TipoMulta> | K12: Contiene todos los tipos de multa que hay

Sheet P-TipoMulta
A1: << Ir al modelo de dominio | B1: << Ir al listado de objetos de dominio | C1: << Ir a la caracterización del objeto de dominio | D1: Ir al muestreo de datos del objeto de dominio >> | E1: Ir al event storming del objeto de dominio >>
A2: Objeto de Dominio: | B2: ='Objetos de Dominio'!A7 -> TipoMulta
A3: Descripción: | B3: ='Objetos de Dominio'!B7 -> Representa los tipos de multa que puede recibir un cliente: por tardanza o por inasistencia.
A4: Numero politica | B4: Descripcion politica | D4: Objeto responsable | E4: Regla responsable
B6: No aplica: es un catálogo de solo lectura, sin comandos que impliquen políticas de negocio propias

Sheet E-TipoMulta
A1: << Ir al modelo de dominio | C1: << Ir al listado de objetos de dominio | F1: << Ir a la caracterización del objeto de dominio | J1: Ir al muestreo de datos del objeto de dominio >>
A2: Objeto de Dominio: | B2: ='Objetos de Dominio'!A7 -> TipoMulta
A3: Descripción: | B3: ='Objetos de Dominio'!B7 -> Representa los tipos de multa que puede recibir un cliente: por tardanza o por inasistencia.
A4: Actor | B4: Action/Command | D4: Entity/Aggregate/Object domain | E4: Read Model | G4: Business Rule/Policy | I4: External System | J4: Domain Event | K4: Hotspot/questions/Risk
A5: Actor | B5: Acción | C5: Descripción | D5: Objeto de dominio | E5: Información externa | G5: Políticas | I5: Sistema Externo | J5: Evento | K5: Aspectos por solucionar
E6: Información | F6: Descripción | G6: Número | H6: Descripción
A7: Dueño | B7: Ver tipos de multa | C7: Permite consultar los tipos de multa que puede recibir un cliente | D7: =$B$2 -> TipoMulta | J7: Tipos de multa consultados
A8: Barbero | B8: Ver tipos de multa | C8: Permite consultar los tipos de multa que puede recibir un cliente | D8: =$B$2 -> TipoMulta | J8: Tipos de multa consultados
A9: Cliente | B9: Ver tipos de multa | C9: Permite consultar los tipos de multa que puede recibir un cliente | D9: =$B$2 -> TipoMulta | J9: Tipos de multa consultados

Sheet M-TipoMulta
A1: <<<< Ir al modulo de dominio | B1: <<<< Ir a objetos de dominio
A2: Representa un identificador que hará unico cada objeto de dominio de este tipo, no se puede repetir | B2: Representa el nombre del tipo de multa | C2: Representa que hace cada tipo de multa | D2: Combinación única indica que no puede existir más de un tipo de multa con el mismo nombre
A3: id | B3: nombre | C3: descripcion | D3: Combinación única
A4: 1 | B4: Tardanza | C4: El cliente llegó a la cita después de la hora acordada, superando los minutos de tiempoEspera definidos en la cita. | D4: =B4 -> Tardanza
A5: 2 | B5: Inasistencia | C5: El cliente no se presentó a la cita agendada: se llegó a la hora estimada de finalización sin que hubiera registrado su llegada. | D5: =B5 -> Inasistencia
B11: Corresponde a la descripcion de los atributos
B12: Corresponde al identificador unico del objeto de dominio
B13: Corresponde a los datos que ingresa el usuario
B14: Corresponde a la combinacion única

Sheet C-Barbero
A1: <<<< Ir al modulo de dominio | B1: <<<< Ir a objetos de dominio
A2: Nombre atributo | B2: Descripción atributo | C2: Identificador del objeto de dominio | D2: Tipo de dato | E2: Obligatorio | F2: Longitud mínima (si aplica) | G2: Longitud máxima (si aplica) | H2: Precisión (si aplica) | I2: Rendondeo (si aplica) | J2: Rango inicial (si aplica) | K2: Rango final (si aplica) | L2: Formato (si aplica) | M2: Reglas especiales (si aplica) | N2: Dato calculado | O2: Aplica ajuste del dato (si aplica) | P2: Carácter de ajuste (si aplica) | Q2: Quitar espacios en blanco al inicio (si aplica) | R2: Quitar espacios en blanco al fin (si aplica) | S2: Dato sensible (si aplica) | T2: Valor por defecto (si aplica) | U2: Auto generado | V2: =A21 -> registrarBarbero | W2: =A24 -> editarContactoBarbero | Y2: =A27 -> editarTiemposAnticipacionBarbero | AA2: =A29 -> consultarDatosBarbero | AB2: =A30 -> desactivarBarbero | AD2: =A32 -> consultarTiemposAnticipacionBarbero | AE2: =A33 -> reactivarBarbero
A3: ='M-Barbero'!A3 -> id | B3: ='M-Barbero'!A2 -> Representa un identificador que hará unico cada objeto de dominio de este tipo, no se puede repetir | C3: Si | D3: Identificador único universal | E3: Si | F3: No aplica | G3: No aplica | H3: No aplica | I3: No aplica | J3: No aplica | K3: No aplica | L3: No aplica | M3: No aplica | N3: No | O3: No aplica | P3: No aplica | Q3: No | R3: No | S3: No | T3: UUID vacio | U3: Si | V3: No requerido | W3: Requerido | X3: No modificable | Y3: Requerido | Z3: No modificable | AA3: No mostrar | AB3: Requerido | AC3: No modificable | AD3: No mostrar | AE3: Requerido | AF3: No modificable
A4: ='M-Barbero'!B3 -> primerNombre | B4: ='M-Barbero'!B2 -> Representa el primer nombre del barbero que trabaja en barbería | C4: No | D4: Alfanumérico | E4: Si | F4: 3 | G4: 100 | H4: No aplica | I4: No aplica | J4: No aplica | K4: No aplica | L4: No aplica | M4: Solo se aceptan caracteres de letras de la 'a' a la 'z', caracteres con tilde y numeros del 0 al 9 | N4: No | O4: No | P4: No | Q4: Si | R4: Si | S4: No | T4: vacío | U4: No | V4: Requerido | W4: No requerido | X4: No modificable | Y4: No requerido | Z4: No modificable | AA4: Mostrar | AB4: No requerido | AC4: No modificable | AD4: No mostrar | AE4: No requerido | AF4: No modificable
A5: ='M-Barbero'!C3 -> segundoNombre | B5: ='M-Barbero'!C2 -> Representa el segundo nombre del barbero que trabaja en barbería | C5: No | D5: Alfanumérico | E5: No | F5: 3 | G5: 100 | H5: No aplica | I5: No aplica | J5: No aplica | K5: No aplica | L5: No aplica | M5: Solo se aceptan caracteres de letras de la 'a' a la 'z', caracteres con tilde y numeros del 0 al 9 | N5: No | O5: No | P5: No | Q5: Si | R5: Si | S5: No | T5: vacío | U5: No | V5: No requerido | W5: No requerido | X5: No modificable | Y5: No requerido | Z5: No modificable | AA5: Mostrar | AB5: No requerido | AC5: No modificable | AD5: No mostrar | AE5: No requerido | AF5: No modificable
A6: ='M-Barbero'!D3 -> primerApellido | B6: ='M-Barbero'!D2 -> Representa el primer apellido del barbero que trabaja en la barbería | C6: No | D6: Alfanumérico | E6: Si | F6: 3 | G6: 100 | H6: No aplica | I6: No aplica | J6: No aplica | K6: No aplica | L6: No aplica | M6: Solo se aceptan caracteres de letras de la 'a' a la 'z', caracteres con tilde y numeros del 0 al 9 | N6: No | O6: No | P6: No | Q6: Si | R6: Si | S6: No | T6: vacío | U6: No | V6: Requerido | W6: No requerido | X6: No modificable | Y6: No requerido | Z6: No modificable | AA6: Mostrar | AB6: No requerido | AC6: No modificable | AD6: No mostrar | AE6: No requerido | AF6: No modificable
A7: ='M-Barbero'!E3 -> segundoApellido | B7: ='M-Barbero'!E2 -> Representa el segundo apellido del barbero que trabaja en la barbería | C7: No | D7: Alfanumérico | E7: No | F7: 3 | G7: 100 | H7: No aplica | I7: No aplica | J7: No aplica | K7: No aplica | L7: No aplica | M7: Solo se aceptan caracteres de letras de la 'a' a la 'z', caracteres con tilde y numeros del 0 al 9 | N7: No | O7: No | P7: No | Q7: Si | R7: Si | S7: No | T7: vacío | U7: No | V7: No requerido | W7: No requerido | X7: No modificable | Y7: No requerido | Z7: No modificable | AA7: Mostrar | AB7: No requerido | AC7: No modificable | AD7: No mostrar | AE7: No requerido | AF7: No modificable
A8: ='M-Barbero'!F3 -> prefijo | B8: ='M-Barbero'!F2 -> Representa cual es el prefijo del numero de celular del barbero | C8: No | D8: PrefijoCelular | E8: Si | F8: No aplica | G8: No aplica | H8: No aplica | I8: No aplica | J8: No aplica | K8: No aplica | L8: No aplica | M8: Aplican las reglas del objeto referenciado | N8: No | O8: No aplica | P8: No aplica | Q8: No aplica | R8: No aplica | S8: No | T8: UUID vacio | U8: No | V8: Requerido | W8: Requerido | X8: Modificable | Y8: No requerido | Z8: No modificable | AA8: Mostrar | AB8: No requerido | AC8: No modificable | AD8: No mostrar | AE8: No requerido | AF8: No modificable
A9: ='M-Barbero'!G3 -> celular | B9: ='M-Barbero'!G2 -> Representa el número de celular del barbero, es el dato que el cliente necesita en caso de que tenga que contactarse con el | C9: No | D9: Alfanumérico | E9: Si | F9: 6 | G9: 15 | H9: No aplica | I9: No aplica | J9: No aplica | K9: No aplica | L9: No aplica | M9: Solo se aceptan caracteres de numeros del '0' al '9' | N9: No | O9: No aplica | P9: No aplica | Q9: Si | R9: Si | S9: Si | T9: 0 | U9: No | V9: Requerido | W9: Requerido | X9: Modificable | Y9: No requerido | Z9: No modificable | AA9: Mostrar | AB9: No requerido | AC9: No modificable | AD9: No mostrar | AE9: No requerido | AF9: No modificable
A10: ='M-Barbero'!H3 -> elNumeroCelularEsCorrecto | B10: ='M-Barbero'!H2 -> Representa si el numero que ingreso el cliente es correcto o no | C10: No | D10: Lógico | E10: Si | F10: No aplica | G10: No aplica | H10: No aplica | I10: No aplica | J10: No aplica | K10: No aplica | L10: No aplica | M10: El barbero debe de poner un si en este atributo | N10: No | O10: No aplica | P10: No aplica | Q10: No aplica | R10: No aplica | S10: No | T10: No | U10: No | V10: Requerido | W10: No requerido | X10: No modificable | Y10: No requerido | Z10: No modificable | AA10: Mostrar | AB10: Requerido | AC10: Modificable | AD10: No mostrar | AE10: Requerido | AF10: Modificable
A11: ='M-Barbero'!I3 -> vigente | B11: ='M-Barbero'!I2 -> Representa si el barbero sigue o no trabajando en la barberia | C11: No | D11: Lógico | E11: No | F11: No aplica | G11: No aplica | H11: No aplica | I11: No aplica | J11: No aplica | K11: No aplica | L11: No aplica | M11: No aplica | N11: Si | O11: No aplica | P11: No aplica | Q11: No aplica | R11: No aplica | S11: No | T11: Si | U11: Si | V11: No requerido | W11: No requerido | X11: No modificable | Y11: No requerido | Z11: No modificable | AA11: Mostrar | AB11: No requerido | AC11: No modificable | AD11: No mostrar | AE11: No requerido | AF11: No modificable
A12: ='M-Barbero'!J3 -> anticipacionEnHorasParaAgendarCita | B12: ='M-Barbero'!J2 -> Representa la parte en horas del tiempo mínimo de anticipación con el que un cliente debe pedirle una cita a este barbero. Junto con anticipacionEnMinutosParaAgendarCita forma el tiempo total de anticipación que exige el barbero | C12: No | D12: Entero | E12: No | F12: No aplica | G12: No aplica | H12: No aplica | I12: No aplica | J12: 0 | K12: 720 | L12: Horas | M12: No aplica | N12: No | O12: No aplica | P12: No aplica | Q12: No aplica | R12: No aplica | S12: No | T12: 0 | U12: No | V12: No requerido | W12: No requerido | X12: No modificable | Y12: Requerido | Z12: Modificable | AA12: No mostrar | AB12: No requerido | AC12: No modificable | AD12: Mostrar | AE12: No requerido | AF12: No modificable
A13: ='M-Barbero'!K3 -> anticipacionEnMinutosParaAgendarCita | B13: ='M-Barbero'!K2 -> Representa la parte en minutos del tiempo mínimo de anticipación con el que un cliente debe pedirle una cita a este barbero. Junto con anticipacionEnHorasParaAgendarCita forma el tiempo total de anticipación que exige el barbero | C13: No | D13: Entero | E13: No | F13: No aplica | G13: No aplica | H13: No aplica | I13: No aplica | J13: 0 | K13: 59 | L13: Minutos | M13: No aplica | N13: No | O13: No aplica | P13: No aplica | Q13: No aplica | R13: No aplica | S13: No | T13: 0 | U13: No | V13: No requerido | W13: No requerido | X13: No modificable | Y13: Requerido | Z13: Modificable | AA13: No mostrar | AB13: No requerido | AC13: No modificable | AD13: Mostrar | AE13: No requerido | AF13: No modificable
A15: Nombre combinación única | B15: Descripción | C15: Atributos involucrados
A16: ='M-Barbero'!L3 -> Combinación única 1 | B16: ='M-Barbero'!L2 -> Combinacion única que indica que no puede existir más de un barbero con el mismo prefijo de celular y número de celular | C16: =A8 -> prefijo
C17: =A9 -> celular
A19: Responsabilidad | C19: Descripción | G19: Entradas | J19: Salida | O19: Políticas (Reglas de Negocio) | Q19: Excepción
G20: Parámetro | H20: Tipo de dato | I20: Descripción | J20: Tipo de Dato | K20: Descripción | O20: Política | P20: Descripción | Q20: Detalle | R20: ¿Qué hago?
A21: registrarBarbero | C21: Comando que permite el ingreso de un nuevo barbero a trabajar en la barbería | G21: datos{primerNombre, segundoNombre, primerApellido, segundoApellido, prefijoCelular, celular, elNumeroCelularEsCorrecto} | H21: Barbero | I21: Contiene la información requerida para registrar un nuevo barbero en la barbería | J21: Barbero | K21: Contiene la información del barbero registrado | O21: ='P-Barbero'!A6 -> P-BAR-0001 | P21: ='P-Barbero'!B6 -> Asegurar que los datos requeridos del barbero (nombre, apellido, prefijo de celular, celular, tiempos de anticipación) sean válidos en tipo de dato, longitud, obligatoriedad, formato y rango | Q21: Generar una excepción indicándole al barbero que los datos ingresados no son válidos | R21: Detener operación
O22: ='P-Barbero'!A7 -> P-BAR-0002 | P22: ='P-Barbero'!B7 -> Asegurar que el número de celular y prefijo de celular no esté siendo utilizado por otro barbero | Q22: Generar una excepción indicándole al usuario que ya existe otro barbero registrado con ese prefijo y número de celular | R22: Detener operación
O23: ='P-Barbero'!A11 -> P-BAR-0006 | P23: ='P-Barbero'!B11 -> Asegurar que el barbero halla puesto un si en el atributo elNumeroCelularEsCorrecto | Q23: Generar una excepción indicándole al barbero que ponga si en elNumeroCelularEsCorrecto | R23: Detener operación
A24: editarContactoBarbero | C24: Permite al barbero actualizar su número de celular y su prefijo | G24: id | H24: UUID | I24: Corresponde al identificador del barbero que va a editar su contacto | J24: Barbero | K24: Contiene la información del barbero con su contacto actualizado | O24: ='P-Barbero'!A12 -> P-BAR-0007 | P24: ='P-Barbero'!B12 -> Asegurar que exista el barbero con el id enviado | Q24: Informar con un mensaje que no existe un barbero con el identificador enviado y por lo tanto no es posible editar el contacto del barbero | R24: Detener operación
G25: datos{prefijoCelular, celular} | H25: Barbero | I25: Contiene el nuevo prefijo y número de celular del barbero | O25: ='P-Barbero'!A9 -> P-BAR-0004 | P25: ='P-Barbero'!B9 -> Asegurar que los datos requeridos del barbero para editar su contacto (prefijo de celular, celular) sean válidos en tipo de dato, longitud, obligatoriedad, formato y rango | Q25: Generar una excepción indicándole al usuario cuáles datos de contacto del barbero no cumplen con las reglas definidas | R25: Detener operación
A27: editarTiemposAnticipacionBarbero | C27: Permite al barbero ajustar cuánta anticipación mínima exige para que le agenden una cita | G27: id | H27: UUID | I27: Corresponde al identificador del barbero que va a editar sus tiempos | J27: Barbero | K27: Contiene la información del barbero con sus tiempos de anticipación actualizados | O27: ='P-Barbero'!A12 -> P-BAR-0007 | P27: ='P-Barbero'!B12 -> Asegurar que exista el barbero con el id enviado | Q27: Informar con un mensaje que no existe un barbero con el identificador enviado y por lo tanto no es posible editar los tiempos de anticipacion del barbero | R27: Detener operación
G28: datos{anticipacionEnHorasParaAgendarCita, anticipacionEnMinutosParaAgendarCita} | H28: Barbero | I28: Contiene los nuevos tiempos de anticipación que exige el barbero | O28: ='P-Barbero'!A10 -> P-BAR-0005 | P28: ='P-Barbero'!B10 -> Asegurar que los datos requeridos del barbero editar sus tiempos de anticipación (prefijo de celular, celular) sean válidos en tipo de dato, longitud, obligatoriedad, formato y rango | Q28: Generar una excepción indicándole al usuario cuáles tiempos de anticipación no cumplen con las reglas definidas | R28: Detener operación
A29: consultarDatosBarbero | C29: Permite a un cliente ver los datos públicos de un barbero, como sus nombres, apellidos y su contacto | G29: id | H29: UUID | I29: Corresponde al identificador del barbero que se va a consultar | J29: Barbero | K29: Contiene la información del barbero consultado por su identificador | O29: ='P-Barbero'!A12 -> P-BAR-0007 | P29: ='P-Barbero'!B12 -> Asegurar que exista el barbero con el id enviado | Q29: Informar con un mensaje que no existe un barbero con el identificador enviado y por lo tanto no es posible consultar los datos | R29: Detener operación
A30: desactivarBarbero | C30: Permite desactivar a un barbero para que ya no pueda recibir nuevas citas | G30: id | H30: UUID | I30: Corresponde al identificador del barbero que va a dejar de trabajar | J30: No retorna ningún valor. En caso de error genera una excepción. | O30: ='P-Barbero'!A8 -> P-BAR-0003 | P30: ='P-Barbero'!B8 -> Asegurar que el barbero no tenga citas futuras pendientes antes de dejar de trabajar en la barbería | Q30: Generar una excepción indicándole al usuario que el barbero no puede dejar de trabajar porque todavía tiene citas futuras pendientes | R30: Detener operación
O31: ='P-Barbero'!A12 -> P-BAR-0007 | P31: ='P-Barbero'!B12 -> Asegurar que exista el barbero con el id enviado | Q31: Informar con un mensaje que no existe un barbero con el identificador enviado y por lo tanto no es posible desactivar el barbero | R31: Detener operación
A32: consultarTiemposAnticipacionBarbero | C32: Permite al barbero ver su tiempo de anticipacion en horas y minutos para sus citas | G32: id | H32: UUID | I32: Corresponde al identificador del barbero que se va a consultar | J32: Barbero | K32: Contiene los tiempos de anticipación que exige el barbero consultado | O32: ='P-Barbero'!A12 -> P-BAR-0007 | P32: ='P-Barbero'!B12 -> Asegurar que exista el barbero con el id enviado | Q32: Informar con un mensaje que no existe un barbero con el identificador enviado y por lo tanto no es posible cosultar los tiempos de anticipación del barbero | R32: Detener operación
A33: reactivarBarbero | C33: Permite activar a un barbero para que ya pueda volver a recibir citas de sus clientes | G33: id | H33: UUID | I33: Corresponde al identificador del barbero que va a dejar de trabajar | J33: No retorna ningún valor. En caso de error genera una excepción. | O33: ='P-Barbero'!A12 -> P-BAR-0007 | P33: ='P-Barbero'!B12 -> Asegurar que exista el barbero con el id enviado | Q33: Informar con un mensaje que no existe un barbero con el identificador enviado y por lo tanto no es posible reactivar el barbero | R33: Detener operación

Sheet P-Barbero
A1: << Ir al modelo de dominio | B1: << Ir al listado de objetos de dominio | C1: << Ir a la caracterización del objeto de dominio | D1: Ir al muestreo de datos del objeto de dominio >> | E1: Ir al event storming del objeto de dominio >>
A2: Objeto de Dominio: | B2: ='Objetos de Dominio'!A8 -> Barbero
A3: Descripción: | B3: ='Objetos de Dominio'!B8 -> Representa a un trabajador de la barbería que atiende clientes según los servicios que sabe realizar, organiza su propio horario y tiene su agenda personal para atender todas las citas que valla teniendo.
A4: Numero politica | B4: Descripcion politica | D4: Objeto responsable | E4: Regla responsable
A6: P-BAR-0001 | B6: Asegurar que los datos requeridos del barbero (nombre, apellido, prefijo de celular, celular, tiempos de anticipación) sean válidos en tipo de dato, longitud, obligatoriedad, formato y rango | D6: Barbero
A7: P-BAR-0002 | B7: Asegurar que el número de celular y prefijo de celular no esté siendo utilizado por otro barbero | D7: Barbero
A8: P-BAR-0003 | B8: Asegurar que el barbero no tenga citas futuras pendientes antes de dejar de trabajar en la barbería | D8: Cita
A9: P-BAR-0004 | B9: Asegurar que los datos requeridos del barbero para editar su contacto (prefijo de celular, celular) sean válidos en tipo de dato, longitud, obligatoriedad, formato y rango | D9: Barbero
A10: P-BAR-0005 | B10: Asegurar que los datos requeridos del barbero editar sus tiempos de anticipación (prefijo de celular, celular) sean válidos en tipo de dato, longitud, obligatoriedad, formato y rango | D10: Barbero
A11: P-BAR-0006 | B11: Asegurar que el barbero halla puesto un si en el atributo elNumeroCelularEsCorrecto | D11: Barbero
A12: P-BAR-0007 | B12: Asegurar que exista el barbero con el id enviado | D12: Barbero

Sheet E-Barbero
A1: << Ir al modelo de dominio | C1: << Ir al listado de objetos de dominio | F1: << Ir a la caracterización del objeto de dominio | J1: Ir al muestreo de datos del objeto de dominio >>
A2: Objeto de Dominio: | B2: ='Objetos de Dominio'!A8 -> Barbero
A3: Descripción: | B3: ='Objetos de Dominio'!B8 -> Representa a un trabajador de la barbería que atiende clientes según los servicios que sabe realizar, organiza su propio horario y tiene su agenda personal para atender todas las citas que valla teniendo.
A4: Actor | B4: Action/Command | D4: Entity/Aggregate/Object domain | E4: Read Model | G4: Business Rule/Policy | I4: External System | J4: Domain Event | K4: Hotspot/questions/Risk
A5: Actor | B5: Acción | C5: Descripción | D5: Objeto de dominio | E5: Información externa | G5: Políticas | I5: Sistema Externo | J5: Evento | K5: Aspectos por solucionar
E6: Información | F6: Descripción | G6: Número | H6: Descripción
A7: Barbero | B7: Registrar barbero a la barbería | C7: Comando que permite el ingreso de un nuevo barbero a trabajar en la barbería | D7: =$B$2 -> Barbero | G7: ='P-Barbero'!A6 -> P-BAR-0001 | H7: aquí | J7: Barbero registrado
G8: ='P-Barbero'!A7 -> P-BAR-0002 | H8: aquí
A9: Barbero | B9: Editar contacto | C9: Permite al barbero actualizar su número de celular y su prefijo | D9: =$B$2 -> Barbero | G9: ='P-Barbero'!A9 -> P-BAR-0004 | H9: aquí | J9: Contacto de barbero actualizado
A10: Barbero | B10: Editar tiempos de anticipación de citas | C10: Permite al barbero ajustar cuánta anticipación mínima exige para que le agenden una cita | D10: =$B$2 -> Barbero | G10: ='P-Barbero'!A10 -> P-BAR-0005 | H10: aquí | J10: Tiempos de anticipación de barbero actualizados
A11: Cliente | B11: Ver datos de un barbero | C11: Permite a un cliente ver los datos públicos de un barbero, como sus nombres, apellidos y su contacto | D11: =$B$2 -> Barbero | J11: Datos de barbero visto
A12: Barbero | B12: Ver datos de un barbero | C12: Permite a un barbero ver los datos públicos de otro barbero, como sus nombres, apellidos y su contacto | D12: =$B$2 -> Barbero | J12: Datos de barbero visto
A13: Barbero | B13: Dejar de trabajar en la barbería | C13: Permite desactivar a un barbero para que ya no pueda recibir nuevas citas, sin borrar su historial | D13: =$B$2 -> Barbero | G13: ='P-Barbero'!A8 -> P-BAR-0003 | H13: aquí | J13: Barbero desactivado
A14: Barbero | B14: Ver tiempos de anticipacion para las citas | C14: Permite al barbero ver su tiempo de anticipacion en horas y minutos para sus citas | D14: =$B$2 -> Barbero | J14: Tiempos de anticipación de barbero vistos
A15: Barbero | B15: Volver a trabajar en la barbería | C15: Permite desactivar a un barbero para que ya no pueda recibir nuevas citas, sin borrar su historial | D15: =$B$2 -> Barbero | J15: Barbero activado

Sheet M-Barbero
A1: <<<< Ir al modulo de dominio | B1: <<<< Ir a objetos de dominio
A2: Representa un identificador que hará unico cada objeto de dominio de este tipo, no se puede repetir | B2: Representa el primer nombre del barbero que trabaja en barbería | C2: Representa el segundo nombre del barbero que trabaja en barbería | D2: Representa el primer apellido del barbero que trabaja en la barbería | E2: Representa el segundo apellido del barbero que trabaja en la barbería | F2: Representa cual es el prefijo del numero de celular del barbero | G2: Representa el número de celular del barbero, es el dato que el cliente necesita en caso de que tenga que contactarse con el | H2: Representa si el numero que ingreso el cliente es correcto o no | I2: Representa si el barbero sigue o no trabajando en la barberia | J2: Representa la parte en horas del tiempo mínimo de anticipación con el que un cliente debe pedirle una cita a este barbero. Junto con anticipacionEnMinutosParaAgendarCita forma el tiempo total de anticipación que exige el barbero | K2: Representa la parte en minutos del tiempo mínimo de anticipación con el que un cliente debe pedirle una cita a este barbero. Junto con anticipacionEnHorasParaAgendarCita forma el tiempo total de anticipación que exige el barbero | L2: Combinacion única que indica que no puede existir más de un barbero con el mismo prefijo de celular y número de celular
A3: id | B3: primerNombre | C3: segundoNombre | D3: primerApellido | E3: segundoApellido | F3: prefijo | G3: celular | H3: elNumeroCelularEsCorrecto | I3: vigente | J3: anticipacionEnHorasParaAgendarCita | K3: anticipacionEnMinutosParaAgendarCita | L3: Combinación única 1
A4: 1 | B4: Juan | C4: Fernando | D4: García | E4: Lopez | F4: ='M-PrefijoCelular'!C4 -> +57 | G4: 3245627890 | H4: Si | I4: si | J4: 24 | K4: 0 | L4: =_xlfn.CONCAT(F4,"-",G4) -> +57-3245627890
A5: 2 | B5: Juan | C5: David | D5: Ortiz | E5: Sanchez | F5: ='M-PrefijoCelular'!C4 -> +57 | G5: 3124518923 | H5: Si | I5: si | J5: 0 | K5: 30 | L5: =_xlfn.CONCAT(F5,"-",G5) -> +57-3124518923
A6: 3 | B6: Carlos | D6: Arbeladez | F6: ='M-PrefijoCelular'!C4 -> +57 | G6: 3214533321 | H6: Si | I6: si | J6: 1 | K6: 0 | L6: =_xlfn.CONCAT(F6,"-",G6) -> +57-3214533321
A7: 4 | B7: Andres | D7: Ramirez | E7: Patiño | F7: ='M-PrefijoCelular'!C5 -> +91 | G7: 9876543210 | H7: Si | I7: no | J7: 0 | K7: 0 | L7: =_xlfn.CONCAT(F7,"-",G7) -> +91-9876543210
A8: 5 | B8: Juan | C8: Carlos | D8: Zambrano | E8: Perez | F8: ='M-PrefijoCelular'!C6 -> +593 | G8: 998765432 | H8: Si | I8: no | J8: 2 | K8: 0 | L8: =_xlfn.CONCAT(F8,"-",G8) -> +593-998765432
B14: Corresponde a la descripcion de los atributos
B15: Corresponde al identificador unico del objeto de dominio
B16: Corresponde a las referencias de otros objetos de dominio
B17: Corresponde a los datos auto generados por el sistema
B18: Corresponde a los datos que ingresa el usuario
B19: Corresponde a la combinacion única

Sheet C-Cliente
A1: <<<< Ir al modulo de dominio | B1: <<<< Ir a objetos de dominio
A2: Nombre atributo | B2: Descripción atributo | C2: Identificador del objeto de dominio | D2: Tipo de dato | E2: Obligatorio | F2: Longitud mínima (si aplica) | G2: Longitud máxima (si aplica) | H2: Precisión (si aplica) | I2: Rendondeo (si aplica) | J2: Rango inicial (si aplica) | K2: Rango final (si aplica) | L2: Formato (si aplica) | M2: Reglas especiales (si aplica) | N2: Dato calculado | O2: Aplica ajuste del dato (si aplica) | P2: Carácter de ajuste (si aplica) | Q2: Quitar espacios en blanco al inicio (si aplica) | R2: Quitar espacios en blanco al fin (si aplica) | S2: Dato sensible (si aplica) | T2: Valor por defecto (si aplica) | U2: Auto generado | V2: =A21 -> registrarCliente | W2: =A23 -> editarContactoCliente | Y2: =A26 -> consultarDatosCliente | Z2: =A27 -> consultarEstadoVetoCliente | AA2: =A28 -> consultarCantidadMultasSinPagar
A3: ='M-Cliente'!A3 -> id | B3: ='M-Cliente'!A2 -> Representa un identificador que hará unico cada objeto de dominio de este tipo, no se puede repetir | C3: Si | D3: Identificador único universal | E3: Si | F3: No aplica | G3: No aplica | H3: No aplica | I3: No aplica | J3: No aplica | K3: No aplica | L3: No aplica | M3: No aplica | N3: Si | O3: No | P3: No aplica | Q3: No aplica | R3: No aplica | S3: No | T3: UUID vacio | U3: Si | V3: No requerido | W3: Requerido | X3: No modificable | Y3: No mostrar | Z3: No mostrar | AA3: No mostrar
A4: ='M-Cliente'!B3 -> primerNombre | B4: ='M-Cliente'!B2 -> Representa el primer nombre de la persona, que va a estar llendo a la barberia para las citas | C4: No | D4: Alfanumérico | E4: Si | F4: 2 | G4: 50 | H4: No aplica | I4: No aplica | J4: No aplica | K4: No aplica | L4: No aplica | M4: Solo se aceptan caracteres de letras de la 'a' a la 'z', caracteres con tilde y numeros del 0 al 9 | N4: No | O4: No | P4: No | Q4: Si | R4: Si | S4: No | T4: Vacio | U4: No | V4: Requerido | W4: No requerido | X4: No modificable | Y4: Mostrar | Z4: No mostrar | AA4: No mostrar
A5: ='M-Cliente'!C3 -> segundoNombre | B5: ='M-Cliente'!C2 -> Representa el segundo nombre de la persona, que va a estar llendo a la barberia para las citas | C5: No | D5: Alfanumérico | E5: No | F5: 2 | G5: 50 | H5: No aplica | I5: No aplica | J5: No aplica | K5: No aplica | L5: No aplica | M5: Solo se aceptan caracteres de letras de la 'a' a la 'z', caracteres con tilde y numeros del 0 al 9 | N5: No | O5: No | P5: No | Q5: Si | R5: Si | S5: No | T5: Vacio | U5: No | V5: No requerido | W5: No requerido | X5: No modificable | Y5: Mostrar | Z5: No mostrar | AA5: No mostrar
A6: ='M-Cliente'!D3 -> primerApellido | B6: ='M-Cliente'!D2 -> Representa el primer apellido de la persona, que va a estar llendo a la barberia para las citas | C6: No | D6: Alfanumérico | E6: Si | F6: 2 | G6: 50 | H6: No aplica | I6: No aplica | J6: No aplica | K6: No aplica | L6: No aplica | M6: Solo se aceptan caracteres de letras de la 'a' a la 'z', caracteres con tilde y numeros del 0 al 9 | N6: No | O6: No | P6: No | Q6: Si | R6: Si | S6: No | T6: Vacio | U6: No | V6: Requerido | W6: No requerido | X6: No modificable | Y6: Mostrar | Z6: No mostrar | AA6: No mostrar
A7: ='M-Cliente'!E3 -> segundoApellido | B7: ='M-Cliente'!E2 -> Representa el segundo apellido de la persona, que va a estar llendo a la barberia para las citas | C7: No | D7: Alfanumérico | E7: No | F7: 2 | G7: 50 | H7: No aplica | I7: No aplica | J7: No aplica | K7: No aplica | L7: No aplica | M7: Solo se aceptan caracteres de letras de la 'a' a la 'z', caracteres con tilde y numeros del 0 al 9 | N7: No | O7: No | P7: No | Q7: Si | R7: Si | S7: No | T7: Vacio | U7: No | V7: No requerido | W7: No requerido | X7: No modificable | Y7: Mostrar | Z7: No mostrar | AA7: No mostrar
A8: ='M-Cliente'!F3 -> prefijoCelular | B8: ='M-Cliente'!F2 -> Representa cual es el prefijo del numero de celular del cliente | C8: No | D8: PrefijoCelular | E8: Si | F8: No aplica | G8: No aplica | H8: No aplica | I8: No aplica | J8: No aplica | K8: No aplica | L8: No aplica | M8: Aplican las reglas del objeto referenciado | N8: No | O8: No aplica | P8: No aplica | Q8: No aplica | R8: No aplica | S8: No | T8: UUID vacio | U8: No | V8: Requerido | W8: Requerido | X8: Modificable | Y8: Mostrar | Z8: No mostrar | AA8: No mostrar
A9: ='M-Cliente'!G3 -> celular | B9: ='M-Cliente'!G2 -> Representa el numero de celular del cliente, es el dato que el barbero necesita en caso de que tenga que contactarse con el | C9: No | D9: Alfanumérico | E9: Si | F9: 6 | G9: 15 | H9: No aplica | I9: No aplica | J9: No aplica | K9: No aplica | L9: No aplica | M9: Solo se aceptan caracteres de numeros del '0' al '9' | N9: No | O9: No aplica | P9: No aplica | Q9: Si | R9: Si | S9: Si | T9: 0 | U9: No | V9: Requerido | W9: Requerido | X9: Modificable | Y9: Mostrar | Z9: No mostrar | AA9: No mostrar
A10: ='M-Cliente'!H3 -> elNumeroCelularEsCorrecto | B10: ='M-Cliente'!H2 -> Representa si el numero que ingreso el cliente es correcto o no | C10: No | D10: Lógico | E10: Si | F10: No aplica | G10: No aplica | H10: No aplica | I10: No aplica | J10: No aplica | K10: No aplica | L10: No aplica | M10: No aplica | N10: No | O10: No aplica | P10: No aplica | Q10: No aplica | R10: No aplica | S10: No | T10: No | U10: No | V10: No requerido | W10: No requerido | X10: Modificable | Y10: Mostrar | Z10: No mostrar | AA10: No mostrar
A11: ='M-Cliente'!I3 -> estaVetado | B11: ='M-Cliente'!I2 -> Representa si el cliente esta en estado de veto o no, cuando el cliente esta vetado el sistema no va a permitir agendar citas con este cliente con ningun barbero | C11: No | D11: Lógico | E11: Si | F11: No aplica | G11: No aplica | H11: No aplica | I11: No aplica | J11: No aplica | K11: No aplica | L11: No aplica | M11: Se calcula a partir de multasSinPagar: basta con una multa sin pagar para que el cliente quede vetado y no pueda agendar; deja de estarlo en el momento en que la paga | N11: Si | O11: No | P11: No aplica | Q11: No aplica | R11: No aplica | S11: No | T11: No | U11: No | V11: No requerido | W11: No requerido | X11: No modificable | Y11: Mostrar | Z11: Mostrar | AA11: No mostrar
A13: Nombre combinación única | B13: Descripción | C13: Atributos involucrados
A14: ='M-Cliente'!J3 -> Combinación única 1 | B14: ='M-Cliente'!J2 -> Combinacion única que indica que no puede existir más de un cliente con el mismo prefijo de celular y número de celular | C14: =A8 -> prefijoCelular
C17: =A9 -> celular
A19: Responsabilidad | C19: Descripción | G19: Entradas | J19: Salida | O19: Políticas (Reglas de Negocio) | Q19: Excepción
G20: Parámetro | H20: Tipo de dato | I20: Descripción | J20: Tipo de Dato | K20: Descripción | O20: Política | P20: Descripción | Q20: Detalle | R20: ¿Qué hago?
A21: registrarCliente | C21: Comando que permite el registro de un nuevo cliente en la barbería | G21: datos{primerNombre, segundoNombre, primerApellido, segundoApellido, prefijoCelular, celular} | H21: Cliente | I21: Contiene la información requerida para registrar un nuevo cliente en la barbería | J21: Cliente | K21: Contiene la información del cliente registrado | O21: ='P-Cliente'!A6 -> P-CLI-0001 | P21: ='P-Cliente'!B6 -> Asegurar que los datos requeridos del cliente (nombres, apellidos, prefijo de celular, celular) sean válidos en tipo de dato, longitud, obligatoriedad, formato y rango | Q21: Generar una excepción indicándole al usuario cuáles datos del cliente no cumplen con las reglas definidas | R21: Detener operación
O22: ='P-Cliente'!A7 -> P-CLI-0002 | P22: ='P-Cliente'!B7 -> Asegurar que el número de celular y prefijo de celular no esté siendo utilizado por otro cliente | Q22: Generar una excepción indicándole al usuario que ya existe otro cliente registrado con ese prefijo y número de celular | R22: Detener operación
A23: editarContactoCliente | C23: Permite al cliente actualizar su número de celular y su prefijo | G23: id | H23: UUID | I23: Corresponde al identificador del cliente que va a editar su contacto | J23: Cliente | K23: Contiene la información del cliente con su contacto actualizado | O23: ='P-Cliente'!A10 -> P-CLI-0005 | P23: ='P-Cliente'!B10 -> Asegurar que exista el cliente con el id enviado | Q23: Informar con un mensaje que no existe un cliente con el identificador enviado y por lo tanto no es posible editar el contacto del cliente | R23: Detener operación
G24: datos{prefijoCelular, celular} | H24: Cliente | I24: Contiene el nuevo prefijo y número de celular del cliente | O24: ='P-Cliente'!A8 -> P-CLI-0003 | P24: ='P-Cliente'!B8 -> Asegurar que los datos requeridos del cliente para editar su contacto (prefijo de celular y celular) sean válidos en tipo de dato, longitud, obligatoriedad, formato y rango | Q24: Generar una excepción indicándole al usuario cuáles datos de contacto del cliente no cumplen con las reglas definidas | R24: Detener operación
A26: consultarDatosCliente | C26: Permite a un barbero ver los datos de un cliente que le va a pedir una cita | G26: id | H26: UUID | I26: Corresponde al identificador del cliente que se va a consultar | J26: Cliente | K26: Contiene la información del cliente consultado por su identificador | O26: ='P-Cliente'!A10 -> P-CLI-0005 | P26: ='P-Cliente'!B10 -> Asegurar que exista el cliente con el id enviado | Q26: Informar con un mensaje que no existe un cliente con el identificador enviado y por lo tanto no es posible llevar a cabo la operación | R26: Detener operación
A27: consultarEstadoVetoCliente | C27: Permite al cliente ver si tiene alguna multa sin pagar que le impida agendar nuevas citas | G27: id | H27: UUID | I27: Corresponde al identificador del cliente que se va a consultar | J27: Lógico | K27: Indica si el cliente está vetado o no para agendar nuevas citas | O27: ='P-Cliente'!A10 -> P-CLI-0005 | P27: ='P-Cliente'!B10 -> Asegurar que exista el cliente con el id enviado | Q27: Informar con un mensaje que no existe un cliente con el identificador enviado y por lo tanto no es posible llevar a cabo la operación | R27: Detener operación
A28: consultarCantidadMultasSinPagar | C28: Permite al cliente ver cuántas multas sin pagar tiene | G28: id | H28: UUID | I28: Corresponde al identificador del cliente que se va a consultar | J28: Entero | K28: Contiene la cantidad de multas sin pagar que tiene el cliente | O28: ='P-Cliente'!A10 -> P-CLI-0005 | P28: ='P-Cliente'!B10 -> Asegurar que exista el cliente con el id enviado | Q28: Informar con un mensaje que no existe un cliente con el identificador enviado y por lo tanto no es posible llevar a cabo la operación | R28: Detener operación

Sheet P-Cliente
A1: << Ir al modelo de dominio | B1: << Ir al listado de objetos de dominio | C1: << Ir a la caracterización del objeto de dominio | D1: Ir al muestreo de datos del objeto de dominio >> | E1: Ir al event storming del objeto de dominio >>
A2: Objeto de Dominio: | B2: ='Objetos de Dominio'!A9 -> Cliente
A3: Descripción: | B3: ='Objetos de Dominio'!B9 -> Representa a la persona que solicita citas en la barbería.
A4: Numero politica | B4: Descripcion politica | D4: Objeto responsable | E4: Regla responsable
A6: P-CLI-0001 | B6: Asegurar que los datos requeridos del cliente (nombres, apellidos, prefijo de celular, celular) sean válidos en tipo de dato, longitud, obligatoriedad, formato y rango | D6: Cliente
A7: P-CLI-0002 | B7: Asegurar que el número de celular y prefijo de celular no esté siendo utilizado por otro cliente | D7: Cliente
A8: P-CLI-0003 | B8: Asegurar que los datos requeridos del cliente para editar su contacto (prefijo de celular y celular) sean válidos en tipo de dato, longitud, obligatoriedad, formato y rango | D8: Cliente
A9: P-CLI-0004 | B9: Asegurar que el cliente no tenga ninguna multa sin pagar antes de permitirle agendar una cita nueva; mientras la tenga permanece vetado | D9: Multa
A10: P-CLI-0005 | B10: Asegurar que exista el cliente con el id enviado | D10: Cliente

Sheet E-Cliente
A1: << Ir al modelo de dominio | C1: << Ir al listado de objetos de dominio | F1: << Ir a la caracterización del objeto de dominio | J1: Ir al muestreo de datos del objeto de dominio >>
A2: Objeto de Dominio: | B2: ='Objetos de Dominio'!A9 -> Cliente
A3: Descripción: | B3: ='Objetos de Dominio'!B9 -> Representa a la persona que solicita citas en la barbería.
A4: Actor | B4: Action/Command | D4: Entity/Aggregate/Object domain | E4: Read Model | G4: Business Rule/Policy | I4: External System | J4: Domain Event | K4: Hotspot/questions/Risk
A5: Actor | B5: Acción | C5: Descripción | D5: Objeto de dominio | E5: Información externa | G5: Políticas | I5: Sistema Externo | J5: Evento | K5: Aspectos por solucionar
E6: Información | F6: Descripción | G6: Número | H6: Descripción
A7: Cliente | B7: Registrar cliente a la barbería | C7: Comando que permite el registro de un nuevo cliente en la barbería | D7: =$B$2 -> Cliente | E7: PrefijoCelular | F7: Permite asignar el prefijo de país del número de celular del cliente. | G7: ='P-Cliente'!A6 -> P-CLI-0001 | H7: ='P-Cliente'!B6 -> Asegurar que los datos requeridos del cliente (nombres, apellidos, prefijo de celular, celular) sean válidos en tipo de dato, longitud, obligatoriedad, formato y rango | J7: Cliente registrado
G8: ='P-Cliente'!A7 -> P-CLI-0002 | H8: ='P-Cliente'!B7 -> Asegurar que el número de celular y prefijo de celular no esté siendo utilizado por otro cliente
A9: Cliente | B9: Editar contacto | C9: Permite al cliente actualizar su número de celular y su prefijo | D9: =$B$2 -> Cliente | E9: PrefijoCelular | F9: Permite actualizar el prefijo de país del número de celular. | G9: ='P-Cliente'!A8 -> P-CLI-0003 | H9: ='P-Cliente'!B8 -> Asegurar que los datos requeridos del cliente para editar su contacto (prefijo de celular y celular) sean válidos en tipo de dato, longitud, obligatoriedad, formato y rango | J9: Contacto de cliente actualizado
A10: Barbero | B10: Ver datos de un cliente | C10: Permite a un barbero ver los datos de un cliente que le va a pedir una cita | D10: =$B$2 -> Cliente | E10: PrefijoCelular | F10: Permite mostrar el número de celular completo con su prefijo. | J10: Datos del cliente vistos
A11: Cliente | B11: Ver estado de vetado | C11: Permite al cliente ver si tiene alguna multa sin pagar que le impida agendar nuevas citas | D11: =$B$2 -> Cliente | J11: Estado de veto del cliente visto
A12: Cliente | B12: Ver cantidad de multas sin pagar | C12: Permite al cliente ver cuántas multas sin pagar tiene | D12: =$B$2 -> Cliente | E12: Multa | F12: Permite contar las multas del cliente que siguen sin pagar. | J12: Multas sin pagar del cliente vistas
A13: Sistema | B13: Dar veto a un cliente | C13: Permite al sistema vetar a un cliente | D13: Cliente | E13: Multa | F13: Permite conocer si el cliente tiene multas sin pagar. | J13: Cliente vetado

Sheet M-Cliente
A1: <<<< Ir al modulo de dominio | B1: <<<< Ir a objetos de dominio
A2: Representa un identificador que hará unico cada objeto de dominio de este tipo, no se puede repetir | B2: Representa el primer nombre de la persona, que va a estar llendo a la barberia para las citas | C2: Representa el segundo nombre de la persona, que va a estar llendo a la barberia para las citas | D2: Representa el primer apellido de la persona, que va a estar llendo a la barberia para las citas | E2: Representa el segundo apellido de la persona, que va a estar llendo a la barberia para las citas | F2: Representa cual es el prefijo del numero de celular del cliente | G2: Representa el numero de celular del cliente, es el dato que el barbero necesita en caso de que tenga que contactarse con el | H2: Representa si el numero que ingreso el cliente es correcto o no | I2: Representa si el cliente esta en estado de veto o no, cuando el cliente esta vetado el sistema no va a permitir agendar citas con este cliente con ningun barbero | J2: Combinacion única que indica que no puede existir más de un cliente con el mismo prefijo de celular y número de celular
A3: id | B3: primerNombre | C3: segundoNombre | D3: primerApellido | E3: segundoApellido | F3: prefijoCelular | G3: celular | H3: elNumeroCelularEsCorrecto | I3: estaVetado | J3: Combinación única 1
A4: 1 | B4: Juan | D4: Gómez | F4: ='M-PrefijoCelular'!C4 -> +57 | G4: 3234528921 | H4: Si | I4: no | J4: =_xlfn.CONCAT(F4,"-",G4) -> +57-3234528921
A5: 2 | B5: Jose | C5: Miguel | D5: Ramirez | E5: Perez | F5: ='M-PrefijoCelular'!C4 -> +57 | G5: 3161657782 | H5: Si | I5: no | J5: =_xlfn.CONCAT(F5,"-",G5) -> +57-3161657782
A6: 3 | B6: Simon | D6: Ochoa | E6: Ramirez | F6: ='M-PrefijoCelular'!C4 -> +57 | G6: 3119884321 | H6: Si | I6: no | J6: =_xlfn.CONCAT(F6,"-",G6) -> +57-3119884321
A7: 4 | B7: Alexis | D7: Gallego | F7: ='M-PrefijoCelular'!C7 -> +58 | G7: 4127359182 | H7: Si | I7: no | J7: =_xlfn.CONCAT(F7,"-",G7) -> +58-4127359182
A8: 5 | B8: Kevin | C8: Andrés | D8: Muñoz | E8: Salazar | F8: ='M-PrefijoCelular'!C4 -> +57 | G8: 3005544332 | H8: Si | I8: si | J8: =_xlfn.CONCAT(F8,"-",G8) -> +57-3005544332
B14: Corresponde a la descripcion de los atributos
B15: Corresponde al identificador unico del objeto de dominio
B16: Corresponde a las referencias de otros objetos de dominio
B17: Corresponde a los datos calculados por el sistema
B18: Corresponde a los datos que ingresa el usuario
B19: Corresponde a la combinacion única

Sheet C-HorarioBarberia
A1: <<<< Ir al modulo de dominio | B1: <<<< Ir a objetos de dominio
A2: Nombre atributo | B2: Descripción atributo | C2: Identificador del objeto de dominio | D2: Tipo de dato | E2: Obligatorio | F2: Longitud mínima (si aplica) | G2: Longitud máxima (si aplica) | H2: Precisión (si aplica) | I2: Rendondeo (si aplica) | J2: Rango inicial (si aplica) | K2: Rango final (si aplica) | L2: Formato (si aplica) | M2: Reglas especiales (si aplica) | N2: Dato calculado | O2: Aplica ajuste del dato (si aplica) | P2: Carácter de ajuste (si aplica) | Q2: Quitar espacios en blanco al inicio (si aplica) | R2: Quitar espacios en blanco al fin (si aplica) | S2: Dato sensible (si aplica) | T2: Valor por defecto (si aplica) | U2: Auto generado | V2: =A21 -> definirHorarioBarberia | W2: =A24 -> consultarHorariosBarberia | X2: =A25 -> desactivarHorarioBarberia
A3: ='M-HorarioBarberia'!A3 -> id | B3: ='M-HorarioBarberia'!A2 -> Representa un identificador que hará unico cada objeto de dominio de este tipo, no se puede repetir | C3: Si | D3: Identificador único universal | E3: Si | F3: No aplica | G3: No aplica | H3: No aplica | I3: No aplica | J3: No aplica | K3: No aplica | L3: No aplica | M3: No aplica | N3: No | O3: No | P3: No aplica | Q3: No aplica | R3: No aplica | S3: No | T3: UUID vacio | U3: Si | V3: No requerido | W3: No mostrar | X3: Requerido
A4: ='M-HorarioBarberia'!B3 -> diaDeLaSemana | B4: ='M-HorarioBarberia'!B2 -> Representa el día de la semana en el que la barberia abre | C4: No | D4: DiaSemana | E4: Si | F4: No aplica | G4: No aplica | H4: No aplica | I4: No aplica | J4: No aplica | K4: No aplica | L4: No aplica | M4: Aplican las reglas del objeto referenciado | N4: No | O4: No | P4: No aplica | Q4: No aplica | R4: No aplica | S4: No | T4: UUID vacio | U4: No | V4: Requerido | W4: Mostrar | X4: No requerido
A5: ='M-HorarioBarberia'!C3 -> horaApertura | B5: ='M-HorarioBarberia'!C2 -> Representa la hora a la que abre la barbería | C5: No | D5: Hora | E5: Si | F5: No aplica | G5: No aplica | H5: No aplica | I5: No aplica | J5: No aplica | K5: No aplica | L5: No aplica | M5: No aplica | N5: No | O5: No | P5: No aplica | Q5: No aplica | R5: No aplica | S5: No | T5: 00:00 | U5: No | V5: Requerido | W5: Mostrar | X5: No requerido
A6: ='M-HorarioBarberia'!D3 -> horaCierre | B6: ='M-HorarioBarberia'!D2 -> Representa la hora a la que cierra la barbería | C6: No | D6: Hora | E6: Si | F6: No aplica | G6: No aplica | H6: No aplica | I6: No aplica | J6: No aplica | K6: No aplica | L6: No aplica | M6: Debe ser mayor a horaApertura | N6: No | O6: No | P6: No aplica | Q6: No aplica | R6: No aplica | S6: No | T6: 00:00 | U6: No | V6: Requerido | W6: Mostrar | X6: No requerido
A7: ='M-HorarioBarberia'!E3 -> fechaCreacion | B7: ='M-HorarioBarberia'!E2 -> Representa la fecha en el que el dueño definio el horario de la barberia. Es un dato calculado que toma la fecha del sistema en ese momento | C7: No | D7: Fecha | E7: Si | F7: No aplica | G7: No aplica | H7: No aplica | I7: No aplica | J7: No aplica | K7: No aplica | L7: No aplica | M7: No aplica | N7: No | O7: No | P7: No aplica | Q7: No aplica | R7: No aplica | S7: No | T7: 1/01/1000 | U7: Si | V7: No requerido | W7: No mostrar | X7: No requerido
A8: ='M-HorarioBarberia'!F3 -> fechaDesactivacion | B8: ='M-HorarioBarberia'!F2 -> Representa la fecha en la que este horario dejó de estar vigente, dueño. Es un dato calculado que toma la fecha del sistema en ese momento | C8: No | D8: Fecha | E8: No | F8: No aplica | G8: No aplica | H8: No aplica | I8: No aplica | J8: No aplica | K8: No aplica | L8: No aplica | M8: No aplica | N8: No | O8: No | P8: No aplica | Q8: No aplica | R8: No aplica | S8: No | T8: 1/01/1000 | U8: Si | V8: No requerido | W8: No mostrar | X8: No requerido
A9: ='M-HorarioBarberia'!G3 -> vigente | B9: ='M-HorarioBarberia'!G2 -> Representa si este horario lo sigue o no vigente en la barberia. Una vez que el dueño desactive el horario de la barberia, no se puede volver a cambiar | C9: No | D9: Lógico | E9: Si | F9: No aplica | G9: No aplica | H9: No aplica | I9: No aplica | J9: No aplica | K9: No aplica | L9: No aplica | M9: Una vez que vigente se ponga como no, no se puede volver a cambiar | N9: No | O9: No | P9: No aplica | Q9: No aplica | R9: No aplica | S9: No | T9: Si | U9: Si | V9: No requerido | W9: No mostrar | X9: No requerido
A11: Nombre combinación única | B11: Descripción | C11: Atributos involucrados
A12: ='M-HorarioBarberia'!H3 -> Combinación única | B12: Combinación única que indica que, entre los horarios vigentes, no puede existir más de un horario de la barbería para el mismo día de la semana con la misma hora de apertura y la misma hora de cierre | C12: =A4 -> diaDeLaSemana
C13: =A5 -> horaApertura
C14: =A6 -> horaCierre
C15: =A7 -> fechaCreacion
C16: =A8 -> fechaDesactivacion
A19: Responsabilidad | C19: Descripción | G19: Entradas | J19: Salida | O19: Políticas (Reglas de Negocio) | Q19: Excepción
G20: Parámetro | H20: Tipo de dato | I20: Descripción | J20: Tipo de Dato | K20: Descripción | O20: Política | P20: Descripción | Q20: Detalle | R20: ¿Qué hago?
A21: definirHorarioBarberia | C21: Comando que permite registrar la hora de apertura y cierre de la barbería para un día de la semana | G21: datos{diaDeLaSemana, horaApertura, horaCierre} | H21: HorarioBarberia | I21: Contiene la información requerida para registrar el horario de la barbería para un día | J21: HorarioBarberia | K21: Contiene la información del horario de la barbería registrado | O21: ='P-HorarioBarberia'!A6 -> P-HBA-0001 | P21: ='P-HorarioBarberia'!B6 -> Asegurar que los datos requeridos (día de la semana, hora de apertura, hora de cierre) sean válidos en tipo de dato, obligatoriedad, formato y rango | Q21: Generar una excepción indicándole al dueño que los datos no cumplen con las reglas definidas | R21: Detener operación
O22: ='P-HorarioBarberia'!A7 -> P-HBA-0002 | P22: ='P-HorarioBarberia'!B7 -> Asegurar que no exista otro horario vigente definido para el mismo día de la semana, que se cruze con las horas de apertura y cierre | Q22: Generar una excepción indicándole al dueño que ya existe un horario vigente para ese día que se cruza con las horas indicadas | R22: Detener operación
O23: ='P-HorarioBarberia'!A12 -> P-HBA-0007 | P23: ='P-HorarioBarberia'!B12 -> Asegurar que el horario de la barbería que se va a desactivar se encuentre vigente | Q23: Generar una excepción indicandole al dueño que la hora de cierre debe de ser mayor a la hora de apertura | R23: Detener operación
A24: consultarHorariosBarberia | C24: Permite al dueño consultar los horarios de apertura y cierre definidos para cada día de la semana | J24: Lista<HorarioBarberia> | K24: Contiene todos los horarios de la barbería vigentes
A25: desactivarHorarioBarberia | C25: Permite desactivar el horario en el que la barberia ya no abrira | G25: id | H25: UUID | I25: Corresponde al identificador del horario de la barbería que se va a desactivar | J25: No retorna ningún valor. En caso de error genera una excepción. | O25: P-HBA-0003 | P25: Asegurar que queden desactivados todos los horarios de barbero que dependen del horario de la barbería que se está desactivando | Q25: Si alguno de los horarios de barbero no pudo ser desactivado, revertir toda la operación e informar el error | R25: Detener operación
O26: ='P-HorarioBarberia'!A9 -> P-HBA-0004 | P26: ='P-HorarioBarberia'!B9 -> Asegurar que queden canceladas, en el estado Cancelación por cambio de políticas de la barbería, todas las citas futuras asociadas a las agendas de los horarios de barbero desactivados. Se consideran futuras las citas cuya agenda tenga una fecha posterior a la fecha actual | Q26: Si alguna de las citas futuras no pudo ser cancelada, revertir toda la operación e informar el error | R26: Detener operación
O27: ='P-HorarioBarberia'!A10 -> P-HBA-0005 | P27: ='P-HorarioBarberia'!B10 -> Asegurar que exista el horario de la barbería con el id enviado | Q27: Informar con un mensaje que no existe un horario de la barbería con el identificador enviado y por lo tanto no es posible llevar a cabo la operación | R27: Detener operación
O28: ='P-HorarioBarberia'!A12 -> P-HBA-0007 | P28: ='P-HorarioBarberia'!B12 -> Asegurar que el horario de la barbería que se va a desactivar se encuentre vigente | Q28: Informar con un mensaje que ese horario de la barbería ya se encuentra desactivado y por lo tanto no puede volver a desactivarse | R28: Detener operación

Sheet P-HorarioBarberia
A1: << Ir al modelo de dominio | B1: << Ir al listado de objetos de dominio | C1: << Ir a la caracterización del objeto de dominio | D1: Ir al muestreo de datos del objeto de dominio >> | E1: Ir al event storming del objeto de dominio >>
A2: Objeto de Dominio: | B2: ='Objetos de Dominio'!A10 -> HorarioBarberia
A3: Descripción: | B3: ='Objetos de Dominio'!B10 -> Representa, día por día, a qué hora abre y cierra el negocio; es el límite dentro del cual debe caber el horario de cualquier barbero.
A4: Numero politica | B4: Descripcion politica | D4: Objeto responsable | E4: Regla responsable
A6: P-HBA-0001 | B6: Asegurar que los datos requeridos (día de la semana, hora de apertura, hora de cierre) sean válidos en tipo de dato, obligatoriedad, formato y rango | D6: HorarioBarberia
A7: P-HBA-0002 | B7: Asegurar que no exista otro horario vigente definido para el mismo día de la semana, que se cruze con las horas de apertura y cierre | D7: HorarioBarberia
A8: P-HBA-0003 | B8: Asegurar que queden desactivados todos los horarios de barbero que dependen del horario de la barbería que se está desactivando | D8: HorarioBarbero
A9: P-HBA-0004 | B9: Asegurar que queden canceladas, en el estado Cancelación por cambio de políticas de la barbería, todas las citas futuras asociadas a las agendas de los horarios de barbero desactivados. Se consideran futuras las citas cuya agenda tenga una fecha posterior a la fecha actual | D9: Cita
A10: P-HBA-0005 | B10: Asegurar que exista el horario de la barbería con el id enviado | D10: HorarioBarberia
A11: P-HBA-0006 | B11: Asegurar que la hora de cierre sea mayor a la hora de apertura | D11: HorarioBarberia
A12: P-HBA-0007 | B12: Asegurar que el horario de la barbería que se va a desactivar se encuentre vigente | D12: HorarioBarberia

Sheet E-HorarioBarberia
A1: << Ir al modelo de dominio | C1: << Ir al listado de objetos de dominio | F1: << Ir a la caracterización del objeto de dominio | J1: Ir al muestreo de datos del objeto de dominio >>
A2: Objeto de Dominio: | B2: ='Objetos de Dominio'!A10 -> HorarioBarberia
A3: Descripción: | B3: ='Objetos de Dominio'!B10 -> Representa, día por día, a qué hora abre y cierra el negocio; es el límite dentro del cual debe caber el horario de cualquier barbero.
A4: Actor | B4: Action/Command | D4: Entity/Aggregate/Object domain | E4: Read Model | G4: Business Rule/Policy | I4: External System | J4: Domain Event | K4: Hotspot/questions/Risk
A5: Actor | B5: Acción | C5: Descripción | D5: Objeto de dominio | E5: Información externa | G5: Políticas | I5: Sistema Externo | J5: Evento | K5: Aspectos por solucionar
E6: Información | F6: Descripción | G6: Número | H6: Descripción
A7: Dueño | B7: Definir un horario de la barbería | C7: Comando que permite registrar la hora de apertura y cierre de la barbería para un día de la semana | D7: =$B$2 -> HorarioBarberia | G7: ='P-HorarioBarberia'!A6 -> P-HBA-0001 | H7: ='P-HorarioBarberia'!B6 -> Asegurar que los datos requeridos (día de la semana, hora de apertura, hora de cierre) sean válidos en tipo de dato, obligatoriedad, formato y rango | J7: Horario de barbería definido
G8: ='P-HorarioBarberia'!A7 -> P-HBA-0002 | H8: ='P-HorarioBarberia'!B7 -> Asegurar que no exista otro horario vigente definido para el mismo día de la semana, que se cruze con las horas de apertura y cierre
G9: ='P-HorarioBarberia'!A11 -> P-HBA-0006 | H9: ='P-HorarioBarberia'!B11 -> Asegurar que la hora de cierre sea mayor a la hora de apertura
A10: Dueño | B10: Ver horarios de la barbería | C10: Permite al dueño consultar los horarios de apertura y cierre definidos para cada día de la semana | D10: =$B$2 -> HorarioBarberia | J10: Horarios de barbería consultados
A11: Barbero | B11: Ver horarios de la barbería | C11: Permite al barbero consultar los horarios de apertura y cierre definidos para cada día de la semana | D11: =$B$2 -> HorarioBarberia | J11: Horarios de barbería consultados
A12: Cliente | B12: Ver horarios de la barbería | C12: Permite al cliente consultar los horarios de apertura y cierre definidos para cada día de la semana | D12: =$B$2 -> HorarioBarberia | J12: Horarios de barbería consultados
A13: Dueño | B13: Desactivar horario de barbería | C13: Permite desactivar el horario en el que la barberia ya no abrira | D13: =$B$2 -> HorarioBarberia | E13: HorarioBarbero | F13: Permite identificar los horarios de barbero que dependen de ese día para desactivarlos. | G13: P-HBA-0003 | H13: Asegurar que queden desactivados todos los horarios de barbero que dependen del horario de la barbería que se está desactivando | J13: Horario de barbería desactivado
E14: Agenda | F14: Permite identificar las citas futuras que quedaron en las agendas de los horarios de barbero desactivados. La agenda no se modifica: solo se recorre para llegar a las citas. | G14: P-HBA-0005 | H14: Asegurar que queden canceladas, en el estado Cancelación por cambio de políticas de la barbería, todas las citas futuras asociadas a las agendas de los horarios de barbero desactivados. Se consideran futuras las citas cuya agenda tenga una fecha posterior a la fecha actual
E15: Cita | F15: Permite identificar las citas futuras que se deben cancelar.
E16: Estado | F16: Permite dejar esas citas en el estado Cancelación. | G16: ='P-HorarioBarberia'!A12 -> P-HBA-0007 | H16: ='P-HorarioBarberia'!B12 -> Asegurar que el horario de la barbería que se va a desactivar se encuentre vigente

Sheet M-HorarioBarberia
A1: <<<< Ir al modulo de dominio | B1: <<<< Ir a objetos de dominio
A2: Representa un identificador que hará unico cada objeto de dominio de este tipo, no se puede repetir | B2: Representa el día de la semana en el que la barberia abre | C2: Representa la hora a la que abre la barbería | D2: Representa la hora a la que cierra la barbería | E2: Representa la fecha en el que el dueño definio el horario de la barberia. Es un dato calculado que toma la fecha del sistema en ese momento | F2: Representa la fecha en la que este horario dejó de estar vigente, dueño. Es un dato calculado que toma la fecha del sistema en ese momento | G2: Representa si este horario lo sigue o no vigente en la barberia. Una vez que el dueño desactive el horario de la barberia, no se puede volver a cambiar | H2: Combinación única que indica que, entre los horarios vigentes, no puede existir más de un horario de la barbería para el mismo día de la semana con la misma hora de apertura, la misma hora de cierre, fecha de creacion y fecha de desactivacion
A3: id | B3: diaDeLaSemana | C3: horaApertura | D3: horaCierre | E3: fechaCreacion | F3: fechaDesactivacion | G3: vigente | H3: Combinación única
A4: 1 | B4: ='M-DiaSemana'!C4 -> Lunes | C4: 0.375 | D4: 0.79166667 | E4: 45242 | F4: 1/01/1000 | G4: Si | H4: =_xlfn.CONCAT(B4,"-",TEXT(C4,"hh:mm"),"-",TEXT(D4,"hh:mm"),"-",TEXT(E4,"dd/mm/yyyy"),"-",TEXT(F4,"dd/mm/yyyy")) -> Lunes-09:00-19:00-12/11/2023-1/01/1000
A5: 2 | B5: ='M-DiaSemana'!C5 -> Martes | C5: 0.375 | D5: 0.79166667 | E5: 45242 | F5: 1/01/1000 | G5: Si | H5: =_xlfn.CONCAT(B5,"-",TEXT(C5,"hh:mm"),"-",TEXT(D5,"hh:mm"),"-",TEXT(E5,"dd/mm/yyyy"),"-",TEXT(F5,"dd/mm/yyyy")) -> Martes-09:00-19:00-12/11/2023-1/01/1000
A6: 3 | B6: ='M-DiaSemana'!C6 -> Miércoles | C6: 0.375 | D6: 0.79166667 | E6: 45242 | F6: 1/01/1000 | G6: Si | H6: =_xlfn.CONCAT(B6,"-",TEXT(C6,"hh:mm"),"-",TEXT(D6,"hh:mm"),"-",TEXT(E6,"dd/mm/yyyy"),"-",TEXT(F6,"dd/mm/yyyy")) -> Miércoles-09:00-19:00-12/11/2023-1/01/1000
A7: 4 | B7: ='M-DiaSemana'!C7 -> Jueves | C7: 0.375 | D7: 0.79166667 | E7: 45242 | F7: 1/01/1000 | G7: Si | H7: =_xlfn.CONCAT(B7,"-",TEXT(C7,"hh:mm"),"-",TEXT(D7,"hh:mm"),"-",TEXT(E7,"dd/mm/yyyy"),"-",TEXT(F7,"dd/mm/yyyy")) -> Jueves-09:00-19:00-12/11/2023-1/01/1000
A8: 5 | B8: ='M-DiaSemana'!C8 -> Viernes | C8: 0.375 | D8: 0.79166667 | E8: 45242 | F8: 1/01/1000 | G8: Si | H8: =_xlfn.CONCAT(B8,"-",TEXT(C8,"hh:mm"),"-",TEXT(D8,"hh:mm"),"-",TEXT(E8,"dd/mm/yyyy"),"-",TEXT(F8,"dd/mm/yyyy")) -> Viernes-09:00-19:00-12/11/2023-1/01/1000
A9: 6 | B9: ='M-DiaSemana'!C9 -> Sábado | C9: 0.33333333 | D9: 0.875 | E9: 45638 | F9: 1/01/1000 | G9: Si | H9: =_xlfn.CONCAT(B9,"-",TEXT(C9,"hh:mm"),"-",TEXT(D9,"hh:mm"),"-",TEXT(E9,"dd/mm/yyyy"),"-",TEXT(F9,"dd/mm/yyyy")) -> Sábado-08:00-21:00-12/12/2024-1/01/1000
A10: 7 | B10: ='M-DiaSemana'!C11 -> Festivo | C10: 0.41666667 | D10: 0.625 | E10: 45638 | F10: 1/01/1000 | G10: Si | H10: =_xlfn.CONCAT(B10,"-",TEXT(C10,"hh:mm"),"-",TEXT(D10,"hh:mm"),"-",TEXT(E10,"dd/mm/yyyy"),"-",TEXT(F10,"dd/mm/yyyy")) -> Festivo-10:00-15:00-12/12/2024-1/01/1000
B16: Corresponde a la descripcion de los atributos
B17: Corresponde al identificador unico del objeto de dominio
B18: Corresponde a las referencias de otros objetos de dominio
B19: Corresponde a los datos auto generados por el sistema
B20: Corresponde a los datos que ingresa el usuario
B21: Corresponde a la combinacion única

Sheet C-Bloqueo
A1: <<<< Ir al modulo de dominio | B1: <<<< Ir a objetos de dominio
A2: Nombre atributo | B2: Descripción atributo | C2: Identificador del objeto de dominio | D2: Tipo de dato | E2: Obligatorio | F2: Longitud mínima (si aplica) | G2: Longitud máxima (si aplica) | H2: Precisión (si aplica) | I2: Rendondeo (si aplica) | J2: Rango inicial (si aplica) | K2: Rango final (si aplica) | L2: Formato (si aplica) | M2: Reglas especiales (si aplica) | N2: Dato calculado | O2: Aplica ajuste del dato (si aplica) | P2: Carácter de ajuste (si aplica) | Q2: Quitar espacios en blanco al inicio (si aplica) | R2: Quitar espacios en blanco al fin (si aplica) | S2: Dato sensible (si aplica) | T2: Valor por defecto (si aplica) | U2: Auto generado | V2: =A15 -> definirBloqueo | W2: =A19 -> eliminarBloqueo | X2: =A21 -> consultarBloqueosPorFecha | Y2: =A22 -> consultarBloqueoPorFechaHora | Z2: =A23 -> editarBloqueo
A3: ='M-Bloqueo'!A3 -> id | B3: ='M-Bloqueo'!A2 -> Representa un identificador que hará unico cada objeto de dominio de este tipo, no se puede repetir | C3: Si | D3: Identificador único universal | E3: Si | F3: No aplica | G3: No aplica | H3: No aplica | I3: No aplica | J3: No aplica | K3: No aplica | L3: No aplica | M3: No aplica | N3: No | O3: No | P3: No aplica | Q3: No | R3: No | S3: No | T3: UUID vacio | U3: Si | V3: No requerido | W3: Requerido | X3: No mostrar | Y3: No mostrar | Z3: Requerido | AA3: No modificable
A4: ='M-Bloqueo'!B3 -> barbero | B4: ='M-Bloqueo'!B2 -> Referencia a qué barbero le pertence este bloqueo | C4: No | D4: Barbero | E4: Si | F4: No aplica | G4: No aplica | H4: No aplica | I4: No aplica | J4: No aplica | K4: No aplica | L4: No aplica | M4: Aplican las reglas del objeto referenciado | N4: No | O4: No aplica | P4: No aplica | Q4: No aplica | R4: No aplica | S4: No | T4: UUID vacio | U4: No | V4: Requerido | W4: No requerido | X4: No mostrar | Y4: No mostrar | Z4: No requerido | AA4: No modificable
A5: ='M-Bloqueo'!C3 -> fechaHoraInicio | B5: ='M-Bloqueo'!C2 -> Representa la fecha y hora en el que el barbero empieza a no estar disponible para atender las citas | C5: No | D5: Fecha hora | E5: Si | F5: No aplica | G5: No aplica | H5: No aplica | I5: No aplica | J5: No aplica | K5: No aplica | L5: No aplica | M5: No aplica | N5: No | O5: No aplica | P5: No aplica | Q5: No aplica | R5: No aplica | S5: No | T5: 01/01/1000 00:00 | U5: No | V5: Requerido | W5: No requerido | X5: Mostrar | Y5: Mostrar | Z5: Requerido | AA5: Modificable
A6: ='M-Bloqueo'!D3 -> fechaHoraFinal | B6: ='M-Bloqueo'!D2 -> Representa la fecha y hora en el que el barbero empieza estar disponible nuevamente para atender las citas | C6: No | D6: Fecha hora | E6: Si | F6: No aplica | G6: No aplica | H6: No aplica | I6: No aplica | J6: No aplica | K6: No aplica | L6: No aplica | M6: Debe ser posterior a fechaHoraInicio | N6: No | O6: No aplica | P6: No aplica | Q6: No aplica | R6: No aplica | S6: No | T6: 01/01/1000 00:00 | U6: No | V6: Requerido | W6: No requerido | X6: Mostrar | Y6: Mostrar | Z6: Requerido | AA6: Modificable
A8: Nombre combinación única | B8: Descripción | C8: Atributos involucrados
A9: ='M-Bloqueo'!E3 -> Combinación única | B9: ='M-Bloqueo'!E2 -> Combinación única que indica que un mismo barbero no puede tener dos bloqueos con la misma fecha y hora de inicio y la misma fecha y hora final | C9: =A4 -> barbero
C10: =A5 -> fechaHoraInicio
C11: =A6 -> fechaHoraFinal
A13: Responsabilidad | C13: Descripción | G13: Entradas | J13: Salida | O13: Políticas (Reglas de Negocio) | Q13: Excepción
G14: Parámetro | H14: Tipo de dato | I14: Descripción | J14: Tipo de Dato | K14: Descripción | O14: Política | P14: Descripción | Q14: Detalle | R14: ¿Qué hago?
A15: definirBloqueo | C15: Comando que permite a un barbero asignar un espacio de no disponibilidad para atender sus citas | G15: datos{barbero, fechaHoraInicio, fechaHoraFinal} | H15: Bloqueo | I15: Contiene la información requerida para registrar un nuevo bloqueo del barbero | J15: Bloqueo | K15: Contiene la información del bloqueo registrado | O15: ='P-Bloqueo'!A6 -> P-BLO-0001 | P15: ='P-Bloqueo'!B6 -> Asegurar que los datos requeridos (fecha y hora de inicio, fecha y hora de fin) sean válidos en tipo de dato, obligatoriedad, formato y rango | Q15: Generar una excepción indicándole al barbero que los datos no cumplen los datos requeridos | R15: Detener operación
O16: ='P-Bloqueo'!A7 -> P-BLO-0002 | P16: ='P-Bloqueo'!B7 -> Rechazar el bloqueo si ya existen citas agendadas dentro de ese mismo rango elegido | Q16: Generar una excepción indicándole al barbero que ese rango no se puede bloquear porque ya tiene citas agendadas | R16: Detener operación
O17: ='P-Bloqueo'!A10 -> P-BLO-0005 | P17: ='P-Bloqueo'!B10 -> Asegurar que el bloqueo no se cruze con otro bloqueo suyo | Q17: Generar una excepción indicándole al barbero que el rango se solapa con otro bloqueo suyo | R17: Detener operación
O18: ='P-Bloqueo'!A12 -> P-BLO-0007 | P18: ='P-Bloqueo'!B12 -> Asegurar que la fecha y hora de fin sea mayor a la fecha y hora de inicio | Q18: Generar una excepción indicandole al barbero que la fecha y hora de fin debe de ser mayor a la fecha y hora de inicio | R18: Detener operación
A19: eliminarBloqueo | C19: Permite a un barbero liberar un espacio de su agenda que había bloqueado previamente | G19: id | H19: UUID | I19: Corresponde al identificador del bloqueo que se va a eliminar | J19: No retorna ningún valor. En caso de error genera una excepción. | O19: ='P-Bloqueo'!A9 -> P-BLO-0004 | P19: ='P-Bloqueo'!B9 -> Asegurar que el bloqueo que se va a editar o eliminar le pertenezca al mismo barbero que hace la solicitud | Q19: Generar una excepción indicándole al usuario que el bloqueo no le pertenece | R19: Detener operación
O20: ='P-Bloqueo'!A11 -> P-BLO-0006 | P20: ='P-Bloqueo'!B11 -> Asegurar que exista el bloqueo con el id enviado | Q20: Informar con un mensaje que no existe un bloqueo con el identificador enviado y por lo tanto no es posible llevar a cabo la operación | R20: Detener operación
A21: consultarBloqueosPorFecha | C21: Permite a un barbero ver los espacios que tiene bloqueados en una fecha dada | G21: filtro{barbero, fecha} | H21: Bloqueo | I21: Contiene el barbero y la fecha por los cuales se van a consultar los bloqueos | J21: Lista<Bloqueo> | K21: Contiene todos los bloqueos del barbero en esa fecha
A22: consultarBloqueoPorFechaHora | C22: Permite al sistema ver si hay o no un bloqueo en una fecha y hora, en el que empieza el bloqueo, para que el determine luego si el cliente puede agenda una cita en ese momento | G22: filtro{barbero, fechaHoraInicio} | H22: Bloqueo | I22: Contiene el barbero y la fecha y hora por las cuales se va a consultar el bloqueo | J22: Bloqueo | K22: Contiene el bloqueo que cubre esa fecha y hora, si existe
A23: editarBloqueo | C23: Permite al barbero poder editar la fecha y hora en que inicia o termina | G23: id | H23: UUID | I23: Corresponde al identificador del bloqueo que se va a editar | J23: Bloqueo | K23: Contiene la información del bloqueo con su rango actualizado | O23: ='P-Bloqueo'!A11 -> P-BLO-0006 | P23: ='P-Bloqueo'!B11 -> Asegurar que exista el bloqueo con el id enviado | Q23: Informar con un mensaje que no existe un bloqueo con el identificador enviado y por lo tanto no es posible llevar a cabo la operación | R23: Detener operación
G24: datos{fechaHoraInicio, fechaHoraFinal} | H24: Bloqueo | I24: Contiene el nuevo rango con el que se va a modificar el bloqueo | O24: ='P-Bloqueo'!A8 -> P-BLO-0003 | P24: ='P-Bloqueo'!B8 -> Asegurar que los datos requeridos para editar el bloqueo (fecha y hora de inicio, fecha y hora de fin) sean válidos en tipo de dato, obligatoriedad, formato y rango, y que la fecha y hora de fin sea mayor a la de inicio | Q24: Generar una excepción indicándole al usuario cuáles datos del bloqueo que se va a editar no cumplen con las reglas definidas | R24: Detener operación
O25: ='P-Bloqueo'!A7 -> P-BLO-0002 | P25: ='P-Bloqueo'!B7 -> Rechazar el bloqueo si ya existen citas agendadas dentro de ese mismo rango elegido | Q25: Generar una excepción indicándole al usuario que ese rango no se puede bloquear porque ya tiene citas agendadas | R25: Detener operación

Sheet P-Bloqueo
A1: << Ir al modelo de dominio | B1: << Ir al listado de objetos de dominio | C1: << Ir a la caracterización del objeto de dominio | D1: Ir al muestreo de datos del objeto de dominio >> | E1: Ir al event storming del objeto de dominio >>
A2: Objeto de Dominio: | B2: ='Objetos de Dominio'!A11 -> Bloqueo
A3: Descripción: | B3: ='Objetos de Dominio'!B11 -> Representa los momentos en que el barbero no esta disponible para atender sus citas, el barbero establece la hora y la fecha en que empieza y termina ese estado de no disponible.
A4: Numero politica | B4: Descripcion politica | D4: Objeto responsable | E4: Regla responsable
A6: P-BLO-0001 | B6: Asegurar que los datos requeridos (fecha y hora de inicio, fecha y hora de fin) sean válidos en tipo de dato, obligatoriedad, formato y rango | D6: Bloqueo
A7: P-BLO-0002 | B7: Rechazar el bloqueo si ya existen citas agendadas dentro de ese mismo rango elegido | D7: Cita
A8: P-BLO-0003 | B8: Asegurar que los datos requeridos para editar el bloqueo (fecha y hora de inicio, fecha y hora de fin) sean válidos en tipo de dato, obligatoriedad, formato y rango, y que la fecha y hora de fin sea mayor a la de inicio | D8: Bloqueo
A9: P-BLO-0004 | B9: Asegurar que el bloqueo que se va a editar o eliminar le pertenezca al mismo barbero que hace la solicitud | D9: Bloqueo
A10: P-BLO-0005 | B10: Asegurar que el bloqueo no se cruze con otro bloqueo suyo | D10: HorarioBarbero
A11: P-BLO-0006 | B11: Asegurar que exista el bloqueo con el id enviado | D11: Bloqueo
A12: P-BLO-0007 | B12: Asegurar que la fecha y hora de fin sea mayor a la fecha y hora de inicio | D12: Bloqueo

Sheet E-Bloqueo
A1: << Ir al modelo de dominio | C1: << Ir al listado de objetos de dominio | F1: << Ir a la caracterización del objeto de dominio | J1: Ir al muestreo de datos del objeto de dominio >>
A2: Objeto de Dominio: | B2: ='Objetos de Dominio'!A11 -> Bloqueo
A3: Descripción: | B3: ='Objetos de Dominio'!B11 -> Representa los momentos en que el barbero no esta disponible para atender sus citas, el barbero establece la hora y la fecha en que empieza y termina ese estado de no disponible.
A4: Actor | B4: Action/Command | D4: Entity/Aggregate/Object domain | E4: Read Model | G4: Business Rule/Policy | I4: External System | J4: Domain Event | K4: Hotspot/questions/Risk
A5: Actor | B5: Acción | C5: Descripción | D5: Objeto de dominio | E5: Información externa | G5: Políticas | I5: Sistema Externo | J5: Evento | K5: Aspectos por solucionar
E6: Información | F6: Descripción | G6: Número | H6: Descripción
A7: Barbero | B7: Definir un bloque de no disponible | C7: Comando que permite a un barbero asiganar un espacio de no disponibilidad para atender sus citas | D7: =$B$2 -> Bloqueo | E7: HorarioBarbero | F7: Permite llegar de las agendas al barbero dueño de cada cita, ya que la cita no referencia al barbero directamente. | G7: ='P-Bloqueo'!A6 -> P-BLO-0001 | H7: ='P-Bloqueo'!B6 -> Asegurar que los datos requeridos (fecha y hora de inicio, fecha y hora de fin) sean válidos en tipo de dato, obligatoriedad, formato y rango | J7: Bloqueo registrado
E8: Agenda | F8: Permite conocer la fecha de cada cita, ya que la cita solo almacena horas. Es lo que hace comparable el rango del bloqueo contra las citas existentes. | G8: ='P-Bloqueo'!A7 -> P-BLO-0002 | H8: ='P-Bloqueo'!B7 -> Rechazar el bloqueo si ya existen citas agendadas dentro de ese mismo rango elegido
E9: Cita | F9: Permite verificar que no haya citas ya agendadas dentro del rango que se va a bloquear. | G9: ='P-Bloqueo'!A10 -> P-BLO-0005 | H9: ='P-Bloqueo'!B10 -> Asegurar que el bloqueo no se cruze con otro bloqueo suyo
E10: Estado | F10: Permite descartar las citas canceladas, que no deben impedir el bloqueo. | G10: ='P-Bloqueo'!A12 -> P-BLO-0007 | H10: ='P-Bloqueo'!B12 -> Asegurar que la fecha y hora de fin sea mayor a la fecha y hora de inicio
A11: Barbero | B11: Eliminar un bloqueo | C11: Permite a un barbero liberar un espacio de su agenda que había bloqueado previamente | D11: =$B$2 -> Bloqueo | G11: ='P-Bloqueo'!A9 -> P-BLO-0004 | H11: ='P-Bloqueo'!B9 -> Asegurar que el bloqueo que se va a editar o eliminar le pertenezca al mismo barbero que hace la solicitud | J11: Bloqueo cancelado
A12: Barbero | B12: Ver bloqueos en una fecha | C12: Permite a un barbero ver los espacios que tiene bloqueados en una fecha dada | D12: =$B$2 -> Bloqueo | J12: Bloqueos vistos
A13: Sistema | B13: Ver bloqueo en una fecha y hora de inicio | C13: Permite al sistema ver si hay o no un bloqueo en una fecha y hora, en el que empieza el bloqueo, para que el determine luego si el cliente puede agendar una cita en ese momento | D13: =$B$2 -> Bloqueo | J13: Bloqueo visto
A14: Barbero | B14: Ver bloqueo en una fecha y hora de inicio | C14: Permite al barbero ver si hay o no un bloqueo en una fecha y hora, en el que empieza el bloqueo, para que mire si el puso o no un bloqueo | D14: =$B$2 -> Bloqueo | J14: Bloqueo visto
A15: Barbero | B15: Editar un bloqueo | C15: Permite al barbero poder editar la fecha y hora en que inicia o termina | D15: =$B$2 -> Bloqueo | E15: HorarioBarbero | F15: Permite llegar de las agendas al barbero dueño de cada cita, ya que la cita no referencia al barbero directamente. | G15: ='P-Bloqueo'!A7 -> P-BLO-0002 | H15: ='P-Bloqueo'!B7 -> Rechazar el bloqueo si ya existen citas agendadas dentro de ese mismo rango elegido | J15: Bloqueo editado
E16: Agenda | F16: Permite conocer la fecha de cada cita, ya que la cita solo almacena horas. Es lo que hace comparable el rango del bloqueo contra las citas existentes.
E17: Cita | F17: Permite verificar que el nuevo rango no choque con citas ya agendadas. | G17: ='P-Bloqueo'!A8 -> P-BLO-0003 | H17: ='P-Bloqueo'!B8 -> Asegurar que los datos requeridos para editar el bloqueo (fecha y hora de inicio, fecha y hora de fin) sean válidos en tipo de dato, obligatoriedad, formato y rango, y que la fecha y hora de fin sea mayor a la de inicio
E18: Estado | F18: Permite descartar las citas canceladas, que no deben impedir el bloqueo.

Sheet M-Bloqueo
A1: <<<< Ir al modulo de dominio | B1: <<<< Ir a objetos de dominio
A2: Representa un identificador que hará unico cada objeto de dominio de este tipo, no se puede repetir | B2: Referencia a qué barbero le pertence este bloqueo | C2: Representa la fecha y hora en el que el barbero empieza a no estar disponible para atender las citas | D2: Representa la fecha y hora en el que el barbero empieza estar disponible nuevamente para atender las citas | E2: Combinación única que indica que un mismo barbero no puede tener dos bloqueos con la misma fecha y hora de inicio y la misma fecha y hora final
A3: id | B3: barbero | C3: fechaHoraInicio | D3: fechaHoraFinal | E3: Combinación única
A4: 1 | B4: ='M-Barbero'!L4 -> +57-3245627890 | C4: 46188.5 | D4: 46188.542 | E4: =_xlfn.CONCAT(B4,"-",TEXT(C4,"dd/mm/yyyy hh:mm"),"-",TEXT(D4,"dd/mm/yyyy hh:mm")) -> +57-3245627890-15/06/2026 12:00-15/06/2026 13:00
A5: 2 | B5: ='M-Barbero'!L5 -> +57-3124518923 | C5: 46189.417 | D5: 46189.438 | E5: =_xlfn.CONCAT(B5,"-",TEXT(C5,"dd/mm/yyyy hh:mm"),"-",TEXT(D5,"dd/mm/yyyy hh:mm")) -> +57-3124518923-16/06/2026 10:00-16/06/2026 10:30
A6: 3 | B6: ='M-Barbero'!L6 -> +57-3214533321 | C6: 46191.583 | D6: 46191.625 | E6: =_xlfn.CONCAT(B6,"-",TEXT(C6,"dd/mm/yyyy hh:mm"),"-",TEXT(D6,"dd/mm/yyyy hh:mm")) -> +57-3214533321-18/06/2026 14:00-18/06/2026 15:00
A7: 4 | B7: ='M-Barbero'!L7 -> +91-9876543210 | C7: 46193.375 | D7: 46193.396 | E7: =_xlfn.CONCAT(B7,"-",TEXT(C7,"dd/mm/yyyy hh:mm"),"-",TEXT(D7,"dd/mm/yyyy hh:mm")) -> +91-9876543210-20/06/2026 09:00-20/06/2026 09:30
A8: 5 | B8: ='M-Barbero'!L7 -> +91-9876543210 | C8: 46195.667 | D8: 46195.698 | E8: =_xlfn.CONCAT(B8,"-",TEXT(C8,"dd/mm/yyyy hh:mm"),"-",TEXT(D8,"dd/mm/yyyy hh:mm")) -> +91-9876543210-22/06/2026 16:00-22/06/2026 16:45
B14: Corresponde a la descripcion de los atributos
B15: Corresponde al identificador unico del objeto de dominio
B16: Corresponde a las referencias de otros objetos de dominio
B17: Corresponde a los datos que ingresa el usuario
B18: Corresponde a la combinacion única

Sheet C-BarberoServicio
A1: <<<< Ir al modulo de dominio | B1: <<<< Ir a objetos de dominio
A2: Nombre atributo | B2: Descripción atributo | C2: Identificador del objeto de dominio | D2: Tipo de dato | E2: Obligatorio | F2: Longitud mínima (si aplica) | G2: Longitud máxima (si aplica) | H2: Precisión (si aplica) | I2: Rendondeo (si aplica) | J2: Rango inicial (si aplica) | K2: Rango final (si aplica) | L2: Formato (si aplica) | M2: Reglas especiales (si aplica) | N2: Dato calculado | O2: Aplica ajuste del dato (si aplica) | P2: Carácter de ajuste (si aplica) | Q2: Quitar espacios en blanco al inicio (si aplica) | R2: Quitar espacios en blanco al fin (si aplica) | S2: Dato sensible (si aplica) | T2: Valor por defecto (si aplica) | U2: Auto generado | V2: =A17 -> habilitarServicioBarbero | W2: =A20 -> ajustarTiemposServicioBarbero | Y2: =A23 -> consultarServiciosElegidos | Z2: =A24 -> consultarServiciosDeBarbero | AA2: =A25 -> desactivarServicioBarbero | AB2: =A27 -> reactivarServicioBarbero
A3: ='M-BarberoServicio'!A3 -> id | B3: ='M-BarberoServicio'!A2 -> Representa un identificador que hará unico cada objeto de dominio de este tipo, no se puede repetir | C3: Si | D3: Identificador único universal | E3: Si | F3: No aplica | G3: No aplica | H3: No aplica | I3: No aplica | J3: No aplica | K3: No aplica | L3: No aplica | M3: No aplica | N3: No | O3: No aplica | P3: No aplica | Q3: No aplica | R3: No aplica | S3: No | T3: UUID vacio | U3: Si | V3: No requerido | W3: Requerido | X3: No modificable | Y3: No mostrar | Z3: No mostrar | AA3: Requerido | AB3: Requerido
A4: ='M-BarberoServicio'!B3 -> barbero | B4: ='M-BarberoServicio'!B2 -> Representa el nombre y apellidos del barbero | C4: No | D4: Barbero | E4: Si | F4: No aplica | G4: No aplica | H4: No aplica | I4: No aplica | J4: No aplica | K4: No aplica | L4: No aplica | M4: Aplican las reglas del objeto referenciado | N4: No | O4: No aplica | P4: No aplica | Q4: No aplica | R4: No aplica | S4: No | T4: UUID vacio | U4: No | V4: Requerido | W4: No requerido | X4: No modificable | Y4: No mostrar | Z4: Mostrar | AA4: No requerido | AB4: No requerido
A5: ='M-BarberoServicio'!C3 -> servicio | B5: ='M-BarberoServicio'!C2 -> Representa el nombre del servicio de la barberia | C5: No | D5: Servicio | E5: Si | F5: No aplica | G5: No aplica | H5: No aplica | I5: No aplica | J5: No aplica | K5: No aplica | L5: No aplica | M5: Aplican las reglas del objeto referenciado | N5: No | O5: No aplica | P5: No aplica | Q5: No aplica | R5: No aplica | S5: No | T5: UUID vacio | U5: No | V5: Requerido | W5: No requerido | X5: No modificable | Y5: Mostrar | Z5: Mostrar | AA5: No requerido | AB5: No requerido
A6: ='M-BarberoServicio'!D3 -> duracionEnHoras | B6: ='M-BarberoServicio'!D2 -> Representa la cantidad de horas que un barbero tarda en realizar un servicio, esta duracion el barbero debe de ser consiente de cuanto se demora en realizarlo | C6: No | D6: Entero | E6: Si | F6: No aplica | G6: No aplica | H6: No aplica | I6: No aplica | J6: 0 | K6: 3 | L6: No aplica | M6: No aplica | N6: No | O6: No aplica | P6: No aplica | Q6: No aplica | R6: No aplica | S6: No | T6: 0 | U6: No | V6: Requerido | W6: Requerido | X6: Modificable | Y6: Mostrar | Z6: No mostrar | AA6: No requerido | AB6: No requerido
A7: ='M-BarberoServicio'!E3 -> duracionEnMinutos | B7: ='M-BarberoServicio'!E2 -> Representa la cantidad de minutos que un barbero tarda en realizar un servicio, esta duracion el barbero debe de ser consiente de cuanto se demora en realizarlo | C7: No | D7: Entero | E7: Si | F7: No aplica | G7: No aplica | H7: No aplica | I7: No aplica | J7: 0 | K7: 59 | L7: No aplica | M7: No aplica | N7: No | O7: No aplica | P7: No aplica | Q7: No aplica | R7: No aplica | S7: No | T7: 0 | U7: No | V7: Requerido | W7: Requerido | X7: Modificable | Y7: Mostrar | Z7: No mostrar | AA7: No requerido | AB7: No requerido
A8: ='M-BarberoServicio'!F3 -> tiempoExtra | B8: ='M-BarberoServicio'!F2 -> Representa la cantidad de minutos que un barbero pone de tiempo extra en las citas de su agenda, cada barbero usa este tiempo porque hay ocaciones que la cita se puede demorar más de lo previsto. Este tiempo les ayuda a evitar que se les retrase la agenda | C8: No | D8: Entero | E8: No | F8: No aplica | G8: No aplica | H8: No aplica | I8: No aplica | J8: 0 | K8: 59 | L8: No aplica | M8: No aplica | N8: No | O8: No aplica | P8: No aplica | Q8: No aplica | R8: No aplica | S8: No | T8: 0 | U8: No | V8: Requerido | W8: Requerido | X8: Modificable | Y8: Mostrar | Z8: No mostrar | AA8: No requerido | AB8: No requerido
A9: ='M-BarberoServicio'!G3 -> vigente | B9: ='M-BarberoServicio'!G2 -> Representa si el barbero sigue o no presentando el servicio en la barbería | C9: No | D9: Lógico | E9: Si | F9: No aplica | G9: No aplica | H9: No aplica | I9: No aplica | J9: No aplica | K9: No aplica | L9: No aplica | M9: No aplica | N9: No | O9: No aplica | P9: No aplica | Q9: No aplica | R9: No aplica | S9: No | T9: Si | U9: No | V9: No requerido | W9: No requerido | X9: No modificable | Y9: No mostrar | Z9: No mostrar | AA9: No requerido | AB9: No requerido
A11: Nombre combinación única | B11: Descripción | C11: Atributos involucrados
A12: ='M-BarberoServicio'!H3 -> Combinación única | B12: ='M-BarberoServicio'!H2 -> Combinación única que indica que un mismo barbero no puede aparecer dos veces ofreciendo el mismo servicio | C12: barbero
C13: servicio
A15: Responsabilidad | C15: Descripción | G15: Entradas | J15: Salida | O15: Políticas (Reglas de Negocio) | Q15: Excepción
G16: Parámetro | H16: Tipo de dato | I16: Descripción | J16: Tipo de Dato | K16: Descripción | O16: Política | P16: Descripción | Q16: Detalle | R16: ¿Qué hago?
A17: habilitarServicioBarbero | C17: Comando que permite a un barbero indicar que sabe realizar un servicio del catálogo, con su duración y colchón | G17: datos{barbero, servicio, duracionEnHoras, duracionEnMinutos, tiempoExtra} | H17: BarberoServicio | I17: Contiene la información requerida para habilitarle un servicio a un barbero | J17: BarberoServicio | K17: Contiene la información del servicio habilitado para el barbero | O17: ='P-BarberoServicio'!A6 -> P-BSE-0001 | P17: ='P-BarberoServicio'!B6 -> Asegurar que los datos requeridos (duración en horas, duración en minutos, tiempo extra) sean válidos en tipo de dato, obligatoriedad y rango | Q17: Generar una excepción indicándole al barbero que los datos no cumplen las reglas definidas | R17: Detener operación
O18: ='P-BarberoServicio'!A7 -> P-BSE-0002 | P18: ='P-BarberoServicio'!B7 -> Asegurar que el barbero no tenga ya definido ese mismo servicio | Q18: Generar una excepción indicándole el barbero ya tiene habilitado ese mismo servicio | R18: Detener operación
O19: ='P-BarberoServicio'!A9 -> P-BSE-0004 | P19: ='P-BarberoServicio'!B9 -> Asegurar que la suma del tiempo en horas y minutos de la realizacion del servicio por el barbero sea mayor a cero | Q19: Generar una excepción indicándole al barbero que los no se puede realizar un servicio en tiempo cero, es decir que debe de poner un timpio mayor a cer, ya que en la hora o en el minuto | R19: Detener operación
A20: ajustarTiemposServicioBarbero | C20: Permite modificar la duración y el tiempo extra que un barbero usa para un servicio ya habilitado | G20: id | H20: UUID | I20: Corresponde al identificador del servicio del barbero que se va a ajustar | J20: BarberoServicio | K20: Contiene la información del servicio del barbero con sus tiempos actualizados | O20: ='P-BarberoServicio'!A8 -> P-BSE-0003 | P20: ='P-BarberoServicio'!B8 -> Asegurar que exista el servicio definido del barbero con el id enviado | Q20: Informar con un mensaje que no existe un servicio habilitado del barbero con el identificador enviado y por lo tanto no es posible llevar a cabo la operación | R20: Detener operación
G21: datos{duracionEnHoras, duracionEnMinutos, tiempoExtra} | H21: BarberoServicio | I21: Contiene los nuevos tiempos con los que se va a modificar el servicio | O21: ='P-BarberoServicio'!A6 -> P-BSE-0001 | P21: ='P-BarberoServicio'!B6 -> Asegurar que los datos requeridos (duración en horas, duración en minutos, tiempo extra) sean válidos en tipo de dato, obligatoriedad y rango | Q21: Generar una excepción indicándole al barbero que los datos no cumplen las reglas definidas | R21: Detener operación
O22: ='P-BarberoServicio'!A9 -> P-BSE-0004 | P22: ='P-BarberoServicio'!B9 -> Asegurar que la suma del tiempo en horas y minutos de la realizacion del servicio por el barbero sea mayor a cero | Q22: Generar una excepción indicándole al barbero que los no se puede realizar un servicio en tiempo cero, es decir que debe de poner un timpio mayor a cer, ya que en la hora o en el minuto | R22: Detener operación
A23: consultarServiciosElegidos | C23: Permite a un barbero consultar los servicios que esten vigentes | G23: filtro{barbero} | H23: BarberoServicio | I23: Contiene el barbero por el cual se van a consultar sus servicios habilitados | J23: Lista<BarberoServicio> | K23: Contiene todos los servicios que el barbero tiene habilitados
A24: consultarServiciosDeBarbero | C24: Permite a un cliente consultar qué servicios ofrece un barbero en particular | G24: filtro{barbero} | H24: BarberoServicio | I24: Contiene el barbero por el cual se van a consultar los servicios que ofrece | J24: Lista<BarberoServicio> | K24: Contiene todos los servicios vigentes que ofrece ese barbero
A25: desactivarServicioBarbero | C25: Permite a un barbero desactivar un servicio que ya no quiere seguir ofreciendo | G25: id | H25: UUID | I25: Corresponde al identificador del servicio del barbero que se va a desactivar | J25: No retorna ningún valor. En caso de error genera una excepción. | O25: ='P-BarberoServicio'!A8 -> P-BSE-0003 | P25: ='P-BarberoServicio'!B8 -> Asegurar que exista el servicio definido del barbero con el id enviado | Q25: Informar con un mensaje que no existe un servicio habilitado del barbero con el identificador enviado y por lo tanto no es posible llevar a cabo la operación | R25: Detener operación
O26: ='P-BarberoServicio'!A10 -> P-BSE-0005 | P26: ='P-BarberoServicio'!B10 -> Asegurar que el estado de BarberoServicio este vigente | Q26: Informar al barbero que el servicio que quiere desactivar, ya se encuentra desactivado | R26: Detener operación
A27: reactivarServicioBarbero | C27: Permite a un barbero activar un servicio que ya se habia desactivado | G27: id | H27: UUID | I27: Corresponde al identificador del servicio del barbero que se va a desactivar | J27: No retorna ningún valor. En caso de error genera una excepción. | O27: ='P-BarberoServicio'!A8 -> P-BSE-0003 | P27: ='P-BarberoServicio'!B8 -> Asegurar que exista el servicio definido del barbero con el id enviado | Q27: Informar con un mensaje que no existe un servicio habilitado del barbero con el identificador enviado y por lo tanto no es posible llevar a cabo la operación | R27: Detener operación
O28: ='P-BarberoServicio'!A11 -> P-BSE-0006 | P28: ='P-BarberoServicio'!B11 -> Asegurar que el estado del BarberoServicio no este vigente | Q28: Informar al barbero que el servicio que quiere reactivar, ya se encuentra activado | R28: Detener operación

Sheet P-BarberoServicio
A1: << Ir al modelo de dominio | B1: << Ir al listado de objetos de dominio | C1: << Ir a la caracterización del objeto de dominio | D1: Ir al muestreo de datos del objeto de dominio >> | E1: Ir al event storming del objeto de dominio >>
A2: Objeto de Dominio: | B2: ='Objetos de Dominio'!A12 -> BarberoServicio
A3: Descripción: | B3: ='Objetos de Dominio'!B12 -> Representa qué servicios sabe hacer cada barbero, cuánto se demora en realizarlos y cuánto tiempo extra usa de colchón, ya que no todos los barberos ofrecen los mismos servicios que están en la barbería.
A4: Numero politica | B4: Descripcion politica | D4: Objeto responsable | E4: Regla responsable
A6: P-BSE-0001 | B6: Asegurar que los datos requeridos (duración en horas, duración en minutos, tiempo extra) sean válidos en tipo de dato, obligatoriedad y rango | D6: BarberoServicio
A7: P-BSE-0002 | B7: Asegurar que el barbero no tenga ya definido ese mismo servicio | D7: BarberoServicio
A8: P-BSE-0003 | B8: Asegurar que exista el servicio definido del barbero con el id enviado | D8: BarberoServicio
A9: P-BSE-0004 | B9: Asegurar que la suma del tiempo en horas y minutos de la realizacion del servicio por el barbero sea mayor a cero | D9: BarberoServicio
A10: P-BSE-0005 | B10: Asegurar que el estado de BarberoServicio este vigente | D10: BarberoServicio
A11: P-BSE-0006 | B11: Asegurar que el estado del BarberoServicio no este vigente | D11: BarberoServicio

Sheet E-BarberoServicio
A1: << Ir al modelo de dominio | C1: << Ir al listado de objetos de dominio | F1: << Ir a la caracterización del objeto de dominio | J1: Ir al muestreo de datos del objeto de dominio >>
A2: Objeto de Dominio: | B2: ='Objetos de Dominio'!A12 -> BarberoServicio
A3: Descripción: | B3: ='Objetos de Dominio'!B12 -> Representa qué servicios sabe hacer cada barbero, cuánto se demora en realizarlos y cuánto tiempo extra usa de colchón, ya que no todos los barberos ofrecen los mismos servicios que están en la barbería.
A4: Actor | B4: Action/Command | D4: Entity/Aggregate/Object domain | E4: Read Model | G4: Business Rule/Policy | I4: External System | J4: Domain Event | K4: Hotspot/questions/Risk
A5: Actor | B5: Acción | C5: Descripción | D5: Objeto de dominio | E5: Información externa | G5: Políticas | I5: Sistema Externo | J5: Evento | K5: Aspectos por solucionar
E6: Información | F6: Descripción | G6: Número | H6: Descripción
A7: Barbero | B7: Definir un servicio para el barbero | C7: Comando que permite a un barbero indicar que sabe realizar un servicio del catálogo, con su duración y colchón | D7: =$B$2 -> BarberoServicio | G7: ='P-BarberoServicio'!A6 -> P-BSE-0001 | H7: aquí | J7: Servicio habilitado para barbero
G8: ='P-BarberoServicio'!A7 -> P-BSE-0002 | H8: aquí
G9: ='P-BarberoServicio'!A9 -> P-BSE-0004 | H9: aquí
A10: Barbero | B10: Ajustar los tiempos de un servicio del barbero | C10: Permite modificar la duración y el tiempo extra que un barbero usa para un servicio ya habilitado | D10: =$B$2 -> BarberoServicio | G10: ='P-BarberoServicio'!A6 -> P-BSE-0001 | H10: aquí | J10: Tiempos de servicio de barbero actualizados
G11: ='P-BarberoServicio'!A9 -> P-BSE-0004 | H11: aquí
A12: Barbero | B12: Ver servicios elegidos | C12: Permite a un barbero consultar los servicios que tiene habilitados | D12: =$B$2 -> BarberoServicio | J12: Servicios de barbero consultados
A13: Cliente | B13: Ver servicios de un barbero | C13: Permite a un cliente consultar qué servicios ofrece un barbero en particular | D13: =$B$2 -> BarberoServicio | J13: Servicios de barbero consultados
A14: Barbero | B14: Dejar de prestar el servicio para el catálogo | C14: Permite a un barbero desactivar un servicio que ya no quiere seguir ofreciendo | D14: =$B$2 -> BarberoServicio | G14: ='P-BarberoServicio'!A10 -> P-BSE-0005 | H14: aquí | J14: Servicio de barbero desactivado
A15: Barbero | B15: Volver prestar el servicio para el catálogo | C15: Permite a un barbero desactivar un servicio que ya no quiere seguir ofreciendo | D15: =$B$2 -> BarberoServicio | G15: ='P-BarberoServicio'!A11 -> P-BSE-0006 | H15: aquí | J15: Servicio de barbero reactivado

Sheet M-BarberoServicio
A1: <<<< Ir al modulo de dominio | B1: <<<< Ir a objetos de dominio
A2: Representa un identificador que hará unico cada objeto de dominio de este tipo, no se puede repetir | B2: Representa el nombre y apellidos del barbero | C2: Representa el nombre del servicio de la barberia | D2: Representa la cantidad de horas que un barbero tarda en realizar un servicio, esta duracion el barbero debe de ser consiente de cuanto se demora en realizarlo | E2: Representa la cantidad de minutos que un barbero tarda en realizar un servicio, esta duracion el barbero debe de ser consiente de cuanto se demora en realizarlo | F2: Representa la cantidad de minutos que un barbero pone de tiempo extra en las citas de su agenda, cada barbero usa este tiempo porque hay ocaciones que la cita se puede demorar más de lo previsto. Este tiempo les ayuda a evitar que se les retrase la agenda | G2: Representa si el barbero sigue o no presentando el servicio en la barbería | H2: Combinación única que indica que un mismo barbero no puede aparecer dos veces ofreciendo el mismo servicio
A3: id | B3: barbero | C3: servicio | D3: duracionEnHoras | E3: duracionEnMinutos | F3: tiempoExtra | G3: vigente | H3: Combinación única
A4: 1 | B4: =_xlfn.CONCAT('M-Barbero'!B4," ",'M-Barbero'!D4) -> Juan García | C4: ='M-Servicio'!B4 -> Motilada | D4: 0 | E4: 45 | F4: 15 | G4: si | H4: =_xlfn.CONCAT(B4,"-",C4) -> Juan García-Motilada
A5: 2 | B5: =_xlfn.CONCAT('M-Barbero'!B5," ",'M-Barbero'!D5) -> Juan Ortiz | C5: ='M-Servicio'!B5 -> Corte de barba | D5: 0 | E5: 10 | F5: 5 | G5: si | H5: =_xlfn.CONCAT(B5,"-",C5) -> Juan Ortiz-Corte de barba
A6: 3 | B6: =_xlfn.CONCAT('M-Barbero'!B6," ",'M-Barbero'!D6) -> Carlos Arbeladez | C6: ='M-Servicio'!B6 -> Perfilada de barba | D6: 0 | E6: 15 | F6: 5 | G6: si | H6: =_xlfn.CONCAT(B6,"-",C6) -> Carlos Arbeladez-Perfilada de barba
A7: 4 | B7: =_xlfn.CONCAT('M-Barbero'!B7," ",'M-Barbero'!D7) -> Andres Ramirez | C7: ='M-Servicio'!B7 -> Arreglo completo de barba con toalla caliente | D7: 0 | E7: 40 | F7: 10 | G7: si | H7: =_xlfn.CONCAT(B7,"-",C7) -> Andres Ramirez-Arreglo completo de barba con toalla caliente
A8: 5 | B8: =_xlfn.CONCAT('M-Barbero'!B5," ",'M-Barbero'!D5) -> Juan Ortiz | C8: ='M-Servicio'!B4 -> Motilada | D8: 0 | E8: 40 | F8: 10 | G8: si | H8: =_xlfn.CONCAT(B8,"-",C8) -> Juan Ortiz-Motilada
A9: 6 | B9: =_xlfn.CONCAT('M-Barbero'!B6," ",'M-Barbero'!D6) -> Carlos Arbeladez | C9: ='M-Servicio'!B5 -> Corte de barba | D9: 0 | E9: 15 | F9: 5 | G9: si | H9: =_xlfn.CONCAT(B9,"-",C9) -> Carlos Arbeladez-Corte de barba
A10: 7 | B10: =_xlfn.CONCAT('M-Barbero'!B4," ",'M-Barbero'!D4) -> Juan García | C10: ='M-Servicio'!B6 -> Perfilada de barba | D10: 0 | E10: 20 | F10: 5 | G10: si | H10: =_xlfn.CONCAT(B10,"-",C10) -> Juan García-Perfilada de barba
A11: 8 | B11: =_xlfn.CONCAT('M-Barbero'!B7," ",'M-Barbero'!D7) -> Andres Ramirez | C11: ='M-Servicio'!B4 -> Motilada | D11: 0 | E11: 50 | F11: 15 | G11: si | H11: =_xlfn.CONCAT(B11,"-",C11) -> Andres Ramirez-Motilada
A12: 9 | B12: =_xlfn.CONCAT('M-Barbero'!B8," ",'M-Barbero'!D8) -> Juan Zambrano | C12: ='M-Servicio'!B5 -> Corte de barba | D12: 0 | E12: 12 | F12: 5 | G12: si | H12: =_xlfn.CONCAT(B12,"-",C12) -> Juan Zambrano-Corte de barba
B14: Corresponde a la descripcion de los atributos
B15: Corresponde al identificador unico del objeto de dominio
B16: Corresponde a las referencias de otros objetos de dominio
B17: Corresponde a los datos que ingresa el usuario
B18: Corresponde a los datos auto generados por el sistema
B19: Corresponde a la combinacion única

Sheet C-HorarioBarbero
A1: <<<< Ir al modulo de dominio | B1: <<<< Ir a objetos de dominio
A2: Nombre atributo | B2: Descripción atributo | C2: Identificador del objeto de dominio | D2: Tipo de dato | E2: Obligatorio | F2: Longitud mínima (si aplica) | G2: Longitud máxima (si aplica) | H2: Precisión (si aplica) | I2: Rendondeo (si aplica) | J2: Rango inicial (si aplica) | K2: Rango final (si aplica) | L2: Formato (si aplica) | M2: Reglas especiales (si aplica) | N2: Dato calculado | O2: Aplica ajuste del dato (si aplica) | P2: Carácter de ajuste (si aplica) | Q2: Quitar espacios en blanco al inicio (si aplica) | R2: Quitar espacios en blanco al fin (si aplica) | S2: Dato sensible (si aplica) | T2: Valor por defecto (si aplica) | U2: Auto generado | V2: =A22 -> definirHorarioDeTrabajo | W2: =A25 -> consultarHorariosDefinidos | X2: =A26 -> desactivarHorarioDeTrabajo | Y2: =A29 -> consultarHorariosDeTrabajoDeBarbero
A3: ='M-HorarioBarbero'!A3 -> id | B3: ='M-HorarioBarbero'!A2 -> Representa un identificador que hará unico cada objeto de dominio de este tipo, no se puede repetir | C3: Si | D3: Identificador único universal | E3: Si | F3: No aplica | G3: No aplica | H3: No aplica | I3: No aplica | J3: No aplica | K3: No aplica | L3: No aplica | M3: No aplica | N3: No | O3: No | P3: No aplica | Q3: No | R3: No | S3: No | T3: UUID vacio | U3: Si | V3: No requerido | W3: No mostrar | X3: Requerido | Y3: No mostrar
A4: ='M-HorarioBarbero'!B3 -> barbero | B4: ='M-HorarioBarbero'!B2 -> Referencia a que barbero va a ser dueño de este horario | C4: No | D4: Barbero | E4: Si | F4: No aplica | G4: No aplica | H4: No aplica | I4: No aplica | J4: No aplica | K4: No aplica | L4: No aplica | M4: Aplican las reglas del objeto referenciado | N4: No | O4: No aplica | P4: No aplica | Q4: No aplica | R4: No aplica | S4: No | T4: UUID vacio | U4: No | V4: Requerido | W4: No mostrar | X4: No requerido | Y4: Mostrar
A5: ='M-HorarioBarbero'!C3 -> horarioDeLaBarberia | B5: ='M-HorarioBarbero'!C2 -> Hace referencia a la agenda del barbero en la que queda guardado este horario de trabajo | C5: No | D5: HorarioBarberia | E5: Si | F5: No aplica | G5: No aplica | H5: No aplica | I5: No aplica | J5: No aplica | K5: No aplica | L5: No aplica | M5: Aplican las reglas del objeto referenciado | N5: No | O5: No aplica | P5: No aplica | Q5: No aplica | R5: No aplica | S5: No | T5: UUID vacio | U5: No | V5: Requerido | W5: Mostrar | X5: No requerido | Y5: Mostrar
A6: ='M-HorarioBarbero'!D3 -> horaInicio | B6: ='M-HorarioBarbero'!D2 -> Representa la hora en la que el barbero empieza a estar disponible ese dia | C6: No | D6: Hora | E6: Si | F6: No aplica | G6: No aplica | H6: No aplica | I6: No aplica | J6: No aplica | K6: No aplica | L6: No aplica | M6: Debe estar dentro del rango de horarioDeLaBarberia | N6: No | O6: No aplica | P6: No aplica | Q6: No aplica | R6: No aplica | S6: No | T6: 00:00 | U6: No | V6: Requerido | W6: Mostrar | X6: No requerido | Y6: Mostrar
A7: ='M-HorarioBarbero'!E3 -> horaFinal | B7: ='M-HorarioBarbero'!E2 -> Representa la hora en la que el barbero deja de estar disponible ese día. | C7: No | D7: Hora | E7: Si | F7: No aplica | G7: No aplica | H7: No aplica | I7: No aplica | J7: No aplica | K7: No aplica | L7: No aplica | M7: Debe ser mayor a horaInicio y estar dentro del rango de horarioDeLaBarberia | N7: No | O7: No aplica | P7: No aplica | Q7: No aplica | R7: No aplica | S7: No | T7: 00:00 | U7: No | V7: Requerido | W7: Mostrar | X7: No requerido | Y7: Mostrar
A8: ='M-HorarioBarbero'!F3 -> fechaCreacion | B8: ='M-HorarioBarbero'!F2 -> Representa la fecha en el que el barbero creo su horario. Es un dato calculado que toma la fecha de hoy cuando el barbero la crea | C8: No | D8: Fecha | E8: Si | F8: No aplica | G8: No aplica | H8: No aplica | I8: No aplica | J8: No aplica | K8: No aplica | L8: No aplica | M8: Toma la fecha del sistema en el momento en que el barbero crea este horario | N8: Si | O8: No aplica | P8: No aplica | Q8: No aplica | R8: No aplica | S8: No | T8: 01/01/1000 | U8: Si | V8: No requerido | W8: Mostrar | X8: No requerido | Y8: No mostrar
A9: ='M-HorarioBarbero'!G3 -> fechaDesactivacion | B9: ='M-HorarioBarbero'!G2 -> Representa la fecha en la que este horario dejó de estar vigente, ya sea porque el barbero lo retiró o porque se desactivó el horario de la barbería del que depende. Es un dato calculado que toma la fecha del sistema en ese momento. | C9: No | D9: Fecha | E9: No | F9: No aplica | G9: No aplica | H9: No aplica | I9: No aplica | J9: No aplica | K9: No aplica | L9: No aplica | M9: Toma la fecha del sistema en el momento en que el barbero desactiva este horario. Su valor por defecto es 01/01/1000 mientras siga vigente | N9: Si | O9: No aplica | P9: No aplica | Q9: No aplica | R9: No aplica | S9: No | T9: 01/01/1000 | U9: Si | V9: No requerido | W9: Mostrar | X9: No requerido | Y9: No mostrar
A10: ='M-HorarioBarbero'!H3 -> vigente | B10: ='M-HorarioBarbero'!H2 -> Representa si este horario lo sigue o no usando el barbero. Una vez que el barbero cambie este estado a no vigente, no se puede volver a cambiar | C10: No | D10: Lógico | E10: Si | F10: No aplica | G10: No aplica | H10: No aplica | I10: No aplica | J10: No aplica | K10: No aplica | L10: No aplica | M10: Una vez se cambia a No, no puede volver a cambiar a Si | N10: No | O10: No aplica | P10: No aplica | Q10: No aplica | R10: No aplica | S10: No | T10: Si | U10: Si | V10: No requerido | W10: Mostrar | X10: No requerido | Y10: No mostrar
A12: Nombre combinación única | B12: Descripción | C12: Atributos involucrados
A13: ='M-HorarioBarbero'!I3 -> Combinación única | B13: ='M-HorarioBarbero'!I2 -> Combinación única que indica que un mismo barbero no puede tener dos horarios con el mismo día de la barbería, la misma hora de inicio, la misma hora final, misma fecha de creacion y de desactivacion | C13: =A4 -> barbero
C14: =A5 -> horarioDeLaBarberia
C15: =A6 -> horaInicio
C16: =A7 -> horaFinal
C17: ='C-HorarioBarbero'!A8 -> fechaCreacion
C18: =A9 -> fechaDesactivacion
A20: Responsabilidad | C20: Descripción | G20: Entradas | J20: Salida | O20: Políticas (Reglas de Negocio) | Q20: Excepción
G21: Parámetro | H21: Tipo de dato | I21: Descripción | J21: Tipo de Dato | K21: Descripción | O21: Política | P21: Descripción | Q21: Detalle | R21: ¿Qué hago?
A22: definirHorarioDeTrabajo | C22: Comando que permite a un barbero registrar el día de la semana y las horas en que trabaja | G22: datos{barbero, horarioDeLaBarberia, horaInicio, horaFinal} | H22: HorarioBarbero | I22: Contiene la información requerida para registrar el horario de trabajo del barbero | J22: HorarioBarbero | K22: Contiene la información del horario de trabajo registrado | O22: ='P-HorarioBarbero'!A6 -> P-HBO-0001 | P22: ='P-HorarioBarbero'!B6 -> Asegurar que los datos requeridos (día de la semana, hora de inicio, hora de fin) sean válidos en tipo de dato, obligatoriedad, formato y rango | Q22: Generar una excepción indicándole al barbero que los datos no cumplen las reglas definidas | R22: Detener operación
O23: ='P-HorarioBarbero'!A7 -> P-HBO-0002 | P23: ='P-HorarioBarbero'!B7 -> Asegurar que el horario de trabajo esté dentro del horario de apertura y cierre de la barbería para ese día | Q23: Generar una excepción indicándole al usuario que el horario de trabajo queda por fuera del horario de apertura y cierre de la barbería para ese día | R23: Detener operación
O24: ='P-HorarioBarbero'!A10 -> P-HBO-0006 | P24: ='P-HorarioBarbero'!B10 -> Asegurar que la hora de fin sea mayor a la hora de inicio | Q24: Generar una excepción indicándole al barbero que la hora de fin debe ser mayor a la hora de inicio | R24: Detener operación
A25: consultarHorariosDefinidos | C25: Permite a un barbero consultar los horarios de trabajo que ha definido | G25: filtro{barbero} | H25: HorarioBarbero | I25: Contiene el barbero por el cual se van a consultar sus horarios de trabajo | J25: Lista<HorarioBarbero> | K25: Contiene todos los horarios de trabajo que el barbero tiene definidos
A26: desactivarHorarioDeTrabajo | C26: Permite a un barbero desactivar un horario para dejar de trabajar ese día de la semana, cancelando las citas futuras que dependían de él | G26: id | H26: UUID | I26: Corresponde al identificador del horario de trabajo que se va a desactivar | K26: No retorna ningún valor. En caso de error genera una excepción. | O26: ='P-HorarioBarbero'!A8 -> P-HBO-0004 | P26: ='P-HorarioBarbero'!B8 -> Asegurar que queden canceladas, en el estado Cancelación, todas las citas futuras asociadas a las agendas generadas a partir de ese horario de trabajo. Se consideran futuras las citas cuya agenda tenga una fecha posterior a la fecha actual | Q26: Si alguna de las citas futuras no pudo ser cancelada, revertir toda la operación e informar el error | R26: Detener operación
O27: ='P-HorarioBarbero'!A9 -> P-HBO-0005 | P27: ='P-HorarioBarbero'!B9 -> Asegurar que exista el horario de trabajo del barbero con el id enviado | Q27: Informar con un mensaje que no existe un horario de trabajo con el identificador enviado y por lo tanto no es posible llevar a cabo la operación | R27: Detener operación
O28: ='P-HorarioBarbero'!A11 -> P-HBO-0007 | P28: ='P-HorarioBarbero'!B11 -> Asegurar que el horario de trabajo que se va a desactivar se encuentre vigente | Q28: Informar con un mensaje que ese horario de trabajo ya se encuentra desactivado y por lo tanto no puede volver a desactivarse | R28: Detener operación
A29: consultarHorariosDeTrabajoDeBarbero | C29: Permite a un cliente consultar en qué días y horas trabaja un barbero | G29: filtro{barbero} | H29: HorarioBarbero | I29: Contiene el barbero por el cual se van a consultar sus horarios de trabajo | J29: Lista<HorarioBarbero> | K29: Contiene todos los horarios de trabajo vigentes de ese barbero

Sheet P-HorarioBarbero
A1: << Ir al modelo de dominio | B1: << Ir al listado de objetos de dominio | C1: << Ir a la caracterización del objeto de dominio | D1: Ir al muestreo de datos del objeto de dominio >> | E1: Ir al event storming del objeto de dominio >>
A2: Objeto de Dominio: | B2: ='Objetos de Dominio'!A13 -> HorarioBarbero
A3: Descripción: | B3: ='Objetos de Dominio'!B13 -> Representa el día de la semana en que trabaja un barbero, junto con la hora en la que empieza y termina su jornada de trabajo.
A4: Numero politica | B4: Descripcion politica | D4: Objeto responsable | E4: Regla responsable
A6: P-HBO-0001 | B6: Asegurar que los datos requeridos (día de la semana, hora de inicio, hora de fin) sean válidos en tipo de dato, obligatoriedad, formato y rango | D6: HorarioBarbero
A7: P-HBO-0002 | B7: Asegurar que el horario de trabajo esté dentro del horario de apertura y cierre de la barbería para ese día | D7: HorarioBarberia
A8: P-HBO-0004 | B8: Asegurar que queden canceladas, en el estado Cancelación, todas las citas futuras asociadas a las agendas generadas a partir de ese horario de trabajo. Se consideran futuras las citas cuya agenda tenga una fecha posterior a la fecha actual | D8: Cita
A9: P-HBO-0005 | B9: Asegurar que exista el horario de trabajo del barbero con el id enviado | D9: HorarioBarbero
A10: P-HBO-0006 | B10: Asegurar que la hora de fin sea mayor a la hora de inicio | D10: HorarioBarbero
A11: P-HBO-0007 | B11: Asegurar que el horario de trabajo que se va a desactivar se encuentre vigente | D11: HorarioBarbero

Sheet E-HorarioBarbero
A1: << Ir al modelo de dominio | C1: << Ir al listado de objetos de dominio | F1: << Ir a la caracterización del objeto de dominio | J1: Ir al muestreo de datos del objeto de dominio >>
A2: Objeto de Dominio: | B2: ='Objetos de Dominio'!A13 -> HorarioBarbero
A3: Descripción: | B3: ='Objetos de Dominio'!B13 -> Representa el día de la semana en que trabaja un barbero, junto con la hora en la que empieza y termina su jornada de trabajo.
A4: Actor | B4: Action/Command | D4: Entity/Aggregate/Object domain | E4: Read Model | G4: Business Rule/Policy | I4: External System | J4: Domain Event | K4: Hotspot/questions/Risk
A5: Actor | B5: Acción | C5: Descripción | D5: Objeto de dominio | E5: Información externa | G5: Políticas | I5: Sistema Externo | J5: Evento | K5: Aspectos por solucionar
E6: Información | F6: Descripción | G6: Número | H6: Descripción
A7: Barbero | B7: Definir mi horario de trabajo | C7: Comando que permite a un barbero registrar el día de la semana y las horas en que trabaja | D7: =$B$2 -> HorarioBarbero | G7: ='P-HorarioBarbero'!A6 -> P-HBO-0001 | H7: ='P-HorarioBarbero'!B6 -> Asegurar que los datos requeridos (día de la semana, hora de inicio, hora de fin) sean válidos en tipo de dato, obligatoriedad, formato y rango | J7: Horario de barbero definido
G8: ='P-HorarioBarbero'!A7 -> P-HBO-0002 | H8: ='P-HorarioBarbero'!B7 -> Asegurar que el horario de trabajo esté dentro del horario de apertura y cierre de la barbería para ese día
G9: ='P-HorarioBarbero'!A10 -> P-HBO-0006 | H9: ='P-HorarioBarbero'!B10 -> Asegurar que la hora de fin sea mayor a la hora de inicio
A10: Barbero | B10: Ver mis horarios definidos | C10: Permite a un barbero consultar los horarios de trabajo que ha definido | D10: =$B$2 -> HorarioBarbero | J10: Horarios de barbero consultados
A11: Barbero | B11: Desactivar horario de trabajo | C11: Permite a un barbero desactivar un horario para dejar de trabajar ese día de la semana, cancelando las citas futuras que dependían de él | D11: =$B$2 -> HorarioBarbero | E11: Agenda | F11: Permite identificar las citas futuras que quedaron en las agendas generadas a partir de ese horario. La agenda no se modifica: solo se recorre para llegar a las citas. | G11: ='P-HorarioBarbero'!A8 -> P-HBO-0004 | H11: ='P-HorarioBarbero'!B8 -> Asegurar que queden canceladas, en el estado Cancelación, todas las citas futuras asociadas a las agendas generadas a partir de ese horario de trabajo. Se consideran futuras las citas cuya agenda tenga una fecha posterior a la fecha actual | J11: Horario de barbero desactivado | K11: Los bloqueos no se liberan en cascada: un bloqueo sobre una jornada que ya no existe no afecta la disponibilidad del barbero, y un bloqueo puede abarcar días en los que el barbero sigue trabajando.
E12: Cita | F12: Permite identificar las citas futuras que se deben cancelar.
E13: Estado | F13: Permite dejar esas citas en el estado Cancelación. | G13: ='P-HorarioBarbero'!A9 -> P-HBO-0005 | H13: ='P-HorarioBarbero'!B9 -> Asegurar que exista el horario de trabajo del barbero con el id enviado
G14: ='P-HorarioBarbero'!A11 -> P-HBO-0007 | H14: ='P-HorarioBarbero'!B11 -> Asegurar que el horario de trabajo que se va a desactivar se encuentre vigente
A15: Cliente | B15: Ver horarios de trabajo de un barbero | C15: Permite a un cliente consultar en qué días y horas trabaja un barbero | D15: =$B$2 -> HorarioBarbero | J15: Horarios de barbero consultados

Sheet M-HorarioBarbero
A1: <<<< Ir al modulo de dominio | B1: <<<< Ir a objetos de dominio
A2: Representa un identificador que hará unico cada objeto de dominio de este tipo, no se puede repetir | B2: Referencia a que barbero va a ser dueño de este horario | C2: Hace referencia a la agenda del barbero en la que queda guardado este horario de trabajo | D2: Representa la hora en la que el barbero empieza a estar disponible ese dia | E2: Representa la hora en la que el barbero deja de estar disponible ese día. | F2: Representa la fecha en el que el barbero creo su horario. Es un dato calculado que toma la fecha de hoy cuando el barbero la crea | G2: Representa la fecha en la que este horario dejó de estar vigente, ya sea porque el barbero lo retiró o porque se desactivó el horario de la barbería del que depende. Es un dato calculado que toma la fecha del sistema en ese momento. | H2: Representa si este horario lo sigue o no usando el barbero. Una vez que el barbero cambie este estado a no vigente, no se puede volver a cambiar | I2: Combinación única que indica que un mismo barbero no puede tener dos horarios con el mismo día de la barbería, la misma hora de inicio, la misma hora final, misma fecha de creacion y de desactivacion
A3: id | B3: barbero | C3: horarioDeLaBarberia | D3: horaInicio | E3: horaFinal | F3: fechaCreacion | G3: fechaDesactivacion | H3: vigente | I3: Combinación única
A4: 1 | B4: ='M-Barbero'!L4 -> +57-3245627890 | C4: ='M-HorarioBarberia'!H4 -> Lunes-09:00-19:00-12/11/2023-1/01/1000 | D4: 0.41666667 | E4: 0.66666667 | F4: 45780 | G4: 1/01/1000 | H4: si | I4: =_xlfn.CONCAT(B4,"-",C4,"-",TEXT(D4,"hh:mm"),"-",TEXT(E4,"hh:mm")) -> +57-3245627890-Lunes-09:00-19:00-12/11/2023-1/01/1000-10:00-16:00
A5: 2 | B5: ='M-Barbero'!L5 -> +57-3124518923 | C5: ='M-HorarioBarberia'!H5 -> Martes-09:00-19:00-12/11/2023-1/01/1000 | D5: 0.375 | E5: 0.625 | F5: 45718 | G5: 1/01/1000 | H5: si | I5: =_xlfn.CONCAT(B5,"-",C5,"-",TEXT(D5,"hh:mm"),"-",TEXT(E5,"hh:mm")) -> +57-3124518923-Martes-09:00-19:00-12/11/2023-1/01/1000-09:00-15:00
A6: 3 | B6: ='M-Barbero'!L6 -> +57-3214533321 | C6: ='M-HorarioBarberia'!H7 -> Jueves-09:00-19:00-12/11/2023-1/01/1000 | D6: 0.54166667 | E6: 0.79166667 | F6: 44917 | G6: 1/01/1000 | H6: si | I6: =_xlfn.CONCAT(B6,"-",C6,"-",TEXT(D6,"hh:mm"),"-",TEXT(E6,"hh:mm")) -> +57-3214533321-Jueves-09:00-19:00-12/11/2023-1/01/1000-13:00-19:00
A7: 4 | B7: ='M-Barbero'!L7 -> +91-9876543210 | C7: ='M-HorarioBarberia'!H9 -> Sábado-08:00-21:00-12/12/2024-1/01/1000 | D7: 0.33333333 | E7: 0.58333333 | F7: 45915 | G7: 46023 | H7: no | I7: =_xlfn.CONCAT(B7,"-",C7,"-",TEXT(D7,"hh:mm"),"-",TEXT(E7,"hh:mm")) -> +91-9876543210-Sábado-08:00-21:00-12/12/2024-1/01/1000-08:00-14:00
A8: 5 | B8: ='M-Barbero'!L7 -> +91-9876543210 | C8: ='M-HorarioBarberia'!H10 -> Festivo-10:00-15:00-12/12/2024-1/01/1000 | D8: 0.5 | E8: 0.625 | F8: 46054 | G8: 46083 | H8: no | I8: =_xlfn.CONCAT(B8,"-",C8,"-",TEXT(D8,"hh:mm"),"-",TEXT(E8,"hh:mm")) -> +91-9876543210-Festivo-10:00-15:00-12/12/2024-1/01/1000-12:00-15:00
B14: Corresponde a la descripcion de los atributos
B15: Corresponde al identificador unico del objeto de dominio
B16: Corresponde a las referencias de otros objetos de dominio
B17: Corresponde a los datos auto generados por el sistema
B18: Corresponde a los datos que ingresa el usuario
B19: Corresponde a la combinacion única

Sheet C-Agenda
A1: <<<< Ir al modulo de dominio | B1: <<<< Ir a objetos de dominio
A2: Nombre atributo | B2: Descripción atributo | C2: Identificador del objeto de dominio | D2: Tipo de dato | E2: Obligatorio | F2: Longitud mínima (si aplica) | G2: Longitud máxima (si aplica) | H2: Precisión (si aplica) | I2: Rendondeo (si aplica) | J2: Rango inicial (si aplica) | K2: Rango final (si aplica) | L2: Formato (si aplica) | M2: Reglas especiales (si aplica) | N2: Dato calculado | O2: Aplica ajuste del dato (si aplica) | P2: Carácter de ajuste (si aplica) | Q2: Quitar espacios en blanco al inicio (si aplica) | R2: Quitar espacios en blanco al fin (si aplica) | S2: Dato sensible (si aplica) | T2: Valor por defecto (si aplica) | U2: Auto generado | V2: =A13 -> crearAgendaBarbero | W2: =A15 -> consultarDisponibilidadBarbero | X2: =A16 -> consultarCitasDeAgenda | Y2: consultarCitasPorBarberoYRango
A3: ='M-Agenda'!A3 -> id | B3: ='M-Agenda'!A2 -> Representa un identificador que hará unico cada objeto de dominio de este tipo, no se puede repetir | C3: Si | D3: Identificador único universal | E3: Si | F3: No aplica | G3: No aplica | H3: No aplica | I3: No aplica | J3: No aplica | K3: No aplica | L3: No aplica | M3: No aplica | N3: No | O3: No | P3: No aplica | Q3: No | R3: No | S3: No | T3: UUID vacio | U3: Si | V3: No requerido | W3: No mostrar | X3: No mostrar | Y3: No mostrar
A4: ='M-Agenda'!B3 -> horarioDelBarbero | B4: ='M-Agenda'!B2 -> Hace referencia al horario de trabajo del barbero (día de la semana, hora de inicio y hora final) al que pertenece esta agenda | C4: No | D4: HorarioBarbero | E4: Si | F4: No aplica | G4: No aplica | H4: No aplica | I4: No aplica | J4: No aplica | K4: No aplica | L4: No aplica | M4: Aplican las reglas del objeto referenciado | N4: No | O4: No aplica | P4: No aplica | Q4: No aplica | R4: No aplica | S4: No | T4: UUID vacio | U4: No | V4: Requerido | W4: No mostrar | X4: Mostrar | Y4: Mostrar
A5: ='M-Agenda'!C3 -> fecha | B5: ='M-Agenda'!C2 -> Representa la fecha específica en el que la agenda va a guardar las citas de ese barbero | C5: No | D5: Fecha | E5: Si | F5: No aplica | G5: No aplica | H5: No aplica | I5: No aplica | J5: No aplica | K5: No aplica | L5: No aplica | M5: No aplica | N5: No | O5: No aplica | P5: No aplica | Q5: No aplica | R5: No aplica | S5: No | T5: 01/01/1000 | U5: Si | V5: Requerido | W5: Mostrar | X5: Mostrar | Y5: Mostrar
A7: Nombre combinación única | B7: Descripción | C7: Atributos involucrados
A8: ='M-Agenda'!D3 -> Combinación única | B8: ='M-Agenda'!D2 -> Combinación única que indica que un mismo horario de barbero no puede tener más de una agenda para el mismo día | C8: =A4 -> horarioDelBarbero
C9: =A5 -> fecha
A11: Responsabilidad | C11: Descripción | G11: Entradas | J11: Salida | O11: Políticas (Reglas de Negocio) | Q11: Excepción
G12: Parámetro | H12: Tipo de dato | I12: Descripción | J12: Tipo de Dato | K12: Descripción | O12: Política | P12: Descripción | Q12: Detalle | R12: ¿Qué hago?
A13: crearAgendaBarbero | C13: Comando que crea la agenda del día para un barbero y pueda saber que citas debe de atender | G13: datos{horarioDelBarbero, fecha} | H13: Agenda | I13: Contiene la información requerida para abrirle la agenda del día a un barbero | J13: Agenda | K13: Contiene la información de la agenda abierta | O13: ='P-Agenda'!A6 -> P-AGE-0001 | P13: ='P-Agenda'!B6 -> Asegurar que no exista ya una agenda para ese mismo horario de barbero y esa misma fecha | Q13: Generar una excepción indicándole al usuario que ya existe una agenda para ese horario de barbero y esa misma fecha | R13: Detener operación
O14: ='P-Agenda'!A7 -> P-AGE-0002 | P14: ='P-Agenda'!B7 -> Asegurar que el barbero esté vigente antes de abrirle una nueva agenda | Q14: Generar una excepción indicándole al usuario que no se le puede abrir agenda porque el barbero no está vigente | R14: Detener operación
A15: consultarDisponibilidadBarbero | C15: Permite a un cliente ver qué espacios le quedan libres a un barbero en una fecha, descontando sus citas ya agendadas y sus bloqueos | G15: filtro{barbero, fecha} | H15: Agenda | I15: Contiene el barbero y la fecha por los cuales se va a consultar la disponibilidad | J15: Lista<Hora> | K15: Contiene los espacios libres del barbero en esa fecha, descontando sus citas y sus bloqueos | O15: ='P-Agenda'!A8 -> P-AGE-0003 | P15: ='P-Agenda'!B8 -> Al consultar la disponibilidad de una agenda, descontar de la jornada del barbero las horas que ya tienen una cita y las que están cubiertas por un bloqueo | Q15: Si no se pueden descontar las citas o los bloqueos, informar que la disponibilidad no se pudo calcular | R15: Detener operación
A16: consultarCitasDeAgenda | C16: Permite consultar todas las citas agrupadas en la agenda de un barbero para una fecha puntual | G16: filtro{barbero, fecha} | H16: Agenda | I16: Contiene el barbero y la fecha por los cuales se van a consultar las citas | J16: Lista<Cita> | K16: Contiene todas las citas agrupadas en la agenda del barbero para esa fecha
A17: consultarCitasPorBarberoYRango | C17: Permite consultar las citas no canceladas de un barbero dentro de un rango de fecha y hora, recorriendo todas las agendas comprendidas en ese rango | G17: filtro{barbero, fechaHoraInicio, fechaHoraFinal} | H17: Agenda | I17: Contiene el barbero y el rango de fecha y hora por los cuales se van a consultar las citas | J17: Lista<Cita> | K17: Contiene todas las citas no canceladas del barbero comprendidas en ese rango de fecha y hora

Sheet P-Agenda
A1: << Ir al modelo de dominio | B1: << Ir al listado de objetos de dominio | C1: << Ir a la caracterización del objeto de dominio | D1: Ir al muestreo de datos del objeto de dominio >> | E1: Ir al event storming del objeto de dominio >>
A2: Objeto de Dominio: | B2: ='Objetos de Dominio'!A14 -> Agenda
A3: Descripción: | B3: ='Objetos de Dominio'!B14 -> Representa una fecha puntual en donde el barbero ve todas las citas que debe de atender ese día.
A4: Numero politica | B4: Descripcion politica | D4: Objeto responsable | E4: Regla responsable
A6: P-AGE-0001 | B6: Asegurar que no exista ya una agenda para ese mismo horario de barbero y esa misma fecha | D6: Agenda
A7: P-AGE-0002 | B7: Asegurar que el barbero esté vigente antes de abrirle una nueva agenda | D7: Barbero
A8: P-AGE-0003 | B8: Al consultar la disponibilidad de una agenda, descontar de la jornada del barbero las horas que ya tienen una cita y las que están cubiertas por un bloqueo | D8: Agenda

Sheet E-Agenda
A1: << Ir al modelo de dominio | C1: << Ir al listado de objetos de dominio | F1: << Ir a la caracterización del objeto de dominio | J1: Ir al muestreo de datos del objeto de dominio >>
A2: Objeto de Dominio: | B2: ='Objetos de Dominio'!A14 -> Agenda
A3: Descripción: | B3: ='Objetos de Dominio'!B14 -> Representa una fecha puntual en donde el barbero ve todas las citas que debe de atender ese día.
A4: Actor | B4: Action/Command | D4: Entity/Aggregate/Object domain | E4: Read Model | G4: Business Rule/Policy | I4: External System | J4: Domain Event | K4: Hotspot/questions/Risk
A5: Actor | B5: Acción | C5: Descripción | D5: Objeto de dominio | E5: Información externa | G5: Políticas | I5: Sistema Externo | J5: Evento | K5: Aspectos por solucionar
E6: Información | F6: Descripción | G6: Número | H6: Descripción
A7: Sistema | B7: Crear la agenda de un barbero para una fecha | C7: Comando que crea la agenda del día para un barbero y pueda saber que citas debe de atender | D7: =$B$2 -> Agenda | E7: Barbero | F7: Permite verificar que el barbero esté vigente antes de abrirle la agenda. | G7: ='P-Agenda'!A6 -> P-AGE-0001 | H7: ='P-Agenda'!B6 -> Asegurar que no exista ya una agenda para ese mismo horario de barbero y esa misma fecha | J7: Agenda creada
E8: HorarioBarbero | F8: Permite conocer la jornada de trabajo del barbero para esa fecha. | G8: ='P-Agenda'!A7 -> P-AGE-0002 | H8: ='P-Agenda'!B7 -> Asegurar que el barbero esté vigente antes de abrirle una nueva agenda
A9: Cliente | B9: Consultar la disponibilidad de un barbero para una fecha | C9: Permite a un cliente ver qué espacios le quedan libres a un barbero en una fecha, descontando sus citas ya agendadas y sus bloqueos | D9: =$B$2 -> Agenda | E9: Cita | F9: Permite conocer las horas de esa fecha que ya están ocupadas por una cita. | G9: ='P-Agenda'!A8 -> P-AGE-0003 | H9: ='P-Agenda'!B8 -> Al consultar la disponibilidad de una agenda, descontar de la jornada del barbero las horas que ya tienen una cita y las que están cubiertas por un bloqueo | J9: Disponibilidad de barbero consultada
E10: Bloqueo | F10: Permite conocer las horas de esa fecha en las que el barbero no está disponible.
A11: Barbero | B11: Consultar las citas de un barbero para una fecha | C11: Permite consultar todas las citas agrupadas en la agenda de un barbero para una fecha puntual | D11: =$B$2 -> Agenda | J11: Citas de agenda consultadas
A12: Cliente | B12: Consultar las citas de un barbero para una fecha | C12: Permite consultar todas las citas agrupadas en la agenda de un barbero para una fecha puntual | D12: =$B$2 -> Agenda | J12: Citas de agenda consultadas
A13: Sistema | B13: Consultar las citas de un barbero en un rango de fecha y hora | C13: Permite consultar las citas no canceladas de un barbero dentro de un rango de fecha y hora, recorriendo todas las agendas comprendidas en ese rango | D13: =$B$2 -> Agenda | E13: Cita | F13: Permite conocer las horas de las citas de cada agenda comprendida en el rango. | J13: Citas de barbero por rango consultadas
E14: Estado | F14: Permite descartar las citas canceladas.

Sheet M-Agenda
A1: <<<< Ir al modulo de dominio | B1: <<<< Ir a objetos de dominio
A2: Representa un identificador que hará unico cada objeto de dominio de este tipo, no se puede repetir | B2: Hace referencia al horario de trabajo del barbero (día de la semana, hora de inicio y hora final) al que pertenece esta agenda | C2: Representa la fecha específica en el que la agenda va a guardar las citas de ese barbero | D2: Combinación única que indica que un mismo horario de barbero no puede tener más de una agenda para el mismo día
A3: id | B3: horarioDelBarbero | C3: fecha | D3: Combinación única
A4: 1 | B4: ='M-HorarioBarbero'!I4 -> +57-3245627890-Lunes-09:00-19:00-12/11/2023-1/01/1000-10:00-16:00 | C4: 46265 | D4: =_xlfn.CONCAT(B4,"-",TEXT(C4,"dd/mm/yyyy")) -> +57-3245627890-Lunes-09:00-19:00-12/11/2023-1/01/1000-10:00-16:00-31/08/2026
A5: 2 | B5: ='M-HorarioBarbero'!I5 -> +57-3124518923-Martes-09:00-19:00-12/11/2023-1/01/1000-09:00-15:00 | C5: 46091 | D5: =_xlfn.CONCAT(B5,"-",TEXT(C5,"dd/mm/yyyy")) -> +57-3124518923-Martes-09:00-19:00-12/11/2023-1/01/1000-09:00-15:00-10/03/2026
A6: 3 | B6: ='M-HorarioBarbero'!I6 -> +57-3214533321-Jueves-09:00-19:00-12/11/2023-1/01/1000-13:00-19:00 | C6: 46156 | D6: =_xlfn.CONCAT(B6,"-",TEXT(C6,"dd/mm/yyyy")) -> +57-3214533321-Jueves-09:00-19:00-12/11/2023-1/01/1000-13:00-19:00-14/05/2026
A7: 4 | B7: ='M-HorarioBarbero'!I8 -> +91-9876543210-Festivo-10:00-15:00-12/12/2024-1/01/1000-12:00-15:00 | C7: 46073 | D7: =_xlfn.CONCAT(B7,"-",TEXT(C7,"dd/mm/yyyy")) -> +91-9876543210-Festivo-10:00-15:00-12/12/2024-1/01/1000-12:00-15:00-20/02/2026
A8: 5 | B8: ='M-HorarioBarbero'!I7 -> +91-9876543210-Sábado-08:00-21:00-12/12/2024-1/01/1000-08:00-14:00 | C8: 45983 | D8: =_xlfn.CONCAT(B8,"-",TEXT(C8,"dd/mm/yyyy")) -> +91-9876543210-Sábado-08:00-21:00-12/12/2024-1/01/1000-08:00-14:00-22/11/2025
A9: 6 | B9: ='M-HorarioBarbero'!I6 -> +57-3214533321-Jueves-09:00-19:00-12/11/2023-1/01/1000-13:00-19:00 | C9: 46240 | D9: =_xlfn.CONCAT(B9,"-",TEXT(C9,"dd/mm/yyyy")) -> +57-3214533321-Jueves-09:00-19:00-12/11/2023-1/01/1000-13:00-19:00-06/08/2026
A10: 7 | B10: ='M-HorarioBarbero'!I4 -> +57-3245627890-Lunes-09:00-19:00-12/11/2023-1/01/1000-10:00-16:00 | C10: 46174 | D10: =_xlfn.CONCAT(B10,"-",TEXT(C10,"dd/mm/yyyy")) -> +57-3245627890-Lunes-09:00-19:00-12/11/2023-1/01/1000-10:00-16:00-01/06/2026
A11: 8 | B11: ='M-HorarioBarbero'!I5 -> +57-3124518923-Martes-09:00-19:00-12/11/2023-1/01/1000-09:00-15:00 | C11: 46189 | D11: =_xlfn.CONCAT(B11,"-",TEXT(C11,"dd/mm/yyyy")) -> +57-3124518923-Martes-09:00-19:00-12/11/2023-1/01/1000-09:00-15:00-16/06/2026
A12: 9 | B12: ='M-HorarioBarbero'!I6 -> +57-3214533321-Jueves-09:00-19:00-12/11/2023-1/01/1000-13:00-19:00 | C12: 46205 | D12: =_xlfn.CONCAT(B12,"-",TEXT(C12,"dd/mm/yyyy")) -> +57-3214533321-Jueves-09:00-19:00-12/11/2023-1/01/1000-13:00-19:00-02/07/2026
B18: Corresponde a la descripcion de los atributos
B19: Corresponde al identificador unico del objeto de dominio
B20: Corresponde a las referencias de otros objetos de dominio
B21: Corresponde a los datos auto generados por el sistema
B22: Corresponde a la combinacion única

Sheet C-Cita
A1: <<<< Ir al modulo de dominio | B1: <<<< Ir a objetos de dominio
A2: Nombre atributo | B2: Descripción atributo | C2: Identificador del objeto de dominio | D2: Tipo de dato | E2: Obligatorio | F2: Longitud mínima (si aplica) | G2: Longitud máxima (si aplica) | H2: Precisión (si aplica) | I2: Rendondeo (si aplica) | J2: Rango inicial (si aplica) | K2: Rango final (si aplica) | L2: Formato (si aplica) | M2: Reglas especiales (si aplica) | N2: Dato calculado | O2: Aplica ajuste del dato (si aplica) | P2: Carácter de ajuste (si aplica) | Q2: Quitar espacios en blanco al inicio (si aplica) | R2: Quitar espacios en blanco al fin (si aplica) | S2: Dato sensible (si aplica) | T2: Valor por defecto (si aplica) | U2: Auto generado | V2: =A28 -> pedirCita | W2: =A36 -> reprogramarCita | Y2: =A41 -> cancelarCitaPorCliente | AA2: =A44 -> cancelarCitaPorBarbero | AC2: =A47 -> registrarLlegadaCliente | AE2: =A51 -> iniciarAtencionCliente | AG2: =A55 -> finalizarAtencionCliente | AI2: =A58 -> registrarInasistenciaCliente
A3: ='M-Cita'!A3 -> id | B3: ='M-Cita'!A2 -> Representa un identificador que hará unico cada objeto de dominio de este tipo, no se puede repetir | C3: Si | D3: Identificador único universal | E3: Si | F3: No aplica | G3: No aplica | H3: No aplica | I3: No aplica | J3: No aplica | K3: No aplica | L3: No aplica | M3: No aplica | N3: No | O3: No | P3: No aplica | Q3: No | R3: No | S3: No | T3: UUID vacio | U3: Si | V3: No requerido | W3: Requerido | X3: No modificable | Y3: Requerido | Z3: No modificable | AA3: Requerido | AB3: No modificable | AC3: Requerido | AD3: No modificable | AE3: Requerido | AF3: No modificable | AG3: Requerido | AH3: No modificable | AI3: Requerido | AJ3: No modificable
A4: ='M-Cita'!B3 -> cliente | B4: ='M-Cita'!B2 -> Representa a cuál cliente le pertenece esta cita | C4: No | D4: Cliente | E4: Si | F4: No aplica | G4: No aplica | H4: No aplica | I4: No aplica | J4: No aplica | K4: No aplica | L4: No aplica | M4: Se muestra el nombre completo del cliente, no una combinación única, únicamente para lectura humana en el muestreo | N4: No | O4: No aplica | P4: No aplica | Q4: No aplica | R4: No aplica | S4: No | T4: UUID vacio | U4: No | V4: Requerido | W4: No requerido | X4: No modificable | Y4: No requerido | Z4: No modificable | AA4: No requerido | AB4: No modificable | AC4: No requerido | AD4: No modificable | AE4: No requerido | AF4: No modificable | AG4: No requerido | AH4: No modificable | AI4: No requerido | AJ4: No modificable
A5: ='M-Cita'!C3 -> agenda | B5: ='M-Cita'!C2 -> Referencia en cual agenda va a estar esta cita | C5: No | D5: Agenda | E5: Si | F5: No aplica | G5: No aplica | H5: No aplica | I5: No aplica | J5: No aplica | K5: No aplica | L5: No aplica | M5: Aplican las reglas del objeto referenciado | N5: No | O5: No aplica | P5: No aplica | Q5: No aplica | R5: No aplica | S5: No | T5: UUID vacio | U5: No | V5: Requerido | W5: Requerido | X5: Modificable | Y5: No requerido | Z5: No modificable | AA5: No requerido | AB5: No modificable | AC5: No requerido | AD5: No modificable | AE5: No requerido | AF5: No modificable | AG5: No requerido | AH5: No modificable | AI5: No requerido | AJ5: No modificable
A6: ='M-Cita'!D3 -> estado | B6: ='M-Cita'!D2 -> Representa en qué estado se encuentra esta cita puntual: agendada, finalizada, cancelada, con tardanza del cliente o del barbero, o inasistencia | C6: No | D6: Estado | E6: Si | F6: No aplica | G6: No aplica | H6: No aplica | I6: No aplica | J6: No aplica | K6: No aplica | L6: No aplica | M6: Aplican las reglas del objeto referenciado | N6: No | O6: No aplica | P6: No aplica | Q6: No aplica | R6: No aplica | S6: No | T6: Agendado | U6: No | V6: No requerido | W6: No requerido | X6: No modificable | Y6: No requerido | Z6: Modificable | AA6: No requerido | AB6: Modificable | AC6: No requerido | AD6: Modificable | AE6: No requerido | AF6: Modificable | AG6: No requerido | AH6: Modificable | AI6: No requerido | AJ6: Modificable
A7: ='M-Cita'!E3 -> horaInicio | B7: ='M-Cita'!E2 -> Representa la hora en la que se va a realizar la cita al cliente | C7: No | D7: Hora | E7: Si | F7: No aplica | G7: No aplica | H7: No aplica | I7: No aplica | J7: No aplica | K7: No aplica | L7: No aplica | M7: Debe de estar dentro del horario de trabajo del barbero | N7: No | O7: No aplica | P7: No aplica | Q7: No aplica | R7: No aplica | S7: No | T7: 00:00 | U7: No | V7: Requerido | W7: Requerido | X7: Modificable | Y7: No requerido | Z7: No modificable | AA7: No requerido | AB7: No modificable | AC7: No requerido | AD7: No modificable | AE7: No requerido | AF7: No modificable | AG7: No requerido | AH7: No modificable | AI7: No requerido | AJ7: No modificable
A8: ='M-Cita'!F3 -> horaFinEstimada | B8: ='M-Cita'!F2 -> Representa la hora en la que se espera que termine la cita, sumando horaInicio más la duración total de los servicios pedidos. Es un dato calculado | C8: No | D8: Hora | E8: Si | F8: No aplica | G8: No aplica | H8: No aplica | I8: No aplica | J8: No aplica | K8: No aplica | L8: No aplica | M8: horaInicio + duracion (en minutos) y debe de estar dentro del horario de trabajo del barbero | N8: Si | O8: No aplica | P8: No aplica | Q8: No aplica | R8: No aplica | S8: No | T8: 00:00 | U8: No | V8: No requerido | W8: No requerido | X8: Modificable | Y8: No requerido | Z8: No modificable | AA8: No requerido | AB8: No modificable | AC8: No requerido | AD8: No modificable | AE8: No requerido | AF8: No modificable | AG8: No requerido | AH8: No modificable | AI8: No requerido | AJ8: No modificable
A9: ='M-Cita'!G3 -> horaLlegadaCliente | B9: ='M-Cita'!G2 -> Representa la hora real en la que el cliente llegó a la barbería para esta cita. Su valor por defecto es 00:00 y es permitido: significa que el cliente aún no ha llegado | C9: No | D9: Hora | E9: No | F9: No aplica | G9: No aplica | H9: No aplica | I9: No aplica | J9: No aplica | K9: No aplica | L9: No aplica | M9: No aplica | N9: No | O9: No aplica | P9: No aplica | Q9: No aplica | R9: No aplica | S9: No | T9: 00:00 | U9: No | V9: No requerido | W9: No requerido | X9: No modificable | Y9: No requerido | Z9: No modificable | AA9: No requerido | AB9: No modificable | AC9: Requerido | AD9: Modificable | AE9: No requerido | AF9: No modificable | AG9: No requerido | AH9: No modificable | AI9: No requerido | AJ9: No modificable
A10: ='M-Cita'!H3 -> horaDelBarberoPreparado | B10: ='M-Cita'!H2 -> Representa la hora real en la que el barbero quedó listo y disponible para empezar a atender esta cita. Su valor por defecto es 00:00 y es permitido: significa que el barbero aún no se ha preparado | C10: No | D10: Hora | E10: No | F10: No aplica | G10: No aplica | H10: No aplica | I10: No aplica | J10: No aplica | K10: No aplica | L10: No aplica | M10: No aplica | N10: No | O10: No aplica | P10: No aplica | Q10: No aplica | R10: No aplica | S10: No | T10: 00:00 | U10: No | V10: No requerido | W10: No requerido | X10: No modificable | Y10: No requerido | Z10: No modificable | AA10: No requerido | AB10: No modificable | AC10: No requerido | AD10: No modificable | AE10: No requerido | AF10: Modificable | AG10: No requerido | AH10: No modificable | AI10: No requerido | AJ10: No modificable
A11: ='M-Cita'!I3 -> horaInicioAtencion | B11: ='M-Cita'!I2 -> Representa la hora real en la que el barbero empezó a atender al cliente. Su valor por defecto es 00:00 y es permitido: significa que la atención aún no ha comenzado | C11: No | D11: Hora | E11: No | F11: No aplica | G11: No aplica | H11: No aplica | I11: No aplica | J11: No aplica | K11: No aplica | L11: No aplica | M11: No aplica | N11: No | O11: No aplica | P11: No aplica | Q11: No aplica | R11: No aplica | S11: No | T11: 00:00 | U11: No | V11: No requerido | W11: No requerido | X11: No modificable | Y11: No requerido | Z11: No modificable | AA11: No requerido | AB11: No modificable | AC11: No requerido | AD11: No modificable | AE11: Requerido | AF11: Modificable | AG11: No requerido | AH11: No modificable | AI11: No requerido | AJ11: No modificable
A12: ='M-Cita'!J3 -> horaFinAtencion | B12: ='M-Cita'!J2 -> Representa la hora real en la que el barbero terminó de atender al cliente. Su valor por defecto es 00:00 y es permitido: significa que la atención aún no ha terminado | C12: No | D12: Hora | E12: No | F12: No aplica | G12: No aplica | H12: No aplica | I12: No aplica | J12: No aplica | K12: No aplica | L12: No aplica | M12: No aplica | N12: No | O12: No aplica | P12: No aplica | Q12: No aplica | R12: No aplica | S12: No | T12: 00:00 | U12: No | V12: No requerido | W12: No requerido | X12: No modificable | Y12: No requerido | Z12: No modificable | AA12: No requerido | AB12: No modificable | AC12: No requerido | AD12: No modificable | AE12: No requerido | AF12: No modificable | AG12: Requerido | AH12: Modificable | AI12: No requerido | AJ12: No modificable
A13: ='M-Cita'!K3 -> duracionHoras | B13: ='M-Cita'!K2 -> Representa la cantidad total de horas que va a durar la cita, sumando la duración de cada servicio pedido más el tiempo extra de cada uno. Es un dato calculado | C13: No | D13: Entero | E13: No | F13: No aplica | G13: No aplica | H13: No aplica | I13: No aplica | J13: 0 | K13: 3 | L13: No aplica | M13: Resulta de dividir entre 60 la suma de duracionServicio + tiempoExtra de todos los CitaServicio de esta cita (parte en horas) | N13: Si | O13: No aplica | P13: No aplica | Q13: No aplica | R13: No aplica | S13: No | T13: 0 | U13: No | V13: No requerido | W13: No requerido | X13: No modificable | Y13: No requerido | Z13: No modificable | AA13: No requerido | AB13: No modificable | AC13: No requerido | AD13: No modificable | AE13: No requerido | AF13: No modificable | AG13: No requerido | AH13: Modificable | AI13: No requerido | AJ13: No modificable
A14: ='M-Cita'!L3 -> duracionMinutos | B14: ='M-Cita'!L2 -> Representa la cantidad total de minutos que va a durar la cita, sumando la duración de cada servicio pedido más el tiempo extra de cada uno. Es un dato calculado | C14: No | D14: Entero | E14: No | F14: No aplica | G14: No aplica | H14: No aplica | I14: No aplica | J14: 0 | K14: 59 | L14: No aplica | M14: Resto en minutos de dividir entre 60 la suma de duracionServicio + tiempoExtra de todos los CitaServicio de esta cita (parte en minutos) | N14: Si | O14: No aplica | P14: No aplica | Q14: No aplica | R14: No aplica | S14: No | T14: 0 | U14: No | V14: No requerido | W14: No requerido | X14: No modificable | Y14: No requerido | Z14: No modificable | AA14: No requerido | AB14: No modificable | AC14: No requerido | AD14: No modificable | AE14: No requerido | AF14: No modificable | AG14: No requerido | AH14: Modificable | AI14: No requerido | AJ14: No modificable
A15: ='M-Cita'!M3 -> minutosTardanzaCliente | B15: ='M-Cita'!M2 -> Representa cuántos minutos después de horaInicio llegó el cliente. Si llegó a tiempo o aún no ha llegado su valor es 0. Es un dato calculado | C15: No | D15: Entero | E15: No | F15: No aplica | G15: No aplica | H15: No aplica | I15: No aplica | J15: 0 | K15: 300 | L15: No aplica | M15: Si horaLlegadaCliente es 00:00 (no ha llegado), 0. Si no, MAX(0, horaLlegadaCliente - horaInicio) en minutos | N15: Si | O15: No aplica | P15: No aplica | Q15: No aplica | R15: No aplica | S15: No | T15: 0 | U15: No | V15: No requerido | W15: No requerido | X15: No modificable | Y15: No requerido | Z15: No modificable | AA15: No requerido | AB15: No modificable | AC15: No requerido | AD15: Modificable | AE15: No requerido | AF15: No modificable | AG15: No requerido | AH15: No modificable | AI15: No requerido | AJ15: No modificable
A16: ='M-Cita'!N3 -> minutosDemoraBarbero | B16: ='M-Cita'!N2 -> Representa cuántos minutos después de la llegada del cliente empezó el barbero a atenderlo. Si no hubo demora su valor es 0. Es un dato calculado | C16: No | D16: Entero | E16: No | F16: No aplica | G16: No aplica | H16: No aplica | I16: No aplica | J16: 0 | K16: 300 | L16: No aplica | M16: Si horaInicioAtencion es 00:00 (no ha empezado), 0. Si no, MAX(0, horaInicioAtencion - MAX(horaLlegadaCliente, horaInicio)) en minutos | N16: Si | O16: No aplica | P16: No aplica | Q16: No aplica | R16: No aplica | S16: No | T16: 0 | U16: No | V16: No requerido | W16: No requerido | X16: No modificable | Y16: No requerido | Z16: No modificable | AA16: No requerido | AB16: No modificable | AC16: No requerido | AD16: No modificable | AE16: No requerido | AF16: Modificable | AG16: No requerido | AH16: No modificable | AI16: No requerido | AJ16: No modificable
A17: ='M-Cita'!O3 -> porcentajeDescuento | B17: ='M-Cita'!O2 -> Representa el descuento que el barbero le concede al cliente por haberse demorado en atenderlo; solo se descuenta del precioTotal cuando la cita queda en el estado "El barbero se demoro" | C17: No | D17: Entero | E17: No | F17: No aplica | G17: No aplica | H17: No aplica | I17: No aplica | J17: 0 | K17: 100 | L17: No aplica | M17: Lo define el barbero y queda congelado en la cita; solo se descuenta del precioTotal cuando la cita queda en el estado "El barbero se demoro" | N17: No | O17: No aplica | P17: No aplica | Q17: No aplica | R17: No aplica | S17: No | T17: 0 | U17: No | V17: No requerido | W17: No requerido | X17: No modificable | Y17: No requerido | Z17: No modificable | AA17: No requerido | AB17: No modificable | AC17: No requerido | AD17: No modificable | AE17: No requerido | AF17: No modificable | AG17: No requerido | AH17: No modificable | AI17: No requerido | AJ17: No modificable
A18: ='M-Cita'!P3 -> multa | B18: ='M-Cita'!P2 -> Representa el precio de sancion, en caso de que el cliente se demore | C18: No | D18: Entero | E18: No | F18: No aplica | G18: No aplica | H18: No aplica | I18: No aplica | J18: 0 | K18: 100000 | L18: No aplica | M18: Lo define el barbero al momento de agendar la cita y queda congelado en ella; es el valor que se le cobra al cliente si su tardanza supera el tiempoEspera de esta misma cita | N18: No | O18: No aplica | P18: No aplica | Q18: No aplica | R18: No aplica | S18: No | T18: 0 | U18: No | V18: No requerido | W18: No requerido | X18: No modificable | Y18: No requerido | Z18: No modificable | AA18: No requerido | AB18: No modificable | AC18: No requerido | AD18: No modificable | AE18: No requerido | AF18: No modificable | AG18: No requerido | AH18: No modificable | AI18: No requerido | AJ18: No modificable
A19: ='M-Cita'!Q3 -> tiempoEspera | B19: ='M-Cita'!Q2 -> Representa la cantidad de minutos en el que el barbero puede esperar a un cliente, después de este tiempo de espera se le hace una sanción por retraso. Si el barbero se pasa de este tiempo se le da el descuento al cliente | C19: No | D19: Entero | E19: No | F19: No aplica | G19: No aplica | H19: No aplica | I19: No aplica | J19: 0 | K19: 60 | L19: No aplica | M19: Es el mismo margen para las dos partes: si el cliente lo supera se le genera una Multa de tipo Tardanza por el valor de multa, y si el barbero lo supera se le aplica al cliente el porcentajeDescuento sobre el precioTotal | N19: No | O19: No aplica | P19: No aplica | Q19: No aplica | R19: No aplica | S19: No | T19: 0 | U19: No | V19: No requerido | W19: No requerido | X19: No modificable | Y19: No requerido | Z19: No modificable | AA19: No requerido | AB19: No modificable | AC19: No requerido | AD19: No modificable | AE19: No requerido | AF19: No modificable | AG19: No requerido | AH19: No modificable | AI19: No requerido | AJ19: No modificable
A20: ='M-Cita'!R3 -> precioTotal | B20: ='M-Cita'!R2 -> Representa cuánto debe pagar el cliente por los servicios de esta cita: la suma del precioServicio de todos sus CitaServicio, al que solo se le aplica el porcentajeDescuento cuando la cita quedó en el estado "El barbero se demoro" | C20: No | D20: Entero | E20: Si | F20: No aplica | G20: No aplica | H20: No aplica | I20: No aplica | J20: 0 | K20: 3000000 | L20: No aplica | M20: Suma del precioServicio de todos los CitaServicio de esta cita. Si el estado de la cita es "El barbero se demoro" se le resta el porcentajeDescuento; en cualquier otro estado se cobra la suma completa | N20: Si | O20: No aplica | P20: No aplica | Q20: No aplica | R20: No aplica | S20: No | T20: 0 | U20: No | V20: No requerido | W20: No requerido | X20: No modificable | Y20: No requerido | Z20: No modificable | AA20: No requerido | AB20: No modificable | AC20: No requerido | AD20: No modificable | AE20: No requerido | AF20: No modificable | AG20: No requerido | AH20: Modificable | AI20: No requerido | AJ20: No modificable
A22: Nombre combinación única | B22: Descripción | C22: Atributos involucrados
A23: ='M-Cita'!S3 -> Combinación única | B23: ='M-Cita'!S2 -> Combinación única que indica que una misma agenda no puede tener dos citas que empiecen a la misma hora | C23: =A5 -> agenda
C24: =A7 -> horaInicio
A26: Responsabilidad | C26: Descripción | G26: Entradas | J26: Salida | O26: Políticas (Reglas de Negocio) | Q26: Excepción
G27: Parámetro | H27: Tipo de dato | I27: Descripción | J27: Tipo de Dato | K27: Descripción | O27: Política | P27: Descripción | Q27: Detalle | R27: ¿Qué hago?
A28: pedirCita | C28: Comando que permite a un cliente solicitar una cita con un barbero, en una fecha y hora puntual, con uno o más servicios | G28: datos{cliente, agenda, horaInicio, servicios} | H28: Cita | I28: Contiene la información requerida para agendar una nueva cita con un barbero | J28: Cita | K28: Contiene la información de la cita agendada | O28: ='P-Cita'!A6 -> P-CIT-0001 | P28: ='P-Cita'!B6 -> Asegurar que los datos requeridos (hora de inicio, servicios solicitados) sean válidos en tipo de dato, obligatoriedad, formato y rango | Q28: Generar una excepción indicándole al cliente cuáles datos de la cita no cumplen con las reglas definidas | R28: Detener operación
O29: ='P-Cita'!A7 -> P-CIT-0002 | P29: ='P-Cita'!B7 -> Asegurar que el cliente no esté vetado antes de permitirle agendar | Q29: Generar una excepción indicándole al cliente que no puede agendar porque el cliente está vetado | R29: Detener operación
O30: ='P-Cita'!A8 -> P-CIT-0003 | P30: ='P-Cita'!B8 -> Asegurar que la agenda tenga disponibilidad y que la hora solicitada quepa dentro del horario del barbero sin solaparse con otra cita o bloqueo | Q30: Generar una excepción indicándole al cliente que el barbero no tiene disponibilidad en la hora solicitada | R30: Detener operación
O31: ='P-Cita'!A19 -> P-CIT-0014 | P31: ='P-Cita'!B19 -> Asegurar que la hora solicitada no caiga dentro de ningún bloqueo del barbero, ni que la cita se extienda sobre uno | Q31: Generar una excepción indicándole al cliente que la hora solicitada cae dentro de un bloqueo del barbero | R31: Detener operación
O32: ='P-Cita'!A9 -> P-CIT-0004 | P32: ='P-Cita'!B9 -> Asegurar que cada servicio solicitado esté habilitado para ese barbero | Q32: Generar una excepción indicándole al cliente que alguno de los servicios pedidos no está habilitado para ese barbero | R32: Detener operación
O33: ='P-Cita'!A18 -> P-CIT-0013 | P33: ='P-Cita'!B18 -> Asegurar que todos los servicios pedidos en la cita correspondan a un mismo barbero, porque una cita la atiende un único barbero de principio a fin | Q33: Generar una excepción indicándole al cliente que los servicios pedidos pertenecen a más de un barbero | R33: Detener operación
O34: ='P-Cita'!A10 -> P-CIT-0005 | P34: ='P-Cita'!B10 -> Asegurar que la cita se solicite con al menos la anticipación mínima definida por el barbero | Q34: Generar una excepción indicándole al cliente que la cita no cumple con la anticipación mínima que exige el barbero | R34: Detener operación
O35: ='P-Cita'!A11 -> P-CIT-0006 | P35: ='P-Cita'!B11 -> Congelar en la cita el valor de multa, el tiempoEspera y el porcentajeDescuento en el momento de agendarla, para que un cambio posterior no altere citas ya registradas | Q35: Si los valores de multa, tiempoEspera y porcentajeDescuento no se pueden congelar, no registrar la cita | R35: Detener operación
A36: reprogramarCita | C36: Permite a un cliente cambiar la fecha, hora o barbero de una cita que aún no ha ocurrido | G36: id | H36: UUID | I36: Corresponde al identificador de la cita que se va a reprogramar | J36: Cita | K36: Contiene la información de la cita reprogramada | O36: ='P-Cita'!A20 -> P-CIT-0015 | P36: ='P-Cita'!B20 -> Asegurar que exista la cita con el id enviado | Q36: Informar con un mensaje que no existe una cita con el identificador enviado y por lo tanto no es posible llevar a cabo la operación | R36: Detener operación
G37: datos{agenda, horaInicio} | I37: Contiene la nueva agenda y hora con las que se va a reprogramar la cita | O37: ='P-Cita'!A21 -> P-CIT-0016 | P37: ='P-Cita'!B21 -> Asegurar que la cita se encuentre en estado Agendada | Q37: Generar una excepción indicándole al cliente que la cita no se puede reprogramar porque no se encuentra en estado Agendada | R37: Detener operación
O38: ='P-Cita'!A8 -> P-CIT-0003 | P38: ='P-Cita'!B8 -> Asegurar que la agenda tenga disponibilidad y que la hora solicitada quepa dentro del horario del barbero sin solaparse con otra cita o bloqueo | Q38: Generar una excepción indicándole al cliente que el barbero no tiene disponibilidad en la hora solicitada | R38: Detener operación
O39: ='P-Cita'!A19 -> P-CIT-0014 | P39: ='P-Cita'!B19 -> Asegurar que la hora solicitada no caiga dentro de ningún bloqueo del barbero, ni que la cita se extienda sobre uno | Q39: Generar una excepción indicándole al cliente que la hora solicitada cae dentro de un bloqueo del barbero | R39: Detener operación
O40: ='P-Cita'!A10 -> P-CIT-0005 | P40: ='P-Cita'!B10 -> Asegurar que la cita se solicite con al menos la anticipación mínima definida por el barbero | Q40: Generar una excepción indicándole al cliente que la cita no cumple con la anticipación mínima que exige el barbero | R40: Detener operación
A41: cancelarCitaPorCliente | C41: Permite a un cliente cancelar una cita antes de que ocurra, siempre que falten 2 horas o más para su horaInicio | G41: id | I41: Corresponde al identificador de la cita que el cliente va a cancelar | J41: Cita | K41: Contiene la cita en el estado Cancelada por el cliente | O41: ='P-Cita'!A20 -> P-CIT-0015 | P41: ='P-Cita'!B20 -> Asegurar que exista la cita con el id enviado | Q41: Informar con un mensaje que no existe una cita con el identificador enviado y por lo tanto no es posible llevar a cabo la operación | R41: Detener operación
O42: ='P-Cita'!A21 -> P-CIT-0016 | P42: ='P-Cita'!B21 -> Asegurar que la cita se encuentre en estado Agendada | Q42: Generar una excepción indicándole al cliente que la cita no se puede cancelar porque no se encuentra en estado Agendada | R42: Detener operación
O43: ='P-Cita'!A16 -> P-CIT-0011 | P43: ='P-Cita'!B16 -> Rechazar la cancelación cuando falten menos de 2 horas para la horaInicio de la cita: en ese caso el sistema no le permite al cliente cancelarla y la cita se mantiene | Q43: Generar una excepción indicándole al cliente que ya no puede cancelar la cita porque faltan menos de 2 horas para su horaInicio | R43: Detener operación
A44: cancelarCitaPorBarbero | C44: Permite a un barbero cancelar una cita antes de que ocurra | G44: id | I44: Corresponde al identificador de la cita que el barbero va a cancelar | J44: Cita | K44: Contiene la cita en el estado Cancelada por el barbero | O44: ='P-Cita'!A20 -> P-CIT-0015 | P44: ='P-Cita'!B20 -> Asegurar que exista la cita con el id enviado | Q44: Informar con un mensaje que no existe una cita con el identificador enviado y por lo tanto no es posible llevar a cabo la operación | R44: Detener operación
O45: ='P-Cita'!A21 -> P-CIT-0016 | P45: ='P-Cita'!B21 -> Asegurar que la cita se encuentre en estado Agendada | Q45: Generar una excepción indicándole al barbero que la cita no se puede cancelar porque no se encuentra en estado Agendada | R45: Detener operación
O46: ='P-Cita'!A17 -> P-CIT-0012 | P46: ='P-Cita'!B17 -> Asegurar que el barbero cancele la cita con al menos 2 horas de anticipación frente a su horaInicio | Q46: Generar una excepción indicándole al barbero que ya no puede cancelar la cita porque faltan menos de 2 horas para su horaInicio | R46: Detener operación
A47: registrarLlegadaCliente | C47: Permite al barbero marcar la hora real en que el cliente llegó a su cita | G47: id | H47: UUID | I47: Corresponde al identificador de la cita a la que llegó el cliente | J47: Cita | K47: Contiene la cita con la hora de llegada del cliente registrada | O47: ='P-Cita'!A20 -> P-CIT-0015 | P47: ='P-Cita'!B20 -> Asegurar que exista la cita con el id enviado | Q47: Informar con un mensaje que no existe una cita con el identificador enviado y por lo tanto no es posible llevar a cabo la operación | R47: Detener operación
O48: ='P-Cita'!A21 -> P-CIT-0016 | P48: ='P-Cita'!B21 -> Asegurar que la cita se encuentre en estado Agendada | Q48: Generar una excepción indicándole al barbero que no se puede registrar la llegada porque la cita no se encuentra en estado Agendada | R48: Detener operación
G49: horaLlegadaCliente | H49: Hora | I49: Contiene la hora real en la que el cliente llegó a la barbería | O49: ='P-Cita'!A24 -> P-CIT-0019 | P49: ='P-Cita'!B24 -> Asegurar que la llegada del cliente no haya sido registrada previamente | Q49: Generar una excepción indicándole al barbero que la llegada del cliente ya fue registrada | R49: Detener operación
O50: ='P-Cita'!A15 -> P-CIT-0010 | P50: ='P-Cita'!B15 -> Si minutosTardanzaCliente supera el tiempoEspera de la cita, generar una Multa de tipo Tardanza por el valor de multa de esa misma cita | Q50: Si la multa por tardanza no se puede generar, registrar el error y dejar la tardanza sin multa | R50: Detener operación
A51: iniciarAtencionCliente | C51: Permite al barbero marcar el inicio real de la atención de la cita | G51: id | H51: UUID | I51: Corresponde al identificador de la cita que se va a iniciar | J51: Cita | K51: Contiene la cita con la hora de inicio de la atención registrada | O51: ='P-Cita'!A20 -> P-CIT-0015 | P51: ='P-Cita'!B20 -> Asegurar que exista la cita con el id enviado | Q51: Informar con un mensaje que no existe una cita con el identificador enviado y por lo tanto no es posible llevar a cabo la operación | R51: Detener operación
O52: ='P-Cita'!A22 -> P-CIT-0017 | P52: ='P-Cita'!B22 -> Asegurar que la llegada del cliente esté registrada y que la cita se encuentre en estado Agendada o El cliente se demoro | Q52: Generar una excepción indicándole al barbero que no se puede iniciar la atención porque la llegada del cliente no está registrada o la cita no se encuentra en estado Agendada o El cliente se demoro | R52: Detener operación
G53: horaInicioAtencion | H53: Hora | I53: Contiene la hora real en la que el barbero empezó a atender | O53: ='P-Cita'!A25 -> P-CIT-0020 | P53: ='P-Cita'!B25 -> Asegurar que la atención de la cita no haya sido iniciada previamente | Q53: Generar una excepción indicándole al barbero que la atención de la cita ya fue iniciada | R53: Detener operación
